Workbook

Sheet Revenue_Budget
A1: FY | B1: Project | C1: Vertical | D1: Region | E1: Sub Region | F1: Region Head | G1: Practice Head | H1: 45748 | I1: =EDATE(H1,1) -> 45778 | J1: =EDATE(I1,1) -> 45809 | K1: =EDATE(J1,1) -> 45839 | L1: =EDATE(K1,1) -> 45870 | M1: =EDATE(L1,1) -> 45901 | N1: =EDATE(M1,1) -> 45931 | O1: =EDATE(N1,1) -> 45962 | P1: =EDATE(O1,1) -> 45992 | ... S1: =EDATE(R1,1) -> 46082
A2: FY2025-26 | B2: Honeywell | C2: =VLOOKUP(B2,Mapping!A:B,2,0) -> Lateral | D2: =VLOOKUP(B2,Mapping!A:C,3,0) -> South | E2: =VLOOKUP(B2,Mapping!A:D,4,0) -> South 1 | F2: =VLOOKUP(B2,Mapping!A:E,5,0) -> Bapi | G2: =VLOOKUP(B2,Mapping!A:F,6,0) -> Bapi | H2: 115.01649 | I2: 161.02309 | J2: 184.02639 | K2: 119.20399 | L2: 166.88559 | M2: 190.72639 | N2: 102.45399 | O2: 143.43559 | P2: 163.92639 | Q2: 120.04149 | R2: 168.05809 | S2: 192.06639
A3: FY2025-26 | B3: Pfizer | C3: =VLOOKUP(B3,Mapping!A:B,2,0) -> Lateral | D3: =VLOOKUP(B3,Mapping!A:C,3,0) -> West | E3: =VLOOKUP(B3,Mapping!A:D,4,0) -> West 1 | F3: =VLOOKUP(B3,Mapping!A:E,5,0) -> Anjli | G3: =VLOOKUP(B3,Mapping!A:F,6,0) -> Usha | H3: 9.75 | I3: 13.65 | J3: 15.6 | K3: 8.625 | L3: 12.075 | M3: 13.8 | N3: 5.625 | O3: 7.875 | P3: 9 | Q3: 9.6428625 | R3: 13.500008 | S3: 15.42858
A4: FY2025-26 | B4: Tata Motors | C4: =VLOOKUP(B4,Mapping!A:B,2,0) -> Lateral | D4: =VLOOKUP(B4,Mapping!A:C,3,0) -> West | E4: =VLOOKUP(B4,Mapping!A:D,4,0) -> West 2 | F4: =VLOOKUP(B4,Mapping!A:E,5,0) -> Anjli | G4: =VLOOKUP(B4,Mapping!A:F,6,0) -> Shweta | H4: 0 | I4: 0 | J4: 0 | K4: 0 | L4: 0 | M4: 0 | N4: 0 | O4: 0 | P4: 0 | Q4: 0 | R4: 0 | S4: 0
A5: FY2025-26 | B5: SKF India | C5: =VLOOKUP(B5,Mapping!A:B,2,0) -> Lateral | D5: =VLOOKUP(B5,Mapping!A:C,3,0) -> North | E5: =VLOOKUP(B5,Mapping!A:D,4,0) -> North | F5: =VLOOKUP(B5,Mapping!A:E,5,0) -> Anjli | G5: =VLOOKUP(B5,Mapping!A:F,6,0) -> Archana | H5: 13.9875 | I5: 19.5825 | J5: 22.38 | K5: 13.05 | L5: 18.27 | M5: 20.88 | N5: 10.6425 | O5: 14.8995 | P5: 17.028 | Q5: 12.2175 | R5: 17.1045 | S5: 19.548
A6: FY2025-26 | B6: Siemens | C6: =VLOOKUP(B6,Mapping!A:B,2,0) -> Lateral | D6: =VLOOKUP(B6,Mapping!A:C,3,0) -> South | E6: =VLOOKUP(B6,Mapping!A:D,4,0) -> South 1 | F6: =VLOOKUP(B6,Mapping!A:E,5,0) -> Sulabh | G6: =VLOOKUP(B6,Mapping!A:F,6,0) -> Kunal | H6: 17.625 | I6: 24.675 | J6: 28.2 | K6: 18.375 | L6: 25.725 | M6: 29.4 | N6: 17.625 | O6: 24.675 | P6: 28.2 | Q6: 15.105 | R6: 21.147 | S6: 24.168
A7: FY2025-26 | B7: Pidilite | C7: =VLOOKUP(B7,Mapping!A:B,2,0) -> Lateral | D7: =VLOOKUP(B7,Mapping!A:C,3,0) -> West | E7: =VLOOKUP(B7,Mapping!A:D,4,0) -> West 1 | F7: =VLOOKUP(B7,Mapping!A:E,5,0) -> Anjli | G7: =VLOOKUP(B7,Mapping!A:F,6,0) -> Usha | H7: 10.016875 | I7: 14.023625 | J7: 16.027 | K7: 11.6875 | L7: 16.3625 | M7: 18.7 | N7: 11.1875 | O7: 15.6625 | P7: 17.9 | Q7: 12.1875 | R7: 17.0625 | S7: 19.5
A8: FY2025-26 | B8: Vertiv | C8: =VLOOKUP(B8,Mapping!A:B,2,0) -> Lateral | D8: =VLOOKUP(B8,Mapping!A:C,3,0) -> West | E8: =VLOOKUP(B8,Mapping!A:D,4,0) -> West 2 | F8: =VLOOKUP(B8,Mapping!A:E,5,0) -> Anjli | G8: =VLOOKUP(B8,Mapping!A:F,6,0) -> Shweta | H8: 4.025 | I8: 5.635 | J8: 6.44 | K8: 4.65 | L8: 6.51 | M8: 7.44 | N8: 4.65 | O8: 6.51 | P8: 7.44 | Q8: 3.375 | R8: 4.725 | S8: 5.4
A9: FY2025-26 | B9: Birla Paints | C9: =VLOOKUP(B9,Mapping!A:B,2,0) -> Lateral | D9: =VLOOKUP(B9,Mapping!A:C,3,0) -> West | E9: =VLOOKUP(B9,Mapping!A:D,4,0) -> West 1 | F9: =VLOOKUP(B9,Mapping!A:E,5,0) -> Anjli | G9: =VLOOKUP(B9,Mapping!A:F,6,0) -> Geetu | H9: 7.5 | I9: 10.5 | J9: 12 | K9: 7.5 | L9: 10.5 | M9: 12 | N9: 7.5 | O9: 10.5 | P9: 12 | Q9: 7.5 | R9: 10.5 | S9: 12
A10: FY2025-26 | B10: Ingram Micro | C10: =VLOOKUP(B10,Mapping!A:B,2,0) -> Lateral | D10: =VLOOKUP(B10,Mapping!A:C,3,0) -> West | E10: =VLOOKUP(B10,Mapping!A:D,4,0) -> West 1 | F10: =VLOOKUP(B10,Mapping!A:E,5,0) -> Anjli | G10: =VLOOKUP(B10,Mapping!A:F,6,0) -> Geetu | H10: 6.9375 | I10: 9.7125 | J10: 11.1 | K10: 6.15 | L10: 8.61 | M10: 9.84 | N10: 5.25 | O10: 7.35 | P10: 8.4 | Q10: 6.5625 | R10: 9.1875 | S10: 10.5
A11: FY2025-26 | B11: HPE | C11: =VLOOKUP(B11,Mapping!A:B,2,0) -> Lateral | D11: =VLOOKUP(B11,Mapping!A:C,3,0) -> South | E11: =VLOOKUP(B11,Mapping!A:D,4,0) -> South 1 | F11: =VLOOKUP(B11,Mapping!A:E,5,0) -> Mahak | G11: =VLOOKUP(B11,Mapping!A:F,6,0) -> Mahak | H11: 90.74246 | I11: 127.03944 | J11: 145.18794 | K11: 103.77792 | L11: 145.28909 | M11: 166.04468 | N11: 92.472596 | O11: 129.46163 | P11: 147.95615 | Q11: 91.161021 | R11: 127.62543 | S11: 145.85763
A12: FY2025-26 | B12: Isuzu | C12: =VLOOKUP(B12,Mapping!A:B,2,0) -> Lateral | D12: =VLOOKUP(B12,Mapping!A:C,3,0) -> South | E12: =VLOOKUP(B12,Mapping!A:D,4,0) -> South 1 | F12: =VLOOKUP(B12,Mapping!A:E,5,0) -> Anjli | G12: =VLOOKUP(B12,Mapping!A:F,6,0) -> Satya | H12: 4.5375 | I12: 6.3525 | J12: 7.26 | K12: 6.05 | L12: 8.47 | M12: 9.68 | N12: 6.3975 | O12: 8.9565 | P12: 10.236 | Q12: 6.48 | R12: 9.072 | S12: 10.368
A13: FY2025-26 | B13: Mahindra Holidays | C13: =VLOOKUP(B13,Mapping!A:B,2,0) -> Lateral | D13: =VLOOKUP(B13,Mapping!A:C,3,0) -> West | E13: =VLOOKUP(B13,Mapping!A:D,4,0) -> West 1 | F13: =VLOOKUP(B13,Mapping!A:E,5,0) -> Anjli | G13: =VLOOKUP(B13,Mapping!A:F,6,0) -> Geetu | H13: 6.45 | I13: 9.03 | J13: 10.32 | K13: 6.45 | L13: 9.03 | M13: 10.32 | N13: 4 | O13: 5.6 | P13: 6.4 | Q13: 8 | R13: 11.2 | S13: 12.8
... A41: FY2025-26 | B41: M2P Fintech | C41: =VLOOKUP(B41,Mapping!A:B,2,0) -> Lateral | D41: =VLOOKUP(B41,Mapping!A:C,3,0) -> South | E41: =VLOOKUP(B41,Mapping!A:D,4,0) -> South 2 | F41: =VLOOKUP(B41,Mapping!A:E,5,0) -> Sulabh | G41: =VLOOKUP(B41,Mapping!A:F,6,0) -> Krishna | H41: 9.723616 | I41: 13.613062 | J41: 15.557786 | K41: 14.585424 | L41: 20.419594 | M41: 23.336678 | N41: 10.695978 | O41: 14.974369 | P41: 17.113564 | Q41: 13.613062 | R41: 19.058287 | S41: 21.7809
A42: FY2025-26 | B42: Tata Power | C42: =VLOOKUP(B42,Mapping!A:B,2,0) -> Lateral | D42: =VLOOKUP(B42,Mapping!A:C,3,0) -> West | E42: =VLOOKUP(B42,Mapping!A:D,4,0) -> West 1 | F42: =VLOOKUP(B42,Mapping!A:E,5,0) -> Anjli | G42: =VLOOKUP(B42,Mapping!A:F,6,0) -> Elton
A43: FY2025-26 | B43: ThyssenKrupp | C43: =VLOOKUP(B43,Mapping!A:B,2,0) -> Lateral | D43: =VLOOKUP(B43,Mapping!A:C,3,0) -> West | E43: =VLOOKUP(B43,Mapping!A:D,4,0) -> West 2 | F43: =VLOOKUP(B43,Mapping!A:E,5,0) -> Anjli | G43: =VLOOKUP(B43,Mapping!A:F,6,0) -> Shweta
A44: FY2025-26 | B44: Fedex | C44: =VLOOKUP(B44,Mapping!A:B,2,0) -> Lateral | D44: =VLOOKUP(B44,Mapping!A:C,3,0) -> West | E44: =VLOOKUP(B44,Mapping!A:D,4,0) -> West 1 | F44: =VLOOKUP(B44,Mapping!A:E,5,0) -> Anjli | G44: =VLOOKUP(B44,Mapping!A:F,6,0) -> Elton
A45: FY2025-26 | B45: Titan | C45: =VLOOKUP(B45,Mapping!A:B,2,0) -> Lateral | D45: =VLOOKUP(B45,Mapping!A:C,3,0) -> South | E45: =VLOOKUP(B45,Mapping!A:D,4,0) -> South 2 | F45: =VLOOKUP(B45,Mapping!A:E,5,0) -> Sulabh | G45: =VLOOKUP(B45,Mapping!A:F,6,0) -> Subu
A46: FY2025-26 | B46: Ultratech | C46: =VLOOKUP(B46,Mapping!A:B,2,0) -> Lateral | D46: =VLOOKUP(B46,Mapping!A:C,3,0) -> West | E46: =VLOOKUP(B46,Mapping!A:D,4,0) -> West 1 | F46: =VLOOKUP(B46,Mapping!A:E,5,0) -> Anjli | G46: =VLOOKUP(B46,Mapping!A:F,6,0) -> Elton
A47: FY2025-26 | B47: L&T (New) | C47: =VLOOKUP(B47,Mapping!A:B,2,0) -> Lateral | D47: =VLOOKUP(B47,Mapping!A:C,3,0) -> South | E47: =VLOOKUP(B47,Mapping!A:D,4,0) -> South 2 | F47: =VLOOKUP(B47,Mapping!A:E,5,0) -> Sulabh | G47: =VLOOKUP(B47,Mapping!A:F,6,0) -> Sulabh
A48: FY2025-26 | B48: DRL | C48: =VLOOKUP(B48,Mapping!A:B,2,0) -> Lateral | D48: =VLOOKUP(B48,Mapping!A:C,3,0) -> South | E48: =VLOOKUP(B48,Mapping!A:D,4,0) -> South 2 | F48: =VLOOKUP(B48,Mapping!A:E,5,0) -> Sulabh | G48: =VLOOKUP(B48,Mapping!A:F,6,0) -> Sulabh
A49: FY2025-26 | B49: Robert Bosch | C49: =VLOOKUP(B49,Mapping!A:B,2,0) -> Lateral | D49: =VLOOKUP(B49,Mapping!A:C,3,0) -> South | E49: =VLOOKUP(B49,Mapping!A:D,4,0) -> South 2 | F49: =VLOOKUP(B49,Mapping!A:E,5,0) -> Sulabh | G49: =VLOOKUP(B49,Mapping!A:F,6,0) -> Abhilash
A50: FY2025-26 | B50: Tata Teleservices | C50: =VLOOKUP(B50,Mapping!A:B,2,0) -> Lateral | D50: =VLOOKUP(B50,Mapping!A:C,3,0) -> West | E50: =VLOOKUP(B50,Mapping!A:D,4,0) -> West 1 | F50: =VLOOKUP(B50,Mapping!A:E,5,0) -> Anjli | G50: =VLOOKUP(B50,Mapping!A:F,6,0) -> Elton
A51: FY2025-26 | B51: Honeywell Leadership | C51: =VLOOKUP(B51,Mapping!A:B,2,0) -> Leadership | D51: =VLOOKUP(B51,Mapping!A:C,3,0) -> South | E51: =VLOOKUP(B51,Mapping!A:D,4,0) -> South 1 | F51: =VLOOKUP(B51,Mapping!A:E,5,0) -> Bapi | G51: =VLOOKUP(B51,Mapping!A:F,6,0) -> Parul | H51: 1.5 | I51: 2.1 | J51: 2.4 | K51: 1.25 | L51: 1.75 | M51: 2 | N51: 1.25 | O51: 1.75 | P51: 2 | Q51: 1.25 | R51: 1.75 | S51: 2
A52: FY2025-26 | B52: Siemens Leadership | C52: =VLOOKUP(B52,Mapping!A:B,2,0) -> Leadership | D52: =VLOOKUP(B52,Mapping!A:C,3,0) -> South | E52: =VLOOKUP(B52,Mapping!A:D,4,0) -> South 2 | F52: =VLOOKUP(B52,Mapping!A:E,5,0) -> Sulabh | G52: =VLOOKUP(B52,Mapping!A:F,6,0) -> Parul | H52: 1.25 | I52: 1.75 | J52: 2 | K52: 1.25 | L52: 1.75 | M52: 2 | N52: 1.25 | O52: 1.75 | P52: 2 | Q52: 1.25 | R52: 1.75 | S52: 2
A53: FY2025-26 | B53: Vertiv Leadership | C53: =VLOOKUP(B53,Mapping!A:B,2,0) -> Leadership | D53: =VLOOKUP(B53,Mapping!A:C,3,0) -> West | E53: =VLOOKUP(B53,Mapping!A:D,4,0) -> West 2 | F53: =VLOOKUP(B53,Mapping!A:E,5,0) -> Anjli | G53: =VLOOKUP(B53,Mapping!A:F,6,0) -> Parul | H53: 2 | I53: 2.8 | J53: 3.2 | K53: 2 | L53: 2.8 | M53: 3.2 | N53: 2 | O53: 2.8 | P53: 3.2 | Q53: 2 | R53: 2.8 | S53: 3.2
A54: FY2025-26 | B54: M&M Leadership | C54: =VLOOKUP(B54,Mapping!A:B,2,0) -> Leadership | D54: =VLOOKUP(B54,Mapping!A:C,3,0) -> West | E54: =VLOOKUP(B54,Mapping!A:D,4,0) -> West 1 | F54: =VLOOKUP(B54,Mapping!A:E,5,0) -> Anjli | G54: =VLOOKUP(B54,Mapping!A:F,6,0) -> Parul | H54: 8.75 | I54: 12.25 | J54: 14 | K54: 8.75 | L54: 12.25 | M54: 14 | N54: 21.25 | O54: 29.75 | P54: 34 | Q54: 21.25 | R54: 29.75 | S54: 34
A55: FY2025-26 | B55: AMNS Leadership | C55: =VLOOKUP(B55,Mapping!A:B,2,0) -> Leadership | D55: =VLOOKUP(B55,Mapping!A:C,3,0) -> West | E55: =VLOOKUP(B55,Mapping!A:D,4,0) -> West 1 | F55: =VLOOKUP(B55,Mapping!A:E,5,0) -> Anjli | G55: =VLOOKUP(B55,Mapping!A:F,6,0) -> Parul | H55: 4.375 | I55: 6.125 | J55: 7 | K55: 4.375 | L55: 6.125 | M55: 7 | N55: 4.375 | O55: 6.125 | P55: 7 | Q55: 4.375 | R55: 6.125 | S55: 7
A56: FY2025-26 | B56: Nagarjuna Leadership | C56: =VLOOKUP(B56,Mapping!A:B,2,0) -> Leadership | D56: =VLOOKUP(B56,Mapping!A:C,3,0) -> South | E56: =VLOOKUP(B56,Mapping!A:D,4,0) -> South 2 | F56: =VLOOKUP(B56,Mapping!A:E,5,0) -> Sulabh | G56: =VLOOKUP(B56,Mapping!A:F,6,0) -> Parul | H56: 0.25 | I56: 0.35 | J56: 0.4 | K56: 0.25 | L56: 0.35 | M56: 0.4 | N56: 0.25 | O56: 0.35 | P56: 0.4 | Q56: 0.25 | R56: 0.35 | S56: 0.4
A57: FY2025-26 | B57: Royal Enfield Leadership | C57: =VLOOKUP(B57,Mapping!A:B,2,0) -> Leadership | D57: =VLOOKUP(B57,Mapping!A:C,3,0) -> South | E57: =VLOOKUP(B57,Mapping!A:D,4,0) -> South 2 | F57: =VLOOKUP(B57,Mapping!A:E,5,0) -> Sulabh | G57: =VLOOKUP(B57,Mapping!A:F,6,0) -> Parul | H57: 0 | I57: 0 | J57: 0 | K57: 1.25 | L57: 1.75 | M57: 2 | N57: 0 | O57: 0 | P57: 0 | Q57: 0 | R57: 0 | S57: 0
A58: FY2025-26 | B58: Sterling Tools Leadership | C58: =VLOOKUP(B58,Mapping!A:B,2,0) -> Leadership | D58: =VLOOKUP(B58,Mapping!A:C,3,0) -> North | E58: =VLOOKUP(B58,Mapping!A:D,4,0) -> North | F58: =VLOOKUP(B58,Mapping!A:E,5,0) -> Anjli | G58: =VLOOKUP(B58,Mapping!A:F,6,0) -> Parul | H58: 0 | I58: 0 | J58: 0 | K58: 1.25 | L58: 1.75 | M58: 2 | N58: 0 | O58: 0 | P58: 0 | Q58: 0 | R58: 0 | S58: 0
A59: FY2025-26 | B59: Mahindra Holidays Leadership | C59: =VLOOKUP(B59,Mapping!A:B,2,0) -> Leadership | D59: =VLOOKUP(B59,Mapping!A:C,3,0) -> West | E59: =VLOOKUP(B59,Mapping!A:D,4,0) -> West 1 | F59: =VLOOKUP(B59,Mapping!A:E,5,0) -> Anjli | G59: =VLOOKUP(B59,Mapping!A:F,6,0) -> Parul | H59: 0 | I59: 0 | J59: 0 | K59: 0 | L59: 0 | M59: 0 | N59: 0 | O59: 0 | P59: 0 | Q59: 0 | R59: 0 | S59: 0
A60: FY2025-26 | B60: Hyundai Motor Leadership | C60: =VLOOKUP(B60,Mapping!A:B,2,0) -> Leadership | D60: =VLOOKUP(B60,Mapping!A:C,3,0) -> West | E60: =VLOOKUP(B60,Mapping!A:D,4,0) -> West 2 | F60: =VLOOKUP(B60,Mapping!A:E,5,0) -> Anjli | G60: =VLOOKUP(B60,Mapping!A:F,6,0) -> Parul | H60: 0 | I60: 0 | J60: 0 | K60: 0 | L60: 0 | M60: 0 | N60: 0 | O60: 0 | P60: 0 | Q60: 0 | R60: 0 | S60: 0
A61: FY2025-26 | B61: JINDAL STAINLESS Leadership | C61: =VLOOKUP(B61,Mapping!A:B,2,0) -> Leadership | D61: =VLOOKUP(B61,Mapping!A:C,3,0) -> North | E61: =VLOOKUP(B61,Mapping!A:D,4,0) -> North | F61: =VLOOKUP(B61,Mapping!A:E,5,0) -> Anjli | G61: =VLOOKUP(B61,Mapping!A:F,6,0) -> Parul | H61: 0 | I61: 0 | J61: 0 | K61: 0 | L61: 0 | M61: 0 | N61: 0 | O61: 0 | P61: 0 | Q61: 0 | R61: 0 | S61: 0
A62: FY2025-26 | B62: SUZUKI R&D Leadership | C62: =VLOOKUP(B62,Mapping!A:B,2,0) -> Leadership | D62: =VLOOKUP(B62,Mapping!A:C,3,0) -> North | E62: =VLOOKUP(B62,Mapping!A:D,4,0) -> North | F62: =VLOOKUP(B62,Mapping!A:E,5,0) -> Anjli | G62: =VLOOKUP(B62,Mapping!A:F,6,0) -> Parul | H62: 0 | I62: 0 | J62: 0 | K62: 0 | L62: 0 | M62: 0 | N62: 0 | O62: 0 | P62: 0 | Q62: 0 | R62: 0 | S62: 0
... A73: FY2025-26 | B73: ABB | C73: =VLOOKUP(B73,Mapping!A:B,2,0) -> Lateral | D73: =VLOOKUP(B73,Mapping!A:C,3,0) -> South | E73: =VLOOKUP(B73,Mapping!A:D,4,0) -> South 2 | F73: =VLOOKUP(B73,Mapping!A:E,5,0) -> Sulabh | G73: =VLOOKUP(B73,Mapping!A:F,6,0) -> Satya | H73: 0 | I73: 0 | J73: 0 | K73: 0 | L73: 0 | M73: 0 | N73: 0 | O73: 0 | P73: 0 | Q73: 0 | R73: 0 | S73: 0
A74: FY2025-26 | B74: TCG Group | C74: =VLOOKUP(B74,Mapping!A:B,2,0) -> Lateral | D74: =VLOOKUP(B74,Mapping!A:C,3,0) -> West | E74: =VLOOKUP(B74,Mapping!A:D,4,0) -> West 1 | F74: =VLOOKUP(B74,Mapping!A:E,5,0) -> Anjli | G74: =VLOOKUP(B74,Mapping!A:F,6,0) -> Anjli
A75: FY2025-26 | B75: Proterial | C75: =VLOOKUP(B75,Mapping!A:B,2,0) -> #N/A | D75: =VLOOKUP(B75,Mapping!A:C,3,0) -> #N/A | E75: =VLOOKUP(B75,Mapping!A:D,4,0) -> #N/A | F75: =VLOOKUP(B75,Mapping!A:E,5,0) -> #N/A | G75: =VLOOKUP(B75,Mapping!A:F,6,0) -> #N/A
A76: FY2025-26 | B76: CG Power | C76: =VLOOKUP(B76,Mapping!A:B,2,0) -> Lateral | D76: =VLOOKUP(B76,Mapping!A:C,3,0) -> West | E76: =VLOOKUP(B76,Mapping!A:D,4,0) -> West 1 | F76: =VLOOKUP(B76,Mapping!A:E,5,0) -> Anjli | G76: =VLOOKUP(B76,Mapping!A:F,6,0) -> Anjli

Sheet CM_Budget
A1: =Revenue_Budget!A1 -> FY | B1: =Revenue_Budget!B1 -> Project | C1: =Revenue_Budget!C1 -> Vertical | D1: =Revenue_Budget!D1 -> Region | E1: =Revenue_Budget!E1 -> Sub Region | F1: =Revenue_Budget!F1 -> Region Head | G1: =Revenue_Budget!G1 -> Practice Head | H1: =Revenue_Budget!H1 -> 45748 | ... S1: =Revenue_Budget!S1 -> 46082
A2: FY2025-26 | B2: Honeywell | C2: =VLOOKUP(B2,Mapping!A:B,2,0) -> Lateral | D2: =VLOOKUP(B2,Mapping!A:C,3,0) -> South | E2: =VLOOKUP(B2,Mapping!A:D,4,0) -> South 1 | F2: =VLOOKUP(B2,Mapping!A:E,5,0) -> Bapi | G2: =VLOOKUP(B2,Mapping!A:F,6,0) -> Bapi | H2: 64.189553 | I2: 89.865374 | J2: 102.70328 | K2: 66.526554 | L2: 93.137176 | M2: 106.44249 | N2: 57.178547 | O2: 80.049966 | P2: 91.485676 | Q2: 66.993955 | R2: 93.791537 | S2: 107.19033
A3: FY2025-26 | B3: Pfizer | C3: =VLOOKUP(B3,Mapping!A:B,2,0) -> Lateral | D3: =VLOOKUP(B3,Mapping!A:C,3,0) -> West | E3: =VLOOKUP(B3,Mapping!A:D,4,0) -> West 1 | F3: =VLOOKUP(B3,Mapping!A:E,5,0) -> Anjli | G3: =VLOOKUP(B3,Mapping!A:F,6,0) -> Usha | H3: 4.0111674 | I3: 5.6156344 | J3: 6.4178679 | K3: 3.5483404 | L3: 4.9676766 | M3: 5.6773447 | N3: 2.3141351 | O3: 3.2397891 | P3: 3.7026161 | Q3: 3.9670909 | R3: 5.5539273 | S3: 6.3473454
A4: FY2025-26 | B4: Tata Motors | C4: =VLOOKUP(B4,Mapping!A:B,2,0) -> Lateral | D4: =VLOOKUP(B4,Mapping!A:C,3,0) -> West | E4: =VLOOKUP(B4,Mapping!A:D,4,0) -> West 2 | F4: =VLOOKUP(B4,Mapping!A:E,5,0) -> Anjli | G4: =VLOOKUP(B4,Mapping!A:F,6,0) -> Shweta | H4: 0 | I4: 0 | J4: 0 | K4: 0 | L4: 0 | M4: 0 | N4: 0 | O4: 0 | P4: 0 | Q4: 0 | R4: 0 | S4: 0
A5: FY2025-26 | B5: SKF India | C5: =VLOOKUP(B5,Mapping!A:B,2,0) -> Lateral | D5: =VLOOKUP(B5,Mapping!A:C,3,0) -> North | E5: =VLOOKUP(B5,Mapping!A:D,4,0) -> North | F5: =VLOOKUP(B5,Mapping!A:E,5,0) -> Anjli | G5: =VLOOKUP(B5,Mapping!A:F,6,0) -> Archana | H5: 5.595 | I5: 7.833 | J5: 8.952 | K5: 5.22 | L5: 7.308 | M5: 8.352 | N5: 4.257 | O5: 5.9598 | P5: 6.8112 | Q5: 4.887 | R5: 6.8418 | S5: 7.8192
A6: FY2025-26 | B6: Siemens | C6: =VLOOKUP(B6,Mapping!A:B,2,0) -> Lateral | D6: =VLOOKUP(B6,Mapping!A:C,3,0) -> South | E6: =VLOOKUP(B6,Mapping!A:D,4,0) -> South 1 | F6: =VLOOKUP(B6,Mapping!A:E,5,0) -> Sulabh | G6: =VLOOKUP(B6,Mapping!A:F,6,0) -> Kunal | H6: 7.05 | I6: 9.87 | J6: 11.28 | K6: 7.35 | L6: 10.29 | M6: 11.76 | N6: 7.05 | O6: 9.87 | P6: 11.28 | Q6: 6.042 | R6: 8.4588 | S6: 9.6672
A7: FY2025-26 | B7: Pidilite | C7: =VLOOKUP(B7,Mapping!A:B,2,0) -> Lateral | D7: =VLOOKUP(B7,Mapping!A:C,3,0) -> West | E7: =VLOOKUP(B7,Mapping!A:D,4,0) -> West 1 | F7: =VLOOKUP(B7,Mapping!A:E,5,0) -> Anjli | G7: =VLOOKUP(B7,Mapping!A:F,6,0) -> Usha | H7: 4.00675 | I7: 5.60945 | J7: 6.4108 | K7: 4.675 | L7: 6.545 | M7: 7.48 | N7: 4.475 | O7: 6.265 | P7: 7.16 | Q7: 4.875 | R7: 6.825 | S7: 7.8
A8: FY2025-26 | B8: Vertiv | C8: =VLOOKUP(B8,Mapping!A:B,2,0) -> Lateral | D8: =VLOOKUP(B8,Mapping!A:C,3,0) -> West | E8: =VLOOKUP(B8,Mapping!A:D,4,0) -> West 2 | F8: =VLOOKUP(B8,Mapping!A:E,5,0) -> Anjli | G8: =VLOOKUP(B8,Mapping!A:F,6,0) -> Shweta | H8: 1.7927307 | I8: 2.509823 | J8: 2.8683691 | K8: 2.071105 | L8: 2.899547 | M8: 3.313768 | N8: 2.071105 | O8: 2.899547 | P8: 3.313768 | Q8: 1.5032214 | R8: 2.1045099 | S8: 2.4051542
A9: FY2025-26 | B9: Birla Paints | C9: =VLOOKUP(B9,Mapping!A:B,2,0) -> Lateral | D9: =VLOOKUP(B9,Mapping!A:C,3,0) -> West | E9: =VLOOKUP(B9,Mapping!A:D,4,0) -> West 1 | F9: =VLOOKUP(B9,Mapping!A:E,5,0) -> Anjli | G9: =VLOOKUP(B9,Mapping!A:F,6,0) -> Geetu | H9: 3 | I9: 4.2 | J9: 4.8 | K9: 3 | L9: 4.2 | M9: 4.8 | N9: 3 | O9: 4.2 | P9: 4.8 | Q9: 3 | R9: 4.2 | S9: 4.8
A10: FY2025-26 | B10: Ingram Micro | C10: =VLOOKUP(B10,Mapping!A:B,2,0) -> Lateral | D10: =VLOOKUP(B10,Mapping!A:C,3,0) -> West | E10: =VLOOKUP(B10,Mapping!A:D,4,0) -> West 1 | F10: =VLOOKUP(B10,Mapping!A:E,5,0) -> Anjli | G10: =VLOOKUP(B10,Mapping!A:F,6,0) -> Geetu | H10: 3.1471675 | I10: 4.4060345 | J10: 5.0354681 | K10: 2.7899215 | L10: 3.9058901 | M10: 4.4638744 | N10: 2.3816403 | O10: 3.3342964 | P10: 3.8106245 | Q10: 2.9770504 | R10: 4.1678705 | S10: 4.7632806
A11: FY2025-26 | B11: HPE | C11: =VLOOKUP(B11,Mapping!A:B,2,0) -> Lateral | D11: =VLOOKUP(B11,Mapping!A:C,3,0) -> South | E11: =VLOOKUP(B11,Mapping!A:D,4,0) -> South 1 | F11: =VLOOKUP(B11,Mapping!A:E,5,0) -> Mahak | G11: =VLOOKUP(B11,Mapping!A:F,6,0) -> Mahak | H11: 36.296984 | I11: 50.815778 | J11: 58.075175 | K11: 41.511169 | L11: 58.115637 | M11: 66.41787 | N11: 36.989038 | O11: 51.784654 | P11: 59.182461 | Q11: 36.464409 | R11: 51.050172 | S11: 58.343054
A12: FY2025-26 | B12: Isuzu | C12: =VLOOKUP(B12,Mapping!A:B,2,0) -> Lateral | D12: =VLOOKUP(B12,Mapping!A:C,3,0) -> South | E12: =VLOOKUP(B12,Mapping!A:D,4,0) -> South 1 | F12: =VLOOKUP(B12,Mapping!A:E,5,0) -> Anjli | G12: =VLOOKUP(B12,Mapping!A:F,6,0) -> Satya | H12: 2.676132 | I12: 3.7465848 | J12: 4.2818112 | K12: 3.568176 | L12: 4.9954463 | M12: 5.7090815 | N12: 3.7731249 | O12: 5.2823749 | P12: 6.0369999 | Q12: 3.8217819 | R12: 5.3504946 | S12: 6.114851
A13: FY2025-26 | B13: Mahindra Holidays | C13: =VLOOKUP(B13,Mapping!A:B,2,0) -> Lateral | D13: =VLOOKUP(B13,Mapping!A:C,3,0) -> West | E13: =VLOOKUP(B13,Mapping!A:D,4,0) -> West 1 | F13: =VLOOKUP(B13,Mapping!A:E,5,0) -> Anjli | G13: =VLOOKUP(B13,Mapping!A:F,6,0) -> Geetu | H13: 2.58 | I13: 3.612 | J13: 4.128 | K13: 2.58 | L13: 3.612 | M13: 4.128 | N13: 1.6 | O13: 2.24 | P13: 2.56 | Q13: 3.2 | R13: 4.48 | S13: 5.12
... A41: FY2025-26 | B41: M2P Fintech | C41: =VLOOKUP(B41,Mapping!A:B,2,0) -> Lateral | D41: =VLOOKUP(B41,Mapping!A:C,3,0) -> South | E41: =VLOOKUP(B41,Mapping!A:D,4,0) -> South 2 | F41: =VLOOKUP(B41,Mapping!A:E,5,0) -> Sulabh | G41: =VLOOKUP(B41,Mapping!A:F,6,0) -> Krishna | H41: 3.8894464 | I41: 5.445225 | J41: 6.2231142 | K41: 5.8341696 | L41: 8.1678374 | M41: 9.3346714 | N41: 4.278391 | O41: 5.9897475 | P41: 6.8454257 | Q41: 5.445225 | R41: 7.6233149 | S41: 8.7123599
A42: FY2025-26 | B42: Tata Power | C42: =VLOOKUP(B42,Mapping!A:B,2,0) -> Lateral | D42: =VLOOKUP(B42,Mapping!A:C,3,0) -> West | E42: =VLOOKUP(B42,Mapping!A:D,4,0) -> West 1 | F42: =VLOOKUP(B42,Mapping!A:E,5,0) -> Anjli | G42: =VLOOKUP(B42,Mapping!A:F,6,0) -> Elton
A43: FY2025-26 | B43: ThyssenKrupp | C43: =VLOOKUP(B43,Mapping!A:B,2,0) -> Lateral | D43: =VLOOKUP(B43,Mapping!A:C,3,0) -> West | E43: =VLOOKUP(B43,Mapping!A:D,4,0) -> West 2 | F43: =VLOOKUP(B43,Mapping!A:E,5,0) -> Anjli | G43: =VLOOKUP(B43,Mapping!A:F,6,0) -> Shweta
A44: FY2025-26 | B44: Fedex | C44: =VLOOKUP(B44,Mapping!A:B,2,0) -> Lateral | D44: =VLOOKUP(B44,Mapping!A:C,3,0) -> West | E44: =VLOOKUP(B44,Mapping!A:D,4,0) -> West 1 | F44: =VLOOKUP(B44,Mapping!A:E,5,0) -> Anjli | G44: =VLOOKUP(B44,Mapping!A:F,6,0) -> Elton
A45: FY2025-26 | B45: Titan | C45: =VLOOKUP(B45,Mapping!A:B,2,0) -> Lateral | D45: =VLOOKUP(B45,Mapping!A:C,3,0) -> South | E45: =VLOOKUP(B45,Mapping!A:D,4,0) -> South 2 | F45: =VLOOKUP(B45,Mapping!A:E,5,0) -> Sulabh | G45: =VLOOKUP(B45,Mapping!A:F,6,0) -> Subu
A46: FY2025-26 | B46: Ultratech | C46: =VLOOKUP(B46,Mapping!A:B,2,0) -> Lateral | D46: =VLOOKUP(B46,Mapping!A:C,3,0) -> West | E46: =VLOOKUP(B46,Mapping!A:D,4,0) -> West 1 | F46: =VLOOKUP(B46,Mapping!A:E,5,0) -> Anjli | G46: =VLOOKUP(B46,Mapping!A:F,6,0) -> Elton
A47: FY2025-26 | B47: L&T (New) | C47: =VLOOKUP(B47,Mapping!A:B,2,0) -> Lateral | D47: =VLOOKUP(B47,Mapping!A:C,3,0) -> South | E47: =VLOOKUP(B47,Mapping!A:D,4,0) -> South 2 | F47: =VLOOKUP(B47,Mapping!A:E,5,0) -> Sulabh | G47: =VLOOKUP(B47,Mapping!A:F,6,0) -> Sulabh
A48: FY2025-26 | B48: DRL | C48: =VLOOKUP(B48,Mapping!A:B,2,0) -> Lateral | D48: =VLOOKUP(B48,Mapping!A:C,3,0) -> South | E48: =VLOOKUP(B48,Mapping!A:D,4,0) -> South 2 | F48: =VLOOKUP(B48,Mapping!A:E,5,0) -> Sulabh | G48: =VLOOKUP(B48,Mapping!A:F,6,0) -> Sulabh
A49: FY2025-26 | B49: Robert Bosch | C49: =VLOOKUP(B49,Mapping!A:B,2,0) -> Lateral | D49: =VLOOKUP(B49,Mapping!A:C,3,0) -> South | E49: =VLOOKUP(B49,Mapping!A:D,4,0) -> South 2 | F49: =VLOOKUP(B49,Mapping!A:E,5,0) -> Sulabh | G49: =VLOOKUP(B49,Mapping!A:F,6,0) -> Abhilash
A50: FY2025-26 | B50: Tata Teleservices | C50: =VLOOKUP(B50,Mapping!A:B,2,0) -> Lateral | D50: =VLOOKUP(B50,Mapping!A:C,3,0) -> West | E50: =VLOOKUP(B50,Mapping!A:D,4,0) -> West 1 | F50: =VLOOKUP(B50,Mapping!A:E,5,0) -> Anjli | G50: =VLOOKUP(B50,Mapping!A:F,6,0) -> Elton
A51: FY2025-26 | B51: Honeywell Leadership | C51: =VLOOKUP(B51,Mapping!A:B,2,0) -> Leadership | D51: =VLOOKUP(B51,Mapping!A:C,3,0) -> South | E51: =VLOOKUP(B51,Mapping!A:D,4,0) -> South 1 | F51: =VLOOKUP(B51,Mapping!A:E,5,0) -> Bapi | G51: =VLOOKUP(B51,Mapping!A:F,6,0) -> Parul | H51: 0.6 | I51: 0.84 | J51: 0.96 | K51: 0.5 | L51: 0.7 | M51: 0.8 | N51: 0.5 | O51: 0.7 | P51: 0.8 | Q51: 0.5 | R51: 0.7 | S51: 0.8
A52: FY2025-26 | B52: Siemens Leadership | C52: =VLOOKUP(B52,Mapping!A:B,2,0) -> Leadership | D52: =VLOOKUP(B52,Mapping!A:C,3,0) -> South | E52: =VLOOKUP(B52,Mapping!A:D,4,0) -> South 2 | F52: =VLOOKUP(B52,Mapping!A:E,5,0) -> Sulabh | G52: =VLOOKUP(B52,Mapping!A:F,6,0) -> Parul | H52: 0.5 | I52: 0.7 | J52: 0.8 | K52: 0.5 | L52: 0.7 | M52: 0.8 | N52: 0.5 | O52: 0.7 | P52: 0.8 | Q52: 0.5 | R52: 0.7 | S52: 0.8
A53: FY2025-26 | B53: Vertiv Leadership | C53: =VLOOKUP(B53,Mapping!A:B,2,0) -> Leadership | D53: =VLOOKUP(B53,Mapping!A:C,3,0) -> West | E53: =VLOOKUP(B53,Mapping!A:D,4,0) -> West 2 | F53: =VLOOKUP(B53,Mapping!A:E,5,0) -> Anjli | G53: =VLOOKUP(B53,Mapping!A:F,6,0) -> Parul | H53: 0.8 | I53: 1.12 | J53: 1.28 | K53: 0.8 | L53: 1.12 | M53: 1.28 | N53: 0.8 | O53: 1.12 | P53: 1.28 | Q53: 0.8 | R53: 1.12 | S53: 1.28
A54: FY2025-26 | B54: M&M Leadership | C54: =VLOOKUP(B54,Mapping!A:B,2,0) -> Leadership | D54: =VLOOKUP(B54,Mapping!A:C,3,0) -> West | E54: =VLOOKUP(B54,Mapping!A:D,4,0) -> West 1 | F54: =VLOOKUP(B54,Mapping!A:E,5,0) -> Anjli | G54: =VLOOKUP(B54,Mapping!A:F,6,0) -> Parul | H54: 3.5 | I54: 4.9 | J54: 5.6 | K54: 3.5 | L54: 4.9 | M54: 5.6 | N54: 8.5 | O54: 11.9 | P54: 13.6 | Q54: 8.5 | R54: 11.9 | S54: 13.6
A55: FY2025-26 | B55: AMNS Leadership | C55: =VLOOKUP(B55,Mapping!A:B,2,0) -> Leadership | D55: =VLOOKUP(B55,Mapping!A:C,3,0) -> West | E55: =VLOOKUP(B55,Mapping!A:D,4,0) -> West 1 | F55: =VLOOKUP(B55,Mapping!A:E,5,0) -> Anjli | G55: =VLOOKUP(B55,Mapping!A:F,6,0) -> Parul | H55: 1.75 | I55: 2.45 | J55: 2.8 | K55: 1.75 | L55: 2.45 | M55: 2.8 | N55: 1.75 | O55: 2.45 | P55: 2.8 | Q55: 1.75 | R55: 2.45 | S55: 2.8
A56: FY2025-26 | B56: Nagarjuna Leadership | C56: =VLOOKUP(B56,Mapping!A:B,2,0) -> Leadership | D56: =VLOOKUP(B56,Mapping!A:C,3,0) -> South | E56: =VLOOKUP(B56,Mapping!A:D,4,0) -> South 2 | F56: =VLOOKUP(B56,Mapping!A:E,5,0) -> Sulabh | G56: =VLOOKUP(B56,Mapping!A:F,6,0) -> Parul | H56: 0.1 | I56: 0.14 | J56: 0.16 | K56: 0.1 | L56: 0.14 | M56: 0.16 | N56: 0.1 | O56: 0.14 | P56: 0.16 | Q56: 0.1 | R56: 0.14 | S56: 0.16
A57: FY2025-26 | B57: Royal Enfield Leadership | C57: =VLOOKUP(B57,Mapping!A:B,2,0) -> Leadership | D57: =VLOOKUP(B57,Mapping!A:C,3,0) -> South | E57: =VLOOKUP(B57,Mapping!A:D,4,0) -> South 2 | F57: =VLOOKUP(B57,Mapping!A:E,5,0) -> Sulabh | G57: =VLOOKUP(B57,Mapping!A:F,6,0) -> Parul | H57: 0 | I57: 0 | J57: 0 | K57: 0.5 | L57: 0.7 | M57: 0.8 | N57: 0 | O57: 0 | P57: 0 | Q57: 0 | R57: 0 | S57: 0
A58: FY2025-26 | B58: Sterling Tools Leadership | C58: =VLOOKUP(B58,Mapping!A:B,2,0) -> Leadership | D58: =VLOOKUP(B58,Mapping!A:C,3,0) -> North | E58: =VLOOKUP(B58,Mapping!A:D,4,0) -> North | F58: =VLOOKUP(B58,Mapping!A:E,5,0) -> Anjli | G58: =VLOOKUP(B58,Mapping!A:F,6,0) -> Parul | H58: 0 | I58: 0 | J58: 0 | K58: 0.5 | L58: 0.7 | M58: 0.8 | N58: 0 | O58: 0 | P58: 0 | Q58: 0 | R58: 0 | S58: 0
A59: FY2025-26 | B59: Mahindra Holidays Leadership | C59: =VLOOKUP(B59,Mapping!A:B,2,0) -> Leadership | D59: =VLOOKUP(B59,Mapping!A:C,3,0) -> West | E59: =VLOOKUP(B59,Mapping!A:D,4,0) -> West 1 | F59: =VLOOKUP(B59,Mapping!A:E,5,0) -> Anjli | G59: =VLOOKUP(B59,Mapping!A:F,6,0) -> Parul | H59: 0 | I59: 0 | J59: 0 | K59: 0 | L59: 0 | M59: 0 | N59: 0 | O59: 0 | P59: 0 | Q59: 0 | R59: 0 | S59: 0
A60: FY2025-26 | B60: Hyundai Motor Leadership | C60: =VLOOKUP(B60,Mapping!A:B,2,0) -> Leadership | D60: =VLOOKUP(B60,Mapping!A:C,3,0) -> West | E60: =VLOOKUP(B60,Mapping!A:D,4,0) -> West 2 | F60: =VLOOKUP(B60,Mapping!A:E,5,0) -> Anjli | G60: =VLOOKUP(B60,Mapping!A:F,6,0) -> Parul | H60: 0 | I60: 0 | J60: 0 | K60: 0 | L60: 0 | M60: 0 | N60: 0 | O60: 0 | P60: 0 | Q60: 0 | R60: 0 | S60: 0
A61: FY2025-26 | B61: JINDAL STAINLESS Leadership | C61: =VLOOKUP(B61,Mapping!A:B,2,0) -> Leadership | D61: =VLOOKUP(B61,Mapping!A:C,3,0) -> North | E61: =VLOOKUP(B61,Mapping!A:D,4,0) -> North | F61: =VLOOKUP(B61,Mapping!A:E,5,0) -> Anjli | G61: =VLOOKUP(B61,Mapping!A:F,6,0) -> Parul | H61: 0 | I61: 0 | J61: 0 | K61: 0 | L61: 0 | M61: 0 | N61: 0 | O61: 0 | P61: 0 | Q61: 0 | R61: 0 | S61: 0
A62: FY2025-26 | B62: SUZUKI R&D Leadership | C62: =VLOOKUP(B62,Mapping!A:B,2,0) -> Leadership | D62: =VLOOKUP(B62,Mapping!A:C,3,0) -> North | E62: =VLOOKUP(B62,Mapping!A:D,4,0) -> North | F62: =VLOOKUP(B62,Mapping!A:E,5,0) -> Anjli | G62: =VLOOKUP(B62,Mapping!A:F,6,0) -> Parul | H62: 0 | I62: 0 | J62: 0 | K62: 0 | L62: 0 | M62: 0 | N62: 0 | O62: 0 | P62: 0 | Q62: 0 | R62: 0 | S62: 0
... A73: FY2025-26 | B73: ABB | C73: =VLOOKUP(B73,Mapping!A:B,2,0) -> Lateral | D73: =VLOOKUP(B73,Mapping!A:C,3,0) -> South | E73: =VLOOKUP(B73,Mapping!A:D,4,0) -> South 2 | F73: =VLOOKUP(B73,Mapping!A:E,5,0) -> Sulabh | G73: =VLOOKUP(B73,Mapping!A:F,6,0) -> Satya | H73: 0 | I73: 0 | J73: 0 | K73: 0 | L73: 0 | M73: 0 | N73: 0 | O73: 0 | P73: 0 | Q73: 0 | R73: 0 | S73: 0
A74: FY2025-26 | B74: TCG Group | C74: =VLOOKUP(B74,Mapping!A:B,2,0) -> Lateral | D74: =VLOOKUP(B74,Mapping!A:C,3,0) -> West | E74: =VLOOKUP(B74,Mapping!A:D,4,0) -> West 1 | F74: =VLOOKUP(B74,Mapping!A:E,5,0) -> Anjli | G74: =VLOOKUP(B74,Mapping!A:F,6,0) -> Anjli
A75: FY2025-26 | B75: Proterial | C75: =VLOOKUP(B75,Mapping!A:B,2,0) -> #N/A | D75: =VLOOKUP(B75,Mapping!A:C,3,0) -> #N/A | E75: =VLOOKUP(B75,Mapping!A:D,4,0) -> #N/A | F75: =VLOOKUP(B75,Mapping!A:E,5,0) -> #N/A | G75: =VLOOKUP(B75,Mapping!A:F,6,0) -> #N/A
A76: FY2025-26 | B76: CG Power | C76: =VLOOKUP(B76,Mapping!A:B,2,0) -> Lateral | D76: =VLOOKUP(B76,Mapping!A:C,3,0) -> West | E76: =VLOOKUP(B76,Mapping!A:D,4,0) -> West 1 | F76: =VLOOKUP(B76,Mapping!A:E,5,0) -> Anjli | G76: =VLOOKUP(B76,Mapping!A:F,6,0) -> Anjli

Sheet Target Rev Productivity
A1: =Revenue_Budget!A1 -> FY | B1: =Revenue_Budget!B1 -> Project | C1: =Revenue_Budget!C1 -> Vertical | D1: =Revenue_Budget!D1 -> Region | E1: =Revenue_Budget!E1 -> Sub Region | F1: =Revenue_Budget!F1 -> Region Head | G1: =Revenue_Budget!G1 -> Practice Head | H1: =Revenue_Budget!H1 -> 45748 | ... S1: =Revenue_Budget!S1 -> 46082
A2: FY2025-26 | B2: Honeywell | C2: =VLOOKUP(B2,Mapping!A:B,2,0) -> Lateral | D2: =VLOOKUP(B2,Mapping!A:C,3,0) -> South | E2: =VLOOKUP(B2,Mapping!A:D,4,0) -> South 1 | F2: =VLOOKUP(B2,Mapping!A:E,5,0) -> Bapi | G2: =VLOOKUP(B2,Mapping!A:F,6,0) -> Bapi | H2: 3.2921657 | I2: 3.2921657 | J2: 3.2921657 | K2: 3.5555389 | L2: 3.5555389 | M2: 3.5555389 | N2: 3.0287924 | O2: 3.0287924 | P2: 3.0287924 | Q2: 3.2921657 | R2: 3.2921657 | S2: 3.2921657
A3: FY2025-26 | B3: Pfizer | C3: =VLOOKUP(B3,Mapping!A:B,2,0) -> Lateral | D3: =VLOOKUP(B3,Mapping!A:C,3,0) -> West | E3: =VLOOKUP(B3,Mapping!A:D,4,0) -> West 1 | F3: =VLOOKUP(B3,Mapping!A:E,5,0) -> Anjli | G3: =VLOOKUP(B3,Mapping!A:F,6,0) -> Usha | H3: 2.9191617 | I3: 2.9191617 | J3: 2.9191617 | K3: 3.1526946 | L3: 3.1526946 | M3: 3.1526946 | N3: 2.6856287 | O3: 2.6856287 | P3: 2.6856287 | Q3: 2.9191617 | R3: 2.9191617 | S3: 2.9191617
A4: FY2025-26 | B4: Tata Motors | C4: =VLOOKUP(B4,Mapping!A:B,2,0) -> Lateral | D4: =VLOOKUP(B4,Mapping!A:C,3,0) -> West | E4: =VLOOKUP(B4,Mapping!A:D,4,0) -> West 2 | F4: =VLOOKUP(B4,Mapping!A:E,5,0) -> Anjli | G4: =VLOOKUP(B4,Mapping!A:F,6,0) -> Shweta | H4: 2.2 | I4: 2.2 | J4: 2.2 | K4: 2.3 | L4: 2.3 | M4: 2.3 | N4: 2 | O4: 2 | P4: 2 | Q4: 2.2 | R4: 2.2 | S4: 2.2
A5: FY2025-26 | B5: SKF India | C5: =VLOOKUP(B5,Mapping!A:B,2,0) -> Lateral | D5: =VLOOKUP(B5,Mapping!A:C,3,0) -> North | E5: =VLOOKUP(B5,Mapping!A:D,4,0) -> North | F5: =VLOOKUP(B5,Mapping!A:E,5,0) -> Anjli | G5: =VLOOKUP(B5,Mapping!A:F,6,0) -> Archana | H5: 1.7212242 | I5: 1.7212242 | J5: 1.7212242 | K5: 1.8589222 | L5: 1.8589222 | M5: 1.8589222 | N5: 1.5835263 | O5: 1.5835263 | P5: 1.5835263 | Q5: 1.7212242 | R5: 1.7212242 | S5: 1.7212242
A6: FY2025-26 | B6: Siemens | C6: =VLOOKUP(B6,Mapping!A:B,2,0) -> Lateral | D6: =VLOOKUP(B6,Mapping!A:C,3,0) -> South | E6: =VLOOKUP(B6,Mapping!A:D,4,0) -> South 1 | F6: =VLOOKUP(B6,Mapping!A:E,5,0) -> Sulabh | G6: =VLOOKUP(B6,Mapping!A:F,6,0) -> Kunal | H6: 2.5484745 | I6: 2.5484745 | J6: 2.5484745 | K6: 2.7523524 | L6: 2.7523524 | M6: 2.7523524 | N6: 2.3445965 | O6: 2.3445965 | P6: 2.3445965 | Q6: 2.5484745 | R6: 2.5484745 | S6: 2.5484745
A7: FY2025-26 | B7: Pidilite | C7: =VLOOKUP(B7,Mapping!A:B,2,0) -> Lateral | D7: =VLOOKUP(B7,Mapping!A:C,3,0) -> West | E7: =VLOOKUP(B7,Mapping!A:D,4,0) -> West 1 | F7: =VLOOKUP(B7,Mapping!A:E,5,0) -> Anjli | G7: =VLOOKUP(B7,Mapping!A:F,6,0) -> Usha | H7: 1.9461078 | I7: 1.9461078 | J7: 1.9461078 | K7: 2.1017964 | L7: 2.1017964 | M7: 2.1017964 | N7: 1.7904192 | O7: 1.7904192 | P7: 1.7904192 | Q7: 1.9461078 | R7: 1.9461078 | S7: 1.9461078
A8: FY2025-26 | B8: Vertiv | C8: =VLOOKUP(B8,Mapping!A:B,2,0) -> Lateral | D8: =VLOOKUP(B8,Mapping!A:C,3,0) -> West | E8: =VLOOKUP(B8,Mapping!A:D,4,0) -> West 2 | F8: =VLOOKUP(B8,Mapping!A:E,5,0) -> Anjli | G8: =VLOOKUP(B8,Mapping!A:F,6,0) -> Shweta | H8: 2.5948104 | I8: 2.5948104 | J8: 2.5948104 | K8: 2.8023952 | L8: 2.8023952 | M8: 2.8023952 | N8: 2.3872255 | O8: 2.3872255 | P8: 2.3872255 | Q8: 2.5948104 | R8: 2.5948104 | S8: 2.5948104
A9: FY2025-26 | B9: Birla Paints | C9: =VLOOKUP(B9,Mapping!A:B,2,0) -> Lateral | D9: =VLOOKUP(B9,Mapping!A:C,3,0) -> West | E9: =VLOOKUP(B9,Mapping!A:D,4,0) -> West 1 | F9: =VLOOKUP(B9,Mapping!A:E,5,0) -> Anjli | G9: =VLOOKUP(B9,Mapping!A:F,6,0) -> Geetu | H9: 1.9461078 | I9: 1.9461078 | J9: 1.9461078 | K9: 2.1017964 | L9: 2.1017964 | M9: 2.1017964 | N9: 1.7904192 | O9: 1.7904192 | P9: 1.7904192 | Q9: 1.9461078 | R9: 1.9461078 | S9: 1.9461078
A10: FY2025-26 | B10: Ingram Micro | C10: =VLOOKUP(B10,Mapping!A:B,2,0) -> Lateral | D10: =VLOOKUP(B10,Mapping!A:C,3,0) -> West | E10: =VLOOKUP(B10,Mapping!A:D,4,0) -> West 1 | F10: =VLOOKUP(B10,Mapping!A:E,5,0) -> Anjli | G10: =VLOOKUP(B10,Mapping!A:F,6,0) -> Geetu | H10: 3.0575142 | I10: 3.0575142 | J10: 3.0575142 | K10: 3.3763798 | L10: 3.3763798 | M10: 3.3763798 | N10: 2.9840319 | O10: 2.9840319 | P10: 2.9840319 | Q10: 3.243513 | R10: 3.243513 | S10: 3.243513
A11: FY2025-26 | B11: HPE | C11: =VLOOKUP(B11,Mapping!A:B,2,0) -> Lateral | D11: =VLOOKUP(B11,Mapping!A:C,3,0) -> South | E11: =VLOOKUP(B11,Mapping!A:D,4,0) -> South 1 | F11: =VLOOKUP(B11,Mapping!A:E,5,0) -> Mahak | G11: =VLOOKUP(B11,Mapping!A:F,6,0) -> Mahak | H11: 3.1767893 | I11: 3.1767893 | J11: 3.1767893 | K11: 3.4309324 | L11: 3.4309324 | M11: 3.4309324 | N11: 2.9226461 | O11: 2.9226461 | P11: 2.9226461 | Q11: 3.1767893 | R11: 3.1767893 | S11: 3.1767893
A12: FY2025-26 | B12: Isuzu | C12: =VLOOKUP(B12,Mapping!A:B,2,0) -> Lateral | D12: =VLOOKUP(B12,Mapping!A:C,3,0) -> South | E12: =VLOOKUP(B12,Mapping!A:D,4,0) -> South 1 | F12: =VLOOKUP(B12,Mapping!A:E,5,0) -> Anjli | G12: =VLOOKUP(B12,Mapping!A:F,6,0) -> Satya | H12: 3.4844597 | I12: 3.4844597 | J12: 3.4844597 | K12: 3.2928144 | L12: 3.2928144 | M12: 3.2928144 | N12: 2.80499 | O12: 2.80499 | P12: 2.80499 | Q12: 3.0489022 | R12: 3.0489022 | S12: 3.0489022
A13: FY2025-26 | B13: Mahindra Holidays | C13: =VLOOKUP(B13,Mapping!A:B,2,0) -> Lateral | D13: =VLOOKUP(B13,Mapping!A:C,3,0) -> West | E13: =VLOOKUP(B13,Mapping!A:D,4,0) -> West 1 | F13: =VLOOKUP(B13,Mapping!A:E,5,0) -> Anjli | G13: =VLOOKUP(B13,Mapping!A:F,6,0) -> Geetu | H13: 1.6217565 | I13: 1.6217565 | J13: 1.6217565 | K13: 1.751497 | L13: 1.751497 | M13: 1.751497 | N13: 1.492016 | O13: 1.492016 | P13: 1.492016 | Q13: 1.6217565 | R13: 1.6217565 | S13: 1.6217565
... A76: FY2025-26 | B76: CG Power | C76: =VLOOKUP(B76,Mapping!A:B,2,0) -> Lateral | D76: =VLOOKUP(B76,Mapping!A:C,3,0) -> West | E76: =VLOOKUP(B76,Mapping!A:D,4,0) -> West 1 | F76: =VLOOKUP(B76,Mapping!A:E,5,0) -> Anjli | G76: =VLOOKUP(B76,Mapping!A:F,6,0) -> Anjli | H76: 2.2 | I76: 2.2 | J76: 2.2 | K76: 2.3 | L76: 2.3 | M76: 2.3 | N76: 2 | O76: 2 | P76: 2 | Q76: 2.2 | R76: 2.2 | S76: 2.2

Sheet Rev_Forecast
A1: =Revenue_Budget!A1 -> FY | B1: =Revenue_Budget!B1 -> Project | C1: =Revenue_Budget!C1 -> Vertical | D1: =Revenue_Budget!D1 -> Region | E1: =Revenue_Budget!E1 -> Sub Region | F1: =Revenue_Budget!F1 -> Region Head | G1: =Revenue_Budget!G1 -> Practice Head | H1: =Revenue_Budget!H1 -> 45748 | ... S1: =Revenue_Budget!S1 -> 46082
A2: FY2025-26 | B2: Honeywell | C2: =VLOOKUP(B2,Mapping!A:B,2,0) -> Lateral | D2: =VLOOKUP(B2,Mapping!A:C,3,0) -> South | E2: =VLOOKUP(B2,Mapping!A:D,4,0) -> South 1 | F2: =VLOOKUP(B2,Mapping!A:E,5,0) -> Bapi | G2: =VLOOKUP(B2,Mapping!A:F,6,0) -> Bapi | H2: 110 | I2: 154 | J2: 176 | K2: 119.20399 | L2: 166.88559 | M2: 190.72639 | N2: 82.453995 | O2: 115.43559 | P2: 131.92639 | Q2: 120 | R2: 152.66749 | S2: 134.57613
A3: FY2025-26 | B3: Pfizer | C3: =VLOOKUP(B3,Mapping!A:B,2,0) -> Lateral | D3: =VLOOKUP(B3,Mapping!A:C,3,0) -> West | E3: =VLOOKUP(B3,Mapping!A:D,4,0) -> West 1 | F3: =VLOOKUP(B3,Mapping!A:E,5,0) -> Anjli | G3: =VLOOKUP(B3,Mapping!A:F,6,0) -> Usha | H3: 4.375 | I3: 6.125 | J3: 7 | K3: 6.5 | L3: 9.1 | M3: 10.4 | N3: 4 | O3: 5.6 | P3: 6.4 | Q3: 8 | R3: 6.805 | S3: 7
A4: FY2025-26 | B4: Tata Motors | C4: =VLOOKUP(B4,Mapping!A:B,2,0) -> Lateral | D4: =VLOOKUP(B4,Mapping!A:C,3,0) -> West | E4: =VLOOKUP(B4,Mapping!A:D,4,0) -> West 2 | F4: =VLOOKUP(B4,Mapping!A:E,5,0) -> Anjli | G4: =VLOOKUP(B4,Mapping!A:F,6,0) -> Shweta | H4: 1.125 | I4: 1.575 | J4: 1.8 | K4: 0 | L4: 0 | M4: 0 | N4: 0 | O4: 0 | P4: 0 | S4: 0
A5: FY2025-26 | B5: SKF India | C5: =VLOOKUP(B5,Mapping!A:B,2,0) -> Lateral | D5: =VLOOKUP(B5,Mapping!A:C,3,0) -> North | E5: =VLOOKUP(B5,Mapping!A:D,4,0) -> North | F5: =VLOOKUP(B5,Mapping!A:E,5,0) -> Anjli | G5: =VLOOKUP(B5,Mapping!A:F,6,0) -> Archana | H5: 12.75 | I5: 17.85 | J5: 20.4 | K5: 13.05 | L5: 18.27 | M5: 20.88 | N5: 8.025 | O5: 11.235 | P5: 12.84 | Q5: 13 | R5: 21.7 | S5: 17
A6: FY2025-26 | B6: Siemens | C6: =VLOOKUP(B6,Mapping!A:B,2,0) -> Lateral | D6: =VLOOKUP(B6,Mapping!A:C,3,0) -> South | E6: =VLOOKUP(B6,Mapping!A:D,4,0) -> South 1 | F6: =VLOOKUP(B6,Mapping!A:E,5,0) -> Sulabh | G6: =VLOOKUP(B6,Mapping!A:F,6,0) -> Kunal | H6: 2.5 | I6: 3.5 | J6: 4 | K6: 6.75 | L6: 9.45 | M6: 10.8 | N6: 2.5 | O6: 3.5 | P6: 4 | Q6: 5 | R6: 23.6872 | S6: 24
A7: FY2025-26 | B7: Pidilite | C7: =VLOOKUP(B7,Mapping!A:B,2,0) -> Lateral | D7: =VLOOKUP(B7,Mapping!A:C,3,0) -> West | E7: =VLOOKUP(B7,Mapping!A:D,4,0) -> West 1 | F7: =VLOOKUP(B7,Mapping!A:E,5,0) -> Anjli | G7: =VLOOKUP(B7,Mapping!A:F,6,0) -> Usha | H7: 16.375 | I7: 22.925 | J7: 26.2 | K7: 18.375 | L7: 25.725 | M7: 29.4 | N7: 15 | O7: 21 | P7: 24 | Q7: 19.75 | R7: 3.88 | S7: 7.25
A8: FY2025-26 | B8: Vertiv | C8: =VLOOKUP(B8,Mapping!A:B,2,0) -> Lateral | D8: =VLOOKUP(B8,Mapping!A:C,3,0) -> West | E8: =VLOOKUP(B8,Mapping!A:D,4,0) -> West 2 | F8: =VLOOKUP(B8,Mapping!A:E,5,0) -> Anjli | G8: =VLOOKUP(B8,Mapping!A:F,6,0) -> Shweta | H8: 4 | I8: 5.6 | J8: 6.4 | K8: 5 | L8: 7 | M8: 8 | N8: 7.5 | O8: 10.5 | P8: 12 | Q8: 6.4272 | R8: 5.2736 | S8: 4.5
A9: FY2025-26 | B9: Birla Paints | C9: =VLOOKUP(B9,Mapping!A:B,2,0) -> Lateral | D9: =VLOOKUP(B9,Mapping!A:C,3,0) -> West | E9: =VLOOKUP(B9,Mapping!A:D,4,0) -> West 1 | F9: =VLOOKUP(B9,Mapping!A:E,5,0) -> Anjli | G9: =VLOOKUP(B9,Mapping!A:F,6,0) -> Geetu | H9: 0 | I9: 0 | J9: 0 | K9: 0 | L9: 0 | M9: 0 | N9: 0 | O9: 0 | P9: 0 | R9: 11.25 | S9: 13
A10: FY2025-26 | B10: Ingram Micro | C10: =VLOOKUP(B10,Mapping!A:B,2,0) -> Lateral | D10: =VLOOKUP(B10,Mapping!A:C,3,0) -> West | E10: =VLOOKUP(B10,Mapping!A:D,4,0) -> West 1 | F10: =VLOOKUP(B10,Mapping!A:E,5,0) -> Anjli | G10: =VLOOKUP(B10,Mapping!A:F,6,0) -> Geetu | H10: 8 | I10: 11.2 | J10: 12.8 | K10: 7.6875 | L10: 10.7625 | M10: 12.3 | N10: 7.5 | O10: 10.5 | P10: 12 | Q10: 10 | S10: 0
A11: FY2025-26 | B11: HPE | C11: =VLOOKUP(B11,Mapping!A:B,2,0) -> Lateral | D11: =VLOOKUP(B11,Mapping!A:C,3,0) -> South | E11: =VLOOKUP(B11,Mapping!A:D,4,0) -> South 1 | F11: =VLOOKUP(B11,Mapping!A:E,5,0) -> Mahak | G11: =VLOOKUP(B11,Mapping!A:F,6,0) -> Mahak | H11: 3.625 | I11: 5.075 | J11: 5.8 | K11: 2.5 | L11: 3.5 | M11: 4 | N11: 2.5 | O11: 3.5 | P11: 4 | Q11: 1.5 | R11: 224 | S11: 129
A12: FY2025-26 | B12: Isuzu | C12: =VLOOKUP(B12,Mapping!A:B,2,0) -> Lateral | D12: =VLOOKUP(B12,Mapping!A:C,3,0) -> South | E12: =VLOOKUP(B12,Mapping!A:D,4,0) -> South 1 | F12: =VLOOKUP(B12,Mapping!A:E,5,0) -> Anjli | G12: =VLOOKUP(B12,Mapping!A:F,6,0) -> Satya | H12: 9 | I12: 12.6 | J12: 14.4 | K12: 8.55 | L12: 11.97 | M12: 13.68 | N12: 9.045 | O12: 12.663 | P12: 14.472 | Q12: 13.75 | R12: -6.89698 | S12: 5
A13: FY2025-26 | B13: Mahindra Holidays | C13: =VLOOKUP(B13,Mapping!A:B,2,0) -> Lateral | D13: =VLOOKUP(B13,Mapping!A:C,3,0) -> West | E13: =VLOOKUP(B13,Mapping!A:D,4,0) -> West 1 | F13: =VLOOKUP(B13,Mapping!A:E,5,0) -> Anjli | G13: =VLOOKUP(B13,Mapping!A:F,6,0) -> Geetu | H13: 1.75 | I13: 2.45 | J13: 2.8 | K13: 2.525 | L13: 3.535 | M13: 4.04 | N13: 1 | O13: 1.4 | P13: 1.6 | R13: 6.97 | S13: 7
A14: FY2025-26 | B14: BITS | C14: =VLOOKUP(B14,Mapping!A:B,2,0) -> Lateral | D14: =VLOOKUP(B14,Mapping!A:C,3,0) -> South | E14: =VLOOKUP(B14,Mapping!A:D,4,0) -> South 2 | F14: =VLOOKUP(B14,Mapping!A:E,5,0) -> Sulabh | G14: =VLOOKUP(B14,Mapping!A:F,6,0) -> Krishna | H14: 70 | I14: 98 | J14: 112 | K14: 85 | L14: 119 | M14: 136 | N14: 78.75 | O14: 110.25 | P14: 126 | Q14: 130 | R14: 12.00338 | S14: 0
A15: FY2025-26 | B15: M&M | C15: =VLOOKUP(B15,Mapping!A:B,2,0) -> Lateral | D15: =VLOOKUP(B15,Mapping!A:C,3,0) -> West | E15: =VLOOKUP(B15,Mapping!A:D,4,0) -> West 1 | F15: =VLOOKUP(B15,Mapping!A:E,5,0) -> Anjli | G15: =VLOOKUP(B15,Mapping!A:F,6,0) -> Dhriti | H15: 5.375 | I15: 7.525 | J15: 8.6 | K15: 6.05 | L15: 8.47 | M15: 9.68 | N15: 6.375 | O15: 8.925 | P15: 10.2 | Q15: 5.98 | R15: 120.94803 | S15: 132.86
A16: FY2025-26 | B16: P&G | C16: =VLOOKUP(B16,Mapping!A:B,2,0) -> Lateral | D16: =VLOOKUP(B16,Mapping!A:C,3,0) -> South | E16: =VLOOKUP(B16,Mapping!A:D,4,0) -> South 2 | F16: =VLOOKUP(B16,Mapping!A:E,5,0) -> Sulabh | G16: =VLOOKUP(B16,Mapping!A:F,6,0) -> Krishna | H16: 5.625 | I16: 7.875 | J16: 9 | K16: 5.95125 | L16: 8.33175 | M16: 9.522 | N16: 4.95 | O16: 6.93 | P16: 7.92 | Q16: 5 | S16: 0
A17: FY2025-26 | B17: Wipro | C17: =VLOOKUP(B17,Mapping!A:B,2,0) -> Lateral | D17: =VLOOKUP(B17,Mapping!A:C,3,0) -> South | E17: =VLOOKUP(B17,Mapping!A:D,4,0) -> South 1 | F17: =VLOOKUP(B17,Mapping!A:E,5,0) -> Sulabh | G17: =VLOOKUP(B17,Mapping!A:F,6,0) -> Subu | H17: 3 | I17: 4.2 | J17: 4.8 | K17: 3.14825 | L17: 4.40755 | M17: 5.0372 | N17: 3 | O17: 4.2 | P17: 4.8 | Q17: 4 | R17: -15.7025 | S17: 20
A18: FY2025-26 | B18: Tata Marcopolo | C18: =VLOOKUP(B18,Mapping!A:B,2,0) -> Lateral | D18: =VLOOKUP(B18,Mapping!A:C,3,0) -> West | E18: =VLOOKUP(B18,Mapping!A:D,4,0) -> West 2 | F18: =VLOOKUP(B18,Mapping!A:E,5,0) -> Anjli | G18: =VLOOKUP(B18,Mapping!A:F,6,0) -> Anjli | H18: 66 | I18: 92.4 | J18: 105.6 | K18: 71.175 | L18: 99.645 | M18: 113.88 | N18: 82.5 | O18: 115.5 | P18: 132 | Q18: 140 | S18: 0
A19: FY2025-26 | B19: DP World | C19: =VLOOKUP(B19,Mapping!A:B,2,0) -> Lateral | D19: =VLOOKUP(B19,Mapping!A:C,3,0) -> West | E19: =VLOOKUP(B19,Mapping!A:D,4,0) -> West 1 | F19: =VLOOKUP(B19,Mapping!A:E,5,0) -> Anjli | G19: =VLOOKUP(B19,Mapping!A:F,6,0) -> Geetu | H19: 1.32 | I19: 1.848 | J19: 2.112 | K19: 0 | L19: 0 | M19: 0 | N19: 0 | O19: 0 | P19: 0 | R19: 4.5 | S19: 8.57
A20: FY2025-26 | B20: Ametek | C20: =VLOOKUP(B20,Mapping!A:B,2,0) -> Lateral | D20: =VLOOKUP(B20,Mapping!A:C,3,0) -> South | E20: =VLOOKUP(B20,Mapping!A:D,4,0) -> South 1 | F20: =VLOOKUP(B20,Mapping!A:E,5,0) -> Sulabh | G20: =VLOOKUP(B20,Mapping!A:F,6,0) -> Satya | H20: 17.1 | I20: 23.94 | J20: 27.36 | K20: 41.85 | L20: 58.59 | M20: 66.96 | N20: 25 | O20: 35 | P20: 40 | Q20: 55 | S20: 0
A21: FY2025-26 | B21: AMNS | C21: =VLOOKUP(B21,Mapping!A:B,2,0) -> Lateral | D21: =VLOOKUP(B21,Mapping!A:C,3,0) -> West | E21: =VLOOKUP(B21,Mapping!A:D,4,0) -> West 1 | F21: =VLOOKUP(B21,Mapping!A:E,5,0) -> Anjli | G21: =VLOOKUP(B21,Mapping!A:F,6,0) -> Alifia | H21: 8.5 | I21: 11.9 | J21: 13.6 | K21: 4.05 | L21: 5.67 | M21: 6.48 | N21: 5.26 | O21: 7.364 | P21: 8.416 | Q21: 8.27 | R21: 21.7 | S21: 30
A22: FY2025-26 | B22: Tata Electronics | C22: =VLOOKUP(B22,Mapping!A:B,2,0) -> Lateral | D22: =VLOOKUP(B22,Mapping!A:C,3,0) -> South | E22: =VLOOKUP(B22,Mapping!A:D,4,0) -> South 2 | F22: =VLOOKUP(B22,Mapping!A:E,5,0) -> Sulabh | G22: =VLOOKUP(B22,Mapping!A:F,6,0) -> Subu | H22: 3.15 | I22: 4.41 | J22: 5.04 | K22: 4 | L22: 5.6 | M22: 6.4 | N22: 0 | O22: 0 | P22: 0 | R22: -0.26681 | S22: 5.8369
A23: FY2025-26 | B23: Jindal Stainless | C23: =VLOOKUP(B23,Mapping!A:B,2,0) -> Lateral | D23: =VLOOKUP(B23,Mapping!A:C,3,0) -> North | E23: =VLOOKUP(B23,Mapping!A:D,4,0) -> North | F23: =VLOOKUP(B23,Mapping!A:E,5,0) -> Anjli | G23: =VLOOKUP(B23,Mapping!A:F,6,0) -> Archana | H23: 27.5 | I23: 38.5 | J23: 44 | K23: 37.75 | L23: 52.85 | M23: 60.4 | N23: 22.5 | O23: 31.5 | P23: 36 | Q23: 30 | R23: 6.8787 | S23: 10
A24: FY2025-26 | B24: Nomiso | C24: =VLOOKUP(B24,Mapping!A:B,2,0) -> Lateral | D24: =VLOOKUP(B24,Mapping!A:C,3,0) -> South | E24: =VLOOKUP(B24,Mapping!A:D,4,0) -> South 2 | F24: =VLOOKUP(B24,Mapping!A:E,5,0) -> Sulabh | G24: =VLOOKUP(B24,Mapping!A:F,6,0) -> Krishna | H24: 11.625 | I24: 16.275 | J24: 18.6 | K24: 3 | L24: 4.2 | M24: 4.8 | N24: 5 | O24: 7 | P24: 8 | Q24: 3.58 | S24: 0
A25: FY2025-26 | B25: Schaeffler | C25: =VLOOKUP(B25,Mapping!A:B,2,0) -> Lateral | D25: =VLOOKUP(B25,Mapping!A:C,3,0) -> West | E25: =VLOOKUP(B25,Mapping!A:D,4,0) -> West 2 | F25: =VLOOKUP(B25,Mapping!A:E,5,0) -> Anjli | G25: =VLOOKUP(B25,Mapping!A:F,6,0) -> Shweta | H25: 0 | I25: 0 | J25: 0 | K25: 0 | L25: 0 | M25: 0 | N25: 0 | O25: 0 | P25: 0 | R25: 10.42 | S25: 9
A26: FY2025-26 | B26: Royal Enfield | C26: =VLOOKUP(B26,Mapping!A:B,2,0) -> Lateral | D26: =VLOOKUP(B26,Mapping!A:C,3,0) -> South | E26: =VLOOKUP(B26,Mapping!A:D,4,0) -> South 2 | F26: =VLOOKUP(B26,Mapping!A:E,5,0) -> Sulabh | G26: =VLOOKUP(B26,Mapping!A:F,6,0) -> Krishna | H26: 7 | I26: 9.8 | J26: 11.2 | K26: 11.5 | L26: 16.1 | M26: 18.4 | N26: 7.5 | O26: 10.5 | P26: 12 | Q26: 10 | R26: 11.89968 | S26: 17.10032
A27: FY2025-26 | B27: SBI Card | C27: =VLOOKUP(B27,Mapping!A:B,2,0) -> Lateral | D27: =VLOOKUP(B27,Mapping!A:C,3,0) -> North | E27: =VLOOKUP(B27,Mapping!A:D,4,0) -> North | F27: =VLOOKUP(B27,Mapping!A:E,5,0) -> Anjli | G27: =VLOOKUP(B27,Mapping!A:F,6,0) -> Archana | H27: 4.5 | I27: 6.3 | J27: 7.2 | K27: 4 | L27: 5.6 | M27: 6.4 | N27: 5 | O27: 7 | P27: 8 | Q27: 5 | R27: 18.9 | S27: 20
A28: FY2025-26 | B28: Hyundai Motor | C28: =VLOOKUP(B28,Mapping!A:B,2,0) -> Lateral | D28: =VLOOKUP(B28,Mapping!A:C,3,0) -> West | E28: =VLOOKUP(B28,Mapping!A:D,4,0) -> West 2 | F28: =VLOOKUP(B28,Mapping!A:E,5,0) -> Anjli | G28: =VLOOKUP(B28,Mapping!A:F,6,0) -> Shweta | H28: 5.4925 | I28: 7.6895 | J28: 8.788 | K28: 6.75 | L28: 9.45 | M28: 10.8 | N28: 9 | O28: 12.6 | P28: 14.4 | Q28: 10.25 | R28: 14.24 | S28: 5
A29: FY2025-26 | B29: Maruti Suzuki(MSIL) | C29: =VLOOKUP(B29,Mapping!A:B,2,0) -> Lateral | D29: =VLOOKUP(B29,Mapping!A:C,3,0) -> North | E29: =VLOOKUP(B29,Mapping!A:D,4,0) -> North | F29: =VLOOKUP(B29,Mapping!A:E,5,0) -> Anjli | G29: =VLOOKUP(B29,Mapping!A:F,6,0) -> Archana | H29: 8.9 | I29: 12.46 | J29: 14.24 | K29: 10.25 | L29: 14.35 | M29: 16.4 | N29: 8.775 | O29: 12.285 | P29: 14.04 | Q29: 5 | R29: 34.97242 | S29: 45
A30: FY2025-26 | B30: Excelacom | C30: =VLOOKUP(B30,Mapping!A:B,2,0) -> Lateral | D30: =VLOOKUP(B30,Mapping!A:C,3,0) -> South | E30: =VLOOKUP(B30,Mapping!A:D,4,0) -> South 2 | F30: =VLOOKUP(B30,Mapping!A:E,5,0) -> Sulabh | G30: =VLOOKUP(B30,Mapping!A:F,6,0) -> Krishna | H30: 8.75 | I30: 12.25 | J30: 14 | K30: 8 | L30: 11.2 | M30: 12.8 | N30: 5 | O30: 7 | P30: 8 | Q30: 5 | S30: 0
A31: FY2025-26 | B31: Tata Consumer | C31: =VLOOKUP(B31,Mapping!A:B,2,0) -> Lateral | D31: =VLOOKUP(B31,Mapping!A:C,3,0) -> West | E31: =VLOOKUP(B31,Mapping!A:D,4,0) -> West 1 | F31: =VLOOKUP(B31,Mapping!A:E,5,0) -> Anjli | G31: =VLOOKUP(B31,Mapping!A:F,6,0) -> Geetu | H31: 21.5 | I31: 30.1 | J31: 34.4 | K31: 29.25 | L31: 40.95 | M31: 46.8 | N31: 33.75 | O31: 47.25 | P31: 54 | Q31: 42 | R31: 19.03 | S31: 19.75
A32: FY2025-26 | B32: Tata Play | C32: =VLOOKUP(B32,Mapping!A:B,2,0) -> Lateral | D32: =VLOOKUP(B32,Mapping!A:C,3,0) -> West | E32: =VLOOKUP(B32,Mapping!A:D,4,0) -> West 1 | F32: =VLOOKUP(B32,Mapping!A:E,5,0) -> Anjli | G32: =VLOOKUP(B32,Mapping!A:F,6,0) -> Geetu | H32: 2.5 | I32: 3.5 | J32: 4 | K32: 3 | L32: 4.2 | M32: 4.8 | N32: 0 | O32: 0 | P32: 0 | R32: 0.248 | S32: 1.04
A33: FY2025-26 | B33: Mahindra Finance | C33: =VLOOKUP(B33,Mapping!A:B,2,0) -> Lateral | D33: =VLOOKUP(B33,Mapping!A:C,3,0) -> West | E33: =VLOOKUP(B33,Mapping!A:D,4,0) -> West 1 | F33: =VLOOKUP(B33,Mapping!A:E,5,0) -> Anjli | G33: =VLOOKUP(B33,Mapping!A:F,6,0) -> Geetu | H33: 11.5 | I33: 16.1 | J33: 18.4 | K33: 12.5625 | L33: 17.5875 | M33: 20.1 | N33: 15 | O33: 21 | P33: 24 | Q33: 20.25 | R33: 3.22 | S33: 3.2
A34: FY2025-26 | B34: Suzuki R&D | C34: =VLOOKUP(B34,Mapping!A:B,2,0) -> Lateral | D34: =VLOOKUP(B34,Mapping!A:C,3,0) -> North | E34: =VLOOKUP(B34,Mapping!A:D,4,0) -> North | F34: =VLOOKUP(B34,Mapping!A:E,5,0) -> Anjli | G34: =VLOOKUP(B34,Mapping!A:F,6,0) -> Archana | H34: 0.925 | I34: 1.295 | J34: 1.48 | K34: 0.375 | L34: 0.525 | M34: 0.6 | N34: 0.375 | O34: 0.525 | P34: 0.6 | Q34: 1.04 | R34: -1.267 | S34: 0
A35: FY2025-26 | B35: Subros Ltd | C35: =VLOOKUP(B35,Mapping!A:B,2,0) -> Lateral | D35: =VLOOKUP(B35,Mapping!A:C,3,0) -> North | E35: =VLOOKUP(B35,Mapping!A:D,4,0) -> North | F35: =VLOOKUP(B35,Mapping!A:E,5,0) -> Anjli | G35: =VLOOKUP(B35,Mapping!A:F,6,0) -> Archana | H35: 6.25 | I35: 8.75 | J35: 10 | K35: 3.168 | L35: 4.4352 | M35: 5.0688 | N35: 2.4 | O35: 3.36 | P35: 3.84 | Q35: 3.2 | R35: 2.9498 | S35: 6
A36: FY2025-26 | B36: Atomberg Technologies | C36: =VLOOKUP(B36,Mapping!A:B,2,0) -> Lateral | D36: =VLOOKUP(B36,Mapping!A:C,3,0) -> West | E36: =VLOOKUP(B36,Mapping!A:D,4,0) -> West 1 | F36: =VLOOKUP(B36,Mapping!A:E,5,0) -> Anjli | G36: =VLOOKUP(B36,Mapping!A:F,6,0) -> Geetu | H36: 0 | I36: 0 | J36: 0 | K36: 0 | L36: 0 | M36: 0 | N36: 0 | O36: 0 | P36: 0 | R36: 9.11 | S36: 7.51
A37: FY2025-26 | B37: Bridgestone | C37: =VLOOKUP(B37,Mapping!A:B,2,0) -> Lateral | D37: =VLOOKUP(B37,Mapping!A:C,3,0) -> West | E37: =VLOOKUP(B37,Mapping!A:D,4,0) -> West 2 | F37: =VLOOKUP(B37,Mapping!A:E,5,0) -> Anjli | G37: =VLOOKUP(B37,Mapping!A:F,6,0) -> Shweta | H37: 3.075 | I37: 4.305 | J37: 4.92 | K37: 6.7995 | L37: 9.5193 | M37: 10.8792 | N37: 5.025 | O37: 7.035 | P37: 8.04 | Q37: 1 | R37: 3.06 | S37: 5
A38: FY2025-26 | B38: Ambuja Cement | C38: =VLOOKUP(B38,Mapping!A:B,2,0) -> Lateral | D38: =VLOOKUP(B38,Mapping!A:C,3,0) -> West | E38: =VLOOKUP(B38,Mapping!A:D,4,0) -> West 1 | F38: =VLOOKUP(B38,Mapping!A:E,5,0) -> Anjli | G38: =VLOOKUP(B38,Mapping!A:F,6,0) -> Ankit | H38: 5.625 | I38: 7.875 | J38: 9 | K38: 4.7235 | L38: 6.6129 | M38: 7.5576 | N38: 5.27 | O38: 7.378 | P38: 8.432 | Q38: 7.51 | R38: 29.50095 | S38: 56
A39: FY2025-26 | B39: Ashok Leyland | C39: =VLOOKUP(B39,Mapping!A:B,2,0) -> Lateral | D39: =VLOOKUP(B39,Mapping!A:C,3,0) -> South | E39: =VLOOKUP(B39,Mapping!A:D,4,0) -> South 2 | F39: =VLOOKUP(B39,Mapping!A:E,5,0) -> Sulabh | G39: =VLOOKUP(B39,Mapping!A:F,6,0) -> Krishna | H39: 3 | I39: 4.2 | J39: 4.8 | K39: 4 | L39: 5.6 | M39: 6.4 | N39: 4 | O39: 5.6 | P39: 6.4 | Q39: 4 | R39: 6 | S39: 24
A40: FY2025-26 | B40: Sterling Tools | C40: =VLOOKUP(B40,Mapping!A:B,2,0) -> Lateral | D40: =VLOOKUP(B40,Mapping!A:C,3,0) -> North | E40: =VLOOKUP(B40,Mapping!A:D,4,0) -> North | F40: =VLOOKUP(B40,Mapping!A:E,5,0) -> Anjli | G40: =VLOOKUP(B40,Mapping!A:F,6,0) -> Archana | H40: 30 | I40: 42 | J40: 48 | K40: 22.5 | L40: 31.5 | M40: 36 | N40: 26.25 | O40: 36.75 | P40: 42 | Q40: 38 | R40: 6.59455 | S40: 6.8
A41: FY2025-26 | B41: M2P Fintech | C41: =VLOOKUP(B41,Mapping!A:B,2,0) -> Lateral | D41: =VLOOKUP(B41,Mapping!A:C,3,0) -> South | E41: =VLOOKUP(B41,Mapping!A:D,4,0) -> South 2 | F41: =VLOOKUP(B41,Mapping!A:E,5,0) -> Sulabh | G41: =VLOOKUP(B41,Mapping!A:F,6,0) -> Krishna | H41: 11.5 | I41: 16.1 | J41: 18.4 | K41: 15.525 | L41: 21.735 | M41: 24.84 | N41: 13.225 | O41: 18.515 | P41: 21.16 | Q41: 10 | S41: 0
A42: FY2025-26 | B42: Tata Power | C42: =VLOOKUP(B42,Mapping!A:B,2,0) -> Lateral | D42: =VLOOKUP(B42,Mapping!A:C,3,0) -> West | E42: =VLOOKUP(B42,Mapping!A:D,4,0) -> West 1 | F42: =VLOOKUP(B42,Mapping!A:E,5,0) -> Anjli | G42: =VLOOKUP(B42,Mapping!A:F,6,0) -> Elton | H42: 3.25 | I42: 4.55 | J42: 5.2 | K42: 11.05 | L42: 15.47 | M42: 17.68 | N42: 4.8 | O42: 6.72 | P42: 7.68 | Q42: 5.3 | S42: 0
A43: FY2025-26 | B43: ThyssenKrupp | C43: =VLOOKUP(B43,Mapping!A:B,2,0) -> Lateral | D43: =VLOOKUP(B43,Mapping!A:C,3,0) -> West | E43: =VLOOKUP(B43,Mapping!A:D,4,0) -> West 2 | F43: =VLOOKUP(B43,Mapping!A:E,5,0) -> Anjli | G43: =VLOOKUP(B43,Mapping!A:F,6,0) -> Shweta | H43: 10 | I43: 14 | J43: 16 | K43: 7.5 | L43: 10.5 | M43: 12 | N43: 0 | O43: 0 | P43: 0 | S43: 0
A44: FY2025-26 | B44: Fedex | C44: =VLOOKUP(B44,Mapping!A:B,2,0) -> Lateral | D44: =VLOOKUP(B44,Mapping!A:C,3,0) -> West | E44: =VLOOKUP(B44,Mapping!A:D,4,0) -> West 1 | F44: =VLOOKUP(B44,Mapping!A:E,5,0) -> Anjli | G44: =VLOOKUP(B44,Mapping!A:F,6,0) -> Elton | H44: 1.5 | I44: 2.1 | J44: 2.4 | K44: 1.25 | L44: 1.75 | M44: 2 | N44: 1.25 | O44: 1.75 | P44: 2 | Q44: 0 | S44: 0
A45: FY2025-26 | B45: Titan | C45: =VLOOKUP(B45,Mapping!A:B,2,0) -> Lateral | D45: =VLOOKUP(B45,Mapping!A:C,3,0) -> South | E45: =VLOOKUP(B45,Mapping!A:D,4,0) -> South 2 | F45: =VLOOKUP(B45,Mapping!A:E,5,0) -> Sulabh | G45: =VLOOKUP(B45,Mapping!A:F,6,0) -> Subu | H45: 1 | I45: 1.4 | J45: 1.6 | K45: 3.75 | L45: 5.25 | M45: 6 | N45: 2.5 | O45: 3.5 | P45: 4 | S45: 0
A46: FY2025-26 | B46: Ultratech | C46: =VLOOKUP(B46,Mapping!A:B,2,0) -> Lateral | D46: =VLOOKUP(B46,Mapping!A:C,3,0) -> West | E46: =VLOOKUP(B46,Mapping!A:D,4,0) -> West 1 | F46: =VLOOKUP(B46,Mapping!A:E,5,0) -> Anjli | G46: =VLOOKUP(B46,Mapping!A:F,6,0) -> Elton | K46: 7.35 | L46: 10.29 | M46: 11.76 | N46: 2 | O46: 2.8 | P46: 3.2 | Q46: 2.5 | S46: 0
A47: FY2025-26 | B47: L&T (New) | C47: =VLOOKUP(B47,Mapping!A:B,2,0) -> Lateral | D47: =VLOOKUP(B47,Mapping!A:C,3,0) -> South | E47: =VLOOKUP(B47,Mapping!A:D,4,0) -> South 2 | F47: =VLOOKUP(B47,Mapping!A:E,5,0) -> Sulabh | G47: =VLOOKUP(B47,Mapping!A:F,6,0) -> Sulabh | H47: 12.675 | I47: 17.745 | J47: 20.28 | K47: 13.75 | L47: 19.25 | M47: 22 | N47: 17.5 | O47: 24.5 | P47: 28 | Q47: 10 | S47: 0
A48: FY2025-26 | B48: DRL | C48: =VLOOKUP(B48,Mapping!A:B,2,0) -> Lateral | D48: =VLOOKUP(B48,Mapping!A:C,3,0) -> South | E48: =VLOOKUP(B48,Mapping!A:D,4,0) -> South 2 | F48: =VLOOKUP(B48,Mapping!A:E,5,0) -> Sulabh | G48: =VLOOKUP(B48,Mapping!A:F,6,0) -> Sulabh | H48: 5 | I48: 7 | J48: 8 | K48: 4.375 | L48: 6.125 | M48: 7 | N48: 3.5 | O48: 4.9 | P48: 5.6 | Q48: 5 | S48: 0
A49: FY2025-26 | B49: Robert Bosch | C49: =VLOOKUP(B49,Mapping!A:B,2,0) -> Lateral | D49: =VLOOKUP(B49,Mapping!A:C,3,0) -> South | E49: =VLOOKUP(B49,Mapping!A:D,4,0) -> South 2 | F49: =VLOOKUP(B49,Mapping!A:E,5,0) -> Sulabh | G49: =VLOOKUP(B49,Mapping!A:F,6,0) -> Abhilash | K49: 0.625 | L49: 0.875 | M49: 1 | N49: 0.5 | O49: 0.7 | P49: 0.8 | S49: 0
A50: FY2025-26 | B50: Tata Teleservices | C50: =VLOOKUP(B50,Mapping!A:B,2,0) -> Lateral | D50: =VLOOKUP(B50,Mapping!A:C,3,0) -> West | E50: =VLOOKUP(B50,Mapping!A:D,4,0) -> West 1 | F50: =VLOOKUP(B50,Mapping!A:E,5,0) -> Anjli | G50: =VLOOKUP(B50,Mapping!A:F,6,0) -> Elton | H50: 5.4925 | I50: 7.6895 | J50: 8.788 | K50: 0.75 | L50: 1.05 | M50: 1.2 | N50: 0 | O50: 0 | P50: 0 | S50: 0
A51: FY2025-26 | B51: Honeywell Leadership | C51: =VLOOKUP(B51,Mapping!A:B,2,0) -> Leadership | D51: =VLOOKUP(B51,Mapping!A:C,3,0) -> South | E51: =VLOOKUP(B51,Mapping!A:D,4,0) -> South 1 | F51: =VLOOKUP(B51,Mapping!A:E,5,0) -> Bapi | G51: =VLOOKUP(B51,Mapping!A:F,6,0) -> Parul | K51: 0 | L51: 0 | M51: 0 | N51: 0 | O51: 0 | P51: 0 | R51: 1.0269 | S51: 0
A52: FY2025-26 | B52: Siemens Leadership | C52: =VLOOKUP(B52,Mapping!A:B,2,0) -> Leadership | D52: =VLOOKUP(B52,Mapping!A:C,3,0) -> South | E52: =VLOOKUP(B52,Mapping!A:D,4,0) -> South 2 | F52: =VLOOKUP(B52,Mapping!A:E,5,0) -> Sulabh | G52: =VLOOKUP(B52,Mapping!A:F,6,0) -> Parul | K52: 0 | L52: 0 | M52: 0 | N52: 0.9 | O52: 1.26 | P52: 1.44 | Q52: 1.5 | R52: -0.35 | S52: 0
A53: FY2025-26 | B53: Vertiv Leadership | C53: =VLOOKUP(B53,Mapping!A:B,2,0) -> Leadership | D53: =VLOOKUP(B53,Mapping!A:C,3,0) -> West | E53: =VLOOKUP(B53,Mapping!A:D,4,0) -> West 2 | F53: =VLOOKUP(B53,Mapping!A:E,5,0) -> Anjli | G53: =VLOOKUP(B53,Mapping!A:F,6,0) -> Parul | K53: 0 | L53: 0 | M53: 0 | N53: 1.1 | O53: 1.54 | P53: 1.76 | Q53: 1.5 | R53: 1.7 | S53: 5
A54: FY2025-26 | B54: M&M Leadership | C54: =VLOOKUP(B54,Mapping!A:B,2,0) -> Leadership | D54: =VLOOKUP(B54,Mapping!A:C,3,0) -> West | E54: =VLOOKUP(B54,Mapping!A:D,4,0) -> West 1 | F54: =VLOOKUP(B54,Mapping!A:E,5,0) -> Anjli | G54: =VLOOKUP(B54,Mapping!A:F,6,0) -> Parul | K54: 0.85 | L54: 1.19 | M54: 1.36 | N54: 1.5 | O54: 2.1 | P54: 2.4 | R54: 30.42 | S54: 105
A55: FY2025-26 | B55: AMNS Leadership | C55: =VLOOKUP(B55,Mapping!A:B,2,0) -> Leadership | D55: =VLOOKUP(B55,Mapping!A:C,3,0) -> West | E55: =VLOOKUP(B55,Mapping!A:D,4,0) -> West 1 | F55: =VLOOKUP(B55,Mapping!A:E,5,0) -> Anjli | G55: =VLOOKUP(B55,Mapping!A:F,6,0) -> Parul | H55: 0 | I55: 0 | J55: 0 | K55: 0 | L55: 0 | M55: 0 | N55: 0 | O55: 0 | P55: 0 | Q55: 63.333333 | S55: 10
A56: FY2025-26 | B56: Nagarjuna Leadership | C56: =VLOOKUP(B56,Mapping!A:B,2,0) -> Leadership | D56: =VLOOKUP(B56,Mapping!A:C,3,0) -> South | E56: =VLOOKUP(B56,Mapping!A:D,4,0) -> South 2 | F56: =VLOOKUP(B56,Mapping!A:E,5,0) -> Sulabh | G56: =VLOOKUP(B56,Mapping!A:F,6,0) -> Parul | H56: 0 | I56: 0 | J56: 0 | K56: 0 | L56: 0 | M56: 0 | N56: 0 | O56: 0 | P56: 0 | R56: -1 | S56: 0
A57: FY2025-26 | B57: Royal Enfield Leadership | C57: =VLOOKUP(B57,Mapping!A:B,2,0) -> Leadership | D57: =VLOOKUP(B57,Mapping!A:C,3,0) -> South | E57: =VLOOKUP(B57,Mapping!A:D,4,0) -> South 2 | F57: =VLOOKUP(B57,Mapping!A:E,5,0) -> Sulabh | G57: =VLOOKUP(B57,Mapping!A:F,6,0) -> Parul | H57: 1.5 | I57: 2.1 | J57: 2.4 | K57: 5 | L57: 7 | M57: 8 | N57: 5.025 | O57: 7.035 | P57: 8.04 | Q57: 9.2 | R57: -1.62 | S57: 0
A58: FY2025-26 | B58: Sterling Tools Leadership | C58: =VLOOKUP(B58,Mapping!A:B,2,0) -> Leadership | D58: =VLOOKUP(B58,Mapping!A:C,3,0) -> North | E58: =VLOOKUP(B58,Mapping!A:D,4,0) -> North | F58: =VLOOKUP(B58,Mapping!A:E,5,0) -> Anjli | G58: =VLOOKUP(B58,Mapping!A:F,6,0) -> Parul | H58: 0 | I58: 0 | J58: 0 | K58: 0 | L58: 0 | M58: 0 | N58: 1.3125 | O58: 1.8375 | P58: 2.1 | S58: 0
A59: FY2025-26 | B59: Mahindra Holidays Leadership | C59: =VLOOKUP(B59,Mapping!A:B,2,0) -> Leadership | D59: =VLOOKUP(B59,Mapping!A:C,3,0) -> West | E59: =VLOOKUP(B59,Mapping!A:D,4,0) -> West 1 | F59: =VLOOKUP(B59,Mapping!A:E,5,0) -> Anjli | G59: =VLOOKUP(B59,Mapping!A:F,6,0) -> Parul | H59: 0 | I59: 0 | J59: 0 | K59: 0 | L59: 0 | M59: 0 | N59: 0 | O59: 0 | P59: 0 | Q59: 4 | S59: 0
A60: FY2025-26 | B60: Hyundai Motor Leadership | C60: =VLOOKUP(B60,Mapping!A:B,2,0) -> Leadership | D60: =VLOOKUP(B60,Mapping!A:C,3,0) -> West | E60: =VLOOKUP(B60,Mapping!A:D,4,0) -> West 2 | F60: =VLOOKUP(B60,Mapping!A:E,5,0) -> Anjli | G60: =VLOOKUP(B60,Mapping!A:F,6,0) -> Parul | H60: 0 | I60: 0 | J60: 0 | K60: 11.14 | L60: 15.596 | M60: 17.824 | N60: 5.825 | O60: 8.155 | P60: 9.32 | Q60: 9.7 | S60: 0
A61: FY2025-26 | B61: JINDAL STAINLESS Leadership | C61: =VLOOKUP(B61,Mapping!A:B,2,0) -> Leadership | D61: =VLOOKUP(B61,Mapping!A:C,3,0) -> North | E61: =VLOOKUP(B61,Mapping!A:D,4,0) -> North | F61: =VLOOKUP(B61,Mapping!A:E,5,0) -> Anjli | G61: =VLOOKUP(B61,Mapping!A:F,6,0) -> Parul | K61: 0 | L61: 0 | M61: 0 | N61: 0 | O61: 0 | P61: 0 | S61: 0
A62: FY2025-26 | B62: SUZUKI R&D Leadership | C62: =VLOOKUP(B62,Mapping!A:B,2,0) -> Leadership | D62: =VLOOKUP(B62,Mapping!A:C,3,0) -> North | E62: =VLOOKUP(B62,Mapping!A:D,4,0) -> North | F62: =VLOOKUP(B62,Mapping!A:E,5,0) -> Anjli | G62: =VLOOKUP(B62,Mapping!A:F,6,0) -> Parul | K62: 0 | L62: 0 | M62: 0 | N62: 0 | O62: 0 | P62: 0 | S62: 0
A63: FY2025-26 | B63: Pfizer Leadership | C63: =VLOOKUP(B63,Mapping!A:B,2,0) -> Leadership | D63: =VLOOKUP(B63,Mapping!A:C,3,0) -> West | E63: =VLOOKUP(B63,Mapping!A:D,4,0) -> West 1 | F63: =VLOOKUP(B63,Mapping!A:E,5,0) -> Anjli | G63: =VLOOKUP(B63,Mapping!A:F,6,0) -> Parul | K63: 0 | L63: 0 | M63: 0 | N63: 0 | O63: 0 | P63: 0 | S63: 0
A64: FY2025-26 | B64: Subros Leadership | C64: =VLOOKUP(B64,Mapping!A:B,2,0) -> Leadership | D64: =VLOOKUP(B64,Mapping!A:C,3,0) -> North | E64: =VLOOKUP(B64,Mapping!A:D,4,0) -> North | F64: =VLOOKUP(B64,Mapping!A:E,5,0) -> Anjli | G64: =VLOOKUP(B64,Mapping!A:F,6,0) -> Parul | H64: 0 | I64: 0 | J64: 0 | K64: 0 | L64: 0 | M64: 0 | N64: 0 | O64: 0 | P64: 0 | Q64: 3.95 | S64: 1.5
A65: FY2025-26 | B65: Optum | C65: =VLOOKUP(B65,Mapping!A:B,2,0) -> Lateral | D65: =VLOOKUP(B65,Mapping!A:C,3,0) -> South | E65: =VLOOKUP(B65,Mapping!A:D,4,0) -> South 1 | F65: =VLOOKUP(B65,Mapping!A:E,5,0) -> Ashish | G65: =VLOOKUP(B65,Mapping!A:F,6,0) -> Ashish | H65: 0.575 | I65: 0.805 | J65: 0.92 | K65: 0 | L65: 0 | M65: 0 | N65: 0 | O65: 0 | P65: 0 | R65: 81 | S65: 62.726
A66: FY2025-26 | B66: New Sales + Mining | C66: =VLOOKUP(B66,Mapping!A:B,2,0) -> Lateral | D66: =VLOOKUP(B66,Mapping!A:C,3,0) -> New Sales | E66: =VLOOKUP(B66,Mapping!A:D,4,0) -> New Sales | F66: =VLOOKUP(B66,Mapping!A:E,5,0) -> Nizar | G66: =VLOOKUP(B66,Mapping!A:F,6,0) -> Nizar | N66: 0.5 | O66: 0.7 | P66: 0.8 | Q66: 1.04 | S66: 0
A67: FY2025-26 | B67: Pernod Ricard | C67: =VLOOKUP(B67,Mapping!A:B,2,0) -> Lateral | D67: =VLOOKUP(B67,Mapping!A:C,3,0) -> North | E67: =VLOOKUP(B67,Mapping!A:D,4,0) -> North | F67: =VLOOKUP(B67,Mapping!A:E,5,0) -> Anjli | G67: =VLOOKUP(B67,Mapping!A:F,6,0) -> Archana | Q67: 3 | R67: 10.4 | S67: 11
A68: FY2025-26 | B68: UniCharm | C68: =VLOOKUP(B68,Mapping!A:B,2,0) -> Lateral | D68: =VLOOKUP(B68,Mapping!A:C,3,0) -> North | E68: =VLOOKUP(B68,Mapping!A:D,4,0) -> North | F68: =VLOOKUP(B68,Mapping!A:E,5,0) -> Anjli | G68: =VLOOKUP(B68,Mapping!A:F,6,0) -> Archana | Q68: 2 | R68: 3.1 | S68: 6.65
A69: FY2025-26 | B69: Saint Gobain | C69: =VLOOKUP(B69,Mapping!A:B,2,0) -> #N/A | D69: =VLOOKUP(B69,Mapping!A:C,3,0) -> #N/A | E69: =VLOOKUP(B69,Mapping!A:D,4,0) -> #N/A | F69: =VLOOKUP(B69,Mapping!A:E,5,0) -> #N/A | G69: =VLOOKUP(B69,Mapping!A:F,6,0) -> #N/A | R69: 3.72 | S69: 3.72
A70: FY2025-26 | B70: Leap India | C70: =VLOOKUP(B70,Mapping!A:B,2,0) -> Lateral | D70: =VLOOKUP(B70,Mapping!A:C,3,0) -> West | E70: =VLOOKUP(B70,Mapping!A:D,4,0) -> West 1 | F70: =VLOOKUP(B70,Mapping!A:E,5,0) -> Anjli | G70: =VLOOKUP(B70,Mapping!A:F,6,0) -> Geetu | R70: 6.82272 | S70: 9.8
A71: FY2025-26 | B71: NeoSoft | C71: =VLOOKUP(B71,Mapping!A:B,2,0) -> Lateral | D71: =VLOOKUP(B71,Mapping!A:C,3,0) -> West | E71: =VLOOKUP(B71,Mapping!A:D,4,0) -> West 1 | F71: =VLOOKUP(B71,Mapping!A:E,5,0) -> Anjli | G71: =VLOOKUP(B71,Mapping!A:F,6,0) -> Archana | R71: 1.95 | S71: 3.95
A72: FY2025-26 | B72: Siemens Healthnier | C72: =VLOOKUP(B72,Mapping!A:B,2,0) -> Lateral | D72: =VLOOKUP(B72,Mapping!A:C,3,0) -> South | E72: =VLOOKUP(B72,Mapping!A:D,4,0) -> South 2 | F72: =VLOOKUP(B72,Mapping!A:E,5,0) -> Sulabh | G72: =VLOOKUP(B72,Mapping!A:F,6,0) -> Lekhana | R72: 3.95 | S72: 3
A73: FY2025-26 | B73: ABB | C73: =VLOOKUP(B73,Mapping!A:B,2,0) -> Lateral | D73: =VLOOKUP(B73,Mapping!A:C,3,0) -> South | E73: =VLOOKUP(B73,Mapping!A:D,4,0) -> South 2 | F73: =VLOOKUP(B73,Mapping!A:E,5,0) -> Sulabh | G73: =VLOOKUP(B73,Mapping!A:F,6,0) -> Satya | R73: 5.62187 | S73: 6.29375
A74: FY2025-26 | B74: TCG Group | C74: =VLOOKUP(B74,Mapping!A:B,2,0) -> Lateral | D74: =VLOOKUP(B74,Mapping!A:C,3,0) -> West | E74: =VLOOKUP(B74,Mapping!A:D,4,0) -> West 1 | F74: =VLOOKUP(B74,Mapping!A:E,5,0) -> Anjli | G74: =VLOOKUP(B74,Mapping!A:F,6,0) -> Anjli | S74: 2
A75: FY2025-26 | B75: Proterial | C75: =VLOOKUP(B75,Mapping!A:B,2,0) -> #N/A | D75: =VLOOKUP(B75,Mapping!A:C,3,0) -> #N/A | E75: =VLOOKUP(B75,Mapping!A:D,4,0) -> #N/A | F75: =VLOOKUP(B75,Mapping!A:E,5,0) -> #N/A | G75: =VLOOKUP(B75,Mapping!A:F,6,0) -> #N/A | R75: 1.85 | S75: 4.4
A76: FY2025-26 | B76: CG Power | C76: =VLOOKUP(B76,Mapping!A:B,2,0) -> Lateral | D76: =VLOOKUP(B76,Mapping!A:C,3,0) -> West | E76: =VLOOKUP(B76,Mapping!A:D,4,0) -> West 1 | F76: =VLOOKUP(B76,Mapping!A:E,5,0) -> Anjli | G76: =VLOOKUP(B76,Mapping!A:F,6,0) -> Anjli | R76: 0.434 | S76: 2

Sheet CM_Forecast
A1: =Revenue_Budget!A1 -> FY | B1: =Revenue_Budget!B1 -> Project | C1: =Revenue_Budget!C1 -> Vertical | D1: =Revenue_Budget!D1 -> Region | E1: =Revenue_Budget!E1 -> Sub Region | F1: =Revenue_Budget!F1 -> Region Head | G1: =Revenue_Budget!G1 -> Practice Head | H1: =Revenue_Budget!H1 -> 45748 | ... S1: =Revenue_Budget!S1 -> 46082
A2: FY2025-26 | B2: Honeywell | C2: =VLOOKUP(B2,Mapping!A:B,2,0) -> Lateral | D2: =VLOOKUP(B2,Mapping!A:C,3,0) -> South | E2: =VLOOKUP(B2,Mapping!A:D,4,0) -> South 1 | F2: =VLOOKUP(B2,Mapping!A:E,5,0) -> Bapi | G2: =VLOOKUP(B2,Mapping!A:F,6,0) -> Bapi | H2: =IFERROR(Rev_Forecast!H2*45%,0) -> 49.5 | I2: =IFERROR(Rev_Forecast!I2*45%,0) -> 69.3 | J2: =IFERROR(Rev_Forecast!J2*45%,0) -> 79.2 | K2: =IFERROR(Rev_Forecast!K2*45%,0) -> 53.641798 | L2: =IFERROR(Rev_Forecast!L2*45%,0) -> 75.098517 | M2: =IFERROR(Rev_Forecast!M2*45%,0) -> 85.826876 | N2: =IFERROR(Rev_Forecast!N2*45%,0) -> 37.104298 | O2: =IFERROR(Rev_Forecast!O2*45%,0) -> 51.946017 | ... S2: =IFERROR(Rev_Forecast!S2*45%,0) -> 60.559258
A3: FY2025-26 | B3: Pfizer | C3: =VLOOKUP(B3,Mapping!A:B,2,0) -> Lateral | D3: =VLOOKUP(B3,Mapping!A:C,3,0) -> West | E3: =VLOOKUP(B3,Mapping!A:D,4,0) -> West 1 | F3: =VLOOKUP(B3,Mapping!A:E,5,0) -> Anjli | G3: =VLOOKUP(B3,Mapping!A:F,6,0) -> Usha | H3: =IFERROR(Rev_Forecast!H3*45%,0) -> 1.96875 | I3: =IFERROR(Rev_Forecast!I3*45%,0) -> 2.75625 | J3: =IFERROR(Rev_Forecast!J3*45%,0) -> 3.15 | K3: =IFERROR(Rev_Forecast!K3*45%,0) -> 2.925 | L3: =IFERROR(Rev_Forecast!L3*45%,0) -> 4.095 | M3: =IFERROR(Rev_Forecast!M3*45%,0) -> 4.68 | N3: =IFERROR(Rev_Forecast!N3*45%,0) -> 1.8 | O3: =IFERROR(Rev_Forecast!O3*45%,0) -> 2.52 | ... S3: =IFERROR(Rev_Forecast!S3*45%,0) -> 3.15
A4: FY2025-26 | B4: Tata Motors | C4: =VLOOKUP(B4,Mapping!A:B,2,0) -> Lateral | D4: =VLOOKUP(B4,Mapping!A:C,3,0) -> West | E4: =VLOOKUP(B4,Mapping!A:D,4,0) -> West 2 | F4: =VLOOKUP(B4,Mapping!A:E,5,0) -> Anjli | G4: =VLOOKUP(B4,Mapping!A:F,6,0) -> Shweta | H4: =IFERROR(Rev_Forecast!H4*45%,0) -> 0.50625 | I4: =IFERROR(Rev_Forecast!I4*45%,0) -> 0.70875 | J4: =IFERROR(Rev_Forecast!J4*45%,0) -> 0.81 | K4: =IFERROR(Rev_Forecast!K4*45%,0) -> 0 | L4: =IFERROR(Rev_Forecast!L4*45%,0) -> 0 | M4: =IFERROR(Rev_Forecast!M4*45%,0) -> 0 | N4: =IFERROR(Rev_Forecast!N4*45%,0) -> 0 | O4: =IFERROR(Rev_Forecast!O4*45%,0) -> 0 | ... S4: =IFERROR(Rev_Forecast!S4*45%,0) -> 0
A5: FY2025-26 | B5: SKF India | C5: =VLOOKUP(B5,Mapping!A:B,2,0) -> Lateral | D5: =VLOOKUP(B5,Mapping!A:C,3,0) -> North | E5: =VLOOKUP(B5,Mapping!A:D,4,0) -> North | F5: =VLOOKUP(B5,Mapping!A:E,5,0) -> Anjli | G5: =VLOOKUP(B5,Mapping!A:F,6,0) -> Archana | H5: =IFERROR(Rev_Forecast!H5*45%,0) -> 5.7375 | I5: =IFERROR(Rev_Forecast!I5*45%,0) -> 8.0325 | J5: =IFERROR(Rev_Forecast!J5*45%,0) -> 9.18 | K5: =IFERROR(Rev_Forecast!K5*45%,0) -> 5.8725 | L5: =IFERROR(Rev_Forecast!L5*45%,0) -> 8.2215 | M5: =IFERROR(Rev_Forecast!M5*45%,0) -> 9.396 | N5: =IFERROR(Rev_Forecast!N5*45%,0) -> 3.61125 | O5: =IFERROR(Rev_Forecast!O5*45%,0) -> 5.05575 | ... S5: =IFERROR(Rev_Forecast!S5*45%,0) -> 7.65
A6: FY2025-26 | B6: Siemens | C6: =VLOOKUP(B6,Mapping!A:B,2,0) -> Lateral | D6: =VLOOKUP(B6,Mapping!A:C,3,0) -> South | E6: =VLOOKUP(B6,Mapping!A:D,4,0) -> South 1 | F6: =VLOOKUP(B6,Mapping!A:E,5,0) -> Sulabh | G6: =VLOOKUP(B6,Mapping!A:F,6,0) -> Kunal | H6: =IFERROR(Rev_Forecast!H6*45%,0) -> 1.125 | I6: =IFERROR(Rev_Forecast!I6*45%,0) -> 1.575 | J6: =IFERROR(Rev_Forecast!J6*45%,0) -> 1.8 | K6: =IFERROR(Rev_Forecast!K6*45%,0) -> 3.0375 | L6: =IFERROR(Rev_Forecast!L6*45%,0) -> 4.2525 | M6: =IFERROR(Rev_Forecast!M6*45%,0) -> 4.86 | N6: =IFERROR(Rev_Forecast!N6*45%,0) -> 1.125 | O6: =IFERROR(Rev_Forecast!O6*45%,0) -> 1.575 | ... S6: =IFERROR(Rev_Forecast!S6*45%,0) -> 10.8
A7: FY2025-26 | B7: Pidilite | C7: =VLOOKUP(B7,Mapping!A:B,2,0) -> Lateral | D7: =VLOOKUP(B7,Mapping!A:C,3,0) -> West | E7: =VLOOKUP(B7,Mapping!A:D,4,0) -> West 1 | F7: =VLOOKUP(B7,Mapping!A:E,5,0) -> Anjli | G7: =VLOOKUP(B7,Mapping!A:F,6,0) -> Usha | H7: =IFERROR(Rev_Forecast!H7*45%,0) -> 7.36875 | I7: =IFERROR(Rev_Forecast!I7*45%,0) -> 10.31625 | J7: =IFERROR(Rev_Forecast!J7*45%,0) -> 11.79 | K7: =IFERROR(Rev_Forecast!K7*45%,0) -> 8.26875 | L7: =IFERROR(Rev_Forecast!L7*45%,0) -> 11.57625 | M7: =IFERROR(Rev_Forecast!M7*45%,0) -> 13.23 | N7: =IFERROR(Rev_Forecast!N7*45%,0) -> 6.75 | O7: =IFERROR(Rev_Forecast!O7*45%,0) -> 9.45 | ... S7: =IFERROR(Rev_Forecast!S7*45%,0) -> 3.2625
A8: FY2025-26 | B8: Vertiv | C8: =VLOOKUP(B8,Mapping!A:B,2,0) -> Lateral | D8: =VLOOKUP(B8,Mapping!A:C,3,0) -> West | E8: =VLOOKUP(B8,Mapping!A:D,4,0) -> West 2 | F8: =VLOOKUP(B8,Mapping!A:E,5,0) -> Anjli | G8: =VLOOKUP(B8,Mapping!A:F,6,0) -> Shweta | H8: =IFERROR(Rev_Forecast!H8*45%,0) -> 1.8 | I8: =IFERROR(Rev_Forecast!I8*45%,0) -> 2.52 | J8: =IFERROR(Rev_Forecast!J8*45%,0) -> 2.88 | K8: =IFERROR(Rev_Forecast!K8*45%,0) -> 2.25 | L8: =IFERROR(Rev_Forecast!L8*45%,0) -> 3.15 | M8: =IFERROR(Rev_Forecast!M8*45%,0) -> 3.6 | N8: =IFERROR(Rev_Forecast!N8*45%,0) -> 3.375 | O8: =IFERROR(Rev_Forecast!O8*45%,0) -> 4.725 | ... S8: =IFERROR(Rev_Forecast!S8*45%,0) -> 2.025
A9: FY2025-26 | B9: Birla Paints | C9: =VLOOKUP(B9,Mapping!A:B,2,0) -> Lateral | D9: =VLOOKUP(B9,Mapping!A:C,3,0) -> West | E9: =VLOOKUP(B9,Mapping!A:D,4,0) -> West 1 | F9: =VLOOKUP(B9,Mapping!A:E,5,0) -> Anjli | G9: =VLOOKUP(B9,Mapping!A:F,6,0) -> Geetu | H9: =IFERROR(Rev_Forecast!H9*45%,0) -> 0 | I9: =IFERROR(Rev_Forecast!I9*45%,0) -> 0 | J9: =IFERROR(Rev_Forecast!J9*45%,0) -> 0 | K9: =IFERROR(Rev_Forecast!K9*45%,0) -> 0 | L9: =IFERROR(Rev_Forecast!L9*45%,0) -> 0 | M9: =IFERROR(Rev_Forecast!M9*45%,0) -> 0 | N9: =IFERROR(Rev_Forecast!N9*45%,0) -> 0 | O9: =IFERROR(Rev_Forecast!O9*45%,0) -> 0 | ... S9: =IFERROR(Rev_Forecast!S9*45%,0) -> 5.85
A10: FY2025-26 | B10: Ingram Micro | C10: =VLOOKUP(B10,Mapping!A:B,2,0) -> Lateral | D10: =VLOOKUP(B10,Mapping!A:C,3,0) -> West | E10: =VLOOKUP(B10,Mapping!A:D,4,0) -> West 1 | F10: =VLOOKUP(B10,Mapping!A:E,5,0) -> Anjli | G10: =VLOOKUP(B10,Mapping!A:F,6,0) -> Geetu | H10: =IFERROR(Rev_Forecast!H10*45%,0) -> 3.6 | I10: =IFERROR(Rev_Forecast!I10*45%,0) -> 5.04 | J10: =IFERROR(Rev_Forecast!J10*45%,0) -> 5.76 | K10: =IFERROR(Rev_Forecast!K10*45%,0) -> 3.459375 | L10: =IFERROR(Rev_Forecast!L10*45%,0) -> 4.843125 | M10: =IFERROR(Rev_Forecast!M10*45%,0) -> 5.535 | N10: =IFERROR(Rev_Forecast!N10*45%,0) -> 3.375 | O10: =IFERROR(Rev_Forecast!O10*45%,0) -> 4.725 | ... S10: =IFERROR(Rev_Forecast!S10*45%,0) -> 0
A11: FY2025-26 | B11: HPE | C11: =VLOOKUP(B11,Mapping!A:B,2,0) -> Lateral | D11: =VLOOKUP(B11,Mapping!A:C,3,0) -> South | E11: =VLOOKUP(B11,Mapping!A:D,4,0) -> South 1 | F11: =VLOOKUP(B11,Mapping!A:E,5,0) -> Mahak | G11: =VLOOKUP(B11,Mapping!A:F,6,0) -> Mahak | H11: =IFERROR(Rev_Forecast!H11*45%,0) -> 1.63125 | I11: =IFERROR(Rev_Forecast!I11*45%,0) -> 2.28375 | J11: =IFERROR(Rev_Forecast!J11*45%,0) -> 2.61 | K11: =IFERROR(Rev_Forecast!K11*45%,0) -> 1.125 | L11: =IFERROR(Rev_Forecast!L11*45%,0) -> 1.575 | M11: =IFERROR(Rev_Forecast!M11*45%,0) -> 1.8 | N11: =IFERROR(Rev_Forecast!N11*45%,0) -> 1.125 | O11: =IFERROR(Rev_Forecast!O11*45%,0) -> 1.575 | ... S11: =IFERROR(Rev_Forecast!S11*45%,0) -> 58.05
A12: FY2025-26 | B12: Isuzu | C12: =VLOOKUP(B12,Mapping!A:B,2,0) -> Lateral | D12: =VLOOKUP(B12,Mapping!A:C,3,0) -> South | E12: =VLOOKUP(B12,Mapping!A:D,4,0) -> South 1 | F12: =VLOOKUP(B12,Mapping!A:E,5,0) -> Anjli | G12: =VLOOKUP(B12,Mapping!A:F,6,0) -> Satya | H12: =IFERROR(Rev_Forecast!H12*45%,0) -> 4.05 | I12: =IFERROR(Rev_Forecast!I12*45%,0) -> 5.67 | J12: =IFERROR(Rev_Forecast!J12*45%,0) -> 6.48 | K12: =IFERROR(Rev_Forecast!K12*45%,0) -> 3.8475 | L12: =IFERROR(Rev_Forecast!L12*45%,0) -> 5.3865 | M12: =IFERROR(Rev_Forecast!M12*45%,0) -> 6.156 | N12: =IFERROR(Rev_Forecast!N12*45%,0) -> 4.07025 | O12: =IFERROR(Rev_Forecast!O12*45%,0) -> 5.69835 | ... S12: =IFERROR(Rev_Forecast!S12*45%,0) -> 2.25
A13: FY2025-26 | B13: Mahindra Holidays | C13: =VLOOKUP(B13,Mapping!A:B,2,0) -> Lateral | D13: =VLOOKUP(B13,Mapping!A:C,3,0) -> West | E13: =VLOOKUP(B13,Mapping!A:D,4,0) -> West 1 | F13: =VLOOKUP(B13,Mapping!A:E,5,0) -> Anjli | G13: =VLOOKUP(B13,Mapping!A:F,6,0) -> Geetu | H13: =IFERROR(Rev_Forecast!H13*45%,0) -> 0.7875 | I13: =IFERROR(Rev_Forecast!I13*45%,0) -> 1.1025 | J13: =IFERROR(Rev_Forecast!J13*45%,0) -> 1.26 | K13: =IFERROR(Rev_Forecast!K13*45%,0) -> 1.13625 | L13: =IFERROR(Rev_Forecast!L13*45%,0) -> 1.59075 | M13: =IFERROR(Rev_Forecast!M13*45%,0) -> 1.818 | N13: =IFERROR(Rev_Forecast!N13*45%,0) -> 0.45 | O13: =IFERROR(Rev_Forecast!O13*45%,0) -> 0.63 | ... S13: =IFERROR(Rev_Forecast!S13*45%,0) -> 3.15
... A76: FY2025-26 | B76: CG Power | C76: =VLOOKUP(B76,Mapping!A:B,2,0) -> Lateral | D76: =VLOOKUP(B76,Mapping!A:C,3,0) -> West | E76: =VLOOKUP(B76,Mapping!A:D,4,0) -> West 1 | F76: =VLOOKUP(B76,Mapping!A:E,5,0) -> Anjli | G76: =VLOOKUP(B76,Mapping!A:F,6,0) -> Anjli | H76: =IFERROR(Rev_Forecast!H76*45%,0) -> 0 | I76: =IFERROR(Rev_Forecast!I76*45%,0) -> 0 | J76: =IFERROR(Rev_Forecast!J76*45%,0) -> 0 | K76: =IFERROR(Rev_Forecast!K76*45%,0) -> 0 | L76: =IFERROR(Rev_Forecast!L76*45%,0) -> 0 | M76: =IFERROR(Rev_Forecast!M76*45%,0) -> 0 | N76: =IFERROR(Rev_Forecast!N76*45%,0) -> 0 | O76: =IFERROR(Rev_Forecast!O76*45%,0) -> 0 | ... S76: =IFERROR(Rev_Forecast!S76*45%,0) -> 0.9

Sheet Mapping
A1: Project | B1: Vertical | C1: Region | D1: Sub Region | E1: Region Head | F1: Practice Head
A2: Honeywell | B2: Lateral | C2: South | D2: South 1 | E2: Bapi | F2: Bapi
A3: Pfizer | B3: Lateral | C3: West | D3: West 1 | E3: Anjli | F3: Usha
A4: Tata Motors | B4: Lateral | C4: West | D4: West 2 | E4: Anjli | F4: Shweta
A5: SKF India | B5: Lateral | C5: North | D5: North | E5: Anjli | F5: Archana
A6: Siemens | B6: Lateral | C6: South | D6: South 1 | E6: Sulabh | F6: Kunal
A7: Pidilite | B7: Lateral | C7: West | D7: West 1 | E7: Anjli | F7: Usha
A8: Vertiv | B8: Lateral | C8: West | D8: West 2 | E8: Anjli | F8: Shweta
A9: Birla Paints | B9: Lateral | C9: West | D9: West 1 | E9: Anjli | F9: Geetu
A10: Ingram Micro | B10: Lateral | C10: West | D10: West 1 | E10: Anjli | F10: Geetu
A11: HPE | B11: Lateral | C11: South | D11: South 1 | E11: Mahak | F11: Mahak
A12: Isuzu | B12: Lateral | C12: South | D12: South 1 | E12: Anjli | F12: Satya
... A79: Kale Logistics | B79: Lateral | C79: West | D79: West 1 | E79: Anjli | F79: Anjli

Sheet Revenue_Actual
A1: =Revenue_Budget!A1 -> FY | B1: =Revenue_Budget!B1 -> Project | C1: =Revenue_Budget!C1 -> Vertical | D1: =Revenue_Budget!D1 -> Region | E1: =Revenue_Budget!E1 -> Sub Region | F1: =Revenue_Budget!F1 -> Region Head | G1: =Revenue_Budget!G1 -> Practice Head | H1: =Revenue_Budget!H1 -> 45748 | ... S1: =Revenue_Budget!S1 -> 46082 | T1: FY'26 Total
A2: FY2025-26 | B2: Honeywell | C2: =VLOOKUP(B2,Mapping!A:B,2,0) -> Lateral | D2: =VLOOKUP(B2,Mapping!A:C,3,0) -> South | E2: =VLOOKUP(B2,Mapping!A:D,4,0) -> South 1 | F2: =VLOOKUP(B2,Mapping!A:E,5,0) -> Bapi | G2: =VLOOKUP(B2,Mapping!A:F,6,0) -> Bapi | H2: 130.6 | I2: 156 | J2: 176.55102 | K2: 152.66667 | L2: 164.71964 | M2: 133.45 | N2: 80 | O2: 125 | P2: 133.5 | Q2: 157.75638 | R2: 152.66749 | S2: 142.41367 | T2: =SUM(H2:S2) -> 1705.3249
A3: FY2025-26 | B3: Pfizer | C3: =VLOOKUP(B3,Mapping!A:B,2,0) -> Lateral | D3: =VLOOKUP(B3,Mapping!A:C,3,0) -> West | E3: =VLOOKUP(B3,Mapping!A:D,4,0) -> West 1 | F3: =VLOOKUP(B3,Mapping!A:E,5,0) -> Anjli | G3: =VLOOKUP(B3,Mapping!A:F,6,0) -> Usha | H3: 5.915 | I3: 6.76 | J3: 7.41 | K3: 6.7 | L3: 9 | M3: 7.3 | N3: 7.7 | O3: 3.5 | P3: 6.08 | Q3: 8.6 | R3: 6.805 | S3: 11.90265 | T3: =SUM(H3:S3) -> 87.67265
A4: FY2025-26 | B4: Tata Motors | C4: =VLOOKUP(B4,Mapping!A:B,2,0) -> Lateral | D4: =VLOOKUP(B4,Mapping!A:C,3,0) -> West | E4: =VLOOKUP(B4,Mapping!A:D,4,0) -> West 2 | F4: =VLOOKUP(B4,Mapping!A:E,5,0) -> Anjli | G4: =VLOOKUP(B4,Mapping!A:F,6,0) -> Shweta | H4: 4 | I4: 1.2 | J4: 0.88 | K4: 0 | L4: 0 | M4: 0 | N4: 0 | O4: 0 | P4: 0 | Q4: 0 | R4: 0 | S4: -9.32999 | T4: =SUM(H4:S4) -> -3.24999
A5: FY2025-26 | B5: SKF India | C5: =VLOOKUP(B5,Mapping!A:B,2,0) -> Lateral | D5: =VLOOKUP(B5,Mapping!A:C,3,0) -> North | E5: =VLOOKUP(B5,Mapping!A:D,4,0) -> North | F5: =VLOOKUP(B5,Mapping!A:E,5,0) -> Anjli | G5: =VLOOKUP(B5,Mapping!A:F,6,0) -> Archana | H5: 20 | I5: 15.11 | J5: 35 | K5: 16 | L5: 19 | M5: 22 | N5: 25 | O5: 35 | P5: 38 | Q5: 17 | R5: 21.7 | S5: 37.65218 | T5: =SUM(H5:S5) -> 301.46218
A6: FY2025-26 | B6: Siemens | C6: =VLOOKUP(B6,Mapping!A:B,2,0) -> Lateral | D6: =VLOOKUP(B6,Mapping!A:C,3,0) -> South | E6: =VLOOKUP(B6,Mapping!A:D,4,0) -> South 1 | F6: =VLOOKUP(B6,Mapping!A:E,5,0) -> Sulabh | G6: =VLOOKUP(B6,Mapping!A:F,6,0) -> Kunal | H6: 14.5 | I6: 20 | J6: 23 | K6: 18.3 | L6: 25 | M6: 25.08965 | N6: 18 | O6: 28 | P6: 22 | Q6: 22.65 | R6: 24 | S6: -4.41285 | T6: =SUM(H6:S6) -> 236.1268
A7: FY2025-26 | B7: Pidilite | C7: =VLOOKUP(B7,Mapping!A:B,2,0) -> Lateral | D7: =VLOOKUP(B7,Mapping!A:C,3,0) -> West | E7: =VLOOKUP(B7,Mapping!A:D,4,0) -> West 1 | F7: =VLOOKUP(B7,Mapping!A:E,5,0) -> Anjli | G7: =VLOOKUP(B7,Mapping!A:F,6,0) -> Usha | H7: 7.57 | I7: 9 | J7: 9 | K7: 9.105 | L7: 7 | M7: 9.965 | N7: 7.5 | O7: 11 | P7: 7.54 | Q7: 3.535 | R7: 3.88 | S7: 8.76 | T7: =SUM(H7:S7) -> 93.855
A8: FY2025-26 | B8: Vertiv | C8: =VLOOKUP(B8,Mapping!A:B,2,0) -> Lateral | D8: =VLOOKUP(B8,Mapping!A:C,3,0) -> West | E8: =VLOOKUP(B8,Mapping!A:D,4,0) -> West 2 | F8: =VLOOKUP(B8,Mapping!A:E,5,0) -> Anjli | G8: =VLOOKUP(B8,Mapping!A:F,6,0) -> Shweta | H8: 8.07 | I8: 3.697 | J8: 2.07799 | K8: 7.76233 | L8: 2.41 | M8: 3.44778 | N8: 2.9 | O8: 2.3 | P8: 5.56233 | Q8: -0.25748 | R8: 5.2736 | S8: 3.75501 | T8: =SUM(H8:S8) -> 46.99856
A9: FY2025-26 | B9: Birla Paints | C9: =VLOOKUP(B9,Mapping!A:B,2,0) -> Lateral | D9: =VLOOKUP(B9,Mapping!A:C,3,0) -> West | E9: =VLOOKUP(B9,Mapping!A:D,4,0) -> West 1 | F9: =VLOOKUP(B9,Mapping!A:E,5,0) -> Anjli | G9: =VLOOKUP(B9,Mapping!A:F,6,0) -> Geetu | H9: 13.05 | I9: 13.0725 | J9: 9.5 | K9: 7.44 | L9: 11.41 | M9: 14.88 | N9: 12.5 | O9: 9.96725 | P9: 22.19 | Q9: 14.387 | R9: 11.25 | S9: 12.29125 | T9: =SUM(H9:S9) -> 151.938
A10: FY2025-26 | B10: Ingram Micro | C10: =VLOOKUP(B10,Mapping!A:B,2,0) -> Lateral | D10: =VLOOKUP(B10,Mapping!A:C,3,0) -> West | E10: =VLOOKUP(B10,Mapping!A:D,4,0) -> West 1 | F10: =VLOOKUP(B10,Mapping!A:E,5,0) -> Anjli | G10: =VLOOKUP(B10,Mapping!A:F,6,0) -> Geetu | H10: 0.915 | I10: 1 | J10: 4.2 | K10: 0.645 | L10: 1.25 | M10: 1.072 | N10: 0.004 | O10: 1 | P10: 0.6237 | Q10: -2.2527 | R10: 0 | S10: 0 | T10: =SUM(H10:S10) -> 8.457
A11: FY2025-26 | B11: HPE | C11: =VLOOKUP(B11,Mapping!A:B,2,0) -> Lateral | D11: =VLOOKUP(B11,Mapping!A:C,3,0) -> South | E11: =VLOOKUP(B11,Mapping!A:D,4,0) -> South 1 | F11: =VLOOKUP(B11,Mapping!A:E,5,0) -> Mahak | G11: =VLOOKUP(B11,Mapping!A:F,6,0) -> Mahak | H11: 79 | I11: 89 | J11: 91.4 | K11: 70.07864 | L11: 101.00179 | M11: 176.3 | N11: 92 | O11: 145 | P11: 186 | Q11: 147 | R11: 224 | S11: 162.98824 | T11: =SUM(H11:S11) -> 1563.7687
A12: FY2025-26 | B12: Isuzu | C12: =VLOOKUP(B12,Mapping!A:B,2,0) -> Lateral | D12: =VLOOKUP(B12,Mapping!A:C,3,0) -> South | E12: =VLOOKUP(B12,Mapping!A:D,4,0) -> South 1 | F12: =VLOOKUP(B12,Mapping!A:E,5,0) -> Anjli | G12: =VLOOKUP(B12,Mapping!A:F,6,0) -> Satya | H12: 6.63939 | I12: 9.06 | J12: 12.1525 | K12: 6.92168 | L12: 8 | M12: 8.7 | N12: 5.096 | O12: 3.9482 | P12: 12.644 | Q12: 5.78411 | R12: -6.89698 | S12: 4.874 | T12: =SUM(H12:S12) -> 76.9229
A13: FY2025-26 | B13: Mahindra Holidays | C13: =VLOOKUP(B13,Mapping!A:B,2,0) -> Lateral | D13: =VLOOKUP(B13,Mapping!A:C,3,0) -> West | E13: =VLOOKUP(B13,Mapping!A:D,4,0) -> West 1 | F13: =VLOOKUP(B13,Mapping!A:E,5,0) -> Anjli | G13: =VLOOKUP(B13,Mapping!A:F,6,0) -> Geetu | H13: 4.91 | I13: 5.768 | J13: 2.34 | K13: 1.18 | L13: 3.8 | M13: 5.641 | N13: 4.013 | O13: 4.46 | P13: 3.7 | Q13: 2.31 | R13: 6.97 | S13: 3.432 | T13: =SUM(H13:S13) -> 48.524
... A76: FY2025-26 | B76: CG Power | C76: =VLOOKUP(B76,Mapping!A:B,2,0) -> Lateral | D76: =VLOOKUP(B76,Mapping!A:C,3,0) -> West | E76: =VLOOKUP(B76,Mapping!A:D,4,0) -> West 1 | F76: =VLOOKUP(B76,Mapping!A:E,5,0) -> Anjli | G76: =VLOOKUP(B76,Mapping!A:F,6,0) -> Anjli | H76: 0 | I76: 0 | J76: 0 | K76: 0 | L76: 0 | M76: 0 | N76: 0 | O76: 0 | P76: 0 | Q76: 0 | R76: 0.434 | S76: 11.096 | T76: =SUM(H76:S76) -> 11.53
A77: FY2025-26 | B77: Triveni | C77: Exclusive | D77: Exclusive | E77: Exclusive | F77: Amit Jain | G77: Naved | H77: 0 | I77: 0 | J77: 0 | K77: 0 | L77: 0 | M77: 0 | N77: 0 | O77: 0 | P77: 0 | Q77: 2.511 | R77: -0.07331 | S77: 0 | T77: =SUM(H77:S77) -> 2.43769
A78: FY2025-26 | B78: Banswara | C78: Exclusive | D78: Exclusive | E78: Exclusive | F78: Amit Jain | G78: Naved | H78: 0 | I78: 0 | J78: 0 | K78: 0 | L78: 0 | M78: 0 | N78: 0 | O78: 0 | P78: 0 | Q78: 0 | R78: 0 | S78: 0 | T78: =SUM(H78:S78) -> 0
A79: FY2025-26 | B79: Gala Precision | C79: Exclusive | D79: Exclusive | E79: Exclusive | F79: Amit Jain | G79: Naved | H79: 0 | I79: 0 | J79: 0 | K79: 0 | L79: 0 | M79: 0 | N79: 0 | O79: 0 | P79: 0 | Q79: 0 | R79: 0 | S79: 0 | T79: =SUM(H79:S79) -> 0
A80: FY2025-26 | B80: ITW India | C80: Exclusive | D80: Exclusive | E80: Exclusive | F80: Amit Jain | G80: Naved | H80: 0 | I80: 0 | J80: 0 | K80: 0 | L80: 0 | M80: 0 | N80: 0 | O80: 0 | P80: 0 | Q80: 0 | R80: 0 | S80: 0.6392 | T80: =SUM(H80:S80) -> 0.6392
A81: FY2025-26 | B81: Primetals Technologies | C81: Exclusive | D81: Exclusive | E81: Exclusive | F81: Amit Jain | G81: Naved | H81: 0 | I81: 0 | J81: 0 | K81: 0 | L81: 0 | M81: 0 | N81: 0 | O81: 0 | P81: 0 | Q81: 0 | R81: 0 | S81: 0 | T81: =SUM(H81:S81) -> 0
A82: FY2025-26 | B82: Arvind Smartspaces | C82: Exclusive | D82: Exclusive | E82: Exclusive | F82: Amit Jain | G82: Naved | H82: 0 | I82: 0 | J82: 0 | K82: 0 | L82: 0 | M82: 0 | N82: 0 | O82: 0 | P82: 0 | Q82: 0.6 | R82: 0 | S82: 0.9375 | T82: =SUM(H82:S82) -> 1.5375
A83: FY2025-26 | B83: Autofit | C83: Exclusive | D83: Exclusive | E83: Exclusive | F83: Amit Jain | G83: Naved | H83: 0 | I83: 0 | J83: 0 | K83: 0 | L83: 0 | M83: 0 | N83: 0 | O83: 0 | P83: 0 | Q83: 0 | R83: 0 | S83: 0 | T83: =SUM(H83:S83) -> 0
A84: FY2025-26 | B84: Carplai | C84: Exclusive | D84: Exclusive | E84: Exclusive | F84: Amit Jain | G84: Naved | H84: 0 | I84: 0 | J84: 0 | K84: 0 | L84: 0 | M84: 0 | N84: 0 | O84: 0 | P84: 0 | Q84: 1.48541 | R84: 0 | S84: 0 | T84: =SUM(H84:S84) -> 1.48541
A85: FY2025-26 | B85: Middle East | C85: Exclusive | D85: Exclusive | E85: Exclusive | F85: Amit Jain | G85: Naved | H85: 0 | I85: 0 | J85: 0 | K85: 0 | L85: 0 | M85: 0 | N85: 0 | O85: 0 | P85: 0 | Q85: 4.19832 | R85: 0 | S85: -1.04958 | T85: =SUM(H85:S85) -> 3.14874
A86: FY2025-26 | B86: L&T Energy | C86: Lateral | D86: West | E86: West 1 | F86: Anjli | G86: Anjli | H86: 0 | I86: 0 | J86: 0 | K86: 0 | L86: 0 | M86: 0 | N86: 0 | O86: 0 | P86: 0 | Q86: 0 | R86: 0 | S86: -3.51928 | T86: =SUM(H86:S86) -> -3.51928
A87: FY2025-26 | B87: Ace Designers | C87: Exclusive | D87: Exclusive | E87: Exclusive | F87: Amit Jain | G87: Naved | H87: 0 | I87: 0 | J87: 0 | K87: 0 | L87: 0 | M87: 0 | N87: 0 | O87: 0 | P87: 0 | Q87: 0 | R87: 0 | S87: 1.23285 | T87: =SUM(H87:S87) -> 1.23285
A88: FY2025-26 | B88: Century Link

Sheet CM Actual
A1: =Revenue_Budget!A1 -> FY | B1: =Revenue_Budget!B1 -> Project | C1: =Revenue_Budget!C1 -> Vertical | D1: =Revenue_Budget!D1 -> Region | E1: =Revenue_Budget!E1 -> Sub Region | F1: =Revenue_Budget!F1 -> Region Head | G1: =Revenue_Budget!G1 -> Practice Head | H1: =Revenue_Budget!H1 -> 45748 | ... S1: =Revenue_Budget!S1 -> 46082 | T1: Total
A2: FY2025-26 | B2: Honeywell | C2: =VLOOKUP(B2,Mapping!A:B,2,0) -> Lateral | D2: =VLOOKUP(B2,Mapping!A:C,3,0) -> South | E2: =VLOOKUP(B2,Mapping!A:D,4,0) -> South 1 | F2: =VLOOKUP(B2,Mapping!A:E,5,0) -> Bapi | G2: =VLOOKUP(B2,Mapping!A:F,6,0) -> Bapi | H2: 66.781524 | I2: 92.612259 | J2: 111.51055 | K2: 87.545449 | L2: 98.708907 | M2: 65.45902 | N2: 12.77867 | O2: 54.836437 | P2: 68.605459 | Q2: 93.363158 | R2: 92.839734 | S2: 72.291474 | T2: =SUM(H2:S2) -> 917.33264
A3: FY2025-26 | B3: Pfizer | C3: =VLOOKUP(B3,Mapping!A:B,2,0) -> Lateral | D3: =VLOOKUP(B3,Mapping!A:C,3,0) -> West | E3: =VLOOKUP(B3,Mapping!A:D,4,0) -> West 1 | F3: =VLOOKUP(B3,Mapping!A:E,5,0) -> Anjli | G3: =VLOOKUP(B3,Mapping!A:F,6,0) -> Usha | H3: -0.34990617 | I3: -0.82397239 | J3: 1.9315226 | K3: 0.78358536 | L3: 3.3181818 | M3: 1.9148444 | N3: 2.2445784 | O3: -1.2490711 | P3: 1.5383782 | Q3: 4.0312575 | R3: 2.4028778 | S3: 7.6305569 | T3: =SUM(H3:S3) -> 23.372833
A4: FY2025-26 | B4: Tata Motors | C4: =VLOOKUP(B4,Mapping!A:B,2,0) -> Lateral | D4: =VLOOKUP(B4,Mapping!A:C,3,0) -> West | E4: =VLOOKUP(B4,Mapping!A:D,4,0) -> West 2 | F4: =VLOOKUP(B4,Mapping!A:E,5,0) -> Anjli | G4: =VLOOKUP(B4,Mapping!A:F,6,0) -> Shweta | H4: 3.864208 | I4: 0.16504838 | J4: 0.10993156 | K4: -0.37001472 | L4: -0.08169 | M4: -0.0873 | N4: 0 | O4: 0 | P4: =-2076/100000 -> -0.02076 | Q4: 0 | R4: -0.02068 | S4: -9.31674 | T4: =SUM(H4:S4) -> -5.7579968
A5: FY2025-26 | B5: SKF India | C5: =VLOOKUP(B5,Mapping!A:B,2,0) -> Lateral | D5: =VLOOKUP(B5,Mapping!A:C,3,0) -> North | E5: =VLOOKUP(B5,Mapping!A:D,4,0) -> North | F5: =VLOOKUP(B5,Mapping!A:E,5,0) -> Anjli | G5: =VLOOKUP(B5,Mapping!A:F,6,0) -> Archana | H5: 4.8011796 | I5: -2.9507205 | J5: 17.987564 | K5: -0.36737824 | L5: 2.1804304 | M5: 4.3734074 | N5: 8.1191309 | O5: 17.791559 | P5: 21.443097 | Q5: -0.22095092 | R5: 8.3810987 | S5: 18.160515 | T5: =SUM(H5:S5) -> 99.698932
A6: FY2025-26 | B6: Siemens | C6: =VLOOKUP(B6,Mapping!A:B,2,0) -> Lateral | D6: =VLOOKUP(B6,Mapping!A:C,3,0) -> South | E6: =VLOOKUP(B6,Mapping!A:D,4,0) -> South 1 | F6: =VLOOKUP(B6,Mapping!A:E,5,0) -> Sulabh | G6: =VLOOKUP(B6,Mapping!A:F,6,0) -> Kunal | H6: 1.2827816 | I6: 7.711711 | J6: 9.5124114 | K6: 5.7678338 | L6: 12.142506 | M6: 12.181757 | N6: 4.8417416 | O6: 15.361321 | P6: 8.4984083 | Q6: 9.3283532 | R6: 9.0789552 | S6: -19.595804 | T6: =SUM(H6:S6) -> 76.111976
A7: FY2025-26 | B7: Pidilite | C7: =VLOOKUP(B7,Mapping!A:B,2,0) -> Lateral | D7: =VLOOKUP(B7,Mapping!A:C,3,0) -> West | E7: =VLOOKUP(B7,Mapping!A:D,4,0) -> West 1 | F7: =VLOOKUP(B7,Mapping!A:E,5,0) -> Anjli | G7: =VLOOKUP(B7,Mapping!A:F,6,0) -> Usha | H7: 0.28052493 | I7: 1.7407947 | J7: 1.675848 | K7: 1.9689589 | L7: -0.60443749 | M7: 3.2641139 | N7: 0.75114756 | O7: 2.4861031 | P7: 0.73708264 | Q7: -5.0451947 | R7: -7.208619 | S7: -2.0592078 | T7: =SUM(H7:S7) -> -2.0128853
A8: FY2025-26 | B8: Vertiv | C8: =VLOOKUP(B8,Mapping!A:B,2,0) -> Lateral | D8: =VLOOKUP(B8,Mapping!A:C,3,0) -> West | E8: =VLOOKUP(B8,Mapping!A:D,4,0) -> West 2 | F8: =VLOOKUP(B8,Mapping!A:E,5,0) -> Anjli | G8: =VLOOKUP(B8,Mapping!A:F,6,0) -> Shweta | H8: 4.8069279 | I8: -0.60393373 | J8: -1.2315266 | K8: 4.5278036 | L8: -0.66508048 | M8: 0.86162832 | N8: 0.26829475 | O8: -0.48609584 | P8: 3.0493092 | Q8: -3.0291951 | R8: 2.7182277 | S8: 0.96288921 | T8: =SUM(H8:S8) -> 11.179249
A9: FY2025-26 | B9: Birla Paints | C9: =VLOOKUP(B9,Mapping!A:B,2,0) -> Lateral | D9: =VLOOKUP(B9,Mapping!A:C,3,0) -> West | E9: =VLOOKUP(B9,Mapping!A:D,4,0) -> West 1 | F9: =VLOOKUP(B9,Mapping!A:E,5,0) -> Anjli | G9: =VLOOKUP(B9,Mapping!A:F,6,0) -> Geetu | H9: 3.3405557 | I9: 2.846487 | J9: 0.24110742 | K9: -0.84415728 | L9: 3.6194994 | M9: 5.5846808 | N9: 1.4683891 | O9: -2.0977962 | P9: 11.223469 | Q9: 3.3937426 | R9: 0.82208629 | S9: 2.4700251 | T9: =SUM(H9:S9) -> 32.068089
A10: FY2025-26 | B10: Ingram Micro | C10: =VLOOKUP(B10,Mapping!A:B,2,0) -> Lateral | D10: =VLOOKUP(B10,Mapping!A:C,3,0) -> West | E10: =VLOOKUP(B10,Mapping!A:D,4,0) -> West 1 | F10: =VLOOKUP(B10,Mapping!A:E,5,0) -> Anjli | G10: =VLOOKUP(B10,Mapping!A:F,6,0) -> Geetu | H10: -2.3281961 | I10: -1.9815798 | J10: 1.093341 | K10: -1.9933637 | L10: -1.4095212 | M10: -0.96433278 | N10: -2.0682828 | O10: -0.80642703 | P10: -0.5602706 | Q10: -2.3776405 | R10: -0.00034 | S10: 0 | T10: =SUM(H10:S10) -> -13.396613
A11: FY2025-26 | B11: HPE | C11: =VLOOKUP(B11,Mapping!A:B,2,0) -> Lateral | D11: =VLOOKUP(B11,Mapping!A:C,3,0) -> South | E11: =VLOOKUP(B11,Mapping!A:D,4,0) -> South 1 | F11: =VLOOKUP(B11,Mapping!A:E,5,0) -> Mahak | G11: =VLOOKUP(B11,Mapping!A:F,6,0) -> Mahak | H11: 10.804419 | I11: 29.301528 | J11: 27.809086 | K11: 8.6762385 | L11: 37.68729 | M11: 112.40431 | N11: 27.153346 | O11: 77.889477 | P11: 121.02262 | Q11: 82.342684 | R11: 125.77431 | S11: 14.631461 | T11: =SUM(H11:S11) -> 675.49676
A12: FY2025-26 | B12: Isuzu | C12: =VLOOKUP(B12,Mapping!A:B,2,0) -> Lateral | D12: =VLOOKUP(B12,Mapping!A:C,3,0) -> South | E12: =VLOOKUP(B12,Mapping!A:D,4,0) -> South 1 | F12: =VLOOKUP(B12,Mapping!A:E,5,0) -> Anjli | G12: =VLOOKUP(B12,Mapping!A:F,6,0) -> Satya | H12: 1.6087971 | I12: 3.7439232 | J12: 7.0142933 | K12: 2.085113 | L12: 3.6476157 | M12: 4.3534148 | N12: 0.65351823 | O12: -0.57650605 | P12: 8.1205593 | Q12: 1.0908186 | R12: -11.414293 | S12: 1.1014828 | T12: =SUM(H12:S12) -> 21.428737
A13: FY2025-26 | B13: Mahindra Holidays | C13: =VLOOKUP(B13,Mapping!A:B,2,0) -> Lateral | D13: =VLOOKUP(B13,Mapping!A:C,3,0) -> West | E13: =VLOOKUP(B13,Mapping!A:D,4,0) -> West 1 | F13: =VLOOKUP(B13,Mapping!A:E,5,0) -> Anjli | G13: =VLOOKUP(B13,Mapping!A:F,6,0) -> Geetu | H13: -2.1556563 | I13: -2.2067243 | J13: -5.6026531 | K13: -5.4999534 | L13: -3.758601 | M13: -2.2291509 | N13: -4.1525232 | O13: -3.5005022 | P13: -2.9584699 | Q13: -4.0265644 | R13: 1.6417339 | S13: -2.4946111 | T13: =SUM(H13:S13) -> -36.943676
A14: FY2025-26 | B14: BITS | C14: =VLOOKUP(B14,Mapping!A:B,2,0) -> Lateral | D14: =VLOOKUP(B14,Mapping!A:C,3,0) -> South | E14: =VLOOKUP(B14,Mapping!A:D,4,0) -> South 2 | F14: =VLOOKUP(B14,Mapping!A:E,5,0) -> Sulabh | G14: =VLOOKUP(B14,Mapping!A:F,6,0) -> Krishna | H14: 1.2763879 | I14: 1.4129094 | J14: 1.7122049 | K14: 3.5363268 | L14: 1.3567362 | M14: 1.4831761 | N14: 1.1955337 | O14: 1.1029159 | P14: 1.1226288 | Q14: 0.72496808 | R14: 8.7972261 | S14: 6.330042 | T14: =SUM(H14:S14) -> 30.051056
A15: FY2025-26 | B15: M&M | C15: =VLOOKUP(B15,Mapping!A:B,2,0) -> Lateral | D15: =VLOOKUP(B15,Mapping!A:C,3,0) -> West | E15: =VLOOKUP(B15,Mapping!A:D,4,0) -> West 1 | F15: =VLOOKUP(B15,Mapping!A:E,5,0) -> Anjli | G15: =VLOOKUP(B15,Mapping!A:F,6,0) -> Dhriti | H15: 28.810128 | I15: 32.29357 | J15: 55.444253 | K15: 41.654506 | L15: 27.557864 | M15: 41.696116 | N15: 12.402396 | O15: 72.645574 | P15: 134.12152 | Q15: 78.375359 | R15: 41.841916 | S15: 79.149468 | T15: =SUM(H15:S15) -> 645.99267
A16: FY2025-26 | B16: P&G | C16: =VLOOKUP(B16,Mapping!A:B,2,0) -> Lateral | D16: =VLOOKUP(B16,Mapping!A:C,3,0) -> South | E16: =VLOOKUP(B16,Mapping!A:D,4,0) -> South 2 | F16: =VLOOKUP(B16,Mapping!A:E,5,0) -> Sulabh | G16: =VLOOKUP(B16,Mapping!A:F,6,0) -> Krishna | H16: 0 | I16: 0 | J16: 0 | K16: 0 | L16: 0 | M16: 0 | N16: 0 | O16: 0 | P16: 0 | Q16: 0 | R16: 0 | S16: 0 | T16: =SUM(H16:S16) -> 0
... A76: FY2025-26 | B76: CG Power | C76: =VLOOKUP(B76,Mapping!A:B,2,0) -> Lateral | D76: =VLOOKUP(B76,Mapping!A:C,3,0) -> West | E76: =VLOOKUP(B76,Mapping!A:D,4,0) -> West 1 | F76: =VLOOKUP(B76,Mapping!A:E,5,0) -> Anjli | G76: =VLOOKUP(B76,Mapping!A:F,6,0) -> Anjli | H76: 0 | I76: 0 | J76: 0 | K76: 0 | L76: 0 | M76: 0 | N76: 0 | O76: 0 | P76: 0 | Q76: 0 | R76: -0.98954643 | S76: 2.1067936 | T76: =SUM(H76:S76) -> 1.1172471
A77: FY2025-26 | B77: Triveni | C77: Exclusive | D77: Exclusive | E77: Exclusive | F77: Amit Jain | G77: Naved | P77: -1.6896975 | Q77: 0.32909836 | R77: -2.5073206 | S77: -2.7989859 | T77: =SUM(H77:S77) -> -6.6669056
A78: FY2025-26 | B78: Banswara | C78: Exclusive | D78: Exclusive | E78: Exclusive | F78: Amit Jain | G78: Naved | P78: 0 | Q78: 0 | R78: 0 | S78: 0 | T78: =SUM(H78:S78) -> 0
A79: FY2025-26 | B79: Gala Precision | C79: Exclusive | D79: Exclusive | E79: Exclusive | F79: Amit Jain | G79: Naved | P79: 0 | Q79: 0 | R79: 0 | S79: 0 | T79: =SUM(H79:S79) -> 0
A80: FY2025-26 | B80: ITW India | C80: Exclusive | D80: Exclusive | E80: Exclusive | F80: Amit Jain | G80: Naved | P80: 0 | Q80: 0 | R80: 0 | S80: 0.6392 | T80: =SUM(H80:S80) -> 0.6392
A81: FY2025-26 | B81: Primetals Technologies | C81: Exclusive | D81: Exclusive | E81: Exclusive | F81: Amit Jain | G81: Naved | P81: 0 | Q81: 0 | R81: 0 | S81: 0 | T81: =SUM(H81:S81) -> 0
A82: FY2025-26 | B82: Arvind Smartspaces | C82: Exclusive | D82: Exclusive | E82: Exclusive | F82: Amit Jain | G82: Naved | P82: 0 | Q82: 0.6 | R82: 0 | S82: 0.9375 | T82: =SUM(H82:S82) -> 1.5375
A83: FY2025-26 | B83: Autofit | C83: Exclusive | D83: Exclusive | E83: Exclusive | F83: Amit Jain | G83: Naved | P83: 0 | Q83: 0 | R83: 0 | S83: 0 | T83: =SUM(H83:S83) -> 0
A84: FY2025-26 | B84: Carplai | C84: Exclusive | D84: Exclusive | E84: Exclusive | F84: Amit Jain | G84: Naved | P84: 0 | Q84: 1.48541 | R84: 0 | S84: 0 | T84: =SUM(H84:S84) -> 1.48541
A85: FY2025-26 | B85: Middle East | C85: Exclusive | D85: Exclusive | E85: Exclusive | F85: Amit Jain | G85: Naved | P85: -4.3069737 | Q85: 0.056569072 | R85: -2.9769183 | S85: -3.6389251 | T85: =SUM(H85:S85) -> -10.866248
A86: FY2025-26 | B86: L&T Energy | C86: Lateral | D86: West | E86: West 1 | F86: Anjli | G86: Anjli | P86: 0 | Q86: 0 | R86: 0 | S86: -3.51928 | T86: =SUM(H86:S86) -> -3.51928
A87: FY2025-26 | B87: Ace Designers | C87: Exclusive | D87: Exclusive | E87: Exclusive | F87: Amit Jain | G87: Naved | P87: 0 | Q87: 0 | R87: 0 | S87: 1.23285 | T87: =SUM(H87:S87) -> 1.23285

Sheet Rev_Productivity_Actual
A1: =Revenue_Budget!A1 -> FY | B1: =Revenue_Budget!B1 -> Project | C1: =Revenue_Budget!C1 -> Vertical | D1: =Revenue_Budget!D1 -> Region | E1: =Revenue_Budget!E1 -> Sub Region | F1: =Revenue_Budget!F1 -> Region Head | G1: =Revenue_Budget!G1 -> Practice Head | H1: =Revenue_Budget!H1 -> 45748 | ... S1: =Revenue_Budget!S1 -> 46082
A2: FY2025-26 | B2: Honeywell | C2: =VLOOKUP(B2,Mapping!A:B,2,0) -> Lateral | D2: =VLOOKUP(B2,Mapping!A:C,3,0) -> South | E2: =VLOOKUP(B2,Mapping!A:D,4,0) -> South 1 | F2: =VLOOKUP(B2,Mapping!A:E,5,0) -> Bapi | G2: =VLOOKUP(B2,Mapping!A:F,6,0) -> Bapi | H2: 2.0185471 | I2: 2.2941176 | J2: 2.7672574 | K2: 2.5444445 | L2: 2.7181459 | M2: 2.2057851 | N2: 1.322314 | O2: 2.0661157 | P2: 2.3017241 | Q2: 1.0914105
A3: FY2025-26 | B3: Pfizer | C3: =VLOOKUP(B3,Mapping!A:B,2,0) -> Lateral | D3: =VLOOKUP(B3,Mapping!A:C,3,0) -> West | E3: =VLOOKUP(B3,Mapping!A:D,4,0) -> West 1 | F3: =VLOOKUP(B3,Mapping!A:E,5,0) -> Anjli | G3: =VLOOKUP(B3,Mapping!A:F,6,0) -> Usha | H3: 0.93888889 | I3: 0.95886525 | J3: 1.1761905 | K3: 1.0806452 | L3: 1.7307692 | M3: 1.4038462 | N3: 1.4807692 | O3: 0.77777778 | P3: 1.3511111 | Q3: 1.0152761
A4: FY2025-26 | B4: Tata Motors | C4: =VLOOKUP(B4,Mapping!A:B,2,0) -> Lateral | D4: =VLOOKUP(B4,Mapping!A:C,3,0) -> West | E4: =VLOOKUP(B4,Mapping!A:D,4,0) -> West 2 | F4: =VLOOKUP(B4,Mapping!A:E,5,0) -> Anjli | G4: =VLOOKUP(B4,Mapping!A:F,6,0) -> Shweta | H4: 0 | I4: 0.72727273 | J4: 0.51764706 | K4: 0 | L4: 0 | M4: 0 | N4: 0 | O4: 0 | P4: 0 | Q4: 0
A5: FY2025-26 | B5: SKF India | C5: =VLOOKUP(B5,Mapping!A:B,2,0) -> Lateral | D5: =VLOOKUP(B5,Mapping!A:C,3,0) -> North | E5: =VLOOKUP(B5,Mapping!A:D,4,0) -> North | F5: =VLOOKUP(B5,Mapping!A:E,5,0) -> Anjli | G5: =VLOOKUP(B5,Mapping!A:F,6,0) -> Archana | H5: 1.4285714 | I5: 0.9875817 | J5: 2.2727273 | K5: 1.1347518 | L5: 1.3475177 | M5: 1.4814815 | N5: 1.6556291 | O5: 2.173913 | P5: 2.5165563 | Q5: 1.0565001
A6: FY2025-26 | B6: Siemens | C6: =VLOOKUP(B6,Mapping!A:B,2,0) -> Lateral | D6: =VLOOKUP(B6,Mapping!A:C,3,0) -> South | E6: =VLOOKUP(B6,Mapping!A:D,4,0) -> South 1 | F6: =VLOOKUP(B6,Mapping!A:E,5,0) -> Sulabh | G6: =VLOOKUP(B6,Mapping!A:F,6,0) -> Kunal | H6: 1.0431655 | I6: 1.5503876 | J6: 1.5862069 | K6: 1.464 | L6: 2 | M6: 2.007172 | N6: 1.44 | O6: 2.24 | P6: 1.76 | Q6: 1.0657317
A7: FY2025-26 | B7: Pidilite | C7: =VLOOKUP(B7,Mapping!A:B,2,0) -> Lateral | D7: =VLOOKUP(B7,Mapping!A:C,3,0) -> West | E7: =VLOOKUP(B7,Mapping!A:D,4,0) -> West 1 | F7: =VLOOKUP(B7,Mapping!A:E,5,0) -> Anjli | G7: =VLOOKUP(B7,Mapping!A:F,6,0) -> Usha | H7: 0.757 | I7: 1.0227273 | J7: 0.91836735 | K7: 1.1824675 | L7: 0.8045977 | M7: 1.2941558 | N7: 0.70093458 | O7: 1.1 | P7: 0.87674419 | Q7: 0.70329465
A8: FY2025-26 | B8: Vertiv | C8: =VLOOKUP(B8,Mapping!A:B,2,0) -> Lateral | D8: =VLOOKUP(B8,Mapping!A:C,3,0) -> West | E8: =VLOOKUP(B8,Mapping!A:D,4,0) -> West 2 | F8: =VLOOKUP(B8,Mapping!A:E,5,0) -> Anjli | G8: =VLOOKUP(B8,Mapping!A:F,6,0) -> Shweta | H8: 1.7543478 | I8: 0.90170732 | J8: 0.57721944 | K8: 2.5039774 | L8: 0.77741935 | M8: 1.6418 | N8: 1.3809524 | O8: 1.0952381 | P8: 2.6487286 | Q8: 1.3198644
A9: FY2025-26 | B9: Birla Paints | C9: =VLOOKUP(B9,Mapping!A:B,2,0) -> Lateral | D9: =VLOOKUP(B9,Mapping!A:C,3,0) -> West | E9: =VLOOKUP(B9,Mapping!A:D,4,0) -> West 1 | F9: =VLOOKUP(B9,Mapping!A:E,5,0) -> Anjli | G9: =VLOOKUP(B9,Mapping!A:F,6,0) -> Geetu | H9: 1.2794118 | I9: 1.287931 | J9: 0.93596059 | K9: 0.66726457 | L9: 1.1823834 | M9: 1.3971831 | N9: 1.1737089 | O9: 0.89392377 | P9: 1.912931 | Q9: 0.94362724
A10: FY2025-26 | B10: Ingram Micro | C10: =VLOOKUP(B10,Mapping!A:B,2,0) -> Lateral | D10: =VLOOKUP(B10,Mapping!A:C,3,0) -> West | E10: =VLOOKUP(B10,Mapping!A:D,4,0) -> West 1 | F10: =VLOOKUP(B10,Mapping!A:E,5,0) -> Anjli | G10: =VLOOKUP(B10,Mapping!A:F,6,0) -> Geetu | H10: 0.24078947 | I10: 0.26315789 | J10: 1.1052632 | K10: 0.23888889 | L10: 0.46296296 | M10: 0.63058824 | N10: 0.0023529412 | O10: 0.66666667 | P10: 0.4158 | Q10: 0.12494055
A11: FY2025-26 | B11: HPE | C11: =VLOOKUP(B11,Mapping!A:B,2,0) -> Lateral | D11: =VLOOKUP(B11,Mapping!A:C,3,0) -> South | E11: =VLOOKUP(B11,Mapping!A:D,4,0) -> South 1 | F11: =VLOOKUP(B11,Mapping!A:E,5,0) -> Mahak | G11: =VLOOKUP(B11,Mapping!A:F,6,0) -> Mahak | H11: 1.5192308 | I11: 1.8163265 | J11: 1.8653061 | K11: 1.4449204 | L11: 2.2198196 | M11: 3.8747253 | N11: 2.021978 | O11: 3.1868132 | P11: 4.0879121 | Q11: 1.3470274
A12: FY2025-26 | B12: Isuzu | C12: =VLOOKUP(B12,Mapping!A:B,2,0) -> Lateral | D12: =VLOOKUP(B12,Mapping!A:C,3,0) -> South | E12: =VLOOKUP(B12,Mapping!A:D,4,0) -> South 1 | F12: =VLOOKUP(B12,Mapping!A:E,5,0) -> Anjli | G12: =VLOOKUP(B12,Mapping!A:F,6,0) -> Satya | H12: 1.5298134 | I12: 2.0907692 | J12: 2.8044231 | K12: 1.5973108 | L12: 2.4 | M12: 2.6047904 | N12: 1.5257485 | O12: 1.1820958 | P12: 3.7856287 | Q12: 1.4051771
A13: FY2025-26 | B13: Mahindra Holidays | C13: =VLOOKUP(B13,Mapping!A:B,2,0) -> Lateral | D13: =VLOOKUP(B13,Mapping!A:C,3,0) -> West | E13: =VLOOKUP(B13,Mapping!A:D,4,0) -> West 1 | F13: =VLOOKUP(B13,Mapping!A:E,5,0) -> Anjli | G13: =VLOOKUP(B13,Mapping!A:F,6,0) -> Geetu | H13: 0.47669903 | I13: 0.56273171 | J13: 0.208 | K13: 0.14478528 | L13: 0.41530055 | M13: 0.61650273 | N13: 0.49239264 | O13: 0.54723926 | P13: 0.40217391 | Q13: 0.79207055
... A23: FY2025-26 | B23: Jindal Stainless | C23: =VLOOKUP(B23,Mapping!A:B,2,0) -> Lateral | D23: =VLOOKUP(B23,Mapping!A:C,3,0) -> North | E23: =VLOOKUP(B23,Mapping!A:D,4,0) -> North | F23: =VLOOKUP(B23,Mapping!A:E,5,0) -> Anjli | G23: =VLOOKUP(B23,Mapping!A:F,6,0) -> Archana | H23: 1.4088803 | I23: 3.2647059 | J23: 1.745098 | K23: 2.5882353 | L23: 2.1140328 | M23: 1.3 | N23: 1.8225806 | O23: 5.3333333 | P23: 1.0149254 | Q23: 1.0020184
A24: FY2025-26 | B24: Nomiso | C24: =VLOOKUP(B24,Mapping!A:B,2,0) -> Lateral | D24: =VLOOKUP(B24,Mapping!A:C,3,0) -> South | E24: =VLOOKUP(B24,Mapping!A:D,4,0) -> South 2 | F24: =VLOOKUP(B24,Mapping!A:E,5,0) -> Sulabh | G24: =VLOOKUP(B24,Mapping!A:F,6,0) -> Krishna | H24: - | I24: - | J24: - | K24: - | L24: - | M24: - | N24: - | O24: - | P24: - | Q24: -
A25: FY2025-26 | B25: Schaeffler | C25: =VLOOKUP(B25,Mapping!A:B,2,0) -> Lateral | D25: =VLOOKUP(B25,Mapping!A:C,3,0) -> West | E25: =VLOOKUP(B25,Mapping!A:D,4,0) -> West 2 | F25: =VLOOKUP(B25,Mapping!A:E,5,0) -> Anjli | G25: =VLOOKUP(B25,Mapping!A:F,6,0) -> Shweta | H25: 1.0596026 | I25: 0.66875 | J25: 1.7875 | K25: 1.3018868 | L25: 1.0784314 | M25: 1.6393443 | N25: 1.7803279 | O25: 0.78431373 | P25: 1.5686275 | Q25: 0.98526996
A26: FY2025-26 | B26: Royal Enfield | C26: =VLOOKUP(B26,Mapping!A:B,2,0) -> Lateral | D26: =VLOOKUP(B26,Mapping!A:C,3,0) -> South | E26: =VLOOKUP(B26,Mapping!A:D,4,0) -> South 2 | F26: =VLOOKUP(B26,Mapping!A:E,5,0) -> Sulabh | G26: =VLOOKUP(B26,Mapping!A:F,6,0) -> Krishna | H26: 0.60737705 | I26: 0.83751569 | J26: 2.8649294 | K26: 0.98333333 | L26: 3.3333333 | M26: 2.5446429 | N26: 1.2227441 | O26: 2.3010526 | P26: 1.4076923 | Q26: 1.2656139
A27: FY2025-26 | B27: SBI Card | C27: =VLOOKUP(B27,Mapping!A:B,2,0) -> Lateral | D27: =VLOOKUP(B27,Mapping!A:C,3,0) -> North | E27: =VLOOKUP(B27,Mapping!A:D,4,0) -> North | F27: =VLOOKUP(B27,Mapping!A:E,5,0) -> Anjli | G27: =VLOOKUP(B27,Mapping!A:F,6,0) -> Archana | H27: 0.69230769 | I27: 0.55111111 | J27: 0.94890511 | K27: 1.048951 | L27: 0.97902098 | M27: 0.92896175 | N27: 0.65543443 | O27: 0.80691643 | P27: 1.1331445 | Q27: 0.78745418
A28: FY2025-26 | B28: Hyundai Motor | C28: =VLOOKUP(B28,Mapping!A:B,2,0) -> Lateral | D28: =VLOOKUP(B28,Mapping!A:C,3,0) -> West | E28: =VLOOKUP(B28,Mapping!A:D,4,0) -> West 2 | F28: =VLOOKUP(B28,Mapping!A:E,5,0) -> Anjli | G28: =VLOOKUP(B28,Mapping!A:F,6,0) -> Shweta | H28: 0.90154799 | I28: 1.3333333 | J28: 1.584126 | K28: 1.6666667 | L28: 1.1320755 | M28: 1.509434 | N28: 1.1385096 | O28: 1.9230769 | P28: 0.91666667 | Q28: 0.90885305
A29: FY2025-26 | B29: Maruti Suzuki(MSIL) | C29: =VLOOKUP(B29,Mapping!A:B,2,0) -> Lateral | D29: =VLOOKUP(B29,Mapping!A:C,3,0) -> North | E29: =VLOOKUP(B29,Mapping!A:D,4,0) -> North | F29: =VLOOKUP(B29,Mapping!A:E,5,0) -> Anjli | G29: =VLOOKUP(B29,Mapping!A:F,6,0) -> Archana | H29: 0.55070382 | I29: 0.62380438 | J29: 0.49773756 | K29: 0.73349633 | L29: 1.4 | M29: 1.025641 | N29: 1.1538462 | O29: 0.73417722 | P29: 1.0204082 | Q29: 0.9359877
A30: FY2025-26 | B30: Excelacom | C30: =VLOOKUP(B30,Mapping!A:B,2,0) -> Lateral | D30: =VLOOKUP(B30,Mapping!A:C,3,0) -> South | E30: =VLOOKUP(B30,Mapping!A:D,4,0) -> South 2 | F30: =VLOOKUP(B30,Mapping!A:E,5,0) -> Sulabh | G30: =VLOOKUP(B30,Mapping!A:F,6,0) -> Krishna | H30: 0.80033333 | I30: 0 | J30: 2.576 | K30: 0.669 | L30: 0.669 | M30: 0 | N30: 0 | O30: 0 | P30: 0 | Q30: 0
A31: FY2025-26 | B31: Tata Consumer | C31: =VLOOKUP(B31,Mapping!A:B,2,0) -> Lateral | D31: =VLOOKUP(B31,Mapping!A:C,3,0) -> West | E31: =VLOOKUP(B31,Mapping!A:D,4,0) -> West 1 | F31: =VLOOKUP(B31,Mapping!A:E,5,0) -> Anjli | G31: =VLOOKUP(B31,Mapping!A:F,6,0) -> Geetu | H31: 0.92485549 | I31: 1.3895425 | J31: 1.372549 | K31: 1.4309859 | L31: 0.58566197 | M31: 1.4788732 | N31: 1.3415493 | O31: 1.6428571 | P31: 2.389313 | Q31: 0.82052344
A32: FY2025-26 | B32: Tata Play | C32: =VLOOKUP(B32,Mapping!A:B,2,0) -> Lateral | D32: =VLOOKUP(B32,Mapping!A:C,3,0) -> West | E32: =VLOOKUP(B32,Mapping!A:D,4,0) -> West 1 | F32: =VLOOKUP(B32,Mapping!A:E,5,0) -> Anjli | G32: =VLOOKUP(B32,Mapping!A:F,6,0) -> Geetu | H32: 0.59584615 | I32: 1.7 | J32: 0.21538462 | K32: 0.94833333 | L32: 0.035454545 | M32: 0.45 | N32: 0.70833333 | O32: 0.35 | P32: 1.82 | Q32: 1.1460005
A33: FY2025-26 | B33: Mahindra Finance | C33: =VLOOKUP(B33,Mapping!A:B,2,0) -> Lateral | D33: =VLOOKUP(B33,Mapping!A:C,3,0) -> West | E33: =VLOOKUP(B33,Mapping!A:D,4,0) -> West 1 | F33: =VLOOKUP(B33,Mapping!A:E,5,0) -> Anjli | G33: =VLOOKUP(B33,Mapping!A:F,6,0) -> Geetu | H33: 0.57307692 | I33: 0.7504 | J33: 0.91428571 | K33: 1.9534884 | L33: 3.6521739 | M33: 2.8965517 | N33: 2.2068966 | O33: 2.2068966 | P33: 2.7333333 | Q33: 0
A34: FY2025-26 | B34: Suzuki R&D | C34: =VLOOKUP(B34,Mapping!A:B,2,0) -> Lateral | D34: =VLOOKUP(B34,Mapping!A:C,3,0) -> North | E34: =VLOOKUP(B34,Mapping!A:D,4,0) -> North | F34: =VLOOKUP(B34,Mapping!A:E,5,0) -> Anjli | G34: =VLOOKUP(B34,Mapping!A:F,6,0) -> Archana | H34: 1.1815 | I34: 1 | J34: 1 | K34: 0 | L34: 0 | M34: 0 | N34: 0 | O34: 2 | P34: 0 | Q34: 0.77474055
A35: FY2025-26 | B35: Subros Ltd | C35: =VLOOKUP(B35,Mapping!A:B,2,0) -> Lateral | D35: =VLOOKUP(B35,Mapping!A:C,3,0) -> North | E35: =VLOOKUP(B35,Mapping!A:D,4,0) -> North | F35: =VLOOKUP(B35,Mapping!A:E,5,0) -> Anjli | G35: =VLOOKUP(B35,Mapping!A:F,6,0) -> Archana | H35: 1.1838 | I35: 0.76923077 | J35: 0.23076923 | K35: 0.44776119 | L35: 0.69444444 | M35: 0.56458333 | N35: 0.27777778 | O35: 0.31483871 | P35: 0.88 | Q35: 0.96298986
A36: FY2025-26 | B36: Atomberg Technologies | C36: =VLOOKUP(B36,Mapping!A:B,2,0) -> Lateral | D36: =VLOOKUP(B36,Mapping!A:C,3,0) -> West | E36: =VLOOKUP(B36,Mapping!A:D,4,0) -> West 1 | F36: =VLOOKUP(B36,Mapping!A:E,5,0) -> Anjli | G36: =VLOOKUP(B36,Mapping!A:F,6,0) -> Geetu | H36: 1.0809524 | I36: 1.0895238 | J36: 1.0352 | K36: 1.6213592 | L36: 1.4407767 | M36: 1.6873786 | N36: 1.2485437 | O36: 1.6699029 | P36: 2.1862745 | Q36: 0.85234055
... A41: FY2025-26 | B41: M2P Fintech | C41: =VLOOKUP(B41,Mapping!A:B,2,0) -> Lateral | D41: =VLOOKUP(B41,Mapping!A:C,3,0) -> South | E41: =VLOOKUP(B41,Mapping!A:D,4,0) -> South 2 | F41: =VLOOKUP(B41,Mapping!A:E,5,0) -> Sulabh | G41: =VLOOKUP(B41,Mapping!A:F,6,0) -> Krishna | H41: 0.94 | I41: 1.6252439 | J41: 3.0726569 | K41: 0.62623529 | L41: -0.459125 | M41: 0 | N41: 0 | O41: 0 | P41: 0 | Q41: 0.59803055
A42: FY2025-26 | B42: Tata Power | C42: =VLOOKUP(B42,Mapping!A:B,2,0) -> Lateral | D42: =VLOOKUP(B42,Mapping!A:C,3,0) -> West | E42: =VLOOKUP(B42,Mapping!A:D,4,0) -> West 1 | F42: =VLOOKUP(B42,Mapping!A:E,5,0) -> Anjli | G42: =VLOOKUP(B42,Mapping!A:F,6,0) -> Elton | H42: - | I42: - | J42: - | K42: - | L42: - | M42: - | N42: - | O42: - | P42: - | Q42: -
A43: FY2025-26 | B43: ThyssenKrupp | C43: =VLOOKUP(B43,Mapping!A:B,2,0) -> Lateral | D43: =VLOOKUP(B43,Mapping!A:C,3,0) -> West | E43: =VLOOKUP(B43,Mapping!A:D,4,0) -> West 2 | F43: =VLOOKUP(B43,Mapping!A:E,5,0) -> Anjli | G43: =VLOOKUP(B43,Mapping!A:F,6,0) -> Shweta | H43: - | I43: - | J43: - | K43: - | L43: - | M43: - | N43: - | O43: - | P43: - | Q43: -
A44: FY2025-26 | B44: Fedex | C44: =VLOOKUP(B44,Mapping!A:B,2,0) -> Lateral | D44: =VLOOKUP(B44,Mapping!A:C,3,0) -> West | E44: =VLOOKUP(B44,Mapping!A:D,4,0) -> West 1 | F44: =VLOOKUP(B44,Mapping!A:E,5,0) -> Anjli | G44: =VLOOKUP(B44,Mapping!A:F,6,0) -> Elton | H44: - | I44: - | J44: - | K44: - | L44: - | M44: - | N44: - | O44: - | P44: - | Q44: -
A45: FY2025-26 | B45: Titan | C45: =VLOOKUP(B45,Mapping!A:B,2,0) -> Lateral | D45: =VLOOKUP(B45,Mapping!A:C,3,0) -> South | E45: =VLOOKUP(B45,Mapping!A:D,4,0) -> South 2 | F45: =VLOOKUP(B45,Mapping!A:E,5,0) -> Sulabh | G45: =VLOOKUP(B45,Mapping!A:F,6,0) -> Subu | H45: - | I45: - | J45: - | K45: - | L45: - | M45: - | N45: - | O45: - | P45: - | Q45: 0
A46: FY2025-26 | B46: Ultratech | C46: =VLOOKUP(B46,Mapping!A:B,2,0) -> Lateral | D46: =VLOOKUP(B46,Mapping!A:C,3,0) -> West | E46: =VLOOKUP(B46,Mapping!A:D,4,0) -> West 1 | F46: =VLOOKUP(B46,Mapping!A:E,5,0) -> Anjli | G46: =VLOOKUP(B46,Mapping!A:F,6,0) -> Elton | H46: - | I46: - | J46: - | K46: - | L46: - | M46: - | N46: - | O46: - | P46: - | Q46: -
A47: FY2025-26 | B47: L&T (New) | C47: =VLOOKUP(B47,Mapping!A:B,2,0) -> Lateral | D47: =VLOOKUP(B47,Mapping!A:C,3,0) -> South | E47: =VLOOKUP(B47,Mapping!A:D,4,0) -> South 2 | F47: =VLOOKUP(B47,Mapping!A:E,5,0) -> Sulabh | G47: =VLOOKUP(B47,Mapping!A:F,6,0) -> Sulabh | H47: - | I47: - | J47: - | K47: - | L47: - | M47: - | N47: - | O47: - | P47: - | Q47: -
A48: FY2025-26 | B48: DRL | C48: =VLOOKUP(B48,Mapping!A:B,2,0) -> Lateral | D48: =VLOOKUP(B48,Mapping!A:C,3,0) -> South | E48: =VLOOKUP(B48,Mapping!A:D,4,0) -> South 2 | F48: =VLOOKUP(B48,Mapping!A:E,5,0) -> Sulabh | G48: =VLOOKUP(B48,Mapping!A:F,6,0) -> Sulabh | H48: - | I48: - | J48: - | K48: - | L48: - | M48: - | N48: - | O48: - | P48: - | Q48: 0
A49: FY2025-26 | B49: Robert Bosch | C49: =VLOOKUP(B49,Mapping!A:B,2,0) -> Lateral | D49: =VLOOKUP(B49,Mapping!A:C,3,0) -> South | E49: =VLOOKUP(B49,Mapping!A:D,4,0) -> South 2 | F49: =VLOOKUP(B49,Mapping!A:E,5,0) -> Sulabh | G49: =VLOOKUP(B49,Mapping!A:F,6,0) -> Abhilash | H49: - | I49: - | J49: - | K49: - | L49: - | M49: - | N49: - | O49: - | P49: - | Q49: 0
A50: FY2025-26 | B50: Tata Teleservices | C50: =VLOOKUP(B50,Mapping!A:B,2,0) -> Lateral | D50: =VLOOKUP(B50,Mapping!A:C,3,0) -> West | E50: =VLOOKUP(B50,Mapping!A:D,4,0) -> West 1 | F50: =VLOOKUP(B50,Mapping!A:E,5,0) -> Anjli | G50: =VLOOKUP(B50,Mapping!A:F,6,0) -> Elton | H50: - | I50: - | J50: - | K50: - | L50: - | M50: - | N50: - | O50: - | P50: - | Q50: -
A51: FY2025-26 | B51: Honeywell Leadership | C51: =VLOOKUP(B51,Mapping!A:B,2,0) -> Leadership | D51: =VLOOKUP(B51,Mapping!A:C,3,0) -> South | E51: =VLOOKUP(B51,Mapping!A:D,4,0) -> South 1 | F51: =VLOOKUP(B51,Mapping!A:E,5,0) -> Bapi | G51: =VLOOKUP(B51,Mapping!A:F,6,0) -> Parul | H51: 0.26666667 | I51: 1.2 | J51: 0.83764 | K51: 0.127076 | L51: -0.479272 | M51: 1.2 | N51: -0.364628 | O51: -2 | P51: 0 | Q51: 1.7168645
A52: FY2025-26 | B52: Siemens Leadership | C52: =VLOOKUP(B52,Mapping!A:B,2,0) -> Leadership | D52: =VLOOKUP(B52,Mapping!A:C,3,0) -> South | E52: =VLOOKUP(B52,Mapping!A:D,4,0) -> South 2 | F52: =VLOOKUP(B52,Mapping!A:E,5,0) -> Sulabh | G52: =VLOOKUP(B52,Mapping!A:F,6,0) -> Parul | H52: 0 | I52: 0 | J52: 0 | K52: 0 | L52: 9.5 | M52: 9 | N52: 0 | O52: 0 | P52: 0 | Q52: 0
A53: FY2025-26 | B53: Vertiv Leadership | C53: =VLOOKUP(B53,Mapping!A:B,2,0) -> Leadership | D53: =VLOOKUP(B53,Mapping!A:C,3,0) -> West | E53: =VLOOKUP(B53,Mapping!A:D,4,0) -> West 2 | F53: =VLOOKUP(B53,Mapping!A:E,5,0) -> Anjli | G53: =VLOOKUP(B53,Mapping!A:F,6,0) -> Parul | H53: 0 | I53: 2.2 | J53: 0.4 | K53: 17.64 | L53: 33.5 | M53: 3.2 | N53: 0 | O53: -3.845303 | P53: 1.2121212 | Q53: 1.3239709
A54: FY2025-26 | B54: M&M Leadership | C54: =VLOOKUP(B54,Mapping!A:B,2,0) -> Leadership | D54: =VLOOKUP(B54,Mapping!A:C,3,0) -> West | E54: =VLOOKUP(B54,Mapping!A:D,4,0) -> West 1 | F54: =VLOOKUP(B54,Mapping!A:E,5,0) -> Anjli | G54: =VLOOKUP(B54,Mapping!A:F,6,0) -> Parul | H54: 0 | I54: 5.7978947 | J54: 1.395 | K54: 1.3205128 | L54: 3.5441176 | M54: 5.78 | N54: 0.069230769 | O54: 0.4952381 | P54: 2.2925617 | Q54: 1.1972677
A55: FY2025-26 | B55: AMNS Leadership | C55: =VLOOKUP(B55,Mapping!A:B,2,0) -> Leadership | D55: =VLOOKUP(B55,Mapping!A:C,3,0) -> West | E55: =VLOOKUP(B55,Mapping!A:D,4,0) -> West 1 | F55: =VLOOKUP(B55,Mapping!A:E,5,0) -> Anjli | G55: =VLOOKUP(B55,Mapping!A:F,6,0) -> Parul | H55: 1.49 | I55: 1.86 | J55: 4.8 | K55: 1.5 | L55: 5.225 | M55: 5.715 | N55: 0 | O55: 2.75 | P55: 0.335 | Q55: 0.97154055
A56: FY2025-26 | B56: Nagarjuna Leadership | C56: =VLOOKUP(B56,Mapping!A:B,2,0) -> Leadership | D56: =VLOOKUP(B56,Mapping!A:C,3,0) -> South | E56: =VLOOKUP(B56,Mapping!A:D,4,0) -> South 2 | F56: =VLOOKUP(B56,Mapping!A:E,5,0) -> Sulabh | G56: =VLOOKUP(B56,Mapping!A:F,6,0) -> Parul | H56: 0 | I56: 0 | J56: 0 | K56: 0 | L56: 0 | M56: 0 | N56: 0 | O56: 0 | P56: 0 | Q56: 0
A57: FY2025-26 | B57: Royal Enfield Leadership | C57: =VLOOKUP(B57,Mapping!A:B,2,0) -> Leadership | D57: =VLOOKUP(B57,Mapping!A:C,3,0) -> South | E57: =VLOOKUP(B57,Mapping!A:D,4,0) -> South 2 | F57: =VLOOKUP(B57,Mapping!A:E,5,0) -> Sulabh | G57: =VLOOKUP(B57,Mapping!A:F,6,0) -> Parul | H57: 42.31584 | I57: 3.9 | J57: -27.11584 | K57: 0 | L57: 0 | M57: 0 | N57: 0 | O57: 0 | P57: 5.3529412 | Q57: 1.3239405
A58: FY2025-26 | B58: Sterling Tools Leadership | C58: =VLOOKUP(B58,Mapping!A:B,2,0) -> Leadership | D58: =VLOOKUP(B58,Mapping!A:C,3,0) -> North | E58: =VLOOKUP(B58,Mapping!A:D,4,0) -> North | F58: =VLOOKUP(B58,Mapping!A:E,5,0) -> Anjli | G58: =VLOOKUP(B58,Mapping!A:F,6,0) -> Parul | H58: 0 | I58: 0 | J58: 2 | K58: 0 | L58: 0 | M58: 0 | N58: 0 | O58: 0 | P58: 0 | Q58: 0
A59: FY2025-26 | B59: Mahindra Holidays Leadership | C59: =VLOOKUP(B59,Mapping!A:B,2,0) -> Leadership | D59: =VLOOKUP(B59,Mapping!A:C,3,0) -> West | E59: =VLOOKUP(B59,Mapping!A:D,4,0) -> West 1 | F59: =VLOOKUP(B59,Mapping!A:E,5,0) -> Anjli | G59: =VLOOKUP(B59,Mapping!A:F,6,0) -> Parul | H59: 0 | I59: 0 | J59: 0 | K59: 0 | L59: 0 | M59: 0 | N59: 8.0120482 | O59: 2.3614458 | P59: 0 | Q59: 0.95785621
A60: FY2025-26 | B60: Hyundai Motor Leadership | C60: =VLOOKUP(B60,Mapping!A:B,2,0) -> Leadership | D60: =VLOOKUP(B60,Mapping!A:C,3,0) -> West | E60: =VLOOKUP(B60,Mapping!A:D,4,0) -> West 2 | F60: =VLOOKUP(B60,Mapping!A:E,5,0) -> Anjli | G60: =VLOOKUP(B60,Mapping!A:F,6,0) -> Parul | H60: 0 | I60: 0 | J60: 0 | K60: 0 | L60: 0 | M60: 8.94 | N60: 0 | O60: 6 | P60: 0 | Q60: 0.71622055
A61: FY2025-26 | B61: JINDAL STAINLESS Leadership | C61: =VLOOKUP(B61,Mapping!A:B,2,0) -> Leadership | D61: =VLOOKUP(B61,Mapping!A:C,3,0) -> North | E61: =VLOOKUP(B61,Mapping!A:D,4,0) -> North | F61: =VLOOKUP(B61,Mapping!A:E,5,0) -> Anjli | G61: =VLOOKUP(B61,Mapping!A:F,6,0) -> Parul | H61: 0 | I61: 0 | J61: 0 | K61: 0 | L61: 0 | M61: 0 | N61: 0 | O61: 0 | P61: 0 | Q61: 0
A62: FY2025-26 | B62: SUZUKI R&D Leadership | C62: =VLOOKUP(B62,Mapping!A:B,2,0) -> Leadership | D62: =VLOOKUP(B62,Mapping!A:C,3,0) -> North | E62: =VLOOKUP(B62,Mapping!A:D,4,0) -> North | F62: =VLOOKUP(B62,Mapping!A:E,5,0) -> Anjli | G62: =VLOOKUP(B62,Mapping!A:F,6,0) -> Parul | H62: 0 | I62: 0 | J62: 0 | K62: 0 | L62: 0 | M62: 0 | N62: 0 | O62: 0 | P62: 0 | Q62: 0
... A65: FY2025-26 | B65: Optum | C65: =VLOOKUP(B65,Mapping!A:B,2,0) -> Lateral | D65: =VLOOKUP(B65,Mapping!A:C,3,0) -> South | E65: =VLOOKUP(B65,Mapping!A:D,4,0) -> South 1 | F65: =VLOOKUP(B65,Mapping!A:E,5,0) -> Ashish | G65: =VLOOKUP(B65,Mapping!A:F,6,0) -> Ashish | H65: 3.1142857 | I65: 2.6363636 | J65: 3.35 | K65: 3.27 | L65: 3.6312849 | M65: 2.6470588 | N65: 2.8508772 | O65: 2.8735632 | P65: 4.2173913 | Q65: 1.1320647
A66: FY2025-26 | B66: New Sales + Mining | C66: =VLOOKUP(B66,Mapping!A:B,2,0) -> Lateral | D66: =VLOOKUP(B66,Mapping!A:C,3,0) -> New Sales | E66: =VLOOKUP(B66,Mapping!A:D,4,0) -> New Sales | F66: =VLOOKUP(B66,Mapping!A:E,5,0) -> Nizar | G66: =VLOOKUP(B66,Mapping!A:F,6,0) -> Nizar | H66: 0 | I66: 0 | J66: 0 | K66: 0 | L66: 0 | M66: 0 | N66: 0 | O66: 0 | P66: 0 | Q66: -
A67: FY2025-26 | B67: Pernod Ricard | C67: =VLOOKUP(B67,Mapping!A:B,2,0) -> Lateral | D67: =VLOOKUP(B67,Mapping!A:C,3,0) -> North | E67: =VLOOKUP(B67,Mapping!A:D,4,0) -> North | F67: =VLOOKUP(B67,Mapping!A:E,5,0) -> Anjli | G67: =VLOOKUP(B67,Mapping!A:F,6,0) -> Archana | H67: 0.375 | I67: 0.36585366 | J67: 1.052381 | K67: 1.0930233 | L67: 0.77209302 | M67: 1.2698413 | N67: 1.7391304 | O67: 1.8528302 | P67: 2.0338983 | Q67: 0.94337678
A68: FY2025-26 | B68: UniCharm | C68: =VLOOKUP(B68,Mapping!A:B,2,0) -> Lateral | D68: =VLOOKUP(B68,Mapping!A:C,3,0) -> North | E68: =VLOOKUP(B68,Mapping!A:D,4,0) -> North | F68: =VLOOKUP(B68,Mapping!A:E,5,0) -> Anjli | G68: =VLOOKUP(B68,Mapping!A:F,6,0) -> Archana | H68: 0 | I68: 0 | J68: 0 | K68: 0 | L68: 0 | M68: 0 | N68: 0.67307692 | O68: 0.65517241 | P68: 0.86206897 | Q68: 1.0328961
A69: FY2025-26 | B69: Saint Gobain | C69: =VLOOKUP(B69,Mapping!A:B,2,0) -> Lateral | D69: =VLOOKUP(B69,Mapping!A:C,3,0) -> West | E69: =VLOOKUP(B69,Mapping!A:D,4,0) -> West 1 | F69: =VLOOKUP(B69,Mapping!A:E,5,0) -> Anjli | G69: =VLOOKUP(B69,Mapping!A:F,6,0) -> Anjli | H69: 0 | I69: 0 | J69: 0 | K69: 0 | L69: 0 | M69: 0 | N69: 0 | O69: 0 | P69: 0 | Q69: 0.8624318
A70: FY2025-26 | B70: Leap India | C70: =VLOOKUP(B70,Mapping!A:B,2,0) -> Lateral | D70: =VLOOKUP(B70,Mapping!A:C,3,0) -> West | E70: =VLOOKUP(B70,Mapping!A:D,4,0) -> West 1 | F70: =VLOOKUP(B70,Mapping!A:E,5,0) -> Anjli | G70: =VLOOKUP(B70,Mapping!A:F,6,0) -> Geetu | H70: 0 | I70: 5.2777778 | J70: 1.5151515 | K70: 0.42595122 | L70: 0.92682927 | M70: 1.0446927 | N70: 0.76482412 | O70: 1.1971223 | P70: 1.5441176 | Q70: 0.7984473
A71: FY2025-26 | B71: NeoSoft | C71: =VLOOKUP(B71,Mapping!A:B,2,0) -> Lateral | D71: =VLOOKUP(B71,Mapping!A:C,3,0) -> West | E71: =VLOOKUP(B71,Mapping!A:D,4,0) -> West 1 | F71: =VLOOKUP(B71,Mapping!A:E,5,0) -> Anjli | G71: =VLOOKUP(B71,Mapping!A:F,6,0) -> Archana | H71: 0 | I71: 0 | J71: 0 | K71: 0 | L71: 0 | M71: 0 | N71: 0 | O71: 0 | P71: 0 | Q71: 0.81116055
A72: FY2025-26 | B72: Siemens Healthnier | C72: =VLOOKUP(B72,Mapping!A:B,2,0) -> Lateral | D72: =VLOOKUP(B72,Mapping!A:C,3,0) -> South | E72: =VLOOKUP(B72,Mapping!A:D,4,0) -> South 2 | F72: =VLOOKUP(B72,Mapping!A:E,5,0) -> Sulabh | G72: =VLOOKUP(B72,Mapping!A:F,6,0) -> Lekhana | H72: 0.192 | I72: 0.32142857 | J72: 0.38571429 | K72: 0.4 | L72: 0.33333333 | M72: 2.6066667 | N72: 0.5 | O72: 1.07 | P72: 1.026 | Q72: 0.79442388
A73: FY2025-26 | B73: ABB | C73: =VLOOKUP(B73,Mapping!A:B,2,0) -> Lateral | D73: =VLOOKUP(B73,Mapping!A:C,3,0) -> South | E73: =VLOOKUP(B73,Mapping!A:D,4,0) -> South 2 | F73: =VLOOKUP(B73,Mapping!A:E,5,0) -> Sulabh | G73: =VLOOKUP(B73,Mapping!A:F,6,0) -> Satya | H73: 0.35 | I73: 0.225 | J73: 0.31875 | K73: 0.95480769 | L73: 1.3370192 | M73: 0.87759815 | N73: 1.7057057 | O73: 0.19557057 | P73: 0.93822171 | Q73: 1.1589015
A74: FY2025-26 | B74: TCG Group | C74: =VLOOKUP(B74,Mapping!A:B,2,0) -> Lateral | D74: =VLOOKUP(B74,Mapping!A:C,3,0) -> West | E74: =VLOOKUP(B74,Mapping!A:D,4,0) -> West 1 | F74: =VLOOKUP(B74,Mapping!A:E,5,0) -> Anjli | G74: =VLOOKUP(B74,Mapping!A:F,6,0) -> Anjli | H74: - | I74: - | J74: - | K74: - | L74: - | M74: - | N74: - | O74: - | P74: - | Q74: -
A75: FY2025-26 | B75: Metglas | C75: =VLOOKUP(B75,Mapping!A:B,2,0) -> Lateral | D75: =VLOOKUP(B75,Mapping!A:C,3,0) -> West | E75: =VLOOKUP(B75,Mapping!A:D,4,0) -> West 1 | F75: =VLOOKUP(B75,Mapping!A:E,5,0) -> Anjli | G75: =VLOOKUP(B75,Mapping!A:F,6,0) -> Anjli | H75: - | I75: - | J75: - | K75: - | L75: - | M75: - | N75: - | O75: - | P75: - | Q75: 0.78881055
A76: FY2025-26 | B76: CG Power | C76: =VLOOKUP(B76,Mapping!A:B,2,0) -> Lateral | D76: =VLOOKUP(B76,Mapping!A:C,3,0) -> West | E76: =VLOOKUP(B76,Mapping!A:D,4,0) -> West 1 | F76: =VLOOKUP(B76,Mapping!A:E,5,0) -> Anjli | G76: =VLOOKUP(B76,Mapping!A:F,6,0) -> Anjli | H76: - | I76: - | J76: - | K76: - | L76: - | M76: - | N76: - | O76: - | P76: - | Q76: 0

Sheet Taggd_Source_Joiner
A1: =Revenue_Budget!A1 -> FY | B1: =Revenue_Budget!B1 -> Project | C1: =Revenue_Budget!C1 -> Vertical | D1: =Revenue_Budget!D1 -> Region | E1: =Revenue_Budget!E1 -> Sub Region | F1: =Revenue_Budget!F1 -> Region Head | G1: =Revenue_Budget!G1 -> Practice Head | H1: =Revenue_Budget!H1 -> 45748 | ... S1: =Revenue_Budget!S1 -> 46082
A2: FY2025-26 | B2: Honeywell | C2: =VLOOKUP(B2,Mapping!A:B,2,0) -> Lateral | D2: =VLOOKUP(B2,Mapping!A:C,3,0) -> South | E2: =VLOOKUP(B2,Mapping!A:D,4,0) -> South 1 | F2: =VLOOKUP(B2,Mapping!A:E,5,0) -> Bapi | G2: =VLOOKUP(B2,Mapping!A:F,6,0) -> Bapi | H2: 123 | I2: 73 | J2: 145 | K2: 47 | L2: 162 | M2: 167 | N2: 36 | O2: 98 | P2: 163
A3: FY2025-26 | B3: Pfizer | C3: =VLOOKUP(B3,Mapping!A:B,2,0) -> Lateral | D3: =VLOOKUP(B3,Mapping!A:C,3,0) -> West | E3: =VLOOKUP(B3,Mapping!A:D,4,0) -> West 1 | F3: =VLOOKUP(B3,Mapping!A:E,5,0) -> Anjli | G3: =VLOOKUP(B3,Mapping!A:F,6,0) -> Usha | H3: 5 | I3: 2 | J3: 8 | K3: 5 | L3: 10 | M3: 1 | N3: 1 | O3: 0 | P3: 3
A4: FY2025-26 | B4: Tata Motors | C4: =VLOOKUP(B4,Mapping!A:B,2,0) -> Lateral | D4: =VLOOKUP(B4,Mapping!A:C,3,0) -> West | E4: =VLOOKUP(B4,Mapping!A:D,4,0) -> West 2 | F4: =VLOOKUP(B4,Mapping!A:E,5,0) -> Anjli | G4: =VLOOKUP(B4,Mapping!A:F,6,0) -> Shweta | H4: 3 | I4: 5 | J4: 2 | K4: 0 | L4: 0 | M4: 0 | N4: 0 | O4: 0 | P4: 0
A5: FY2025-26 | B5: SKF India | C5: =VLOOKUP(B5,Mapping!A:B,2,0) -> Lateral | D5: =VLOOKUP(B5,Mapping!A:C,3,0) -> North | E5: =VLOOKUP(B5,Mapping!A:D,4,0) -> North | F5: =VLOOKUP(B5,Mapping!A:E,5,0) -> Anjli | G5: =VLOOKUP(B5,Mapping!A:F,6,0) -> Archana | H5: 13 | I5: 6 | J5: 13 | K5: 11 | L5: 11 | M5: 15 | N5: 17 | O5: 10 | P5: 11
A6: FY2025-26 | B6: Siemens | C6: =VLOOKUP(B6,Mapping!A:B,2,0) -> Lateral | D6: =VLOOKUP(B6,Mapping!A:C,3,0) -> South | E6: =VLOOKUP(B6,Mapping!A:D,4,0) -> South 1 | F6: =VLOOKUP(B6,Mapping!A:E,5,0) -> Sulabh | G6: =VLOOKUP(B6,Mapping!A:F,6,0) -> Kunal | H6: 13 | I6: 16 | J6: 32 | K6: 8 | L6: 42 | M6: 69 | N6: 16 | O6: 48 | P6: 25
A7: FY2025-26 | B7: Pidilite | C7: =VLOOKUP(B7,Mapping!A:B,2,0) -> Lateral | D7: =VLOOKUP(B7,Mapping!A:C,3,0) -> West | E7: =VLOOKUP(B7,Mapping!A:D,4,0) -> West 1 | F7: =VLOOKUP(B7,Mapping!A:E,5,0) -> Anjli | G7: =VLOOKUP(B7,Mapping!A:F,6,0) -> Usha | H7: 8 | I7: 6 | J7: 7 | K7: 24 | L7: 16 | M7: 36 | N7: 18 | O7: 14 | P7: 18
A8: FY2025-26 | B8: Vertiv | C8: =VLOOKUP(B8,Mapping!A:B,2,0) -> Lateral | D8: =VLOOKUP(B8,Mapping!A:C,3,0) -> West | E8: =VLOOKUP(B8,Mapping!A:D,4,0) -> West 2 | F8: =VLOOKUP(B8,Mapping!A:E,5,0) -> Anjli | G8: =VLOOKUP(B8,Mapping!A:F,6,0) -> Shweta | H8: 6 | I8: 3 | J8: 1 | K8: 4 | L8: 3 | M8: 4 | N8: 4 | O8: 2 | P8: 5
A9: FY2025-26 | B9: Birla Paints | C9: =VLOOKUP(B9,Mapping!A:B,2,0) -> Lateral | D9: =VLOOKUP(B9,Mapping!A:C,3,0) -> West | E9: =VLOOKUP(B9,Mapping!A:D,4,0) -> West 1 | F9: =VLOOKUP(B9,Mapping!A:E,5,0) -> Anjli | G9: =VLOOKUP(B9,Mapping!A:F,6,0) -> Geetu | H9: 6 | I9: 14 | J9: 12 | K9: 12 | L9: 18 | M9: 19 | N9: 19 | O9: 21 | P9: 21
A10: FY2025-26 | B10: Ingram Micro | C10: =VLOOKUP(B10,Mapping!A:B,2,0) -> Lateral | D10: =VLOOKUP(B10,Mapping!A:C,3,0) -> West | E10: =VLOOKUP(B10,Mapping!A:D,4,0) -> West 1 | F10: =VLOOKUP(B10,Mapping!A:E,5,0) -> Anjli | G10: =VLOOKUP(B10,Mapping!A:F,6,0) -> Geetu | H10: 0 | I10: 1 | J10: 3 | K10: 2 | L10: 1 | M10: 2 | N10: 0 | O10: 0 | P10: 1
A11: FY2025-26 | B11: HPE | C11: =VLOOKUP(B11,Mapping!A:B,2,0) -> Lateral | D11: =VLOOKUP(B11,Mapping!A:C,3,0) -> South | E11: =VLOOKUP(B11,Mapping!A:D,4,0) -> South 1 | F11: =VLOOKUP(B11,Mapping!A:E,5,0) -> Mahak | G11: =VLOOKUP(B11,Mapping!A:F,6,0) -> Mahak | H11: 40 | I11: 32 | J11: 21 | K11: 15 | L11: 17 | M11: 33 | N11: 52 | O11: 58 | P11: 25
A12: FY2025-26 | B12: Isuzu | C12: =VLOOKUP(B12,Mapping!A:B,2,0) -> Lateral | D12: =VLOOKUP(B12,Mapping!A:C,3,0) -> South | E12: =VLOOKUP(B12,Mapping!A:D,4,0) -> South 1 | F12: =VLOOKUP(B12,Mapping!A:E,5,0) -> Anjli | G12: =VLOOKUP(B12,Mapping!A:F,6,0) -> Satya | H12: 2 | I12: 5 | J12: 2 | K12: 11 | L12: 4 | M12: 4 | N12: 1 | O12: 3 | P12: 2
A13: FY2025-26 | B13: Mahindra Holidays | C13: =VLOOKUP(B13,Mapping!A:B,2,0) -> Lateral | D13: =VLOOKUP(B13,Mapping!A:C,3,0) -> West | E13: =VLOOKUP(B13,Mapping!A:D,4,0) -> West 1 | F13: =VLOOKUP(B13,Mapping!A:E,5,0) -> Anjli | G13: =VLOOKUP(B13,Mapping!A:F,6,0) -> Geetu | H13: 18 | I13: 33 | J13: 16 | K13: 10 | L13: 12 | M13: 15 | N13: 14 | O13: 9 | P13: 5
... A76: FY2025-26 | B76: CG Power | C76: =VLOOKUP(B76,Mapping!A:B,2,0) -> Lateral | D76: =VLOOKUP(B76,Mapping!A:C,3,0) -> West | E76: =VLOOKUP(B76,Mapping!A:D,4,0) -> West 1 | F76: =VLOOKUP(B76,Mapping!A:E,5,0) -> Anjli | G76: =VLOOKUP(B76,Mapping!A:F,6,0) -> Anjli | H76: 0 | I76: 0 | J76: 0 | K76: 0 | L76: 0 | M76: 0 | N76: 0 | O76: 0 | P76: 0

Sheet Non Taggd_Source_Joiner
A1: =Revenue_Budget!A1 -> FY | B1: =Revenue_Budget!B1 -> Project | C1: =Revenue_Budget!C1 -> Vertical | D1: =Revenue_Budget!D1 -> Region | E1: =Revenue_Budget!E1 -> Sub Region | F1: =Revenue_Budget!F1 -> Region Head | G1: =Revenue_Budget!G1 -> Practice Head | H1: =Revenue_Budget!H1 -> 45748 | ... S1: =Revenue_Budget!S1 -> 46082
A2: FY2025-26 | B2: Honeywell | C2: =VLOOKUP(B2,Mapping!A:B,2,0) -> Lateral | D2: =VLOOKUP(B2,Mapping!A:C,3,0) -> South | E2: =VLOOKUP(B2,Mapping!A:D,4,0) -> South 1 | F2: =VLOOKUP(B2,Mapping!A:E,5,0) -> Bapi | G2: =VLOOKUP(B2,Mapping!A:F,6,0) -> Bapi | H2: 166 | I2: 312 | J2: 258 | K2: 271 | L2: 305 | M2: 263 | N2: 119 | O2: 68 | P2: 110
A3: FY2025-26 | B3: Pfizer | C3: =VLOOKUP(B3,Mapping!A:B,2,0) -> Lateral | D3: =VLOOKUP(B3,Mapping!A:C,3,0) -> West | E3: =VLOOKUP(B3,Mapping!A:D,4,0) -> West 1 | F3: =VLOOKUP(B3,Mapping!A:E,5,0) -> Anjli | G3: =VLOOKUP(B3,Mapping!A:F,6,0) -> Usha | H3: 10 | I3: 8 | J3: 14 | K3: 15 | L3: 8 | M3: 1 | N3: 1 | O3: 0 | P3: 2
A4: FY2025-26 | B4: Tata Motors | C4: =VLOOKUP(B4,Mapping!A:B,2,0) -> Lateral | D4: =VLOOKUP(B4,Mapping!A:C,3,0) -> West | E4: =VLOOKUP(B4,Mapping!A:D,4,0) -> West 2 | F4: =VLOOKUP(B4,Mapping!A:E,5,0) -> Anjli | G4: =VLOOKUP(B4,Mapping!A:F,6,0) -> Shweta | H4: 0 | I4: 3 | J4: 0 | K4: 0 | L4: 0 | M4: 0 | N4: 0 | O4: 0 | P4: 0
A5: FY2025-26 | B5: SKF India | C5: =VLOOKUP(B5,Mapping!A:B,2,0) -> Lateral | D5: =VLOOKUP(B5,Mapping!A:C,3,0) -> North | E5: =VLOOKUP(B5,Mapping!A:D,4,0) -> North | F5: =VLOOKUP(B5,Mapping!A:E,5,0) -> Anjli | G5: =VLOOKUP(B5,Mapping!A:F,6,0) -> Archana | H5: 15 | I5: 9 | J5: 8 | K5: 9 | L5: 7 | M5: 17 | N5: 16 | O5: 8 | P5: 7
A6: FY2025-26 | B6: Siemens | C6: =VLOOKUP(B6,Mapping!A:B,2,0) -> Lateral | D6: =VLOOKUP(B6,Mapping!A:C,3,0) -> South | E6: =VLOOKUP(B6,Mapping!A:D,4,0) -> South 1 | F6: =VLOOKUP(B6,Mapping!A:E,5,0) -> Sulabh | G6: =VLOOKUP(B6,Mapping!A:F,6,0) -> Kunal | H6: 9 | I6: 6 | J6: 11 | K6: 0 | L6: 7 | M6: 13 | N6: 9 | O6: 9 | P6: 7
A7: FY2025-26 | B7: Pidilite | C7: =VLOOKUP(B7,Mapping!A:B,2,0) -> Lateral | D7: =VLOOKUP(B7,Mapping!A:C,3,0) -> West | E7: =VLOOKUP(B7,Mapping!A:D,4,0) -> West 1 | F7: =VLOOKUP(B7,Mapping!A:E,5,0) -> Anjli | G7: =VLOOKUP(B7,Mapping!A:F,6,0) -> Usha | H7: 0 | I7: 0 | J7: 1 | K7: 13 | L7: 16 | M7: 12 | N7: 8 | O7: 12 | P7: 17
A8: FY2025-26 | B8: Vertiv | C8: =VLOOKUP(B8,Mapping!A:B,2,0) -> Lateral | D8: =VLOOKUP(B8,Mapping!A:C,3,0) -> West | E8: =VLOOKUP(B8,Mapping!A:D,4,0) -> West 2 | F8: =VLOOKUP(B8,Mapping!A:E,5,0) -> Anjli | G8: =VLOOKUP(B8,Mapping!A:F,6,0) -> Shweta | H8: 2 | I8: 1 | J8: 2 | K8: 0 | L8: 0 | M8: 0 | N8: 0 | O8: 2 | P8: 0
A9: FY2025-26 | B9: Birla Paints | C9: =VLOOKUP(B9,Mapping!A:B,2,0) -> Lateral | D9: =VLOOKUP(B9,Mapping!A:C,3,0) -> West | E9: =VLOOKUP(B9,Mapping!A:D,4,0) -> West 1 | F9: =VLOOKUP(B9,Mapping!A:E,5,0) -> Anjli | G9: =VLOOKUP(B9,Mapping!A:F,6,0) -> Geetu | H9: 16 | I9: 29 | J9: 28 | K9: 25 | L9: 29 | M9: 23 | N9: 23 | O9: 25 | P9: 44
A10: FY2025-26 | B10: Ingram Micro | C10: =VLOOKUP(B10,Mapping!A:B,2,0) -> Lateral | D10: =VLOOKUP(B10,Mapping!A:C,3,0) -> West | E10: =VLOOKUP(B10,Mapping!A:D,4,0) -> West 1 | F10: =VLOOKUP(B10,Mapping!A:E,5,0) -> Anjli | G10: =VLOOKUP(B10,Mapping!A:F,6,0) -> Geetu | H10: 1 | I10: 0 | J10: 0 | K10: 2 | L10: 1 | M10: 3 | N10: 0 | O10: 0 | P10: 0
A11: FY2025-26 | B11: HPE | C11: =VLOOKUP(B11,Mapping!A:B,2,0) -> Lateral | D11: =VLOOKUP(B11,Mapping!A:C,3,0) -> South | E11: =VLOOKUP(B11,Mapping!A:D,4,0) -> South 1 | F11: =VLOOKUP(B11,Mapping!A:E,5,0) -> Mahak | G11: =VLOOKUP(B11,Mapping!A:F,6,0) -> Mahak | H11: 53 | I11: 75 | J11: 63 | K11: 39 | L11: 113 | M11: 500 | N11: 59 | O11: 68 | P11: 55
A12: FY2025-26 | B12: Isuzu | C12: =VLOOKUP(B12,Mapping!A:B,2,0) -> Lateral | D12: =VLOOKUP(B12,Mapping!A:C,3,0) -> South | E12: =VLOOKUP(B12,Mapping!A:D,4,0) -> South 1 | F12: =VLOOKUP(B12,Mapping!A:E,5,0) -> Anjli | G12: =VLOOKUP(B12,Mapping!A:F,6,0) -> Satya | H12: 4 | I12: 3 | J12: 0 | K12: 0 | L12: 2 | M12: 8 | N12: 4 | O12: 5 | P12: 2
A13: FY2025-26 | B13: Mahindra Holidays | C13: =VLOOKUP(B13,Mapping!A:B,2,0) -> Lateral | D13: =VLOOKUP(B13,Mapping!A:C,3,0) -> West | E13: =VLOOKUP(B13,Mapping!A:D,4,0) -> West 1 | F13: =VLOOKUP(B13,Mapping!A:E,5,0) -> Anjli | G13: =VLOOKUP(B13,Mapping!A:F,6,0) -> Geetu | H13: 1 | I13: 0 | J13: 0 | K13: 0 | L13: 3 | M13: 2 | N13: 0 | O13: 2 | P13: 0
... A76: FY2025-26 | B76: CG Power | C76: =VLOOKUP(B76,Mapping!A:B,2,0) -> Lateral | D76: =VLOOKUP(B76,Mapping!A:C,3,0) -> West | E76: =VLOOKUP(B76,Mapping!A:D,4,0) -> West 1 | F76: =VLOOKUP(B76,Mapping!A:E,5,0) -> Anjli | G76: =VLOOKUP(B76,Mapping!A:F,6,0) -> Anjli | H76: 0 | I76: 0 | J76: 0 | K76: 0 | L76: 0 | M76: 0 | N76: 0 | O76: 0 | P76: 0

Sheet Revenue_Adjustment
A1: =Revenue_Budget!A1 -> FY | B1: =Revenue_Budget!B1 -> Project | C1: =Revenue_Budget!C1 -> Vertical | D1: =Revenue_Budget!D1 -> Region | E1: =Revenue_Budget!E1 -> Sub Region | F1: =Revenue_Budget!F1 -> Region Head | G1: =Revenue_Budget!G1 -> Practice Head | H1: =Revenue_Budget!H1 -> 45748 | ... S1: =Revenue_Budget!S1 -> 46082 | T1: FY'26
A2: FY2025-26 | B2: Honeywell | C2: =VLOOKUP(B2,Mapping!A:B,2,0) -> Lateral | D2: =VLOOKUP(B2,Mapping!A:C,3,0) -> South | E2: =VLOOKUP(B2,Mapping!A:D,4,0) -> South 1 | F2: =VLOOKUP(B2,Mapping!A:E,5,0) -> Bapi | G2: =VLOOKUP(B2,Mapping!A:F,6,0) -> Bapi | H2: 0 | I2: 0 | J2: 0 | K2: 1.34898 | L2: 9.5 | M2: 49.55 | N2: 0.91 | O2: 0 | P2: 0 | Q2: 0 | R2: 0 | T2: =SUM(H2:S2) -> 61.30898
A3: FY2025-26 | B3: Pfizer | C3: =VLOOKUP(B3,Mapping!A:B,2,0) -> Lateral | D3: =VLOOKUP(B3,Mapping!A:C,3,0) -> West | E3: =VLOOKUP(B3,Mapping!A:D,4,0) -> West 1 | F3: =VLOOKUP(B3,Mapping!A:E,5,0) -> Anjli | G3: =VLOOKUP(B3,Mapping!A:F,6,0) -> Usha | H3: 0 | I3: 0.09 | J3: 0 | K3: 0 | L3: 0 | M3: 0 | N3: 0 | O3: 0 | P3: 0 | Q3: 0 | R3: 0 | T3: =SUM(H3:S3) -> 0.09
A4: FY2025-26 | B4: Tata Motors | C4: =VLOOKUP(B4,Mapping!A:B,2,0) -> Lateral | D4: =VLOOKUP(B4,Mapping!A:C,3,0) -> West | E4: =VLOOKUP(B4,Mapping!A:D,4,0) -> West 2 | F4: =VLOOKUP(B4,Mapping!A:E,5,0) -> Anjli | G4: =VLOOKUP(B4,Mapping!A:F,6,0) -> Shweta | H4: 0 | I4: 0 | J4: 0 | K4: 0 | L4: 0 | M4: 0 | N4: 0 | O4: 0 | P4: 0 | Q4: 0 | R4: 0 | T4: =SUM(H4:S4) -> 0
A5: FY2025-26 | B5: SKF India | C5: =VLOOKUP(B5,Mapping!A:B,2,0) -> Lateral | D5: =VLOOKUP(B5,Mapping!A:C,3,0) -> North | E5: =VLOOKUP(B5,Mapping!A:D,4,0) -> North | F5: =VLOOKUP(B5,Mapping!A:E,5,0) -> Anjli | G5: =VLOOKUP(B5,Mapping!A:F,6,0) -> Archana | H5: 0 | I5: 0 | J5: 0 | K5: 0 | L5: 0 | M5: 0 | N5: 0 | O5: 0 | P5: 0 | Q5: 0 | R5: 0 | T5: =SUM(H5:S5) -> 0
A6: FY2025-26 | B6: Siemens | C6: =VLOOKUP(B6,Mapping!A:B,2,0) -> Lateral | D6: =VLOOKUP(B6,Mapping!A:C,3,0) -> South | E6: =VLOOKUP(B6,Mapping!A:D,4,0) -> South 1 | F6: =VLOOKUP(B6,Mapping!A:E,5,0) -> Sulabh | G6: =VLOOKUP(B6,Mapping!A:F,6,0) -> Kunal | H6: 0 | I6: 0 | J6: 0 | K6: 0 | L6: 0 | M6: 5.11035 | N6: 0 | O6: 0 | P6: 0 | Q6: 0 | R6: 0 | S6: 11.87885 | T6: =SUM(H6:S6) -> 16.9892
A7: FY2025-26 | B7: Pidilite | C7: =VLOOKUP(B7,Mapping!A:B,2,0) -> Lateral | D7: =VLOOKUP(B7,Mapping!A:C,3,0) -> West | E7: =VLOOKUP(B7,Mapping!A:D,4,0) -> West 1 | F7: =VLOOKUP(B7,Mapping!A:E,5,0) -> Anjli | G7: =VLOOKUP(B7,Mapping!A:F,6,0) -> Usha | H7: 0 | I7: 0 | J7: 0 | K7: 0.195 | L7: 0 | M7: 3.355 | N7: 0 | O7: 0 | P7: 0.6 | Q7: 4.945 | R7: 2.32 | S7: 0.22 | T7: =SUM(H7:S7) -> 11.635
A8: FY2025-26 | B8: Vertiv | C8: =VLOOKUP(B8,Mapping!A:B,2,0) -> Lateral | D8: =VLOOKUP(B8,Mapping!A:C,3,0) -> West | E8: =VLOOKUP(B8,Mapping!A:D,4,0) -> West 2 | F8: =VLOOKUP(B8,Mapping!A:E,5,0) -> Anjli | G8: =VLOOKUP(B8,Mapping!A:F,6,0) -> Shweta | H8: 0 | I8: 0.633 | J8: 0 | K8: 0.03767 | L8: 0 | M8: 0.23222 | N8: 0 | O8: 0 | P8: 0.03767 | Q8: 1.49748 | R8: 0 | T8: =SUM(H8:S8) -> 2.43804
A9: FY2025-26 | B9: Birla Paints | C9: =VLOOKUP(B9,Mapping!A:B,2,0) -> Lateral | D9: =VLOOKUP(B9,Mapping!A:C,3,0) -> West | E9: =VLOOKUP(B9,Mapping!A:D,4,0) -> West 1 | F9: =VLOOKUP(B9,Mapping!A:E,5,0) -> Anjli | G9: =VLOOKUP(B9,Mapping!A:F,6,0) -> Geetu | H9: 0 | I9: 0.1275 | J9: 0 | K9: 0 | L9: 0 | M9: 0 | N9: 0 | O9: 1.81275 | P9: 0 | Q9: 0 | R9: 0 | T9: =SUM(H9:S9) -> 1.94025
A10: FY2025-26 | B10: Ingram Micro | C10: =VLOOKUP(B10,Mapping!A:B,2,0) -> Lateral | D10: =VLOOKUP(B10,Mapping!A:C,3,0) -> West | E10: =VLOOKUP(B10,Mapping!A:D,4,0) -> West 1 | F10: =VLOOKUP(B10,Mapping!A:E,5,0) -> Anjli | G10: =VLOOKUP(B10,Mapping!A:F,6,0) -> Geetu | H10: 0 | I10: 0 | J10: 0 | K10: 0.475 | L10: 0 | M10: 0.108 | N10: 0 | O10: 0 | P10: 1.707 | Q10: 2.2527 | R10: 0 | T10: =SUM(H10:S10) -> 4.5427
A11: FY2025-26 | B11: HPE | C11: =VLOOKUP(B11,Mapping!A:B,2,0) -> Lateral | D11: =VLOOKUP(B11,Mapping!A:C,3,0) -> South | E11: =VLOOKUP(B11,Mapping!A:D,4,0) -> South 1 | F11: =VLOOKUP(B11,Mapping!A:E,5,0) -> Mahak | G11: =VLOOKUP(B11,Mapping!A:F,6,0) -> Mahak | H11: 0 | I11: 5 | J11: 5 | K11: 5 | L11: 4.43 | M11: 0 | N11: 0 | O11: 0 | P11: 0 | Q11: 0 | R11: 0 | T11: =SUM(H11:S11) -> 19.43
A12: FY2025-26 | B12: Isuzu | C12: =VLOOKUP(B12,Mapping!A:B,2,0) -> Lateral | D12: =VLOOKUP(B12,Mapping!A:C,3,0) -> South | E12: =VLOOKUP(B12,Mapping!A:D,4,0) -> South 1 | F12: =VLOOKUP(B12,Mapping!A:E,5,0) -> Anjli | G12: =VLOOKUP(B12,Mapping!A:F,6,0) -> Satya | H12: 0 | I12: 0 | J12: 0 | K12: 0 | L12: 0 | M12: 0 | N12: 0.73 | O12: 1.3296 | P12: 0.456 | Q12: 0 | R12: 10.14698 | T12: =SUM(H12:S12) -> 12.66258
A13: FY2025-26 | B13: Mahindra Holidays | C13: =VLOOKUP(B13,Mapping!A:B,2,0) -> Lateral | D13: =VLOOKUP(B13,Mapping!A:C,3,0) -> West | E13: =VLOOKUP(B13,Mapping!A:D,4,0) -> West 1 | F13: =VLOOKUP(B13,Mapping!A:E,5,0) -> Anjli | G13: =VLOOKUP(B13,Mapping!A:F,6,0) -> Geetu | H13: 0 | I13: 0.632 | J13: 0 | K13: 0.46 | L13: 0 | M13: 0.359 | N13: 0.8 | O13: 0.14 | P13: 0 | Q13: 0 | R13: 0 | T13: =SUM(H13:S13) -> 2.391
A14: FY2025-26 | B14: BITS | C14: =VLOOKUP(B14,Mapping!A:B,2,0) -> Lateral | D14: =VLOOKUP(B14,Mapping!A:C,3,0) -> South | E14: =VLOOKUP(B14,Mapping!A:D,4,0) -> South 2 | F14: =VLOOKUP(B14,Mapping!A:E,5,0) -> Sulabh | G14: =VLOOKUP(B14,Mapping!A:F,6,0) -> Krishna | H14: 0 | I14: 0 | J14: 0 | K14: 0 | L14: 0 | M14: 0 | N14: 0 | O14: 0 | P14: 0 | Q14: 0 | R14: 0 | T14: =SUM(H14:S14) -> 0
A15: FY2025-26 | B15: M&M | C15: =VLOOKUP(B15,Mapping!A:B,2,0) -> Lateral | D15: =VLOOKUP(B15,Mapping!A:C,3,0) -> West | E15: =VLOOKUP(B15,Mapping!A:D,4,0) -> West 1 | F15: =VLOOKUP(B15,Mapping!A:E,5,0) -> Anjli | G15: =VLOOKUP(B15,Mapping!A:F,6,0) -> Dhriti | H15: 0 | I15: 0 | J15: 0 | K15: 0 | L15: 0 | M15: 0 | N15: 0 | O15: 0 | P15: 0 | Q15: 0 | R15: 3.74197 | T15: =SUM(H15:S15) -> 3.74197
A16: FY2025-26 | B16: P&G | C16: =VLOOKUP(B16,Mapping!A:B,2,0) -> Lateral | D16: =VLOOKUP(B16,Mapping!A:C,3,0) -> South | E16: =VLOOKUP(B16,Mapping!A:D,4,0) -> South 2 | F16: =VLOOKUP(B16,Mapping!A:E,5,0) -> Sulabh | G16: =VLOOKUP(B16,Mapping!A:F,6,0) -> Krishna | H16: 0 | I16: 0 | J16: 0 | K16: 0 | L16: 0 | M16: 0 | N16: 0 | O16: 0 | P16: 0 | Q16: 0 | R16: 0 | T16: =SUM(H16:S16) -> 0
A17: FY2025-26 | B17: Wipro | C17: =VLOOKUP(B17,Mapping!A:B,2,0) -> Lateral | D17: =VLOOKUP(B17,Mapping!A:C,3,0) -> South | E17: =VLOOKUP(B17,Mapping!A:D,4,0) -> South 1 | F17: =VLOOKUP(B17,Mapping!A:E,5,0) -> Sulabh | G17: =VLOOKUP(B17,Mapping!A:F,6,0) -> Subu | H17: 0 | I17: 0 | J17: 0 | K17: 0 | L17: 0 | M17: 0 | N17: 0 | O17: 0 | P17: 34.665 | Q17: 20.19 | R17: 15.7025 | S17: 22.9275 | T17: =SUM(H17:S17) -> 93.485
A18: FY2025-26 | B18: Tata Marcopolo | C18: =VLOOKUP(B18,Mapping!A:B,2,0) -> Lateral | D18: =VLOOKUP(B18,Mapping!A:C,3,0) -> West | E18: =VLOOKUP(B18,Mapping!A:D,4,0) -> West 2 | F18: =VLOOKUP(B18,Mapping!A:E,5,0) -> Anjli | G18: =VLOOKUP(B18,Mapping!A:F,6,0) -> Anjli | H18: 0 | I18: 0 | J18: 0 | K18: 0 | L18: 0 | M18: 0 | N18: 0 | O18: 0 | P18: 0 | Q18: 0 | R18: 0 | T18: =SUM(H18:S18) -> 0
A19: FY2025-26 | B19: DP World | C19: =VLOOKUP(B19,Mapping!A:B,2,0) -> Lateral | D19: =VLOOKUP(B19,Mapping!A:C,3,0) -> West | E19: =VLOOKUP(B19,Mapping!A:D,4,0) -> West 1 | F19: =VLOOKUP(B19,Mapping!A:E,5,0) -> Anjli | G19: =VLOOKUP(B19,Mapping!A:F,6,0) -> Geetu | H19: 0 | I19: 0 | J19: 0 | K19: 0 | L19: 0 | M19: 1.24446 | N19: 0 | O19: 0 | P19: 0 | Q19: 0.01889 | R19: 0 | T19: =SUM(H19:S19) -> 1.26335
A20: FY2025-26 | B20: Ametek | C20: =VLOOKUP(B20,Mapping!A:B,2,0) -> Lateral | D20: =VLOOKUP(B20,Mapping!A:C,3,0) -> South | E20: =VLOOKUP(B20,Mapping!A:D,4,0) -> South 1 | F20: =VLOOKUP(B20,Mapping!A:E,5,0) -> Sulabh | G20: =VLOOKUP(B20,Mapping!A:F,6,0) -> Satya | H20: 0 | I20: 0 | J20: 0 | K20: 0 | L20: 0 | M20: 0 | N20: 0 | O20: 0 | P20: 0 | Q20: 0 | R20: 0 | T20: =SUM(H20:S20) -> 0
A21: FY2025-26 | B21: AMNS | C21: =VLOOKUP(B21,Mapping!A:B,2,0) -> Lateral | D21: =VLOOKUP(B21,Mapping!A:C,3,0) -> West | E21: =VLOOKUP(B21,Mapping!A:D,4,0) -> West 1 | F21: =VLOOKUP(B21,Mapping!A:E,5,0) -> Anjli | G21: =VLOOKUP(B21,Mapping!A:F,6,0) -> Alifia | H21: 0 | I21: 2.16 | J21: 0 | K21: 12.625 | L21: 0 | M21: 0 | N21: 0 | O21: 0 | P21: 0 | Q21: 0 | R21: 0 | S21: 8.43 | T21: =SUM(H21:S21) -> 23.215
A22: FY2025-26 | B22: Tata Electronics | C22: =VLOOKUP(B22,Mapping!A:B,2,0) -> Lateral | D22: =VLOOKUP(B22,Mapping!A:C,3,0) -> South | E22: =VLOOKUP(B22,Mapping!A:D,4,0) -> South 2 | F22: =VLOOKUP(B22,Mapping!A:E,5,0) -> Sulabh | G22: =VLOOKUP(B22,Mapping!A:F,6,0) -> Subu | H22: 0 | I22: 0 | J22: 0 | K22: 0 | L22: 0.85 | M22: 2.82989 | N22: 0 | O22: 0 | P22: 0.24294 | Q22: 0 | R22: 1.99681 | T22: =SUM(H22:S22) -> 5.91964
A23: FY2025-26 | B23: Jindal Stainless | C23: =VLOOKUP(B23,Mapping!A:B,2,0) -> Lateral | D23: =VLOOKUP(B23,Mapping!A:C,3,0) -> North | E23: =VLOOKUP(B23,Mapping!A:D,4,0) -> North | F23: =VLOOKUP(B23,Mapping!A:E,5,0) -> Anjli | G23: =VLOOKUP(B23,Mapping!A:F,6,0) -> Archana | H23: 0 | I23: 0 | J23: 0 | K23: 0 | L23: 0 | M23: 0 | N23: 0 | O23: 0 | P23: 0 | Q23: 0 | R23: 0 | T23: =SUM(H23:S23) -> 0
A24: FY2025-26 | B24: Nomiso | C24: =VLOOKUP(B24,Mapping!A:B,2,0) -> Lateral | D24: =VLOOKUP(B24,Mapping!A:C,3,0) -> South | E24: =VLOOKUP(B24,Mapping!A:D,4,0) -> South 2 | F24: =VLOOKUP(B24,Mapping!A:E,5,0) -> Sulabh | G24: =VLOOKUP(B24,Mapping!A:F,6,0) -> Krishna | H24: 0 | I24: 0 | J24: 0 | K24: 0 | L24: 0 | M24: 0 | N24: 0 | O24: 0 | P24: 0 | Q24: 0 | R24: 0 | T24: =SUM(H24:S24) -> 0
A25: FY2025-26 | B25: Schaeffler | C25: =VLOOKUP(B25,Mapping!A:B,2,0) -> Lateral | D25: =VLOOKUP(B25,Mapping!A:C,3,0) -> West | E25: =VLOOKUP(B25,Mapping!A:D,4,0) -> West 2 | F25: =VLOOKUP(B25,Mapping!A:E,5,0) -> Anjli | G25: =VLOOKUP(B25,Mapping!A:F,6,0) -> Shweta | H25: 0 | I25: 0 | J25: 0 | K25: 0 | L25: 0 | M25: 0 | N25: 0 | O25: 0 | P25: 0 | Q25: 0 | R25: 0 | T25: =SUM(H25:S25) -> 0
A26: FY2025-26 | B26: Royal Enfield | C26: =VLOOKUP(B26,Mapping!A:B,2,0) -> Lateral | D26: =VLOOKUP(B26,Mapping!A:C,3,0) -> South | E26: =VLOOKUP(B26,Mapping!A:D,4,0) -> South 2 | F26: =VLOOKUP(B26,Mapping!A:E,5,0) -> Sulabh | G26: =VLOOKUP(B26,Mapping!A:F,6,0) -> Krishna | H26: 0 | I26: 0 | J26: 13.55 | K26: 0 | L26: 0 | M26: 0 | N26: 0 | O26: 0 | P26: 0 | Q26: 0 | R26: 3.27032 | T26: =SUM(H26:S26) -> 16.82032
A27: FY2025-26 | B27: SBI Card | C27: =VLOOKUP(B27,Mapping!A:B,2,0) -> Lateral | D27: =VLOOKUP(B27,Mapping!A:C,3,0) -> North | E27: =VLOOKUP(B27,Mapping!A:D,4,0) -> North | F27: =VLOOKUP(B27,Mapping!A:E,5,0) -> Anjli | G27: =VLOOKUP(B27,Mapping!A:F,6,0) -> Archana | H27: 0 | I27: 0 | J27: 0 | K27: 0 | L27: 0 | M27: 0 | N27: 0.2 | O27: 0 | P27: 0 | Q27: 0 | R27: 0 | T27: =SUM(H27:S27) -> 0.2
A28: FY2025-26 | B28: Hyundai Motor | C28: =VLOOKUP(B28,Mapping!A:B,2,0) -> Lateral | D28: =VLOOKUP(B28,Mapping!A:C,3,0) -> West | E28: =VLOOKUP(B28,Mapping!A:D,4,0) -> West 2 | F28: =VLOOKUP(B28,Mapping!A:E,5,0) -> Anjli | G28: =VLOOKUP(B28,Mapping!A:F,6,0) -> Shweta | H28: 0 | I28: 0 | J28: 0 | K28: 0 | L28: 0 | M28: 0 | N28: 0 | O28: 0 | P28: 0 | Q28: 0 | R28: 0 | S28: 20.8 | T28: =SUM(H28:S28) -> 20.8
A29: FY2025-26 | B29: Maruti Suzuki(MSIL) | C29: =VLOOKUP(B29,Mapping!A:B,2,0) -> Lateral | D29: =VLOOKUP(B29,Mapping!A:C,3,0) -> North | E29: =VLOOKUP(B29,Mapping!A:D,4,0) -> North | F29: =VLOOKUP(B29,Mapping!A:E,5,0) -> Anjli | G29: =VLOOKUP(B29,Mapping!A:F,6,0) -> Archana | H29: 0 | I29: 0 | J29: 0 | K29: 0 | L29: 0 | M29: 0 | N29: 0 | O29: 0 | P29: 0 | Q29: 42.83331 | R29: 1.02758 | T29: =SUM(H29:S29) -> 43.86089
A30: FY2025-26 | B30: Excelacom | C30: =VLOOKUP(B30,Mapping!A:B,2,0) -> Lateral | D30: =VLOOKUP(B30,Mapping!A:C,3,0) -> South | E30: =VLOOKUP(B30,Mapping!A:D,4,0) -> South 2 | F30: =VLOOKUP(B30,Mapping!A:E,5,0) -> Sulabh | G30: =VLOOKUP(B30,Mapping!A:F,6,0) -> Krishna | H30: 0 | I30: 0 | J30: 0 | K30: 0 | L30: 0 | M30: 0 | N30: 0 | O30: 0 | P30: 0.66 | Q30: 0 | R30: 0 | S30: 1.338 | T30: =SUM(H30:S30) -> 1.998
A31: FY2025-26 | B31: Tata Consumer | C31: =VLOOKUP(B31,Mapping!A:B,2,0) -> Lateral | D31: =VLOOKUP(B31,Mapping!A:C,3,0) -> West | E31: =VLOOKUP(B31,Mapping!A:D,4,0) -> West 1 | F31: =VLOOKUP(B31,Mapping!A:E,5,0) -> Anjli | G31: =VLOOKUP(B31,Mapping!A:F,6,0) -> Geetu | H31: 0 | I31: 0 | J31: 0 | K31: 0 | L31: 6.68 | M31: 0 | N31: 0 | O31: 0 | P31: 0 | Q31: 0 | R31: 0 | S31: 0.76847 | T31: =SUM(H31:S31) -> 7.44847
A32: FY2025-26 | B32: Tata Play | C32: =VLOOKUP(B32,Mapping!A:B,2,0) -> Lateral | D32: =VLOOKUP(B32,Mapping!A:C,3,0) -> West | E32: =VLOOKUP(B32,Mapping!A:D,4,0) -> West 1 | F32: =VLOOKUP(B32,Mapping!A:E,5,0) -> Anjli | G32: =VLOOKUP(B32,Mapping!A:F,6,0) -> Geetu | H32: 0 | I32: 0 | J32: 0 | K32: 0.452 | L32: 0.45 | M32: 0 | N32: 0 | O32: 0 | P32: 0 | Q32: 0 | R32: 0 | T32: =SUM(H32:S32) -> 0.902
A33: FY2025-26 | B33: Mahindra Finance | C33: =VLOOKUP(B33,Mapping!A:B,2,0) -> Lateral | D33: =VLOOKUP(B33,Mapping!A:C,3,0) -> West | E33: =VLOOKUP(B33,Mapping!A:D,4,0) -> West 1 | F33: =VLOOKUP(B33,Mapping!A:E,5,0) -> Anjli | G33: =VLOOKUP(B33,Mapping!A:F,6,0) -> Geetu | H33: 0 | I33: 0 | J33: 0 | K33: 0 | L33: 0 | M33: 0 | N33: 0 | O33: 0 | P33: 0 | Q33: 0 | R33: 0 | T33: =SUM(H33:S33) -> 0
A34: FY2025-26 | B34: Suzuki R&D | C34: =VLOOKUP(B34,Mapping!A:B,2,0) -> Lateral | D34: =VLOOKUP(B34,Mapping!A:C,3,0) -> North | E34: =VLOOKUP(B34,Mapping!A:D,4,0) -> North | F34: =VLOOKUP(B34,Mapping!A:E,5,0) -> Anjli | G34: =VLOOKUP(B34,Mapping!A:F,6,0) -> Archana | H34: 0 | I34: 0 | J34: 0 | K34: 0 | L34: 0 | M34: 0 | N34: 0 | O34: 0 | P34: 0 | Q34: 0 | R34: 1.267 | T34: =SUM(H34:S34) -> 1.267
A35: FY2025-26 | B35: Subros Ltd | C35: =VLOOKUP(B35,Mapping!A:B,2,0) -> Lateral | D35: =VLOOKUP(B35,Mapping!A:C,3,0) -> North | E35: =VLOOKUP(B35,Mapping!A:D,4,0) -> North | F35: =VLOOKUP(B35,Mapping!A:E,5,0) -> Anjli | G35: =VLOOKUP(B35,Mapping!A:F,6,0) -> Archana | H35: 0 | I35: 0 | J35: 0 | K35: 0 | L35: 0.5675 | M35: 0 | N35: 0 | O35: 3.536 | P35: 0 | Q35: 0 | R35: 0 | T35: =SUM(H35:S35) -> 4.1035
A36: FY2025-26 | B36: Atomberg Technologies | C36: =VLOOKUP(B36,Mapping!A:B,2,0) -> Lateral | D36: =VLOOKUP(B36,Mapping!A:C,3,0) -> West | E36: =VLOOKUP(B36,Mapping!A:D,4,0) -> West 1 | F36: =VLOOKUP(B36,Mapping!A:E,5,0) -> Anjli | G36: =VLOOKUP(B36,Mapping!A:F,6,0) -> Geetu | H36: 0 | I36: 0 | J36: 0 | K36: 0 | L36: 0 | M36: 0 | N36: 0 | O36: 0 | P36: 0 | Q36: 0 | R36: 0 | S36: 0.1276 | T36: =SUM(H36:S36) -> 0.1276
A37: FY2025-26 | B37: Bridgestone | C37: =VLOOKUP(B37,Mapping!A:B,2,0) -> Lateral | D37: =VLOOKUP(B37,Mapping!A:C,3,0) -> West | E37: =VLOOKUP(B37,Mapping!A:D,4,0) -> West 2 | F37: =VLOOKUP(B37,Mapping!A:E,5,0) -> Anjli | G37: =VLOOKUP(B37,Mapping!A:F,6,0) -> Shweta | H37: 0 | I37: 0 | J37: 0 | K37: 0 | L37: 0 | M37: 0 | N37: 0 | O37: 0 | P37: 0 | Q37: 0 | R37: 0 | S37: 0.24249 | T37: =SUM(H37:S37) -> 0.24249
A38: FY2025-26 | B38: Ambuja Cement | C38: =VLOOKUP(B38,Mapping!A:B,2,0) -> Lateral | D38: =VLOOKUP(B38,Mapping!A:C,3,0) -> West | E38: =VLOOKUP(B38,Mapping!A:D,4,0) -> West 1 | F38: =VLOOKUP(B38,Mapping!A:E,5,0) -> Anjli | G38: =VLOOKUP(B38,Mapping!A:F,6,0) -> Ankit | H38: 0 | I38: 0 | J38: 0 | K38: 0 | L38: 0 | M38: 0 | N38: 0 | O38: 0 | P38: 0 | Q38: 0 | R38: 2.08905 | T38: =SUM(H38:S38) -> 2.08905
A39: FY2025-26 | B39: Ashok Leyland | C39: =VLOOKUP(B39,Mapping!A:B,2,0) -> Lateral | D39: =VLOOKUP(B39,Mapping!A:C,3,0) -> South | E39: =VLOOKUP(B39,Mapping!A:D,4,0) -> South 2 | F39: =VLOOKUP(B39,Mapping!A:E,5,0) -> Sulabh | G39: =VLOOKUP(B39,Mapping!A:F,6,0) -> Krishna | H39: 0 | I39: 0.075 | J39: 0.075 | K39: 0 | L39: 1.07 | M39: 0 | N39: 2.12215 | O39: 3.83897 | P39: 0 | Q39: 0 | R39: 0 | T39: =SUM(H39:S39) -> 7.18112
A40: FY2025-26 | B40: Sterling Tools | C40: =VLOOKUP(B40,Mapping!A:B,2,0) -> Lateral | D40: =VLOOKUP(B40,Mapping!A:C,3,0) -> North | E40: =VLOOKUP(B40,Mapping!A:D,4,0) -> North | F40: =VLOOKUP(B40,Mapping!A:E,5,0) -> Anjli | G40: =VLOOKUP(B40,Mapping!A:F,6,0) -> Archana | H40: 0 | I40: 0 | J40: 0 | K40: 0 | L40: 1.20553 | M40: 0 | N40: 0 | O40: 0 | P40: 0 | Q40: 0 | R40: 0.20545 | T40: =SUM(H40:S40) -> 1.41098
A41: FY2025-26 | B41: M2P Fintech | C41: =VLOOKUP(B41,Mapping!A:B,2,0) -> Lateral | D41: =VLOOKUP(B41,Mapping!A:C,3,0) -> South | E41: =VLOOKUP(B41,Mapping!A:D,4,0) -> South 2 | F41: =VLOOKUP(B41,Mapping!A:E,5,0) -> Sulabh | G41: =VLOOKUP(B41,Mapping!A:F,6,0) -> Krishna | H41: 0 | I41: 0 | J41: 0 | K41: 2.8777 | L41: 1.8 | M41: 0 | N41: 0 | O41: 0.31492 | P41: 0 | Q41: 0 | R41: 0 | T41: =SUM(H41:S41) -> 4.99262
A42: FY2025-26 | B42: Tata Power | C42: =VLOOKUP(B42,Mapping!A:B,2,0) -> Lateral | D42: =VLOOKUP(B42,Mapping!A:C,3,0) -> West | E42: =VLOOKUP(B42,Mapping!A:D,4,0) -> West 1 | F42: =VLOOKUP(B42,Mapping!A:E,5,0) -> Anjli | G42: =VLOOKUP(B42,Mapping!A:F,6,0) -> Elton | H42: 0 | I42: 0 | J42: 0 | K42: 0 | L42: 0 | M42: 0 | N42: 0 | O42: 0 | P42: 0 | Q42: 0 | R42: 0 | T42: =SUM(H42:S42) -> 0
A43: FY2025-26 | B43: ThyssenKrupp | C43: =VLOOKUP(B43,Mapping!A:B,2,0) -> Lateral | D43: =VLOOKUP(B43,Mapping!A:C,3,0) -> West | E43: =VLOOKUP(B43,Mapping!A:D,4,0) -> West 2 | F43: =VLOOKUP(B43,Mapping!A:E,5,0) -> Anjli | G43: =VLOOKUP(B43,Mapping!A:F,6,0) -> Shweta | H43: 0 | I43: 0 | J43: 0 | K43: 0 | L43: 0 | M43: 0 | N43: 0 | O43: 0 | P43: 0 | Q43: 0 | R43: 0 | T43: =SUM(H43:S43) -> 0
A44: FY2025-26 | B44: Fedex | C44: =VLOOKUP(B44,Mapping!A:B,2,0) -> Lateral | D44: =VLOOKUP(B44,Mapping!A:C,3,0) -> West | E44: =VLOOKUP(B44,Mapping!A:D,4,0) -> West 1 | F44: =VLOOKUP(B44,Mapping!A:E,5,0) -> Anjli | G44: =VLOOKUP(B44,Mapping!A:F,6,0) -> Elton | H44: 0 | I44: 0 | J44: 0 | K44: 0 | L44: 0 | M44: 0 | N44: 0 | O44: 0 | P44: 0 | Q44: 0 | R44: 0 | T44: =SUM(H44:S44) -> 0
A45: FY2025-26 | B45: Titan | C45: =VLOOKUP(B45,Mapping!A:B,2,0) -> Lateral | D45: =VLOOKUP(B45,Mapping!A:C,3,0) -> South | E45: =VLOOKUP(B45,Mapping!A:D,4,0) -> South 2 | F45: =VLOOKUP(B45,Mapping!A:E,5,0) -> Sulabh | G45: =VLOOKUP(B45,Mapping!A:F,6,0) -> Subu | H45: 0 | I45: 0 | J45: 0 | K45: 0 | L45: 0 | M45: 0 | N45: 0 | O45: 0 | P45: 0 | Q45: 0 | R45: 0 | T45: =SUM(H45:S45) -> 0
A46: FY2025-26 | B46: Ultratech | C46: =VLOOKUP(B46,Mapping!A:B,2,0) -> Lateral | D46: =VLOOKUP(B46,Mapping!A:C,3,0) -> West | E46: =VLOOKUP(B46,Mapping!A:D,4,0) -> West 1 | F46: =VLOOKUP(B46,Mapping!A:E,5,0) -> Anjli | G46: =VLOOKUP(B46,Mapping!A:F,6,0) -> Elton | H46: 0 | I46: 0 | J46: 0 | K46: 0 | L46: 0 | M46: 0 | N46: 0 | O46: 0 | P46: 0 | Q46: 0 | R46: 0 | T46: =SUM(H46:S46) -> 0
A47: FY2025-26 | B47: L&T (New) | C47: =VLOOKUP(B47,Mapping!A:B,2,0) -> Lateral | D47: =VLOOKUP(B47,Mapping!A:C,3,0) -> South | E47: =VLOOKUP(B47,Mapping!A:D,4,0) -> South 2 | F47: =VLOOKUP(B47,Mapping!A:E,5,0) -> Sulabh | G47: =VLOOKUP(B47,Mapping!A:F,6,0) -> Sulabh | H47: 0 | I47: 0 | J47: 0 | K47: 0 | L47: 0 | M47: 0 | N47: 0 | O47: 0 | P47: 0 | Q47: 0 | R47: 0 | T47: =SUM(H47:S47) -> 0
A48: FY2025-26 | B48: DRL | C48: =VLOOKUP(B48,Mapping!A:B,2,0) -> Lateral | D48: =VLOOKUP(B48,Mapping!A:C,3,0) -> South | E48: =VLOOKUP(B48,Mapping!A:D,4,0) -> South 2 | F48: =VLOOKUP(B48,Mapping!A:E,5,0) -> Sulabh | G48: =VLOOKUP(B48,Mapping!A:F,6,0) -> Sulabh | H48: 0 | I48: 0 | J48: 0 | K48: 0 | L48: 0 | M48: 0 | N48: 0 | O48: 0 | P48: 0 | Q48: 0 | R48: 0 | T48: =SUM(H48:S48) -> 0
A49: FY2025-26 | B49: Robert Bosch | C49: =VLOOKUP(B49,Mapping!A:B,2,0) -> Lateral | D49: =VLOOKUP(B49,Mapping!A:C,3,0) -> South | E49: =VLOOKUP(B49,Mapping!A:D,4,0) -> South 2 | F49: =VLOOKUP(B49,Mapping!A:E,5,0) -> Sulabh | G49: =VLOOKUP(B49,Mapping!A:F,6,0) -> Abhilash | H49: 0 | I49: 0 | J49: 0 | K49: 0 | L49: 0 | M49: 0 | N49: 0 | O49: 0 | P49: 0 | Q49: 0 | R49: 0 | T49: =SUM(H49:S49) -> 0
... A51: FY2025-26 | B51: Honeywell Leadership | C51: =VLOOKUP(B51,Mapping!A:B,2,0) -> Leadership | D51: =VLOOKUP(B51,Mapping!A:C,3,0) -> South | E51: =VLOOKUP(B51,Mapping!A:D,4,0) -> South 1 | F51: =VLOOKUP(B51,Mapping!A:E,5,0) -> Bapi | G51: =VLOOKUP(B51,Mapping!A:F,6,0) -> Parul | H51: 0 | I51: 0 | J51: 0 | K51: 0 | L51: 0 | M51: 0 | N51: 0 | O51: 3 | P51: 0 | Q51: 0 | R51: 0 | T51: =SUM(H51:S51) -> 3
A52: FY2025-26 | B52: Siemens Leadership | C52: =VLOOKUP(B52,Mapping!A:B,2,0) -> Leadership | D52: =VLOOKUP(B52,Mapping!A:C,3,0) -> South | E52: =VLOOKUP(B52,Mapping!A:D,4,0) -> South 2 | F52: =VLOOKUP(B52,Mapping!A:E,5,0) -> Sulabh | G52: =VLOOKUP(B52,Mapping!A:F,6,0) -> Parul | H52: 0 | I52: 0 | J52: 0 | K52: 0 | L52: 0 | M52: 0 | N52: 0 | O52: 0 | P52: 0.09 | Q52: 0 | R52: 0.35 | S52: 0.14 | T52: =SUM(H52:S52) -> 0.58
A53: FY2025-26 | B53: Vertiv Leadership | C53: =VLOOKUP(B53,Mapping!A:B,2,0) -> Leadership | D53: =VLOOKUP(B53,Mapping!A:C,3,0) -> West | E53: =VLOOKUP(B53,Mapping!A:D,4,0) -> West 2 | F53: =VLOOKUP(B53,Mapping!A:E,5,0) -> Anjli | G53: =VLOOKUP(B53,Mapping!A:F,6,0) -> Parul | H53: 0 | I53: 0 | J53: 0 | K53: 0 | L53: 0 | M53: 0 | N53: 0 | O53: 1.70662 | P53: 0 | Q53: 0.03767 | R53: 0 | T53: =SUM(H53:S53) -> 1.74429
A54: FY2025-26 | B54: M&M Leadership | C54: =VLOOKUP(B54,Mapping!A:B,2,0) -> Leadership | D54: =VLOOKUP(B54,Mapping!A:C,3,0) -> West | E54: =VLOOKUP(B54,Mapping!A:D,4,0) -> West 1 | F54: =VLOOKUP(B54,Mapping!A:E,5,0) -> Anjli | G54: =VLOOKUP(B54,Mapping!A:F,6,0) -> Parul | H54: 0 | I54: 0 | J54: 0 | K54: 0 | L54: 0 | M54: 0 | N54: 0 | O54: 0 | P54: 0 | Q54: 0 | R54: 0 | T54: =SUM(H54:S54) -> 0
A55: FY2025-26 | B55: AMNS Leadership | C55: =VLOOKUP(B55,Mapping!A:B,2,0) -> Leadership | D55: =VLOOKUP(B55,Mapping!A:C,3,0) -> West | E55: =VLOOKUP(B55,Mapping!A:D,4,0) -> West 1 | F55: =VLOOKUP(B55,Mapping!A:E,5,0) -> Anjli | G55: =VLOOKUP(B55,Mapping!A:F,6,0) -> Parul | H55: 0 | I55: 0 | J55: 0 | K55: 0 | L55: 0 | M55: 0 | N55: 0 | O55: 0 | P55: 4.33 | Q55: 0 | R55: 0 | T55: =SUM(H55:S55) -> 4.33
A56: FY2025-26 | B56: Nagarjuna Leadership | C56: =VLOOKUP(B56,Mapping!A:B,2,0) -> Leadership | D56: =VLOOKUP(B56,Mapping!A:C,3,0) -> South | E56: =VLOOKUP(B56,Mapping!A:D,4,0) -> South 2 | F56: =VLOOKUP(B56,Mapping!A:E,5,0) -> Sulabh | G56: =VLOOKUP(B56,Mapping!A:F,6,0) -> Parul | H56: 0 | I56: 0 | J56: 0 | K56: 0 | L56: 0 | M56: 0 | N56: 0 | O56: 0 | P56: 0 | Q56: 0 | R56: 1 | S56: 1.5 | T56: =SUM(H56:S56) -> 2.5
A57: FY2025-26 | B57: Royal Enfield Leadership | C57: =VLOOKUP(B57,Mapping!A:B,2,0) -> Leadership | D57: =VLOOKUP(B57,Mapping!A:C,3,0) -> South | E57: =VLOOKUP(B57,Mapping!A:D,4,0) -> South 2 | F57: =VLOOKUP(B57,Mapping!A:E,5,0) -> Sulabh | G57: =VLOOKUP(B57,Mapping!A:F,6,0) -> Parul | H57: 0 | I57: 0 | J57: 0 | K57: 0 | L57: 0 | M57: 0 | N57: 0 | O57: 0 | P57: 0 | Q57: 0 | R57: -1.62 | T57: =SUM(H57:S57) -> -1.62
A58: FY2025-26 | B58: Sterling Tools Leadership | C58: =VLOOKUP(B58,Mapping!A:B,2,0) -> Leadership | D58: =VLOOKUP(B58,Mapping!A:C,3,0) -> North | E58: =VLOOKUP(B58,Mapping!A:D,4,0) -> North | F58: =VLOOKUP(B58,Mapping!A:E,5,0) -> Anjli | G58: =VLOOKUP(B58,Mapping!A:F,6,0) -> Parul | H58: 0 | I58: 0 | J58: 0 | K58: 0 | L58: 1 | M58: 0 | N58: 0 | O58: 0 | P58: 0 | Q58: 0 | R58: 0 | T58: =SUM(H58:S58) -> 1
A59: FY2025-26 | B59: Mahindra Holidays Leadership | C59: =VLOOKUP(B59,Mapping!A:B,2,0) -> Leadership | D59: =VLOOKUP(B59,Mapping!A:C,3,0) -> West | E59: =VLOOKUP(B59,Mapping!A:D,4,0) -> West 1 | F59: =VLOOKUP(B59,Mapping!A:E,5,0) -> Anjli | G59: =VLOOKUP(B59,Mapping!A:F,6,0) -> Parul | H59: 0 | I59: 0 | J59: 0 | K59: 0 | L59: 0 | M59: 0 | N59: 0 | O59: 0 | P59: 0 | Q59: 0 | R59: 0 | T59: =SUM(H59:S59) -> 0
A60: FY2025-26 | B60: Hyundai Motor Leadership | C60: =VLOOKUP(B60,Mapping!A:B,2,0) -> Leadership | D60: =VLOOKUP(B60,Mapping!A:C,3,0) -> West | E60: =VLOOKUP(B60,Mapping!A:D,4,0) -> West 2 | F60: =VLOOKUP(B60,Mapping!A:E,5,0) -> Anjli | G60: =VLOOKUP(B60,Mapping!A:F,6,0) -> Parul | H60: 0 | I60: 0 | J60: 0 | K60: 0 | L60: 0 | M60: 0 | N60: 0 | O60: 0 | P60: 0 | Q60: 0 | R60: 0 | T60: =SUM(H60:S60) -> 0
A61: FY2025-26 | B61: JINDAL STAINLESS Leadership | C61: =VLOOKUP(B61,Mapping!A:B,2,0) -> Leadership | D61: =VLOOKUP(B61,Mapping!A:C,3,0) -> North | E61: =VLOOKUP(B61,Mapping!A:D,4,0) -> North | F61: =VLOOKUP(B61,Mapping!A:E,5,0) -> Anjli | G61: =VLOOKUP(B61,Mapping!A:F,6,0) -> Parul | H61: 0 | I61: 0 | J61: 0 | K61: 0 | L61: 0 | M61: 0 | N61: 0 | O61: 0 | P61: 0 | Q61: 0 | R61: 0 | T61: =SUM(H61:S61) -> 0
A62: FY2025-26 | B62: SUZUKI R&D Leadership | C62: =VLOOKUP(B62,Mapping!A:B,2,0) -> Leadership | D62: =VLOOKUP(B62,Mapping!A:C,3,0) -> North | E62: =VLOOKUP(B62,Mapping!A:D,4,0) -> North | F62: =VLOOKUP(B62,Mapping!A:E,5,0) -> Anjli | G62: =VLOOKUP(B62,Mapping!A:F,6,0) -> Parul | H62: 0 | I62: 0 | J62: 0 | K62: 0 | L62: 0 | M62: 0 | N62: 0 | O62: 0 | P62: 0 | Q62: 0 | R62: 0 | T62: =SUM(H62:S62) -> 0
A63: FY2025-26 | B63: Pfizer Leadership | C63: =VLOOKUP(B63,Mapping!A:B,2,0) -> Leadership | D63: =VLOOKUP(B63,Mapping!A:C,3,0) -> West | E63: =VLOOKUP(B63,Mapping!A:D,4,0) -> West 1 | F63: =VLOOKUP(B63,Mapping!A:E,5,0) -> Anjli | G63: =VLOOKUP(B63,Mapping!A:F,6,0) -> Parul | H63: 0 | I63: 0 | J63: 0.67 | K63: 0 | L63: 0 | M63: 0 | N63: 0 | O63: 0 | P63: 0 | Q63: 0 | R63: 0 | T63: =SUM(H63:S63) -> 0.67
A64: FY2025-26 | B64: Subros Leadership | C64: =VLOOKUP(B64,Mapping!A:B,2,0) -> Leadership | D64: =VLOOKUP(B64,Mapping!A:C,3,0) -> North | E64: =VLOOKUP(B64,Mapping!A:D,4,0) -> North | F64: =VLOOKUP(B64,Mapping!A:E,5,0) -> Anjli | G64: =VLOOKUP(B64,Mapping!A:F,6,0) -> Parul | H64: 0 | I64: 0 | J64: 0 | K64: 0 | L64: 0.7 | M64: 0 | N64: 0 | O64: 0 | P64: 0 | Q64: 0.4 | R64: 0 | T64: =SUM(H64:S64) -> 1.1
A65: FY2025-26 | B65: Optum | C65: =VLOOKUP(B65,Mapping!A:B,2,0) -> Lateral | D65: =VLOOKUP(B65,Mapping!A:C,3,0) -> South | E65: =VLOOKUP(B65,Mapping!A:D,4,0) -> South 1 | F65: =VLOOKUP(B65,Mapping!A:E,5,0) -> Ashish | G65: =VLOOKUP(B65,Mapping!A:F,6,0) -> Ashish | H65: 0 | I65: 0 | J65: 0 | K65: 0 | L65: 0 | M65: 0 | N65: 0 | O65: 0 | P65: 0 | Q65: 0 | R65: 0 | T65: =SUM(H65:S65) -> 0
A66: FY2025-26 | B66: New Sales + Mining | C66: =VLOOKUP(B66,Mapping!A:B,2,0) -> Lateral | D66: =VLOOKUP(B66,Mapping!A:C,3,0) -> New Sales | E66: =VLOOKUP(B66,Mapping!A:D,4,0) -> New Sales | F66: =VLOOKUP(B66,Mapping!A:E,5,0) -> Nizar | G66: =VLOOKUP(B66,Mapping!A:F,6,0) -> Nizar | H66: 0 | I66: 0 | J66: 0 | K66: 0 | L66: 0 | M66: 0 | N66: 0 | O66: 0 | P66: 0 | Q66: 0 | R66: 0 | T66: =SUM(H66:S66) -> 0
A67: FY2025-26 | B67: Pernod Ricard | C67: =VLOOKUP(B67,Mapping!A:B,2,0) -> Lateral | D67: =VLOOKUP(B67,Mapping!A:C,3,0) -> North | E67: =VLOOKUP(B67,Mapping!A:D,4,0) -> North | F67: =VLOOKUP(B67,Mapping!A:E,5,0) -> Anjli | G67: =VLOOKUP(B67,Mapping!A:F,6,0) -> Archana | H67: 0 | I67: 0 | J67: 0 | K67: 0 | L67: 0 | M67: 0 | N67: 0 | O67: 0 | P67: 0 | Q67: 0 | R67: 0 | S67: 0.265 | T67: =SUM(H67:S67) -> 0.265
A68: FY2025-26 | B68: UniCharm | C68: =VLOOKUP(B68,Mapping!A:B,2,0) -> Lateral | D68: =VLOOKUP(B68,Mapping!A:C,3,0) -> North | E68: =VLOOKUP(B68,Mapping!A:D,4,0) -> North | F68: =VLOOKUP(B68,Mapping!A:E,5,0) -> Anjli | G68: =VLOOKUP(B68,Mapping!A:F,6,0) -> Archana | H68: 0 | I68: 0 | J68: 0 | K68: 0 | L68: 0 | M68: 0 | N68: 0 | O68: 0 | P68: 0 | Q68: 0 | R68: 0 | T68: =SUM(H68:S68) -> 0
A69: FY2025-26 | B69: Saint Gobain | C69: =VLOOKUP(B69,Mapping!A:B,2,0) -> #N/A | D69: =VLOOKUP(B69,Mapping!A:C,3,0) -> #N/A | E69: =VLOOKUP(B69,Mapping!A:D,4,0) -> #N/A | F69: =VLOOKUP(B69,Mapping!A:E,5,0) -> #N/A | G69: =VLOOKUP(B69,Mapping!A:F,6,0) -> #N/A | H69: 0 | I69: 0 | J69: 0 | K69: 0 | L69: 0 | M69: 0 | N69: 0 | O69: 0 | P69: 0 | Q69: 0 | R69: 0 | T69: =SUM(H69:S69) -> 0
A70: FY2025-26 | B70: Leap India | C70: =VLOOKUP(B70,Mapping!A:B,2,0) -> Lateral | D70: =VLOOKUP(B70,Mapping!A:C,3,0) -> West | E70: =VLOOKUP(B70,Mapping!A:D,4,0) -> West 1 | F70: =VLOOKUP(B70,Mapping!A:E,5,0) -> Anjli | G70: =VLOOKUP(B70,Mapping!A:F,6,0) -> Geetu | H70: 0 | I70: 0 | J70: 0 | K70: 1.884 | L70: 0 | M70: 0 | N70: 0 | O70: 0 | P70: 0 | Q70: 0 | R70: 0.37728 | S70: 0.51496 | T70: =SUM(H70:S70) -> 2.77624
A71: FY2025-26 | B71: NeoSoft | C71: =VLOOKUP(B71,Mapping!A:B,2,0) -> Lateral | D71: =VLOOKUP(B71,Mapping!A:C,3,0) -> West | E71: =VLOOKUP(B71,Mapping!A:D,4,0) -> West 1 | F71: =VLOOKUP(B71,Mapping!A:E,5,0) -> Anjli | G71: =VLOOKUP(B71,Mapping!A:F,6,0) -> Archana | H71: 0 | I71: 0 | J71: 0 | K71: 0 | L71: 0 | M71: 0 | N71: 0 | O71: 0 | P71: 0 | Q71: 0 | R71: 0 | S71: 4.18883 | T71: =SUM(H71:S71) -> 4.18883
A72: FY2025-26 | B72: Siemens Healthnier | C72: =VLOOKUP(B72,Mapping!A:B,2,0) -> Lateral | D72: =VLOOKUP(B72,Mapping!A:C,3,0) -> South | E72: =VLOOKUP(B72,Mapping!A:D,4,0) -> South 2 | F72: =VLOOKUP(B72,Mapping!A:E,5,0) -> Sulabh | G72: =VLOOKUP(B72,Mapping!A:F,6,0) -> Lekhana | H72: 0 | I72: 0 | J72: 0 | K72: 0 | L72: 0 | M72: 0.36 | N72: 0 | O72: 0 | P72: 0 | Q72: 0 | R72: 0 | T72: =SUM(H72:S72) -> 0.36
A73: FY2025-26 | B73: ABB | C73: =VLOOKUP(B73,Mapping!A:B,2,0) -> Lateral | D73: =VLOOKUP(B73,Mapping!A:C,3,0) -> South | E73: =VLOOKUP(B73,Mapping!A:D,4,0) -> South 2 | F73: =VLOOKUP(B73,Mapping!A:E,5,0) -> Sulabh | G73: =VLOOKUP(B73,Mapping!A:F,6,0) -> Satya | H73: 0 | I73: 0.05 | J73: 0 | K73: 0 | L73: 0 | M73: 0 | N73: 0 | O73: 0.49875 | P73: 0 | Q73: 0 | R73: 0 | T73: =SUM(H73:S73) -> 0.54875
A74: FY2025-26 | B74: TCG Group | C74: =VLOOKUP(B74,Mapping!A:B,2,0) -> Lateral | D74: =VLOOKUP(B74,Mapping!A:C,3,0) -> West | E74: =VLOOKUP(B74,Mapping!A:D,4,0) -> West 1 | F74: =VLOOKUP(B74,Mapping!A:E,5,0) -> Anjli | G74: =VLOOKUP(B74,Mapping!A:F,6,0) -> Anjli | H74: 0 | I74: 0 | J74: 0 | K74: 0 | L74: 0 | M74: 0 | N74: 0 | O74: 0 | P74: 0 | Q74: 0 | R74: 0 | T74: =SUM(H74:S74) -> 0
A75: FY2025-26 | B75: Proterial | C75: =VLOOKUP(B75,Mapping!A:B,2,0) -> #N/A | D75: =VLOOKUP(B75,Mapping!A:C,3,0) -> #N/A | E75: =VLOOKUP(B75,Mapping!A:D,4,0) -> #N/A | F75: =VLOOKUP(B75,Mapping!A:E,5,0) -> #N/A | G75: =VLOOKUP(B75,Mapping!A:F,6,0) -> #N/A | H75: 0 | I75: 0 | J75: 0 | K75: 0 | L75: 0 | M75: 0 | N75: 0 | O75: 0 | P75: 0 | Q75: 0 | R75: 0 | T75: =SUM(H75:S75) -> 0
A76: FY2025-26 | B76: CG Power | C76: =VLOOKUP(B76,Mapping!A:B,2,0) -> Lateral | D76: =VLOOKUP(B76,Mapping!A:C,3,0) -> West | E76: =VLOOKUP(B76,Mapping!A:D,4,0) -> West 1 | F76: =VLOOKUP(B76,Mapping!A:E,5,0) -> Anjli | G76: =VLOOKUP(B76,Mapping!A:F,6,0) -> Anjli | H76: 0 | I76: 0 | J76: 0 | K76: 0 | L76: 0 | M76: 0 | N76: 0 | O76: 0 | P76: 0 | Q76: 0 | R76: 0 | T76: =SUM(H76:S76) -> 0
A77: FY2025-26 | B77: Triveni | C77: Exclusive | D77: Exclusive | E77: Exclusive | F77: Amit Jain | G77: Naved | R77: 0.07331 | T77: =SUM(H77:S77) -> 0.07331
A78: FY2025-26 | B78: Dag Exclusive | C78: Exclusive | D78: Exclusive | E78: Exclusive | F78: Amit Jain | G78: Naved | S78: 1.04958 | T78: =SUM(H78:S78) -> 1.04958

Sheet Headcount_Overall
H1: =SUM(H3:H86) -> 578.33 | I1: =SUM(I3:I86) -> 549.9 | J1: =SUM(J3:J86) -> 545 | K1: =SUM(K3:K86) -> 515.5 | L1: =SUM(L3:L86) -> 517 | M1: =SUM(M3:M86) -> 536.2 | N1: =SUM(N3:N86) -> 531 | O1: =SUM(O3:O86) -> 537 | ... S1: =SUM(S3:S86) -> 596
A2: =Revenue_Budget!A1 -> FY | B2: =Revenue_Budget!B1 -> Project | C2: =Revenue_Budget!C1 -> Vertical | D2: =Revenue_Budget!D1 -> Region | E2: =Revenue_Budget!E1 -> Sub Region | F2: =Revenue_Budget!F1 -> Region Head | G2: =Revenue_Budget!G1 -> Practice Head | H2: =Revenue_Budget!H1 -> 45748 | ... S2: =Revenue_Budget!S1 -> 46082
A3: FY2025-26 | B3: Honeywell | C3: =VLOOKUP(B3,Mapping!A:B,2,0) -> Lateral | D3: =VLOOKUP(B3,Mapping!A:C,3,0) -> South | E3: =VLOOKUP(B3,Mapping!A:D,4,0) -> South 1 | F3: =VLOOKUP(B3,Mapping!A:E,5,0) -> Bapi | G3: =VLOOKUP(B3,Mapping!A:F,6,0) -> Bapi | H3: 64.7 | I3: 68 | J3: 63.8 | K3: 60 | L3: 60.6 | M3: 60.5 | N3: 60.5 | O3: 60.5 | P3: 58 | Q3: 59 | R3: 59.5 | S3: 60.4
A4: FY2025-26 | B4: Pfizer | C4: =VLOOKUP(B4,Mapping!A:B,2,0) -> Lateral | D4: =VLOOKUP(B4,Mapping!A:C,3,0) -> West | E4: =VLOOKUP(B4,Mapping!A:D,4,0) -> West 1 | F4: =VLOOKUP(B4,Mapping!A:E,5,0) -> Anjli | G4: =VLOOKUP(B4,Mapping!A:F,6,0) -> Usha | H4: 6.3 | I4: 7.05 | J4: 6.3 | K4: 6.2 | L4: 5.2 | M4: 5.2 | N4: 5.2 | O4: 4.5 | P4: 4.5 | Q4: 4.5 | R4: 4.5 | S4: 4.5
A5: FY2025-26 | B5: Tata Motors | C5: =VLOOKUP(B5,Mapping!A:B,2,0) -> Lateral | D5: =VLOOKUP(B5,Mapping!A:C,3,0) -> West | E5: =VLOOKUP(B5,Mapping!A:D,4,0) -> West 2 | F5: =VLOOKUP(B5,Mapping!A:E,5,0) -> Anjli | G5: =VLOOKUP(B5,Mapping!A:F,6,0) -> Shweta | H5: 0 | I5: 1.65 | J5: 1.7 | K5: - | L5: - | M5: - | N5: - | O5: - | P5: - | Q5: 0 | R5: 0 | S5: 0
A6: FY2025-26 | B6: SKF India | C6: =VLOOKUP(B6,Mapping!A:B,2,0) -> Lateral | D6: =VLOOKUP(B6,Mapping!A:C,3,0) -> North | E6: =VLOOKUP(B6,Mapping!A:D,4,0) -> North | F6: =VLOOKUP(B6,Mapping!A:E,5,0) -> Anjli | G6: =VLOOKUP(B6,Mapping!A:F,6,0) -> Archana | H6: 14 | I6: 15.3 | J6: 15.4 | K6: 14.1 | L6: 14.1 | M6: 14.85 | N6: 15.1 | O6: 16.1 | P6: 15.1 | Q6: 16.3 | R6: 16.5 | S6: 16.5
A7: FY2025-26 | B7: Siemens | C7: =VLOOKUP(B7,Mapping!A:B,2,0) -> Lateral | D7: =VLOOKUP(B7,Mapping!A:C,3,0) -> South | E7: =VLOOKUP(B7,Mapping!A:D,4,0) -> South 1 | F7: =VLOOKUP(B7,Mapping!A:E,5,0) -> Sulabh | G7: =VLOOKUP(B7,Mapping!A:F,6,0) -> Kunal | H7: 13.9 | I7: 12.9 | J7: 14.5 | K7: 12.5 | L7: 12.5 | M7: 12.5 | N7: 12.5 | O7: 12.5 | P7: 12.5 | Q7: 12.5 | R7: 14.5 | S7: 15.5
A8: FY2025-26 | B8: Pidilite | C8: =VLOOKUP(B8,Mapping!A:B,2,0) -> Lateral | D8: =VLOOKUP(B8,Mapping!A:C,3,0) -> West | E8: =VLOOKUP(B8,Mapping!A:D,4,0) -> West 1 | F8: =VLOOKUP(B8,Mapping!A:E,5,0) -> Anjli | G8: =VLOOKUP(B8,Mapping!A:F,6,0) -> Usha | H8: 10 | I8: 8.8 | J8: 9.8 | K8: 7.7 | L8: 8.7 | M8: 7.7 | N8: 10.7 | O8: 10 | P8: 8.6 | Q8: 12.2 | R8: 13.2 | S8: 13.15
A9: FY2025-26 | B9: Vertiv | C9: =VLOOKUP(B9,Mapping!A:B,2,0) -> Lateral | D9: =VLOOKUP(B9,Mapping!A:C,3,0) -> West | E9: =VLOOKUP(B9,Mapping!A:D,4,0) -> West 2 | F9: =VLOOKUP(B9,Mapping!A:E,5,0) -> Anjli | G9: =VLOOKUP(B9,Mapping!A:F,6,0) -> Shweta | H9: 4.6 | I9: 4.1 | J9: 3.6 | K9: 3.1 | L9: 3.1 | M9: 2.1 | N9: 2.1 | O9: 2.1 | P9: 2.1 | Q9: 2.1 | R9: 2.1 | S9: 3
A10: FY2025-26 | B10: Birla Paints | C10: =VLOOKUP(B10,Mapping!A:B,2,0) -> Lateral | D10: =VLOOKUP(B10,Mapping!A:C,3,0) -> West | E10: =VLOOKUP(B10,Mapping!A:D,4,0) -> West 1 | F10: =VLOOKUP(B10,Mapping!A:E,5,0) -> Anjli | G10: =VLOOKUP(B10,Mapping!A:F,6,0) -> Geetu | H10: 10.2 | I10: 10.15 | J10: 10.15 | K10: 11.15 | L10: 9.65 | M10: 10.65 | N10: 10.65 | O10: 11.15 | P10: 11.6 | Q10: 11.65 | R10: 11.65 | S10: 11.65
A11: FY2025-26 | B11: Ingram Micro | C11: =VLOOKUP(B11,Mapping!A:B,2,0) -> Lateral | D11: =VLOOKUP(B11,Mapping!A:C,3,0) -> West | E11: =VLOOKUP(B11,Mapping!A:D,4,0) -> West 1 | F11: =VLOOKUP(B11,Mapping!A:E,5,0) -> Anjli | G11: =VLOOKUP(B11,Mapping!A:F,6,0) -> Geetu | H11: 3.8 | I11: 3.8 | J11: 3.8 | K11: 2.7 | L11: 2.7 | M11: 1.7 | N11: 1.7 | O11: 1.5 | P11: 1.5 | Q11: 1 | R11: 0 | S11: 0
A12: FY2025-26 | B12: HPE | C12: =VLOOKUP(B12,Mapping!A:B,2,0) -> Lateral | D12: =VLOOKUP(B12,Mapping!A:C,3,0) -> South | E12: =VLOOKUP(B12,Mapping!A:D,4,0) -> South 1 | F12: =VLOOKUP(B12,Mapping!A:E,5,0) -> Mahak | G12: =VLOOKUP(B12,Mapping!A:F,6,0) -> Mahak | H12: 52 | I12: 49 | J12: 49 | K12: 48.5 | L12: 45.5 | M12: 45.5 | N12: 45.5 | O12: 45.5 | P12: 45.5 | Q12: 48 | R12: 50.5 | S12: 50.9
A13: FY2025-26 | B13: Isuzu | C13: =VLOOKUP(B13,Mapping!A:B,2,0) -> Lateral | D13: =VLOOKUP(B13,Mapping!A:C,3,0) -> South | E13: =VLOOKUP(B13,Mapping!A:D,4,0) -> South 1 | F13: =VLOOKUP(B13,Mapping!A:E,5,0) -> Anjli | G13: =VLOOKUP(B13,Mapping!A:F,6,0) -> Satya | H13: 4.34 | I13: 4.3333333 | J13: 4.3333333 | K13: 4.3333333 | L13: 3.3333333 | M13: 3.34 | N13: 3.34 | O13: 3.34 | P13: 3.34 | Q13: 3.34 | R13: 3.34 | S13: 2.84
A14: FY2025-26 | B14: Mahindra Holidays | C14: =VLOOKUP(B14,Mapping!A:B,2,0) -> Lateral | D14: =VLOOKUP(B14,Mapping!A:C,3,0) -> West | E14: =VLOOKUP(B14,Mapping!A:D,4,0) -> West 1 | F14: =VLOOKUP(B14,Mapping!A:E,5,0) -> Anjli | G14: =VLOOKUP(B14,Mapping!A:F,6,0) -> Geetu | H14: 10.3 | I14: 10.25 | J14: 11.25 | K14: 8.15 | L14: 9.15 | M14: 9.15 | N14: 8.15 | O14: 8.15 | P14: 9.2 | Q14: 8 | R14: 8 | S14: 9
A15: FY2025-26 | B15: BITS | C15: =VLOOKUP(B15,Mapping!A:B,2,0) -> Lateral | D15: =VLOOKUP(B15,Mapping!A:C,3,0) -> South | E15: =VLOOKUP(B15,Mapping!A:D,4,0) -> South 2 | F15: =VLOOKUP(B15,Mapping!A:E,5,0) -> Sulabh | G15: =VLOOKUP(B15,Mapping!A:F,6,0) -> Krishna | H15: 3.1 | I15: 3.1 | J15: 3.1 | K15: 3.1 | L15: 3.1 | M15: 3.1 | N15: 3.1 | O15: 3 | P15: 3.3 | Q15: 3.5 | R15: 3.5 | S15: 3.5
A16: FY2025-26 | B16: M&M | C16: =VLOOKUP(B16,Mapping!A:B,2,0) -> Lateral | D16: =VLOOKUP(B16,Mapping!A:C,3,0) -> West | E16: =VLOOKUP(B16,Mapping!A:D,4,0) -> West 1 | F16: =VLOOKUP(B16,Mapping!A:E,5,0) -> Anjli | G16: =VLOOKUP(B16,Mapping!A:F,6,0) -> Dhriti | H16: 67.5 | I16: 59.5 | J16: 60 | K16: 58 | L16: 69 | M16: 78 | N16: 79 | O16: 76 | P16: 75 | Q16: 74 | R16: 84 | S16: 72
A17: FY2025-26 | B17: P&G | C17: =VLOOKUP(B17,Mapping!A:B,2,0) -> Lateral | D17: =VLOOKUP(B17,Mapping!A:C,3,0) -> South | E17: =VLOOKUP(B17,Mapping!A:D,4,0) -> South 2 | F17: =VLOOKUP(B17,Mapping!A:E,5,0) -> Sulabh | G17: =VLOOKUP(B17,Mapping!A:F,6,0) -> Krishna | H17: 3 | I17: 2 | J17: 2 | K17: 1 | L17: 1 | M17: - | N17: - | O17: - | P17: - | Q17: 0 | R17: 0 | S17: 0
A18: FY2025-26 | B18: Wipro | C18: =VLOOKUP(B18,Mapping!A:B,2,0) -> Lateral | D18: =VLOOKUP(B18,Mapping!A:C,3,0) -> South | E18: =VLOOKUP(B18,Mapping!A:D,4,0) -> South 1 | F18: =VLOOKUP(B18,Mapping!A:E,5,0) -> Sulabh | G18: =VLOOKUP(B18,Mapping!A:F,6,0) -> Subu | H18: 13 | I18: 12.7 | J18: 13 | K18: 13 | L18: 14 | M18: 13 | N18: 12 | O18: 18 | P18: 18 | Q18: 19 | R18: 19 | S18: 16
A19: FY2025-26 | B19: Tata Marcopolo | C19: =VLOOKUP(B19,Mapping!A:B,2,0) -> Lateral | D19: =VLOOKUP(B19,Mapping!A:C,3,0) -> West | E19: =VLOOKUP(B19,Mapping!A:D,4,0) -> West 2 | F19: =VLOOKUP(B19,Mapping!A:E,5,0) -> Anjli | G19: =VLOOKUP(B19,Mapping!A:F,6,0) -> Anjli | H19: 1 | I19: - | J19: - | K19: - | L19: - | M19: - | N19: - | O19: - | P19: - | Q19: 0 | R19: 0 | S19: 0
A20: FY2025-26 | B20: DP World | C20: =VLOOKUP(B20,Mapping!A:B,2,0) -> Lateral | D20: =VLOOKUP(B20,Mapping!A:C,3,0) -> West | E20: =VLOOKUP(B20,Mapping!A:D,4,0) -> West 1 | F20: =VLOOKUP(B20,Mapping!A:E,5,0) -> Anjli | G20: =VLOOKUP(B20,Mapping!A:F,6,0) -> Geetu | H20: 13.66 | I20: 12.7 | J20: 10.25 | K20: 11.15 | L20: 8.65 | M20: 7.65 | N20: 7.65 | O20: 7.15 | P20: 6.1 | Q20: 5.15 | R20: 5.15 | S20: 4.15
A21: FY2025-26 | B21: Ametek | C21: =VLOOKUP(B21,Mapping!A:B,2,0) -> Lateral | D21: =VLOOKUP(B21,Mapping!A:C,3,0) -> South | E21: =VLOOKUP(B21,Mapping!A:D,4,0) -> South 1 | F21: =VLOOKUP(B21,Mapping!A:E,5,0) -> Sulabh | G21: =VLOOKUP(B21,Mapping!A:F,6,0) -> Satya | H21: 1.33 | I21: 1.3333333 | J21: 1.3333333 | K21: 1.3333333 | L21: 1.3333333 | M21: 1.33 | N21: 1.33 | O21: 0.33 | P21: 0.33 | Q21: 0.33 | R21: 0.33 | S21: 0.33
A22: FY2025-26 | B22: AMNS | C22: =VLOOKUP(B22,Mapping!A:B,2,0) -> Lateral | D22: =VLOOKUP(B22,Mapping!A:C,3,0) -> West | E22: =VLOOKUP(B22,Mapping!A:D,4,0) -> West 1 | F22: =VLOOKUP(B22,Mapping!A:E,5,0) -> Anjli | G22: =VLOOKUP(B22,Mapping!A:F,6,0) -> Alifia | H22: 33.1 | I22: 33.1 | J22: 33.1 | K22: 30 | L22: 29 | M22: 28 | N22: 28 | O22: 29 | P22: 31 | Q22: 34 | R22: 38.5 | S22: 38
A23: FY2025-26 | B23: Tata Electronics | C23: =VLOOKUP(B23,Mapping!A:B,2,0) -> Lateral | D23: =VLOOKUP(B23,Mapping!A:C,3,0) -> South | E23: =VLOOKUP(B23,Mapping!A:D,4,0) -> South 2 | F23: =VLOOKUP(B23,Mapping!A:E,5,0) -> Sulabh | G23: =VLOOKUP(B23,Mapping!A:F,6,0) -> Subu | H23: 6.5 | I23: 8.3 | J23: 5.1 | K23: 4.1 | L23: 4.2 | M23: 5.2 | N23: 4.2 | O23: 4 | P23: 3.2 | Q23: 3 | R23: 3 | S23: 2
A24: FY2025-26 | B24: Jindal Stainless | C24: =VLOOKUP(B24,Mapping!A:B,2,0) -> Lateral | D24: =VLOOKUP(B24,Mapping!A:C,3,0) -> North | E24: =VLOOKUP(B24,Mapping!A:D,4,0) -> North | F24: =VLOOKUP(B24,Mapping!A:E,5,0) -> Anjli | G24: =VLOOKUP(B24,Mapping!A:F,6,0) -> Archana | H24: 6.1 | I24: 5.1 | J24: 5.1 | K24: 5.1 | L24: 6.1 | M24: 6.2 | N24: 6.2 | O24: 6.75 | P24: 6.7 | Q24: 7.45 | R24: 6.45 | S24: 6.45
A25: FY2025-26 | B25: Nomiso | C25: =VLOOKUP(B25,Mapping!A:B,2,0) -> Lateral | D25: =VLOOKUP(B25,Mapping!A:C,3,0) -> South | E25: =VLOOKUP(B25,Mapping!A:D,4,0) -> South 2 | F25: =VLOOKUP(B25,Mapping!A:E,5,0) -> Sulabh | G25: =VLOOKUP(B25,Mapping!A:F,6,0) -> Krishna | Q25: 0 | R25: 0 | S25: 0
A26: FY2025-26 | B26: Schaeffler | C26: =VLOOKUP(B26,Mapping!A:B,2,0) -> Lateral | D26: =VLOOKUP(B26,Mapping!A:C,3,0) -> West | E26: =VLOOKUP(B26,Mapping!A:D,4,0) -> West 2 | F26: =VLOOKUP(B26,Mapping!A:E,5,0) -> Anjli | G26: =VLOOKUP(B26,Mapping!A:F,6,0) -> Shweta | H26: 7.55 | I26: 4.8 | J26: 4.8 | K26: 5.3 | L26: 5.1 | M26: 6.1 | N26: 6.1 | O26: 5.1 | P26: 5.1 | Q26: 5.1 | R26: 5.1 | S26: 6
A27: FY2025-26 | B27: Royal Enfield | C27: =VLOOKUP(B27,Mapping!A:B,2,0) -> Lateral | D27: =VLOOKUP(B27,Mapping!A:C,3,0) -> South | E27: =VLOOKUP(B27,Mapping!A:D,4,0) -> South 2 | F27: =VLOOKUP(B27,Mapping!A:E,5,0) -> Sulabh | G27: =VLOOKUP(B27,Mapping!A:F,6,0) -> Krishna | H27: 6.1 | I27: 5.1 | J27: 5.1 | K27: 5.1 | L27: 5.1 | M27: 11.2 | N27: 10.2 | O27: 9.5 | P27: 13 | Q27: 17.33 | R27: 18.4 | S27: 20.7
A28: FY2025-26 | B28: SBI Card | C28: =VLOOKUP(B28,Mapping!A:B,2,0) -> Lateral | D28: =VLOOKUP(B28,Mapping!A:C,3,0) -> North | E28: =VLOOKUP(B28,Mapping!A:D,4,0) -> North | F28: =VLOOKUP(B28,Mapping!A:E,5,0) -> Anjli | G28: =VLOOKUP(B28,Mapping!A:F,6,0) -> Archana | H28: 13 | I28: 13.5 | J28: 13.7 | K28: 14.3 | L28: 14.3 | M28: 18.3 | N28: 18.3 | O28: 17.35 | P28: 17.65 | Q28: 15.4 | R28: 14.4 | S28: 13.4
A29: FY2025-26 | B29: Hyundai Motor | C29: =VLOOKUP(B29,Mapping!A:B,2,0) -> Lateral | D29: =VLOOKUP(B29,Mapping!A:C,3,0) -> West | E29: =VLOOKUP(B29,Mapping!A:D,4,0) -> West 2 | F29: =VLOOKUP(B29,Mapping!A:E,5,0) -> Anjli | G29: =VLOOKUP(B29,Mapping!A:F,6,0) -> Shweta | H29: 16.15 | I29: 12.6 | J29: 10.4 | K29: 9.6 | L29: 10.6 | M29: 10.6 | N29: 9.4 | O29: 10.4 | P29: 8.4 | Q29: 6.4 | R29: 6.4 | S29: 7
A30: FY2025-26 | B30: Maruti Suzuki(MSIL) | C30: =VLOOKUP(B30,Mapping!A:B,2,0) -> Lateral | D30: =VLOOKUP(B30,Mapping!A:C,3,0) -> North | E30: =VLOOKUP(B30,Mapping!A:D,4,0) -> North | F30: =VLOOKUP(B30,Mapping!A:E,5,0) -> Anjli | G30: =VLOOKUP(B30,Mapping!A:F,6,0) -> Archana | H30: 52.4 | I30: 45.65 | J30: 44.2 | K30: 40.9 | L30: 40 | M30: 39 | N30: 39 | O30: 39.5 | P30: 39.2 | Q30: 37.75 | R30: 33.85 | S30: 33.85
A31: FY2025-26 | B31: Excelacom | C31: =VLOOKUP(B31,Mapping!A:B,2,0) -> Lateral | D31: =VLOOKUP(B31,Mapping!A:C,3,0) -> South | E31: =VLOOKUP(B31,Mapping!A:D,4,0) -> South 2 | F31: =VLOOKUP(B31,Mapping!A:E,5,0) -> Sulabh | G31: =VLOOKUP(B31,Mapping!A:F,6,0) -> Krishna | H31: 3 | I31: 0 | J31: 1 | K31: 1 | L31: 1 | M31: - | N31: - | O31: - | P31: - | Q31: 0 | R31: 0 | S31: 0
A32: FY2025-26 | B32: Tata Consumer | C32: =VLOOKUP(B32,Mapping!A:B,2,0) -> Lateral | D32: =VLOOKUP(B32,Mapping!A:C,3,0) -> West | E32: =VLOOKUP(B32,Mapping!A:D,4,0) -> West 1 | F32: =VLOOKUP(B32,Mapping!A:E,5,0) -> Anjli | G32: =VLOOKUP(B32,Mapping!A:F,6,0) -> Geetu | H32: 17.3 | I32: 15.3 | J32: 15.3 | K32: 14.2 | L32: 14.2 | M32: 14.2 | N32: 14.2 | O32: 14 | P32: 13.1 | Q32: 15.2 | R32: 14.2 | S32: 16.2
A33: FY2025-26 | B33: Tata Play | C33: =VLOOKUP(B33,Mapping!A:B,2,0) -> Lateral | D33: =VLOOKUP(B33,Mapping!A:C,3,0) -> West | E33: =VLOOKUP(B33,Mapping!A:D,4,0) -> West 1 | F33: =VLOOKUP(B33,Mapping!A:E,5,0) -> Anjli | G33: =VLOOKUP(B33,Mapping!A:F,6,0) -> Geetu | H33: 1.3 | I33: 1.3 | J33: 1.3 | K33: 1.2 | L33: 2.2 | M33: 1.2 | N33: 1.2 | O33: 1 | P33: 1 | Q33: 1 | R33: 1 | S33: 1
A34: FY2025-26 | B34: Mahindra Finance | C34: =VLOOKUP(B34,Mapping!A:B,2,0) -> Lateral | D34: =VLOOKUP(B34,Mapping!A:C,3,0) -> West | E34: =VLOOKUP(B34,Mapping!A:D,4,0) -> West 1 | F34: =VLOOKUP(B34,Mapping!A:E,5,0) -> Anjli | G34: =VLOOKUP(B34,Mapping!A:F,6,0) -> Geetu | H34: 7.8 | I34: 6.25 | J34: 5.25 | K34: 2.15 | L34: 1.15 | M34: 1.45 | N34: 1.45 | O34: 1.45 | P34: 1.5 | Q34: 0 | R34: 0 | S34: 0
A35: FY2025-26 | B35: Suzuki R&D | C35: =VLOOKUP(B35,Mapping!A:B,2,0) -> Lateral | D35: =VLOOKUP(B35,Mapping!A:C,3,0) -> North | E35: =VLOOKUP(B35,Mapping!A:D,4,0) -> North | F35: =VLOOKUP(B35,Mapping!A:E,5,0) -> Anjli | G35: =VLOOKUP(B35,Mapping!A:F,6,0) -> Archana | H35: 2 | I35: 2 | J35: 2 | K35: 2 | L35: 2 | M35: 2 | N35: 1 | O35: 1 | P35: 1 | Q35: 0.1 | R35: 1 | S35: 1
A36: FY2025-26 | B36: Subros Ltd | C36: =VLOOKUP(B36,Mapping!A:B,2,0) -> Lateral | D36: =VLOOKUP(B36,Mapping!A:C,3,0) -> North | E36: =VLOOKUP(B36,Mapping!A:D,4,0) -> North | F36: =VLOOKUP(B36,Mapping!A:E,5,0) -> Anjli | G36: =VLOOKUP(B36,Mapping!A:F,6,0) -> Archana | H36: 2.5 | I36: 2.6 | J36: 2.6 | K36: 3.35 | L36: 3.6 | M36: 3.6 | N36: 3.6 | O36: 4.65 | P36: 3.75 | Q36: 3.65 | R36: 3.65 | S36: 3.65
A37: FY2025-26 | B37: Atomberg Technologies | C37: =VLOOKUP(B37,Mapping!A:B,2,0) -> Lateral | D37: =VLOOKUP(B37,Mapping!A:C,3,0) -> West | E37: =VLOOKUP(B37,Mapping!A:D,4,0) -> West 1 | F37: =VLOOKUP(B37,Mapping!A:E,5,0) -> Anjli | G37: =VLOOKUP(B37,Mapping!A:F,6,0) -> Geetu | H37: 6.3 | I37: 5.25 | J37: 6.25 | K37: 5.15 | L37: 5.15 | M37: 5.15 | N37: 5.15 | O37: 5.15 | P37: 5.1 | Q37: 5.15 | R37: 5.15 | S37: 5.15
A38: FY2025-26 | B38: Bridgestone | C38: =VLOOKUP(B38,Mapping!A:B,2,0) -> Lateral | D38: =VLOOKUP(B38,Mapping!A:C,3,0) -> West | E38: =VLOOKUP(B38,Mapping!A:D,4,0) -> West 2 | F38: =VLOOKUP(B38,Mapping!A:E,5,0) -> Anjli | G38: =VLOOKUP(B38,Mapping!A:F,6,0) -> Shweta | H38: 4.2 | I38: 2.2 | J38: 1.7 | K38: 2.2 | L38: 3.4 | M38: 4.4 | N38: 3.4 | O38: 2.4 | P38: 2.4 | Q38: 2.4 | R38: 3.4 | S38: 3
A39: FY2025-26 | B39: Ambuja Cement | C39: =VLOOKUP(B39,Mapping!A:B,2,0) -> Lateral | D39: =VLOOKUP(B39,Mapping!A:C,3,0) -> West | E39: =VLOOKUP(B39,Mapping!A:D,4,0) -> West 1 | F39: =VLOOKUP(B39,Mapping!A:E,5,0) -> Anjli | G39: =VLOOKUP(B39,Mapping!A:F,6,0) -> Ankit | H39: 24 | I39: 24 | J39: 22 | K39: 21 | L39: 20 | M39: 19 | N39: 19 | O39: 22 | P39: 24 | Q39: 25 | R39: 25 | S39: 23
A40: FY2025-26 | B40: Ashok Leyland | C40: =VLOOKUP(B40,Mapping!A:B,2,0) -> Lateral | D40: =VLOOKUP(B40,Mapping!A:C,3,0) -> South | E40: =VLOOKUP(B40,Mapping!A:D,4,0) -> South 2 | F40: =VLOOKUP(B40,Mapping!A:E,5,0) -> Sulabh | G40: =VLOOKUP(B40,Mapping!A:F,6,0) -> Krishna | H40: 12.3 | I40: 12.3 | J40: 14.1 | K40: 14.1 | L40: 13.5 | M40: 16.5 | N40: 15.5 | O40: 16.5 | P40: 14.5 | Q40: 15.5 | R40: 14.75 | S40: 13.65
A41: FY2025-26 | B41: Sterling Tools | C41: =VLOOKUP(B41,Mapping!A:B,2,0) -> Lateral | D41: =VLOOKUP(B41,Mapping!A:C,3,0) -> North | E41: =VLOOKUP(B41,Mapping!A:D,4,0) -> North | F41: =VLOOKUP(B41,Mapping!A:E,5,0) -> Anjli | G41: =VLOOKUP(B41,Mapping!A:F,6,0) -> Archana | H41: 7 | I41: 6.3 | J41: 6.3 | K41: 5.45 | L41: 5.2 | M41: 4.45 | N41: 4.15 | O41: 4.2 | P41: 4.3 | Q41: 4.25 | R41: 4.15 | S41: 4.15
A42: FY2025-26 | B42: M2P Fintech | C42: =VLOOKUP(B42,Mapping!A:B,2,0) -> Lateral | D42: =VLOOKUP(B42,Mapping!A:C,3,0) -> South | E42: =VLOOKUP(B42,Mapping!A:D,4,0) -> South 2 | F42: =VLOOKUP(B42,Mapping!A:E,5,0) -> Sulabh | G42: =VLOOKUP(B42,Mapping!A:F,6,0) -> Krishna | H42: 5 | I42: 4.1 | J42: 5.1 | K42: 5.1 | L42: 4 | M42: 0 | N42: 0 | O42: 0 | P42: 1 | Q42: 1 | R42: 1 | S42: 1
A43: FY2025-26 | B43: Tata Power | C43: =VLOOKUP(B43,Mapping!A:B,2,0) -> Lateral | D43: =VLOOKUP(B43,Mapping!A:C,3,0) -> West | E43: =VLOOKUP(B43,Mapping!A:D,4,0) -> West 1 | F43: =VLOOKUP(B43,Mapping!A:E,5,0) -> Anjli | G43: =VLOOKUP(B43,Mapping!A:F,6,0) -> Elton | H43: 0 | I43: 0 | J43: 0 | K43: 0 | L43: 0 | M43: 0 | N43: 0 | O43: 0 | P43: 0 | Q43: 0 | R43: 0 | S43: 0
... A48: FY2025-26 | B48: L&T (New) | C48: =VLOOKUP(B48,Mapping!A:B,2,0) -> Lateral | D48: =VLOOKUP(B48,Mapping!A:C,3,0) -> South | E48: =VLOOKUP(B48,Mapping!A:D,4,0) -> South 2 | F48: =VLOOKUP(B48,Mapping!A:E,5,0) -> Sulabh | G48: =VLOOKUP(B48,Mapping!A:F,6,0) -> Sulabh | H48: 0 | I48: 0 | J48: 0 | K48: 0 | L48: 0 | M48: 0 | N48: 0 | O48: 0 | P48: 0 | Q48: 0 | R48: 0 | S48: 0
A49: FY2025-26 | B49: DRL | C49: =VLOOKUP(B49,Mapping!A:B,2,0) -> Lateral | D49: =VLOOKUP(B49,Mapping!A:C,3,0) -> South | E49: =VLOOKUP(B49,Mapping!A:D,4,0) -> South 2 | F49: =VLOOKUP(B49,Mapping!A:E,5,0) -> Sulabh | G49: =VLOOKUP(B49,Mapping!A:F,6,0) -> Sulabh | H49: 0 | I49: 0 | J49: 0 | L49: 0 | M49: 0 | N49: 0 | O49: 0 | P49: 0 | Q49: 0 | R49: 0 | S49: 0
A50: FY2025-26 | B50: Robert Bosch | C50: =VLOOKUP(B50,Mapping!A:B,2,0) -> Lateral | D50: =VLOOKUP(B50,Mapping!A:C,3,0) -> South | E50: =VLOOKUP(B50,Mapping!A:D,4,0) -> South 2 | F50: =VLOOKUP(B50,Mapping!A:E,5,0) -> Sulabh | G50: =VLOOKUP(B50,Mapping!A:F,6,0) -> Abhilash | H50: 0 | I50: 0 | J50: 0 | K50: 0 | L50: 0 | M50: 0 | N50: 0 | O50: 0 | P50: 0 | Q50: 0 | R50: 0 | S50: 0
A51: FY2025-26 | B51: Tata Teleservices | C51: =VLOOKUP(B51,Mapping!A:B,2,0) -> Lateral | D51: =VLOOKUP(B51,Mapping!A:C,3,0) -> West | E51: =VLOOKUP(B51,Mapping!A:D,4,0) -> West 1 | F51: =VLOOKUP(B51,Mapping!A:E,5,0) -> Anjli | G51: =VLOOKUP(B51,Mapping!A:F,6,0) -> Elton | Q51: 0 | R51: 0 | S51: 0
A52: FY2025-26 | B52: Honeywell Leadership | C52: =VLOOKUP(B52,Mapping!A:B,2,0) -> Leadership | D52: =VLOOKUP(B52,Mapping!A:C,3,0) -> South | E52: =VLOOKUP(B52,Mapping!A:D,4,0) -> South 1 | F52: =VLOOKUP(B52,Mapping!A:E,5,0) -> Bapi | G52: =VLOOKUP(B52,Mapping!A:F,6,0) -> Parul | H52: 1.5 | I52: 2.5 | J52: 2.5 | K52: 2.5 | L52: 2.5 | M52: 2.5 | N52: 2.5 | O52: 1.5 | P52: 2.5 | Q52: 2.5 | R52: 2 | S52: 0
A53: FY2025-26 | B53: Siemens Leadership | C53: =VLOOKUP(B53,Mapping!A:B,2,0) -> Leadership | D53: =VLOOKUP(B53,Mapping!A:C,3,0) -> South | E53: =VLOOKUP(B53,Mapping!A:D,4,0) -> South 2 | F53: =VLOOKUP(B53,Mapping!A:E,5,0) -> Sulabh | G53: =VLOOKUP(B53,Mapping!A:F,6,0) -> Parul | H53: 0 | I53: 0 | J53: 0 | K53: 0.5 | L53: 0.5 | M53: 0.5 | N53: 0 | O53: 0 | P53: 0 | Q53: 0 | R53: 0 | S53: 0
A54: FY2025-26 | B54: Vertiv Leadership | C54: =VLOOKUP(B54,Mapping!A:B,2,0) -> Leadership | D54: =VLOOKUP(B54,Mapping!A:C,3,0) -> West | E54: =VLOOKUP(B54,Mapping!A:D,4,0) -> West 2 | F54: =VLOOKUP(B54,Mapping!A:E,5,0) -> Anjli | G54: =VLOOKUP(B54,Mapping!A:F,6,0) -> Parul | H54: 0.5 | I54: 0.5 | J54: 0.5 | K54: 0.5 | L54: 0.5 | M54: 0.5 | N54: 0.33 | O54: 0.33 | P54: 0.33 | Q54: 0.33 | R54: 0.2 | S54: 0.2
A55: FY2025-26 | B55: M&M Leadership | C55: =VLOOKUP(B55,Mapping!A:B,2,0) -> Leadership | D55: =VLOOKUP(B55,Mapping!A:C,3,0) -> West | E55: =VLOOKUP(B55,Mapping!A:D,4,0) -> West 1 | F55: =VLOOKUP(B55,Mapping!A:E,5,0) -> Anjli | G55: =VLOOKUP(B55,Mapping!A:F,6,0) -> Parul | H55: 4.5 | I55: 4.75 | J55: 6 | K55: 7.8 | L55: 6.8 | M55: 5.5 | N55: 6.5 | O55: 10.5 | P55: 11.5 | Q55: 12.5 | R55: 1 | S55: 12.5
A56: FY2025-26 | B56: AMNS Leadership | C56: =VLOOKUP(B56,Mapping!A:B,2,0) -> Leadership | D56: =VLOOKUP(B56,Mapping!A:C,3,0) -> West | E56: =VLOOKUP(B56,Mapping!A:D,4,0) -> West 1 | F56: =VLOOKUP(B56,Mapping!A:E,5,0) -> Anjli | G56: =VLOOKUP(B56,Mapping!A:F,6,0) -> Parul | H56: 2 | I56: 2 | J56: 2 | K56: 2 | L56: 2 | M56: 2 | N56: 2 | O56: 2 | P56: 2 | Q56: 2 | R56: 0 | S56: 0
A57: FY2025-26 | B57: Nagarjuna Leadership | C57: =VLOOKUP(B57,Mapping!A:B,2,0) -> Leadership | D57: =VLOOKUP(B57,Mapping!A:C,3,0) -> South | E57: =VLOOKUP(B57,Mapping!A:D,4,0) -> South 2 | F57: =VLOOKUP(B57,Mapping!A:E,5,0) -> Sulabh | G57: =VLOOKUP(B57,Mapping!A:F,6,0) -> Parul | H57: 0 | I57: 0 | J57: 0 | K57: 0 | L57: 0 | M57: 0 | N57: 0 | O57: 0 | P57: 0 | Q57: 0 | R57: 0 | S57: 0.2
A58: FY2025-26 | B58: Royal Enfield Leadership | C58: =VLOOKUP(B58,Mapping!A:B,2,0) -> Leadership | D58: =VLOOKUP(B58,Mapping!A:C,3,0) -> South | E58: =VLOOKUP(B58,Mapping!A:D,4,0) -> South 2 | F58: =VLOOKUP(B58,Mapping!A:E,5,0) -> Sulabh | G58: =VLOOKUP(B58,Mapping!A:F,6,0) -> Parul | H58: 0.5 | I58: 0.5 | J58: 0.5 | K58: 0 | L58: 0 | M58: 0 | N58: 0.34 | O58: 0.34 | P58: 0.34 | Q58: 0.34 | R58: 0.2 | S58: 0.2
A59: FY2025-26 | B59: Sterling Tools Leadership | C59: =VLOOKUP(B59,Mapping!A:B,2,0) -> Leadership | D59: =VLOOKUP(B59,Mapping!A:C,3,0) -> North | E59: =VLOOKUP(B59,Mapping!A:D,4,0) -> North | F59: =VLOOKUP(B59,Mapping!A:E,5,0) -> Anjli | G59: =VLOOKUP(B59,Mapping!A:F,6,0) -> Parul | H59: 0.5 | I59: 0.5 | J59: 0.5 | K59: 0 | L59: 0 | M59: 0 | N59: 0 | O59: 0 | P59: 0 | Q59: 0 | R59: 0 | S59: 0
A60: FY2025-26 | B60: Mahindra Holidays Leadership | C60: =VLOOKUP(B60,Mapping!A:B,2,0) -> Leadership | D60: =VLOOKUP(B60,Mapping!A:C,3,0) -> West | E60: =VLOOKUP(B60,Mapping!A:D,4,0) -> West 1 | F60: =VLOOKUP(B60,Mapping!A:E,5,0) -> Anjli | G60: =VLOOKUP(B60,Mapping!A:F,6,0) -> Parul | H60: 0 | I60: 0 | J60: 0 | K60: 0.5 | L60: 0 | M60: 0.5 | N60: 0.83 | O60: 0.83 | P60: 0.83 | Q60: 0.83 | R60: 0 | S60: 0
A61: FY2025-26 | B61: Hyundai Motor Leadership | C61: =VLOOKUP(B61,Mapping!A:B,2,0) -> Leadership | D61: =VLOOKUP(B61,Mapping!A:C,3,0) -> West | E61: =VLOOKUP(B61,Mapping!A:D,4,0) -> West 2 | F61: =VLOOKUP(B61,Mapping!A:E,5,0) -> Anjli | G61: =VLOOKUP(B61,Mapping!A:F,6,0) -> Parul | H61: 0.5 | I61: 0.5 | J61: 0.5 | K61: 0.5 | L61: 0.5 | M61: 0.5 | N61: 0.5 | O61: 0.5 | P61: 0.5 | Q61: 0.5 | R61: 0.2 | S61: 0
A62: FY2025-26 | B62: JINDAL STAINLESS Leadership | C62: =VLOOKUP(B62,Mapping!A:B,2,0) -> Leadership | D62: =VLOOKUP(B62,Mapping!A:C,3,0) -> North | E62: =VLOOKUP(B62,Mapping!A:D,4,0) -> North | F62: =VLOOKUP(B62,Mapping!A:E,5,0) -> Anjli | G62: =VLOOKUP(B62,Mapping!A:F,6,0) -> Parul | H62: 0 | I62: 0 | J62: 0 | K62: 0 | L62: 0 | M62: 0 | N62: 0 | O62: 0 | P62: 0 | Q62: 0 | R62: 0 | S62: 0
A63: FY2025-26 | B63: SUZUKI R&D Leadership | C63: =VLOOKUP(B63,Mapping!A:B,2,0) -> Leadership | D63: =VLOOKUP(B63,Mapping!A:C,3,0) -> North | E63: =VLOOKUP(B63,Mapping!A:D,4,0) -> North | F63: =VLOOKUP(B63,Mapping!A:E,5,0) -> Anjli | G63: =VLOOKUP(B63,Mapping!A:F,6,0) -> Parul | H63: 0 | I63: 0 | J63: 0 | K63: 0 | L63: 0 | M63: 0 | N63: 0 | O63: 0 | P63: 0 | Q63: 0 | R63: 0 | S63: 0
... A71: FY2025-26 | B71: Leap India | C71: =VLOOKUP(B71,Mapping!A:B,2,0) -> Lateral | D71: =VLOOKUP(B71,Mapping!A:C,3,0) -> West | E71: =VLOOKUP(B71,Mapping!A:D,4,0) -> West 1 | F71: =VLOOKUP(B71,Mapping!A:E,5,0) -> Anjli | G71: =VLOOKUP(B71,Mapping!A:F,6,0) -> Geetu | H71: 0 | I71: 1.8 | J71: 8.25 | K71: 10.25 | L71: 10.25 | M71: 8.95 | N71: 9.95 | O71: 6.95 | P71: 6.8 | Q71: 8.15 | R71: 8.15 | S71: 7.2
A72: FY2025-26 | B72: NeoSoft | C72: =VLOOKUP(B72,Mapping!A:B,2,0) -> Lateral | D72: =VLOOKUP(B72,Mapping!A:C,3,0) -> West | E72: =VLOOKUP(B72,Mapping!A:D,4,0) -> West 1 | F72: =VLOOKUP(B72,Mapping!A:E,5,0) -> Anjli | G72: =VLOOKUP(B72,Mapping!A:F,6,0) -> Archana | H72: - | I72: - | J72: - | K72: - | L72: - | M72: - | N72: - | O72: 2 | P72: 3.5 | Q72: 6 | R72: 7 | S72: 8
A73: FY2025-26 | B73: Siemens Healthnier | C73: =VLOOKUP(B73,Mapping!A:B,2,0) -> Lateral | D73: =VLOOKUP(B73,Mapping!A:C,3,0) -> South | E73: =VLOOKUP(B73,Mapping!A:D,4,0) -> South 2 | F73: =VLOOKUP(B73,Mapping!A:E,5,0) -> Sulabh | G73: =VLOOKUP(B73,Mapping!A:F,6,0) -> Lekhana | H73: 8 | I73: 7 | J73: 7 | K73: 5 | L73: 6 | M73: 6 | N73: 5 | O73: 5 | P73: 5 | Q73: 6 | R73: 5 | S73: 5
A74: FY2025-26 | B74: ABB | C74: =VLOOKUP(B74,Mapping!A:B,2,0) -> Lateral | D74: =VLOOKUP(B74,Mapping!A:C,3,0) -> South | E74: =VLOOKUP(B74,Mapping!A:D,4,0) -> South 2 | F74: =VLOOKUP(B74,Mapping!A:E,5,0) -> Sulabh | G74: =VLOOKUP(B74,Mapping!A:F,6,0) -> Satya | H74: 5 | I74: 7.3333333 | J74: 5.3333333 | K74: 4.3333333 | L74: 4.3333333 | M74: 4.33 | N74: 3.33 | O74: 3.33 | P74: 4.33 | Q74: 3.33 | R74: 3.33 | S74: 5.33
A75: FY2025-26 | B75: TCG Group | C75: =VLOOKUP(B75,Mapping!A:B,2,0) -> Lateral | D75: =VLOOKUP(B75,Mapping!A:C,3,0) -> West | E75: =VLOOKUP(B75,Mapping!A:D,4,0) -> West 1 | F75: =VLOOKUP(B75,Mapping!A:E,5,0) -> Anjli | G75: =VLOOKUP(B75,Mapping!A:F,6,0) -> Anjli | H75: 0 | I75: 0 | J75: 0 | K75: 0 | L75: 0 | M75: 0 | N75: 0 | O75: 0 | P75: 0 | Q75: 0 | R75: 0 | S75: 0
A76: FY2025-26 | B76: Metglas | C76: =VLOOKUP(B76,Mapping!A:B,2,0) -> Lateral | D76: =VLOOKUP(B76,Mapping!A:C,3,0) -> West | E76: =VLOOKUP(B76,Mapping!A:D,4,0) -> West 1 | F76: =VLOOKUP(B76,Mapping!A:E,5,0) -> Anjli | G76: =VLOOKUP(B76,Mapping!A:F,6,0) -> Anjli | H76: 0 | I76: 0 | J76: 0 | K76: 0 | L76: 0 | M76: 0 | N76: 0 | O76: 0 | P76: 0 | Q76: 1 | R76: 1.1 | S76: 1.1
A77: FY2025-26 | B77: CG Power | C77: =VLOOKUP(B77,Mapping!A:B,2,0) -> Lateral | D77: =VLOOKUP(B77,Mapping!A:C,3,0) -> West | E77: =VLOOKUP(B77,Mapping!A:D,4,0) -> West 1 | F77: =VLOOKUP(B77,Mapping!A:E,5,0) -> Anjli | G77: =VLOOKUP(B77,Mapping!A:F,6,0) -> Anjli | H77: 0 | I77: 0 | J77: 0 | K77: 0 | L77: 0 | M77: 0 | N77: 0 | O77: 0 | P77: 0 | Q77: 0 | R77: 3.2 | S77: 17.7
A78: FY2025-26 | B78: Triveni | C78: Exclusive | D78: Exclusive | E78: Exclusive | F78: Amit Jain | G78: Naved | Q78: 3 | R78: 3.1 | S78: 3.8
A79: FY2025-26 | B79: Banswara | C79: Exclusive | D79: Exclusive | E79: Exclusive | F79: Amit Jain | G79: Naved | Q79: 0 | R79: 0 | S79: 0
A80: FY2025-26 | B80: Gala Precision | C80: Exclusive | D80: Exclusive | E80: Exclusive | F80: Amit Jain | G80: Naved | Q80: 0 | R80: 0 | S80: 0
A81: FY2025-26 | B81: ITW India | C81: Exclusive | D81: Exclusive | E81: Exclusive | F81: Amit Jain | G81: Naved | Q81: 0 | R81: 0 | S81: 0
A82: FY2025-26 | B82: Primetals Technologies | C82: Exclusive | D82: Exclusive | E82: Exclusive | F82: Amit Jain | G82: Naved | Q82: 0 | R82: 0 | S82: 0
A83: FY2025-26 | B83: Arvind Smartspaces | C83: Exclusive | D83: Exclusive | E83: Exclusive | F83: Amit Jain | G83: Naved | Q83: 0 | R83: 0 | S83: 0
A84: FY2025-26 | B84: Autofit | C84: Exclusive | D84: Exclusive | E84: Exclusive | F84: Amit Jain | G84: Naved | Q84: 0 | R84: 0 | S84: 0
A85: FY2025-26 | B85: Carplai | C85: Exclusive | D85: Exclusive | E85: Exclusive | F85: Amit Jain | G85: Naved | Q85: 0 | R85: 0 | S85: 0
A86: FY2025-26 | B86: Middle East | C86: Exclusive | D86: Exclusive | E86: Exclusive | F86: Amit Jain | G86: Naved | Q86: 1.33 | R86: 1 | S86: 0.3
A87: FY2025-26 | B87: Ace Designers | C87: Exclusive | D87: Exclusive | E87: Exclusive | F87: Amit Jain | G87: Naved | Q87: 0 | R87: 0 | S87: 0

Sheet Headcount_WL1
A1: =Revenue_Budget!A1 -> FY | B1: =Revenue_Budget!B1 -> Project | C1: =Revenue_Budget!C1 -> Vertical | D1: =Revenue_Budget!D1 -> Region | E1: =Revenue_Budget!E1 -> Sub Region | F1: =Revenue_Budget!F1 -> Region Head | G1: =Revenue_Budget!G1 -> Practice Head | H1: =Revenue_Budget!H1 -> 45748 | ... S1: =Revenue_Budget!S1 -> 46082
A2: FY2025-26 | B2: Honeywell | C2: =VLOOKUP(B2,Mapping!A:B,2,0) -> Lateral | D2: =VLOOKUP(B2,Mapping!A:C,3,0) -> South | E2: =VLOOKUP(B2,Mapping!A:D,4,0) -> South 1 | F2: =VLOOKUP(B2,Mapping!A:E,5,0) -> Bapi | G2: =VLOOKUP(B2,Mapping!A:F,6,0) -> Bapi | H2: 44.4 | I2: 47.1 | J2: 42 | K2: 39.5 | L2: 39.5 | M2: 39.5 | N2: 39.5 | O2: 39.5 | P2: 37 | Q2: 38 | R2: 38.5 | S2: 37.4
A3: FY2025-26 | B3: Pfizer | C3: =VLOOKUP(B3,Mapping!A:B,2,0) -> Lateral | D3: =VLOOKUP(B3,Mapping!A:C,3,0) -> West | E3: =VLOOKUP(B3,Mapping!A:D,4,0) -> West 1 | F3: =VLOOKUP(B3,Mapping!A:E,5,0) -> Anjli | G3: =VLOOKUP(B3,Mapping!A:F,6,0) -> Usha | H3: 5.1 | I3: 5.85 | J3: 5.1 | K3: 5 | L3: 4 | M3: 4 | N3: 4 | O3: 3.5 | P3: 3.5 | Q3: 3.5 | R3: 3.5 | S3: 3.5
A4: FY2025-26 | B4: Tata Motors | C4: =VLOOKUP(B4,Mapping!A:B,2,0) -> Lateral | D4: =VLOOKUP(B4,Mapping!A:C,3,0) -> West | E4: =VLOOKUP(B4,Mapping!A:D,4,0) -> West 2 | F4: =VLOOKUP(B4,Mapping!A:E,5,0) -> Anjli | G4: =VLOOKUP(B4,Mapping!A:F,6,0) -> Shweta | H4: 0 | I4: 1.5 | J4: 1.5 | K4: - | L4: - | M4: - | N4: - | O4: - | P4: - | Q4: 0 | R4: 0 | S4: 0
A5: FY2025-26 | B5: SKF India | C5: =VLOOKUP(B5,Mapping!A:B,2,0) -> Lateral | D5: =VLOOKUP(B5,Mapping!A:C,3,0) -> North | E5: =VLOOKUP(B5,Mapping!A:D,4,0) -> North | F5: =VLOOKUP(B5,Mapping!A:E,5,0) -> Anjli | G5: =VLOOKUP(B5,Mapping!A:F,6,0) -> Archana | H5: 9 | I5: 10.2 | J5: 10.3 | K5: 9 | L5: 9 | M5: 9.75 | N5: 10 | O5: 11 | P5: 10 | Q5: 11.1 | R5: 11.3 | S5: 11.3
A6: FY2025-26 | B6: Siemens | C6: =VLOOKUP(B6,Mapping!A:B,2,0) -> Lateral | D6: =VLOOKUP(B6,Mapping!A:C,3,0) -> South | E6: =VLOOKUP(B6,Mapping!A:D,4,0) -> South 1 | F6: =VLOOKUP(B6,Mapping!A:E,5,0) -> Sulabh | G6: =VLOOKUP(B6,Mapping!A:F,6,0) -> Kunal | H6: 12.2 | I6: 11.2 | J6: 13 | K6: 11 | L6: 11 | M6: 11 | N6: 11 | O6: 11 | P6: 11 | Q6: 11 | R6: 13 | S6: 14
A7: FY2025-26 | B7: Pidilite | C7: =VLOOKUP(B7,Mapping!A:B,2,0) -> Lateral | D7: =VLOOKUP(B7,Mapping!A:C,3,0) -> West | E7: =VLOOKUP(B7,Mapping!A:D,4,0) -> West 1 | F7: =VLOOKUP(B7,Mapping!A:E,5,0) -> Anjli | G7: =VLOOKUP(B7,Mapping!A:F,6,0) -> Usha | H7: 9 | I7: 8.1 | J7: 9.1 | K7: 7 | L7: 8 | M7: 7 | N7: 10 | O7: 8.5 | P7: 7.5 | Q7: 11.5 | R7: 11.5 | S7: 11.5
A8: FY2025-26 | B8: Vertiv | C8: =VLOOKUP(B8,Mapping!A:B,2,0) -> Lateral | D8: =VLOOKUP(B8,Mapping!A:C,3,0) -> West | E8: =VLOOKUP(B8,Mapping!A:D,4,0) -> West 2 | F8: =VLOOKUP(B8,Mapping!A:E,5,0) -> Anjli | G8: =VLOOKUP(B8,Mapping!A:F,6,0) -> Shweta | H8: 4.5 | I8: 3.5 | J8: 3.5 | K8: 3 | L8: 3 | M8: 2 | N8: 2 | O8: 2 | P8: 2 | Q8: 2 | R8: 2 | S8: 2
A9: FY2025-26 | B9: Birla Paints | C9: =VLOOKUP(B9,Mapping!A:B,2,0) -> Lateral | D9: =VLOOKUP(B9,Mapping!A:C,3,0) -> West | E9: =VLOOKUP(B9,Mapping!A:D,4,0) -> West 1 | F9: =VLOOKUP(B9,Mapping!A:E,5,0) -> Anjli | G9: =VLOOKUP(B9,Mapping!A:F,6,0) -> Geetu | H9: 8 | I9: 9 | J9: 9 | K9: 10 | L9: 9 | M9: 10 | N9: 9 | O9: 9.5 | P9: 10.5 | Q9: 10.5 | R9: 10.5 | S9: 10.5
A10: FY2025-26 | B10: Ingram Micro | C10: =VLOOKUP(B10,Mapping!A:B,2,0) -> Lateral | D10: =VLOOKUP(B10,Mapping!A:C,3,0) -> West | E10: =VLOOKUP(B10,Mapping!A:D,4,0) -> West 1 | F10: =VLOOKUP(B10,Mapping!A:E,5,0) -> Anjli | G10: =VLOOKUP(B10,Mapping!A:F,6,0) -> Geetu | H10: 3.1 | I10: 3.1 | J10: 3.1 | K10: 2 | L10: 2 | M10: 1 | N10: 1 | O10: 1 | P10: 1 | Q10: 0 | R10: 0 | S10: 0
A11: FY2025-26 | B11: HPE | C11: =VLOOKUP(B11,Mapping!A:B,2,0) -> Lateral | D11: =VLOOKUP(B11,Mapping!A:C,3,0) -> South | E11: =VLOOKUP(B11,Mapping!A:D,4,0) -> South 1 | F11: =VLOOKUP(B11,Mapping!A:E,5,0) -> Mahak | G11: =VLOOKUP(B11,Mapping!A:F,6,0) -> Mahak | H11: 35 | I11: 34 | J11: 34 | K11: 31.5 | L11: 28.5 | M11: 28.5 | N11: 28.5 | O11: 28.5 | P11: 29 | Q11: 32 | R11: 34.5 | S11: 34.9
A12: FY2025-26 | B12: Isuzu | C12: =VLOOKUP(B12,Mapping!A:B,2,0) -> Lateral | D12: =VLOOKUP(B12,Mapping!A:C,3,0) -> South | E12: =VLOOKUP(B12,Mapping!A:D,4,0) -> South 1 | F12: =VLOOKUP(B12,Mapping!A:E,5,0) -> Anjli | G12: =VLOOKUP(B12,Mapping!A:F,6,0) -> Satya | H12: 2 | I12: 2 | J12: 2 | K12: 2 | L12: 2 | M12: 2 | N12: 2 | O12: 2 | P12: 2 | Q12: 2 | R12: 2 | S12: 1.5
A13: FY2025-26 | B13: Mahindra Holidays | C13: =VLOOKUP(B13,Mapping!A:B,2,0) -> Lateral | D13: =VLOOKUP(B13,Mapping!A:C,3,0) -> West | E13: =VLOOKUP(B13,Mapping!A:D,4,0) -> West 1 | F13: =VLOOKUP(B13,Mapping!A:E,5,0) -> Anjli | G13: =VLOOKUP(B13,Mapping!A:F,6,0) -> Geetu | H13: 8.1 | I13: 8.1 | J13: 9.1 | K13: 7 | L13: 8 | M13: 8 | N13: 7 | O13: 7 | P13: 8 | Q13: 7 | R13: 7 | S13: 8
A14: FY2025-26 | B14: BITS | C14: =VLOOKUP(B14,Mapping!A:B,2,0) -> Lateral | D14: =VLOOKUP(B14,Mapping!A:C,3,0) -> South | E14: =VLOOKUP(B14,Mapping!A:D,4,0) -> South 2 | F14: =VLOOKUP(B14,Mapping!A:E,5,0) -> Sulabh | G14: =VLOOKUP(B14,Mapping!A:F,6,0) -> Krishna | H14: 2 | I14: 2 | J14: 2 | K14: 2 | L14: 2 | M14: 2 | N14: 2 | O14: 2 | P14: 2 | Q14: 2 | R14: 2 | S14: 2
A15: FY2025-26 | B15: M&M | C15: =VLOOKUP(B15,Mapping!A:B,2,0) -> Lateral | D15: =VLOOKUP(B15,Mapping!A:C,3,0) -> West | E15: =VLOOKUP(B15,Mapping!A:D,4,0) -> West 1 | F15: =VLOOKUP(B15,Mapping!A:E,5,0) -> Anjli | G15: =VLOOKUP(B15,Mapping!A:F,6,0) -> Dhriti | H15: 59.5 | I15: 52.5 | J15: 53 | K15: 50 | L15: 60 | M15: 68 | N15: 67 | O15: 65 | P15: 63 | Q15: 62 | R15: 66 | S15: 62
A16: FY2025-26 | B16: P&G | C16: =VLOOKUP(B16,Mapping!A:B,2,0) -> Lateral | D16: =VLOOKUP(B16,Mapping!A:C,3,0) -> South | E16: =VLOOKUP(B16,Mapping!A:D,4,0) -> South 2 | F16: =VLOOKUP(B16,Mapping!A:E,5,0) -> Sulabh | G16: =VLOOKUP(B16,Mapping!A:F,6,0) -> Krishna | H16: 2 | I16: 1 | J16: 1 | K16: 1 | L16: 1 | M16: - | N16: - | O16: - | P16: - | Q16: 0 | R16: 0 | S16: 0
A17: FY2025-26 | B17: Wipro | C17: =VLOOKUP(B17,Mapping!A:B,2,0) -> Lateral | D17: =VLOOKUP(B17,Mapping!A:C,3,0) -> South | E17: =VLOOKUP(B17,Mapping!A:D,4,0) -> South 1 | F17: =VLOOKUP(B17,Mapping!A:E,5,0) -> Sulabh | G17: =VLOOKUP(B17,Mapping!A:F,6,0) -> Subu | H17: 11 | I17: 10.7 | J17: 11 | K17: 11 | L17: 12 | M17: 11 | N17: 10 | O17: 16 | P17: 16 | Q17: 17 | R17: 17 | S17: 14
A18: FY2025-26 | B18: Tata Marcopolo | C18: =VLOOKUP(B18,Mapping!A:B,2,0) -> Lateral | D18: =VLOOKUP(B18,Mapping!A:C,3,0) -> West | E18: =VLOOKUP(B18,Mapping!A:D,4,0) -> West 2 | F18: =VLOOKUP(B18,Mapping!A:E,5,0) -> Anjli | G18: =VLOOKUP(B18,Mapping!A:F,6,0) -> Anjli | H18: 1 | I18: - | J18: - | K18: - | L18: - | M18: - | N18: - | O18: - | P18: - | Q18: 0 | R18: 0 | S18: 0
A19: FY2025-26 | B19: DP World | C19: =VLOOKUP(B19,Mapping!A:B,2,0) -> Lateral | D19: =VLOOKUP(B19,Mapping!A:C,3,0) -> West | E19: =VLOOKUP(B19,Mapping!A:D,4,0) -> West 1 | F19: =VLOOKUP(B19,Mapping!A:E,5,0) -> Anjli | G19: =VLOOKUP(B19,Mapping!A:F,6,0) -> Geetu | H19: 11.96 | I19: 11.5 | J19: 9.1 | K19: 10 | L19: 8 | M19: 7 | N19: 7 | O19: 6.5 | P19: 5.5 | Q19: 4.5 | R19: 4.5 | S19: 3.5
A20: FY2025-26 | B20: Ametek | C20: =VLOOKUP(B20,Mapping!A:B,2,0) -> Lateral | D20: =VLOOKUP(B20,Mapping!A:C,3,0) -> South | E20: =VLOOKUP(B20,Mapping!A:D,4,0) -> South 1 | F20: =VLOOKUP(B20,Mapping!A:E,5,0) -> Sulabh | G20: =VLOOKUP(B20,Mapping!A:F,6,0) -> Satya | H20: 1 | I20: 1 | J20: 1 | K20: 1 | L20: 1 | M20: 1 | N20: 1 | O20: - | P20: - | Q20: 0 | R20: 0 | S20: 0
A21: FY2025-26 | B21: AMNS | C21: =VLOOKUP(B21,Mapping!A:B,2,0) -> Lateral | D21: =VLOOKUP(B21,Mapping!A:C,3,0) -> West | E21: =VLOOKUP(B21,Mapping!A:D,4,0) -> West 1 | F21: =VLOOKUP(B21,Mapping!A:E,5,0) -> Anjli | G21: =VLOOKUP(B21,Mapping!A:F,6,0) -> Alifia | H21: 28.1 | I21: 27.1 | J21: 27.1 | K21: 24 | L21: 23 | M21: 22 | N21: 22 | O21: 23 | P21: 24 | Q21: 27 | R21: 32.5 | S21: 32
A22: FY2025-26 | B22: Tata Electronics | C22: =VLOOKUP(B22,Mapping!A:B,2,0) -> Lateral | D22: =VLOOKUP(B22,Mapping!A:C,3,0) -> South | E22: =VLOOKUP(B22,Mapping!A:D,4,0) -> South 2 | F22: =VLOOKUP(B22,Mapping!A:E,5,0) -> Sulabh | G22: =VLOOKUP(B22,Mapping!A:F,6,0) -> Subu | H22: 5.2 | I22: 7.2 | J22: 4 | K22: 3 | L22: 4 | M22: 4 | N22: 3 | O22: 3 | P22: 2 | Q22: 2 | R22: 2 | S22: 1
A23: FY2025-26 | B23: Jindal Stainless | C23: =VLOOKUP(B23,Mapping!A:B,2,0) -> Lateral | D23: =VLOOKUP(B23,Mapping!A:C,3,0) -> North | E23: =VLOOKUP(B23,Mapping!A:D,4,0) -> North | F23: =VLOOKUP(B23,Mapping!A:E,5,0) -> Anjli | G23: =VLOOKUP(B23,Mapping!A:F,6,0) -> Archana | H23: 5 | I23: 4 | J23: 4 | K23: 4 | L23: 4 | M23: 4 | N23: 4 | O23: 4 | P23: 4.2 | Q23: 5.2 | R23: 4.2 | S23: 4.2
A24: FY2025-26 | B24: Nomiso | C24: =VLOOKUP(B24,Mapping!A:B,2,0) -> Lateral | D24: =VLOOKUP(B24,Mapping!A:C,3,0) -> South | E24: =VLOOKUP(B24,Mapping!A:D,4,0) -> South 2 | F24: =VLOOKUP(B24,Mapping!A:E,5,0) -> Sulabh | G24: =VLOOKUP(B24,Mapping!A:F,6,0) -> Krishna | H24: 0 | I24: 0 | J24: 0 | K24: 0 | L24: 0 | M24: 0 | N24: 0 | O24: 0 | P24: 0 | Q24: 0 | R24: 0 | S24: 0
A25: FY2025-26 | B25: Schaeffler | C25: =VLOOKUP(B25,Mapping!A:B,2,0) -> Lateral | D25: =VLOOKUP(B25,Mapping!A:C,3,0) -> West | E25: =VLOOKUP(B25,Mapping!A:D,4,0) -> West 2 | F25: =VLOOKUP(B25,Mapping!A:E,5,0) -> Anjli | G25: =VLOOKUP(B25,Mapping!A:F,6,0) -> Shweta | H25: 5 | I25: 3.5 | J25: 3.5 | K25: 4 | L25: 4 | M25: 5 | N25: 5 | O25: 4 | P25: 4 | Q25: 4 | R25: 4 | S25: 4
A26: FY2025-26 | B26: Royal Enfield | C26: =VLOOKUP(B26,Mapping!A:B,2,0) -> Lateral | D26: =VLOOKUP(B26,Mapping!A:C,3,0) -> South | E26: =VLOOKUP(B26,Mapping!A:D,4,0) -> South 2 | F26: =VLOOKUP(B26,Mapping!A:E,5,0) -> Sulabh | G26: =VLOOKUP(B26,Mapping!A:F,6,0) -> Krishna | H26: 4 | I26: 4 | J26: 4 | K26: 4 | L26: 4 | M26: 10 | N26: 9 | O26: 8 | P26: 12 | Q26: 14 | R26: 14 | S26: 18.2
A27: FY2025-26 | B27: SBI Card | C27: =VLOOKUP(B27,Mapping!A:B,2,0) -> Lateral | D27: =VLOOKUP(B27,Mapping!A:C,3,0) -> North | E27: =VLOOKUP(B27,Mapping!A:D,4,0) -> North | F27: =VLOOKUP(B27,Mapping!A:E,5,0) -> Anjli | G27: =VLOOKUP(B27,Mapping!A:F,6,0) -> Archana | H27: 11 | I27: 11.3 | J27: 11.5 | K27: 12.1 | L27: 12.1 | M27: 16.1 | N27: 16.1 | O27: 15.1 | P27: 15.4 | Q27: 13.3 | R27: 12.3 | S27: 11.3
A28: FY2025-26 | B28: Hyundai Motor | C28: =VLOOKUP(B28,Mapping!A:B,2,0) -> Lateral | D28: =VLOOKUP(B28,Mapping!A:C,3,0) -> West | E28: =VLOOKUP(B28,Mapping!A:D,4,0) -> West 2 | F28: =VLOOKUP(B28,Mapping!A:E,5,0) -> Anjli | G28: =VLOOKUP(B28,Mapping!A:F,6,0) -> Shweta | H28: 15 | I28: 12 | J28: 10 | K28: 8 | L28: 9 | M28: 10 | N28: 9 | O28: 10 | P28: 8 | Q28: 6 | R28: 6 | S28: 6
A29: FY2025-26 | B29: Maruti Suzuki(MSIL) | C29: =VLOOKUP(B29,Mapping!A:B,2,0) -> Lateral | D29: =VLOOKUP(B29,Mapping!A:C,3,0) -> North | E29: =VLOOKUP(B29,Mapping!A:D,4,0) -> North | F29: =VLOOKUP(B29,Mapping!A:E,5,0) -> Anjli | G29: =VLOOKUP(B29,Mapping!A:F,6,0) -> Archana | H29: 47.5 | I29: 41.35 | J29: 39.9 | K29: 34.6 | L29: 34.6 | M29: 33.6 | N29: 33.6 | O29: 34.1 | P29: 33.8 | Q29: 33.6 | R29: 29.7 | S29: 29.7
A30: FY2025-26 | B30: Excelacom | C30: =VLOOKUP(B30,Mapping!A:B,2,0) -> Lateral | D30: =VLOOKUP(B30,Mapping!A:C,3,0) -> South | E30: =VLOOKUP(B30,Mapping!A:D,4,0) -> South 2 | F30: =VLOOKUP(B30,Mapping!A:E,5,0) -> Sulabh | G30: =VLOOKUP(B30,Mapping!A:F,6,0) -> Krishna | H30: 2 | I30: 0 | J30: 1 | K30: 1 | L30: 1 | M30: - | N30: - | O30: - | P30: - | Q30: 0 | R30: 0 | S30: 0
A31: FY2025-26 | B31: Tata Consumer | C31: =VLOOKUP(B31,Mapping!A:B,2,0) -> Lateral | D31: =VLOOKUP(B31,Mapping!A:C,3,0) -> West | E31: =VLOOKUP(B31,Mapping!A:D,4,0) -> West 1 | F31: =VLOOKUP(B31,Mapping!A:E,5,0) -> Anjli | G31: =VLOOKUP(B31,Mapping!A:F,6,0) -> Geetu | H31: 15.1 | I31: 14.1 | J31: 14.1 | K31: 13 | L31: 13 | M31: 13 | N31: 13 | O31: 13 | P31: 12 | Q31: 14 | R31: 13 | S31: 14
A32: FY2025-26 | B32: Tata Play | C32: =VLOOKUP(B32,Mapping!A:B,2,0) -> Lateral | D32: =VLOOKUP(B32,Mapping!A:C,3,0) -> West | E32: =VLOOKUP(B32,Mapping!A:D,4,0) -> West 1 | F32: =VLOOKUP(B32,Mapping!A:E,5,0) -> Anjli | G32: =VLOOKUP(B32,Mapping!A:F,6,0) -> Geetu | H32: 1.1 | I32: 1.1 | J32: 1.1 | K32: 1 | L32: 2 | M32: 1 | N32: 1 | O32: 1 | P32: 1 | Q32: 1 | R32: 1 | S32: 1
A33: FY2025-26 | B33: Mahindra Finance | C33: =VLOOKUP(B33,Mapping!A:B,2,0) -> Lateral | D33: =VLOOKUP(B33,Mapping!A:C,3,0) -> West | E33: =VLOOKUP(B33,Mapping!A:D,4,0) -> West 1 | F33: =VLOOKUP(B33,Mapping!A:E,5,0) -> Anjli | G33: =VLOOKUP(B33,Mapping!A:F,6,0) -> Geetu | H33: 7.1 | I33: 5.1 | J33: 4.1 | K33: 2 | L33: 1 | M33: 1 | N33: 1 | O33: 1 | P33: 1 | Q33: 0 | R33: 0 | S33: 0
A34: FY2025-26 | B34: Suzuki R&D | C34: =VLOOKUP(B34,Mapping!A:B,2,0) -> Lateral | D34: =VLOOKUP(B34,Mapping!A:C,3,0) -> North | E34: =VLOOKUP(B34,Mapping!A:D,4,0) -> North | F34: =VLOOKUP(B34,Mapping!A:E,5,0) -> Anjli | G34: =VLOOKUP(B34,Mapping!A:F,6,0) -> Archana | H34: 1 | I34: 1 | J34: 1 | K34: 1 | L34: 1 | M34: 1 | N34: 1 | O34: 1 | P34: 1 | Q34: 0.1 | R34: 1 | S34: 1
A35: FY2025-26 | B35: Subros Ltd | C35: =VLOOKUP(B35,Mapping!A:B,2,0) -> Lateral | D35: =VLOOKUP(B35,Mapping!A:C,3,0) -> North | E35: =VLOOKUP(B35,Mapping!A:D,4,0) -> North | F35: =VLOOKUP(B35,Mapping!A:E,5,0) -> Anjli | G35: =VLOOKUP(B35,Mapping!A:F,6,0) -> Archana | H35: 2 | I35: 2 | J35: 2 | K35: 2.75 | L35: 3 | M35: 3 | N35: 3 | O35: 4 | P35: 3.1 | Q35: 3.1 | R35: 3.1 | S35: 3.1
A36: FY2025-26 | B36: Atomberg Technologies | C36: =VLOOKUP(B36,Mapping!A:B,2,0) -> Lateral | D36: =VLOOKUP(B36,Mapping!A:C,3,0) -> West | E36: =VLOOKUP(B36,Mapping!A:D,4,0) -> West 1 | F36: =VLOOKUP(B36,Mapping!A:E,5,0) -> Anjli | G36: =VLOOKUP(B36,Mapping!A:F,6,0) -> Geetu | H36: 5.1 | I36: 4.1 | J36: 5.1 | K36: 4 | L36: 4 | M36: 4 | N36: 4 | O36: 4 | P36: 4 | Q36: 4 | R36: 4 | S36: 4
A37: FY2025-26 | B37: Bridgestone | C37: =VLOOKUP(B37,Mapping!A:B,2,0) -> Lateral | D37: =VLOOKUP(B37,Mapping!A:C,3,0) -> West | E37: =VLOOKUP(B37,Mapping!A:D,4,0) -> West 2 | F37: =VLOOKUP(B37,Mapping!A:E,5,0) -> Anjli | G37: =VLOOKUP(B37,Mapping!A:F,6,0) -> Shweta | H37: 3.5 | I37: 1.5 | J37: 1.5 | K37: 2 | L37: 2 | M37: 2 | N37: 1 | O37: 1 | P37: 1 | Q37: 1 | R37: 2 | S37: 2
A38: FY2025-26 | B38: Ambuja Cement | C38: =VLOOKUP(B38,Mapping!A:B,2,0) -> Lateral | D38: =VLOOKUP(B38,Mapping!A:C,3,0) -> West | E38: =VLOOKUP(B38,Mapping!A:D,4,0) -> West 1 | F38: =VLOOKUP(B38,Mapping!A:E,5,0) -> Anjli | G38: =VLOOKUP(B38,Mapping!A:F,6,0) -> Ankit | H38: 23 | I38: 23 | J38: 21 | K38: 20 | L38: 19 | M38: 18 | N38: 18 | O38: 20 | P38: 22 | Q38: 23 | R38: 24 | S38: 22
A39: FY2025-26 | B39: Ashok Leyland | C39: =VLOOKUP(B39,Mapping!A:B,2,0) -> Lateral | D39: =VLOOKUP(B39,Mapping!A:C,3,0) -> South | E39: =VLOOKUP(B39,Mapping!A:D,4,0) -> South 2 | F39: =VLOOKUP(B39,Mapping!A:E,5,0) -> Sulabh | G39: =VLOOKUP(B39,Mapping!A:F,6,0) -> Krishna | H39: 8.2 | I39: 8.2 | J39: 9 | K39: 9 | L39: 9 | M39: 12 | N39: 11 | O39: 12 | P39: 10 | Q39: 11 | R39: 10 | S39: 9
A40: FY2025-26 | B40: Sterling Tools | C40: =VLOOKUP(B40,Mapping!A:B,2,0) -> Lateral | D40: =VLOOKUP(B40,Mapping!A:C,3,0) -> North | E40: =VLOOKUP(B40,Mapping!A:D,4,0) -> North | F40: =VLOOKUP(B40,Mapping!A:E,5,0) -> Anjli | G40: =VLOOKUP(B40,Mapping!A:F,6,0) -> Archana | H40: 6 | I40: 5.2 | J40: 5.2 | K40: 4.35 | L40: 4.1 | M40: 3.35 | N40: 3.1 | O40: 3.1 | P40: 3.2 | Q40: 3.2 | R40: 3.1 | S40: 3.1
A41: FY2025-26 | B41: M2P Fintech | C41: =VLOOKUP(B41,Mapping!A:B,2,0) -> Lateral | D41: =VLOOKUP(B41,Mapping!A:C,3,0) -> South | E41: =VLOOKUP(B41,Mapping!A:D,4,0) -> South 2 | F41: =VLOOKUP(B41,Mapping!A:E,5,0) -> Sulabh | G41: =VLOOKUP(B41,Mapping!A:F,6,0) -> Krishna | H41: 4 | I41: 3 | J41: 5 | K41: 5 | L41: 4 | M41: 0 | N41: 0 | O41: 0 | P41: 1 | Q41: 1 | R41: 1 | S41: 1
A42: FY2025-26 | B42: Tata Power | C42: =VLOOKUP(B42,Mapping!A:B,2,0) -> Lateral | D42: =VLOOKUP(B42,Mapping!A:C,3,0) -> West | E42: =VLOOKUP(B42,Mapping!A:D,4,0) -> West 1 | F42: =VLOOKUP(B42,Mapping!A:E,5,0) -> Anjli | G42: =VLOOKUP(B42,Mapping!A:F,6,0) -> Elton | H42: 0 | I42: 0 | J42: 0 | K42: 0 | L42: 0 | M42: 0 | N42: 0 | O42: 0 | P42: 0 | Q42: 0 | R42: 0 | S42: 0
... A67: FY2025-26 | B67: Pernod Ricard | C67: =VLOOKUP(B67,Mapping!A:B,2,0) -> Lateral | D67: =VLOOKUP(B67,Mapping!A:C,3,0) -> North | E67: =VLOOKUP(B67,Mapping!A:D,4,0) -> North | F67: =VLOOKUP(B67,Mapping!A:E,5,0) -> Anjli | G67: =VLOOKUP(B67,Mapping!A:F,6,0) -> Archana | H67: 3 | I67: 3 | J67: 3.1 | K67: 3.2 | L67: 3.2 | M67: 4.2 | N67: 4.2 | O67: 3.7 | P67: 4.3 | Q67: 5.3 | R67: 4.2 | S67: 3.2
A68: FY2025-26 | B68: UniCharm | C68: =VLOOKUP(B68,Mapping!A:B,2,0) -> Lateral | D68: =VLOOKUP(B68,Mapping!A:C,3,0) -> North | E68: =VLOOKUP(B68,Mapping!A:D,4,0) -> North | F68: =VLOOKUP(B68,Mapping!A:E,5,0) -> Anjli | G68: =VLOOKUP(B68,Mapping!A:F,6,0) -> Archana | H68: - | I68: - | J68: - | K68: - | L68: - | M68: 2 | N68: 2 | O68: 2 | P68: 2 | Q68: 2.1 | R68: 3.1 | S68: 2.1
