Workbook

Sheet Revenue_Budget
A1: FY | B1: Project | C1: Vertical | D1: Region | E1: Sub Region | F1: Region Head | G1: Practice Head | H1: 45383 | I1: =EDATE(H1,1) -> 45413 | J1: =EDATE(I1,1) -> 45444 | K1: =EDATE(J1,1) -> 45474 | L1: =EDATE(K1,1) -> 45505 | M1: =EDATE(L1,1) -> 45536 | N1: =EDATE(M1,1) -> 45566 | O1: =EDATE(N1,1) -> 45597 | P1: =EDATE(O1,1) -> 45627 | ... S1: =EDATE(R1,1) -> 45717
A2: FY2024-25 | B2: Tata Motors | C2: =VLOOKUP(B2,Mapping!B:C,2,0) -> Lateral | D2: =VLOOKUP(B2,Mapping!B:D,3,0) -> West | E2: =VLOOKUP(B2,Mapping!B:E,4,0) -> West 2 | F2: =VLOOKUP(B2,Mapping!B:F,5,0) -> Anjli | G2: =VLOOKUP(B2,Mapping!B:G,6,0) -> Shweta | H2: 25 | I2: 35 | J2: 40 | K2: 43.5 | L2: 60.9 | M2: 69.6 | N2: 49.025 | O2: 68.635 | P2: 78.44 | Q2: 50.8825 | R2: 71.2355 | S2: 81.412
A3: FY2024-25 | B3: Schaeffler | C3: =VLOOKUP(B3,Mapping!B:C,2,0) -> Lateral | D3: =VLOOKUP(B3,Mapping!B:D,3,0) -> West | E3: =VLOOKUP(B3,Mapping!B:E,4,0) -> West 2 | F3: =VLOOKUP(B3,Mapping!B:F,5,0) -> Anjli | G3: =VLOOKUP(B3,Mapping!B:G,6,0) -> Shweta | H3: 6.175 | I3: 8.645 | J3: 9.88 | K3: 6.35 | L3: 8.89 | M3: 10.16 | N3: 6.65 | O3: 9.31 | P3: 10.64 | Q3: 7.0325 | R3: 9.8455 | S3: 11.252
A4: FY2024-25 | B4: Vertiv | C4: =VLOOKUP(B4,Mapping!B:C,2,0) -> Lateral | D4: =VLOOKUP(B4,Mapping!B:D,3,0) -> West | E4: =VLOOKUP(B4,Mapping!B:E,4,0) -> West 2 | F4: =VLOOKUP(B4,Mapping!B:F,5,0) -> Anjli | G4: =VLOOKUP(B4,Mapping!B:G,6,0) -> Shweta | H4: 3 | I4: 4.2 | J4: 4.8 | K4: 3.675 | L4: 5.145 | M4: 5.88 | N4: 3.825 | O4: 5.355 | P4: 6.12 | Q4: 4.0575 | R4: 5.6805 | S4: 6.492
A5: FY2024-25 | B5: Tata Marcopolo | C5: =VLOOKUP(B5,Mapping!B:C,2,0) -> Lateral | D5: =VLOOKUP(B5,Mapping!B:D,3,0) -> West | E5: =VLOOKUP(B5,Mapping!B:E,4,0) -> West 2 | F5: =VLOOKUP(B5,Mapping!B:F,5,0) -> Anjli | G5: =VLOOKUP(B5,Mapping!B:G,6,0) -> Anjli | H5: 1.125 | I5: 1.575 | J5: 1.8 | K5: 1.125 | L5: 1.575 | M5: 1.8 | N5: 1.125 | O5: 1.575 | P5: 1.8 | Q5: 1.2075 | R5: 1.6905 | S5: 1.932
A6: FY2024-25 | B6: ThyssenKrupp | C6: =VLOOKUP(B6,Mapping!B:C,2,0) -> Lateral | D6: =VLOOKUP(B6,Mapping!B:D,3,0) -> West | E6: =VLOOKUP(B6,Mapping!B:E,4,0) -> West 2 | F6: =VLOOKUP(B6,Mapping!B:F,5,0) -> Anjli | G6: =VLOOKUP(B6,Mapping!B:G,6,0) -> Shweta | H6: 15.4 | I6: 21.56 | J6: 24.64 | K6: 15.925 | L6: 22.295 | M6: 25.48 | N6: 16.575 | O6: 23.205 | P6: 26.52 | Q6: 17.3075 | R6: 24.2305 | S6: 27.692
A7: FY2024-25 | B7: Ultratech | C7: =VLOOKUP(B7,Mapping!B:C,2,0) -> Lateral | D7: =VLOOKUP(B7,Mapping!B:D,3,0) -> West | E7: =VLOOKUP(B7,Mapping!B:E,4,0) -> West 1 | F7: =VLOOKUP(B7,Mapping!B:F,5,0) -> Anjli | G7: =VLOOKUP(B7,Mapping!B:G,6,0) -> Elton | H7: 0.375 | I7: 0.525 | J7: 0.6 | K7: 1.8 | L7: 2.52 | M7: 2.88 | N7: 1.95 | O7: 2.73 | P7: 3.12 | Q7: 2.1825 | R7: 3.0555 | S7: 3.492
A8: FY2024-25 | B8: Tata Teleservices | C8: =VLOOKUP(B8,Mapping!B:C,2,0) -> Lateral | D8: =VLOOKUP(B8,Mapping!B:D,3,0) -> West | E8: =VLOOKUP(B8,Mapping!B:E,4,0) -> West 1 | F8: =VLOOKUP(B8,Mapping!B:F,5,0) -> Anjli | G8: =VLOOKUP(B8,Mapping!B:G,6,0) -> Elton | H8: 3.125 | I8: 4.375 | J8: 5 | K8: 6.25 | L8: 8.75 | M8: 10 | N8: 6.25 | O8: 8.75 | P8: 10 | Q8: 6.3325 | R8: 8.8655 | S8: 10.132
A9: FY2024-25 | B9: Hyundai Motor | C9: =VLOOKUP(B9,Mapping!B:C,2,0) -> Lateral | D9: =VLOOKUP(B9,Mapping!B:D,3,0) -> West | E9: =VLOOKUP(B9,Mapping!B:E,4,0) -> West 2 | F9: =VLOOKUP(B9,Mapping!B:F,5,0) -> Anjli | G9: =VLOOKUP(B9,Mapping!B:G,6,0) -> Shweta | H9: 3.75 | I9: 5.25 | J9: 6 | K9: 7.5 | L9: 10.5 | M9: 12 | N9: 10 | O9: 14 | P9: 16 | Q9: 8 | R9: 11.2 | S9: 12.8
A10: FY2024-25 | B10: Bridgestone | C10: =VLOOKUP(B10,Mapping!B:C,2,0) -> Lateral | D10: =VLOOKUP(B10,Mapping!B:D,3,0) -> West | E10: =VLOOKUP(B10,Mapping!B:E,4,0) -> West 2 | F10: =VLOOKUP(B10,Mapping!B:F,5,0) -> Anjli | G10: =VLOOKUP(B10,Mapping!B:G,6,0) -> Shweta | H10: 0 | I10: 0 | J10: 0 | K10: 0 | L10: 0 | M10: 0 | N10: 0 | O10: 0 | P10: 0 | Q10: 0 | R10: 0 | S10: 0
A11: FY2024-25 | B11: SKF India | C11: =VLOOKUP(B11,Mapping!B:C,2,0) -> Lateral | D11: =VLOOKUP(B11,Mapping!B:D,3,0) -> North | E11: =VLOOKUP(B11,Mapping!B:E,4,0) -> North | F11: =VLOOKUP(B11,Mapping!B:F,5,0) -> Anjli | G11: =VLOOKUP(B11,Mapping!B:G,6,0) -> Archana | H11: 11.375 | I11: 15.925 | J11: 18.2 | K11: 11.5 | L11: 16.1 | M11: 18.4 | N11: 11.5 | O11: 16.1 | P11: 18.4 | Q11: 11.5825 | R11: 16.2155 | S11: 18.532
A12: FY2024-25 | B12: Jindal Stainless | C12: =VLOOKUP(B12,Mapping!B:C,2,0) -> Lateral | D12: =VLOOKUP(B12,Mapping!B:D,3,0) -> North | E12: =VLOOKUP(B12,Mapping!B:E,4,0) -> North | F12: =VLOOKUP(B12,Mapping!B:F,5,0) -> Anjli | G12: =VLOOKUP(B12,Mapping!B:G,6,0) -> Archana | H12: 9 | I12: 12.6 | J12: 14.4 | K12: 7.9075 | L12: 11.0705 | M12: 12.652 | N12: 7.6575 | O12: 10.7205 | P12: 12.252 | Q12: 7.865 | R12: 11.011 | S12: 12.584
A13: FY2024-25 | B13: Maruti Suzuki(MSIL) | C13: =VLOOKUP(B13,Mapping!B:C,2,0) -> Lateral | D13: =VLOOKUP(B13,Mapping!B:D,3,0) -> North | E13: =VLOOKUP(B13,Mapping!B:E,4,0) -> North | F13: =VLOOKUP(B13,Mapping!B:F,5,0) -> Anjli | G13: =VLOOKUP(B13,Mapping!B:G,6,0) -> Archana | H13: 4.25 | I13: 5.95 | J13: 6.8 | K13: 7.5 | L13: 10.5 | M13: 12 | N13: 8.75 | O13: 12.25 | P13: 14 | Q13: 10 | R13: 14 | S13: 16
... A58: FY2024-25 | B58: New Sales + Mining | C58: =VLOOKUP(B58,Mapping!B:C,2,0) -> Lateral | D58: =VLOOKUP(B58,Mapping!B:D,3,0) -> New Sales | E58: =VLOOKUP(B58,Mapping!B:E,4,0) -> New Sales | F58: =VLOOKUP(B58,Mapping!B:F,5,0) -> Nizar | G58: =VLOOKUP(B58,Mapping!B:G,6,0) -> Nizar | H58: 95.92492 | I58: 134.29489 | J58: 153.47987 | K58: 191.84984 | L58: 268.58978 | M58: 306.95974 | N58: 287.77476 | O58: 402.88466 | P58: 460.43962 | Q58: 383.69968 | R58: 537.17955 | S58: 613.91949
H59: In lacs

Sheet CM_Budget
A1: =Revenue_Budget!A1 -> FY | B1: =Revenue_Budget!B1 -> Project | C1: =Revenue_Budget!C1 -> Vertical | D1: =Revenue_Budget!D1 -> Region | E1: =Revenue_Budget!E1 -> Sub Region | F1: =Revenue_Budget!F1 -> Region Head | G1: =Revenue_Budget!G1 -> Practice Head | H1: =Revenue_Budget!H1 -> 45383 | ... S1: =Revenue_Budget!S1 -> 45717
A2: FY2024-25 | B2: Tata Motors | C2: =VLOOKUP(B2,Mapping!B:C,2,0) -> Lateral | D2: =VLOOKUP(B2,Mapping!B:D,3,0) -> West | E2: =VLOOKUP(B2,Mapping!B:E,4,0) -> West 2 | F2: =VLOOKUP(B2,Mapping!B:F,5,0) -> Anjli | G2: =VLOOKUP(B2,Mapping!B:G,6,0) -> Shweta | H2: =Revenue_Budget!H2*42% -> 10.5 | I2: =Revenue_Budget!I2*42% -> 14.7 | J2: =Revenue_Budget!J2*42% -> 16.8 | K2: =Revenue_Budget!K2*42% -> 18.27 | L2: =Revenue_Budget!L2*42% -> 25.578 | M2: =Revenue_Budget!M2*42% -> 29.232 | N2: =Revenue_Budget!N2*42% -> 20.5905 | O2: =Revenue_Budget!O2*42% -> 28.8267 | ... S2: =Revenue_Budget!S2*42% -> 34.19304
A3: FY2024-25 | B3: Schaeffler | C3: =VLOOKUP(B3,Mapping!B:C,2,0) -> Lateral | D3: =VLOOKUP(B3,Mapping!B:D,3,0) -> West | E3: =VLOOKUP(B3,Mapping!B:E,4,0) -> West 2 | F3: =VLOOKUP(B3,Mapping!B:F,5,0) -> Anjli | G3: =VLOOKUP(B3,Mapping!B:G,6,0) -> Shweta | H3: =Revenue_Budget!H3*42% -> 2.5935 | I3: =Revenue_Budget!I3*42% -> 3.6309 | J3: =Revenue_Budget!J3*42% -> 4.1496 | K3: =Revenue_Budget!K3*42% -> 2.667 | L3: =Revenue_Budget!L3*42% -> 3.7338 | M3: =Revenue_Budget!M3*42% -> 4.2672 | N3: =Revenue_Budget!N3*42% -> 2.793 | O3: =Revenue_Budget!O3*42% -> 3.9102 | ... S3: =Revenue_Budget!S3*42% -> 4.72584
A4: FY2024-25 | B4: Vertiv | C4: =VLOOKUP(B4,Mapping!B:C,2,0) -> Lateral | D4: =VLOOKUP(B4,Mapping!B:D,3,0) -> West | E4: =VLOOKUP(B4,Mapping!B:E,4,0) -> West 2 | F4: =VLOOKUP(B4,Mapping!B:F,5,0) -> Anjli | G4: =VLOOKUP(B4,Mapping!B:G,6,0) -> Shweta | H4: =Revenue_Budget!H4*42% -> 1.26 | I4: =Revenue_Budget!I4*42% -> 1.764 | J4: =Revenue_Budget!J4*42% -> 2.016 | K4: =Revenue_Budget!K4*42% -> 1.5435 | L4: =Revenue_Budget!L4*42% -> 2.1609 | M4: =Revenue_Budget!M4*42% -> 2.4696 | N4: =Revenue_Budget!N4*42% -> 1.6065 | O4: =Revenue_Budget!O4*42% -> 2.2491 | ... S4: =Revenue_Budget!S4*42% -> 2.72664
A5: FY2024-25 | B5: Tata Marcopolo | C5: =VLOOKUP(B5,Mapping!B:C,2,0) -> Lateral | D5: =VLOOKUP(B5,Mapping!B:D,3,0) -> West | E5: =VLOOKUP(B5,Mapping!B:E,4,0) -> West 2 | F5: =VLOOKUP(B5,Mapping!B:F,5,0) -> Anjli | G5: =VLOOKUP(B5,Mapping!B:G,6,0) -> Anjli | H5: =Revenue_Budget!H5*42% -> 0.4725 | I5: =Revenue_Budget!I5*42% -> 0.6615 | J5: =Revenue_Budget!J5*42% -> 0.756 | K5: =Revenue_Budget!K5*42% -> 0.4725 | L5: =Revenue_Budget!L5*42% -> 0.6615 | M5: =Revenue_Budget!M5*42% -> 0.756 | N5: =Revenue_Budget!N5*42% -> 0.4725 | O5: =Revenue_Budget!O5*42% -> 0.6615 | ... S5: =Revenue_Budget!S5*42% -> 0.81144
A6: FY2024-25 | B6: ThyssenKrupp | C6: =VLOOKUP(B6,Mapping!B:C,2,0) -> Lateral | D6: =VLOOKUP(B6,Mapping!B:D,3,0) -> West | E6: =VLOOKUP(B6,Mapping!B:E,4,0) -> West 2 | F6: =VLOOKUP(B6,Mapping!B:F,5,0) -> Anjli | G6: =VLOOKUP(B6,Mapping!B:G,6,0) -> Shweta | H6: =Revenue_Budget!H6*42% -> 6.468 | I6: =Revenue_Budget!I6*42% -> 9.0552 | J6: =Revenue_Budget!J6*42% -> 10.3488 | K6: =Revenue_Budget!K6*42% -> 6.6885 | L6: =Revenue_Budget!L6*42% -> 9.3639 | M6: =Revenue_Budget!M6*42% -> 10.7016 | N6: =Revenue_Budget!N6*42% -> 6.9615 | O6: =Revenue_Budget!O6*42% -> 9.7461 | ... S6: =Revenue_Budget!S6*42% -> 11.63064
A7: FY2024-25 | B7: Ultratech | C7: =VLOOKUP(B7,Mapping!B:C,2,0) -> Lateral | D7: =VLOOKUP(B7,Mapping!B:D,3,0) -> West | E7: =VLOOKUP(B7,Mapping!B:E,4,0) -> West 1 | F7: =VLOOKUP(B7,Mapping!B:F,5,0) -> Anjli | G7: =VLOOKUP(B7,Mapping!B:G,6,0) -> Elton | H7: =Revenue_Budget!H7*42% -> 0.1575 | I7: =Revenue_Budget!I7*42% -> 0.2205 | J7: =Revenue_Budget!J7*42% -> 0.252 | K7: =Revenue_Budget!K7*42% -> 0.756 | L7: =Revenue_Budget!L7*42% -> 1.0584 | M7: =Revenue_Budget!M7*42% -> 1.2096 | N7: =Revenue_Budget!N7*42% -> 0.819 | O7: =Revenue_Budget!O7*42% -> 1.1466 | ... S7: =Revenue_Budget!S7*42% -> 1.46664
A8: FY2024-25 | B8: Tata Teleservices | C8: =VLOOKUP(B8,Mapping!B:C,2,0) -> Lateral | D8: =VLOOKUP(B8,Mapping!B:D,3,0) -> West | E8: =VLOOKUP(B8,Mapping!B:E,4,0) -> West 1 | F8: =VLOOKUP(B8,Mapping!B:F,5,0) -> Anjli | G8: =VLOOKUP(B8,Mapping!B:G,6,0) -> Elton | H8: =Revenue_Budget!H8*42% -> 1.3125 | I8: =Revenue_Budget!I8*42% -> 1.8375 | J8: =Revenue_Budget!J8*42% -> 2.1 | K8: =Revenue_Budget!K8*42% -> 2.625 | L8: =Revenue_Budget!L8*42% -> 3.675 | M8: =Revenue_Budget!M8*42% -> 4.2 | N8: =Revenue_Budget!N8*42% -> 2.625 | O8: =Revenue_Budget!O8*42% -> 3.675 | ... S8: =Revenue_Budget!S8*42% -> 4.25544
A9: FY2024-25 | B9: Hyundai Motor | C9: =VLOOKUP(B9,Mapping!B:C,2,0) -> Lateral | D9: =VLOOKUP(B9,Mapping!B:D,3,0) -> West | E9: =VLOOKUP(B9,Mapping!B:E,4,0) -> West 2 | F9: =VLOOKUP(B9,Mapping!B:F,5,0) -> Anjli | G9: =VLOOKUP(B9,Mapping!B:G,6,0) -> Shweta | H9: =Revenue_Budget!H9*42% -> 1.575 | I9: =Revenue_Budget!I9*42% -> 2.205 | J9: =Revenue_Budget!J9*42% -> 2.52 | K9: =Revenue_Budget!K9*42% -> 3.15 | L9: =Revenue_Budget!L9*42% -> 4.41 | M9: =Revenue_Budget!M9*42% -> 5.04 | N9: =Revenue_Budget!N9*42% -> 4.2 | O9: =Revenue_Budget!O9*42% -> 5.88 | ... S9: =Revenue_Budget!S9*42% -> 5.376
A10: FY2024-25 | B10: Bridgestone | C10: =VLOOKUP(B10,Mapping!B:C,2,0) -> Lateral | D10: =VLOOKUP(B10,Mapping!B:D,3,0) -> West | E10: =VLOOKUP(B10,Mapping!B:E,4,0) -> West 2 | F10: =VLOOKUP(B10,Mapping!B:F,5,0) -> Anjli | G10: =VLOOKUP(B10,Mapping!B:G,6,0) -> Shweta | H10: =Revenue_Budget!H10*42% -> 0 | I10: =Revenue_Budget!I10*42% -> 0 | J10: =Revenue_Budget!J10*42% -> 0 | K10: =Revenue_Budget!K10*42% -> 0 | L10: =Revenue_Budget!L10*42% -> 0 | M10: =Revenue_Budget!M10*42% -> 0 | N10: =Revenue_Budget!N10*42% -> 0 | O10: =Revenue_Budget!O10*42% -> 0 | ... S10: =Revenue_Budget!S10*42% -> 0
A11: FY2024-25 | B11: SKF India | C11: =VLOOKUP(B11,Mapping!B:C,2,0) -> Lateral | D11: =VLOOKUP(B11,Mapping!B:D,3,0) -> North | E11: =VLOOKUP(B11,Mapping!B:E,4,0) -> North | F11: =VLOOKUP(B11,Mapping!B:F,5,0) -> Anjli | G11: =VLOOKUP(B11,Mapping!B:G,6,0) -> Archana | H11: =Revenue_Budget!H11*42% -> 4.7775 | I11: =Revenue_Budget!I11*42% -> 6.6885 | J11: =Revenue_Budget!J11*42% -> 7.644 | K11: =Revenue_Budget!K11*42% -> 4.83 | L11: =Revenue_Budget!L11*42% -> 6.762 | M11: =Revenue_Budget!M11*42% -> 7.728 | N11: =Revenue_Budget!N11*42% -> 4.83 | O11: =Revenue_Budget!O11*42% -> 6.762 | ... S11: =Revenue_Budget!S11*42% -> 7.78344
A12: FY2024-25 | B12: Jindal Stainless | C12: =VLOOKUP(B12,Mapping!B:C,2,0) -> Lateral | D12: =VLOOKUP(B12,Mapping!B:D,3,0) -> North | E12: =VLOOKUP(B12,Mapping!B:E,4,0) -> North | F12: =VLOOKUP(B12,Mapping!B:F,5,0) -> Anjli | G12: =VLOOKUP(B12,Mapping!B:G,6,0) -> Archana | H12: =Revenue_Budget!H12*42% -> 3.78 | I12: =Revenue_Budget!I12*42% -> 5.292 | J12: =Revenue_Budget!J12*42% -> 6.048 | K12: =Revenue_Budget!K12*42% -> 3.32115 | L12: =Revenue_Budget!L12*42% -> 4.64961 | M12: =Revenue_Budget!M12*42% -> 5.31384 | N12: =Revenue_Budget!N12*42% -> 3.21615 | O12: =Revenue_Budget!O12*42% -> 4.50261 | ... S12: =Revenue_Budget!S12*42% -> 5.28528
A13: FY2024-25 | B13: Maruti Suzuki(MSIL) | C13: =VLOOKUP(B13,Mapping!B:C,2,0) -> Lateral | D13: =VLOOKUP(B13,Mapping!B:D,3,0) -> North | E13: =VLOOKUP(B13,Mapping!B:E,4,0) -> North | F13: =VLOOKUP(B13,Mapping!B:F,5,0) -> Anjli | G13: =VLOOKUP(B13,Mapping!B:G,6,0) -> Archana | H13: =Revenue_Budget!H13*42% -> 1.785 | I13: =Revenue_Budget!I13*42% -> 2.499 | J13: =Revenue_Budget!J13*42% -> 2.856 | K13: =Revenue_Budget!K13*42% -> 3.15 | L13: =Revenue_Budget!L13*42% -> 4.41 | M13: =Revenue_Budget!M13*42% -> 5.04 | N13: =Revenue_Budget!N13*42% -> 3.675 | O13: =Revenue_Budget!O13*42% -> 5.145 | ... S13: =Revenue_Budget!S13*42% -> 6.72
... A58: FY2024-25 | B58: New Sales + Mining | C58: =VLOOKUP(B58,Mapping!B:C,2,0) -> Lateral | D58: =VLOOKUP(B58,Mapping!B:D,3,0) -> New Sales | E58: =VLOOKUP(B58,Mapping!B:E,4,0) -> New Sales | F58: =VLOOKUP(B58,Mapping!B:F,5,0) -> Nizar | G58: =VLOOKUP(B58,Mapping!B:G,6,0) -> Nizar | H58: =Revenue_Budget!H58*42% -> 40.288466 | I58: =Revenue_Budget!I58*42% -> 56.403853 | J58: =Revenue_Budget!J58*42% -> 64.461546 | K58: =Revenue_Budget!K58*42% -> 80.576933 | L58: =Revenue_Budget!L58*42% -> 112.80771 | M58: =Revenue_Budget!M58*42% -> 128.92309 | N58: =Revenue_Budget!N58*42% -> 120.8654 | O58: =Revenue_Budget!O58*42% -> 169.21156 | ... S58: =Revenue_Budget!S58*42% -> 257.84618
H59: Check denomination

Sheet Target_Rev_Productivity
A1: FY | B1: Project | C1: Vertical | D1: Region | E1: Sub Region | F1: Region Head | G1: Practice Head | H1: 45383 | I1: =EDATE(H1,1) -> 45413 | J1: =EDATE(I1,1) -> 45444 | K1: =EDATE(J1,1) -> 45474 | L1: =EDATE(K1,1) -> 45505 | M1: =EDATE(L1,1) -> 45536 | N1: =EDATE(M1,1) -> 45566 | O1: =EDATE(N1,1) -> 45597 | P1: =EDATE(O1,1) -> 45627 | ... S1: =EDATE(R1,1) -> 45717
A2: FY2024-25 | B2: Tata Motors | C2: =VLOOKUP(B2,Mapping!B:C,2,0) -> Lateral | D2: =VLOOKUP(B2,Mapping!B:D,3,0) -> West | E2: =VLOOKUP(B2,Mapping!B:E,4,0) -> West 2 | F2: =VLOOKUP(B2,Mapping!B:F,5,0) -> Anjli | G2: =VLOOKUP(B2,Mapping!B:G,6,0) -> Shweta | H2: 0.97948379 | I2: 0.98666667 | J2: 1.1285266 | K2: 1.2770642 | L2: 1.6457143 | M2: 1.1889908 | N2: 1.1889908 | O2: 1.2274884 | P2: 2.644898 | Q2: 1.6858537 | R2: 1.5652174 | S2: 3.78
A3: FY2024-25 | B3: Schaeffler | C3: =VLOOKUP(B3,Mapping!B:C,2,0) -> Lateral | D3: =VLOOKUP(B3,Mapping!B:D,3,0) -> West | E3: =VLOOKUP(B3,Mapping!B:E,4,0) -> West 2 | F3: =VLOOKUP(B3,Mapping!B:F,5,0) -> Anjli | G3: =VLOOKUP(B3,Mapping!B:G,6,0) -> Shweta | H3: 1.3010204 | I3: 1.6363636 | J3: 1.4482759 | K3: 1.5867769 | L3: 1.7142857 | M3: 2.7428571 | N3: 1.3090909 | O3: 1.5 | P3: 0.22222222 | Q3: 1.904 | R3: 1.8 | S3: 2.6237333
A4: FY2024-25 | B4: Vertiv | C4: =VLOOKUP(B4,Mapping!B:C,2,0) -> Lateral | D4: =VLOOKUP(B4,Mapping!B:D,3,0) -> West | E4: =VLOOKUP(B4,Mapping!B:E,4,0) -> West 2 | F4: =VLOOKUP(B4,Mapping!B:F,5,0) -> Anjli | G4: =VLOOKUP(B4,Mapping!B:G,6,0) -> Shweta | H4: 0.8 | I4: 1.4 | J4: 0.91 | K4: 2.25 | L4: 1.14 | M4: 1.8 | N4: 0.66 | O4: 1.88 | P4: 3.04 | Q4: 1.369 | R4: 0.96 | S4: 0.248
A5: FY2024-25 | B5: Tata Marcopolo | C5: =VLOOKUP(B5,Mapping!B:C,2,0) -> Lateral | D5: =VLOOKUP(B5,Mapping!B:D,3,0) -> West | E5: =VLOOKUP(B5,Mapping!B:E,4,0) -> West 2 | F5: =VLOOKUP(B5,Mapping!B:F,5,0) -> Anjli | G5: =VLOOKUP(B5,Mapping!B:G,6,0) -> Anjli | H5: 0.84 | I5: 2.28 | J5: 1.704 | K5: 0.492 | L5: 2.4 | M5: 2.508 | N5: 0.132 | O5: 1.8 | P5: 1.8 | Q5: 1.8 | R5: 1.8 | S5: 0.912
A6: FY2024-25 | B6: ThyssenKrupp | C6: =VLOOKUP(B6,Mapping!B:C,2,0) -> Lateral | D6: =VLOOKUP(B6,Mapping!B:D,3,0) -> West | E6: =VLOOKUP(B6,Mapping!B:E,4,0) -> West 2 | F6: =VLOOKUP(B6,Mapping!B:F,5,0) -> Anjli | G6: =VLOOKUP(B6,Mapping!B:G,6,0) -> Shweta | H6: 1.7585485 | I6: 1.8 | J6: 1.8544832 | K6: 1.495082 | L6: 1.8526316 | M6: 1.7723077 | N6: 1.28 | O6: 0.90857143 | P6: 3.4285714 | Q6: 1.8 | R6: 30 | S6: 1.8
A7: FY2024-25 | B7: Ultratech | C7: =VLOOKUP(B7,Mapping!B:C,2,0) -> Lateral | D7: =VLOOKUP(B7,Mapping!B:D,3,0) -> West | E7: =VLOOKUP(B7,Mapping!B:E,4,0) -> West 1 | F7: =VLOOKUP(B7,Mapping!B:F,5,0) -> Anjli | G7: =VLOOKUP(B7,Mapping!B:G,6,0) -> Elton | H7: 1.248 | I7: -0.132 | J7: 1.2 | K7: 0.12 | L7: 1.8 | M7: 1.8 | N7: 1.8 | O7: 1.8 | P7: 1.8 | Q7: 1.8 | R7: 1.8 | S7: 1.8
A8: FY2024-25 | B8: Tata Teleservices | C8: =VLOOKUP(B8,Mapping!B:C,2,0) -> Lateral | D8: =VLOOKUP(B8,Mapping!B:D,3,0) -> West | E8: =VLOOKUP(B8,Mapping!B:E,4,0) -> West 1 | F8: =VLOOKUP(B8,Mapping!B:F,5,0) -> Anjli | G8: =VLOOKUP(B8,Mapping!B:G,6,0) -> Elton | H8: 1.8 | I8: 1.8 | J8: 1.8 | K8: 1.8 | L8: 1.8 | M8: 1.8 | N8: 1.8 | O8: 1.8 | P8: 1.8 | Q8: 1.8 | R8: 1.8 | S8: 1.8
A9: FY2024-25 | B9: Hyundai Motor | C9: =VLOOKUP(B9,Mapping!B:C,2,0) -> Lateral | D9: =VLOOKUP(B9,Mapping!B:D,3,0) -> West | E9: =VLOOKUP(B9,Mapping!B:E,4,0) -> West 2 | F9: =VLOOKUP(B9,Mapping!B:F,5,0) -> Anjli | G9: =VLOOKUP(B9,Mapping!B:G,6,0) -> Shweta | H9: 0.9984 | I9: 4.92 | J9: 2.4888 | K9: 2.8571429 | L9: 3.2 | M9: 3.2 | N9: 1.6340426 | O9: 2.5008 | P9: 1.25 | Q9: 1.6236 | R9: 1.5 | S9: 1.3935484
A10: FY2024-25 | B10: Bridgestone | C10: =VLOOKUP(B10,Mapping!B:C,2,0) -> Lateral | D10: =VLOOKUP(B10,Mapping!B:D,3,0) -> West | E10: =VLOOKUP(B10,Mapping!B:E,4,0) -> West 2 | F10: =VLOOKUP(B10,Mapping!B:F,5,0) -> Anjli | G10: =VLOOKUP(B10,Mapping!B:G,6,0) -> Shweta | H10: 1.8 | I10: 1.8 | J10: 1.8 | K10: 1.8 | L10: 1.8 | M10: 1.8 | N10: 1.8 | O10: 0.72 | P10: 1.8 | Q10: 1.32 | R10: 0.6 | S10: 2
A11: FY2024-25 | B11: SKF India | C11: =VLOOKUP(B11,Mapping!B:C,2,0) -> Lateral | D11: =VLOOKUP(B11,Mapping!B:D,3,0) -> North | E11: =VLOOKUP(B11,Mapping!B:E,4,0) -> North | F11: =VLOOKUP(B11,Mapping!B:F,5,0) -> Anjli | G11: =VLOOKUP(B11,Mapping!B:G,6,0) -> Archana | H11: 2.4252632 | I11: 2.3428571 | J11: 1.8743259 | K11: 1.2 | L11: 1.6363636 | M11: 2.0727273 | N11: 1.84 | O11: 2.7333333 | P11: 1.8666667 | Q11: 3.4666667 | R11: 2 | S11: 1.7466667
A12: FY2024-25 | B12: Jindal Stainless | C12: =VLOOKUP(B12,Mapping!B:C,2,0) -> Lateral | D12: =VLOOKUP(B12,Mapping!B:D,3,0) -> North | E12: =VLOOKUP(B12,Mapping!B:E,4,0) -> North | F12: =VLOOKUP(B12,Mapping!B:F,5,0) -> Anjli | G12: =VLOOKUP(B12,Mapping!B:G,6,0) -> Archana | H12: 1.2631579 | I12: 1.8 | J12: 2.52 | K12: 1.56 | L12: 2.0666667 | M12: 3 | N12: 1.8 | O12: 1.425 | P12: 2.4 | Q12: 1.975611 | R12: 1.236 | S12: 4.014
A13: FY2024-25 | B13: Maruti Suzuki(MSIL) | C13: =VLOOKUP(B13,Mapping!B:C,2,0) -> Lateral | D13: =VLOOKUP(B13,Mapping!B:D,3,0) -> North | E13: =VLOOKUP(B13,Mapping!B:E,4,0) -> North | F13: =VLOOKUP(B13,Mapping!B:F,5,0) -> Anjli | G13: =VLOOKUP(B13,Mapping!B:G,6,0) -> Archana | H13: 6 | I13: 0.438 | J13: 4.11 | K13: 0.74534161 | L13: 0.61538462 | M13: 0.31840796 | N13: 1.0344828 | O13: 1.0068966 | P13: 0.97333333 | Q13: 0.67848101 | R13: 0.51724138 | S13: 1.9901714
... A58: FY2024-25 | B58: New Sales + Mining | C58: =VLOOKUP(B58,Mapping!B:C,2,0) -> Lateral | D58: =VLOOKUP(B58,Mapping!B:D,3,0) -> New Sales | E58: =VLOOKUP(B58,Mapping!B:E,4,0) -> New Sales | F58: =VLOOKUP(B58,Mapping!B:F,5,0) -> Nizar | G58: =VLOOKUP(B58,Mapping!B:G,6,0) -> Nizar | H58: 1.8 | I58: 1.8 | J58: 1.8 | K58: 1.8 | L58: 1.8 | M58: 1.8 | N58: 1.8 | O58: 1.8 | P58: 1.8 | Q58: 1.8 | R58: 1.8 | S58: 1.8
H59: Value= Per recuiter per project in Lacs

Sheet Rev_Forecast
A1: FY | B1: Project | C1: Vertical | D1: Region | E1: Sub Region | F1: Region Head | G1: Practice Head | H1: 45383 | I1: =EDATE(H1,1) -> 45413 | J1: =EDATE(I1,1) -> 45444 | K1: =EDATE(J1,1) -> 45474 | L1: =EDATE(K1,1) -> 45505 | M1: =EDATE(L1,1) -> 45536 | N1: =EDATE(M1,1) -> 45566 | O1: =EDATE(N1,1) -> 45597 | P1: =EDATE(O1,1) -> 45627 | ... S1: =EDATE(R1,1) -> 45717
A2: FY2024-25 | B2: Tata Motors | C2: =VLOOKUP(B2,Mapping!B:C,2,0) -> Lateral | D2: =VLOOKUP(B2,Mapping!B:D,3,0) -> West | E2: =VLOOKUP(B2,Mapping!B:E,4,0) -> West 2 | F2: =VLOOKUP(B2,Mapping!B:F,5,0) -> Anjli | G2: =VLOOKUP(B2,Mapping!B:G,6,0) -> Shweta | H2: 25 | I2: 35 | J2: 40 | K2: 43.5 | L2: 60.9 | M2: 69.6 | N2: 49.025 | O2: 68.635 | P2: 78.44 | Q2: 50.8825 | R2: 71.2355 | S2: 81.412
A3: FY2024-25 | B3: Schaeffler | C3: =VLOOKUP(B3,Mapping!B:C,2,0) -> Lateral | D3: =VLOOKUP(B3,Mapping!B:D,3,0) -> West | E3: =VLOOKUP(B3,Mapping!B:E,4,0) -> West 2 | F3: =VLOOKUP(B3,Mapping!B:F,5,0) -> Anjli | G3: =VLOOKUP(B3,Mapping!B:G,6,0) -> Shweta | H3: 6.175 | I3: 8.645 | J3: 9.88 | K3: 6.35 | L3: 8.89 | M3: 10.16 | N3: 6.65 | O3: 9.31 | P3: 10.64 | Q3: 7.0325 | R3: 9.8455 | S3: 11.252
A4: FY2024-25 | B4: Vertiv | C4: =VLOOKUP(B4,Mapping!B:C,2,0) -> Lateral | D4: =VLOOKUP(B4,Mapping!B:D,3,0) -> West | E4: =VLOOKUP(B4,Mapping!B:E,4,0) -> West 2 | F4: =VLOOKUP(B4,Mapping!B:F,5,0) -> Anjli | G4: =VLOOKUP(B4,Mapping!B:G,6,0) -> Shweta | H4: 3 | I4: 4.2 | J4: 4.8 | K4: 3.675 | L4: 5.145 | M4: 5.88 | N4: 3.825 | O4: 5.355 | P4: 6.12 | Q4: 4.0575 | R4: 5.6805 | S4: 6.492
A5: FY2024-25 | B5: Tata Marcopolo | C5: =VLOOKUP(B5,Mapping!B:C,2,0) -> Lateral | D5: =VLOOKUP(B5,Mapping!B:D,3,0) -> West | E5: =VLOOKUP(B5,Mapping!B:E,4,0) -> West 2 | F5: =VLOOKUP(B5,Mapping!B:F,5,0) -> Anjli | G5: =VLOOKUP(B5,Mapping!B:G,6,0) -> Anjli | H5: 1.125 | I5: 1.575 | J5: 1.8 | K5: 1.125 | L5: 1.575 | M5: 1.8 | N5: 1.125 | O5: 1.575 | P5: 1.8 | Q5: 1.2075 | R5: 1.6905 | S5: 1.932
A6: FY2024-25 | B6: ThyssenKrupp | C6: =VLOOKUP(B6,Mapping!B:C,2,0) -> Lateral | D6: =VLOOKUP(B6,Mapping!B:D,3,0) -> West | E6: =VLOOKUP(B6,Mapping!B:E,4,0) -> West 2 | F6: =VLOOKUP(B6,Mapping!B:F,5,0) -> Anjli | G6: =VLOOKUP(B6,Mapping!B:G,6,0) -> Shweta | H6: 15.4 | I6: 21.56 | J6: 24.64 | K6: 15.925 | L6: 22.295 | M6: 25.48 | N6: 16.575 | O6: 23.205 | P6: 26.52 | Q6: 17.3075 | R6: 24.2305 | S6: 27.692
A7: FY2024-25 | B7: Ultratech | C7: =VLOOKUP(B7,Mapping!B:C,2,0) -> Lateral | D7: =VLOOKUP(B7,Mapping!B:D,3,0) -> West | E7: =VLOOKUP(B7,Mapping!B:E,4,0) -> West 1 | F7: =VLOOKUP(B7,Mapping!B:F,5,0) -> Anjli | G7: =VLOOKUP(B7,Mapping!B:G,6,0) -> Elton | H7: 0.375 | I7: 0.525 | J7: 0.6 | K7: 1.8 | L7: 2.52 | M7: 2.88 | N7: 1.95 | O7: 2.73 | P7: 3.12 | Q7: 2.1825 | R7: 3.0555 | S7: 3.492
A8: FY2024-25 | B8: Tata Teleservices | C8: =VLOOKUP(B8,Mapping!B:C,2,0) -> Lateral | D8: =VLOOKUP(B8,Mapping!B:D,3,0) -> West | E8: =VLOOKUP(B8,Mapping!B:E,4,0) -> West 1 | F8: =VLOOKUP(B8,Mapping!B:F,5,0) -> Anjli | G8: =VLOOKUP(B8,Mapping!B:G,6,0) -> Elton | H8: 3.125 | I8: 4.375 | J8: 5 | K8: 6.25 | L8: 8.75 | M8: 10 | N8: 6.25 | O8: 8.75 | P8: 10 | Q8: 6.3325 | R8: 8.8655 | S8: 10.132
A9: FY2024-25 | B9: Hyundai Motor | C9: =VLOOKUP(B9,Mapping!B:C,2,0) -> Lateral | D9: =VLOOKUP(B9,Mapping!B:D,3,0) -> West | E9: =VLOOKUP(B9,Mapping!B:E,4,0) -> West 2 | F9: =VLOOKUP(B9,Mapping!B:F,5,0) -> Anjli | G9: =VLOOKUP(B9,Mapping!B:G,6,0) -> Shweta | H9: 3.75 | I9: 5.25 | J9: 6 | K9: 7.5 | L9: 10.5 | M9: 12 | N9: 10 | O9: 14 | P9: 16 | Q9: 8 | R9: 11.2 | S9: 12.8
A10: FY2024-25 | B10: Bridgestone | C10: =VLOOKUP(B10,Mapping!B:C,2,0) -> Lateral | D10: =VLOOKUP(B10,Mapping!B:D,3,0) -> West | E10: =VLOOKUP(B10,Mapping!B:E,4,0) -> West 2 | F10: =VLOOKUP(B10,Mapping!B:F,5,0) -> Anjli | G10: =VLOOKUP(B10,Mapping!B:G,6,0) -> Shweta | H10: 0 | I10: 0 | J10: 0 | K10: 0 | L10: 0 | M10: 0 | N10: 0 | O10: 0 | P10: 0 | Q10: 0 | R10: 0 | S10: 0
A11: FY2024-25 | B11: SKF India | C11: =VLOOKUP(B11,Mapping!B:C,2,0) -> Lateral | D11: =VLOOKUP(B11,Mapping!B:D,3,0) -> North | E11: =VLOOKUP(B11,Mapping!B:E,4,0) -> North | F11: =VLOOKUP(B11,Mapping!B:F,5,0) -> Anjli | G11: =VLOOKUP(B11,Mapping!B:G,6,0) -> Archana | H11: 11.375 | I11: 15.925 | J11: 18.2 | K11: 11.5 | L11: 16.1 | M11: 18.4 | N11: 11.5 | O11: 16.1 | P11: 18.4 | Q11: 11.5825 | R11: 16.2155 | S11: 18.532
A12: FY2024-25 | B12: Jindal Stainless | C12: =VLOOKUP(B12,Mapping!B:C,2,0) -> Lateral | D12: =VLOOKUP(B12,Mapping!B:D,3,0) -> North | E12: =VLOOKUP(B12,Mapping!B:E,4,0) -> North | F12: =VLOOKUP(B12,Mapping!B:F,5,0) -> Anjli | G12: =VLOOKUP(B12,Mapping!B:G,6,0) -> Archana | H12: 9 | I12: 12.6 | J12: 14.4 | K12: 7.9075 | L12: 11.0705 | M12: 12.652 | N12: 7.6575 | O12: 10.7205 | P12: 12.252 | Q12: 7.865 | R12: 11.011 | S12: 12.584
A13: FY2024-25 | B13: Maruti Suzuki(MSIL) | C13: =VLOOKUP(B13,Mapping!B:C,2,0) -> Lateral | D13: =VLOOKUP(B13,Mapping!B:D,3,0) -> North | E13: =VLOOKUP(B13,Mapping!B:E,4,0) -> North | F13: =VLOOKUP(B13,Mapping!B:F,5,0) -> Anjli | G13: =VLOOKUP(B13,Mapping!B:G,6,0) -> Archana | H13: 4.25 | I13: 5.95 | J13: 6.8 | K13: 7.5 | L13: 10.5 | M13: 12 | N13: 8.75 | O13: 12.25 | P13: 14 | Q13: 10 | R13: 14 | S13: 16
... A57: FY2024-25 | B57: Common | C57: =VLOOKUP(B57,Mapping!B:C,2,0) -> Lateral | D57: =VLOOKUP(B57,Mapping!B:D,3,0) -> Common | E57: =VLOOKUP(B57,Mapping!B:E,4,0) -> North | F57: =VLOOKUP(B57,Mapping!B:F,5,0) -> Common | G57: =VLOOKUP(B57,Mapping!B:G,6,0) -> Common | H57: 12.5 | I57: 17.5 | J57: 20 | K57: 0 | L57: 0 | M57: 0 | N57: 0 | O57: 0 | P57: 0 | Q57: 0 | R57: 0 | S57: 0
I58: Rev forecast in lacs

Sheet CM_Forecast
A1: FY | B1: Project | C1: Vertical | D1: Region | E1: Sub Region | F1: Region Head | G1: Practice Head | H1: 45383 | I1: =EDATE(H1,1) -> 45413 | J1: =EDATE(I1,1) -> 45444 | K1: =EDATE(J1,1) -> 45474 | L1: =EDATE(K1,1) -> 45505 | M1: =EDATE(L1,1) -> 45536 | N1: =EDATE(M1,1) -> 45566 | O1: =EDATE(N1,1) -> 45597 | P1: =EDATE(O1,1) -> 45627 | ... S1: =EDATE(R1,1) -> 45717
A2: FY2024-25 | B2: Tata Motors | C2: =VLOOKUP(B2,Mapping!B:C,2,0) -> Lateral | D2: =VLOOKUP(B2,Mapping!B:D,3,0) -> West | E2: =VLOOKUP(B2,Mapping!B:E,4,0) -> West 2 | F2: =VLOOKUP(B2,Mapping!B:F,5,0) -> Anjli | G2: =VLOOKUP(B2,Mapping!B:G,6,0) -> Shweta | H2: =CM_Budget!H2-95% -> 9.55 | I2: =CM_Budget!I2-95% -> 13.75 | J2: =CM_Budget!J2-95% -> 15.85 | K2: =CM_Budget!K2-95% -> 17.32 | L2: =CM_Budget!L2-95% -> 24.628 | M2: =CM_Budget!M2-95% -> 28.282 | N2: =CM_Budget!N2-95% -> 19.6405 | O2: =CM_Budget!O2-95% -> 27.8767 | ... S2: =CM_Budget!S2-95% -> 33.24304
A3: FY2024-25 | B3: Schaeffler | C3: =VLOOKUP(B3,Mapping!B:C,2,0) -> Lateral | D3: =VLOOKUP(B3,Mapping!B:D,3,0) -> West | E3: =VLOOKUP(B3,Mapping!B:E,4,0) -> West 2 | F3: =VLOOKUP(B3,Mapping!B:F,5,0) -> Anjli | G3: =VLOOKUP(B3,Mapping!B:G,6,0) -> Shweta | H3: =CM_Budget!H3-95% -> 1.6435 | I3: =CM_Budget!I3-95% -> 2.6809 | J3: =CM_Budget!J3-95% -> 3.1996 | K3: =CM_Budget!K3-95% -> 1.717 | L3: =CM_Budget!L3-95% -> 2.7838 | M3: =CM_Budget!M3-95% -> 3.3172 | N3: =CM_Budget!N3-95% -> 1.843 | O3: =CM_Budget!O3-95% -> 2.9602 | ... S3: =CM_Budget!S3-95% -> 3.77584
A4: FY2024-25 | B4: Vertiv | C4: =VLOOKUP(B4,Mapping!B:C,2,0) -> Lateral | D4: =VLOOKUP(B4,Mapping!B:D,3,0) -> West | E4: =VLOOKUP(B4,Mapping!B:E,4,0) -> West 2 | F4: =VLOOKUP(B4,Mapping!B:F,5,0) -> Anjli | G4: =VLOOKUP(B4,Mapping!B:G,6,0) -> Shweta | H4: =CM_Budget!H4-95% -> 0.31 | I4: =CM_Budget!I4-95% -> 0.814 | J4: =CM_Budget!J4-95% -> 1.066 | K4: =CM_Budget!K4-95% -> 0.5935 | L4: =CM_Budget!L4-95% -> 1.2109 | M4: =CM_Budget!M4-95% -> 1.5196 | N4: =CM_Budget!N4-95% -> 0.6565 | O4: =CM_Budget!O4-95% -> 1.2991 | ... S4: =CM_Budget!S4-95% -> 1.77664
A5: FY2024-25 | B5: Tata Marcopolo | C5: =VLOOKUP(B5,Mapping!B:C,2,0) -> Lateral | D5: =VLOOKUP(B5,Mapping!B:D,3,0) -> West | E5: =VLOOKUP(B5,Mapping!B:E,4,0) -> West 2 | F5: =VLOOKUP(B5,Mapping!B:F,5,0) -> Anjli | G5: =VLOOKUP(B5,Mapping!B:G,6,0) -> Anjli | H5: =CM_Budget!H5-95% -> -0.4775 | I5: =CM_Budget!I5-95% -> -0.2885 | J5: =CM_Budget!J5-95% -> -0.194 | K5: =CM_Budget!K5-95% -> -0.4775 | L5: =CM_Budget!L5-95% -> -0.2885 | M5: =CM_Budget!M5-95% -> -0.194 | N5: =CM_Budget!N5-95% -> -0.4775 | O5: =CM_Budget!O5-95% -> -0.2885 | ... S5: =CM_Budget!S5-95% -> -0.13856
A6: FY2024-25 | B6: ThyssenKrupp | C6: =VLOOKUP(B6,Mapping!B:C,2,0) -> Lateral | D6: =VLOOKUP(B6,Mapping!B:D,3,0) -> West | E6: =VLOOKUP(B6,Mapping!B:E,4,0) -> West 2 | F6: =VLOOKUP(B6,Mapping!B:F,5,0) -> Anjli | G6: =VLOOKUP(B6,Mapping!B:G,6,0) -> Shweta | H6: =CM_Budget!H6-95% -> 5.518 | I6: =CM_Budget!I6-95% -> 8.1052 | J6: =CM_Budget!J6-95% -> 9.3988 | K6: =CM_Budget!K6-95% -> 5.7385 | L6: =CM_Budget!L6-95% -> 8.4139 | M6: =CM_Budget!M6-95% -> 9.7516 | N6: =CM_Budget!N6-95% -> 6.0115 | O6: =CM_Budget!O6-95% -> 8.7961 | ... S6: =CM_Budget!S6-95% -> 10.68064
A7: FY2024-25 | B7: Ultratech | C7: =VLOOKUP(B7,Mapping!B:C,2,0) -> Lateral | D7: =VLOOKUP(B7,Mapping!B:D,3,0) -> West | E7: =VLOOKUP(B7,Mapping!B:E,4,0) -> West 1 | F7: =VLOOKUP(B7,Mapping!B:F,5,0) -> Anjli | G7: =VLOOKUP(B7,Mapping!B:G,6,0) -> Elton | H7: =CM_Budget!H7-95% -> -0.7925 | I7: =CM_Budget!I7-95% -> -0.7295 | J7: =CM_Budget!J7-95% -> -0.698 | K7: =CM_Budget!K7-95% -> -0.194 | L7: =CM_Budget!L7-95% -> 0.1084 | M7: =CM_Budget!M7-95% -> 0.2596 | N7: =CM_Budget!N7-95% -> -0.131 | O7: =CM_Budget!O7-95% -> 0.1966 | ... S7: =CM_Budget!S7-95% -> 0.51664
A8: FY2024-25 | B8: Tata Teleservices | C8: =VLOOKUP(B8,Mapping!B:C,2,0) -> Lateral | D8: =VLOOKUP(B8,Mapping!B:D,3,0) -> West | E8: =VLOOKUP(B8,Mapping!B:E,4,0) -> West 1 | F8: =VLOOKUP(B8,Mapping!B:F,5,0) -> Anjli | G8: =VLOOKUP(B8,Mapping!B:G,6,0) -> Elton | H8: =CM_Budget!H8-95% -> 0.3625 | I8: =CM_Budget!I8-95% -> 0.8875 | J8: =CM_Budget!J8-95% -> 1.15 | K8: =CM_Budget!K8-95% -> 1.675 | L8: =CM_Budget!L8-95% -> 2.725 | M8: =CM_Budget!M8-95% -> 3.25 | N8: =CM_Budget!N8-95% -> 1.675 | O8: =CM_Budget!O8-95% -> 2.725 | ... S8: =CM_Budget!S8-95% -> 3.30544
A9: FY2024-25 | B9: Hyundai Motor | C9: =VLOOKUP(B9,Mapping!B:C,2,0) -> Lateral | D9: =VLOOKUP(B9,Mapping!B:D,3,0) -> West | E9: =VLOOKUP(B9,Mapping!B:E,4,0) -> West 2 | F9: =VLOOKUP(B9,Mapping!B:F,5,0) -> Anjli | G9: =VLOOKUP(B9,Mapping!B:G,6,0) -> Shweta | H9: =CM_Budget!H9-95% -> 0.625 | I9: =CM_Budget!I9-95% -> 1.255 | J9: =CM_Budget!J9-95% -> 1.57 | K9: =CM_Budget!K9-95% -> 2.2 | L9: =CM_Budget!L9-95% -> 3.46 | M9: =CM_Budget!M9-95% -> 4.09 | N9: =CM_Budget!N9-95% -> 3.25 | O9: =CM_Budget!O9-95% -> 4.93 | ... S9: =CM_Budget!S9-95% -> 4.426
A10: FY2024-25 | B10: Bridgestone | C10: =VLOOKUP(B10,Mapping!B:C,2,0) -> Lateral | D10: =VLOOKUP(B10,Mapping!B:D,3,0) -> West | E10: =VLOOKUP(B10,Mapping!B:E,4,0) -> West 2 | F10: =VLOOKUP(B10,Mapping!B:F,5,0) -> Anjli | G10: =VLOOKUP(B10,Mapping!B:G,6,0) -> Shweta | H10: =CM_Budget!H10-95% -> -0.95 | I10: =CM_Budget!I10-95% -> -0.95 | J10: =CM_Budget!J10-95% -> -0.95 | K10: =CM_Budget!K10-95% -> -0.95 | L10: =CM_Budget!L10-95% -> -0.95 | M10: =CM_Budget!M10-95% -> -0.95 | N10: =CM_Budget!N10-95% -> -0.95 | O10: =CM_Budget!O10-95% -> -0.95 | ... S10: =CM_Budget!S10-95% -> -0.95
A11: FY2024-25 | B11: SKF India | C11: =VLOOKUP(B11,Mapping!B:C,2,0) -> Lateral | D11: =VLOOKUP(B11,Mapping!B:D,3,0) -> North | E11: =VLOOKUP(B11,Mapping!B:E,4,0) -> North | F11: =VLOOKUP(B11,Mapping!B:F,5,0) -> Anjli | G11: =VLOOKUP(B11,Mapping!B:G,6,0) -> Archana | H11: =CM_Budget!H11-95% -> 3.8275 | I11: =CM_Budget!I11-95% -> 5.7385 | J11: =CM_Budget!J11-95% -> 6.694 | K11: =CM_Budget!K11-95% -> 3.88 | L11: =CM_Budget!L11-95% -> 5.812 | M11: =CM_Budget!M11-95% -> 6.778 | N11: =CM_Budget!N11-95% -> 3.88 | O11: =CM_Budget!O11-95% -> 5.812 | ... S11: =CM_Budget!S11-95% -> 6.83344
A12: FY2024-25 | B12: Jindal Stainless | C12: =VLOOKUP(B12,Mapping!B:C,2,0) -> Lateral | D12: =VLOOKUP(B12,Mapping!B:D,3,0) -> North | E12: =VLOOKUP(B12,Mapping!B:E,4,0) -> North | F12: =VLOOKUP(B12,Mapping!B:F,5,0) -> Anjli | G12: =VLOOKUP(B12,Mapping!B:G,6,0) -> Archana | H12: =CM_Budget!H12-95% -> 2.83 | I12: =CM_Budget!I12-95% -> 4.342 | J12: =CM_Budget!J12-95% -> 5.098 | K12: =CM_Budget!K12-95% -> 2.37115 | L12: =CM_Budget!L12-95% -> 3.69961 | M12: =CM_Budget!M12-95% -> 4.36384 | N12: =CM_Budget!N12-95% -> 2.26615 | O12: =CM_Budget!O12-95% -> 3.55261 | ... S12: =CM_Budget!S12-95% -> 4.33528
A13: FY2024-25 | B13: Maruti Suzuki(MSIL) | C13: =VLOOKUP(B13,Mapping!B:C,2,0) -> Lateral | D13: =VLOOKUP(B13,Mapping!B:D,3,0) -> North | E13: =VLOOKUP(B13,Mapping!B:E,4,0) -> North | F13: =VLOOKUP(B13,Mapping!B:F,5,0) -> Anjli | G13: =VLOOKUP(B13,Mapping!B:G,6,0) -> Archana | H13: =CM_Budget!H13-95% -> 0.835 | I13: =CM_Budget!I13-95% -> 1.549 | J13: =CM_Budget!J13-95% -> 1.906 | K13: =CM_Budget!K13-95% -> 2.2 | L13: =CM_Budget!L13-95% -> 3.46 | M13: =CM_Budget!M13-95% -> 4.09 | N13: =CM_Budget!N13-95% -> 2.725 | O13: =CM_Budget!O13-95% -> 4.195 | ... S13: =CM_Budget!S13-95% -> 5.77
... A57: FY2024-25 | B57: Common | C57: =VLOOKUP(B57,Mapping!B:C,2,0) -> Lateral | D57: =VLOOKUP(B57,Mapping!B:D,3,0) -> Common | E57: =VLOOKUP(B57,Mapping!B:E,4,0) -> North | F57: =VLOOKUP(B57,Mapping!B:F,5,0) -> Common | G57: =VLOOKUP(B57,Mapping!B:G,6,0) -> Common | H57: =CM_Budget!H57-95% -> 4.3 | I57: =CM_Budget!I57-95% -> 6.4 | J57: =CM_Budget!J57-95% -> 7.45 | K57: =CM_Budget!K57-95% -> -0.95 | L57: =CM_Budget!L57-95% -> -0.95 | M57: =CM_Budget!M57-95% -> -0.95 | N57: =CM_Budget!N57-95% -> -0.95 | O57: =CM_Budget!O57-95% -> -0.95 | ... S57: =CM_Budget!S57-95% -> -0.95
G59: CM= Contribution Margin in Lacs

Sheet Revenue_Actual
A1: FY | B1: Project | C1: Vertical | D1: Region | E1: Sub Region | F1: Region Head | G1: Practice Head | H1: 45383 | I1: =EDATE(H1,1) -> 45413 | J1: =EDATE(I1,1) -> 45444 | K1: =EDATE(J1,1) -> 45474 | L1: =EDATE(K1,1) -> 45505 | M1: =EDATE(L1,1) -> 45536 | N1: =EDATE(M1,1) -> 45566 | O1: =EDATE(N1,1) -> 45597 | P1: =EDATE(O1,1) -> 45627 | ... S1: =EDATE(R1,1) -> 45717
A2: FY2024-25 | B2: Tata Motors | C2: =VLOOKUP(B2,Mapping!B:C,2,0) -> Lateral | D2: =VLOOKUP(B2,Mapping!B:D,3,0) -> West | E2: =VLOOKUP(B2,Mapping!B:E,4,0) -> West 2 | F2: =VLOOKUP(B2,Mapping!B:F,5,0) -> Anjli | G2: =VLOOKUP(B2,Mapping!B:G,6,0) -> Shweta | H2: 37 | I2: 37 | J2: 30 | K2: 29 | L2: 36 | M2: 31 | N2: 27 | O2: 26.391 | P2: 54 | Q2: 28.8 | R2: 15 | S2: 6.3
A3: FY2024-25 | B3: Schaeffler | C3: =VLOOKUP(B3,Mapping!B:C,2,0) -> Lateral | D3: =VLOOKUP(B3,Mapping!B:D,3,0) -> West | E3: =VLOOKUP(B3,Mapping!B:E,4,0) -> West 2 | F3: =VLOOKUP(B3,Mapping!B:F,5,0) -> Anjli | G3: =VLOOKUP(B3,Mapping!B:G,6,0) -> Shweta | H3: 8.5 | I3: 7.5 | J3: 7 | K3: 8 | L3: 10 | M3: 12 | N3: 3 | O3: 4 | P3: 0.5 | Q3: 4.76 | R3: 6 | S3: 9.839
A4: FY2024-25 | B4: Vertiv | C4: =VLOOKUP(B4,Mapping!B:C,2,0) -> Lateral | D4: =VLOOKUP(B4,Mapping!B:D,3,0) -> West | E4: =VLOOKUP(B4,Mapping!B:E,4,0) -> West 2 | F4: =VLOOKUP(B4,Mapping!B:F,5,0) -> Anjli | G4: =VLOOKUP(B4,Mapping!B:G,6,0) -> Shweta | H4: 4 | I4: 7 | J4: 4.55 | K4: 7.5 | L4: 3.8 | M4: 6 | N4: 2.2 | O4: 4.7 | P4: 7.6 | Q4: 3.4225 | R4: 4 | S4: 0.93
A5: FY2024-25 | B5: Tata Marcopolo | C5: =VLOOKUP(B5,Mapping!B:C,2,0) -> Lateral | D5: =VLOOKUP(B5,Mapping!B:D,3,0) -> West | E5: =VLOOKUP(B5,Mapping!B:E,4,0) -> West 2 | F5: =VLOOKUP(B5,Mapping!B:F,5,0) -> Anjli | G5: =VLOOKUP(B5,Mapping!B:G,6,0) -> Anjli | H5: 0.7 | I5: 1.9 | J5: 1.42 | K5: 0.41 | L5: 2 | M5: 2.09 | N5: 0.11 | O5: 0 | P5: 3 | Q5: 0 | R5: 0 | S5: 0.76
A6: FY2024-25 | B6: ThyssenKrupp | C6: =VLOOKUP(B6,Mapping!B:C,2,0) -> Lateral | D6: =VLOOKUP(B6,Mapping!B:D,3,0) -> West | E6: =VLOOKUP(B6,Mapping!B:E,4,0) -> West 2 | F6: =VLOOKUP(B6,Mapping!B:F,5,0) -> Anjli | G6: =VLOOKUP(B6,Mapping!B:G,6,0) -> Shweta | H6: 21 | I6: 21 | J6: 23.18104 | K6: 19 | L6: 22 | M6: 24 | N6: 12 | O6: 2.12 | P6: 10 | Q6: 0 | R6: 5 | S6: -9.93469
A7: FY2024-25 | B7: Ultratech | C7: =VLOOKUP(B7,Mapping!B:C,2,0) -> Lateral | D7: =VLOOKUP(B7,Mapping!B:D,3,0) -> West | E7: =VLOOKUP(B7,Mapping!B:E,4,0) -> West 1 | F7: =VLOOKUP(B7,Mapping!B:F,5,0) -> Anjli | G7: =VLOOKUP(B7,Mapping!B:G,6,0) -> Elton | H7: 1.56 | I7: -0.165 | J7: 1.5 | K7: 0.15 | L7: 0 | M7: 0 | N7: 0 | O7: 0 | P7: 0 | Q7: 0 | R7: 0 | S7: 0
A8: FY2024-25 | B8: Tata Teleservices | C8: =VLOOKUP(B8,Mapping!B:C,2,0) -> Lateral | D8: =VLOOKUP(B8,Mapping!B:D,3,0) -> West | E8: =VLOOKUP(B8,Mapping!B:E,4,0) -> West 1 | F8: =VLOOKUP(B8,Mapping!B:F,5,0) -> Anjli | G8: =VLOOKUP(B8,Mapping!B:G,6,0) -> Elton | H8: 0 | I8: 0 | J8: 0 | K8: 0 | L8: 0 | M8: 0 | N8: 0 | O8: 0 | P8: 0 | Q8: 0 | R8: 0 | S8: 0
A9: FY2024-25 | B9: Hyundai Motor | C9: =VLOOKUP(B9,Mapping!B:C,2,0) -> Lateral | D9: =VLOOKUP(B9,Mapping!B:D,3,0) -> West | E9: =VLOOKUP(B9,Mapping!B:E,4,0) -> West 2 | F9: =VLOOKUP(B9,Mapping!B:F,5,0) -> Anjli | G9: =VLOOKUP(B9,Mapping!B:G,6,0) -> Shweta | H9: 4.16 | I9: 20.5 | J9: 10.37 | K9: 12.5 | L9: 18 | M9: 26 | N9: 16 | O9: 28.134 | P9: 12.5 | Q9: 16.236 | R9: 15 | S9: 18
A10: FY2024-25 | B10: Bridgestone | C10: =VLOOKUP(B10,Mapping!B:C,2,0) -> Lateral | D10: =VLOOKUP(B10,Mapping!B:D,3,0) -> West | E10: =VLOOKUP(B10,Mapping!B:E,4,0) -> West 2 | F10: =VLOOKUP(B10,Mapping!B:F,5,0) -> Anjli | G10: =VLOOKUP(B10,Mapping!B:G,6,0) -> Shweta | H10: 0 | I10: 0 | J10: 0 | K10: 0 | L10: 0 | M10: 0 | N10: 0 | O10: 0.6 | P10: 0 | Q10: 1.1 | R10: 1 | S10: 5
A11: FY2024-25 | B11: SKF India | C11: =VLOOKUP(B11,Mapping!B:C,2,0) -> Lateral | D11: =VLOOKUP(B11,Mapping!B:D,3,0) -> North | E11: =VLOOKUP(B11,Mapping!B:E,4,0) -> North | F11: =VLOOKUP(B11,Mapping!B:F,5,0) -> Anjli | G11: =VLOOKUP(B11,Mapping!B:G,6,0) -> Archana | H11: 19.2 | I11: 20.5 | J11: 17.96229 | K11: 12 | L11: 15 | M11: 19 | N11: 15.333333 | O11: 20.5 | P11: 14 | Q11: 26 | R11: 15 | S11: 13.1
A12: FY2024-25 | B12: Jindal Stainless | C12: =VLOOKUP(B12,Mapping!B:C,2,0) -> Lateral | D12: =VLOOKUP(B12,Mapping!B:D,3,0) -> North | E12: =VLOOKUP(B12,Mapping!B:E,4,0) -> North | F12: =VLOOKUP(B12,Mapping!B:F,5,0) -> Anjli | G12: =VLOOKUP(B12,Mapping!B:G,6,0) -> Archana | H12: 12 | I12: 15 | J12: 21 | K12: 13 | L12: 15.5 | M12: 25 | N12: 15 | O12: 9.5 | P12: 16 | Q12: 13.17074 | R12: 8.24 | S12: 13.38
A13: FY2024-25 | B13: Maruti Suzuki(MSIL) | C13: =VLOOKUP(B13,Mapping!B:C,2,0) -> Lateral | D13: =VLOOKUP(B13,Mapping!B:D,3,0) -> North | E13: =VLOOKUP(B13,Mapping!B:E,4,0) -> North | F13: =VLOOKUP(B13,Mapping!B:F,5,0) -> Anjli | G13: =VLOOKUP(B13,Mapping!B:G,6,0) -> Archana | H13: 2 | I13: 0.73 | J13: 22.2625 | K13: 10 | L13: 10 | M13: 8 | N13: 25 | O13: 36.5 | P13: 36.5 | Q13: 26.8 | R13: 20 | S13: 87.07
... A57: FY2024-25 | B57: Common | C57: =VLOOKUP(B57,Mapping!B:C,2,0) -> Lateral | D57: =VLOOKUP(B57,Mapping!B:D,3,0) -> Common | E57: =VLOOKUP(B57,Mapping!B:E,4,0) -> North | F57: =VLOOKUP(B57,Mapping!B:F,5,0) -> Common | G57: =VLOOKUP(B57,Mapping!B:G,6,0) -> Common | H57: 0 | I57: 0 | J57: 0 | K57: 0 | L57: 0 | M57: 0 | N57: 0 | O57: 0 | P57: 0 | Q57: 0 | R57: 0 | S57: 0
H59: Actual rev, when the month is closed; actual closed rev per month in lacs

Sheet Mapping
A1: FY | B1: Project | C1: Vertical | D1: Region | E1: Sub Region | F1: Region Head | G1: Practice Head
A2: FY2024-25 | B2: Tata Motors | C2: Lateral | D2: West | E2: West 2 | F2: Anjli | G2: Shweta
A3: FY2024-25 | B3: Schaeffler | C3: Lateral | D3: West | E3: West 2 | F3: Anjli | G3: Shweta
A4: FY2024-25 | B4: Vertiv | C4: Lateral | D4: West | E4: West 2 | F4: Anjli | G4: Shweta
A5: FY2024-25 | B5: Tata Marcopolo | C5: Lateral | D5: West | E5: West 2 | F5: Anjli | G5: Anjli
A6: FY2024-25 | B6: ThyssenKrupp | C6: Lateral | D6: West | E6: West 2 | F6: Anjli | G6: Shweta
A7: FY2024-25 | B7: Ultratech | C7: Lateral | D7: West | E7: West 1 | F7: Anjli | G7: Elton
A8: FY2024-25 | B8: Tata Teleservices | C8: Lateral | D8: West | E8: West 1 | F8: Anjli | G8: Elton
A9: FY2024-25 | B9: Hyundai Motor | C9: Lateral | D9: West | E9: West 2 | F9: Anjli | G9: Shweta
A10: FY2024-25 | B10: Bridgestone | C10: Lateral | D10: West | E10: West 2 | F10: Anjli | G10: Shweta
A11: FY2024-25 | B11: SKF India | C11: Lateral | D11: North | E11: North | F11: Anjli | G11: Archana
A12: FY2024-25 | B12: Jindal Stainless | C12: Lateral | D12: North | E12: North | F12: Anjli | G12: Archana
... A70: FY2024-25 | B70: Bench | C70: Lateral | D70: North | E70: North | F70: Anjli | G70: Anjli

Sheet CM_Actual
A1: FY | B1: Project | C1: Vertical | D1: Region | E1: Sub Region | F1: Region Head | G1: Practice Head | H1: 45383 | I1: =EDATE(H1,1) -> 45413 | J1: =EDATE(I1,1) -> 45444 | K1: =EDATE(J1,1) -> 45474 | L1: =EDATE(K1,1) -> 45505 | M1: =EDATE(L1,1) -> 45536 | N1: =EDATE(M1,1) -> 45566 | O1: =EDATE(N1,1) -> 45597 | P1: =EDATE(O1,1) -> 45627 | ... S1: =EDATE(R1,1) -> 45717
A2: FY2024-25 | B2: Tata Motors | C2: =VLOOKUP(B2,Mapping!B:C,2,0) -> Lateral | D2: =VLOOKUP(B2,Mapping!B:D,3,0) -> West | E2: =VLOOKUP(B2,Mapping!B:E,4,0) -> West 2 | F2: =VLOOKUP(B2,Mapping!B:F,5,0) -> Anjli | G2: =VLOOKUP(B2,Mapping!B:G,6,0) -> Shweta | H2: -3.4984519 | I2: -6.5972696 | J2: -1.1916842 | K2: 5.0178822 | L2: 13.220138 | M2: 4.4822498 | N2: 4.8323542 | O2: 5.7312193 | P2: 33.229707 | Q2: 11.970097 | R2: 5.1508936 | S2: 4.6148518
A3: FY2024-25 | B3: Schaeffler | C3: =VLOOKUP(B3,Mapping!B:C,2,0) -> Lateral | D3: =VLOOKUP(B3,Mapping!B:D,3,0) -> West | E3: =VLOOKUP(B3,Mapping!B:E,4,0) -> West 2 | F3: =VLOOKUP(B3,Mapping!B:F,5,0) -> Anjli | G3: =VLOOKUP(B3,Mapping!B:G,6,0) -> Shweta | H3: 3.0061758 | I3: 2.7177188 | J3: 1.7372026 | K3: 3.1769207 | L3: 4.7466494 | M3: 7.4672317 | N3: 0.41144086 | O3: 1.1419194 | P3: -2.2911981 | Q3: 1.7933945 | R3: 2.2400803 | S3: 3.56148
A4: FY2024-25 | B4: Vertiv | C4: =VLOOKUP(B4,Mapping!B:C,2,0) -> Lateral | D4: =VLOOKUP(B4,Mapping!B:D,3,0) -> West | E4: =VLOOKUP(B4,Mapping!B:E,4,0) -> West 2 | F4: =VLOOKUP(B4,Mapping!B:F,5,0) -> Anjli | G4: =VLOOKUP(B4,Mapping!B:G,6,0) -> Shweta | H4: -0.56970164 | I4: 2.9827788 | J4: 0.65480495 | K4: 5.16508 | L4: 1.4827097 | M4: 3.2502316 | N4: 0.37179758 | O4: 3.1404575 | P4: 5.9769285 | Q4: 1.8480259 | R4: 0.75939029 | S4: -2.5081089
A5: FY2024-25 | B5: Tata Marcopolo | C5: =VLOOKUP(B5,Mapping!B:C,2,0) -> Lateral | D5: =VLOOKUP(B5,Mapping!B:D,3,0) -> West | E5: =VLOOKUP(B5,Mapping!B:E,4,0) -> West 2 | F5: =VLOOKUP(B5,Mapping!B:F,5,0) -> Anjli | G5: =VLOOKUP(B5,Mapping!B:G,6,0) -> Anjli | H5: 0.15938975 | I5: 1.3526798 | J5: 0.88973212 | K5: -0.15096749 | L5: 1.4423874 | M5: 1.391727 | N5: -0.3917531 | O5: -0.62316998 | P5: 2.9845 | Q5: 0 | R5: -0.60034794 | S5: 0.063611554
A6: FY2024-25 | B6: ThyssenKrupp | C6: =VLOOKUP(B6,Mapping!B:C,2,0) -> Lateral | D6: =VLOOKUP(B6,Mapping!B:D,3,0) -> West | E6: =VLOOKUP(B6,Mapping!B:E,4,0) -> West 2 | F6: =VLOOKUP(B6,Mapping!B:F,5,0) -> Anjli | G6: =VLOOKUP(B6,Mapping!B:G,6,0) -> Shweta | H6: 8.546737 | I6: 8.540657 | J6: 10.467796 | K6: 6.2661246 | L6: 9.779377 | M6: 8.9807436 | N6: 2.1368529 | O6: -1.1204576 | P6: 6.5426247 | Q6: -1.113497 | R6: 3.9500194 | S6: -10.18564
A7: FY2024-25 | B7: Ultratech | C7: =VLOOKUP(B7,Mapping!B:C,2,0) -> Lateral | D7: =VLOOKUP(B7,Mapping!B:D,3,0) -> West | E7: =VLOOKUP(B7,Mapping!B:E,4,0) -> West 1 | F7: =VLOOKUP(B7,Mapping!B:F,5,0) -> Anjli | G7: =VLOOKUP(B7,Mapping!B:G,6,0) -> Elton | H7: 0.54808962 | I7: -1.1869603 | J7: 0.51190317 | K7: -0.85937623 | L7: -0.47666693 | M7: -0.3304896 | N7: 0 | O7: 0 | P7: 0 | Q7: 0 | R7: 0 | S7: 0
A8: FY2024-25 | B8: Tata Teleservices | C8: =VLOOKUP(B8,Mapping!B:C,2,0) -> Lateral | D8: =VLOOKUP(B8,Mapping!B:D,3,0) -> West | E8: =VLOOKUP(B8,Mapping!B:E,4,0) -> West 1 | F8: =VLOOKUP(B8,Mapping!B:F,5,0) -> Anjli | G8: =VLOOKUP(B8,Mapping!B:G,6,0) -> Elton | H8: -1.8422604 | I8: -2.5059706 | J8: -1.8014569 | K8: -2.2088625 | L8: -1.6417652 | M8: -1.6650784 | N8: -1.4955862 | O8: -1.4709 | P8: -1.5810076 | Q8: -1.5704428 | R8: -0.55099794 | S8: 0
A9: FY2024-25 | B9: Hyundai Motor | C9: =VLOOKUP(B9,Mapping!B:C,2,0) -> Lateral | D9: =VLOOKUP(B9,Mapping!B:D,3,0) -> West | E9: =VLOOKUP(B9,Mapping!B:E,4,0) -> West 2 | F9: =VLOOKUP(B9,Mapping!B:F,5,0) -> Anjli | G9: =VLOOKUP(B9,Mapping!B:G,6,0) -> Shweta | H9: -0.55189151 | I9: 15.390729 | J9: 5.220185 | K9: 6.6558432 | L9: 11.663532 | M9: 14.550595 | N9: 9.2125417 | O9: 17.331414 | P9: 3.0805555 | Q9: 6.2148158 | R9: 5.2146752 | S9: 4.0521489
A10: FY2024-25 | B10: Bridgestone | C10: =VLOOKUP(B10,Mapping!B:C,2,0) -> Lateral | D10: =VLOOKUP(B10,Mapping!B:D,3,0) -> West | E10: =VLOOKUP(B10,Mapping!B:E,4,0) -> West 2 | F10: =VLOOKUP(B10,Mapping!B:F,5,0) -> Anjli | G10: =VLOOKUP(B10,Mapping!B:G,6,0) -> Shweta | H10: 0 | I10: 0 | J10: 0 | K10: 0 | L10: 0 | M10: 0 | N10: 0 | O10: 0.042748413 | P10: 0 | Q10: 0.50353862 | R10: -0.50642589 | S10: 1.4748987
A11: FY2024-25 | B11: SKF India | C11: =VLOOKUP(B11,Mapping!B:C,2,0) -> Lateral | D11: =VLOOKUP(B11,Mapping!B:D,3,0) -> North | E11: =VLOOKUP(B11,Mapping!B:E,4,0) -> North | F11: =VLOOKUP(B11,Mapping!B:F,5,0) -> Anjli | G11: =VLOOKUP(B11,Mapping!B:G,6,0) -> Archana | H11: 4.6980365 | I11: 6.8777673 | J11: 3.8764851 | K11: -3.5287873 | L11: 0.042528792 | M11: 2.8735876 | N11: 1.9245568 | O11: 7.0447554 | P11: 0.25151648 | Q11: 12.345171 | R11: 1.3633688 | S11: -1.8978582
A12: FY2024-25 | B12: Jindal Stainless | C12: =VLOOKUP(B12,Mapping!B:C,2,0) -> Lateral | D12: =VLOOKUP(B12,Mapping!B:D,3,0) -> North | E12: =VLOOKUP(B12,Mapping!B:E,4,0) -> North | F12: =VLOOKUP(B12,Mapping!B:F,5,0) -> Anjli | G12: =VLOOKUP(B12,Mapping!B:G,6,0) -> Archana | H12: -0.073688688 | I12: 3.7797275 | J12: 8.4423232 | K12: 1.3150083 | L12: 4.4873035 | M12: 11.871054 | N12: 4.4473037 | O12: 0.46354478 | P12: 7.2081351 | Q12: 5.0415955 | R12: 0.82177898 | S12: 10.568915
A13: FY2024-25 | B13: Maruti Suzuki(MSIL) | C13: =VLOOKUP(B13,Mapping!B:C,2,0) -> Lateral | D13: =VLOOKUP(B13,Mapping!B:D,3,0) -> North | E13: =VLOOKUP(B13,Mapping!B:E,4,0) -> North | F13: =VLOOKUP(B13,Mapping!B:F,5,0) -> Anjli | G13: =VLOOKUP(B13,Mapping!B:G,6,0) -> Archana | H13: 1.7438099 | I13: -0.87595038 | J13: 18.087254 | K13: -2.4251811 | L13: -7.1897254 | M13: -15.548451 | N13: 2.7316406 | O13: 3.0527432 | P13: 2.8710284 | Q13: -8.4179521 | R13: -16.363207 | S13: 36.152401
... A58: FY2024-25 | B58: Bench | C58: =VLOOKUP(B58,Mapping!B:C,2,0) -> Lateral | D58: =VLOOKUP(B58,Mapping!B:D,3,0) -> North | E58: =VLOOKUP(B58,Mapping!B:E,4,0) -> North | F58: =VLOOKUP(B58,Mapping!B:F,5,0) -> Anjli | G58: =VLOOKUP(B58,Mapping!B:G,6,0) -> Anjli | H58: 0 | I58: 0 | J58: -0.0505 | K58: -0.0465 | L58: -0.049 | M58: -0.8 | N58: -0.0155 | O58: -0.0155 | P58: -0.031 | Q58: 0 | R58: 0 | S58: 0
H62: CM actual in Lacs

Sheet Taggd_Source_Joiner
A1: FY | B1: Project | C1: Vertical | D1: Region | E1: Sub Region | F1: Region Head | G1: Practice Head | H1: 45383 | I1: =EDATE(H1,1) -> 45413 | J1: =EDATE(I1,1) -> 45444 | K1: =EDATE(J1,1) -> 45474 | L1: =EDATE(K1,1) -> 45505 | M1: =EDATE(L1,1) -> 45536 | N1: =EDATE(M1,1) -> 45566 | O1: =EDATE(N1,1) -> 45597 | P1: =EDATE(O1,1) -> 45627 | ... S1: =EDATE(R1,1) -> 45717
A2: FY2024-25 | B2: Tata Motors | C2: =VLOOKUP(B2,Mapping!B:C,2,0) -> Lateral | D2: =VLOOKUP(B2,Mapping!B:D,3,0) -> West | E2: =VLOOKUP(B2,Mapping!B:E,4,0) -> West 2 | F2: =VLOOKUP(B2,Mapping!B:F,5,0) -> Anjli | G2: =VLOOKUP(B2,Mapping!B:G,6,0) -> Shweta | H2: 19 | I2: 0 | J2: 7 | K2: 24 | L2: 31 | M2: 28 | N2: 0 | O2: 28 | P2: 32 | Q2: 0 | R2: 25 | S2: 28
A3: FY2024-25 | B3: Schaeffler | C3: =VLOOKUP(B3,Mapping!B:C,2,0) -> Lateral | D3: =VLOOKUP(B3,Mapping!B:D,3,0) -> West | E3: =VLOOKUP(B3,Mapping!B:E,4,0) -> West 2 | F3: =VLOOKUP(B3,Mapping!B:F,5,0) -> Anjli | G3: =VLOOKUP(B3,Mapping!B:G,6,0) -> Shweta | H3: 11 | I3: 0 | J3: 9 | K3: 10 | L3: 3 | M3: 7 | N3: 9 | O3: 9 | P3: 3 | Q3: 1 | R3: 12 | S3: 9
A4: FY2024-25 | B4: Vertiv | C4: =VLOOKUP(B4,Mapping!B:C,2,0) -> Lateral | D4: =VLOOKUP(B4,Mapping!B:D,3,0) -> West | E4: =VLOOKUP(B4,Mapping!B:E,4,0) -> West 2 | F4: =VLOOKUP(B4,Mapping!B:F,5,0) -> Anjli | G4: =VLOOKUP(B4,Mapping!B:G,6,0) -> Shweta | H4: 7 | I4: 0 | J4: 8 | K4: 3 | L4: 2 | M4: 4 | N4: 3 | O4: 2 | P4: 7 | Q4: 2 | R4: 2 | S4: 1
A5: FY2024-25 | B5: Tata Marcopolo | C5: =VLOOKUP(B5,Mapping!B:C,2,0) -> Lateral | D5: =VLOOKUP(B5,Mapping!B:D,3,0) -> West | E5: =VLOOKUP(B5,Mapping!B:E,4,0) -> West 2 | F5: =VLOOKUP(B5,Mapping!B:F,5,0) -> Anjli | G5: =VLOOKUP(B5,Mapping!B:G,6,0) -> Anjli | H5: 0 | I5: 0 | J5: 2 | K5: 1 | L5: 2 | M5: 0 | N5: 0 | O5: 0 | P5: 1 | Q5: 0 | R5: 0 | S5: 0
A6: FY2024-25 | B6: ThyssenKrupp | C6: =VLOOKUP(B6,Mapping!B:C,2,0) -> Lateral | D6: =VLOOKUP(B6,Mapping!B:D,3,0) -> West | E6: =VLOOKUP(B6,Mapping!B:E,4,0) -> West 2 | F6: =VLOOKUP(B6,Mapping!B:F,5,0) -> Anjli | G6: =VLOOKUP(B6,Mapping!B:G,6,0) -> Shweta | H6: 0 | I6: 0 | J6: 18 | K6: 30 | L6: 32 | M6: 26 | N6: 14 | O6: 17 | P6: 12 | Q6: 8 | R6: 0 | S6: 0
A7: FY2024-25 | B7: Ultratech | C7: =VLOOKUP(B7,Mapping!B:C,2,0) -> Lateral | D7: =VLOOKUP(B7,Mapping!B:D,3,0) -> West | E7: =VLOOKUP(B7,Mapping!B:E,4,0) -> West 1 | F7: =VLOOKUP(B7,Mapping!B:F,5,0) -> Anjli | G7: =VLOOKUP(B7,Mapping!B:G,6,0) -> Elton | H7: 0 | I7: 0 | J7: 2 | K7: 0 | L7: 0 | M7: 0 | N7: 0 | O7: 0 | P7: 0 | Q7: 0 | R7: 0 | S7: 0
A8: FY2024-25 | B8: Tata Teleservices | C8: =VLOOKUP(B8,Mapping!B:C,2,0) -> Lateral | D8: =VLOOKUP(B8,Mapping!B:D,3,0) -> West | E8: =VLOOKUP(B8,Mapping!B:E,4,0) -> West 1 | F8: =VLOOKUP(B8,Mapping!B:F,5,0) -> Anjli | G8: =VLOOKUP(B8,Mapping!B:G,6,0) -> Elton | H8: 0 | I8: 0 | J8: 0 | K8: 0 | L8: 0 | M8: 0 | N8: 7 | O8: 0 | P8: 0 | Q8: 0 | R8: 0 | S8: 0
A9: FY2024-25 | B9: Hyundai Motor | C9: =VLOOKUP(B9,Mapping!B:C,2,0) -> Lateral | D9: =VLOOKUP(B9,Mapping!B:D,3,0) -> West | E9: =VLOOKUP(B9,Mapping!B:E,4,0) -> West 2 | F9: =VLOOKUP(B9,Mapping!B:F,5,0) -> Anjli | G9: =VLOOKUP(B9,Mapping!B:G,6,0) -> Shweta | H9: 46 | I9: 0 | J9: 2 | K9: 6 | L9: 18 | M9: 26 | N9: 14 | O9: 26 | P9: 30 | Q9: 26 | R9: 29 | S9: 25
A10: FY2024-25 | B10: Bridgestone | C10: =VLOOKUP(B10,Mapping!B:C,2,0) -> Lateral | D10: =VLOOKUP(B10,Mapping!B:D,3,0) -> West | E10: =VLOOKUP(B10,Mapping!B:E,4,0) -> West 2 | F10: =VLOOKUP(B10,Mapping!B:F,5,0) -> Anjli | G10: =VLOOKUP(B10,Mapping!B:G,6,0) -> Shweta | H10: 0 | I10: 0 | J10: 0 | K10: 0 | L10: 0 | M10: 0 | N10: 0 | O10: 0 | P10: 0 | Q10: 0 | R10: 0 | S10: 0
A11: FY2024-25 | B11: SKF India | C11: =VLOOKUP(B11,Mapping!B:C,2,0) -> Lateral | D11: =VLOOKUP(B11,Mapping!B:D,3,0) -> North | E11: =VLOOKUP(B11,Mapping!B:E,4,0) -> North | F11: =VLOOKUP(B11,Mapping!B:F,5,0) -> Anjli | G11: =VLOOKUP(B11,Mapping!B:G,6,0) -> Archana | H11: 12 | I11: 0 | J11: 16 | K11: 13 | L11: 15 | M11: 18 | N11: 7 | O11: 7 | P11: 12 | Q11: 2 | R11: 11 | S11: 13
A12: FY2024-25 | B12: Jindal Stainless | C12: =VLOOKUP(B12,Mapping!B:C,2,0) -> Lateral | D12: =VLOOKUP(B12,Mapping!B:D,3,0) -> North | E12: =VLOOKUP(B12,Mapping!B:E,4,0) -> North | F12: =VLOOKUP(B12,Mapping!B:F,5,0) -> Anjli | G12: =VLOOKUP(B12,Mapping!B:G,6,0) -> Archana | H12: 11 | I12: 0 | J12: 14 | K12: 17 | L12: 14 | M12: 23 | N12: 10 | O12: 17 | P12: 21 | Q12: 7 | R12: 6 | S12: 7
A13: FY2024-25 | B13: Maruti Suzuki(MSIL) | C13: =VLOOKUP(B13,Mapping!B:C,2,0) -> Lateral | D13: =VLOOKUP(B13,Mapping!B:D,3,0) -> North | E13: =VLOOKUP(B13,Mapping!B:E,4,0) -> North | F13: =VLOOKUP(B13,Mapping!B:F,5,0) -> Anjli | G13: =VLOOKUP(B13,Mapping!B:G,6,0) -> Archana | H13: 63 | I13: 0 | J13: 0 | K13: 0 | L13: 2 | M13: 17 | N13: 14 | O13: 23 | P13: 28 | Q13: 69 | R13: 89 | S13: 183
A14: FY2024-25 | B14: Suzuki R&D | C14: =VLOOKUP(B14,Mapping!B:C,2,0) -> Lateral | D14: =VLOOKUP(B14,Mapping!B:D,3,0) -> North | E14: =VLOOKUP(B14,Mapping!B:E,4,0) -> North | F14: =VLOOKUP(B14,Mapping!B:F,5,0) -> Anjli | G14: =VLOOKUP(B14,Mapping!B:G,6,0) -> Archana | H14: 1 | P14: 0 | Q14: 0 | R14: 0 | S14: 0
A15: FY2024-25 | B15: Subros Ltd | C15: =VLOOKUP(B15,Mapping!B:C,2,0) -> Lateral | D15: =VLOOKUP(B15,Mapping!B:D,3,0) -> North | E15: =VLOOKUP(B15,Mapping!B:E,4,0) -> North | F15: =VLOOKUP(B15,Mapping!B:F,5,0) -> Anjli | G15: =VLOOKUP(B15,Mapping!B:G,6,0) -> Archana | H15: 1 | I15: 0 | J15: 0 | K15: 0 | L15: 0 | M15: 0 | N15: 0 | O15: 0 | P15: 1 | Q15: 0 | R15: 0 | S15: 0
A16: FY2024-25 | B16: Pernod Ricard | C16: =VLOOKUP(B16,Mapping!B:C,2,0) -> Lateral | D16: =VLOOKUP(B16,Mapping!B:D,3,0) -> North | E16: =VLOOKUP(B16,Mapping!B:E,4,0) -> North | F16: =VLOOKUP(B16,Mapping!B:F,5,0) -> Anjli | G16: =VLOOKUP(B16,Mapping!B:G,6,0) -> Archana | H16: 0 | I16: 0 | J16: 0 | K16: 0 | L16: 0 | M16: 0 | N16: 0 | O16: 0 | P16: 0 | Q16: 0 | R16: 0 | S16: 0
A17: FY2024-25 | B17: Pfizer | C17: =VLOOKUP(B17,Mapping!B:C,2,0) -> Lateral | D17: =VLOOKUP(B17,Mapping!B:D,3,0) -> West | E17: =VLOOKUP(B17,Mapping!B:E,4,0) -> West 1 | F17: =VLOOKUP(B17,Mapping!B:F,5,0) -> Anjli | G17: =VLOOKUP(B17,Mapping!B:G,6,0) -> Usha | H17: 16 | I17: 0 | J17: 10 | K17: 10 | L17: 6 | M17: 6 | N17: 14 | O17: 16 | P17: 10 | Q17: 14 | R17: 15 | S17: 16
A18: FY2024-25 | B18: Tata Power | C18: =VLOOKUP(B18,Mapping!B:C,2,0) -> Lateral | D18: =VLOOKUP(B18,Mapping!B:D,3,0) -> West | E18: =VLOOKUP(B18,Mapping!B:E,4,0) -> West 1 | F18: =VLOOKUP(B18,Mapping!B:F,5,0) -> Anjli | G18: =VLOOKUP(B18,Mapping!B:G,6,0) -> Elton | H18: 0 | I18: 0 | J18: 1 | K18: 0 | L18: 0 | M18: 0 | N18: 0 | O18: 0 | P18: 0 | Q18: 0 | R18: 0 | S18: 0
A19: FY2024-25 | B19: Pidilite | C19: =VLOOKUP(B19,Mapping!B:C,2,0) -> Lateral | D19: =VLOOKUP(B19,Mapping!B:D,3,0) -> West | E19: =VLOOKUP(B19,Mapping!B:E,4,0) -> West 1 | F19: =VLOOKUP(B19,Mapping!B:F,5,0) -> Anjli | G19: =VLOOKUP(B19,Mapping!B:G,6,0) -> Usha | H19: 19 | I19: 0 | J19: 14 | K19: 15 | L19: 15 | M19: 50 | N19: 18 | O19: 21 | P19: 20 | Q19: 28 | R19: 19 | S19: 23
A20: FY2024-25 | B20: Birla Paints | C20: =VLOOKUP(B20,Mapping!B:C,2,0) -> Lateral | D20: =VLOOKUP(B20,Mapping!B:D,3,0) -> West | E20: =VLOOKUP(B20,Mapping!B:E,4,0) -> West 1 | F20: =VLOOKUP(B20,Mapping!B:F,5,0) -> Anjli | G20: =VLOOKUP(B20,Mapping!B:G,6,0) -> Geetu | H20: 5 | I20: 0 | J20: 21 | K20: 11 | L20: 34 | M20: 20 | N20: 23 | O20: 6 | P20: 1 | Q20: 4 | R20: 16 | S20: 8
A21: FY2024-25 | B21: M&M | C21: =VLOOKUP(B21,Mapping!B:C,2,0) -> Lateral & Leadership | D21: =VLOOKUP(B21,Mapping!B:D,3,0) -> West | E21: =VLOOKUP(B21,Mapping!B:E,4,0) -> West 1 | F21: =VLOOKUP(B21,Mapping!B:F,5,0) -> Anjli | G21: =VLOOKUP(B21,Mapping!B:G,6,0) -> Dhriti | H21: 94 | I21: 0 | J21: 114 | K21: 114 | L21: 84 | M21: 92 | N21: 75 | O21: 89 | P21: 94 | Q21: 105 | R21: 89 | S21: 87
A22: FY2024-25 | B22: DP World | C22: =VLOOKUP(B22,Mapping!B:C,2,0) -> Lateral | D22: =VLOOKUP(B22,Mapping!B:D,3,0) -> West | E22: =VLOOKUP(B22,Mapping!B:E,4,0) -> West 1 | F22: =VLOOKUP(B22,Mapping!B:F,5,0) -> Anjli | G22: =VLOOKUP(B22,Mapping!B:G,6,0) -> Geetu | H22: 16 | I22: 0 | J22: 19 | K22: 18 | L22: 9 | M22: 17 | N22: 6 | O22: 11 | P22: 9 | Q22: 10 | R22: 6 | S22: 14
A23: FY2024-25 | B23: AMNS | C23: =VLOOKUP(B23,Mapping!B:C,2,0) -> Lateral | D23: =VLOOKUP(B23,Mapping!B:D,3,0) -> West | E23: =VLOOKUP(B23,Mapping!B:E,4,0) -> West 1 | F23: =VLOOKUP(B23,Mapping!B:F,5,0) -> Anjli | G23: =VLOOKUP(B23,Mapping!B:G,6,0) -> Alifia | H23: 35 | I23: 0 | J23: 86 | K23: 75 | L23: 41 | M23: 79 | N23: 23 | O23: 32 | P23: 37 | Q23: 47 | R23: 65 | S23: 60
A24: FY2024-25 | B24: Mahindra Holidays | C24: =VLOOKUP(B24,Mapping!B:C,2,0) -> Lateral | D24: =VLOOKUP(B24,Mapping!B:D,3,0) -> West | E24: =VLOOKUP(B24,Mapping!B:E,4,0) -> West 1 | F24: =VLOOKUP(B24,Mapping!B:F,5,0) -> Anjli | G24: =VLOOKUP(B24,Mapping!B:G,6,0) -> Geetu | H24: 22 | I24: 0 | J24: 26 | K24: 10 | L24: 21 | M24: 17 | N24: 1 | O24: 2 | P24: 0 | Q24: 8 | R24: 13 | S24: 13
A25: FY2024-25 | B25: WTW | C25: =VLOOKUP(B25,Mapping!B:C,2,0) -> Lateral | D25: =VLOOKUP(B25,Mapping!B:D,3,0) -> West | E25: =VLOOKUP(B25,Mapping!B:E,4,0) -> West 1 | F25: =VLOOKUP(B25,Mapping!B:F,5,0) -> Anjli | G25: =VLOOKUP(B25,Mapping!B:G,6,0) -> Geetu | H25: 0 | I25: 0 | J25: 0 | K25: 0 | L25: 0 | M25: 0 | N25: 0 | O25: 0 | P25: 0 | Q25: 0 | R25: 0 | S25: 0
A26: FY2024-25 | B26: Fedex | C26: =VLOOKUP(B26,Mapping!B:C,2,0) -> Lateral | D26: =VLOOKUP(B26,Mapping!B:D,3,0) -> West | E26: =VLOOKUP(B26,Mapping!B:E,4,0) -> West 1 | F26: =VLOOKUP(B26,Mapping!B:F,5,0) -> Anjli | G26: =VLOOKUP(B26,Mapping!B:G,6,0) -> Elton | H26: 0 | I26: 0 | J26: 1 | K26: 1 | L26: 0 | M26: 0 | N26: 0 | O26: 0 | P26: 0 | Q26: 0 | R26: 1 | S26: 0
... A40: FY2024-25 | B40: P&G | C40: =VLOOKUP(B40,Mapping!B:C,2,0) -> Lateral | D40: =VLOOKUP(B40,Mapping!B:D,3,0) -> South | E40: =VLOOKUP(B40,Mapping!B:E,4,0) -> South 2 | F40: =VLOOKUP(B40,Mapping!B:F,5,0) -> Sulabh | G40: =VLOOKUP(B40,Mapping!B:G,6,0) -> Krishna | H40: 0 | I40: 0 | J40: 0 | K40: 0 | L40: 0 | M40: 0 | N40: 0 | O40: 0 | P40: 0 | Q40: 0 | R40: 0 | S40: 0
A41: FY2024-25 | B41: L&T Energy | C41: =VLOOKUP(B41,Mapping!B:C,2,0) -> Lateral | D41: =VLOOKUP(B41,Mapping!B:D,3,0) -> South | E41: =VLOOKUP(B41,Mapping!B:E,4,0) -> South 2 | F41: =VLOOKUP(B41,Mapping!B:F,5,0) -> Sulabh | G41: =VLOOKUP(B41,Mapping!B:G,6,0) -> Krishna | H41: 0 | P41: 0 | Q41: 0 | R41: 0 | S41: 0
A42: FY2024-25 | B42: Tata Electronics | C42: =VLOOKUP(B42,Mapping!B:C,2,0) -> Lateral | D42: =VLOOKUP(B42,Mapping!B:D,3,0) -> South | E42: =VLOOKUP(B42,Mapping!B:E,4,0) -> South 2 | F42: =VLOOKUP(B42,Mapping!B:F,5,0) -> Sulabh | G42: =VLOOKUP(B42,Mapping!B:G,6,0) -> Subu | H42: 7 | I42: 0 | J42: 24 | K42: 26 | L42: 48 | M42: 23 | N42: 4 | O42: 11 | P42: 9 | Q42: 7 | R42: 11 | S42: 16
A43: FY2024-25 | B43: Royal Enfield | C43: =VLOOKUP(B43,Mapping!B:C,2,0) -> Lateral | D43: =VLOOKUP(B43,Mapping!B:D,3,0) -> South | E43: =VLOOKUP(B43,Mapping!B:E,4,0) -> South 2 | F43: =VLOOKUP(B43,Mapping!B:F,5,0) -> Sulabh | G43: =VLOOKUP(B43,Mapping!B:G,6,0) -> Krishna | H43: 1 | I43: 0 | J43: 2 | K43: 6 | L43: 4 | M43: 1 | N43: 0 | O43: 2 | P43: 0 | Q43: 3 | R43: 1 | S43: 2
A44: FY2024-25 | B44: Excelacom | C44: =VLOOKUP(B44,Mapping!B:C,2,0) -> Lateral | D44: =VLOOKUP(B44,Mapping!B:D,3,0) -> South | E44: =VLOOKUP(B44,Mapping!B:E,4,0) -> South 2 | F44: =VLOOKUP(B44,Mapping!B:F,5,0) -> Sulabh | G44: =VLOOKUP(B44,Mapping!B:G,6,0) -> Krishna | H44: 1 | I44: 0 | J44: 9 | K44: 1 | L44: 3 | M44: 3 | N44: 23 | O44: 3 | P44: 23 | Q44: 0 | R44: 1 | S44: 2
A45: FY2024-25 | B45: Viteos | C45: =VLOOKUP(B45,Mapping!B:C,2,0) -> Lateral | D45: =VLOOKUP(B45,Mapping!B:D,3,0) -> South | E45: =VLOOKUP(B45,Mapping!B:E,4,0) -> South 2 | F45: =VLOOKUP(B45,Mapping!B:F,5,0) -> Sulabh | G45: =VLOOKUP(B45,Mapping!B:G,6,0) -> Krishna | H45: 0 | I45: 0 | J45: 0 | K45: 0 | L45: 0 | M45: 0 | N45: 0 | O45: 0 | P45: 0 | Q45: 0 | R45: 0 | S45: 0
A46: FY2024-25 | B46: Ashok Leyland | C46: =VLOOKUP(B46,Mapping!B:C,2,0) -> Lateral | D46: =VLOOKUP(B46,Mapping!B:D,3,0) -> South | E46: =VLOOKUP(B46,Mapping!B:E,4,0) -> South 2 | F46: =VLOOKUP(B46,Mapping!B:F,5,0) -> Sulabh | G46: =VLOOKUP(B46,Mapping!B:G,6,0) -> Krishna | H46: 0 | I46: 0 | J46: 0 | K46: 0 | L46: 0 | M46: 0 | N46: 0 | O46: 0 | P46: 0 | Q46: 0 | R46: 1 | S46: 2
A47: FY2024-25 | B47: M2P Fintech | C47: =VLOOKUP(B47,Mapping!B:C,2,0) -> Lateral | D47: =VLOOKUP(B47,Mapping!B:D,3,0) -> South | E47: =VLOOKUP(B47,Mapping!B:E,4,0) -> South 2 | F47: =VLOOKUP(B47,Mapping!B:F,5,0) -> Sulabh | G47: =VLOOKUP(B47,Mapping!B:G,6,0) -> Krishna | H47: 0 | I47: 0 | J47: 0 | K47: 0 | L47: 0 | M47: 0 | N47: 0 | O47: 0 | P47: 0 | Q47: 0 | R47: 0 | S47: 0
A48: FY2024-25 | B48: ABB | C48: =VLOOKUP(B48,Mapping!B:C,2,0) -> Lateral | D48: =VLOOKUP(B48,Mapping!B:D,3,0) -> South | E48: =VLOOKUP(B48,Mapping!B:E,4,0) -> South 2 | F48: =VLOOKUP(B48,Mapping!B:F,5,0) -> Sulabh | G48: =VLOOKUP(B48,Mapping!B:G,6,0) -> Satya | H48: 0 | I48: 0 | J48: 0 | K48: 0 | L48: 0 | M48: 0 | N48: 0 | O48: 0 | P48: 0 | Q48: 0 | R48: 0 | S48: 0
A49: FY2024-25 | B49: Honeywell | C49: =VLOOKUP(B49,Mapping!B:C,2,0) -> Lateral & Leadership | D49: =VLOOKUP(B49,Mapping!B:D,3,0) -> Bapi | E49: =VLOOKUP(B49,Mapping!B:E,4,0) -> South 1 | F49: =VLOOKUP(B49,Mapping!B:F,5,0) -> Bapi | G49: =VLOOKUP(B49,Mapping!B:G,6,0) -> Bapi | H49: 126 | I49: 0 | J49: 164 | K49: 206 | L49: 288 | M49: 161 | N49: 103 | O49: 50 | P49: 114 | Q49: 68 | R49: 123 | S49: 195
A50: FY2024-25 | B50: Siemens | C50: =VLOOKUP(B50,Mapping!B:C,2,0) -> Lateral | D50: =VLOOKUP(B50,Mapping!B:D,3,0) -> South | E50: =VLOOKUP(B50,Mapping!B:E,4,0) -> South 1 | F50: =VLOOKUP(B50,Mapping!B:F,5,0) -> Sulabh | G50: =VLOOKUP(B50,Mapping!B:G,6,0) -> Kunal | H50: 22 | I50: 0 | J50: 20 | K50: 15 | L50: 37 | M50: 29 | N50: 0 | O50: 26 | P50: 18 | Q50: 18 | R50: 34 | S50: 31
A51: FY2024-25 | B51: Robert Bosch | C51: =VLOOKUP(B51,Mapping!B:C,2,0) -> Lateral | D51: =VLOOKUP(B51,Mapping!B:D,3,0) -> South | E51: =VLOOKUP(B51,Mapping!B:E,4,0) -> South 2 | F51: =VLOOKUP(B51,Mapping!B:F,5,0) -> Sulabh | G51: =VLOOKUP(B51,Mapping!B:G,6,0) -> Abhilash | H51: 0 | I51: 0 | J51: 3 | K51: 3 | L51: 0 | M51: 0 | N51: 0 | O51: 0 | P51: 0 | Q51: 0 | R51: 0 | S51: 0
A52: FY2024-25 | B52: HPE | C52: =VLOOKUP(B52,Mapping!B:C,2,0) -> Lateral | D52: =VLOOKUP(B52,Mapping!B:D,3,0) -> Mahak | E52: =VLOOKUP(B52,Mapping!B:E,4,0) -> South 1 | F52: =VLOOKUP(B52,Mapping!B:F,5,0) -> Mahak | G52: =VLOOKUP(B52,Mapping!B:G,6,0) -> Mahak | H52: 40 | I52: 0 | J52: 0 | K52: 16 | L52: 13 | M52: 54 | N52: 23 | O52: 32 | P52: 35 | Q52: 39 | R52: 28 | S52: 34
A53: FY2024-25 | B53: Isuzu | C53: =VLOOKUP(B53,Mapping!B:C,2,0) -> Lateral | D53: =VLOOKUP(B53,Mapping!B:D,3,0) -> South | E53: =VLOOKUP(B53,Mapping!B:E,4,0) -> South 1 | F53: =VLOOKUP(B53,Mapping!B:F,5,0) -> Sulabh | G53: =VLOOKUP(B53,Mapping!B:G,6,0) -> Satya | H53: 2 | I53: 0 | J53: 3 | K53: 7 | L53: 0 | M53: 2 | N53: 3 | O53: 2 | P53: 0 | Q53: 4 | R53: 0 | S53: 1
... A57: FY2024-25 | B57: Common | C57: =VLOOKUP(B57,Mapping!B:C,2,0) -> Lateral | D57: =VLOOKUP(B57,Mapping!B:D,3,0) -> Common | E57: =VLOOKUP(B57,Mapping!B:E,4,0) -> North | F57: =VLOOKUP(B57,Mapping!B:F,5,0) -> Common | G57: =VLOOKUP(B57,Mapping!B:G,6,0) -> Common | H57: 0 | I57: 0 | J57: 0 | K57: 0 | L57: 0 | M57: 0 | N57: 0 | O57: 0 | P57: 0 | Q57: 0 | R57: 0 | S57: 0
G61: taggd source joiner (denomination)- total taggd joiner / work level 1 headcount
G62: work level 1- grade of the employee

Sheet Non Taggd Source Joiner
A1: FY | B1: Project | C1: Vertical | D1: Region | E1: Sub Region | F1: Region Head | G1: Practice Head | H1: 45383 | I1: =EDATE(H1,1) -> 45413 | J1: =EDATE(I1,1) -> 45444 | K1: =EDATE(J1,1) -> 45474 | L1: =EDATE(K1,1) -> 45505 | M1: =EDATE(L1,1) -> 45536 | N1: =EDATE(M1,1) -> 45566 | O1: =EDATE(N1,1) -> 45597 | P1: =EDATE(O1,1) -> 45627 | ... S1: =EDATE(R1,1) -> 45717
A2: FY2024-25 | B2: Tata Motors | C2: =VLOOKUP(B2,Mapping!B:C,2,0) -> Lateral | D2: =VLOOKUP(B2,Mapping!B:D,3,0) -> West | E2: =VLOOKUP(B2,Mapping!B:E,4,0) -> West 2 | F2: =VLOOKUP(B2,Mapping!B:F,5,0) -> Anjli | G2: =VLOOKUP(B2,Mapping!B:G,6,0) -> Shweta | H2: 7 | I2: 0 | J2: 9 | K2: 351 | L2: 38 | M2: 31 | N2: 0 | O2: 23 | P2: 17 | Q2: 0 | R2: 24 | S2: 25
A3: FY2024-25 | B3: Schaeffler | C3: =VLOOKUP(B3,Mapping!B:C,2,0) -> Lateral | D3: =VLOOKUP(B3,Mapping!B:D,3,0) -> West | E3: =VLOOKUP(B3,Mapping!B:E,4,0) -> West 2 | F3: =VLOOKUP(B3,Mapping!B:F,5,0) -> Anjli | G3: =VLOOKUP(B3,Mapping!B:G,6,0) -> Shweta | H3: 9 | I3: 0 | J3: 9 | K3: 10 | L3: 0 | M3: 6 | N3: 3 | O3: 3 | P3: 9 | Q3: 2 | R3: 1 | S3: 5
A4: FY2024-25 | B4: Vertiv | C4: =VLOOKUP(B4,Mapping!B:C,2,0) -> Lateral | D4: =VLOOKUP(B4,Mapping!B:D,3,0) -> West | E4: =VLOOKUP(B4,Mapping!B:E,4,0) -> West 2 | F4: =VLOOKUP(B4,Mapping!B:F,5,0) -> Anjli | G4: =VLOOKUP(B4,Mapping!B:G,6,0) -> Shweta | H4: 2 | I4: 0 | J4: 2 | K4: 0 | L4: 1 | M4: 5 | N4: 1 | O4: 1 | P4: 0 | Q4: 1 | R4: 0 | S4: 2
A5: FY2024-25 | B5: Tata Marcopolo | C5: =VLOOKUP(B5,Mapping!B:C,2,0) -> Lateral | D5: =VLOOKUP(B5,Mapping!B:D,3,0) -> West | E5: =VLOOKUP(B5,Mapping!B:E,4,0) -> West 2 | F5: =VLOOKUP(B5,Mapping!B:F,5,0) -> Anjli | G5: =VLOOKUP(B5,Mapping!B:G,6,0) -> Anjli | H5: 0 | I5: 0 | J5: 0 | K5: 1 | L5: 0 | M5: 0 | N5: 1 | O5: 0 | P5: 0 | Q5: 0 | R5: 0 | S5: 1
A6: FY2024-25 | B6: ThyssenKrupp | C6: =VLOOKUP(B6,Mapping!B:C,2,0) -> Lateral | D6: =VLOOKUP(B6,Mapping!B:D,3,0) -> West | E6: =VLOOKUP(B6,Mapping!B:E,4,0) -> West 2 | F6: =VLOOKUP(B6,Mapping!B:F,5,0) -> Anjli | G6: =VLOOKUP(B6,Mapping!B:G,6,0) -> Shweta | H6: 0 | I6: 0 | J6: 10 | K6: 12 | L6: 12 | M6: 11 | N6: 6 | O6: 7 | P6: 2 | Q6: 3 | R6: 0 | S6: 0
A7: FY2024-25 | B7: Ultratech | C7: =VLOOKUP(B7,Mapping!B:C,2,0) -> Lateral | D7: =VLOOKUP(B7,Mapping!B:D,3,0) -> West | E7: =VLOOKUP(B7,Mapping!B:E,4,0) -> West 1 | F7: =VLOOKUP(B7,Mapping!B:F,5,0) -> Anjli | G7: =VLOOKUP(B7,Mapping!B:G,6,0) -> Elton | H7: 0 | I7: 0 | J7: 3 | K7: 0 | L7: 0 | M7: 0 | N7: 0 | O7: 0 | P7: 0 | Q7: 0 | R7: 0 | S7: 0
A8: FY2024-25 | B8: Tata Teleservices | C8: =VLOOKUP(B8,Mapping!B:C,2,0) -> Lateral | D8: =VLOOKUP(B8,Mapping!B:D,3,0) -> West | E8: =VLOOKUP(B8,Mapping!B:E,4,0) -> West 1 | F8: =VLOOKUP(B8,Mapping!B:F,5,0) -> Anjli | G8: =VLOOKUP(B8,Mapping!B:G,6,0) -> Elton | H8: 0 | I8: 0 | J8: 0 | K8: 0 | L8: 0 | M8: 0 | N8: 3 | O8: 0 | P8: 0 | Q8: 0 | R8: 0 | S8: 0
A9: FY2024-25 | B9: Hyundai Motor | C9: =VLOOKUP(B9,Mapping!B:C,2,0) -> Lateral | D9: =VLOOKUP(B9,Mapping!B:D,3,0) -> West | E9: =VLOOKUP(B9,Mapping!B:E,4,0) -> West 2 | F9: =VLOOKUP(B9,Mapping!B:F,5,0) -> Anjli | G9: =VLOOKUP(B9,Mapping!B:G,6,0) -> Shweta | H9: 1 | I9: 0 | J9: 0 | K9: 0 | L9: 6 | M9: 2 | N9: 2 | O9: 1 | P9: 4 | Q9: 0 | R9: 0 | S9: 0
A10: FY2024-25 | B10: Bridgestone | C10: =VLOOKUP(B10,Mapping!B:C,2,0) -> Lateral | D10: =VLOOKUP(B10,Mapping!B:D,3,0) -> West | E10: =VLOOKUP(B10,Mapping!B:E,4,0) -> West 2 | F10: =VLOOKUP(B10,Mapping!B:F,5,0) -> Anjli | G10: =VLOOKUP(B10,Mapping!B:G,6,0) -> Shweta | H10: 0 | I10: 0 | J10: 0 | K10: 0 | L10: 0 | M10: 0 | N10: 0 | O10: 0 | P10: 0 | Q10: 0 | R10: 0 | S10: 0
A11: FY2024-25 | B11: SKF India | C11: =VLOOKUP(B11,Mapping!B:C,2,0) -> Lateral | D11: =VLOOKUP(B11,Mapping!B:D,3,0) -> North | E11: =VLOOKUP(B11,Mapping!B:E,4,0) -> North | F11: =VLOOKUP(B11,Mapping!B:F,5,0) -> Anjli | G11: =VLOOKUP(B11,Mapping!B:G,6,0) -> Archana | H11: 16 | I11: 0 | J11: 9 | K11: 8 | L11: 5 | M11: 17 | N11: 6 | O11: 2 | P11: 6 | Q11: 7 | R11: 3 | S11: 11
A12: FY2024-25 | B12: Jindal Stainless | C12: =VLOOKUP(B12,Mapping!B:C,2,0) -> Lateral | D12: =VLOOKUP(B12,Mapping!B:D,3,0) -> North | E12: =VLOOKUP(B12,Mapping!B:E,4,0) -> North | F12: =VLOOKUP(B12,Mapping!B:F,5,0) -> Anjli | G12: =VLOOKUP(B12,Mapping!B:G,6,0) -> Archana | H12: 0 | I12: 0 | J12: 0 | K12: 0 | L12: 0 | M12: 0 | N12: 0 | O12: 0 | P12: 0 | Q12: 0 | R12: 0 | S12: 0
A13: FY2024-25 | B13: Maruti Suzuki(MSIL) | C13: =VLOOKUP(B13,Mapping!B:C,2,0) -> Lateral | D13: =VLOOKUP(B13,Mapping!B:D,3,0) -> North | E13: =VLOOKUP(B13,Mapping!B:E,4,0) -> North | F13: =VLOOKUP(B13,Mapping!B:F,5,0) -> Anjli | G13: =VLOOKUP(B13,Mapping!B:G,6,0) -> Archana | H13: 0 | I13: 0 | J13: 0 | K13: 0 | L13: 0 | M13: 0 | N13: 0 | O13: 1 | P13: 0 | Q13: 0 | R13: 0 | S13: 78
A14: FY2024-25 | B14: Suzuki R&D | C14: =VLOOKUP(B14,Mapping!B:C,2,0) -> Lateral | D14: =VLOOKUP(B14,Mapping!B:D,3,0) -> North | E14: =VLOOKUP(B14,Mapping!B:E,4,0) -> North | F14: =VLOOKUP(B14,Mapping!B:F,5,0) -> Anjli | G14: =VLOOKUP(B14,Mapping!B:G,6,0) -> Archana | H14: 0 | P14: 0 | Q14: 0 | R14: 0 | S14: 0
A15: FY2024-25 | B15: Subros Ltd | C15: =VLOOKUP(B15,Mapping!B:C,2,0) -> Lateral | D15: =VLOOKUP(B15,Mapping!B:D,3,0) -> North | E15: =VLOOKUP(B15,Mapping!B:E,4,0) -> North | F15: =VLOOKUP(B15,Mapping!B:F,5,0) -> Anjli | G15: =VLOOKUP(B15,Mapping!B:G,6,0) -> Archana | H15: 0 | I15: 0 | J15: 0 | K15: 0 | L15: 0 | M15: 0 | N15: 0 | O15: 0 | P15: 0 | Q15: 0 | R15: 0 | S15: 0
A16: FY2024-25 | B16: Pernod Ricard | C16: =VLOOKUP(B16,Mapping!B:C,2,0) -> Lateral | D16: =VLOOKUP(B16,Mapping!B:D,3,0) -> North | E16: =VLOOKUP(B16,Mapping!B:E,4,0) -> North | F16: =VLOOKUP(B16,Mapping!B:F,5,0) -> Anjli | G16: =VLOOKUP(B16,Mapping!B:G,6,0) -> Archana | H16: 0 | I16: 0 | J16: 0 | K16: 0 | L16: 0 | M16: 0 | N16: 0 | O16: 0 | P16: 0 | Q16: 0 | R16: 0 | S16: 0
A17: FY2024-25 | B17: Pfizer | C17: =VLOOKUP(B17,Mapping!B:C,2,0) -> Lateral | D17: =VLOOKUP(B17,Mapping!B:D,3,0) -> West | E17: =VLOOKUP(B17,Mapping!B:E,4,0) -> West 1 | F17: =VLOOKUP(B17,Mapping!B:F,5,0) -> Anjli | G17: =VLOOKUP(B17,Mapping!B:G,6,0) -> Usha | H17: 0 | I17: 0 | J17: 12 | K17: 16 | L17: 12 | M17: 11 | N17: 0 | O17: 0 | P17: 0 | Q17: 0 | R17: 0 | S17: 0
A18: FY2024-25 | B18: Tata Power | C18: =VLOOKUP(B18,Mapping!B:C,2,0) -> Lateral | D18: =VLOOKUP(B18,Mapping!B:D,3,0) -> West | E18: =VLOOKUP(B18,Mapping!B:E,4,0) -> West 1 | F18: =VLOOKUP(B18,Mapping!B:F,5,0) -> Anjli | G18: =VLOOKUP(B18,Mapping!B:G,6,0) -> Elton | H18: 0 | I18: 0 | J18: 0 | K18: 0 | L18: 0 | M18: 0 | N18: 0 | O18: 0 | P18: 0 | Q18: 0 | R18: 0 | S18: 0
A19: FY2024-25 | B19: Pidilite | C19: =VLOOKUP(B19,Mapping!B:C,2,0) -> Lateral | D19: =VLOOKUP(B19,Mapping!B:D,3,0) -> West | E19: =VLOOKUP(B19,Mapping!B:E,4,0) -> West 1 | F19: =VLOOKUP(B19,Mapping!B:F,5,0) -> Anjli | G19: =VLOOKUP(B19,Mapping!B:G,6,0) -> Usha | H19: 22 | I19: 0 | J19: 10 | K19: 0 | L19: 9 | M19: 3 | N19: 18 | O19: 7 | P19: 17 | Q19: 22 | R19: 17 | S19: 29
A20: FY2024-25 | B20: Birla Paints | C20: =VLOOKUP(B20,Mapping!B:C,2,0) -> Lateral | D20: =VLOOKUP(B20,Mapping!B:D,3,0) -> West | E20: =VLOOKUP(B20,Mapping!B:E,4,0) -> West 1 | F20: =VLOOKUP(B20,Mapping!B:F,5,0) -> Anjli | G20: =VLOOKUP(B20,Mapping!B:G,6,0) -> Geetu | H20: 16 | I20: 0 | J20: 51 | K20: 5 | L20: 43 | M20: 41 | N20: 34 | O20: 18 | P20: 0 | Q20: 20 | R20: 26 | S20: 14
A21: FY2024-25 | B21: M&M | C21: =VLOOKUP(B21,Mapping!B:C,2,0) -> Lateral & Leadership | D21: =VLOOKUP(B21,Mapping!B:D,3,0) -> West | E21: =VLOOKUP(B21,Mapping!B:E,4,0) -> West 1 | F21: =VLOOKUP(B21,Mapping!B:F,5,0) -> Anjli | G21: =VLOOKUP(B21,Mapping!B:G,6,0) -> Dhriti | H21: 0 | I21: 0 | J21: 108 | K21: 215 | L21: 651 | M21: 201 | N21: 175 | O21: 102 | P21: 94 | Q21: 133 | R21: 103 | S21: 88
A22: FY2024-25 | B22: DP World | C22: =VLOOKUP(B22,Mapping!B:C,2,0) -> Lateral | D22: =VLOOKUP(B22,Mapping!B:D,3,0) -> West | E22: =VLOOKUP(B22,Mapping!B:E,4,0) -> West 1 | F22: =VLOOKUP(B22,Mapping!B:F,5,0) -> Anjli | G22: =VLOOKUP(B22,Mapping!B:G,6,0) -> Geetu | H22: 37 | I22: 0 | J22: 9 | K22: 15 | L22: 10 | M22: 8 | N22: 5 | O22: 15 | P22: 15 | Q22: 18 | R22: 17 | S22: 24
A23: FY2024-25 | B23: AMNS | C23: =VLOOKUP(B23,Mapping!B:C,2,0) -> Lateral | D23: =VLOOKUP(B23,Mapping!B:D,3,0) -> West | E23: =VLOOKUP(B23,Mapping!B:E,4,0) -> West 1 | F23: =VLOOKUP(B23,Mapping!B:F,5,0) -> Anjli | G23: =VLOOKUP(B23,Mapping!B:G,6,0) -> Alifia | H23: 0 | I23: 0 | J23: 39 | K23: 37 | L23: 17 | M23: 20 | N23: 34 | O23: 39 | P23: 68 | Q23: 47 | R23: 43 | S23: 24
A24: FY2024-25 | B24: Mahindra Holidays | C24: =VLOOKUP(B24,Mapping!B:C,2,0) -> Lateral | D24: =VLOOKUP(B24,Mapping!B:D,3,0) -> West | E24: =VLOOKUP(B24,Mapping!B:E,4,0) -> West 1 | F24: =VLOOKUP(B24,Mapping!B:F,5,0) -> Anjli | G24: =VLOOKUP(B24,Mapping!B:G,6,0) -> Geetu | H24: 1 | I24: 0 | J24: 1 | K24: 10 | L24: 8 | M24: 0 | N24: 0 | O24: 0 | P24: 13 | Q24: 1 | R24: 0 | S24: 3
A25: FY2024-25 | B25: WTW | C25: =VLOOKUP(B25,Mapping!B:C,2,0) -> Lateral | D25: =VLOOKUP(B25,Mapping!B:D,3,0) -> West | E25: =VLOOKUP(B25,Mapping!B:E,4,0) -> West 1 | F25: =VLOOKUP(B25,Mapping!B:F,5,0) -> Anjli | G25: =VLOOKUP(B25,Mapping!B:G,6,0) -> Geetu | H25: 0 | I25: 0 | J25: 5 | K25: 0 | L25: 0 | M25: 0 | N25: 0 | O25: 0 | P25: 0 | Q25: 0 | R25: 0 | S25: 0
A26: FY2024-25 | B26: Fedex | C26: =VLOOKUP(B26,Mapping!B:C,2,0) -> Lateral | D26: =VLOOKUP(B26,Mapping!B:D,3,0) -> West | E26: =VLOOKUP(B26,Mapping!B:E,4,0) -> West 1 | F26: =VLOOKUP(B26,Mapping!B:F,5,0) -> Anjli | G26: =VLOOKUP(B26,Mapping!B:G,6,0) -> Elton | H26: 0 | I26: 0 | J26: 0 | K26: 0 | L26: 0 | M26: 0 | N26: 0 | O26: 0 | P26: 0 | Q26: 0 | R26: 0 | S26: 0
... A40: FY2024-25 | B40: P&G | C40: =VLOOKUP(B40,Mapping!B:C,2,0) -> Lateral | D40: =VLOOKUP(B40,Mapping!B:D,3,0) -> South | E40: =VLOOKUP(B40,Mapping!B:E,4,0) -> South 2 | F40: =VLOOKUP(B40,Mapping!B:F,5,0) -> Sulabh | G40: =VLOOKUP(B40,Mapping!B:G,6,0) -> Krishna | H40: 0 | I40: 0 | J40: 0 | K40: 0 | L40: 0 | M40: 0 | N40: 0 | O40: 0 | P40: 0 | Q40: 0 | R40: 0 | S40: 0
A41: FY2024-25 | B41: L&T Energy | C41: =VLOOKUP(B41,Mapping!B:C,2,0) -> Lateral | D41: =VLOOKUP(B41,Mapping!B:D,3,0) -> South | E41: =VLOOKUP(B41,Mapping!B:E,4,0) -> South 2 | F41: =VLOOKUP(B41,Mapping!B:F,5,0) -> Sulabh | G41: =VLOOKUP(B41,Mapping!B:G,6,0) -> Krishna | H41: 0 | P41: 0 | Q41: 0 | R41: 0 | S41: 0
A42: FY2024-25 | B42: Tata Electronics | C42: =VLOOKUP(B42,Mapping!B:C,2,0) -> Lateral | D42: =VLOOKUP(B42,Mapping!B:D,3,0) -> South | E42: =VLOOKUP(B42,Mapping!B:E,4,0) -> South 2 | F42: =VLOOKUP(B42,Mapping!B:F,5,0) -> Sulabh | G42: =VLOOKUP(B42,Mapping!B:G,6,0) -> Subu | H42: 0 | I42: 0 | J42: 10 | K42: 6 | L42: 4 | M42: 3 | N42: 6 | O42: 20 | P42: 3 | Q42: 2 | R42: 1 | S42: 5
A43: FY2024-25 | B43: Royal Enfield | C43: =VLOOKUP(B43,Mapping!B:C,2,0) -> Lateral | D43: =VLOOKUP(B43,Mapping!B:D,3,0) -> South | E43: =VLOOKUP(B43,Mapping!B:E,4,0) -> South 2 | F43: =VLOOKUP(B43,Mapping!B:F,5,0) -> Sulabh | G43: =VLOOKUP(B43,Mapping!B:G,6,0) -> Krishna | H43: 0 | I43: 0 | J43: 0 | K43: 0 | L43: 0 | M43: 0 | N43: 0 | O43: 0 | P43: 0 | Q43: 0 | R43: 0 | S43: 0
A44: FY2024-25 | B44: Excelacom | C44: =VLOOKUP(B44,Mapping!B:C,2,0) -> Lateral | D44: =VLOOKUP(B44,Mapping!B:D,3,0) -> South | E44: =VLOOKUP(B44,Mapping!B:E,4,0) -> South 2 | F44: =VLOOKUP(B44,Mapping!B:F,5,0) -> Sulabh | G44: =VLOOKUP(B44,Mapping!B:G,6,0) -> Krishna | H44: 0 | I44: 0 | J44: 0 | K44: 0 | L44: 0 | M44: 0 | N44: 0 | O44: 0 | P44: 0 | Q44: 0 | R44: 0 | S44: 0
A45: FY2024-25 | B45: Viteos | C45: =VLOOKUP(B45,Mapping!B:C,2,0) -> Lateral | D45: =VLOOKUP(B45,Mapping!B:D,3,0) -> South | E45: =VLOOKUP(B45,Mapping!B:E,4,0) -> South 2 | F45: =VLOOKUP(B45,Mapping!B:F,5,0) -> Sulabh | G45: =VLOOKUP(B45,Mapping!B:G,6,0) -> Krishna | H45: 0 | I45: 0 | J45: 0 | K45: 0 | L45: 0 | M45: 0 | N45: 0 | O45: 0 | P45: 0 | Q45: 0 | R45: 0 | S45: 0
A46: FY2024-25 | B46: Ashok Leyland | C46: =VLOOKUP(B46,Mapping!B:C,2,0) -> Lateral | D46: =VLOOKUP(B46,Mapping!B:D,3,0) -> South | E46: =VLOOKUP(B46,Mapping!B:E,4,0) -> South 2 | F46: =VLOOKUP(B46,Mapping!B:F,5,0) -> Sulabh | G46: =VLOOKUP(B46,Mapping!B:G,6,0) -> Krishna | H46: 0 | I46: 0 | J46: 0 | K46: 0 | L46: 0 | M46: 0 | N46: 0 | O46: 0 | P46: 0 | Q46: 0 | R46: 1 | S46: 5
A47: FY2024-25 | B47: M2P Fintech | C47: =VLOOKUP(B47,Mapping!B:C,2,0) -> Lateral | D47: =VLOOKUP(B47,Mapping!B:D,3,0) -> South | E47: =VLOOKUP(B47,Mapping!B:E,4,0) -> South 2 | F47: =VLOOKUP(B47,Mapping!B:F,5,0) -> Sulabh | G47: =VLOOKUP(B47,Mapping!B:G,6,0) -> Krishna | H47: 0 | I47: 0 | J47: 0 | K47: 0 | L47: 0 | M47: 0 | N47: 0 | O47: 0 | P47: 0 | Q47: 0 | R47: 0 | S47: 0
A48: FY2024-25 | B48: ABB | C48: =VLOOKUP(B48,Mapping!B:C,2,0) -> Lateral | D48: =VLOOKUP(B48,Mapping!B:D,3,0) -> South | E48: =VLOOKUP(B48,Mapping!B:E,4,0) -> South 2 | F48: =VLOOKUP(B48,Mapping!B:F,5,0) -> Sulabh | G48: =VLOOKUP(B48,Mapping!B:G,6,0) -> Satya | H48: 0 | I48: 0 | J48: 0 | K48: 0 | L48: 0 | M48: 0 | N48: 0 | O48: 0 | P48: 0 | Q48: 0 | R48: 0 | S48: 0
A49: FY2024-25 | B49: Honeywell | C49: =VLOOKUP(B49,Mapping!B:C,2,0) -> Lateral & Leadership | D49: =VLOOKUP(B49,Mapping!B:D,3,0) -> Bapi | E49: =VLOOKUP(B49,Mapping!B:E,4,0) -> South 1 | F49: =VLOOKUP(B49,Mapping!B:F,5,0) -> Bapi | G49: =VLOOKUP(B49,Mapping!B:G,6,0) -> Bapi | H49: 164 | I49: 0 | J49: 177 | K49: 240 | L49: 149 | M49: 178 | N49: 270 | O49: 141 | P49: 130 | Q49: 407 | R49: 84 | S49: 167
A50: FY2024-25 | B50: Siemens | C50: =VLOOKUP(B50,Mapping!B:C,2,0) -> Lateral | D50: =VLOOKUP(B50,Mapping!B:D,3,0) -> South | E50: =VLOOKUP(B50,Mapping!B:E,4,0) -> South 1 | F50: =VLOOKUP(B50,Mapping!B:F,5,0) -> Sulabh | G50: =VLOOKUP(B50,Mapping!B:G,6,0) -> Kunal | H50: 16 | I50: 0 | J50: 16 | K50: 6 | L50: 26 | M50: 12 | N50: 0 | O50: 16 | P50: 7 | Q50: 7 | R50: 18 | S50: 10
A51: FY2024-25 | B51: Robert Bosch | C51: =VLOOKUP(B51,Mapping!B:C,2,0) -> Lateral | D51: =VLOOKUP(B51,Mapping!B:D,3,0) -> South | E51: =VLOOKUP(B51,Mapping!B:E,4,0) -> South 2 | F51: =VLOOKUP(B51,Mapping!B:F,5,0) -> Sulabh | G51: =VLOOKUP(B51,Mapping!B:G,6,0) -> Abhilash | H51: 0 | I51: 0 | J51: 0 | K51: 0 | L51: 0 | M51: 0 | N51: 0 | O51: 0 | P51: 0 | Q51: 0 | R51: 0 | S51: 0
A52: FY2024-25 | B52: HPE | C52: =VLOOKUP(B52,Mapping!B:C,2,0) -> Lateral | D52: =VLOOKUP(B52,Mapping!B:D,3,0) -> Mahak | E52: =VLOOKUP(B52,Mapping!B:E,4,0) -> South 1 | F52: =VLOOKUP(B52,Mapping!B:F,5,0) -> Mahak | G52: =VLOOKUP(B52,Mapping!B:G,6,0) -> Mahak | H52: 51 | I52: 0 | J52: 6 | K52: 189 | L52: 10 | M52: 159 | N52: 443 | O52: 51 | P52: 159 | Q52: 81 | R52: 594 | S52: 111
A53: FY2024-25 | B53: Isuzu | C53: =VLOOKUP(B53,Mapping!B:C,2,0) -> Lateral | D53: =VLOOKUP(B53,Mapping!B:D,3,0) -> South | E53: =VLOOKUP(B53,Mapping!B:E,4,0) -> South 1 | F53: =VLOOKUP(B53,Mapping!B:F,5,0) -> Sulabh | G53: =VLOOKUP(B53,Mapping!B:G,6,0) -> Satya | H53: 4 | I53: 0 | J53: 7 | K53: 1 | L53: 2 | M53: 3 | N53: 3 | O53: 3 | P53: 0 | Q53: 2 | R53: 2 | S53: 1
... A57: FY2024-25 | B57: Common | C57: =VLOOKUP(B57,Mapping!B:C,2,0) -> Lateral | D57: =VLOOKUP(B57,Mapping!B:D,3,0) -> Common | E57: =VLOOKUP(B57,Mapping!B:E,4,0) -> North | F57: =VLOOKUP(B57,Mapping!B:F,5,0) -> Common | G57: =VLOOKUP(B57,Mapping!B:G,6,0) -> Common | H57: 0 | I57: 0 | J57: 0 | K57: 0 | L57: 0 | M57: 0 | N57: 0 | O57: 0 | P57: 0 | Q57: 0 | R57: 0 | S57: 0
H62: Non taggd joiner is just number of people joined from non taggd source

Sheet Rev_Adjustment
A1: FY | B1: Project | C1: Vertical | D1: Region | E1: Sub Region | F1: Region Head | G1: Practice Head | H1: 45383 | I1: =EDATE(H1,1) -> 45413 | J1: =EDATE(I1,1) -> 45444 | K1: =EDATE(J1,1) -> 45474 | L1: =EDATE(K1,1) -> 45505 | M1: =EDATE(L1,1) -> 45536 | N1: =EDATE(M1,1) -> 45566 | O1: =EDATE(N1,1) -> 45597 | P1: =EDATE(O1,1) -> 45627 | ... S1: =EDATE(R1,1) -> 45717
A2: FY2024-25 | B2: Tata Motors | C2: =VLOOKUP(B2,Mapping!B:C,2,0) -> Lateral | D2: =VLOOKUP(B2,Mapping!B:D,3,0) -> West | E2: =VLOOKUP(B2,Mapping!B:E,4,0) -> West 2 | F2: =VLOOKUP(B2,Mapping!B:F,5,0) -> Anjli | G2: =VLOOKUP(B2,Mapping!B:G,6,0) -> Shweta | H2: 0 | I2: 0 | J2: 0 | K2: 0 | L2: 0 | M2: 0 | N2: 0 | O2: 0 | P2: 0 | Q2: 0 | R2: 0 | S2: 0
A3: FY2024-25 | B3: Schaeffler | C3: =VLOOKUP(B3,Mapping!B:C,2,0) -> Lateral | D3: =VLOOKUP(B3,Mapping!B:D,3,0) -> West | E3: =VLOOKUP(B3,Mapping!B:E,4,0) -> West 2 | F3: =VLOOKUP(B3,Mapping!B:F,5,0) -> Anjli | G3: =VLOOKUP(B3,Mapping!B:G,6,0) -> Shweta | H3: 0 | I3: 0 | J3: 0 | K3: 0 | L3: 0 | M3: 0 | N3: 0 | O3: 0 | P3: 0 | Q3: 0 | R3: 0 | S3: 0
A4: FY2024-25 | B4: Vertiv | C4: =VLOOKUP(B4,Mapping!B:C,2,0) -> Lateral | D4: =VLOOKUP(B4,Mapping!B:D,3,0) -> West | E4: =VLOOKUP(B4,Mapping!B:E,4,0) -> West 2 | F4: =VLOOKUP(B4,Mapping!B:F,5,0) -> Anjli | G4: =VLOOKUP(B4,Mapping!B:G,6,0) -> Shweta | H4: 0 | I4: 0 | J4: 0 | K4: 0 | L4: 0 | M4: 0 | N4: 0 | O4: 0 | P4: 0 | Q4: 0 | R4: 0 | S4: 0
A5: FY2024-25 | B5: Tata Marcopolo | C5: =VLOOKUP(B5,Mapping!B:C,2,0) -> Lateral | D5: =VLOOKUP(B5,Mapping!B:D,3,0) -> West | E5: =VLOOKUP(B5,Mapping!B:E,4,0) -> West 2 | F5: =VLOOKUP(B5,Mapping!B:F,5,0) -> Anjli | G5: =VLOOKUP(B5,Mapping!B:G,6,0) -> Anjli | H5: 0 | I5: 0 | J5: 0 | K5: 0 | L5: 0 | M5: 0 | N5: 0 | O5: 0 | P5: 0 | Q5: 0 | R5: 0 | S5: 0
A6: FY2024-25 | B6: ThyssenKrupp | C6: =VLOOKUP(B6,Mapping!B:C,2,0) -> Lateral | D6: =VLOOKUP(B6,Mapping!B:D,3,0) -> West | E6: =VLOOKUP(B6,Mapping!B:E,4,0) -> West 2 | F6: =VLOOKUP(B6,Mapping!B:F,5,0) -> Anjli | G6: =VLOOKUP(B6,Mapping!B:G,6,0) -> Shweta | H6: 0 | I6: 0 | J6: 0 | K6: 0 | L6: 0 | M6: 0 | N6: 0 | O6: 0 | P6: 0 | Q6: 0 | R6: 0 | S6: 0
A7: FY2024-25 | B7: Ultratech | C7: =VLOOKUP(B7,Mapping!B:C,2,0) -> Lateral | D7: =VLOOKUP(B7,Mapping!B:D,3,0) -> West | E7: =VLOOKUP(B7,Mapping!B:E,4,0) -> West 1 | F7: =VLOOKUP(B7,Mapping!B:F,5,0) -> Anjli | G7: =VLOOKUP(B7,Mapping!B:G,6,0) -> Elton | H7: 0 | I7: 0 | J7: 0 | K7: 0 | L7: 0 | M7: 0 | N7: 0 | O7: 0 | P7: 0 | Q7: 0 | R7: 0 | S7: 0
A8: FY2024-25 | B8: Tata Teleservices | C8: =VLOOKUP(B8,Mapping!B:C,2,0) -> Lateral | D8: =VLOOKUP(B8,Mapping!B:D,3,0) -> West | E8: =VLOOKUP(B8,Mapping!B:E,4,0) -> West 1 | F8: =VLOOKUP(B8,Mapping!B:F,5,0) -> Anjli | G8: =VLOOKUP(B8,Mapping!B:G,6,0) -> Elton | H8: 0 | I8: 0 | J8: 0 | K8: 0 | L8: 0 | M8: 0 | N8: 0 | O8: 0 | P8: 0 | Q8: 0 | R8: 0 | S8: 0
A9: FY2024-25 | B9: Hyundai Motor | C9: =VLOOKUP(B9,Mapping!B:C,2,0) -> Lateral | D9: =VLOOKUP(B9,Mapping!B:D,3,0) -> West | E9: =VLOOKUP(B9,Mapping!B:E,4,0) -> West 2 | F9: =VLOOKUP(B9,Mapping!B:F,5,0) -> Anjli | G9: =VLOOKUP(B9,Mapping!B:G,6,0) -> Shweta | H9: 0 | I9: 0 | J9: 0 | K9: 0 | L9: 0 | M9: 0 | N9: 0 | O9: 0 | P9: 0 | Q9: 0 | R9: 0 | S9: 0
A10: FY2024-25 | B10: Bridgestone | C10: =VLOOKUP(B10,Mapping!B:C,2,0) -> Lateral | D10: =VLOOKUP(B10,Mapping!B:D,3,0) -> West | E10: =VLOOKUP(B10,Mapping!B:E,4,0) -> West 2 | F10: =VLOOKUP(B10,Mapping!B:F,5,0) -> Anjli | G10: =VLOOKUP(B10,Mapping!B:G,6,0) -> Shweta | H10: 0 | I10: 0 | J10: 0 | K10: 0 | L10: 0 | M10: 0 | N10: 0 | O10: 0 | P10: 0 | Q10: 0 | R10: 0 | S10: 0
A11: FY2024-25 | B11: SKF India | C11: =VLOOKUP(B11,Mapping!B:C,2,0) -> Lateral | D11: =VLOOKUP(B11,Mapping!B:D,3,0) -> North | E11: =VLOOKUP(B11,Mapping!B:E,4,0) -> North | F11: =VLOOKUP(B11,Mapping!B:F,5,0) -> Anjli | G11: =VLOOKUP(B11,Mapping!B:G,6,0) -> Archana | H11: 0 | I11: 0 | J11: 0 | K11: 0 | L11: 0 | M11: 0 | N11: 0 | O11: 0 | P11: 0 | Q11: 0 | R11: 0 | S11: 0
A12: FY2024-25 | B12: Jindal Stainless | C12: =VLOOKUP(B12,Mapping!B:C,2,0) -> Lateral | D12: =VLOOKUP(B12,Mapping!B:D,3,0) -> North | E12: =VLOOKUP(B12,Mapping!B:E,4,0) -> North | F12: =VLOOKUP(B12,Mapping!B:F,5,0) -> Anjli | G12: =VLOOKUP(B12,Mapping!B:G,6,0) -> Archana | H12: 0 | I12: 0 | J12: 0 | K12: 0 | L12: 0 | M12: 0 | N12: 0 | O12: 0 | P12: 0 | Q12: 0 | R12: 0 | S12: 0
A13: FY2024-25 | B13: Maruti Suzuki(MSIL) | C13: =VLOOKUP(B13,Mapping!B:C,2,0) -> Lateral | D13: =VLOOKUP(B13,Mapping!B:D,3,0) -> North | E13: =VLOOKUP(B13,Mapping!B:E,4,0) -> North | F13: =VLOOKUP(B13,Mapping!B:F,5,0) -> Anjli | G13: =VLOOKUP(B13,Mapping!B:G,6,0) -> Archana | H13: 0 | I13: 0 | J13: 0 | K13: 0 | L13: 0 | M13: 0 | N13: 0 | O13: 0 | P13: 0 | Q13: 0 | R13: 0 | S13: 0
... A57: FY2024-25 | B57: Common | C57: =VLOOKUP(B57,Mapping!B:C,2,0) -> Lateral | D57: =VLOOKUP(B57,Mapping!B:D,3,0) -> Common | E57: =VLOOKUP(B57,Mapping!B:E,4,0) -> North | F57: =VLOOKUP(B57,Mapping!B:F,5,0) -> Common | G57: =VLOOKUP(B57,Mapping!B:G,6,0) -> Common | H57: 0 | I57: 0 | J57: 0 | K57: 0 | L57: 0 | M57: 0 | N57: 0 | O57: 0 | P57: 0 | Q57: 0 | R57: 0 | S57: 0
H60: As it is, denomination in lacs; this basically any changes in rev that happend

Sheet Actual Headcount WL1
A1: FY | B1: Project | C1: Vertical | D1: Region | E1: Sub Region | F1: Region Head | G1: Practice Head | H1: 45383 | I1: =EDATE(H1,1) -> 45413 | J1: =EDATE(I1,1) -> 45444 | K1: =EDATE(J1,1) -> 45474 | L1: =EDATE(K1,1) -> 45505 | M1: =EDATE(L1,1) -> 45536 | N1: =EDATE(M1,1) -> 45566 | O1: =EDATE(N1,1) -> 45597 | P1: =EDATE(O1,1) -> 45627 | ... S1: =EDATE(R1,1) -> 45717
A2: FY2024-25 | B2: Tata Motors | C2: =VLOOKUP(B2,Mapping!B:C,2,0) -> Lateral | D2: =VLOOKUP(B2,Mapping!B:D,3,0) -> West | E2: =VLOOKUP(B2,Mapping!B:E,4,0) -> West 2 | F2: =VLOOKUP(B2,Mapping!B:F,5,0) -> Anjli | G2: =VLOOKUP(B2,Mapping!B:G,6,0) -> Shweta | H2: 45.33 | I2: 45 | J2: 31.9 | K2: 27.25 | L2: 26.25 | M2: 27.25 | N2: 27.25 | O2: 25.8 | P2: 24.5 | Q2: 20.5 | R2: 11.5 | S2: 2
A3: FY2024-25 | B3: Schaeffler | C3: =VLOOKUP(B3,Mapping!B:C,2,0) -> Lateral | D3: =VLOOKUP(B3,Mapping!B:D,3,0) -> West | E3: =VLOOKUP(B3,Mapping!B:E,4,0) -> West 2 | F3: =VLOOKUP(B3,Mapping!B:F,5,0) -> Anjli | G3: =VLOOKUP(B3,Mapping!B:G,6,0) -> Shweta | H3: 7.84 | I3: 5.5 | J3: 5.8 | K3: 6.05 | L3: 7 | M3: 5.25 | N3: 2.75 | O3: 3.2 | P3: 2.7 | Q3: 3 | R3: 4 | S3: 4.5
A4: FY2024-25 | B4: Vertiv | C4: =VLOOKUP(B4,Mapping!B:C,2,0) -> Lateral | D4: =VLOOKUP(B4,Mapping!B:D,3,0) -> West | E4: =VLOOKUP(B4,Mapping!B:E,4,0) -> West 2 | F4: =VLOOKUP(B4,Mapping!B:F,5,0) -> Anjli | G4: =VLOOKUP(B4,Mapping!B:G,6,0) -> Shweta | H4: 6 | I4: 6 | J4: 6 | K4: 4 | L4: 4 | M4: 4 | N4: 4 | O4: 3 | P4: 3 | Q4: 3 | R4: 5 | S4: 4.5
A5: FY2024-25 | B5: Tata Marcopolo | C5: =VLOOKUP(B5,Mapping!B:C,2,0) -> Lateral | D5: =VLOOKUP(B5,Mapping!B:D,3,0) -> West | E5: =VLOOKUP(B5,Mapping!B:E,4,0) -> West 2 | F5: =VLOOKUP(B5,Mapping!B:F,5,0) -> Anjli | G5: =VLOOKUP(B5,Mapping!B:G,6,0) -> Anjli | H5: 1 | I5: 1 | J5: 1 | K5: 1 | L5: 1 | M5: 1 | N5: 1 | O5: 1.2 | P5: 0 | Q5: 0 | R5: 1 | S5: 1
A6: FY2024-25 | B6: ThyssenKrupp | C6: =VLOOKUP(B6,Mapping!B:C,2,0) -> Lateral | D6: =VLOOKUP(B6,Mapping!B:D,3,0) -> West | E6: =VLOOKUP(B6,Mapping!B:E,4,0) -> West 2 | F6: =VLOOKUP(B6,Mapping!B:F,5,0) -> Anjli | G6: =VLOOKUP(B6,Mapping!B:G,6,0) -> Shweta | H6: 14.33 | I6: 14 | J6: 15 | K6: 15.25 | L6: 14.25 | M6: 16.25 | N6: 11.25 | O6: 2.8 | P6: 3.5 | Q6: 0.2 | R6: 0.2 | S6: 0
A7: FY2024-25 | B7: Ultratech | C7: =VLOOKUP(B7,Mapping!B:C,2,0) -> Lateral | D7: =VLOOKUP(B7,Mapping!B:D,3,0) -> West | E7: =VLOOKUP(B7,Mapping!B:E,4,0) -> West 1 | F7: =VLOOKUP(B7,Mapping!B:F,5,0) -> Anjli | G7: =VLOOKUP(B7,Mapping!B:G,6,0) -> Elton | H7: 1.5 | I7: 1.5 | J7: 1.5 | K7: 1.5 | L7: 0.75 | M7: 0.5 | N7: 0 | O7: 0 | P7: 0 | Q7: 0 | R7: 0 | S7: 0
A8: FY2024-25 | B8: Tata Teleservices | C8: =VLOOKUP(B8,Mapping!B:C,2,0) -> Lateral | D8: =VLOOKUP(B8,Mapping!B:D,3,0) -> West | E8: =VLOOKUP(B8,Mapping!B:E,4,0) -> West 1 | F8: =VLOOKUP(B8,Mapping!B:F,5,0) -> Anjli | G8: =VLOOKUP(B8,Mapping!B:G,6,0) -> Elton | H8: 1.5 | I8: 3 | J8: 2.4 | K8: 3 | L8: 2 | M8: 2 | N8: 2 | O8: 2 | P8: 2 | Q8: 2 | R8: 1 | S8: 0
A9: FY2024-25 | B9: Hyundai Motor | C9: =VLOOKUP(B9,Mapping!B:C,2,0) -> Lateral | D9: =VLOOKUP(B9,Mapping!B:D,3,0) -> West | E9: =VLOOKUP(B9,Mapping!B:E,4,0) -> West 2 | F9: =VLOOKUP(B9,Mapping!B:F,5,0) -> Anjli | G9: =VLOOKUP(B9,Mapping!B:G,6,0) -> Shweta | H9: 5 | I9: 5 | J9: 5 | K9: 5.25 | L9: 6.75 | M9: 9.75 | N9: 11.75 | O9: 13.5 | P9: 12 | Q9: 12 | R9: 12 | S9: 15.5
A10: FY2024-25 | B10: Bridgestone | C10: =VLOOKUP(B10,Mapping!B:C,2,0) -> Lateral | D10: =VLOOKUP(B10,Mapping!B:D,3,0) -> West | E10: =VLOOKUP(B10,Mapping!B:E,4,0) -> West 2 | F10: =VLOOKUP(B10,Mapping!B:F,5,0) -> Anjli | G10: =VLOOKUP(B10,Mapping!B:G,6,0) -> Shweta | H10: 0 | I10: 0 | J10: 0 | K10: 0 | L10: 0 | M10: 0 | N10: 0 | O10: 1 | P10: 0 | Q10: 1 | R10: 2 | S10: 3
A11: FY2024-25 | B11: SKF India | C11: =VLOOKUP(B11,Mapping!B:C,2,0) -> Lateral | D11: =VLOOKUP(B11,Mapping!B:D,3,0) -> North | E11: =VLOOKUP(B11,Mapping!B:E,4,0) -> North | F11: =VLOOKUP(B11,Mapping!B:F,5,0) -> Anjli | G11: =VLOOKUP(B11,Mapping!B:G,6,0) -> Archana | H11: 9.5 | I11: 10.5 | J11: 11.5 | K11: 12 | L11: 11 | M11: 11 | N11: 10 | O11: 9 | P11: 9 | Q11: 9 | R11: 9 | S11: 9
A12: FY2024-25 | B12: Jindal Stainless | C12: =VLOOKUP(B12,Mapping!B:C,2,0) -> Lateral | D12: =VLOOKUP(B12,Mapping!B:D,3,0) -> North | E12: =VLOOKUP(B12,Mapping!B:E,4,0) -> North | F12: =VLOOKUP(B12,Mapping!B:F,5,0) -> Anjli | G12: =VLOOKUP(B12,Mapping!B:G,6,0) -> Archana | H12: 11.4 | I12: 10 | J12: 10 | K12: 10 | L12: 9 | M12: 10 | N12: 10 | O12: 8 | P12: 8 | Q12: 8 | R12: 8 | S12: 4
A13: FY2024-25 | B13: Maruti Suzuki(MSIL) | C13: =VLOOKUP(B13,Mapping!B:C,2,0) -> Lateral | D13: =VLOOKUP(B13,Mapping!B:D,3,0) -> North | E13: =VLOOKUP(B13,Mapping!B:E,4,0) -> North | F13: =VLOOKUP(B13,Mapping!B:F,5,0) -> Anjli | G13: =VLOOKUP(B13,Mapping!B:G,6,0) -> Archana | H13: 0.4 | I13: 2 | J13: 6.5 | K13: 16.1 | L13: 19.5 | M13: 30.15 | N13: 29 | O13: 43.5 | P13: 45 | Q13: 47.4 | R13: 46.4 | S13: 52.5
... A58: FY2024-25 | B58: Bench | C58: =VLOOKUP(B58,Mapping!B:C,2,0) -> Lateral | D58: =VLOOKUP(B58,Mapping!B:D,3,0) -> North | E58: =VLOOKUP(B58,Mapping!B:E,4,0) -> North | F58: =VLOOKUP(B58,Mapping!B:F,5,0) -> Anjli | G58: =VLOOKUP(B58,Mapping!B:G,6,0) -> Anjli | H58: 29 | I58: 27 | J58: 27.5 | K58: 19 | L58: 10 | M58: 12 | N58: 11 | O58: 4 | P58: 0 | Q58: 0 | R58: 2 | S58: 1
F61: Work level 1 headcount actual

Sheet Approved_Headcount
A1: FY | B1: Project | C1: Vertical | D1: Region | E1: Sub Region | F1: Region Head | G1: Practice Head | H1: 45383 | I1: =EDATE(H1,1) -> 45413 | J1: =EDATE(I1,1) -> 45444 | K1: =EDATE(J1,1) -> 45474 | L1: =EDATE(K1,1) -> 45505 | M1: =EDATE(L1,1) -> 45536 | N1: =EDATE(M1,1) -> 45566 | O1: =EDATE(N1,1) -> 45597 | P1: =EDATE(O1,1) -> 45627 | ... S1: =EDATE(R1,1) -> 45717
A2: FY2024-25 | B2: Tata Motors | C2: =VLOOKUP(B2,Mapping!B:C,2,0) -> Lateral | D2: =VLOOKUP(B2,Mapping!B:D,3,0) -> West | E2: =VLOOKUP(B2,Mapping!B:E,4,0) -> West 2 | F2: =VLOOKUP(B2,Mapping!B:F,5,0) -> Anjli | G2: =VLOOKUP(B2,Mapping!B:G,6,0) -> Shweta | H2: =Revenue_Actual!H2/Target_Rev_Productivity!H2 -> 37.775 | I2: =Revenue_Actual!I2/Target_Rev_Productivity!I2 -> 37.5 | J2: =Revenue_Actual!J2/Target_Rev_Productivity!J2 -> 26.583333 | K2: =Revenue_Actual!K2/Target_Rev_Productivity!K2 -> 22.708333 | L2: =Revenue_Actual!L2/Target_Rev_Productivity!L2 -> 21.875 | M2: =Revenue_Actual!M2/Target_Rev_Productivity!M2 -> 26.072531 | N2: =Revenue_Actual!N2/Target_Rev_Productivity!N2 -> 22.708333 | O2: =Revenue_Actual!O2/Target_Rev_Productivity!O2 -> 21.5 | ... S2: =Revenue_Actual!S2/Target_Rev_Productivity!S2 -> 1.6666667
A3: FY2024-25 | B3: Schaeffler | C3: =VLOOKUP(B3,Mapping!B:C,2,0) -> Lateral | D3: =VLOOKUP(B3,Mapping!B:D,3,0) -> West | E3: =VLOOKUP(B3,Mapping!B:E,4,0) -> West 2 | F3: =VLOOKUP(B3,Mapping!B:F,5,0) -> Anjli | G3: =VLOOKUP(B3,Mapping!B:G,6,0) -> Shweta | H3: =Revenue_Actual!H3/Target_Rev_Productivity!H3 -> 6.5333333 | I3: =Revenue_Actual!I3/Target_Rev_Productivity!I3 -> 4.5833333 | J3: =Revenue_Actual!J3/Target_Rev_Productivity!J3 -> 4.8333333 | K3: =Revenue_Actual!K3/Target_Rev_Productivity!K3 -> 5.0416667 | L3: =Revenue_Actual!L3/Target_Rev_Productivity!L3 -> 5.8333333 | M3: =Revenue_Actual!M3/Target_Rev_Productivity!M3 -> 4.375 | N3: =Revenue_Actual!N3/Target_Rev_Productivity!N3 -> 2.2916667 | O3: =Revenue_Actual!O3/Target_Rev_Productivity!O3 -> 2.6666667 | ... S3: =Revenue_Actual!S3/Target_Rev_Productivity!S3 -> 3.75
A4: FY2024-25 | B4: Vertiv | C4: =VLOOKUP(B4,Mapping!B:C,2,0) -> Lateral | D4: =VLOOKUP(B4,Mapping!B:D,3,0) -> West | E4: =VLOOKUP(B4,Mapping!B:E,4,0) -> West 2 | F4: =VLOOKUP(B4,Mapping!B:F,5,0) -> Anjli | G4: =VLOOKUP(B4,Mapping!B:G,6,0) -> Shweta | H4: =Revenue_Actual!H4/Target_Rev_Productivity!H4 -> 5 | I4: =Revenue_Actual!I4/Target_Rev_Productivity!I4 -> 5 | J4: =Revenue_Actual!J4/Target_Rev_Productivity!J4 -> 5 | K4: =Revenue_Actual!K4/Target_Rev_Productivity!K4 -> 3.3333333 | L4: =Revenue_Actual!L4/Target_Rev_Productivity!L4 -> 3.3333333 | M4: =Revenue_Actual!M4/Target_Rev_Productivity!M4 -> 3.3333333 | N4: =Revenue_Actual!N4/Target_Rev_Productivity!N4 -> 3.3333333 | O4: =Revenue_Actual!O4/Target_Rev_Productivity!O4 -> 2.5 | ... S4: =Revenue_Actual!S4/Target_Rev_Productivity!S4 -> 3.75
A5: FY2024-25 | B5: Tata Marcopolo | C5: =VLOOKUP(B5,Mapping!B:C,2,0) -> Lateral | D5: =VLOOKUP(B5,Mapping!B:D,3,0) -> West | E5: =VLOOKUP(B5,Mapping!B:E,4,0) -> West 2 | F5: =VLOOKUP(B5,Mapping!B:F,5,0) -> Anjli | G5: =VLOOKUP(B5,Mapping!B:G,6,0) -> Anjli | H5: =Revenue_Actual!H5/Target_Rev_Productivity!H5 -> 0.83333333 | I5: =Revenue_Actual!I5/Target_Rev_Productivity!I5 -> 0.83333333 | J5: =Revenue_Actual!J5/Target_Rev_Productivity!J5 -> 0.83333333 | K5: =Revenue_Actual!K5/Target_Rev_Productivity!K5 -> 0.83333333 | L5: =Revenue_Actual!L5/Target_Rev_Productivity!L5 -> 0.83333333 | M5: =Revenue_Actual!M5/Target_Rev_Productivity!M5 -> 0.83333333 | N5: =Revenue_Actual!N5/Target_Rev_Productivity!N5 -> 0.83333333 | O5: =Revenue_Actual!O5/Target_Rev_Productivity!O5 -> 0 | ... S5: =Revenue_Actual!S5/Target_Rev_Productivity!S5 -> 0.83333333
A6: FY2024-25 | B6: ThyssenKrupp | C6: =VLOOKUP(B6,Mapping!B:C,2,0) -> Lateral | D6: =VLOOKUP(B6,Mapping!B:D,3,0) -> West | E6: =VLOOKUP(B6,Mapping!B:E,4,0) -> West 2 | F6: =VLOOKUP(B6,Mapping!B:F,5,0) -> Anjli | G6: =VLOOKUP(B6,Mapping!B:G,6,0) -> Shweta | H6: =Revenue_Actual!H6/Target_Rev_Productivity!H6 -> 11.941667 | I6: =Revenue_Actual!I6/Target_Rev_Productivity!I6 -> 11.666667 | J6: =Revenue_Actual!J6/Target_Rev_Productivity!J6 -> 12.5 | K6: =Revenue_Actual!K6/Target_Rev_Productivity!K6 -> 12.708333 | L6: =Revenue_Actual!L6/Target_Rev_Productivity!L6 -> 11.875 | M6: =Revenue_Actual!M6/Target_Rev_Productivity!M6 -> 13.541667 | N6: =Revenue_Actual!N6/Target_Rev_Productivity!N6 -> 9.375 | O6: =Revenue_Actual!O6/Target_Rev_Productivity!O6 -> 2.3333333 | ... S6: =Revenue_Actual!S6/Target_Rev_Productivity!S6 -> -5.5192722
A7: FY2024-25 | B7: Ultratech | C7: =VLOOKUP(B7,Mapping!B:C,2,0) -> Lateral | D7: =VLOOKUP(B7,Mapping!B:D,3,0) -> West | E7: =VLOOKUP(B7,Mapping!B:E,4,0) -> West 1 | F7: =VLOOKUP(B7,Mapping!B:F,5,0) -> Anjli | G7: =VLOOKUP(B7,Mapping!B:G,6,0) -> Elton | H7: =Revenue_Actual!H7/Target_Rev_Productivity!H7 -> 1.25 | I7: =Revenue_Actual!I7/Target_Rev_Productivity!I7 -> 1.25 | J7: =Revenue_Actual!J7/Target_Rev_Productivity!J7 -> 1.25 | K7: =Revenue_Actual!K7/Target_Rev_Productivity!K7 -> 1.25 | L7: =Revenue_Actual!L7/Target_Rev_Productivity!L7 -> 0 | M7: =Revenue_Actual!M7/Target_Rev_Productivity!M7 -> 0 | N7: =Revenue_Actual!N7/Target_Rev_Productivity!N7 -> 0 | O7: =Revenue_Actual!O7/Target_Rev_Productivity!O7 -> 0 | ... S7: =Revenue_Actual!S7/Target_Rev_Productivity!S7 -> 0
A8: FY2024-25 | B8: Tata Teleservices | C8: =VLOOKUP(B8,Mapping!B:C,2,0) -> Lateral | D8: =VLOOKUP(B8,Mapping!B:D,3,0) -> West | E8: =VLOOKUP(B8,Mapping!B:E,4,0) -> West 1 | F8: =VLOOKUP(B8,Mapping!B:F,5,0) -> Anjli | G8: =VLOOKUP(B8,Mapping!B:G,6,0) -> Elton | H8: =Revenue_Actual!H8/Target_Rev_Productivity!H8 -> 0 | I8: =Revenue_Actual!I8/Target_Rev_Productivity!I8 -> 0 | J8: =Revenue_Actual!J8/Target_Rev_Productivity!J8 -> 0 | K8: =Revenue_Actual!K8/Target_Rev_Productivity!K8 -> 0 | L8: =Revenue_Actual!L8/Target_Rev_Productivity!L8 -> 0 | M8: =Revenue_Actual!M8/Target_Rev_Productivity!M8 -> 0 | N8: =Revenue_Actual!N8/Target_Rev_Productivity!N8 -> 0 | O8: =Revenue_Actual!O8/Target_Rev_Productivity!O8 -> 0 | ... S8: =Revenue_Actual!S8/Target_Rev_Productivity!S8 -> 0
A9: FY2024-25 | B9: Hyundai Motor | C9: =VLOOKUP(B9,Mapping!B:C,2,0) -> Lateral | D9: =VLOOKUP(B9,Mapping!B:D,3,0) -> West | E9: =VLOOKUP(B9,Mapping!B:E,4,0) -> West 2 | F9: =VLOOKUP(B9,Mapping!B:F,5,0) -> Anjli | G9: =VLOOKUP(B9,Mapping!B:G,6,0) -> Shweta | H9: =Revenue_Actual!H9/Target_Rev_Productivity!H9 -> 4.1666667 | I9: =Revenue_Actual!I9/Target_Rev_Productivity!I9 -> 4.1666667 | J9: =Revenue_Actual!J9/Target_Rev_Productivity!J9 -> 4.1666667 | K9: =Revenue_Actual!K9/Target_Rev_Productivity!K9 -> 4.375 | L9: =Revenue_Actual!L9/Target_Rev_Productivity!L9 -> 5.625 | M9: =Revenue_Actual!M9/Target_Rev_Productivity!M9 -> 8.125 | N9: =Revenue_Actual!N9/Target_Rev_Productivity!N9 -> 9.7916667 | O9: =Revenue_Actual!O9/Target_Rev_Productivity!O9 -> 11.25 | ... S9: =Revenue_Actual!S9/Target_Rev_Productivity!S9 -> 12.916667
A10: FY2024-25 | B10: Bridgestone | C10: =VLOOKUP(B10,Mapping!B:C,2,0) -> Lateral | D10: =VLOOKUP(B10,Mapping!B:D,3,0) -> West | E10: =VLOOKUP(B10,Mapping!B:E,4,0) -> West 2 | F10: =VLOOKUP(B10,Mapping!B:F,5,0) -> Anjli | G10: =VLOOKUP(B10,Mapping!B:G,6,0) -> Shweta | H10: =Revenue_Actual!H10/Target_Rev_Productivity!H10 -> 0 | I10: =Revenue_Actual!I10/Target_Rev_Productivity!I10 -> 0 | J10: =Revenue_Actual!J10/Target_Rev_Productivity!J10 -> 0 | K10: =Revenue_Actual!K10/Target_Rev_Productivity!K10 -> 0 | L10: =Revenue_Actual!L10/Target_Rev_Productivity!L10 -> 0 | M10: =Revenue_Actual!M10/Target_Rev_Productivity!M10 -> 0 | N10: =Revenue_Actual!N10/Target_Rev_Productivity!N10 -> 0 | O10: =Revenue_Actual!O10/Target_Rev_Productivity!O10 -> 0.83333333 | ... S10: =Revenue_Actual!S10/Target_Rev_Productivity!S10 -> 2.5
A11: FY2024-25 | B11: SKF India | C11: =VLOOKUP(B11,Mapping!B:C,2,0) -> Lateral | D11: =VLOOKUP(B11,Mapping!B:D,3,0) -> North | E11: =VLOOKUP(B11,Mapping!B:E,4,0) -> North | F11: =VLOOKUP(B11,Mapping!B:F,5,0) -> Anjli | G11: =VLOOKUP(B11,Mapping!B:G,6,0) -> Archana | H11: =Revenue_Actual!H11/Target_Rev_Productivity!H11 -> 7.9166667 | I11: =Revenue_Actual!I11/Target_Rev_Productivity!I11 -> 8.75 | J11: =Revenue_Actual!J11/Target_Rev_Productivity!J11 -> 9.5833333 | K11: =Revenue_Actual!K11/Target_Rev_Productivity!K11 -> 10 | L11: =Revenue_Actual!L11/Target_Rev_Productivity!L11 -> 9.1666667 | M11: =Revenue_Actual!M11/Target_Rev_Productivity!M11 -> 9.1666667 | N11: =Revenue_Actual!N11/Target_Rev_Productivity!N11 -> 8.3333333 | O11: =Revenue_Actual!O11/Target_Rev_Productivity!O11 -> 7.5 | ... S11: =Revenue_Actual!S11/Target_Rev_Productivity!S11 -> 7.5
A12: FY2024-25 | B12: Jindal Stainless | C12: =VLOOKUP(B12,Mapping!B:C,2,0) -> Lateral | D12: =VLOOKUP(B12,Mapping!B:D,3,0) -> North | E12: =VLOOKUP(B12,Mapping!B:E,4,0) -> North | F12: =VLOOKUP(B12,Mapping!B:F,5,0) -> Anjli | G12: =VLOOKUP(B12,Mapping!B:G,6,0) -> Archana | H12: =Revenue_Actual!H12/Target_Rev_Productivity!H12 -> 9.5 | I12: =Revenue_Actual!I12/Target_Rev_Productivity!I12 -> 8.3333333 | J12: =Revenue_Actual!J12/Target_Rev_Productivity!J12 -> 8.3333333 | K12: =Revenue_Actual!K12/Target_Rev_Productivity!K12 -> 8.3333333 | L12: =Revenue_Actual!L12/Target_Rev_Productivity!L12 -> 7.5 | M12: =Revenue_Actual!M12/Target_Rev_Productivity!M12 -> 8.3333333 | N12: =Revenue_Actual!N12/Target_Rev_Productivity!N12 -> 8.3333333 | O12: =Revenue_Actual!O12/Target_Rev_Productivity!O12 -> 6.6666667 | ... S12: =Revenue_Actual!S12/Target_Rev_Productivity!S12 -> 3.3333333
A13: FY2024-25 | B13: Maruti Suzuki(MSIL) | C13: =VLOOKUP(B13,Mapping!B:C,2,0) -> Lateral | D13: =VLOOKUP(B13,Mapping!B:D,3,0) -> North | E13: =VLOOKUP(B13,Mapping!B:E,4,0) -> North | F13: =VLOOKUP(B13,Mapping!B:F,5,0) -> Anjli | G13: =VLOOKUP(B13,Mapping!B:G,6,0) -> Archana | H13: =Revenue_Actual!H13/Target_Rev_Productivity!H13 -> 0.33333333 | I13: =Revenue_Actual!I13/Target_Rev_Productivity!I13 -> 1.6666667 | J13: =Revenue_Actual!J13/Target_Rev_Productivity!J13 -> 5.4166667 | K13: =Revenue_Actual!K13/Target_Rev_Productivity!K13 -> 13.416667 | L13: =Revenue_Actual!L13/Target_Rev_Productivity!L13 -> 16.25 | M13: =Revenue_Actual!M13/Target_Rev_Productivity!M13 -> 25.125 | N13: =Revenue_Actual!N13/Target_Rev_Productivity!N13 -> 24.166667 | O13: =Revenue_Actual!O13/Target_Rev_Productivity!O13 -> 36.25 | ... S13: =Revenue_Actual!S13/Target_Rev_Productivity!S13 -> 43.75
... A57: FY2024-25 | B57: Common | C57: =VLOOKUP(B57,Mapping!B:C,2,0) -> Lateral | D57: =VLOOKUP(B57,Mapping!B:D,3,0) -> Common | E57: =VLOOKUP(B57,Mapping!B:E,4,0) -> North | F57: =VLOOKUP(B57,Mapping!B:F,5,0) -> Common | G57: =VLOOKUP(B57,Mapping!B:G,6,0) -> Common | H57: =Revenue_Actual!H57/Target_Rev_Productivity!H57 -> 0 | I57: =Revenue_Actual!I57/Target_Rev_Productivity!I57 -> 0 | J57: =Revenue_Actual!J57/Target_Rev_Productivity!J57 -> 0 | K57: =Revenue_Actual!K57/Target_Rev_Productivity!K57 -> 0 | L57: =Revenue_Actual!L57/Target_Rev_Productivity!L57 -> 0 | M57: =Revenue_Actual!M57/Target_Rev_Productivity!M57 -> 0 | N57: =Revenue_Actual!N57/Target_Rev_Productivity!N57 -> 0 | O57: =Revenue_Actual!O57/Target_Rev_Productivity!O57 -> 0 | ... S57: =Revenue_Actual!S57/Target_Rev_Productivity!S57 -> 0

Sheet Actual_Headcount Overall
A1: FY | B1: Project | C1: Vertical | D1: Region | E1: Sub Region | F1: Region Head | G1: Practice Head | H1: 45383 | I1: =EDATE(H1,1) -> 45413 | J1: =EDATE(I1,1) -> 45444 | K1: =EDATE(J1,1) -> 45474 | L1: =EDATE(K1,1) -> 45505 | M1: =EDATE(L1,1) -> 45536 | N1: =EDATE(M1,1) -> 45566 | O1: =EDATE(N1,1) -> 45597 | P1: =EDATE(O1,1) -> 45627 | ... S1: =EDATE(R1,1) -> 45717
A2: FY2024-25 | B2: Tata Motors | C2: =VLOOKUP(B2,Mapping!B:C,2,0) -> Lateral | D2: =VLOOKUP(B2,Mapping!B:D,3,0) -> West | E2: =VLOOKUP(B2,Mapping!B:E,4,0) -> West 2 | F2: =VLOOKUP(B2,Mapping!B:F,5,0) -> Anjli | G2: =VLOOKUP(B2,Mapping!B:G,6,0) -> Shweta | H2: 51.13 | I2: 50.1 | J2: 37 | K2: 29.95 | L2: 28.95 | M2: 30.35 | N2: 30.05 | O2: 27.7 | P2: 27.4 | Q2: 22.4 | R2: 13.4 | S2: 2.15
A3: FY2024-25 | B3: Schaeffler | C3: =VLOOKUP(B3,Mapping!B:C,2,0) -> Lateral | D3: =VLOOKUP(B3,Mapping!B:D,3,0) -> West | E3: =VLOOKUP(B3,Mapping!B:E,4,0) -> West 2 | F3: =VLOOKUP(B3,Mapping!B:F,5,0) -> Anjli | G3: =VLOOKUP(B3,Mapping!B:G,6,0) -> Shweta | H3: 8.84 | I3: 6.5 | J3: 6.8 | K3: 7.05 | L3: 8 | M3: 6.25 | N3: 3.75 | O3: 4.2 | P3: 3.7 | Q3: 4 | R3: 5 | S3: 7.1
A4: FY2024-25 | B4: Vertiv | C4: =VLOOKUP(B4,Mapping!B:C,2,0) -> Lateral | D4: =VLOOKUP(B4,Mapping!B:D,3,0) -> West | E4: =VLOOKUP(B4,Mapping!B:E,4,0) -> West 2 | F4: =VLOOKUP(B4,Mapping!B:F,5,0) -> Anjli | G4: =VLOOKUP(B4,Mapping!B:G,6,0) -> Shweta | H4: 6.5 | I4: 6 | J4: 6 | K4: 4 | L4: 4 | M4: 4 | N4: 4 | O4: 3 | P4: 3 | Q4: 3 | R4: 5 | S4: 4.6
A5: FY2024-25 | B5: Tata Marcopolo | C5: =VLOOKUP(B5,Mapping!B:C,2,0) -> Lateral | D5: =VLOOKUP(B5,Mapping!B:D,3,0) -> West | E5: =VLOOKUP(B5,Mapping!B:E,4,0) -> West 2 | F5: =VLOOKUP(B5,Mapping!B:F,5,0) -> Anjli | G5: =VLOOKUP(B5,Mapping!B:G,6,0) -> Anjli | H5: 1 | I5: 1 | J5: 1 | K5: 1 | L5: 1 | M5: 1 | N5: 1 | O5: 1.2 | P5: 0 | Q5: 0 | R5: 1 | S5: 1
A6: FY2024-25 | B6: ThyssenKrupp | C6: =VLOOKUP(B6,Mapping!B:C,2,0) -> Lateral | D6: =VLOOKUP(B6,Mapping!B:D,3,0) -> West | E6: =VLOOKUP(B6,Mapping!B:E,4,0) -> West 2 | F6: =VLOOKUP(B6,Mapping!B:F,5,0) -> Anjli | G6: =VLOOKUP(B6,Mapping!B:G,6,0) -> Shweta | H6: 15.83 | I6: 15.5 | J6: 16.3 | K6: 16.55 | L6: 15.55 | M6: 17.65 | N6: 12.75 | O6: 3.3 | P6: 4 | Q6: 0.7 | R6: 0.7 | S6: 0
A7: FY2024-25 | B7: Ultratech | C7: =VLOOKUP(B7,Mapping!B:C,2,0) -> Lateral | D7: =VLOOKUP(B7,Mapping!B:D,3,0) -> West | E7: =VLOOKUP(B7,Mapping!B:E,4,0) -> West 1 | F7: =VLOOKUP(B7,Mapping!B:F,5,0) -> Anjli | G7: =VLOOKUP(B7,Mapping!B:G,6,0) -> Elton | H7: 1.5 | I7: 1.5 | J7: 1.5 | K7: 1.5 | L7: 0.75 | M7: 0.5 | N7: 0 | O7: 0 | P7: 0 | Q7: 0 | R7: 0 | S7: 0
A8: FY2024-25 | B8: Tata Teleservices | C8: =VLOOKUP(B8,Mapping!B:C,2,0) -> Lateral | D8: =VLOOKUP(B8,Mapping!B:D,3,0) -> West | E8: =VLOOKUP(B8,Mapping!B:E,4,0) -> West 1 | F8: =VLOOKUP(B8,Mapping!B:F,5,0) -> Anjli | G8: =VLOOKUP(B8,Mapping!B:G,6,0) -> Elton | H8: 1.7 | I8: 3 | J8: 2.4 | K8: 3 | L8: 2 | M8: 2 | N8: 2 | O8: 2 | P8: 2 | Q8: 2 | R8: 1 | S8: 0
A9: FY2024-25 | B9: Hyundai Motor | C9: =VLOOKUP(B9,Mapping!B:C,2,0) -> Lateral | D9: =VLOOKUP(B9,Mapping!B:D,3,0) -> West | E9: =VLOOKUP(B9,Mapping!B:E,4,0) -> West 2 | F9: =VLOOKUP(B9,Mapping!B:F,5,0) -> Anjli | G9: =VLOOKUP(B9,Mapping!B:G,6,0) -> Shweta | H9: 6 | I9: 6 | J9: 6 | K9: 7.25 | L9: 8.75 | M9: 12.05 | N9: 13.15 | O9: 14.7 | P9: 13.2 | Q9: 13.2 | R9: 13.2 | S9: 16.7
A10: FY2024-25 | B10: Bridgestone | C10: =VLOOKUP(B10,Mapping!B:C,2,0) -> Lateral | D10: =VLOOKUP(B10,Mapping!B:D,3,0) -> West | E10: =VLOOKUP(B10,Mapping!B:E,4,0) -> West 2 | F10: =VLOOKUP(B10,Mapping!B:F,5,0) -> Anjli | G10: =VLOOKUP(B10,Mapping!B:G,6,0) -> Shweta | H10: 0 | I10: 0 | J10: 0 | K10: 0 | L10: 0 | M10: 0 | N10: 0 | O10: 1 | P10: 0 | Q10: 1 | R10: 2 | S10: 3.7
A11: FY2024-25 | B11: SKF India | C11: =VLOOKUP(B11,Mapping!B:C,2,0) -> Lateral | D11: =VLOOKUP(B11,Mapping!B:D,3,0) -> North | E11: =VLOOKUP(B11,Mapping!B:E,4,0) -> North | F11: =VLOOKUP(B11,Mapping!B:F,5,0) -> Anjli | G11: =VLOOKUP(B11,Mapping!B:G,6,0) -> Archana | H11: 14 | I11: 14 | J11: 15.5 | K11: 17 | L11: 16 | M11: 16 | N11: 15 | O11: 14 | P11: 14 | Q11: 14 | R11: 14 | S11: 14
A12: FY2024-25 | B12: Jindal Stainless | C12: =VLOOKUP(B12,Mapping!B:C,2,0) -> Lateral | D12: =VLOOKUP(B12,Mapping!B:D,3,0) -> North | E12: =VLOOKUP(B12,Mapping!B:E,4,0) -> North | F12: =VLOOKUP(B12,Mapping!B:F,5,0) -> Anjli | G12: =VLOOKUP(B12,Mapping!B:G,6,0) -> Archana | H12: 14.65 | I12: 13.25 | J12: 13.25 | K12: 13.25 | L12: 12.25 | M12: 13.25 | N12: 13.3 | O12: 10.8 | P12: 10.7 | Q12: 10.5 | R12: 10.2 | S12: 4.2
A13: FY2024-25 | B13: Maruti Suzuki(MSIL) | C13: =VLOOKUP(B13,Mapping!B:C,2,0) -> Lateral | D13: =VLOOKUP(B13,Mapping!B:D,3,0) -> North | E13: =VLOOKUP(B13,Mapping!B:E,4,0) -> North | F13: =VLOOKUP(B13,Mapping!B:F,5,0) -> Anjli | G13: =VLOOKUP(B13,Mapping!B:G,6,0) -> Archana | H13: 0.4 | I13: 2 | J13: 6.5 | K13: 17.1 | L13: 21.5 | M13: 32.15 | N13: 32 | O13: 47 | P13: 47.5 | Q13: 50.9 | R13: 51.2 | S13: 60.3
... A56: FY2024-25 | B56: ABFRL | C56: =VLOOKUP(B56,Mapping!B:C,2,0) -> Lateral | D56: =VLOOKUP(B56,Mapping!B:D,3,0) -> South | E56: =VLOOKUP(B56,Mapping!B:E,4,0) -> South 2 | F56: =VLOOKUP(B56,Mapping!B:F,5,0) -> Sulabh | G56: =VLOOKUP(B56,Mapping!B:G,6,0) -> Satya | H56: 1 | I56: 1 | J56: 1 | K56: 1 | L56: 1 | M56: 0 | N56: 0 | O56: 0 | P56: 0 | Q56: 0 | R56: 0 | S56: 0
A57: FY2024-25 | B57: Common | C57: =VLOOKUP(B57,Mapping!B:C,2,0) -> Lateral | D57: =VLOOKUP(B57,Mapping!B:D,3,0) -> Common | E57: =VLOOKUP(B57,Mapping!B:E,4,0) -> North | F57: =VLOOKUP(B57,Mapping!B:F,5,0) -> Common | G57: =VLOOKUP(B57,Mapping!B:G,6,0) -> Common | H57: =12.7+35 -> 47.7 | I57: =18+34 -> 52 | J57: =24+34 -> 58 | K57: =10.7+26 -> 36.7 | L57: =12+27 -> 39 | M57: =11+20 -> 31 | N57: =12+19 -> 31 | O57: =11.7+11 -> 22.7 | P57: =11.1+2 -> 13.1 | Q57: 9.9 | R57: =7.9+3 -> 10.9 | S57: =12.8+3 -> 15.8
G64: This is overall headcount, not just worklevel 1

Sheet Actual_PPC
A1: FY | B1: Project | C1: Vertical | D1: Region | E1: Sub Region | F1: Region Head | G1: Practice Head | H1: 45383 | I1: =EDATE(H1,1) -> 45413 | J1: =EDATE(I1,1) -> 45444 | K1: =EDATE(J1,1) -> 45474 | L1: =EDATE(K1,1) -> 45505 | M1: =EDATE(L1,1) -> 45536 | N1: =EDATE(M1,1) -> 45566 | O1: =EDATE(N1,1) -> 45597 | P1: =EDATE(O1,1) -> 45627 | ... S1: =EDATE(R1,1) -> 45717
A2: FY2024-25 | B2: Tata Motors | C2: =VLOOKUP(B2,Mapping!B:C,2,0) -> Lateral | D2: =VLOOKUP(B2,Mapping!B:D,3,0) -> West | E2: =VLOOKUP(B2,Mapping!B:E,4,0) -> West 2 | F2: =VLOOKUP(B2,Mapping!B:F,5,0) -> Anjli | G2: =VLOOKUP(B2,Mapping!B:G,6,0) -> Shweta | H2: 79206.829 | I2: 87020.498 | J2: 84301.849 | K2: 80073.849 | L2: 78686.914 | M2: 87373.147 | N2: 73769.204 | O2: 74584.046 | P2: 75803.988 | Q2: 75133.495 | R2: 73500.794 | S2: 78378.984
A3: FY2024-25 | B3: Schaeffler | C3: =VLOOKUP(B3,Mapping!B:C,2,0) -> Lateral | D3: =VLOOKUP(B3,Mapping!B:D,3,0) -> West | E3: =VLOOKUP(B3,Mapping!B:E,4,0) -> West 2 | F3: =VLOOKUP(B3,Mapping!B:F,5,0) -> Anjli | G3: =VLOOKUP(B3,Mapping!B:G,6,0) -> Shweta | H3: 62147.333 | I3: 73573.558 | J3: 77394.079 | K3: 68412.472 | L3: 65666.883 | M3: 72524.292 | N3: 69028.244 | O3: 68049.539 | P3: 75437.788 | Q3: 74165.138 | R3: 75198.394 | S3: 88415.774
A4: FY2024-25 | B4: Vertiv | C4: =VLOOKUP(B4,Mapping!B:C,2,0) -> Lateral | D4: =VLOOKUP(B4,Mapping!B:D,3,0) -> West | E4: =VLOOKUP(B4,Mapping!B:E,4,0) -> West 2 | F4: =VLOOKUP(B4,Mapping!B:F,5,0) -> Anjli | G4: =VLOOKUP(B4,Mapping!B:G,6,0) -> Shweta | H4: 70303.102 | I4: 66953.686 | J4: 64919.917 | K4: 58372.999 | L4: 57932.258 | M4: 68744.211 | N4: 45705.06 | O4: 51984.751 | P4: 54102.382 | Q4: 52482.471 | R4: 64812.194 | S4: 74741.497
A5: FY2024-25 | B5: Tata Marcopolo | C5: =VLOOKUP(B5,Mapping!B:C,2,0) -> Lateral | D5: =VLOOKUP(B5,Mapping!B:D,3,0) -> West | E5: =VLOOKUP(B5,Mapping!B:E,4,0) -> West 2 | F5: =VLOOKUP(B5,Mapping!B:F,5,0) -> Anjli | G5: =VLOOKUP(B5,Mapping!B:G,6,0) -> Anjli | H5: 54061.025 | I5: 54732.019 | J5: 53026.788 | K5: 56096.749 | L5: 55761.258 | M5: 69827.297 | N5: 50175.31 | O5: 51930.832 | R5: 60034.794 | S5: 69638.845
A6: FY2024-25 | B6: ThyssenKrupp | C6: =VLOOKUP(B6,Mapping!B:C,2,0) -> Lateral | D6: =VLOOKUP(B6,Mapping!B:D,3,0) -> West | E6: =VLOOKUP(B6,Mapping!B:E,4,0) -> West 2 | F6: =VLOOKUP(B6,Mapping!B:F,5,0) -> Anjli | G6: =VLOOKUP(B6,Mapping!B:G,6,0) -> Shweta | H6: 78668.749 | I6: 80382.858 | J6: 77995.364 | K6: 76941.846 | L6: 78589.216 | M6: 85094.937 | N6: 77358.016 | O6: 98195.685 | P6: 86434.382 | Q6: 159070.99 | R6: 149997.22
A7: FY2024-25 | B7: Ultratech | C7: =VLOOKUP(B7,Mapping!B:C,2,0) -> Lateral | D7: =VLOOKUP(B7,Mapping!B:D,3,0) -> West | E7: =VLOOKUP(B7,Mapping!B:E,4,0) -> West 1 | F7: =VLOOKUP(B7,Mapping!B:F,5,0) -> Anjli | G7: =VLOOKUP(B7,Mapping!B:G,6,0) -> Elton | H7: 67460.692 | I7: 68130.686 | J7: 65873.122 | K7: 67291.749 | L7: 63555.591 | M7: 66097.92
A8: FY2024-25 | B8: Tata Teleservices | C8: =VLOOKUP(B8,Mapping!B:C,2,0) -> Lateral | D8: =VLOOKUP(B8,Mapping!B:D,3,0) -> West | E8: =VLOOKUP(B8,Mapping!B:E,4,0) -> West 1 | F8: =VLOOKUP(B8,Mapping!B:F,5,0) -> Anjli | G8: =VLOOKUP(B8,Mapping!B:G,6,0) -> Elton | H8: 108368.26 | I8: 83532.353 | J8: 75060.705 | K8: 73628.749 | L8: 82088.258 | M8: 83253.92 | N8: 74779.31 | O8: 73544.998 | P8: 79050.382 | Q8: 78522.138 | R8: 55099.794
A9: FY2024-25 | B9: Hyundai Motor | C9: =VLOOKUP(B9,Mapping!B:C,2,0) -> Lateral | D9: =VLOOKUP(B9,Mapping!B:D,3,0) -> West | E9: =VLOOKUP(B9,Mapping!B:E,4,0) -> West 2 | F9: =VLOOKUP(B9,Mapping!B:F,5,0) -> Anjli | G9: =VLOOKUP(B9,Mapping!B:G,6,0) -> Shweta | H9: 78531.525 | I9: 85154.519 | J9: 85830.251 | K9: 80609.059 | L9: 72416.772 | M9: 95015.813 | N9: 51615.653 | O9: 73486.982 | P9: 71359.428 | Q9: 75918.062 | R9: 74131.249 | S9: 83520.066
A10: FY2024-25 | B10: Bridgestone | C10: =VLOOKUP(B10,Mapping!B:C,2,0) -> Lateral | D10: =VLOOKUP(B10,Mapping!B:D,3,0) -> West | E10: =VLOOKUP(B10,Mapping!B:E,4,0) -> West 2 | F10: =VLOOKUP(B10,Mapping!B:F,5,0) -> Anjli | G10: =VLOOKUP(B10,Mapping!B:G,6,0) -> Shweta | O10: 55725.159 | Q10: 59646.138 | R10: 75321.294 | S10: 95273.007
A11: FY2024-25 | B11: SKF India | C11: =VLOOKUP(B11,Mapping!B:C,2,0) -> Lateral | D11: =VLOOKUP(B11,Mapping!B:D,3,0) -> North | E11: =VLOOKUP(B11,Mapping!B:E,4,0) -> North | F11: =VLOOKUP(B11,Mapping!B:F,5,0) -> Anjli | G11: =VLOOKUP(B11,Mapping!B:G,6,0) -> Archana | H11: 103585.45 | I11: 97301.662 | J11: 90876.161 | K11: 91345.808 | L11: 93484.195 | M11: 100790.08 | N11: 89391.844 | O11: 96108.89 | P11: 98203.454 | Q11: 97534.495 | R11: 97404.509 | S11: 107127.56
A12: FY2024-25 | B12: Jindal Stainless | C12: =VLOOKUP(B12,Mapping!B:C,2,0) -> Lateral | D12: =VLOOKUP(B12,Mapping!B:D,3,0) -> North | E12: =VLOOKUP(B12,Mapping!B:E,4,0) -> North | F12: =VLOOKUP(B12,Mapping!B:F,5,0) -> Anjli | G12: =VLOOKUP(B12,Mapping!B:G,6,0) -> Archana | H12: 82414.257 | I12: 84681.302 | J12: 94774.919 | K12: 88188.617 | L12: 89899.564 | M12: 99086.387 | N12: 79343.581 | O12: 83670.882 | P12: 82166.962 | Q12: 77420.423 | R12: 72727.657 | S12: 66930.607
A13: FY2024-25 | B13: Maruti Suzuki(MSIL) | C13: =VLOOKUP(B13,Mapping!B:C,2,0) -> Lateral | D13: =VLOOKUP(B13,Mapping!B:D,3,0) -> North | E13: =VLOOKUP(B13,Mapping!B:E,4,0) -> North | F13: =VLOOKUP(B13,Mapping!B:F,5,0) -> Anjli | G13: =VLOOKUP(B13,Mapping!B:G,6,0) -> Archana | H13: 64047.525 | I13: 80297.519 | J13: 64234.558 | K13: 72661.878 | L13: 79952.211 | M13: 73245.569 | N13: 69588.623 | O13: 71164.376 | P13: 70797.835 | Q13: 69190.476 | R13: 71021.888 | S13: 84440.463
A14: FY2024-25 | B14: Suzuki R&D | C14: =VLOOKUP(B14,Mapping!B:C,2,0) -> Lateral | D14: =VLOOKUP(B14,Mapping!B:D,3,0) -> North | E14: =VLOOKUP(B14,Mapping!B:E,4,0) -> North | F14: =VLOOKUP(B14,Mapping!B:F,5,0) -> Anjli | G14: =VLOOKUP(B14,Mapping!B:G,6,0) -> Archana | M14: 67014.92 | R14: 61927.794 | S14: 72962.845
A15: FY2024-25 | B15: Subros Ltd | C15: =VLOOKUP(B15,Mapping!B:C,2,0) -> Lateral | D15: =VLOOKUP(B15,Mapping!B:D,3,0) -> North | E15: =VLOOKUP(B15,Mapping!B:E,4,0) -> North | F15: =VLOOKUP(B15,Mapping!B:F,5,0) -> Anjli | G15: =VLOOKUP(B15,Mapping!B:G,6,0) -> Archana | N15: 91345.31 | O15: 65349.801 | P15: 87111.582 | Q15: 108532.14 | R15: 78560.461 | S15: 91606.845
A16: FY2024-25 | B16: Pernod Ricard | C16: =VLOOKUP(B16,Mapping!B:C,2,0) -> Lateral | D16: =VLOOKUP(B16,Mapping!B:D,3,0) -> North | E16: =VLOOKUP(B16,Mapping!B:E,4,0) -> North | F16: =VLOOKUP(B16,Mapping!B:F,5,0) -> Anjli | G16: =VLOOKUP(B16,Mapping!B:G,6,0) -> Archana | S16: 80718.345
A17: FY2024-25 | B17: Pfizer | C17: =VLOOKUP(B17,Mapping!B:C,2,0) -> Lateral | D17: =VLOOKUP(B17,Mapping!B:D,3,0) -> West | E17: =VLOOKUP(B17,Mapping!B:E,4,0) -> West 1 | F17: =VLOOKUP(B17,Mapping!B:F,5,0) -> Anjli | G17: =VLOOKUP(B17,Mapping!B:G,6,0) -> Usha | H17: 84411.078 | I17: 83450.463 | J17: 81671.984 | K17: 73431.074 | L17: 77414.905 | M17: 77007.662 | N17: 75672.47 | O17: 68236.23 | P17: 98496.2 | Q17: 87353.774 | R17: 90448.017 | S17: 94016.037
A18: FY2024-25 | B18: Tata Power | C18: =VLOOKUP(B18,Mapping!B:C,2,0) -> Lateral | D18: =VLOOKUP(B18,Mapping!B:D,3,0) -> West | E18: =VLOOKUP(B18,Mapping!B:E,4,0) -> West 1 | F18: =VLOOKUP(B18,Mapping!B:F,5,0) -> Anjli | G18: =VLOOKUP(B18,Mapping!B:G,6,0) -> Elton | H18: 87396.547 | I18: 88426.976 | J18: 296608.76 | K18: 218407.08
A19: FY2024-25 | B19: Pidilite | C19: =VLOOKUP(B19,Mapping!B:C,2,0) -> Lateral | D19: =VLOOKUP(B19,Mapping!B:D,3,0) -> West | E19: =VLOOKUP(B19,Mapping!B:E,4,0) -> West 1 | F19: =VLOOKUP(B19,Mapping!B:F,5,0) -> Anjli | G19: =VLOOKUP(B19,Mapping!B:G,6,0) -> Usha | H19: 75255.923 | I19: 77711.648 | J19: 78410.095 | K19: 72753.441 | L19: 76365.633 | M19: 77098.089 | N19: 60116.113 | O19: 66050.684 | P19: 72846.73 | Q19: 74888.051 | R19: 73741.074 | S19: 74044.624
A20: FY2024-25 | B20: Birla Paints | C20: =VLOOKUP(B20,Mapping!B:C,2,0) -> Lateral | D20: =VLOOKUP(B20,Mapping!B:D,3,0) -> West | E20: =VLOOKUP(B20,Mapping!B:E,4,0) -> West 1 | F20: =VLOOKUP(B20,Mapping!B:F,5,0) -> Anjli | G20: =VLOOKUP(B20,Mapping!B:G,6,0) -> Geetu | H20: 73997.489 | I20: 75270.4 | J20: 73509.445 | K20: 76123.273 | L20: 78300.861 | M20: 82890.881 | N20: 68449.081 | O20: 61327.566 | P20: 71888.067 | Q20: 81049.128 | R20: 82306.883 | S20: 94195.311
A21: FY2024-25 | B21: M&M | C21: =VLOOKUP(B21,Mapping!B:C,2,0) -> Lateral & Leadership | D21: =VLOOKUP(B21,Mapping!B:D,3,0) -> West | E21: =VLOOKUP(B21,Mapping!B:E,4,0) -> West 1 | F21: =VLOOKUP(B21,Mapping!B:F,5,0) -> Anjli | G21: =VLOOKUP(B21,Mapping!B:G,6,0) -> Dhriti | H21: 74687.716 | I21: 75325.519 | J21: 76779.938 | K21: 75994.908 | L21: 75819.428 | M21: 88688.459 | N21: 69129.755 | O21: 73669.565 | P21: 74284.882 | Q21: 73485.515 | R21: 78427.89 | S21: 88301.585
A22: FY2024-25 | B22: DP World | C22: =VLOOKUP(B22,Mapping!B:C,2,0) -> Lateral | D22: =VLOOKUP(B22,Mapping!B:D,3,0) -> West | E22: =VLOOKUP(B22,Mapping!B:E,4,0) -> West 1 | F22: =VLOOKUP(B22,Mapping!B:F,5,0) -> Anjli | G22: =VLOOKUP(B22,Mapping!B:G,6,0) -> Geetu | H22: 72258.142 | I22: 69212.662 | J22: 68897.309 | K22: 66669.749 | L22: 67849.027 | M22: 76816.883 | N22: 58032.644 | O22: 55955.245 | P22: 60394.049 | Q22: 66804.065 | R22: 66772.725 | S22: 78582.592
A23: FY2024-25 | B23: AMNS | C23: =VLOOKUP(B23,Mapping!B:C,2,0) -> Lateral | D23: =VLOOKUP(B23,Mapping!B:D,3,0) -> West | E23: =VLOOKUP(B23,Mapping!B:E,4,0) -> West 1 | F23: =VLOOKUP(B23,Mapping!B:F,5,0) -> Anjli | G23: =VLOOKUP(B23,Mapping!B:G,6,0) -> Alifia | H23: 81281.397 | I23: 87229.465 | J23: 80344.662 | K23: 78435.804 | L23: 85956.672 | M23: 88169.719 | N23: 76527.134 | O23: 73706.086 | P23: 82143.928 | Q23: 78754.481 | R23: 81930.158 | S23: 82465.65
A24: FY2024-25 | B24: Mahindra Holidays | C24: =VLOOKUP(B24,Mapping!B:C,2,0) -> Lateral | D24: =VLOOKUP(B24,Mapping!B:D,3,0) -> West | E24: =VLOOKUP(B24,Mapping!B:E,4,0) -> West 1 | F24: =VLOOKUP(B24,Mapping!B:F,5,0) -> Anjli | G24: =VLOOKUP(B24,Mapping!B:G,6,0) -> Geetu | H24: 74644.611 | I24: 76274.954 | J24: 71738.298 | K24: 66152.555 | L24: 60051.799 | M24: 61315.559 | N24: 62045.31 | O24: 63479.201 | P24: 71135.882 | Q24: 66077.688 | R24: 55209.464 | S24: 57487.57
A25: FY2024-25 | B25: WTW | C25: =VLOOKUP(B25,Mapping!B:C,2,0) -> Lateral | D25: =VLOOKUP(B25,Mapping!B:D,3,0) -> West | E25: =VLOOKUP(B25,Mapping!B:E,4,0) -> West 1 | F25: =VLOOKUP(B25,Mapping!B:F,5,0) -> Anjli | G25: =VLOOKUP(B25,Mapping!B:G,6,0) -> Geetu | H25: 98025.581 | I25: 84536.249 | J25: 84906.295 | K25: 97751.38 | L25: 70816.58 | M25: 46128.648 | N25: 330790.31
A26: FY2024-25 | B26: Fedex | C26: =VLOOKUP(B26,Mapping!B:C,2,0) -> Lateral | D26: =VLOOKUP(B26,Mapping!B:D,3,0) -> West | E26: =VLOOKUP(B26,Mapping!B:E,4,0) -> West 1 | F26: =VLOOKUP(B26,Mapping!B:F,5,0) -> Anjli | G26: =VLOOKUP(B26,Mapping!B:G,6,0) -> Elton | H26: 103823.9 | I26: 110657.4 | J26: 110656.04 | K26: 105155.67 | L26: 75416.831 | M26: 119628.56 | N26: 69610.833 | O26: 203091.17
A27: FY2024-25 | B27: Tata Consumer | C27: =VLOOKUP(B27,Mapping!B:C,2,0) -> Lateral | D27: =VLOOKUP(B27,Mapping!B:D,3,0) -> West | E27: =VLOOKUP(B27,Mapping!B:E,4,0) -> West 1 | F27: =VLOOKUP(B27,Mapping!B:F,5,0) -> Anjli | G27: =VLOOKUP(B27,Mapping!B:G,6,0) -> Geetu | J27: 64976.788 | K27: 70804.749 | L27: 72984.858 | M27: 63089.761 | N27: 60554.477 | O27: 68171.576 | P27: 66840.686 | Q27: 66190.981 | R27: 63369.313 | S27: 75423.252
A28: FY2024-25 | B28: Tata Play | C28: =VLOOKUP(B28,Mapping!B:C,2,0) -> Lateral | D28: =VLOOKUP(B28,Mapping!B:D,3,0) -> West | E28: =VLOOKUP(B28,Mapping!B:E,4,0) -> West 1 | F28: =VLOOKUP(B28,Mapping!B:F,5,0) -> Anjli | G28: =VLOOKUP(B28,Mapping!B:G,6,0) -> Geetu | J28: 87341.122 | K28: 104582.75 | L28: 93587.924 | M28: 97781.677 | N28: 72529.644 | O28: 128584.8 | P28: 137383.81 | Q28: 126931.14 | R28: 126575.79 | S28: 147083.34
A29: FY2024-25 | B29: Mahindra Finance | C29: =VLOOKUP(B29,Mapping!B:C,2,0) -> Lateral | D29: =VLOOKUP(B29,Mapping!B:D,3,0) -> West | E29: =VLOOKUP(B29,Mapping!B:E,4,0) -> West 1 | F29: =VLOOKUP(B29,Mapping!B:F,5,0) -> Anjli | G29: =VLOOKUP(B29,Mapping!B:G,6,0) -> Geetu | I29: 40818.019 | J29: 57019.951 | K29: 57276.624 | L29: 64597.035 | M29: 80156.975 | N29: 59416.644 | O29: 67745.398 | P29: 72433.791 | Q29: 75712.072 | R29: 64004.189 | S29: 83345.784
A30: FY2024-25 | B30: Atomberg Technologies | C30: =VLOOKUP(B30,Mapping!B:C,2,0) -> Lateral | D30: =VLOOKUP(B30,Mapping!B:D,3,0) -> West | E30: =VLOOKUP(B30,Mapping!B:E,4,0) -> West 1 | F30: =VLOOKUP(B30,Mapping!B:F,5,0) -> Anjli | G30: =VLOOKUP(B30,Mapping!B:G,6,0) -> Geetu | M30: 92983.488 | N30: 60285.31 | O30: 66405.346 | P30: 75774.712 | Q30: 79583.585 | R30: 77806.286 | S30: 88945.13
A31: FY2024-25 | B31: Ambuja Cement | C31: =VLOOKUP(B31,Mapping!B:C,2,0) -> Lateral | D31: =VLOOKUP(B31,Mapping!B:D,3,0) -> West | E31: =VLOOKUP(B31,Mapping!B:E,4,0) -> West 1 | F31: =VLOOKUP(B31,Mapping!B:F,5,0) -> Anjli | G31: =VLOOKUP(B31,Mapping!B:G,6,0) -> Ankit | N31: 60191.31 | O31: 97206.82 | P31: 78764.414 | Q31: 69847.736 | R31: 75325.455 | S31: 105924.08
A32: FY2024-25 | B32: Sterling Tools | C32: =VLOOKUP(B32,Mapping!B:C,2,0) -> Lateral | D32: =VLOOKUP(B32,Mapping!B:D,3,0) -> North | E32: =VLOOKUP(B32,Mapping!B:E,4,0) -> North | F32: =VLOOKUP(B32,Mapping!B:F,5,0) -> Anjli | G32: =VLOOKUP(B32,Mapping!B:G,6,0) -> Archana | Q32: 75759.638 | R32: 83936.937 | S32: 75445.22
A33: FY2024-25 | B33: Wipro | C33: =VLOOKUP(B33,Mapping!B:C,2,0) -> Lateral | D33: =VLOOKUP(B33,Mapping!B:D,3,0) -> South | E33: =VLOOKUP(B33,Mapping!B:E,4,0) -> South 1 | F33: =VLOOKUP(B33,Mapping!B:F,5,0) -> Sulabh | G33: =VLOOKUP(B33,Mapping!B:G,6,0) -> Subu | H33: 87532.682 | I33: 84066.082 | J33: 87931.212 | K33: 78649.312 | L33: 87837.977 | M33: 98820.759 | N33: 99270.974 | O33: 96856.211 | P33: 104505.75 | Q33: 97409.763 | R33: 103013.04 | S33: 106896.29
A34: FY2024-25 | B34: Nomiso | C34: =VLOOKUP(B34,Mapping!B:C,2,0) -> Lateral | D34: =VLOOKUP(B34,Mapping!B:D,3,0) -> South | E34: =VLOOKUP(B34,Mapping!B:E,4,0) -> South 2 | F34: =VLOOKUP(B34,Mapping!B:F,5,0) -> Sulabh | G34: =VLOOKUP(B34,Mapping!B:G,6,0) -> Krishna | I34: 137700.02 | J34: 123451.78 | K34: 103026.92 | L34: 112561.59
A35: FY2024-25 | B35: Ingram Micro | C35: =VLOOKUP(B35,Mapping!B:C,2,0) -> Lateral | D35: =VLOOKUP(B35,Mapping!B:D,3,0) -> West | E35: =VLOOKUP(B35,Mapping!B:E,4,0) -> West 1 | F35: =VLOOKUP(B35,Mapping!B:F,5,0) -> Anjli | G35: =VLOOKUP(B35,Mapping!B:G,6,0) -> Geetu | H35: 84347.181 | I35: 91431.344 | J35: 96821.135 | K35: 88646.52 | L35: 88993.246 | M35: 96162.697 | N35: 83682.178 | O35: 83419.077 | P35: 82685.797 | Q35: 74214.138 | R35: 74366.544 | S35: 85130.574
A36: FY2024-25 | B36: DRL | C36: =VLOOKUP(B36,Mapping!B:C,2,0) -> Lateral | D36: =VLOOKUP(B36,Mapping!B:D,3,0) -> South | E36: =VLOOKUP(B36,Mapping!B:E,4,0) -> South 2 | F36: =VLOOKUP(B36,Mapping!B:F,5,0) -> Sulabh | G36: =VLOOKUP(B36,Mapping!B:G,6,0) -> Sulabh | H36: 85816.222 | I36: 83276.639 | J36: 77000.417 | K36: 84459.549 | L36: 84447.258 | P36: 89276.382 | Q36: 88701.138 | R36: 89736.794
A37: FY2024-25 | B37: SBI Card | C37: =VLOOKUP(B37,Mapping!B:C,2,0) -> Lateral | D37: =VLOOKUP(B37,Mapping!B:D,3,0) -> North | E37: =VLOOKUP(B37,Mapping!B:E,4,0) -> North | F37: =VLOOKUP(B37,Mapping!B:F,5,0) -> Anjli | G37: =VLOOKUP(B37,Mapping!B:G,6,0) -> Archana | I37: 80992.934 | J37: 77721.727 | K37: 76159.432 | L37: 78433.143 | M37: 81998.012 | N37: 74653.133 | O37: 76035.021 | P37: 78690.604 | Q37: 71289.501 | R37: 71620.128 | S37: 81855.178
A38: FY2024-25 | B38: IBM | C38: =VLOOKUP(B38,Mapping!B:C,2,0) -> Lateral | D38: =VLOOKUP(B38,Mapping!B:D,3,0) -> North | E38: =VLOOKUP(B38,Mapping!B:E,4,0) -> North | F38: =VLOOKUP(B38,Mapping!B:F,5,0) -> Anjli | G38: =VLOOKUP(B38,Mapping!B:G,6,0) -> Anjli | I38: 131047.02 | J38: 75872.503 | K38: 77113.977 | L38: 77356.995 | M38: 82473.42
A39: FY2024-25 | B39: BITS | C39: =VLOOKUP(B39,Mapping!B:C,2,0) -> Lateral | D39: =VLOOKUP(B39,Mapping!B:D,3,0) -> South | E39: =VLOOKUP(B39,Mapping!B:E,4,0) -> South 2 | F39: =VLOOKUP(B39,Mapping!B:F,5,0) -> Sulabh | G39: =VLOOKUP(B39,Mapping!B:G,6,0) -> Krishna | H39: 70246.799 | I39: 65263.019 | J39: 65232.122 | K39: 70604.749 | L39: 70105.258 | M39: 77689.947 | N39: 64055.977 | O39: 67980.769 | P39: 68322.382 | Q39: 68962.804 | R39: 71068.375 | S39: 80032.135
A40: FY2024-25 | B40: P&G | C40: =VLOOKUP(B40,Mapping!B:C,2,0) -> Lateral | D40: =VLOOKUP(B40,Mapping!B:D,3,0) -> South | E40: =VLOOKUP(B40,Mapping!B:E,4,0) -> South 2 | F40: =VLOOKUP(B40,Mapping!B:F,5,0) -> Sulabh | G40: =VLOOKUP(B40,Mapping!B:G,6,0) -> Krishna | H40: 69763.525 | I40: 70501.019 | J40: 70021.788 | K40: 75565.249 | L40: 76005.758 | M40: 81957.684 | N40: 69059.81 | O40: 69944.034 | P40: 73198.882 | Q40: 73372.138 | R40: 72537.294 | S40: 82366.845
A41: FY2024-25 | B41: L&T Energy | C41: =VLOOKUP(B41,Mapping!B:C,2,0) -> Lateral | D41: =VLOOKUP(B41,Mapping!B:D,3,0) -> South | E41: =VLOOKUP(B41,Mapping!B:E,4,0) -> South 2 | F41: =VLOOKUP(B41,Mapping!B:F,5,0) -> Sulabh | G41: =VLOOKUP(B41,Mapping!B:G,6,0) -> Krishna | H41: 71443.192
A42: FY2024-25 | B42: Tata Electronics | C42: =VLOOKUP(B42,Mapping!B:C,2,0) -> Lateral | D42: =VLOOKUP(B42,Mapping!B:D,3,0) -> South | E42: =VLOOKUP(B42,Mapping!B:E,4,0) -> South 2 | F42: =VLOOKUP(B42,Mapping!B:F,5,0) -> Sulabh | G42: =VLOOKUP(B42,Mapping!B:G,6,0) -> Subu | H42: 96744.559 | I42: 110695.57 | J42: 90709.619 | K42: 93711.043 | L42: 113562.59 | M42: 120060.21 | N42: 92006.096 | O42: 92605.73 | P42: 86545.473 | Q42: 82787.281 | R42: 77963.321 | S42: 86167.379
A43: FY2024-25 | B43: Royal Enfield | C43: =VLOOKUP(B43,Mapping!B:C,2,0) -> Lateral | D43: =VLOOKUP(B43,Mapping!B:D,3,0) -> South | E43: =VLOOKUP(B43,Mapping!B:E,4,0) -> South 2 | F43: =VLOOKUP(B43,Mapping!B:F,5,0) -> Sulabh | G43: =VLOOKUP(B43,Mapping!B:G,6,0) -> Krishna | H43: 77423.425 | I43: 83374.219 | J43: 83596.329 | K43: 71130.177 | L43: 87992.543 | M43: 90531.395 | N43: 51071.31 | O43: 57886.762 | P43: 66090.882 | Q43: 65562.638 | R43: 69019.604 | S43: 96926.651
A44: FY2024-25 | B44: Excelacom | C44: =VLOOKUP(B44,Mapping!B:C,2,0) -> Lateral | D44: =VLOOKUP(B44,Mapping!B:D,3,0) -> South | E44: =VLOOKUP(B44,Mapping!B:E,4,0) -> South 2 | F44: =VLOOKUP(B44,Mapping!B:F,5,0) -> Sulabh | G44: =VLOOKUP(B44,Mapping!B:G,6,0) -> Krishna | H44: 88460.525 | I44: 71259.619 | J44: 85668.388 | K44: 81665.349 | L44: 98467.508 | M44: 108186.72 | N44: 84661.644 | O44: 96905.378 | P44: 88928.049 | Q44: 88384.138 | S44: 84624.845
A45: FY2024-25 | B45: Viteos | C45: =VLOOKUP(B45,Mapping!B:C,2,0) -> Lateral | D45: =VLOOKUP(B45,Mapping!B:D,3,0) -> South | E45: =VLOOKUP(B45,Mapping!B:E,4,0) -> South 2 | F45: =VLOOKUP(B45,Mapping!B:F,5,0) -> Sulabh | G45: =VLOOKUP(B45,Mapping!B:G,6,0) -> Krishna
A46: FY2024-25 | B46: Ashok Leyland | C46: =VLOOKUP(B46,Mapping!B:C,2,0) -> Lateral | D46: =VLOOKUP(B46,Mapping!B:D,3,0) -> South | E46: =VLOOKUP(B46,Mapping!B:E,4,0) -> South 2 | F46: =VLOOKUP(B46,Mapping!B:F,5,0) -> Sulabh | G46: =VLOOKUP(B46,Mapping!B:G,6,0) -> Krishna | O46: 50658.11 | P46: 55858.882 | Q46: 74838.632 | R46: 83039.431 | S46: 96245.498
A47: FY2024-25 | B47: M2P Fintech | C47: =VLOOKUP(B47,Mapping!B:C,2,0) -> Lateral | D47: =VLOOKUP(B47,Mapping!B:D,3,0) -> South | E47: =VLOOKUP(B47,Mapping!B:E,4,0) -> South 2 | F47: =VLOOKUP(B47,Mapping!B:F,5,0) -> Sulabh | G47: =VLOOKUP(B47,Mapping!B:G,6,0) -> Krishna | P47: 31820.716 | Q47: 66532.844 | R47: 54210.384 | S47: 62864.084
A48: FY2024-25 | B48: ABB | C48: =VLOOKUP(B48,Mapping!B:C,2,0) -> Lateral | D48: =VLOOKUP(B48,Mapping!B:D,3,0) -> South | E48: =VLOOKUP(B48,Mapping!B:E,4,0) -> South 2 | F48: =VLOOKUP(B48,Mapping!B:F,5,0) -> Sulabh | G48: =VLOOKUP(B48,Mapping!B:G,6,0) -> Satya | S48: 67525.845
A49: FY2024-25 | B49: Honeywell | C49: =VLOOKUP(B49,Mapping!B:C,2,0) -> Lateral & Leadership | D49: =VLOOKUP(B49,Mapping!B:D,3,0) -> Bapi | E49: =VLOOKUP(B49,Mapping!B:E,4,0) -> South 1 | F49: =VLOOKUP(B49,Mapping!B:F,5,0) -> Bapi | G49: =VLOOKUP(B49,Mapping!B:G,6,0) -> Bapi | H49: 86888.626 | I49: 86801.311 | J49: 86870.133 | K49: 89029.874 | L49: 91271.541 | M49: 103719.71 | N49: 89297.255 | O49: 87180.721 | P49: 87446.806 | Q49: 89840.152 | R49: 87978.396 | S49: 98753.412
A50: FY2024-25 | B50: Siemens | C50: =VLOOKUP(B50,Mapping!B:C,2,0) -> Lateral | D50: =VLOOKUP(B50,Mapping!B:D,3,0) -> South | E50: =VLOOKUP(B50,Mapping!B:E,4,0) -> South 1 | F50: =VLOOKUP(B50,Mapping!B:F,5,0) -> Sulabh | G50: =VLOOKUP(B50,Mapping!B:G,6,0) -> Kunal | H50: 88666.407 | I50: 90043.419 | J50: 97545.583 | K50: 89049.209 | L50: 93665.835 | M50: 99646.669 | N50: 88141.144 | O50: 87339.13 | P50: 87025.813 | Q50: 86927.919 | R50: 83126.971 | S50: 98327.791
A51: FY2024-25 | B51: Robert Bosch | C51: =VLOOKUP(B51,Mapping!B:C,2,0) -> Lateral | D51: =VLOOKUP(B51,Mapping!B:D,3,0) -> South | E51: =VLOOKUP(B51,Mapping!B:E,4,0) -> South 2 | F51: =VLOOKUP(B51,Mapping!B:F,5,0) -> Sulabh | G51: =VLOOKUP(B51,Mapping!B:G,6,0) -> Abhilash | H51: 87286.15 | I51: 85066.144 | J51: 100459.94 | K51: 102672 | L51: 110168.26 | M51: 110312.66 | N51: 60514.31 | O51: 59279.998 | P51: 64785.382 | Q51: 64257.138 | R51: 63428.794
A52: FY2024-25 | B52: HPE | C52: =VLOOKUP(B52,Mapping!B:C,2,0) -> Lateral | D52: =VLOOKUP(B52,Mapping!B:D,3,0) -> Mahak | E52: =VLOOKUP(B52,Mapping!B:E,4,0) -> South 1 | F52: =VLOOKUP(B52,Mapping!B:F,5,0) -> Mahak | G52: =VLOOKUP(B52,Mapping!B:G,6,0) -> Mahak | H52: 109653.13 | I52: 113402.86 | J52: 121754.76 | K52: 124394.1 | L52: 124792.95 | M52: 134498.85 | N52: 108440.77 | O52: 113038.71 | P52: 118115.29 | Q52: 117545.45 | R52: 120999.31 | S52: 105295.18
A53: FY2024-25 | B53: Isuzu | C53: =VLOOKUP(B53,Mapping!B:C,2,0) -> Lateral | D53: =VLOOKUP(B53,Mapping!B:D,3,0) -> South | E53: =VLOOKUP(B53,Mapping!B:E,4,0) -> South 1 | F53: =VLOOKUP(B53,Mapping!B:F,5,0) -> Sulabh | G53: =VLOOKUP(B53,Mapping!B:G,6,0) -> Satya | H53: 84854.882 | I53: 85761.733 | J53: 76263.503 | K53: 83317.177 | L53: 88767.591 | M53: 105978 | N53: 86080.56 | O53: 89109.529 | P53: 90384.632 | Q53: 90121.388 | R53: 89258.044 | S53: 101218.34
A54: FY2024-25 | B54: Ametek | C54: =VLOOKUP(B54,Mapping!B:C,2,0) -> Lateral | D54: =VLOOKUP(B54,Mapping!B:D,3,0) -> South | E54: =VLOOKUP(B54,Mapping!B:E,4,0) -> South 1 | F54: =VLOOKUP(B54,Mapping!B:F,5,0) -> Sulabh | G54: =VLOOKUP(B54,Mapping!B:G,6,0) -> Satya | H54: 118888.03 | I54: 120385.02 | J54: 123199.18 | K54: 102841.75 | L54: 85076.258 | M54: 94652.961 | N54: 78156.31 | O54: 80679.453 | P54: 91519.382 | Q54: 81899.138 | R54: 46622.794 | S54: 122551.84
A55: FY2024-25 | B55: Titan | C55: =VLOOKUP(B55,Mapping!B:C,2,0) -> Lateral | D55: =VLOOKUP(B55,Mapping!B:D,3,0) -> South | E55: =VLOOKUP(B55,Mapping!B:E,4,0) -> South 2 | F55: =VLOOKUP(B55,Mapping!B:F,5,0) -> Sulabh | G55: =VLOOKUP(B55,Mapping!B:G,6,0) -> Subu | H55: 64422.328 | I55: 75982.372 | J55: 73875.885 | K55: 69643.193 | L55: 79948.758 | M55: 81811.932 | N55: 75106.371 | O55: 80124.693 | P55: 78217.063 | Q55: 75785.695 | R55: 701435.79
A56: FY2024-25 | B56: ABFRL | C56: =VLOOKUP(B56,Mapping!B:C,2,0) -> Lateral | D56: =VLOOKUP(B56,Mapping!B:D,3,0) -> South | E56: =VLOOKUP(B56,Mapping!B:E,4,0) -> South 2 | F56: =VLOOKUP(B56,Mapping!B:F,5,0) -> Sulabh | G56: =VLOOKUP(B56,Mapping!B:G,6,0) -> Satya | H56: 63138 | I56: 62979 | J56: 60101 | K56: 69717 | L56: 71287
A57: FY2024-25 | B57: Common | C57: =VLOOKUP(B57,Mapping!B:C,2,0) -> Lateral | D57: =VLOOKUP(B57,Mapping!B:D,3,0) -> Common | E57: =VLOOKUP(B57,Mapping!B:E,4,0) -> North | F57: =VLOOKUP(B57,Mapping!B:F,5,0) -> Common | G57: =VLOOKUP(B57,Mapping!B:G,6,0) -> Common | H57: 52040.472 | I57: 13558.5 | J57: 2341.75 | K57: 23177.29 | L57: 64026.75 | M57: 4463.6364 | N57: 174792.75 | O57: 106936.75 | P57: 149894.95 | Q57: 229865.96 | R57: 65976.076 | S57: 24717.578
G62: Get calculation

Sheet Unbilled
A1: FY | B1: Project | C1: Vertical | D1: Region | E1: Sub Region | F1: Region Head | G1: Practice Head | H1: 45383 | I1: =EDATE(H1,1) -> 45413 | J1: =EDATE(I1,1) -> 45444 | K1: =EDATE(J1,1) -> 45474 | L1: =EDATE(K1,1) -> 45505 | M1: =EDATE(L1,1) -> 45536 | N1: =EDATE(M1,1) -> 45566 | O1: =EDATE(N1,1) -> 45597 | P1: =EDATE(O1,1) -> 45627 | ... S1: =EDATE(R1,1) -> 45717
A2: FY2024-25 | B2: Tata Motors | C2: =VLOOKUP(B2,Mapping!B:C,2,0) -> Lateral | D2: =VLOOKUP(B2,Mapping!B:D,3,0) -> West | E2: =VLOOKUP(B2,Mapping!B:E,4,0) -> West 2 | F2: =VLOOKUP(B2,Mapping!B:F,5,0) -> Anjli | G2: =VLOOKUP(B2,Mapping!B:G,6,0) -> Shweta | H2: 0 | I2: 0 | J2: 0 | K2: 0 | L2: 0 | M2: 0 | N2: 0 | O2: 0 | P2: 0 | Q2: 0 | R2: 0 | S2: =SUM(G2:R2) -> 0
A3: FY2024-25 | B3: Schaeffler | C3: =VLOOKUP(B3,Mapping!B:C,2,0) -> Lateral | D3: =VLOOKUP(B3,Mapping!B:D,3,0) -> West | E3: =VLOOKUP(B3,Mapping!B:E,4,0) -> West 2 | F3: =VLOOKUP(B3,Mapping!B:F,5,0) -> Anjli | G3: =VLOOKUP(B3,Mapping!B:G,6,0) -> Shweta | H3: 0 | I3: 0 | J3: 0 | K3: 0 | L3: 0 | M3: 0 | N3: 0 | O3: 0 | P3: 0 | Q3: 0 | R3: 0 | S3: =SUM(G3:R3) -> 0
A4: FY2024-25 | B4: Vertiv | C4: =VLOOKUP(B4,Mapping!B:C,2,0) -> Lateral | D4: =VLOOKUP(B4,Mapping!B:D,3,0) -> West | E4: =VLOOKUP(B4,Mapping!B:E,4,0) -> West 2 | F4: =VLOOKUP(B4,Mapping!B:F,5,0) -> Anjli | G4: =VLOOKUP(B4,Mapping!B:G,6,0) -> Shweta | H4: 0 | I4: 0 | J4: 0 | K4: 0 | L4: 0 | M4: 0 | N4: 0 | O4: 0 | P4: 0 | Q4: 0 | R4: 0 | S4: =SUM(G4:R4) -> 0
A5: FY2024-25 | B5: Tata Marcopolo | C5: =VLOOKUP(B5,Mapping!B:C,2,0) -> Lateral | D5: =VLOOKUP(B5,Mapping!B:D,3,0) -> West | E5: =VLOOKUP(B5,Mapping!B:E,4,0) -> West 2 | F5: =VLOOKUP(B5,Mapping!B:F,5,0) -> Anjli | G5: =VLOOKUP(B5,Mapping!B:G,6,0) -> Anjli | H5: 0 | I5: 0 | J5: 0 | K5: 0 | L5: 0 | M5: 0 | N5: 0 | O5: 0 | P5: 0 | Q5: 0 | R5: 0 | S5: =SUM(G5:R5) -> 0
A6: FY2024-25 | B6: ThyssenKrupp | C6: =VLOOKUP(B6,Mapping!B:C,2,0) -> Lateral | D6: =VLOOKUP(B6,Mapping!B:D,3,0) -> West | E6: =VLOOKUP(B6,Mapping!B:E,4,0) -> West 2 | F6: =VLOOKUP(B6,Mapping!B:F,5,0) -> Anjli | G6: =VLOOKUP(B6,Mapping!B:G,6,0) -> Shweta | H6: 0 | I6: 0 | J6: 0 | K6: 0 | L6: 0 | M6: 0 | N6: 0 | O6: 0 | P6: 0 | Q6: 0 | R6: 0 | S6: =SUM(G6:R6) -> 0
A7: FY2024-25 | B7: Ultratech | C7: =VLOOKUP(B7,Mapping!B:C,2,0) -> Lateral | D7: =VLOOKUP(B7,Mapping!B:D,3,0) -> West | E7: =VLOOKUP(B7,Mapping!B:E,4,0) -> West 1 | F7: =VLOOKUP(B7,Mapping!B:F,5,0) -> Anjli | G7: =VLOOKUP(B7,Mapping!B:G,6,0) -> Elton | H7: 0 | I7: 0 | J7: 0 | K7: 0 | L7: 0 | M7: 0 | N7: 0 | O7: 0 | P7: 0 | Q7: 0 | R7: 0 | S7: =SUM(G7:R7) -> 0
A8: FY2024-25 | B8: Tata Teleservices | C8: =VLOOKUP(B8,Mapping!B:C,2,0) -> Lateral | D8: =VLOOKUP(B8,Mapping!B:D,3,0) -> West | E8: =VLOOKUP(B8,Mapping!B:E,4,0) -> West 1 | F8: =VLOOKUP(B8,Mapping!B:F,5,0) -> Anjli | G8: =VLOOKUP(B8,Mapping!B:G,6,0) -> Elton | H8: 0 | I8: 0 | J8: 0 | K8: 0 | L8: 0 | M8: 0 | N8: 0 | O8: 0 | P8: 0 | Q8: 0 | R8: 0 | S8: =SUM(G8:R8) -> 0
A9: FY2024-25 | B9: Hyundai Motor | C9: =VLOOKUP(B9,Mapping!B:C,2,0) -> Lateral | D9: =VLOOKUP(B9,Mapping!B:D,3,0) -> West | E9: =VLOOKUP(B9,Mapping!B:E,4,0) -> West 2 | F9: =VLOOKUP(B9,Mapping!B:F,5,0) -> Anjli | G9: =VLOOKUP(B9,Mapping!B:G,6,0) -> Shweta | H9: 0 | I9: 0 | J9: 0 | K9: 0 | L9: 0 | M9: 0 | N9: 0 | O9: 0 | P9: 0 | Q9: 0 | R9: 0 | S9: =SUM(G9:R9) -> 0
A10: FY2024-25 | B10: Bridgestone | C10: =VLOOKUP(B10,Mapping!B:C,2,0) -> Lateral | D10: =VLOOKUP(B10,Mapping!B:D,3,0) -> West | E10: =VLOOKUP(B10,Mapping!B:E,4,0) -> West 2 | F10: =VLOOKUP(B10,Mapping!B:F,5,0) -> Anjli | G10: =VLOOKUP(B10,Mapping!B:G,6,0) -> Shweta | H10: 0 | I10: 0 | J10: 0 | K10: 0 | L10: 0 | M10: 0 | N10: 0 | O10: 0 | P10: 0 | Q10: 0 | R10: 0 | S10: =SUM(G10:R10) -> 0
A11: FY2024-25 | B11: SKF India | C11: =VLOOKUP(B11,Mapping!B:C,2,0) -> Lateral | D11: =VLOOKUP(B11,Mapping!B:D,3,0) -> North | E11: =VLOOKUP(B11,Mapping!B:E,4,0) -> North | F11: =VLOOKUP(B11,Mapping!B:F,5,0) -> Anjli | G11: =VLOOKUP(B11,Mapping!B:G,6,0) -> Archana | H11: 0 | I11: 0 | J11: 0 | K11: 0 | L11: 0 | M11: 0 | N11: 0 | O11: 0 | P11: 0 | Q11: 0 | R11: 0 | S11: =SUM(G11:R11) -> 0
A12: FY2024-25 | B12: Jindal Stainless | C12: =VLOOKUP(B12,Mapping!B:C,2,0) -> Lateral | D12: =VLOOKUP(B12,Mapping!B:D,3,0) -> North | E12: =VLOOKUP(B12,Mapping!B:E,4,0) -> North | F12: =VLOOKUP(B12,Mapping!B:F,5,0) -> Anjli | G12: =VLOOKUP(B12,Mapping!B:G,6,0) -> Archana | H12: 0 | I12: 0 | J12: 0 | K12: 0 | L12: 0 | M12: 0 | N12: 0 | O12: 0 | P12: 0 | Q12: 0 | R12: 0 | S12: =SUM(G12:R12) -> 0
A13: FY2024-25 | B13: Maruti Suzuki(MSIL) | C13: =VLOOKUP(B13,Mapping!B:C,2,0) -> Lateral | D13: =VLOOKUP(B13,Mapping!B:D,3,0) -> North | E13: =VLOOKUP(B13,Mapping!B:E,4,0) -> North | F13: =VLOOKUP(B13,Mapping!B:F,5,0) -> Anjli | G13: =VLOOKUP(B13,Mapping!B:G,6,0) -> Archana | H13: 0 | I13: 0 | J13: 0 | K13: 0 | L13: 0 | M13: 0 | N13: 0 | O13: 0 | P13: 0 | Q13: 0 | R13: 0 | S13: =SUM(G13:R13) -> 0
... A57: FY2024-25 | B57: Common | C57: =VLOOKUP(B57,Mapping!B:C,2,0) -> Lateral | D57: =VLOOKUP(B57,Mapping!B:D,3,0) -> Common | E57: =VLOOKUP(B57,Mapping!B:E,4,0) -> North | F57: =VLOOKUP(B57,Mapping!B:F,5,0) -> Common | G57: =VLOOKUP(B57,Mapping!B:G,6,0) -> Common | H57: 0 | I57: 0 | J57: 0 | K57: 0 | L57: 0 | M57: 0 | N57: 0 | O57: 0 | P57: 0 | Q57: 0 | R57: 0 | S57: =SUM(G57:R57) -> 0
G63: uninvoived money in lacs

Sheet Collection Target
A1: FY | B1: Project | C1: Vertical | D1: Region | E1: Sub Region | F1: Region Head | G1: Practice Head | H1: 45383 | I1: =EDATE(H1,1) -> 45413 | J1: =EDATE(I1,1) -> 45444 | K1: =EDATE(J1,1) -> 45474 | L1: =EDATE(K1,1) -> 45505 | M1: =EDATE(L1,1) -> 45536 | N1: =EDATE(M1,1) -> 45566 | O1: =EDATE(N1,1) -> 45597 | P1: =EDATE(O1,1) -> 45627 | ... S1: =EDATE(R1,1) -> 45717
A2: FY2024-25 | B2: Tata Motors | C2: =VLOOKUP(B2,Mapping!B:C,2,0) -> Lateral | D2: =VLOOKUP(B2,Mapping!B:D,3,0) -> West | E2: =VLOOKUP(B2,Mapping!B:E,4,0) -> West 2 | F2: =VLOOKUP(B2,Mapping!B:F,5,0) -> Anjli | G2: =VLOOKUP(B2,Mapping!B:G,6,0) -> Shweta | H2: 122.1236 | I2: 46.11734 | J2: 148.20386 | K2: 29.0864 | L2: 46.71206 | M2: 10.05277 | N2: 6.28054 | O2: 59.02512 | P2: 69.96254 | Q2: 31.71898 | R2: 10.25124 | S2: 33.93208
A3: FY2024-25 | B3: Schaeffler | C3: =VLOOKUP(B3,Mapping!B:C,2,0) -> Lateral | D3: =VLOOKUP(B3,Mapping!B:D,3,0) -> West | E3: =VLOOKUP(B3,Mapping!B:E,4,0) -> West 2 | F3: =VLOOKUP(B3,Mapping!B:F,5,0) -> Anjli | G3: =VLOOKUP(B3,Mapping!B:G,6,0) -> Shweta | H3: 1.77 | I3: 27.9475 | J3: 11.67447 | K3: 8.46857 | L3: 8.61435 | M3: 0 | N3: 10.13458 | O3: 22.37195 | P3: 21.73248 | Q3: 22.44402 | R3: 14.72104 | S3: 25.55509
A4: FY2024-25 | B4: Vertiv | C4: =VLOOKUP(B4,Mapping!B:C,2,0) -> Lateral | D4: =VLOOKUP(B4,Mapping!B:D,3,0) -> West | E4: =VLOOKUP(B4,Mapping!B:E,4,0) -> West 2 | F4: =VLOOKUP(B4,Mapping!B:F,5,0) -> Anjli | G4: =VLOOKUP(B4,Mapping!B:G,6,0) -> Shweta | H4: 19.43839 | I4: 12.87464 | J4: 21.26714 | K4: 17.00734 | L4: 10.79464 | M4: 23.76284 | N4: 17.5854 | O4: 21.9514 | P4: 23.9043 | Q4: 10.76854 | R4: 7.55894 | S4: 12.72359
A5: FY2024-25 | B5: Tata Marcopolo | C5: =VLOOKUP(B5,Mapping!B:C,2,0) -> Lateral | D5: =VLOOKUP(B5,Mapping!B:D,3,0) -> West | E5: =VLOOKUP(B5,Mapping!B:E,4,0) -> West 2 | F5: =VLOOKUP(B5,Mapping!B:F,5,0) -> Anjli | G5: =VLOOKUP(B5,Mapping!B:G,6,0) -> Anjli | H5: 0 | I5: 0 | J5: 1.8998 | K5: 3.2922 | L5: 1.8998 | M5: 4.425 | N5: 1.8998 | O5: 4.3778 | P5: 4.3778 | Q5: 4.5017 | R5: 7.8293 | S5: 7.8293
A6: FY2024-25 | B6: ThyssenKrupp | C6: =VLOOKUP(B6,Mapping!B:C,2,0) -> Lateral | D6: =VLOOKUP(B6,Mapping!B:D,3,0) -> West | E6: =VLOOKUP(B6,Mapping!B:E,4,0) -> West 2 | F6: =VLOOKUP(B6,Mapping!B:F,5,0) -> Anjli | G6: =VLOOKUP(B6,Mapping!B:G,6,0) -> Shweta | H6: 35.49084 | I6: 51.94358 | J6: 44.58322 | K6: 40.08617 | L6: 62.22416 | M6: 40.72157 | N6: 12.92083 | O6: 12.92083 | P6: 13.22034 | Q6: 13.22034 | R6: 21.62194 | S6: 10.725
A7: FY2024-25 | B7: Ultratech | C7: =VLOOKUP(B7,Mapping!B:C,2,0) -> Lateral | D7: =VLOOKUP(B7,Mapping!B:D,3,0) -> West | E7: =VLOOKUP(B7,Mapping!B:E,4,0) -> West 1 | F7: =VLOOKUP(B7,Mapping!B:F,5,0) -> Anjli | G7: =VLOOKUP(B7,Mapping!B:G,6,0) -> Elton | H7: 5.43921 | I7: 5.43921 | J7: 8.23463 | K7: 8.23463 | L7: 9.19042 | M7: 9.19042 | N7: 9.19043 | O7: 9.67895 | P7: 9.67895 | Q7: 9.67895 | R7: 9.67895 | S7: 9.67895
A8: FY2024-25 | B8: Tata Teleservices | C8: =VLOOKUP(B8,Mapping!B:C,2,0) -> Lateral | D8: =VLOOKUP(B8,Mapping!B:D,3,0) -> West | E8: =VLOOKUP(B8,Mapping!B:E,4,0) -> West 1 | F8: =VLOOKUP(B8,Mapping!B:F,5,0) -> Anjli | G8: =VLOOKUP(B8,Mapping!B:G,6,0) -> Elton | H8: 28.2846 | I8: 22.72444 | J8: 22.72444 | K8: 5.63878 | L8: 5.63878 | M8: 0 | N8: 0 | O8: 0 | P8: 0 | Q8: 0 | R8: 0 | S8: 0
A9: FY2024-25 | B9: Hyundai Motor | C9: =VLOOKUP(B9,Mapping!B:C,2,0) -> Lateral | D9: =VLOOKUP(B9,Mapping!B:D,3,0) -> West | E9: =VLOOKUP(B9,Mapping!B:E,4,0) -> West 2 | F9: =VLOOKUP(B9,Mapping!B:F,5,0) -> Anjli | G9: =VLOOKUP(B9,Mapping!B:G,6,0) -> Shweta | H9: 0 | I9: 0 | J9: 14.44792 | K9: 19.15848 | L9: 0 | M9: 25.6398 | N9: 25.34662 | O9: 32.07796 | P9: 0.01233 | Q9: 47.53681 | R9: 46.77425 | S9: 20.53988
A10: FY2024-25 | B10: Bridgestone | C10: =VLOOKUP(B10,Mapping!B:C,2,0) -> Lateral | D10: =VLOOKUP(B10,Mapping!B:D,3,0) -> West | E10: =VLOOKUP(B10,Mapping!B:E,4,0) -> West 2 | F10: =VLOOKUP(B10,Mapping!B:F,5,0) -> Anjli | G10: =VLOOKUP(B10,Mapping!B:G,6,0) -> Shweta | H10: 0 | I10: 0 | J10: 0 | K10: 0 | L10: 0 | M10: 0 | N10: 0 | O10: 0 | P10: 0 | Q10: 0 | R10: 0.708 | S10: 2.655
A11: FY2024-25 | B11: SKF India | C11: =VLOOKUP(B11,Mapping!B:C,2,0) -> Lateral | D11: =VLOOKUP(B11,Mapping!B:D,3,0) -> North | E11: =VLOOKUP(B11,Mapping!B:E,4,0) -> North | F11: =VLOOKUP(B11,Mapping!B:F,5,0) -> Anjli | G11: =VLOOKUP(B11,Mapping!B:G,6,0) -> Archana | H11: 0 | I11: 0 | J11: 64.34473 | K11: 31.34411 | L11: 0 | M11: 22.51554 | N11: 19.67948 | O11: 2.773 | P11: 2.773 | Q11: 15.12907 | R11: 38.70513 | S11: 25.7776
A12: FY2024-25 | B12: Jindal Stainless | C12: =VLOOKUP(B12,Mapping!B:C,2,0) -> Lateral | D12: =VLOOKUP(B12,Mapping!B:D,3,0) -> North | E12: =VLOOKUP(B12,Mapping!B:E,4,0) -> North | F12: =VLOOKUP(B12,Mapping!B:F,5,0) -> Anjli | G12: =VLOOKUP(B12,Mapping!B:G,6,0) -> Archana | H12: 31.63625 | I12: 23.52112 | J12: 39.74344 | K12: 37.45714 | L12: 28.14303 | M12: 9.83318 | N12: 8.89688 | O12: 58.43875 | P12: 61.34344 | Q12: 79.73386 | R12: 68.36684 | S12: 35.29805
A13: FY2024-25 | B13: Maruti Suzuki(MSIL) | C13: =VLOOKUP(B13,Mapping!B:C,2,0) -> Lateral | D13: =VLOOKUP(B13,Mapping!B:D,3,0) -> North | E13: =VLOOKUP(B13,Mapping!B:E,4,0) -> North | F13: =VLOOKUP(B13,Mapping!B:F,5,0) -> Anjli | G13: =VLOOKUP(B13,Mapping!B:G,6,0) -> Archana | H13: 0 | I13: 0 | J13: 0 | K13: 0 | L13: 0 | M13: 0 | N13: 0 | O13: 0 | P13: 0 | Q13: 51.85477 | R13: 50.1899 | S13: 0.14206
... A61: FY2024-25 | B61: Atul | C61: =VLOOKUP(B61,Mapping!B:C,2,0) -> Lateral | D61: =VLOOKUP(B61,Mapping!B:D,3,0) -> West | E61: =VLOOKUP(B61,Mapping!B:E,4,0) -> West 1 | F61: =VLOOKUP(B61,Mapping!B:F,5,0) -> Anjli | G61: =VLOOKUP(B61,Mapping!B:G,6,0) -> Anjli | H61: 3.86738 | I61: 3.86738 | J61: 3.86738 | K61: 3.86738 | L61: 3.86738 | M61: 3.86738 | N61: 3.86738 | O61: 0 | P61: 0 | Q61: 0 | R61: 0 | S61: 0
A62: FY2024-25 | B62: Atos | C62: =VLOOKUP(B62,Mapping!B:C,2,0) -> Lateral | D62: =VLOOKUP(B62,Mapping!B:D,3,0) -> West | E62: =VLOOKUP(B62,Mapping!B:E,4,0) -> West 1 | F62: =VLOOKUP(B62,Mapping!B:F,5,0) -> Anjli | G62: =VLOOKUP(B62,Mapping!B:G,6,0) -> Anjli | K62: 22.84126 | L62: 22.84126 | M62: 22.84126 | N62: 22.84126 | O62: 0 | P62: 17.21738 | Q62: 0 | R62: 0 | S62: 0
A63: FY2024-25 | B63: L&T (New) | C63: =VLOOKUP(B63,Mapping!B:C,2,0) -> Lateral | D63: =VLOOKUP(B63,Mapping!B:D,3,0) -> South | E63: =VLOOKUP(B63,Mapping!B:E,4,0) -> South 1 | F63: =VLOOKUP(B63,Mapping!B:F,5,0) -> Sulabh | G63: =VLOOKUP(B63,Mapping!B:G,6,0) -> Subu | K63: 0 | L63: 0 | M63: 0 | N63: 0 | O63: 0 | P63: 0 | Q63: 0 | R63: 0 | S63: 0
A64: FY2024-25 | B64: NCC | C64: =VLOOKUP(B64,Mapping!B:C,2,0) -> Lateral | D64: =VLOOKUP(B64,Mapping!B:D,3,0) -> North | E64: =VLOOKUP(B64,Mapping!B:E,4,0) -> North | F64: =VLOOKUP(B64,Mapping!B:F,5,0) -> Anjli | G64: =VLOOKUP(B64,Mapping!B:G,6,0) -> Anjli | L64: 5.31 | M64: 0 | N64: 0 | O64: 0 | P64: 0 | Q64: 0 | R64: 0 | S64: 0
A65: FY2024-25 | B65: Nagarjuna | C65: =VLOOKUP(B65,Mapping!B:C,2,0) -> Lateral | D65: =VLOOKUP(B65,Mapping!B:D,3,0) -> South | E65: =VLOOKUP(B65,Mapping!B:E,4,0) -> South 1 | F65: =VLOOKUP(B65,Mapping!B:F,5,0) -> Sulabh | G65: =VLOOKUP(B65,Mapping!B:G,6,0) -> Parul | M65: 4.17248 | N65: 0 | O65: 0 | P65: 0 | Q65: 0 | R65: 0 | S65: 0
A66: FY2024-25 | B66: Infocepts | C66: =VLOOKUP(B66,Mapping!B:C,2,0) -> Lateral | D66: =VLOOKUP(B66,Mapping!B:D,3,0) -> South | E66: =VLOOKUP(B66,Mapping!B:E,4,0) -> South 1 | F66: =VLOOKUP(B66,Mapping!B:F,5,0) -> Sulabh | G66: =VLOOKUP(B66,Mapping!B:G,6,0) -> Subu | N66: 0 | O66: 0 | P66: 0 | Q66: 0 | R66: 0 | S66: 0
A67: FY2024-25 | B67: Optum | C67: =VLOOKUP(B67,Mapping!B:C,2,0) -> Lateral | D67: =VLOOKUP(B67,Mapping!B:D,3,0) -> North | E67: =VLOOKUP(B67,Mapping!B:E,4,0) -> North | F67: =VLOOKUP(B67,Mapping!B:F,5,0) -> Ashish | G67: =VLOOKUP(B67,Mapping!B:G,6,0) -> Ashish | Q67: 0 | R67: 0 | S67: 0
A68: FY2024-25 | B68: Kale Logistics | C68: =VLOOKUP(B68,Mapping!B:C,2,0) -> Lateral | D68: =VLOOKUP(B68,Mapping!B:D,3,0) -> West | E68: =VLOOKUP(B68,Mapping!B:E,4,0) -> West 1 | F68: =VLOOKUP(B68,Mapping!B:F,5,0) -> Anjli | G68: =VLOOKUP(B68,Mapping!B:G,6,0) -> Anjli | S68: 0
F72: Static numbers from the finance team

Sheet Revenue_Collected
A1: FY | B1: Project | C1: Vertical | D1: Region | E1: Sub Region | F1: Region Head | G1: Practice Head | H1: 45383 | I1: =EDATE(H1,1) -> 45413 | J1: =EDATE(I1,1) -> 45444 | K1: =EDATE(J1,1) -> 45474 | L1: =EDATE(K1,1) -> 45505 | M1: =EDATE(L1,1) -> 45536 | N1: =EDATE(M1,1) -> 45566 | O1: =EDATE(N1,1) -> 45597 | P1: =EDATE(O1,1) -> 45627 | ... S1: =EDATE(R1,1) -> 45717
A2: FY2024-25 | B2: Tata Motors | C2: =VLOOKUP(B2,Mapping!B:C,2,0) -> Lateral | D2: =VLOOKUP(B2,Mapping!B:D,3,0) -> West | E2: =VLOOKUP(B2,Mapping!B:E,4,0) -> West 2 | F2: =VLOOKUP(B2,Mapping!B:F,5,0) -> Anjli | G2: =VLOOKUP(B2,Mapping!B:G,6,0) -> Shweta | H2: 103.06846 | I2: 90.11539 | J2: 75.93578 | K2: 0 | L2: 109.53426 | M2: 33.62468 | N2: 11.77865 | O2: 16.61626 | P2: 14.08257 | Q2: 88.53881 | R2: 10.82385 | S2: 0
A3: FY2024-25 | B3: Schaeffler | C3: =VLOOKUP(B3,Mapping!B:C,2,0) -> Lateral | D3: =VLOOKUP(B3,Mapping!B:D,3,0) -> West | E3: =VLOOKUP(B3,Mapping!B:E,4,0) -> West 2 | F3: =VLOOKUP(B3,Mapping!B:F,5,0) -> Anjli | G3: =VLOOKUP(B3,Mapping!B:G,6,0) -> Shweta | H3: 0 | I3: 27.53128 | J3: 11.64679 | K3: 8.38245 | L3: 8.52664 | M3: 0 | N3: 0 | O3: 10.03152 | P3: 0 | Q3: 12.11292 | R3: 0 | S3: 0
A4: FY2024-25 | B4: Vertiv | C4: =VLOOKUP(B4,Mapping!B:C,2,0) -> Lateral | D4: =VLOOKUP(B4,Mapping!B:D,3,0) -> West | E4: =VLOOKUP(B4,Mapping!B:E,4,0) -> West 2 | F4: =VLOOKUP(B4,Mapping!B:F,5,0) -> Anjli | G4: =VLOOKUP(B4,Mapping!B:G,6,0) -> Shweta | H4: 5.84325 | I4: 2.06865 | J4: 11.00256 | K4: 5.93352 | L4: 0 | M4: 14.38692 | N4: 0 | O4: 4.59608 | P4: 16.03664 | Q4: 6.52912 | R4: 2.4696 | S4: 1.305
A5: FY2024-25 | B5: Tata Marcopolo | C5: =VLOOKUP(B5,Mapping!B:C,2,0) -> Lateral | D5: =VLOOKUP(B5,Mapping!B:D,3,0) -> West | E5: =VLOOKUP(B5,Mapping!B:E,4,0) -> West 2 | F5: =VLOOKUP(B5,Mapping!B:F,5,0) -> Anjli | G5: =VLOOKUP(B5,Mapping!B:G,6,0) -> Anjli | H5: 1.6902 | I5: 0 | J5: 0.665 | K5: 1.3654 | L5: 0 | M5: 0 | N5: 0 | O5: 0 | P5: 0 | Q5: 0 | R5: 0 | S5: 7.16418
A6: FY2024-25 | B6: ThyssenKrupp | C6: =VLOOKUP(B6,Mapping!B:C,2,0) -> Lateral | D6: =VLOOKUP(B6,Mapping!B:D,3,0) -> West | E6: =VLOOKUP(B6,Mapping!B:E,4,0) -> West 2 | F6: =VLOOKUP(B6,Mapping!B:F,5,0) -> Anjli | G6: =VLOOKUP(B6,Mapping!B:G,6,0) -> Shweta | H6: 9.059 | I6: 38.171166 | J6: 27.26396 | K6: 1.86624 | L6: 44.29957 | M6: 24.7018 | N6: 26.67649 | O6: 24.57961 | P6: 7.93524 | Q6: 0 | R6: 10.29909 | S6: 0
A7: FY2024-25 | B7: Ultratech | C7: =VLOOKUP(B7,Mapping!B:C,2,0) -> Lateral | D7: =VLOOKUP(B7,Mapping!B:D,3,0) -> West | E7: =VLOOKUP(B7,Mapping!B:E,4,0) -> West 1 | F7: =VLOOKUP(B7,Mapping!B:F,5,0) -> Anjli | G7: =VLOOKUP(B7,Mapping!B:G,6,0) -> Elton | H7: 0 | I7: 1.07244 | J7: 0 | K7: 0.7614 | L7: 0 | M7: 0 | N7: 0 | O7: 0 | P7: 0 | Q7: 0 | R7: 0 | S7: 0.04374
A8: FY2024-25 | B8: Tata Teleservices | C8: =VLOOKUP(B8,Mapping!B:C,2,0) -> Lateral | D8: =VLOOKUP(B8,Mapping!B:D,3,0) -> West | E8: =VLOOKUP(B8,Mapping!B:E,4,0) -> West 1 | F8: =VLOOKUP(B8,Mapping!B:F,5,0) -> Anjli | G8: =VLOOKUP(B8,Mapping!B:G,6,0) -> Elton | H8: 0 | I8: 0 | J8: 17.085656 | K8: 0 | L8: 0 | M8: 0 | N8: 0 | O8: 0 | P8: 0 | Q8: 0 | R8: 0 | S8: 0
A9: FY2024-25 | B9: Hyundai Motor | C9: =VLOOKUP(B9,Mapping!B:C,2,0) -> Lateral | D9: =VLOOKUP(B9,Mapping!B:D,3,0) -> West | E9: =VLOOKUP(B9,Mapping!B:E,4,0) -> West 2 | F9: =VLOOKUP(B9,Mapping!B:F,5,0) -> Anjli | G9: =VLOOKUP(B9,Mapping!B:G,6,0) -> Shweta | H9: 0 | I9: 0 | J9: 13.22352 | K9: 17.53488 | L9: 0 | M9: 0 | N9: 9.51283 | O9: 60.395533 | P9: 0 | Q9: 0 | R9: 42.56197 | S9: 0
A10: FY2024-25 | B10: Bridgestone | C10: =VLOOKUP(B10,Mapping!B:C,2,0) -> Lateral | D10: =VLOOKUP(B10,Mapping!B:D,3,0) -> West | E10: =VLOOKUP(B10,Mapping!B:E,4,0) -> West 2 | F10: =VLOOKUP(B10,Mapping!B:F,5,0) -> Anjli | G10: =VLOOKUP(B10,Mapping!B:G,6,0) -> Shweta | H10: 0 | I10: 0 | J10: 0 | K10: 0 | L10: 0 | M10: 0 | N10: 0 | O10: 0 | P10: 0 | Q10: 0 | R10: 0 | S10: 0
A11: FY2024-25 | B11: SKF India | C11: =VLOOKUP(B11,Mapping!B:C,2,0) -> Lateral | D11: =VLOOKUP(B11,Mapping!B:D,3,0) -> North | E11: =VLOOKUP(B11,Mapping!B:E,4,0) -> North | F11: =VLOOKUP(B11,Mapping!B:F,5,0) -> Anjli | G11: =VLOOKUP(B11,Mapping!B:G,6,0) -> Archana | H11: 0 | I11: 0 | J11: 57.768364 | K11: 27.329475 | L11: 7.68901 | M11: 18.31276 | N11: 34.39893 | O11: 22.43852 | P11: 0 | Q11: 0 | R11: 35.566719 | S11: 38.131963
A12: FY2024-25 | B12: Jindal Stainless | C12: =VLOOKUP(B12,Mapping!B:C,2,0) -> Lateral | D12: =VLOOKUP(B12,Mapping!B:D,3,0) -> North | E12: =VLOOKUP(B12,Mapping!B:E,4,0) -> North | F12: =VLOOKUP(B12,Mapping!B:F,5,0) -> Anjli | G12: =VLOOKUP(B12,Mapping!B:G,6,0) -> Archana | H12: 3.23827 | I12: 3.34381 | J12: 24.64207 | K12: 16.49287 | L12: 32.52255 | M12: 0.32492 | N12: 3.81585 | O12: 1.7496 | P12: 0.54459 | Q12: 34.74136 | R12: 43.17629 | S12: 31.671212
A13: FY2024-25 | B13: Maruti Suzuki(MSIL) | C13: =VLOOKUP(B13,Mapping!B:C,2,0) -> Lateral | D13: =VLOOKUP(B13,Mapping!B:D,3,0) -> North | E13: =VLOOKUP(B13,Mapping!B:E,4,0) -> North | F13: =VLOOKUP(B13,Mapping!B:F,5,0) -> Anjli | G13: =VLOOKUP(B13,Mapping!B:G,6,0) -> Archana | H13: 0 | I13: 1.62 | J13: 0 | K13: 0 | L13: 0 | M13: 0 | N13: 0 | O13: 0 | P13: 14.37482 | Q13: 10.000201 | R13: 95.83654 | S13: 1.36528
... A61: FY2024-25 | B61: Atul | C61: =VLOOKUP(B61,Mapping!B:C,2,0) -> Lateral | D61: =VLOOKUP(B61,Mapping!B:D,3,0) -> West | E61: =VLOOKUP(B61,Mapping!B:E,4,0) -> West 1 | F61: =VLOOKUP(B61,Mapping!B:F,5,0) -> Anjli | G61: =VLOOKUP(B61,Mapping!B:G,6,0) -> Anjli | H61: 0 | I61: 0 | J61: 0 | K61: 0 | L61: 0 | M61: 0 | N61: 3.82805 | O61: 0 | P61: 0 | Q61: 0 | R61: 0 | S61: 0
A62: FY2024-25 | B62: NCC | C62: =VLOOKUP(B62,Mapping!B:C,2,0) -> Lateral | D62: =VLOOKUP(B62,Mapping!B:D,3,0) -> North | E62: =VLOOKUP(B62,Mapping!B:E,4,0) -> North | F62: =VLOOKUP(B62,Mapping!B:F,5,0) -> Anjli | G62: =VLOOKUP(B62,Mapping!B:G,6,0) -> Anjli | K62: 0 | L62: 4.86 | M62: 0 | N62: 0 | O62: 0 | P62: 0 | Q62: 0 | R62: 0 | S62: 0
A63: FY2024-25 | B63: Nagarjuna | C63: =VLOOKUP(B63,Mapping!B:C,2,0) -> Lateral | D63: =VLOOKUP(B63,Mapping!B:D,3,0) -> South | E63: =VLOOKUP(B63,Mapping!B:E,4,0) -> South 1 | F63: =VLOOKUP(B63,Mapping!B:F,5,0) -> Sulabh | G63: =VLOOKUP(B63,Mapping!B:G,6,0) -> Parul | M63: 3.81888 | N63: 0 | O63: 0 | P63: 0 | Q63: 0 | R63: 0 | S63: 0
A64: FY2024-25 | B64: Infocepts | C64: =VLOOKUP(B64,Mapping!B:C,2,0) -> Lateral | D64: =VLOOKUP(B64,Mapping!B:D,3,0) -> South | E64: =VLOOKUP(B64,Mapping!B:E,4,0) -> South 1 | F64: =VLOOKUP(B64,Mapping!B:F,5,0) -> Sulabh | G64: =VLOOKUP(B64,Mapping!B:G,6,0) -> Subu | N64: 0.72 | O64: 0 | P64: 0 | Q64: 0 | R64: 0 | S64: 0
A65: FY2024-25 | B65: Atos | C65: =VLOOKUP(B65,Mapping!B:C,2,0) -> Lateral | D65: =VLOOKUP(B65,Mapping!B:D,3,0) -> West | E65: =VLOOKUP(B65,Mapping!B:E,4,0) -> West 1 | F65: =VLOOKUP(B65,Mapping!B:F,5,0) -> Anjli | G65: =VLOOKUP(B65,Mapping!B:G,6,0) -> Anjli | P65: 16.92556 | Q65: 0 | R65: 0 | S65: 0
A66: FY2024-25 | B66: Optum | C66: =VLOOKUP(B66,Mapping!B:C,2,0) -> Lateral | D66: =VLOOKUP(B66,Mapping!B:D,3,0) -> North | E66: =VLOOKUP(B66,Mapping!B:E,4,0) -> North | F66: =VLOOKUP(B66,Mapping!B:F,5,0) -> Ashish | G66: =VLOOKUP(B66,Mapping!B:G,6,0) -> Ashish | Q66: 17.04236 | R66: 0 | S66: 45.276
A67: FY2024-25 | B67: Kale Logistics | C67: =VLOOKUP(B67,Mapping!B:C,2,0) -> Lateral | D67: =VLOOKUP(B67,Mapping!B:D,3,0) -> West | E67: =VLOOKUP(B67,Mapping!B:E,4,0) -> West 1 | F67: =VLOOKUP(B67,Mapping!B:F,5,0) -> Anjli | G67: =VLOOKUP(B67,Mapping!B:G,6,0) -> Anjli | S67: 1.728
E73: How much money has been collected

Sheet Bad Debt
A1: FY | B1: Project | C1: Vertical | D1: Region | E1: Sub Region | F1: Region Head | G1: Practice Head | H1: 45383 | I1: =EDATE(H1,1) -> 45413 | J1: =EDATE(I1,1) -> 45444 | K1: =EDATE(J1,1) -> 45474 | L1: =EDATE(K1,1) -> 45505 | M1: =EDATE(L1,1) -> 45536 | N1: =EDATE(M1,1) -> 45566 | O1: =EDATE(N1,1) -> 45597 | P1: =EDATE(O1,1) -> 45627 | ... S1: =EDATE(R1,1) -> 45717
A2: FY2024-25 | B2: Tata Motors | C2: =VLOOKUP(B2,Mapping!B:C,2,0) -> Lateral | D2: =VLOOKUP(B2,Mapping!B:D,3,0) -> West | E2: =VLOOKUP(B2,Mapping!B:E,4,0) -> West 2 | F2: =VLOOKUP(B2,Mapping!B:F,5,0) -> Anjli | G2: =VLOOKUP(B2,Mapping!B:G,6,0) -> Shweta | H2: 0 | I2: 0 | J2: 0 | K2: 0 | L2: 0 | M2: 0 | N2: 0 | O2: 0 | P2: 0 | Q2: 0 | R2: 0 | S2: 0
A3: FY2024-25 | B3: Schaeffler | C3: =VLOOKUP(B3,Mapping!B:C,2,0) -> Lateral | D3: =VLOOKUP(B3,Mapping!B:D,3,0) -> West | E3: =VLOOKUP(B3,Mapping!B:E,4,0) -> West 2 | F3: =VLOOKUP(B3,Mapping!B:F,5,0) -> Anjli | G3: =VLOOKUP(B3,Mapping!B:G,6,0) -> Shweta | H3: 0 | I3: 0 | J3: 0 | K3: 0 | L3: 0 | M3: 0 | N3: 0 | O3: 0 | P3: 0 | Q3: 0 | R3: 0 | S3: 0
A4: FY2024-25 | B4: Vertiv | C4: =VLOOKUP(B4,Mapping!B:C,2,0) -> Lateral | D4: =VLOOKUP(B4,Mapping!B:D,3,0) -> West | E4: =VLOOKUP(B4,Mapping!B:E,4,0) -> West 2 | F4: =VLOOKUP(B4,Mapping!B:F,5,0) -> Anjli | G4: =VLOOKUP(B4,Mapping!B:G,6,0) -> Shweta | H4: 0 | I4: 0 | J4: 0 | K4: 0 | L4: 0 | M4: 0 | N4: 0 | O4: 0 | P4: 0 | Q4: 0 | R4: 0 | S4: 0
A5: FY2024-25 | B5: Tata Marcopolo | C5: =VLOOKUP(B5,Mapping!B:C,2,0) -> Lateral | D5: =VLOOKUP(B5,Mapping!B:D,3,0) -> West | E5: =VLOOKUP(B5,Mapping!B:E,4,0) -> West 2 | F5: =VLOOKUP(B5,Mapping!B:F,5,0) -> Anjli | G5: =VLOOKUP(B5,Mapping!B:G,6,0) -> Anjli | H5: 0 | I5: 0 | J5: 0 | K5: 0 | L5: 0 | M5: 0 | N5: 0 | O5: 0 | P5: 0 | Q5: 0 | R5: 0 | S5: 0
A6: FY2024-25 | B6: ThyssenKrupp | C6: =VLOOKUP(B6,Mapping!B:C,2,0) -> Lateral | D6: =VLOOKUP(B6,Mapping!B:D,3,0) -> West | E6: =VLOOKUP(B6,Mapping!B:E,4,0) -> West 2 | F6: =VLOOKUP(B6,Mapping!B:F,5,0) -> Anjli | G6: =VLOOKUP(B6,Mapping!B:G,6,0) -> Shweta | H6: 0 | I6: 0 | J6: 0 | K6: 0 | L6: 0 | M6: 0 | N6: 0 | O6: 0 | P6: 0 | Q6: 0 | R6: 0 | S6: 0
A7: FY2024-25 | B7: Ultratech | C7: =VLOOKUP(B7,Mapping!B:C,2,0) -> Lateral | D7: =VLOOKUP(B7,Mapping!B:D,3,0) -> West | E7: =VLOOKUP(B7,Mapping!B:E,4,0) -> West 1 | F7: =VLOOKUP(B7,Mapping!B:F,5,0) -> Anjli | G7: =VLOOKUP(B7,Mapping!B:G,6,0) -> Elton | H7: 0 | I7: 0 | J7: 0 | K7: 0 | L7: 0 | M7: 0 | N7: 0 | O7: 0 | P7: 0 | Q7: 0 | R7: 0 | S7: 0
A8: FY2024-25 | B8: Tata Teleservices | C8: =VLOOKUP(B8,Mapping!B:C,2,0) -> Lateral | D8: =VLOOKUP(B8,Mapping!B:D,3,0) -> West | E8: =VLOOKUP(B8,Mapping!B:E,4,0) -> West 1 | F8: =VLOOKUP(B8,Mapping!B:F,5,0) -> Anjli | G8: =VLOOKUP(B8,Mapping!B:G,6,0) -> Elton | H8: 0 | I8: 0 | J8: 0 | K8: 0 | L8: 0 | M8: 0 | N8: 0 | O8: 0 | P8: 0 | Q8: 0 | R8: 0 | S8: 0
A9: FY2024-25 | B9: Hyundai Motor | C9: =VLOOKUP(B9,Mapping!B:C,2,0) -> Lateral | D9: =VLOOKUP(B9,Mapping!B:D,3,0) -> West | E9: =VLOOKUP(B9,Mapping!B:E,4,0) -> West 2 | F9: =VLOOKUP(B9,Mapping!B:F,5,0) -> Anjli | G9: =VLOOKUP(B9,Mapping!B:G,6,0) -> Shweta | H9: 0 | I9: 0 | J9: 0 | K9: 0 | L9: 0 | M9: 0 | N9: 0 | O9: 0 | P9: 0 | Q9: 0 | R9: 0 | S9: 0
A10: FY2024-25 | B10: Bridgestone | C10: =VLOOKUP(B10,Mapping!B:C,2,0) -> Lateral | D10: =VLOOKUP(B10,Mapping!B:D,3,0) -> West | E10: =VLOOKUP(B10,Mapping!B:E,4,0) -> West 2 | F10: =VLOOKUP(B10,Mapping!B:F,5,0) -> Anjli | G10: =VLOOKUP(B10,Mapping!B:G,6,0) -> Shweta | H10: 0 | I10: 0 | J10: 0 | K10: 0 | L10: 0 | M10: 0 | N10: 0 | O10: 0 | P10: 0 | Q10: 0 | R10: 0 | S10: 0
A11: FY2024-25 | B11: SKF India | C11: =VLOOKUP(B11,Mapping!B:C,2,0) -> Lateral | D11: =VLOOKUP(B11,Mapping!B:D,3,0) -> North | E11: =VLOOKUP(B11,Mapping!B:E,4,0) -> North | F11: =VLOOKUP(B11,Mapping!B:F,5,0) -> Anjli | G11: =VLOOKUP(B11,Mapping!B:G,6,0) -> Archana | H11: 0 | I11: 0 | J11: 0 | K11: 0 | L11: 0 | M11: 0 | N11: 0 | O11: 0 | P11: 0 | Q11: 0 | R11: 0 | S11: 0
A12: FY2024-25 | B12: Jindal Stainless | C12: =VLOOKUP(B12,Mapping!B:C,2,0) -> Lateral | D12: =VLOOKUP(B12,Mapping!B:D,3,0) -> North | E12: =VLOOKUP(B12,Mapping!B:E,4,0) -> North | F12: =VLOOKUP(B12,Mapping!B:F,5,0) -> Anjli | G12: =VLOOKUP(B12,Mapping!B:G,6,0) -> Archana | H12: 0 | I12: 0 | J12: 0 | K12: 0 | L12: 0 | M12: 0 | N12: 0 | O12: 0 | P12: 0 | Q12: 0 | R12: 0 | S12: 0
A13: FY2024-25 | B13: Maruti Suzuki(MSIL) | C13: =VLOOKUP(B13,Mapping!B:C,2,0) -> Lateral | D13: =VLOOKUP(B13,Mapping!B:D,3,0) -> North | E13: =VLOOKUP(B13,Mapping!B:E,4,0) -> North | F13: =VLOOKUP(B13,Mapping!B:F,5,0) -> Anjli | G13: =VLOOKUP(B13,Mapping!B:G,6,0) -> Archana | H13: 0 | I13: 0 | J13: 0 | K13: 0 | L13: 0 | M13: 0 | N13: 0 | O13: 0 | P13: 0 | Q13: 0 | R13: 0 | S13: 0
... A67: FY2024-25 | B67: Kale Logistics | C67: =VLOOKUP(B67,Mapping!B:C,2,0) -> Lateral | D67: =VLOOKUP(B67,Mapping!B:D,3,0) -> West | E67: =VLOOKUP(B67,Mapping!B:E,4,0) -> West 1 | F67: =VLOOKUP(B67,Mapping!B:F,5,0) -> Anjli | G67: =VLOOKUP(B67,Mapping!B:G,6,0) -> Anjli | H67: 0 | I67: 0 | J67: 0 | K67: 0 | L67: 0 | M67: 0 | N67: 0 | O67: 0 | P67: 0 | Q67: 0 | R67: 0 | S67: 0
F72: Money that customer is refusing to give money on different occasions; static numbers

Sheet Actual Cost
A1: FY | B1: Project | C1: Vertical | D1: Region | E1: Sub Region | F1: Region Head | G1: Practice Head | H1: 45383 | I1: =EDATE(H1,1) -> 45413 | J1: =EDATE(I1,1) -> 45444 | K1: =EDATE(J1,1) -> 45474 | L1: =EDATE(K1,1) -> 45505 | M1: =EDATE(L1,1) -> 45536 | O1: =EDATE(M1,1) -> 45566 | P1: =EDATE(O1,1) -> 45597 | Q1: =EDATE(P1,1) -> 45627 | R1: =EDATE(Q1,1) -> 45658 | S1: =EDATE(R1,1) -> 45689 | T1: =EDATE(S1,1) -> 45717
A2: FY2024-25 | B2: Tata Motors | C2: =VLOOKUP(B2,Mapping!B:C,2,0) -> Lateral | D2: =VLOOKUP(B2,Mapping!B:D,3,0) -> West | E2: =VLOOKUP(B2,Mapping!B:E,4,0) -> West 2 | F2: =VLOOKUP(B2,Mapping!B:F,5,0) -> Anjli | G2: =VLOOKUP(B2,Mapping!B:G,6,0) -> Shweta | H2: 4049845.2 | I2: 4359727 | J2: 3119168.4 | K2: 2398211.8 | L2: 2277986.2 | M2: 2651775 | N2: =M2+#REF! -> #REF! | O2: 2216764.6 | P2: 2065978.1 | Q2: 2077029.3 | R2: 1682990.3 | S2: 984910.64 | T2: 168514.82
A3: FY2024-25 | B3: Schaeffler | C3: =VLOOKUP(B3,Mapping!B:C,2,0) -> Lateral | D3: =VLOOKUP(B3,Mapping!B:D,3,0) -> West | E3: =VLOOKUP(B3,Mapping!B:E,4,0) -> West 2 | F3: =VLOOKUP(B3,Mapping!B:F,5,0) -> Anjli | G3: =VLOOKUP(B3,Mapping!B:G,6,0) -> Shweta | H3: 549382.42 | I3: 478228.12 | J3: 526279.74 | K3: 482307.93 | L3: 525335.06 | M3: 453276.83 | N3: =M3+#REF! -> #REF! | O3: 258855.91 | P3: 285808.06 | Q3: 279119.81 | R3: 296660.55 | S3: 375991.97 | T3: 627752
A4: FY2024-25 | B4: Vertiv | C4: =VLOOKUP(B4,Mapping!B:C,2,0) -> Lateral | D4: =VLOOKUP(B4,Mapping!B:D,3,0) -> West | E4: =VLOOKUP(B4,Mapping!B:E,4,0) -> West 2 | F4: =VLOOKUP(B4,Mapping!B:F,5,0) -> Anjli | G4: =VLOOKUP(B4,Mapping!B:G,6,0) -> Shweta | H4: 456970.16 | I4: 401722.12 | J4: 389519.5 | K4: 233492 | L4: 231729.03 | M4: 274976.84 | N4: =M4+#REF! -> #REF! | O4: 182820.24 | P4: 155954.25 | Q4: 162307.15 | R4: 157447.41 | S4: 324060.97 | T4: 343810.89
A5: FY2024-25 | B5: Tata Marcopolo | C5: =VLOOKUP(B5,Mapping!B:C,2,0) -> Lateral | D5: =VLOOKUP(B5,Mapping!B:D,3,0) -> West | E5: =VLOOKUP(B5,Mapping!B:E,4,0) -> West 2 | F5: =VLOOKUP(B5,Mapping!B:F,5,0) -> Anjli | G5: =VLOOKUP(B5,Mapping!B:G,6,0) -> Anjli | H5: 54061.025 | I5: 54732.019 | J5: 53026.788 | K5: 56096.749 | L5: 55761.258 | M5: 69827.297 | N5: =M5+#REF! -> #REF! | O5: 50175.31 | P5: 62316.998 | Q5: 1550 | R5: 0 | S5: 60034.794 | T5: 69638.845
A6: FY2024-25 | B6: ThyssenKrupp | C6: =VLOOKUP(B6,Mapping!B:C,2,0) -> Lateral | D6: =VLOOKUP(B6,Mapping!B:D,3,0) -> West | E6: =VLOOKUP(B6,Mapping!B:E,4,0) -> West 2 | F6: =VLOOKUP(B6,Mapping!B:F,5,0) -> Anjli | G6: =VLOOKUP(B6,Mapping!B:G,6,0) -> Shweta | H6: 1245326.3 | I6: 1245934.3 | J6: 1271324.4 | K6: 1273387.5 | L6: 1222062.3 | M6: 1501925.6 | N6: =M6+#REF! -> #REF! | O6: 986314.71 | P6: 324045.76 | Q6: 345737.53 | R6: 111349.7 | S6: 104998.06 | T6: 25095
A7: FY2024-25 | B7: Ultratech | C7: =VLOOKUP(B7,Mapping!B:C,2,0) -> Lateral | D7: =VLOOKUP(B7,Mapping!B:D,3,0) -> West | E7: =VLOOKUP(B7,Mapping!B:E,4,0) -> West 1 | F7: =VLOOKUP(B7,Mapping!B:F,5,0) -> Anjli | G7: =VLOOKUP(B7,Mapping!B:G,6,0) -> Elton | H7: 101191.04 | I7: 102196.03 | J7: 98809.683 | K7: 100937.62 | L7: 47666.693 | M7: 33048.96 | N7: =M7+#REF! -> #REF! | O7: 0 | P7: 0 | Q7: 0 | R7: 0 | S7: 0 | T7: 0
A8: FY2024-25 | B8: Tata Teleservices | C8: =VLOOKUP(B8,Mapping!B:C,2,0) -> Lateral | D8: =VLOOKUP(B8,Mapping!B:D,3,0) -> West | E8: =VLOOKUP(B8,Mapping!B:E,4,0) -> West 1 | F8: =VLOOKUP(B8,Mapping!B:F,5,0) -> Anjli | G8: =VLOOKUP(B8,Mapping!B:G,6,0) -> Elton | H8: 184226.04 | I8: 250597.06 | J8: 180145.69 | K8: 220886.25 | L8: 164176.52 | M8: 166507.84 | N8: =M8+#REF! -> #REF! | O8: 149558.62 | P8: 147090 | Q8: 158100.76 | R8: 157044.28 | S8: 55099.794 | T8: 0
A9: FY2024-25 | B9: Hyundai Motor | C9: =VLOOKUP(B9,Mapping!B:C,2,0) -> Lateral | D9: =VLOOKUP(B9,Mapping!B:D,3,0) -> West | E9: =VLOOKUP(B9,Mapping!B:E,4,0) -> West 2 | F9: =VLOOKUP(B9,Mapping!B:F,5,0) -> Anjli | G9: =VLOOKUP(B9,Mapping!B:G,6,0) -> Shweta | H9: 471189.15 | I9: 510927.12 | J9: 514981.5 | K9: 584415.68 | L9: 633646.75 | M9: 1144940.5 | N9: =M9+#REF! -> #REF! | O9: 678745.83 | P9: 1080258.6 | Q9: 941944.45 | R9: 1002118.4 | S9: 978532.48 | T9: 1394785.1
A10: FY2024-25 | B10: Bridgestone | C10: =VLOOKUP(B10,Mapping!B:C,2,0) -> Lateral | D10: =VLOOKUP(B10,Mapping!B:D,3,0) -> West | E10: =VLOOKUP(B10,Mapping!B:E,4,0) -> West 2 | F10: =VLOOKUP(B10,Mapping!B:F,5,0) -> Anjli | G10: =VLOOKUP(B10,Mapping!B:G,6,0) -> Shweta | H10: 0 | I10: 0 | J10: 0 | K10: 0 | L10: 0 | M10: 0 | N10: =M10+#REF! -> #REF! | O10: 0 | P10: 55725.159 | Q10: 0 | R10: 59646.138 | S10: 150642.59 | T10: 352510.13
A11: FY2024-25 | B11: SKF India | C11: =VLOOKUP(B11,Mapping!B:C,2,0) -> Lateral | D11: =VLOOKUP(B11,Mapping!B:D,3,0) -> North | E11: =VLOOKUP(B11,Mapping!B:E,4,0) -> North | F11: =VLOOKUP(B11,Mapping!B:F,5,0) -> Anjli | G11: =VLOOKUP(B11,Mapping!B:G,6,0) -> Archana | H11: 1450196.4 | I11: 1362223.3 | J11: 1408580.5 | K11: 1552878.7 | L11: 1495747.1 | M11: 1612641.2 | N11: =M11+#REF! -> #REF! | O11: 1340877.7 | P11: 1345524.5 | Q11: 1374848.4 | R11: 1365482.9 | S11: 1363663.1 | T11: 1499785.8
A12: FY2024-25 | B12: Jindal Stainless | C12: =VLOOKUP(B12,Mapping!B:C,2,0) -> Lateral | D12: =VLOOKUP(B12,Mapping!B:D,3,0) -> North | E12: =VLOOKUP(B12,Mapping!B:E,4,0) -> North | F12: =VLOOKUP(B12,Mapping!B:F,5,0) -> Anjli | G12: =VLOOKUP(B12,Mapping!B:G,6,0) -> Archana | H12: 1207368.9 | I12: 1122027.3 | J12: 1255767.7 | K12: 1168499.2 | L12: 1101269.7 | M12: 1312894.6 | N12: =M12+#REF! -> #REF! | O12: 1055269.6 | P12: 903645.52 | Q12: 879186.49 | R12: 812914.45 | S12: 741822.1 | T12: 281108.55
A13: FY2024-25 | B13: Maruti Suzuki(MSIL) | C13: =VLOOKUP(B13,Mapping!B:C,2,0) -> Lateral | D13: =VLOOKUP(B13,Mapping!B:D,3,0) -> North | E13: =VLOOKUP(B13,Mapping!B:E,4,0) -> North | F13: =VLOOKUP(B13,Mapping!B:F,5,0) -> Anjli | G13: =VLOOKUP(B13,Mapping!B:G,6,0) -> Archana | H13: 25619.01 | I13: 160595.04 | J13: 417524.62 | K13: 1242518.1 | L13: 1718972.5 | M13: 2354845.1 | N13: =M13+#REF! -> #REF! | O13: 2226835.9 | P13: 3344725.7 | Q13: 3362897.2 | R13: 3521795.2 | S13: 3636320.7 | T13: 5091759.9
... A57: FY2024-25 | B57: Common | C57: =VLOOKUP(B57,Mapping!B:C,2,0) -> Lateral | D57: =VLOOKUP(B57,Mapping!B:D,3,0) -> Common | E57: =VLOOKUP(B57,Mapping!B:E,4,0) -> North | F57: =VLOOKUP(B57,Mapping!B:F,5,0) -> Common | G57: =VLOOKUP(B57,Mapping!B:G,6,0) -> Common | H57: 660914 | I57: 244053 | J57: 56202 | K57: 247997 | L57: 768321 | M57: 49100 | N57: =M57+#REF! -> #REF! | O57: 2097513 | P57: 1251160 | Q57: 1663834 | R57: 2275673 | S57: 521211 | T57: 316385
G60: Actual cost on project in Rupees
