Workbook

Sheet Timelines
A1: Serial # | B1: Account Name | C1: PH Approval Date | D1: Reporting Date
A2: 1 | B2: Honeywell | C2: 45748 | D2: 45748
A3: 2 | B3: ISUZU (UD Trucks) | C3: Not Reported | D3: Not Reported
A4: 3 | B4: Siemens - GBS | C4: Not approved | D4: 45763
A5: 4 | B5: Siemens - Advanta | C5: Not approved | D5: 45763
A6: 5 | B6: Robert Bosch | C6: NA | D6: NA
A7: 6 | B7: Siemens - Energy | C7: Not approved | D7: 45763
A8: 7 | B8: HPE | C8: NA | D8: NA
A9: 8 | B9: Ametek | C9: NA | D9: NA
A10: 9 | B10: Titan | C10: NA | D10: NA
A11: 10 | B11: BITS | C11: NA | D11: 45745
A12: 11 | B12: P&G | C12: NA | D12: 45740
A13: 12 | B13: DP World | C13: Not Reported | D13: Not Reported
A14: 13 | B14: TATA Electronics | C14: Not approved | D14: 45749
A15: 14 | B15: Royal Enfield | C15: 45763 | D15: 45763
A16: 15 | B16: Ingram Micro | C16: 45757 | D16: 45757
A17: 16 | B17: Wipro | C17: Not approved | D17: 45755
A18: 17 | B18: NomiSo | C18: NA - Hiring on-hold | D18: NA - Hiring on-hold
A19: 18 | B19: SBI Card | C19: Not approved | D19: 45757
A20: 19 | B20: SKF | C20: Not approved | D20: 45757
A21: 20 | B21: Jindal | C21: Not approved | D21: 45756
A22: 21 | B22: Tata Motors | C22: Inactive Account | D22: Inactive Account
A23: 22 | B23: Vertiv Energy | C23: Not approved | D23: 45754
A24: 23 | B24: Thyssenkrupp | C24: Inactive Account | D24: Inactive Account
A25: 24 | B25: TATA Marco Polo | C25: Inactive Account | D25: Inactive Account
A26: 25 | B26: Schaeffler | C26: Not approved | D26: 45755
A27: 26 | B27: M&M | C27: 45763 | D27: 45757
A28: 27 | B28: Mahindra Holidays | C28: Not Reported | D28: Not Reported
A29: 28 | B29: Pidilite | C29: 45761 | D29: 45758
A30: 29 | B30: TATA Power | C30: NA - Project On-hold | D30: NA - Project On-hold
A31: 30 | B31: Birla Paints | C31: Not approved | D31: 45757
A32: 31 | B32: Fedex | C32: NA - Hiring on-hold | D32: NA - Hiring on-hold
A33: 32 | B33: AMNS | C33: Not approved | D33: 45763
A34: 33 | B34: TATA Tele | C34: NA - Project On-hold | D34: NA - Project On-hold
A35: 34 | B35: WTW | C35: NA - Project On-hold | D35: NA - Project On-hold
A36: 35 | B36: Pfizer | C36: Not approved | D36: 45758
A37: 36 | B37: Excelacom | C37: Moved to Enrichment Platform | D37: Moved to Enrichment Platform
A38: 37 | B38: Hyundai | C38: 45749 | D38: 45749
A39: 38 | B39: Maruti Suzuki | C39: Not Reported | D39: Not Reported
A40: 39 | B40: TATA Fiber | C40: NA - No Offer & Joiner | D40: NA - No Offer & Joiner
A41: 40 | B41: TATA Consumer | C41: 45759 | D41: 45758
A42: 41 | B42: Atomberg | C42: Not approved | D42: 45752
A43: 42 | B43: Subros | C43: Not approved | D43: 45756
A44: 43 | B44: Mahindra Finance | C44: 45754 | D44: 45754
A45: 44 | B45: Ashok Leyland | C45: NA | D45: NA
A46: 45 | B46: Sterling tools | C46: Not Reported | D46: Not Reported

Sheet RAG Logics
B2: RAG | C2: Reporting Status | D2: Validation Status | E2: MET %
C3: Not Reported | D3: Not Validated | E3: < 50%
C4: Not Applicable | D4: Partially Validated | E4: > = 50% - < 75%
C5: Reported | D5: Validated | E5: > = 75 %
B8: * MET% - %(Total MET Metrics / Total Metrics Reported) (([Excludes - NA & Not Reported]))
B9: ** Accounts : < = 6months of Go-Live will have no RAG, Only MET % will be reported
B10: *** All Metrics will have equal weightages for calculations (SLA or KPI)

Sheet Region Summary
F2: April 2024 | G2: April 2024 | H2: April 2024 | I2: April 2024 | J2: May 2024 | K2: May 2024 | L2: May 2024 | M2: May 2024 | N2: June 2024 | O2: June 2024 | P2: June 2024 | Q2: June 2024 | R2: AMJ 2024 | S2: AMJ 2024 | T2: AMJ 2024 | U2: AMJ 2024 | V2: July 2024 | W2: July 2024 | X2: July 2024 | Y2: July 2024 | Z2: August 2024 | AA2: August 2024 | AB2: August 2024 | AC2: August 2024 | AD2: September 2024 | AE2: September 2024 | AF2: September 2024 | AG2: September 2024 | AH2: JAS 2024 | AI2: JAS 2024 | AJ2: JAS 2024 | AK2: JAS 2024 | AL2: Oct 2024 | AM2: Oct 2024 | AN2: Oct 2024 | AO2: Oct 2024 | AP2: Nov 2024 | AQ2: Nov 2024 | AR2: Nov 2024 | AS2: Nov 2024 | AT2: Dec 2024 | AU2: Dec 2024 | AV2: Dec 2024 | AW2: Dec 2024 | AX2: OND 2024 | AY2: OND 2024 | AZ2: OND 2024 | BA2: OND 2024 | BB2: Jan 2025 | BC2: Jan 2025 | BD2: Jan 2025 | BE2: Jan 2025 | BF2: Feb 2025 | BG2: Feb 2025 | BH2: Feb 2025 | BI2: Feb 2025 | BJ2: Mar 2025 | BK2: Mar 2025 | BL2: Mar 2025 | BM2: Mar 2025 | BN2: JFM 2025 | BO2: JFM 2025 | BP2: JFM 2025 | BQ2: JFM 2025 | BR2: YTD 2024-2025 | BS2: YTD 2024-2025 | BT2: YTD 2024-2025 | BU2: YTD 2024-2025 | BV2: 45748 | BW2: 45748 | BX2: 45748 | BY2: 45748 | BZ2: June 2025 | CA2: June 2025 | CB2: June 2025 | CC2: June 2025 | CD2: AMJ-25 | CE2: AMJ-25 | CF2: AMJ-25 | CG2: AMJ-25 | CH2: July 2025 | CI2: July 2025 | CJ2: July 2025 | CK2: July 2025 | CL2: 45894 | CM2: 45894 | CN2: 45894 | CO2: 45894 | CP2: 45925 | CQ2: 45925 | CR2: 45925 | CS2: 45925 | CT2: Oct 2025 | CU2: Oct-2025 | CV2: Oct-2025 | CW2: Oct-2025 | CX2: Nov 2025 | CY2: Nov 2025 | CZ2: Nov 2025 | DA2: Nov 2025 | DB2: JAS-2025 | DC2: JAS-2025 | DD2: JAS-2025 | DE2: JAS-2025 | DF2: Dec 2025 | DG2: Dec 2025 | DH2: Dec 2025 | DI2: Dec 2025 | DJ2: OND 2025 | DK2: OND 2025 | DL2: OND 2025 | DM2: OND 2025 | DN2: Jan 2026 | DO2: Jan 2026 | DP2: Jan 2026 | DQ2: Jan 2026 | DR2: YTD 2025-2026 | DS2: YTD 2025-2026 | DT2: YTD 2025-2026 | DU2: YTD 2025-2026
A3: Serial # | B3: Region Name | C3: PH | D3: Reporting Status | E3: Audit Status | F3: Overall MET% | G3: Contractual Non- Penalty MET% | H3: Contractual Penalty MET% | I3: Internal KPI MET% | J3: Overall MET% | K3: Contractual Non- Penalty MET% | L3: Contractual Penalty MET% | M3: Internal KPI MET% | N3: Overall MET% | O3: Contractual Non- Penalty MET% | P3: Contractual Penalty MET% | Q3: Internal KPI MET% | R3: Overall MET% | S3: Contractual Non- Penalty MET% | T3: Contractual Penalty MET% | U3: Internal KPI MET% | V3: Overall MET% | W3: Contractual Non- Penalty MET% | X3: Contractual Penalty MET% | Y3: Internal KPI MET% | Z3: Overall MET% | AA3: Contractual Non- Penalty MET% | AB3: Contractual Penalty MET% | AC3: Internal KPI MET% | AD3: Overall MET% | AE3: Contractual Non- Penalty MET% | AF3: Contractual Penalty MET% | AG3: Internal KPI MET% | AH3: Overall MET% | AI3: Contractual Non- Penalty MET% | AJ3: Contractual Penalty MET% | AK3: Internal KPI MET% | AL3: Overall MET% | AM3: Contractual Non- Penalty MET% | AN3: Contractual Penalty MET% | AO3: Internal KPI MET% | AP3: Overall MET% | AQ3: Contractual Non- Penalty MET% | AR3: Contractual Penalty MET% | AS3: Internal KPI MET% | AT3: Overall MET% | AU3: Contractual Non- Penalty MET% | AV3: Contractual Penalty MET% | AW3: Internal KPI MET% | AX3: Overall MET% | AY3: Contractual Non- Penalty MET% | AZ3: Contractual Penalty MET% | BA3: Internal KPI MET% | BB3: Overall MET% | BC3: Contractual Non- Penalty MET% | BD3: Contractual Penalty MET% | BE3: Internal KPI MET% | BF3: Overall MET% | BG3: Contractual Non- Penalty MET% | BH3: Contractual Penalty MET% | BI3: Internal KPI MET% | BJ3: Overall MET% | BK3: Contractual Non- Penalty MET% | BL3: Contractual Penalty MET% | BM3: Internal KPI MET% | BN3: Overall MET% | BO3: Contractual Non- Penalty MET% | BP3: Contractual Penalty MET% | BQ3: Internal KPI MET% | BR3: Overall MET% | BS3: Contractual Non- Penalty MET% | BT3: Contractual Penalty MET% | BU3: Internal KPI MET% | BV3: Overall MET% | BW3: Contractual Non- Penalty MET% | BX3: Contractual Penalty MET% | BY3: Internal KPI MET% | BZ3: Overall MET% | CA3: Contractual Non- Penalty MET% | CB3: Contractual Penalty MET% | CC3: Internal KPI MET% | CD3: Overall MET% | CE3: Contractual Non- Penalty MET% | CF3: Contractual Penalty MET% | CG3: Internal KPI MET% | CH3: Overall MET% | CI3: Contractual Non- Penalty MET% | CJ3: Contractual Penalty MET% | CK3: Internal KPI MET% | CL3: Overall MET% | CM3: Contractual Non- Penalty MET% | CN3: Contractual Penalty MET% | CO3: Internal KPI MET% | CP3: Overall MET% | CQ3: Contractual Non- Penalty MET% | CR3: Contractual Penalty MET% | CS3: Internal KPI MET% | CT3: Overall MET% | CU3: Contractual Non- Penalty MET% | CV3: Contractual Penalty MET% | CW3: Internal KPI MET% | CX3: Overall MET% | CY3: Contractual Non- Penalty MET% | CZ3: Contractual Penalty MET% | DA3: Internal KPI MET% | DB3: Overall MET% | DC3: Contractual Non- Penalty MET% | DD3: Contractual Penalty MET% | DE3: Internal KPI MET% | DF3: Overall MET% | DG3: Contractual Non- Penalty MET% | DH3: Contractual Penalty MET% | DI3: Internal KPI MET% | DJ3: Overall MET% | DK3: Contractual Non- Penalty MET% | DL3: Contractual Penalty MET% | DM3: Internal KPI MET% | DN3: Overall MET% | DO3: Contractual Non- Penalty MET% | DP3: Contractual Penalty MET% | DQ3: Internal KPI MET% | DR3: Overall MET% | DS3: Contractual Non- Penalty MET% | DT3: Contractual Penalty MET% | DU3: Internal KPI MET%
A4: 1 | B4: Bangalore | C4: Sulabh | D4: Partially Reported | E4: Partially Validated | F4: 0.64 | G4: 0.96 | H4: 0.69 | I4: 0.38 | J4: =50/73 -> 0.68493151 | K4: =23/25 -> 0.92 | L4: =10/13 -> 0.76923077 | M4: =17/35 -> 0.48571429 | N4: =IFERROR(COUNTIFS('Base File'!$V:$V,"Met",'Base File'!$C:$C,B4)/(COUNTIFS('Base File'!$V:$V,"Met",'Base File'!$C:$C,B4)+COUNTIFS('Base File'!$V:$V,"Not Met",'Base File'!$C:$C,B4)),"NR") -> NR | O4: =IFERROR(COUNTIFS('Base File'!$G:$G,"Contractual SLA",'Base File'!$H:$H,"No",'Base File'!$C:$C,B4,'Base File'!$V:$V,"Met")/SUM(COUNTIFS('Base File'!$G:$G,"Contractual SLA",'Base File'!$H:$H,"No",'Base File'!$C:$C,B4,'Base File'!$V:$V,"Met")+COUNTIFS('Base File'!$G:$G,"Contractual SLA",'Base File'!$H:$H,"No",'Base File'!$C:$C,B4,'Base File'!$V:$V,"Not Met")),"-") -> - | P4: =IFERROR(COUNTIFS('Base File'!$G:$G,"Contractual SLA",'Base File'!$H:$H,"Yes",'Base File'!$C:$C,B4,'Base File'!$V:$V,"Met")/SUM(COUNTIFS('Base File'!$G:$G,"Contractual SLA",'Base File'!$H:$H,"yes",'Base File'!$C:$C,B4,'Base File'!$V:$V,"Met")+COUNTIFS('Base File'!$G:$G,"Contractual SLA",'Base File'!$H:$H,"yes",'Base File'!$C:$C,B4,'Base File'!$V:$V,"Not Met")),"-") -> - | Q4: =IFERROR(COUNTIFS('Base File'!$G:$G,"Internal KPI",'Base File'!$C:$C,B4,'Base File'!$V:$V,"Met")/SUM(COUNTIFS('Base File'!$G:$G,"Internal KPI",'Base File'!$C:$C,B4,'Base File'!$V:$V,"Met")+COUNTIFS('Base File'!$G:$G,"Internal KPI",'Base File'!$C:$C,B4,'Base File'!$V:$V,"Not Met")),"-") -> - | R4: =BR4 -> 0.75 | S4: =BS4 -> 0.9375 | T4: =BT4 -> NR | U4: =BU4 -> 0.625 | V4: =IFERROR(COUNTIFS('Base File'!$X:$X,"Met",'Base File'!$C:$C,B4)/(COUNTIFS('Base File'!$X:$X,"Met",'Base File'!$C:$C,B4)+COUNTIFS('Base File'!$X:$X,"Not Met",'Base File'!$C:$C,B4)),"NR") -> NR | W4: =IFERROR(COUNTIFS('Base File'!$G:$G,"Contractual SLA",'Base File'!$H:$H,"No",'Base File'!$C:$C,B4,'Base File'!$X:$X,"Met")/SUM(COUNTIFS('Base File'!$G:$G,"Contractual SLA",'Base File'!$H:$H,"No",'Base File'!$C:$C,B4,'Base File'!$X:$X,"Met")+COUNTIFS('Base File'!$G:$G,"Contractual SLA",'Base File'!$H:$H,"No",'Base File'!$C:$C,B4,'Base File'!$X:$X,"Not Met")),"-") -> - | X4: =IFERROR(COUNTIFS('Base File'!$G:$G,"Contractual SLA",'Base File'!$H:$H,"Yes",'Base File'!$C:$C,B4,'Base File'!$X:$X,"Met")/SUM(COUNTIFS('Base File'!$G:$G,"Contractual SLA",'Base File'!$H:$H,"yes",'Base File'!$C:$C,B4,'Base File'!$X:$X,"Met")+COUNTIFS('Base File'!$G:$G,"Contractual SLA",'Base File'!$H:$H,"yes",'Base File'!$C:$C,B4,'Base File'!$X:$X,"Not Met")),"-") -> - | Y4: =IFERROR(COUNTIFS('Base File'!$G:$G,"Internal KPI",'Base File'!$C:$C,B4,'Base File'!$X:$X,"Met")/SUM(COUNTIFS('Base File'!$G:$G,"Internal KPI",'Base File'!$C:$C,B4,'Base File'!$X:$X,"Met")+COUNTIFS('Base File'!$G:$G,"Internal KPI",'Base File'!$C:$C,B4,'Base File'!$X:$X,"Not Met")),"-") -> - | Z4: =IFERROR(COUNTIFS('Base File'!$Z:$Z,"Met",'Base File'!$C:$C,B4)/(COUNTIFS('Base File'!$Z:$Z,"Met",'Base File'!$C:$C,B4)+COUNTIFS('Base File'!$Z:$Z,"Not Met",'Base File'!$C:$C,B4)),"NR") -> NR | AA4: =IFERROR(COUNTIFS('Base File'!$G:$G,"Contractual SLA",'Base File'!$H:$H,"No",'Base File'!$C:$C,B4,'Base File'!$Z:$Z,"Met")/SUM(COUNTIFS('Base File'!$G:$G,"Contractual SLA",'Base File'!$H:$H,"No",'Base File'!$C:$C,B4,'Base File'!$Z:$Z,"Met")+COUNTIFS('Base File'!$G:$G,"Contractual SLA",'Base File'!$H:$H,"No",'Base File'!$C:$C,B4,'Base File'!$Z:$Z,"Not Met")),"-") -> - | AB4: =IFERROR(COUNTIFS('Base File'!$G:$G,"Contractual SLA",'Base File'!$H:$H,"Yes",'Base File'!$C:$C,B4,'Base File'!$Z:$Z,"Met")/SUM(COUNTIFS('Base File'!$G:$G,"Contractual SLA",'Base File'!$H:$H,"yes",'Base File'!$C:$C,B4,'Base File'!$Z:$Z,"Met")+COUNTIFS('Base File'!$G:$G,"Contractual SLA",'Base File'!$H:$H,"yes",'Base File'!$C:$C,B4,'Base File'!$Z:$Z,"Not Met")),"-") -> - | AC4: =IFERROR(COUNTIFS('Base File'!$G:$G,"Internal KPI",'Base File'!$C:$C,B4,'Base File'!$Z:$Z,"Met")/SUM(COUNTIFS('Base File'!$G:$G,"Internal KPI",'Base File'!$C:$C,B4,'Base File'!$Z:$Z,"Met")+COUNTIFS('Base File'!$G:$G,"Internal KPI",'Base File'!$C:$C,B4,'Base File'!$Z:$Z,"Not Met")),"-") -> - | AD4: =IFERROR(COUNTIFS('Base File'!$AB:$AB,"Met",'Base File'!$C:$C,B4)/(COUNTIFS('Base File'!$AB:$AB,"Met",'Base File'!$C:$C,B4)+COUNTIFS('Base File'!$AB:$AB,"Not Met",'Base File'!$C:$C,B4)),"NR") -> NR | AE4: =IFERROR(COUNTIFS('Base File'!$G:$G,"Contractual SLA",'Base File'!$H:$H,"No",'Base File'!$C:$C,B4,'Base File'!$AB:$AB,"Met")/SUM(COUNTIFS('Base File'!$G:$G,"Contractual SLA",'Base File'!$H:$H,"No",'Base File'!$C:$C,B4,'Base File'!$AB:$AB,"Met")+COUNTIFS('Base File'!$G:$G,"Contractual SLA",'Base File'!$H:$H,"No",'Base File'!$C:$C,B4,'Base File'!$AB:$AB,"Not Met")),"-") -> - | AF4: =IFERROR(COUNTIFS('Base File'!$G:$G,"Contractual SLA",'Base File'!$H:$H,"Yes",'Base File'!$C:$C,B4,'Base File'!$AB:$AB,"Met")/SUM(COUNTIFS('Base File'!$G:$G,"Contractual SLA",'Base File'!$H:$H,"yes",'Base File'!$C:$C,B4,'Base File'!$AB:$AB,"Met")+COUNTIFS('Base File'!$G:$G,"Contractual SLA",'Base File'!$H:$H,"yes",'Base File'!$C:$C,B4,'Base File'!$AB:$AB,"Not Met")),"-") -> - | AG4: =IFERROR(COUNTIFS('Base File'!$G:$G,"Internal KPI",'Base File'!$C:$C,B4,'Base File'!$AB:$AB,"Met")/SUM(COUNTIFS('Base File'!$G:$G,"Internal KPI",'Base File'!$C:$C,B4,'Base File'!$AB:$AB,"Met")+COUNTIFS('Base File'!$G:$G,"Internal KPI",'Base File'!$C:$C,B4,'Base File'!$AB:$AB,"Not Met")),"-") -> - | AH4: =IFERROR(COUNTIFS('Base File'!$AD:$AD,"Met",'Base File'!$C:$C,B4)/(COUNTIFS('Base File'!$AD:$AD,"Met",'Base File'!$C:$C,B4)+COUNTIFS('Base File'!$AD:$AD,"Not Met",'Base File'!$C:$C,B4)),"NR") -> NR | AI4: =IFERROR(COUNTIFS('Base File'!$G:$G,"Contractual SLA",'Base File'!$H:$H,"No",'Base File'!$C:$C,B4,'Base File'!$AD:$AD,"Met")/SUM(COUNTIFS('Base File'!$G:$G,"Contractual SLA",'Base File'!$H:$H,"No",'Base File'!$C:$C,B4,'Base File'!$AD:$AD,"Met")+COUNTIFS('Base File'!$G:$G,"Contractual SLA",'Base File'!$H:$H,"No",'Base File'!$C:$C,B4,'Base File'!$AD:$AD,"Not Met")),"-") -> - | AJ4: =IFERROR(COUNTIFS('Base File'!$G:$G,"Contractual SLA",'Base File'!$H:$H,"Yes",'Base File'!$C:$C,B4,'Base File'!$AD:$AD,"Met")/SUM(COUNTIFS('Base File'!$G:$G,"Contractual SLA",'Base File'!$H:$H,"yes",'Base File'!$C:$C,B4,'Base File'!$AD:$AD,"Met")+COUNTIFS('Base File'!$G:$G,"Contractual SLA",'Base File'!$H:$H,"yes",'Base File'!$C:$C,B4,'Base File'!$AD:$AD,"Not Met")),"-") -> - | AK4: =IFERROR(COUNTIFS('Base File'!$G:$G,"Internal KPI",'Base File'!$C:$C,B4,'Base File'!$AD:$AD,"Met")/SUM(COUNTIFS('Base File'!$G:$G,"Internal KPI",'Base File'!$C:$C,B4,'Base File'!$AD:$AD,"Met")+COUNTIFS('Base File'!$G:$G,"Internal KPI",'Base File'!$C:$C,B4,'Base File'!$AD:$AD,"Not Met")),"-") -> - | AL4: =25/33 -> 0.75757576 | AM4: =15/15 -> 1 | AN4: NR | AO4: =10/18 -> 0.55555556 | AP4: =23/33 -> 0.6969697 | AQ4: =13/15 -> 0.86666667 | AR4: NR | AS4: =10/18 -> 0.55555556 | AT4: =24/33 -> 0.72727273 | AU4: =14/15 -> 0.93333333 | AV4: NR | AW4: =10/18 -> 0.55555556 | AX4: NR | AY4: NR | AZ4: NR | BA4: NR | BB4: =25/33 -> 0.75757576 | BC4: =14/15 -> 0.93333333 | BD4: NR | BE4: =11/18 -> 0.61111111 | BF4: =27/40 -> 0.675 | BG4: =12/16 -> 0.75 | BH4: NR | BI4: =15/24 -> 0.625 | BJ4: =27/40 -> 0.675 | BK4: =12/16 -> 0.75 | BL4: NR | BM4: =15/24 -> 0.625 | BN4: =28/40 -> 0.7 | BO4: =14/16 -> 0.875 | BP4: NR | BQ4: =14/24 -> 0.58333333 | BR4: =30/40 -> 0.75 | BS4: =15/16 -> 0.9375 | BT4: NR | BU4: =15/24 -> 0.625 | BV4: =32/40 -> 0.8 | BW4: =14/16 -> 0.875 | BX4: NR | BY4: =18/24 -> 0.75 | BZ4: =33/41 -> 0.80487805 | CA4: =14/16 -> 0.875 | CB4: NR | CC4: =19/25 -> 0.76 | CD4: =33/41 -> 0.80487805 | CE4: =15/16 -> 0.9375 | CF4: NR | CG4: =18/25 -> 0.72 | CH4: =28/40 -> 0.7 | CI4: =10/15 -> 0.66666667 | CJ4: NR | CK4: =18/25 -> 0.72 | CL4: =28/40 -> 0.7 | CM4: =13/15 -> 0.86666667 | CN4: NR | CO4: =15/25 -> 0.6 | CP4: =6/7 -> 0.85714286 | CQ4: NR | CR4: NR | CS4: =6/7 -> 0.85714286 | CT4: =31/40 -> 0.775 | CU4: =14/15 -> 0.93333333 | CV4: NR | CW4: =17/25 -> 0.68 | DF4: =6/7 -> 0.85714286 | DG4: NR | DH4: NR | DI4: =6/7 -> 0.85714286 | DJ4: =6/7 -> 0.85714286 | DK4: NR | DL4: NR | DM4: =6/7 -> 0.85714286 | DN4: =34/48 -> 0.70833333 | DO4: =15/15 -> 1 | DP4: =0/2 -> 0 | DQ4: =19/31 -> 0.61290323 | DR4: =37/48 -> 0.77083333 | DS4: =14/15 -> 0.93333333 | DT4: =1/2 -> 0.5 | DU4: =22/31 -> 0.70967742
A5: 2 | B5: Chennai | C5: Krishna | D5: Partially Reported | E5: Partially Validated | F5: =8/8 -> 1 | G5: NR | H5: NA | I5: NR | J5: =11/13 -> 0.84615385 | K5: =8/8 -> 1 | L5: NA | M5: =3/5 -> 0.6 | N5: =IFERROR(COUNTIFS('Base File'!$V:$V,"Met",'Base File'!$C:$C,B5)/(COUNTIFS('Base File'!$V:$V,"Met",'Base File'!$C:$C,B5)+COUNTIFS('Base File'!$V:$V,"Not Met",'Base File'!$C:$C,B5)),"NR") -> NR | O5: =IFERROR(COUNTIFS('Base File'!$G:$G,"Contractual SLA",'Base File'!$H:$H,"No",'Base File'!$C:$C,B5,'Base File'!$V:$V,"Met")/SUM(COUNTIFS('Base File'!$G:$G,"Contractual SLA",'Base File'!$H:$H,"No",'Base File'!$C:$C,B5,'Base File'!$V:$V,"Met")+COUNTIFS('Base File'!$G:$G,"Contractual SLA",'Base File'!$H:$H,"No",'Base File'!$C:$C,B5,'Base File'!$V:$V,"Not Met")),"-") -> - | P5: =IFERROR(COUNTIFS('Base File'!$G:$G,"Contractual SLA",'Base File'!$H:$H,"Yes",'Base File'!$C:$C,B5,'Base File'!$V:$V,"Met")/SUM(COUNTIFS('Base File'!$G:$G,"Contractual SLA",'Base File'!$H:$H,"yes",'Base File'!$C:$C,B5,'Base File'!$V:$V,"Met")+COUNTIFS('Base File'!$G:$G,"Contractual SLA",'Base File'!$H:$H,"yes",'Base File'!$C:$C,B5,'Base File'!$V:$V,"Not Met")),"-") -> - | Q5: =IFERROR(COUNTIFS('Base File'!$G:$G,"Internal KPI",'Base File'!$C:$C,B5,'Base File'!$V:$V,"Met")/SUM(COUNTIFS('Base File'!$G:$G,"Internal KPI",'Base File'!$C:$C,B5,'Base File'!$V:$V,"Met")+COUNTIFS('Base File'!$G:$G,"Internal KPI",'Base File'!$C:$C,B5,'Base File'!$V:$V,"Not Met")),"-") -> - | R5: =BR5 -> 0.57894737 | S5: =BS5 -> 1 | T5: =BT5 -> NA | U5: =BU5 -> 0 | V5: =IFERROR(COUNTIFS('Base File'!$X:$X,"Met",'Base File'!$C:$C,B5)/(COUNTIFS('Base File'!$X:$X,"Met",'Base File'!$C:$C,B5)+COUNTIFS('Base File'!$X:$X,"Not Met",'Base File'!$C:$C,B5)),"NR") -> NR | W5: =IFERROR(COUNTIFS('Base File'!$G:$G,"Contractual SLA",'Base File'!$H:$H,"No",'Base File'!$C:$C,B5,'Base File'!$X:$X,"Met")/SUM(COUNTIFS('Base File'!$G:$G,"Contractual SLA",'Base File'!$H:$H,"No",'Base File'!$C:$C,B5,'Base File'!$X:$X,"Met")+COUNTIFS('Base File'!$G:$G,"Contractual SLA",'Base File'!$H:$H,"No",'Base File'!$C:$C,B5,'Base File'!$X:$X,"Not Met")),"-") -> - | X5: =IFERROR(COUNTIFS('Base File'!$G:$G,"Contractual SLA",'Base File'!$H:$H,"Yes",'Base File'!$C:$C,B5,'Base File'!$X:$X,"Met")/SUM(COUNTIFS('Base File'!$G:$G,"Contractual SLA",'Base File'!$H:$H,"yes",'Base File'!$C:$C,B5,'Base File'!$X:$X,"Met")+COUNTIFS('Base File'!$G:$G,"Contractual SLA",'Base File'!$H:$H,"yes",'Base File'!$C:$C,B5,'Base File'!$X:$X,"Not Met")),"-") -> - | Y5: =IFERROR(COUNTIFS('Base File'!$G:$G,"Internal KPI",'Base File'!$C:$C,B5,'Base File'!$X:$X,"Met")/SUM(COUNTIFS('Base File'!$G:$G,"Internal KPI",'Base File'!$C:$C,B5,'Base File'!$X:$X,"Met")+COUNTIFS('Base File'!$G:$G,"Internal KPI",'Base File'!$C:$C,B5,'Base File'!$X:$X,"Not Met")),"-") -> - | Z5: =IFERROR(COUNTIFS('Base File'!$Z:$Z,"Met",'Base File'!$C:$C,B5)/(COUNTIFS('Base File'!$Z:$Z,"Met",'Base File'!$C:$C,B5)+COUNTIFS('Base File'!$Z:$Z,"Not Met",'Base File'!$C:$C,B5)),"NR") -> NR | AA5: =IFERROR(COUNTIFS('Base File'!$G:$G,"Contractual SLA",'Base File'!$H:$H,"No",'Base File'!$C:$C,B5,'Base File'!$Z:$Z,"Met")/SUM(COUNTIFS('Base File'!$G:$G,"Contractual SLA",'Base File'!$H:$H,"No",'Base File'!$C:$C,B5,'Base File'!$Z:$Z,"Met")+COUNTIFS('Base File'!$G:$G,"Contractual SLA",'Base File'!$H:$H,"No",'Base File'!$C:$C,B5,'Base File'!$Z:$Z,"Not Met")),"-") -> - | AB5: =IFERROR(COUNTIFS('Base File'!$G:$G,"Contractual SLA",'Base File'!$H:$H,"Yes",'Base File'!$C:$C,B5,'Base File'!$Z:$Z,"Met")/SUM(COUNTIFS('Base File'!$G:$G,"Contractual SLA",'Base File'!$H:$H,"yes",'Base File'!$C:$C,B5,'Base File'!$Z:$Z,"Met")+COUNTIFS('Base File'!$G:$G,"Contractual SLA",'Base File'!$H:$H,"yes",'Base File'!$C:$C,B5,'Base File'!$Z:$Z,"Not Met")),"-") -> - | AC5: =IFERROR(COUNTIFS('Base File'!$G:$G,"Internal KPI",'Base File'!$C:$C,B5,'Base File'!$Z:$Z,"Met")/SUM(COUNTIFS('Base File'!$G:$G,"Internal KPI",'Base File'!$C:$C,B5,'Base File'!$Z:$Z,"Met")+COUNTIFS('Base File'!$G:$G,"Internal KPI",'Base File'!$C:$C,B5,'Base File'!$Z:$Z,"Not Met")),"-") -> - | AD5: =IFERROR(COUNTIFS('Base File'!$AB:$AB,"Met",'Base File'!$C:$C,B5)/(COUNTIFS('Base File'!$AB:$AB,"Met",'Base File'!$C:$C,B5)+COUNTIFS('Base File'!$AB:$AB,"Not Met",'Base File'!$C:$C,B5)),"NR") -> NR | AE5: =IFERROR(COUNTIFS('Base File'!$G:$G,"Contractual SLA",'Base File'!$H:$H,"No",'Base File'!$C:$C,B5,'Base File'!$AB:$AB,"Met")/SUM(COUNTIFS('Base File'!$G:$G,"Contractual SLA",'Base File'!$H:$H,"No",'Base File'!$C:$C,B5,'Base File'!$AB:$AB,"Met")+COUNTIFS('Base File'!$G:$G,"Contractual SLA",'Base File'!$H:$H,"No",'Base File'!$C:$C,B5,'Base File'!$AB:$AB,"Not Met")),"-") -> - | AF5: =IFERROR(COUNTIFS('Base File'!$G:$G,"Contractual SLA",'Base File'!$H:$H,"Yes",'Base File'!$C:$C,B5,'Base File'!$AB:$AB,"Met")/SUM(COUNTIFS('Base File'!$G:$G,"Contractual SLA",'Base File'!$H:$H,"yes",'Base File'!$C:$C,B5,'Base File'!$AB:$AB,"Met")+COUNTIFS('Base File'!$G:$G,"Contractual SLA",'Base File'!$H:$H,"yes",'Base File'!$C:$C,B5,'Base File'!$AB:$AB,"Not Met")),"-") -> - | AG5: =IFERROR(COUNTIFS('Base File'!$G:$G,"Internal KPI",'Base File'!$C:$C,B5,'Base File'!$AB:$AB,"Met")/SUM(COUNTIFS('Base File'!$G:$G,"Internal KPI",'Base File'!$C:$C,B5,'Base File'!$AB:$AB,"Met")+COUNTIFS('Base File'!$G:$G,"Internal KPI",'Base File'!$C:$C,B5,'Base File'!$AB:$AB,"Not Met")),"-") -> - | AH5: =IFERROR(COUNTIFS('Base File'!$AD:$AD,"Met",'Base File'!$C:$C,B5)/(COUNTIFS('Base File'!$AD:$AD,"Met",'Base File'!$C:$C,B5)+COUNTIFS('Base File'!$AD:$AD,"Not Met",'Base File'!$C:$C,B5)),"NR") -> NR | AI5: =IFERROR(COUNTIFS('Base File'!$G:$G,"Contractual SLA",'Base File'!$H:$H,"No",'Base File'!$C:$C,B5,'Base File'!$AD:$AD,"Met")/SUM(COUNTIFS('Base File'!$G:$G,"Contractual SLA",'Base File'!$H:$H,"No",'Base File'!$C:$C,B5,'Base File'!$AD:$AD,"Met")+COUNTIFS('Base File'!$G:$G,"Contractual SLA",'Base File'!$H:$H,"No",'Base File'!$C:$C,B5,'Base File'!$AD:$AD,"Not Met")),"-") -> - | AJ5: =IFERROR(COUNTIFS('Base File'!$G:$G,"Contractual SLA",'Base File'!$H:$H,"Yes",'Base File'!$C:$C,B5,'Base File'!$AD:$AD,"Met")/SUM(COUNTIFS('Base File'!$G:$G,"Contractual SLA",'Base File'!$H:$H,"yes",'Base File'!$C:$C,B5,'Base File'!$AD:$AD,"Met")+COUNTIFS('Base File'!$G:$G,"Contractual SLA",'Base File'!$H:$H,"yes",'Base File'!$C:$C,B5,'Base File'!$AD:$AD,"Not Met")),"-") -> - | AK5: =IFERROR(COUNTIFS('Base File'!$G:$G,"Internal KPI",'Base File'!$C:$C,B5,'Base File'!$AD:$AD,"Met")/SUM(COUNTIFS('Base File'!$G:$G,"Internal KPI",'Base File'!$C:$C,B5,'Base File'!$AD:$AD,"Met")+COUNTIFS('Base File'!$G:$G,"Internal KPI",'Base File'!$C:$C,B5,'Base File'!$AD:$AD,"Not Met")),"-") -> - | AL5: =IFERROR(COUNTIFS('Base File'!$AF:$AF,"Met",'Base File'!$C:$C,B5)/(COUNTIFS('Base File'!$AF:$AF,"Met",'Base File'!$C:$C,B5)+COUNTIFS('Base File'!$AF:$AF,"Not Met",'Base File'!$C:$C,B5)),"NR") -> NR | AM5: =IFERROR(COUNTIFS('Base File'!$G:$G,"Contractual SLA",'Base File'!$H:$H,"No",'Base File'!$C:$C,B5,'Base File'!$AF:$AF,"Met")/SUM(COUNTIFS('Base File'!$G:$G,"Contractual SLA",'Base File'!$H:$H,"No",'Base File'!$C:$C,B5,'Base File'!$AF:$AF,"Met")+COUNTIFS('Base File'!$G:$G,"Contractual SLA",'Base File'!$H:$H,"No",'Base File'!$C:$C,B5,'Base File'!$AF:$AF,"Not Met")),"-") -> - | AN5: =IFERROR(COUNTIFS('Base File'!$G:$G,"Contractual SLA",'Base File'!$H:$H,"Yes",'Base File'!$C:$C,B5,'Base File'!$AF:$AF,"Met")/SUM(COUNTIFS('Base File'!$G:$G,"Contractual SLA",'Base File'!$H:$H,"yes",'Base File'!$C:$C,B5,'Base File'!$AF:$AF,"Met")+COUNTIFS('Base File'!$G:$G,"Contractual SLA",'Base File'!$H:$H,"yes",'Base File'!$C:$C,B5,'Base File'!$AF:$AF,"Not Met")),"-") -> - | AO5: =IFERROR(COUNTIFS('Base File'!$G:$G,"Internal KPI",'Base File'!$C:$C,B5,'Base File'!$AF:$AF,"Met")/SUM(COUNTIFS('Base File'!$G:$G,"Internal KPI",'Base File'!$C:$C,B5,'Base File'!$AF:$AF,"Met")+COUNTIFS('Base File'!$G:$G,"Internal KPI",'Base File'!$C:$C,B5,'Base File'!$AF:$AF,"Not Met")),"-") -> - | AP5: =IFERROR(COUNTIFS('Base File'!$AH:$AH,"Met",'Base File'!$C:$C,B5)/(COUNTIFS('Base File'!$AH:$AH,"Met",'Base File'!$C:$C,B5)+COUNTIFS('Base File'!$AH:$AH,"Not Met",'Base File'!$C:$C,B5)),"NR") -> NR | AQ5: =IFERROR(COUNTIFS('Base File'!$G:$G,"Contractual SLA",'Base File'!$H:$H,"No",'Base File'!$C:$C,B5,'Base File'!$AH:$AH,"Met")/SUM(COUNTIFS('Base File'!$G:$G,"Contractual SLA",'Base File'!$H:$H,"No",'Base File'!$C:$C,B5,'Base File'!$AH:$AH,"Met")+COUNTIFS('Base File'!$G:$G,"Contractual SLA",'Base File'!$H:$H,"No",'Base File'!$C:$C,B5,'Base File'!$AH:$AH,"Not Met")),"-") -> - | AR5: =IFERROR(COUNTIFS('Base File'!$G:$G,"Contractual SLA",'Base File'!$H:$H,"Yes",'Base File'!$C:$C,B5,'Base File'!$AH:$AH,"Met")/SUM(COUNTIFS('Base File'!$G:$G,"Contractual SLA",'Base File'!$H:$H,"yes",'Base File'!$C:$C,B5,'Base File'!$AH:$AH,"Met")+COUNTIFS('Base File'!$G:$G,"Contractual SLA",'Base File'!$H:$H,"yes",'Base File'!$C:$C,B5,'Base File'!$AH:$AH,"Not Met")),"-") -> - | AS5: =IFERROR(COUNTIFS('Base File'!$G:$G,"Internal KPI",'Base File'!$C:$C,B5,'Base File'!$AH:$AH,"Met")/SUM(COUNTIFS('Base File'!$G:$G,"Internal KPI",'Base File'!$C:$C,B5,'Base File'!$AH:$AH,"Met")+COUNTIFS('Base File'!$G:$G,"Internal KPI",'Base File'!$C:$C,B5,'Base File'!$AH:$AH,"Not Met")),"-") -> - | AT5: =22/33 -> 0.66666667 | AU5: =10/11 -> 0.90909091 | AV5: =7/7 -> 1 | AW5: =5/15 -> 0.33333333 | AX5: =17/23 -> 0.73913043 | AY5: =8/8 -> 1 | AZ5: =7/7 -> 1 | BA5: =2/8 -> 0.25 | BB5: =20/26 -> 0.76923077 | BC5: =10/11 -> 0.90909091 | BD5: =7/7 -> 1 | BE5: =3/8 -> 0.375 | BF5: =21/27 -> 0.77777778 | BG5: =11/11 -> 1 | BH5: =7/7 -> 1 | BI5: =3/9 -> 0.33333333 | BJ5: =14/19 -> 0.73684211 | BK5: 1 | BL5: NA | BM5: =3/8 -> 0.375 | BN5: =12/19 -> 0.63157895 | BO5: 1 | BP5: NA | BQ5: =1/8 -> 0.125 | BR5: =11/19 -> 0.57894737 | BS5: =11/11 -> 1 | BT5: NA | BU5: =0/8 -> 0 | BV5: =9/14 -> 0.64285714 | BW5: =8/8 -> 1 | BX5: NA | BY5: =1/6 -> 0.16666667 | BZ5: =14/20 -> 0.7 | CA5: =14/20 -> 0.7 | CB5: NA | CC5: =3/9 -> 0.33333333 | CD5: =15/21 -> 0.71428571 | CE5: =15/21 -> 0.71428571 | CF5: NA | CG5: =3/9 -> 0.33333333 | CH5: =8/16 -> 0.5 | CI5: =8/8 -> 1 | CJ5: NA | CK5: =0/8 -> 0 | CL5: =11/16 -> 0.6875 | CM5: =8/8 -> 1 | CN5: NA | CO5: =3/8 -> 0.375 | CP5: =8/8 -> 1 | CQ5: =8/8 -> 1 | CR5: NR | CS5: NR | CT5: =8/8 -> 1 | CU5: =8/8 -> 1 | CV5: NR | CW5: NR | DF5: =7/10 -> 0.7 | DG5: =7/8 -> 0.875 | DH5: NR | DI5: =0/2 -> 0 | DJ5: NR | DK5: NR | DL5: NR | DM5: NR | DN5: =5/12 -> 0.41666667 | DO5: =5/10 -> 0.5 | DP5: NR | DQ5: =0/2 -> 0 | DR5: =4/4 -> 1 | DS5: =4/4 -> 1 | DT5: NR | DU5: NR
A6: 3 | B6: North | C6: Archana | D6: Reported | E6: Validated | F6: =13/20 -> 0.65 | G6: =5/8 -> 0.625 | H6: NA | I6: =8/12 -> 0.66666667 | J6: =13/20 -> 0.65 | K6: =3/8 -> 0.375 | L6: NA | M6: =10/12 -> 0.83333333 | N6: =IFERROR(COUNTIFS('Base File'!$V:$V,"Met",'Base File'!$C:$C,B6)/(COUNTIFS('Base File'!$V:$V,"Met",'Base File'!$C:$C,B6)+COUNTIFS('Base File'!$V:$V,"Not Met",'Base File'!$C:$C,B6)),"NR") -> 0.5862069 | O6: =IFERROR(COUNTIFS('Base File'!$G:$G,"Contractual SLA",'Base File'!$H:$H,"No",'Base File'!$C:$C,B6,'Base File'!$V:$V,"Met")/SUM(COUNTIFS('Base File'!$G:$G,"Contractual SLA",'Base File'!$H:$H,"No",'Base File'!$C:$C,B6,'Base File'!$V:$V,"Met")+COUNTIFS('Base File'!$G:$G,"Contractual SLA",'Base File'!$H:$H,"No",'Base File'!$C:$C,B6,'Base File'!$V:$V,"Not Met")),"-") -> - | P6: =IFERROR(COUNTIFS('Base File'!$G:$G,"Contractual SLA",'Base File'!$H:$H,"Yes",'Base File'!$C:$C,B6,'Base File'!$V:$V,"Met")/SUM(COUNTIFS('Base File'!$G:$G,"Contractual SLA",'Base File'!$H:$H,"yes",'Base File'!$C:$C,B6,'Base File'!$V:$V,"Met")+COUNTIFS('Base File'!$G:$G,"Contractual SLA",'Base File'!$H:$H,"yes",'Base File'!$C:$C,B6,'Base File'!$V:$V,"Not Met")),"-") -> 0.7 | Q6: =IFERROR(COUNTIFS('Base File'!$G:$G,"Internal KPI",'Base File'!$C:$C,B6,'Base File'!$V:$V,"Met")/SUM(COUNTIFS('Base File'!$G:$G,"Internal KPI",'Base File'!$C:$C,B6,'Base File'!$V:$V,"Met")+COUNTIFS('Base File'!$G:$G,"Internal KPI",'Base File'!$C:$C,B6,'Base File'!$V:$V,"Not Met")),"-") -> 0.52631579 | R6: =BR6 -> 0.6 | S6: =BS6 -> - | T6: =BT6 -> 0.73333333 | U6: =BU6 -> 0.46666667 | V6: =IFERROR(COUNTIFS('Base File'!$X:$X,"Met",'Base File'!$C:$C,B6)/(COUNTIFS('Base File'!$X:$X,"Met",'Base File'!$C:$C,B6)+COUNTIFS('Base File'!$X:$X,"Not Met",'Base File'!$C:$C,B6)),"NR") -> 0.5862069 | W6: =IFERROR(COUNTIFS('Base File'!$G:$G,"Contractual SLA",'Base File'!$H:$H,"No",'Base File'!$C:$C,B6,'Base File'!$X:$X,"Met")/SUM(COUNTIFS('Base File'!$G:$G,"Contractual SLA",'Base File'!$H:$H,"No",'Base File'!$C:$C,B6,'Base File'!$X:$X,"Met")+COUNTIFS('Base File'!$G:$G,"Contractual SLA",'Base File'!$H:$H,"No",'Base File'!$C:$C,B6,'Base File'!$X:$X,"Not Met")),"-") -> - | X6: =IFERROR(COUNTIFS('Base File'!$G:$G,"Contractual SLA",'Base File'!$H:$H,"Yes",'Base File'!$C:$C,B6,'Base File'!$X:$X,"Met")/SUM(COUNTIFS('Base File'!$G:$G,"Contractual SLA",'Base File'!$H:$H,"yes",'Base File'!$C:$C,B6,'Base File'!$X:$X,"Met")+COUNTIFS('Base File'!$G:$G,"Contractual SLA",'Base File'!$H:$H,"yes",'Base File'!$C:$C,B6,'Base File'!$X:$X,"Not Met")),"-") -> 0.5 | Y6: =IFERROR(COUNTIFS('Base File'!$G:$G,"Internal KPI",'Base File'!$C:$C,B6,'Base File'!$X:$X,"Met")/SUM(COUNTIFS('Base File'!$G:$G,"Internal KPI",'Base File'!$C:$C,B6,'Base File'!$X:$X,"Met")+COUNTIFS('Base File'!$G:$G,"Internal KPI",'Base File'!$C:$C,B6,'Base File'!$X:$X,"Not Met")),"-") -> 0.63157895 | Z6: =IFERROR(COUNTIFS('Base File'!$Z:$Z,"Met",'Base File'!$C:$C,B6)/(COUNTIFS('Base File'!$Z:$Z,"Met",'Base File'!$C:$C,B6)+COUNTIFS('Base File'!$Z:$Z,"Not Met",'Base File'!$C:$C,B6)),"NR") -> 0.70967742 | AA6: =IFERROR(COUNTIFS('Base File'!$G:$G,"Contractual SLA",'Base File'!$H:$H,"No",'Base File'!$C:$C,B6,'Base File'!$Z:$Z,"Met")/SUM(COUNTIFS('Base File'!$G:$G,"Contractual SLA",'Base File'!$H:$H,"No",'Base File'!$C:$C,B6,'Base File'!$Z:$Z,"Met")+COUNTIFS('Base File'!$G:$G,"Contractual SLA",'Base File'!$H:$H,"No",'Base File'!$C:$C,B6,'Base File'!$Z:$Z,"Not Met")),"-") -> - | AB6: =IFERROR(COUNTIFS('Base File'!$G:$G,"Contractual SLA",'Base File'!$H:$H,"Yes",'Base File'!$C:$C,B6,'Base File'!$Z:$Z,"Met")/SUM(COUNTIFS('Base File'!$G:$G,"Contractual SLA",'Base File'!$H:$H,"yes",'Base File'!$C:$C,B6,'Base File'!$Z:$Z,"Met")+COUNTIFS('Base File'!$G:$G,"Contractual SLA",'Base File'!$H:$H,"yes",'Base File'!$C:$C,B6,'Base File'!$Z:$Z,"Not Met")),"-") -> 0.66666667 | AC6: =IFERROR(COUNTIFS('Base File'!$G:$G,"Internal KPI",'Base File'!$C:$C,B6,'Base File'!$Z:$Z,"Met")/SUM(COUNTIFS('Base File'!$G:$G,"Internal KPI",'Base File'!$C:$C,B6,'Base File'!$Z:$Z,"Met")+COUNTIFS('Base File'!$G:$G,"Internal KPI",'Base File'!$C:$C,B6,'Base File'!$Z:$Z,"Not Met")),"-") -> 0.75 | AD6: =IFERROR(COUNTIFS('Base File'!$AB:$AB,"Met",'Base File'!$C:$C,B6)/(COUNTIFS('Base File'!$AB:$AB,"Met",'Base File'!$C:$C,B6)+COUNTIFS('Base File'!$AB:$AB,"Not Met",'Base File'!$C:$C,B6)),"NR") -> 0.78787879 | AE6: =IFERROR(COUNTIFS('Base File'!$G:$G,"Contractual SLA",'Base File'!$H:$H,"No",'Base File'!$C:$C,B6,'Base File'!$AB:$AB,"Met")/SUM(COUNTIFS('Base File'!$G:$G,"Contractual SLA",'Base File'!$H:$H,"No",'Base File'!$C:$C,B6,'Base File'!$AB:$AB,"Met")+COUNTIFS('Base File'!$G:$G,"Contractual SLA",'Base File'!$H:$H,"No",'Base File'!$C:$C,B6,'Base File'!$AB:$AB,"Not Met")),"-") -> - | AF6: =IFERROR(COUNTIFS('Base File'!$G:$G,"Contractual SLA",'Base File'!$H:$H,"Yes",'Base File'!$C:$C,B6,'Base File'!$AB:$AB,"Met")/SUM(COUNTIFS('Base File'!$G:$G,"Contractual SLA",'Base File'!$H:$H,"yes",'Base File'!$C:$C,B6,'Base File'!$AB:$AB,"Met")+COUNTIFS('Base File'!$G:$G,"Contractual SLA",'Base File'!$H:$H,"yes",'Base File'!$C:$C,B6,'Base File'!$AB:$AB,"Not Met")),"-") -> 0.73333333 | AG6: =IFERROR(COUNTIFS('Base File'!$G:$G,"Internal KPI",'Base File'!$C:$C,B6,'Base File'!$AB:$AB,"Met")/SUM(COUNTIFS('Base File'!$G:$G,"Internal KPI",'Base File'!$C:$C,B6,'Base File'!$AB:$AB,"Met")+COUNTIFS('Base File'!$G:$G,"Internal KPI",'Base File'!$C:$C,B6,'Base File'!$AB:$AB,"Not Met")),"-") -> 0.83333333 | AH6: =IFERROR(COUNTIFS('Base File'!$AD:$AD,"Met",'Base File'!$C:$C,B6)/(COUNTIFS('Base File'!$AD:$AD,"Met",'Base File'!$C:$C,B6)+COUNTIFS('Base File'!$AD:$AD,"Not Met",'Base File'!$C:$C,B6)),"NR") -> 0.66666667 | AI6: =IFERROR(COUNTIFS('Base File'!$G:$G,"Contractual SLA",'Base File'!$H:$H,"No",'Base File'!$C:$C,B6,'Base File'!$AD:$AD,"Met")/SUM(COUNTIFS('Base File'!$G:$G,"Contractual SLA",'Base File'!$H:$H,"No",'Base File'!$C:$C,B6,'Base File'!$AD:$AD,"Met")+COUNTIFS('Base File'!$G:$G,"Contractual SLA",'Base File'!$H:$H,"No",'Base File'!$C:$C,B6,'Base File'!$AD:$AD,"Not Met")),"-") -> - | AJ6: =IFERROR(COUNTIFS('Base File'!$G:$G,"Contractual SLA",'Base File'!$H:$H,"Yes",'Base File'!$C:$C,B6,'Base File'!$AD:$AD,"Met")/SUM(COUNTIFS('Base File'!$G:$G,"Contractual SLA",'Base File'!$H:$H,"yes",'Base File'!$C:$C,B6,'Base File'!$AD:$AD,"Met")+COUNTIFS('Base File'!$G:$G,"Contractual SLA",'Base File'!$H:$H,"yes",'Base File'!$C:$C,B6,'Base File'!$AD:$AD,"Not Met")),"-") -> 0.66666667 | AK6: =IFERROR(COUNTIFS('Base File'!$G:$G,"Internal KPI",'Base File'!$C:$C,B6,'Base File'!$AD:$AD,"Met")/SUM(COUNTIFS('Base File'!$G:$G,"Internal KPI",'Base File'!$C:$C,B6,'Base File'!$AD:$AD,"Met")+COUNTIFS('Base File'!$G:$G,"Internal KPI",'Base File'!$C:$C,B6,'Base File'!$AD:$AD,"Not Met")),"-") -> 0.66666667 | AL6: =IFERROR(COUNTIFS('Base File'!$AF:$AF,"Met",'Base File'!$C:$C,B6)/(COUNTIFS('Base File'!$AF:$AF,"Met",'Base File'!$C:$C,B6)+COUNTIFS('Base File'!$AF:$AF,"Not Met",'Base File'!$C:$C,B6)),"NR") -> 0.59375 | AM6: =IFERROR(COUNTIFS('Base File'!$G:$G,"Contractual SLA",'Base File'!$H:$H,"No",'Base File'!$C:$C,B6,'Base File'!$AF:$AF,"Met")/SUM(COUNTIFS('Base File'!$G:$G,"Contractual SLA",'Base File'!$H:$H,"No",'Base File'!$C:$C,B6,'Base File'!$AF:$AF,"Met")+COUNTIFS('Base File'!$G:$G,"Contractual SLA",'Base File'!$H:$H,"No",'Base File'!$C:$C,B6,'Base File'!$AF:$AF,"Not Met")),"-") -> - | AN6: =IFERROR(COUNTIFS('Base File'!$G:$G,"Contractual SLA",'Base File'!$H:$H,"Yes",'Base File'!$C:$C,B6,'Base File'!$AF:$AF,"Met")/SUM(COUNTIFS('Base File'!$G:$G,"Contractual SLA",'Base File'!$H:$H,"yes",'Base File'!$C:$C,B6,'Base File'!$AF:$AF,"Met")+COUNTIFS('Base File'!$G:$G,"Contractual SLA",'Base File'!$H:$H,"yes",'Base File'!$C:$C,B6,'Base File'!$AF:$AF,"Not Met")),"-") -> 0.73333333 | AO6: =IFERROR(COUNTIFS('Base File'!$G:$G,"Internal KPI",'Base File'!$C:$C,B6,'Base File'!$AF:$AF,"Met")/SUM(COUNTIFS('Base File'!$G:$G,"Internal KPI",'Base File'!$C:$C,B6,'Base File'!$AF:$AF,"Met")+COUNTIFS('Base File'!$G:$G,"Internal KPI",'Base File'!$C:$C,B6,'Base File'!$AF:$AF,"Not Met")),"-") -> 0.47058824 | AP6: =IFERROR(COUNTIFS('Base File'!$AH:$AH,"Met",'Base File'!$C:$C,B6)/(COUNTIFS('Base File'!$AH:$AH,"Met",'Base File'!$C:$C,B6)+COUNTIFS('Base File'!$AH:$AH,"Not Met",'Base File'!$C:$C,B6)),"NR") -> 0.70967742 | AQ6: =IFERROR(COUNTIFS('Base File'!$G:$G,"Contractual SLA",'Base File'!$H:$H,"No",'Base File'!$C:$C,B6,'Base File'!$AH:$AH,"Met")/SUM(COUNTIFS('Base File'!$G:$G,"Contractual SLA",'Base File'!$H:$H,"No",'Base File'!$C:$C,B6,'Base File'!$AH:$AH,"Met")+COUNTIFS('Base File'!$G:$G,"Contractual SLA",'Base File'!$H:$H,"No",'Base File'!$C:$C,B6,'Base File'!$AH:$AH,"Not Met")),"-") -> - | AR6: =IFERROR(COUNTIFS('Base File'!$G:$G,"Contractual SLA",'Base File'!$H:$H,"Yes",'Base File'!$C:$C,B6,'Base File'!$AH:$AH,"Met")/SUM(COUNTIFS('Base File'!$G:$G,"Contractual SLA",'Base File'!$H:$H,"yes",'Base File'!$C:$C,B6,'Base File'!$AH:$AH,"Met")+COUNTIFS('Base File'!$G:$G,"Contractual SLA",'Base File'!$H:$H,"yes",'Base File'!$C:$C,B6,'Base File'!$AH:$AH,"Not Met")),"-") -> 0.6 | AS6: =IFERROR(COUNTIFS('Base File'!$G:$G,"Internal KPI",'Base File'!$C:$C,B6,'Base File'!$AH:$AH,"Met")/SUM(COUNTIFS('Base File'!$G:$G,"Internal KPI",'Base File'!$C:$C,B6,'Base File'!$AH:$AH,"Met")+COUNTIFS('Base File'!$G:$G,"Internal KPI",'Base File'!$C:$C,B6,'Base File'!$AH:$AH,"Not Met")),"-") -> 0.8125 | AT6: =18/25 -> 0.72 | AU6: =3/4 -> 0.75 | AV6: =7/10 -> 0.7 | AW6: =8/11 -> 0.72727273 | AX6: =8/13 -> 0.61538462 | AY6: NR | AZ6: =6/10 -> 0.6 | BA6: =2/3 -> 0.66666667 | BB6: =17/24 -> 0.70833333 | BC6: - | BD6: =8/13 -> 0.61538462 | BE6: =9/11 -> 0.81818182 | BF6: =17/25 -> 0.68 | BG6: - | BH6: =11/15 -> 0.73333333 | BI6: =6/10 -> 0.6 | BJ6: =20/29 -> 0.68965517 | BK6: - | BL6: =11/14 -> 0.78571429 | BM6: =9/15 -> 0.6 | BN6: =17/29 -> 0.5862069 | BO6: - | BP6: =9/14 -> 0.64285714 | BQ6: =8/15 -> 0.53333333 | BR6: =18/30 -> 0.6 | BS6: - | BT6: =11/15 -> 0.73333333 | BU6: =7/15 -> 0.46666667 | BV6: =14/22 -> 0.63636364 | BW6: NA | BX6: =8/10 -> 0.8 | BY6: =6/12 -> 0.5 | BZ6: =24/34 -> 0.70588235 | CA6: NA | CB6: =12/14 -> 0.85714286 | CC6: =12/20 -> 0.6 | CD6: =22/34 -> 0.64705882 | CE6: NA | CF6: =10/14 -> 0.71428571 | CG6: =12/20 -> 0.6 | CH6: =22/36 -> 0.61111111 | CI6: NA | CJ6: =12/14 -> 0.85714286 | CK6: =10/22 -> 0.45454545 | CL6: =19/37 -> 0.51351351 | CM6: NA | CN6: =7/10 -> 0.7 | CO6: =12/27 -> 0.44444444 | CP6: =16/28 -> 0.57142857 | CQ6: NA | CR6: =6/10 -> 0.6 | CS6: =10/18 -> 0.55555556 | CT6: =36/55 -> 0.65454545 | CU6: NA | CV6: =17/22 -> 0.77272727 | CW6: =19/33 -> 0.57575758 | DF6: =43/63 -> 0.68253968 | DG6: - | DH6: =19/25 -> 0.76 | DI6: =24/38 -> 0.63157895 | DJ6: =41/64 -> 0.640625 | DK6: - | DL6: =19/25 -> 0.76 | DM6: =20/32 -> 0.625 | DN6: =44/63 -> 0.6984127 | DO6: - | DP6: =18/23 -> 0.7826087 | DQ6: =26/40 -> 0.65 | DR6: =55/79 -> 0.69620253 | DS6: - | DT6: =26/35 -> 0.74285714 | DU6: =29/44 -> 0.65909091
A7: 4 | B7: Pune | C7: Shweta | D7: Partially Reported | E7: Partially Validated | F7: =17/40 -> 0.425 | G7: =1/4 -> 0.25 | H7: =4/6 -> 0.66666667 | I7: =12/30 -> 0.4 | J7: =23/40 -> 0.575 | K7: =3/4 -> 0.75 | L7: =3/6 -> 0.5 | M7: =17/30 -> 0.56666667 | N7: =IFERROR(COUNTIFS('Base File'!$V:$V,"Met",'Base File'!$C:$C,B7)/(COUNTIFS('Base File'!$V:$V,"Met",'Base File'!$C:$C,B7)+COUNTIFS('Base File'!$V:$V,"Not Met",'Base File'!$C:$C,B7)),"NR") -> NR | O7: =IFERROR(COUNTIFS('Base File'!$G:$G,"Contractual SLA",'Base File'!$H:$H,"No",'Base File'!$C:$C,B7,'Base File'!$V:$V,"Met")/SUM(COUNTIFS('Base File'!$G:$G,"Contractual SLA",'Base File'!$H:$H,"No",'Base File'!$C:$C,B7,'Base File'!$V:$V,"Met")+COUNTIFS('Base File'!$G:$G,"Contractual SLA",'Base File'!$H:$H,"No",'Base File'!$C:$C,B7,'Base File'!$V:$V,"Not Met")),"-") -> - | P7: =IFERROR(COUNTIFS('Base File'!$G:$G,"Contractual SLA",'Base File'!$H:$H,"Yes",'Base File'!$C:$C,B7,'Base File'!$V:$V,"Met")/SUM(COUNTIFS('Base File'!$G:$G,"Contractual SLA",'Base File'!$H:$H,"yes",'Base File'!$C:$C,B7,'Base File'!$V:$V,"Met")+COUNTIFS('Base File'!$G:$G,"Contractual SLA",'Base File'!$H:$H,"yes",'Base File'!$C:$C,B7,'Base File'!$V:$V,"Not Met")),"-") -> - | Q7: =IFERROR(COUNTIFS('Base File'!$G:$G,"Internal KPI",'Base File'!$C:$C,B7,'Base File'!$V:$V,"Met")/SUM(COUNTIFS('Base File'!$G:$G,"Internal KPI",'Base File'!$C:$C,B7,'Base File'!$V:$V,"Met")+COUNTIFS('Base File'!$G:$G,"Internal KPI",'Base File'!$C:$C,B7,'Base File'!$V:$V,"Not Met")),"-") -> - | R7: =BR7 -> 0.45454545 | S7: =BS7 -> NA | T7: =BT7 -> 0.5 | U7: =BU7 -> 0.4375 | V7: =IFERROR(COUNTIFS('Base File'!$X:$X,"Met",'Base File'!$C:$C,B7)/(COUNTIFS('Base File'!$X:$X,"Met",'Base File'!$C:$C,B7)+COUNTIFS('Base File'!$X:$X,"Not Met",'Base File'!$C:$C,B7)),"NR") -> NR | W7: =IFERROR(COUNTIFS('Base File'!$G:$G,"Contractual SLA",'Base File'!$H:$H,"No",'Base File'!$C:$C,B7,'Base File'!$X:$X,"Met")/SUM(COUNTIFS('Base File'!$G:$G,"Contractual SLA",'Base File'!$H:$H,"No",'Base File'!$C:$C,B7,'Base File'!$X:$X,"Met")+COUNTIFS('Base File'!$G:$G,"Contractual SLA",'Base File'!$H:$H,"No",'Base File'!$C:$C,B7,'Base File'!$X:$X,"Not Met")),"-") -> - | X7: =IFERROR(COUNTIFS('Base File'!$G:$G,"Contractual SLA",'Base File'!$H:$H,"Yes",'Base File'!$C:$C,B7,'Base File'!$X:$X,"Met")/SUM(COUNTIFS('Base File'!$G:$G,"Contractual SLA",'Base File'!$H:$H,"yes",'Base File'!$C:$C,B7,'Base File'!$X:$X,"Met")+COUNTIFS('Base File'!$G:$G,"Contractual SLA",'Base File'!$H:$H,"yes",'Base File'!$C:$C,B7,'Base File'!$X:$X,"Not Met")),"-") -> - | Y7: =IFERROR(COUNTIFS('Base File'!$G:$G,"Internal KPI",'Base File'!$C:$C,B7,'Base File'!$X:$X,"Met")/SUM(COUNTIFS('Base File'!$G:$G,"Internal KPI",'Base File'!$C:$C,B7,'Base File'!$X:$X,"Met")+COUNTIFS('Base File'!$G:$G,"Internal KPI",'Base File'!$C:$C,B7,'Base File'!$X:$X,"Not Met")),"-") -> - | Z7: =IFERROR(COUNTIFS('Base File'!$Z:$Z,"Met",'Base File'!$C:$C,B7)/(COUNTIFS('Base File'!$Z:$Z,"Met",'Base File'!$C:$C,B7)+COUNTIFS('Base File'!$Z:$Z,"Not Met",'Base File'!$C:$C,B7)),"NR") -> NR | AA7: =IFERROR(COUNTIFS('Base File'!$G:$G,"Contractual SLA",'Base File'!$H:$H,"No",'Base File'!$C:$C,B7,'Base File'!$Z:$Z,"Met")/SUM(COUNTIFS('Base File'!$G:$G,"Contractual SLA",'Base File'!$H:$H,"No",'Base File'!$C:$C,B7,'Base File'!$Z:$Z,"Met")+COUNTIFS('Base File'!$G:$G,"Contractual SLA",'Base File'!$H:$H,"No",'Base File'!$C:$C,B7,'Base File'!$Z:$Z,"Not Met")),"-") -> - | AB7: =IFERROR(COUNTIFS('Base File'!$G:$G,"Contractual SLA",'Base File'!$H:$H,"Yes",'Base File'!$C:$C,B7,'Base File'!$Z:$Z,"Met")/SUM(COUNTIFS('Base File'!$G:$G,"Contractual SLA",'Base File'!$H:$H,"yes",'Base File'!$C:$C,B7,'Base File'!$Z:$Z,"Met")+COUNTIFS('Base File'!$G:$G,"Contractual SLA",'Base File'!$H:$H,"yes",'Base File'!$C:$C,B7,'Base File'!$Z:$Z,"Not Met")),"-") -> - | AC7: =IFERROR(COUNTIFS('Base File'!$G:$G,"Internal KPI",'Base File'!$C:$C,B7,'Base File'!$Z:$Z,"Met")/SUM(COUNTIFS('Base File'!$G:$G,"Internal KPI",'Base File'!$C:$C,B7,'Base File'!$Z:$Z,"Met")+COUNTIFS('Base File'!$G:$G,"Internal KPI",'Base File'!$C:$C,B7,'Base File'!$Z:$Z,"Not Met")),"-") -> - | AD7: =IFERROR(COUNTIFS('Base File'!$AB:$AB,"Met",'Base File'!$C:$C,B7)/(COUNTIFS('Base File'!$AB:$AB,"Met",'Base File'!$C:$C,B7)+COUNTIFS('Base File'!$AB:$AB,"Not Met",'Base File'!$C:$C,B7)),"NR") -> NR | AE7: =IFERROR(COUNTIFS('Base File'!$G:$G,"Contractual SLA",'Base File'!$H:$H,"No",'Base File'!$C:$C,B7,'Base File'!$AB:$AB,"Met")/SUM(COUNTIFS('Base File'!$G:$G,"Contractual SLA",'Base File'!$H:$H,"No",'Base File'!$C:$C,B7,'Base File'!$AB:$AB,"Met")+COUNTIFS('Base File'!$G:$G,"Contractual SLA",'Base File'!$H:$H,"No",'Base File'!$C:$C,B7,'Base File'!$AB:$AB,"Not Met")),"-") -> - | AF7: =IFERROR(COUNTIFS('Base File'!$G:$G,"Contractual SLA",'Base File'!$H:$H,"Yes",'Base File'!$C:$C,B7,'Base File'!$AB:$AB,"Met")/SUM(COUNTIFS('Base File'!$G:$G,"Contractual SLA",'Base File'!$H:$H,"yes",'Base File'!$C:$C,B7,'Base File'!$AB:$AB,"Met")+COUNTIFS('Base File'!$G:$G,"Contractual SLA",'Base File'!$H:$H,"yes",'Base File'!$C:$C,B7,'Base File'!$AB:$AB,"Not Met")),"-") -> - | AG7: =IFERROR(COUNTIFS('Base File'!$G:$G,"Internal KPI",'Base File'!$C:$C,B7,'Base File'!$AB:$AB,"Met")/SUM(COUNTIFS('Base File'!$G:$G,"Internal KPI",'Base File'!$C:$C,B7,'Base File'!$AB:$AB,"Met")+COUNTIFS('Base File'!$G:$G,"Internal KPI",'Base File'!$C:$C,B7,'Base File'!$AB:$AB,"Not Met")),"-") -> - | AH7: =IFERROR(COUNTIFS('Base File'!$AD:$AD,"Met",'Base File'!$C:$C,B7)/(COUNTIFS('Base File'!$AD:$AD,"Met",'Base File'!$C:$C,B7)+COUNTIFS('Base File'!$AD:$AD,"Not Met",'Base File'!$C:$C,B7)),"NR") -> NR | AI7: =IFERROR(COUNTIFS('Base File'!$G:$G,"Contractual SLA",'Base File'!$H:$H,"No",'Base File'!$C:$C,B7,'Base File'!$AD:$AD,"Met")/SUM(COUNTIFS('Base File'!$G:$G,"Contractual SLA",'Base File'!$H:$H,"No",'Base File'!$C:$C,B7,'Base File'!$AD:$AD,"Met")+COUNTIFS('Base File'!$G:$G,"Contractual SLA",'Base File'!$H:$H,"No",'Base File'!$C:$C,B7,'Base File'!$AD:$AD,"Not Met")),"-") -> - | AJ7: =IFERROR(COUNTIFS('Base File'!$G:$G,"Contractual SLA",'Base File'!$H:$H,"Yes",'Base File'!$C:$C,B7,'Base File'!$AD:$AD,"Met")/SUM(COUNTIFS('Base File'!$G:$G,"Contractual SLA",'Base File'!$H:$H,"yes",'Base File'!$C:$C,B7,'Base File'!$AD:$AD,"Met")+COUNTIFS('Base File'!$G:$G,"Contractual SLA",'Base File'!$H:$H,"yes",'Base File'!$C:$C,B7,'Base File'!$AD:$AD,"Not Met")),"-") -> - | AK7: =IFERROR(COUNTIFS('Base File'!$G:$G,"Internal KPI",'Base File'!$C:$C,B7,'Base File'!$AD:$AD,"Met")/SUM(COUNTIFS('Base File'!$G:$G,"Internal KPI",'Base File'!$C:$C,B7,'Base File'!$AD:$AD,"Met")+COUNTIFS('Base File'!$G:$G,"Internal KPI",'Base File'!$C:$C,B7,'Base File'!$AD:$AD,"Not Met")),"-") -> - | AL7: =IFERROR(COUNTIFS('Base File'!$AF:$AF,"Met",'Base File'!$C:$C,B7)/(COUNTIFS('Base File'!$AF:$AF,"Met",'Base File'!$C:$C,B7)+COUNTIFS('Base File'!$AF:$AF,"Not Met",'Base File'!$C:$C,B7)),"NR") -> NR | AM7: =IFERROR(COUNTIFS('Base File'!$G:$G,"Contractual SLA",'Base File'!$H:$H,"No",'Base File'!$C:$C,B7,'Base File'!$AF:$AF,"Met")/SUM(COUNTIFS('Base File'!$G:$G,"Contractual SLA",'Base File'!$H:$H,"No",'Base File'!$C:$C,B7,'Base File'!$AF:$AF,"Met")+COUNTIFS('Base File'!$G:$G,"Contractual SLA",'Base File'!$H:$H,"No",'Base File'!$C:$C,B7,'Base File'!$AF:$AF,"Not Met")),"-") -> - | AN7: =IFERROR(COUNTIFS('Base File'!$G:$G,"Contractual SLA",'Base File'!$H:$H,"Yes",'Base File'!$C:$C,B7,'Base File'!$AF:$AF,"Met")/SUM(COUNTIFS('Base File'!$G:$G,"Contractual SLA",'Base File'!$H:$H,"yes",'Base File'!$C:$C,B7,'Base File'!$AF:$AF,"Met")+COUNTIFS('Base File'!$G:$G,"Contractual SLA",'Base File'!$H:$H,"yes",'Base File'!$C:$C,B7,'Base File'!$AF:$AF,"Not Met")),"-") -> - | AO7: =IFERROR(COUNTIFS('Base File'!$G:$G,"Internal KPI",'Base File'!$C:$C,B7,'Base File'!$AF:$AF,"Met")/SUM(COUNTIFS('Base File'!$G:$G,"Internal KPI",'Base File'!$C:$C,B7,'Base File'!$AF:$AF,"Met")+COUNTIFS('Base File'!$G:$G,"Internal KPI",'Base File'!$C:$C,B7,'Base File'!$AF:$AF,"Not Met")),"-") -> - | AP7: =IFERROR(COUNTIFS('Base File'!$AH:$AH,"Met",'Base File'!$C:$C,B7)/(COUNTIFS('Base File'!$AH:$AH,"Met",'Base File'!$C:$C,B7)+COUNTIFS('Base File'!$AH:$AH,"Not Met",'Base File'!$C:$C,B7)),"NR") -> NR | AQ7: =IFERROR(COUNTIFS('Base File'!$G:$G,"Contractual SLA",'Base File'!$H:$H,"No",'Base File'!$C:$C,B7,'Base File'!$AH:$AH,"Met")/SUM(COUNTIFS('Base File'!$G:$G,"Contractual SLA",'Base File'!$H:$H,"No",'Base File'!$C:$C,B7,'Base File'!$AH:$AH,"Met")+COUNTIFS('Base File'!$G:$G,"Contractual SLA",'Base File'!$H:$H,"No",'Base File'!$C:$C,B7,'Base File'!$AH:$AH,"Not Met")),"-") -> - | AR7: =IFERROR(COUNTIFS('Base File'!$G:$G,"Contractual SLA",'Base File'!$H:$H,"Yes",'Base File'!$C:$C,B7,'Base File'!$AH:$AH,"Met")/SUM(COUNTIFS('Base File'!$G:$G,"Contractual SLA",'Base File'!$H:$H,"yes",'Base File'!$C:$C,B7,'Base File'!$AH:$AH,"Met")+COUNTIFS('Base File'!$G:$G,"Contractual SLA",'Base File'!$H:$H,"yes",'Base File'!$C:$C,B7,'Base File'!$AH:$AH,"Not Met")),"-") -> - | AS7: =IFERROR(COUNTIFS('Base File'!$G:$G,"Internal KPI",'Base File'!$C:$C,B7,'Base File'!$AH:$AH,"Met")/SUM(COUNTIFS('Base File'!$G:$G,"Internal KPI",'Base File'!$C:$C,B7,'Base File'!$AH:$AH,"Met")+COUNTIFS('Base File'!$G:$G,"Internal KPI",'Base File'!$C:$C,B7,'Base File'!$AH:$AH,"Not Met")),"-") -> - | AT7: =13/28 -> 0.46428571 | AU7: =2/4 -> 0.5 | AV7: =2/2 -> 1 | AW7: =9/22 -> 0.40909091 | AX7: =15/29 -> 0.51724138 | AY7: =3/4 -> 0.75 | AZ7: =1/2 -> 0.5 | BA7: =11/23 -> 0.47826087 | BB7: =14/31 -> 0.4516129 | BC7: =2/3 -> 0.66666667 | BD7: =3/6 -> 0.5 | BE7: =9/22 -> 0.40909091 | BF7: =10/22 -> 0.45454545 | BG7: NA | BH7: =3/6 -> 0.5 | BI7: =7/16 -> 0.4375 | BJ7: =9/21 -> 0.42857143 | BK7: NA | BL7: =2/6 -> 0.33333333 | BM7: =7/15 -> 0.46666667 | BN7: =8/21 -> 0.38095238 | BO7: NA | BP7: =2/6 -> 0.33333333 | BQ7: =6/15 -> 0.4 | BR7: =10/22 -> 0.45454545 | BS7: NA | BT7: =3/6 -> 0.5 | BU7: =7/16 -> 0.4375 | BV7: =7/21 -> 0.33333333 | BW7: NA | BX7: =3/6 -> 0.5 | BY7: =4/15 -> 0.26666667 | BZ7: =13/26 -> 0.5 | CA7: =3/4 -> 0.75 | CB7: =3/5 -> 0.6 | CC7: =7/17 -> 0.41176471 | CD7: =14/26 -> 0.53846154 | CE7: =4/4 -> 1 | CF7: =3/5 -> 0.6 | CG7: =7/17 -> 0.41176471 | CH7: =14/26 -> 0.53846154 | CI7: =3/4 -> 0.75 | CJ7: =2/5 -> 0.4 | CK7: =9/17 -> 0.52941176 | CL7: =16/26 -> 0.61538462 | CM7: =3/4 -> 0.75 | CN7: =3/6 -> 0.5 | CO7: =10/16 -> 0.625 | CP7: =11/27 -> 0.40740741 | CQ7: =3/4 -> 0.75 | CR7: =1/6 -> 0.16666667 | CS7: =7/17 -> 0.41176471 | CT7: =13/25 -> 0.52 | CU7: =3/4 -> 0.75 | CV7: =2/5 -> 0.4 | CW7: =8/16 -> 0.5 | DF7: =6/12 -> 0.5 | DG7: =3/4 -> 0.75 | DH7: NR | DI7: =3/8 -> 0.375 | DJ7: NR | DK7: NR | DL7: NR | DM7: NR | DN7: NR | DO7: NR | DP7: NR | DQ7: NR | DR7: NR | DS7: NR | DT7: NR | DU7: NR
A8: 5 | B8: Mumbai & Gujrat | C8: Elton | D8: NA - Project On-hold | E8: NA - Project On-hold | F8: =61/98 -> 0.62244898 | G8: =15/23 -> 0.65217391 | H8: =2/3 -> 0.66666667 | I8: =44/72 -> 0.61111111 | J8: =68/101 -> 0.67326733 | K8: =19/27 -> 0.7037037 | L8: =5/7 -> 0.71428571 | M8: =44/67 -> 0.65671642 | N8: =IFERROR(COUNTIFS('Base File'!$V:$V,"Met",'Base File'!$C:$C,B8)/(COUNTIFS('Base File'!$V:$V,"Met",'Base File'!$C:$C,B8)+COUNTIFS('Base File'!$V:$V,"Not Met",'Base File'!$C:$C,B8)),"NR") -> NR | O8: =IFERROR(COUNTIFS('Base File'!$G:$G,"Contractual SLA",'Base File'!$H:$H,"No",'Base File'!$C:$C,B8,'Base File'!$V:$V,"Met")/SUM(COUNTIFS('Base File'!$G:$G,"Contractual SLA",'Base File'!$H:$H,"No",'Base File'!$C:$C,B8,'Base File'!$V:$V,"Met")+COUNTIFS('Base File'!$G:$G,"Contractual SLA",'Base File'!$H:$H,"No",'Base File'!$C:$C,B8,'Base File'!$V:$V,"Not Met")),"-") -> - | P8: =IFERROR(COUNTIFS('Base File'!$G:$G,"Contractual SLA",'Base File'!$H:$H,"Yes",'Base File'!$C:$C,B8,'Base File'!$V:$V,"Met")/SUM(COUNTIFS('Base File'!$G:$G,"Contractual SLA",'Base File'!$H:$H,"yes",'Base File'!$C:$C,B8,'Base File'!$V:$V,"Met")+COUNTIFS('Base File'!$G:$G,"Contractual SLA",'Base File'!$H:$H,"yes",'Base File'!$C:$C,B8,'Base File'!$V:$V,"Not Met")),"-") -> - | Q8: =IFERROR(COUNTIFS('Base File'!$G:$G,"Internal KPI",'Base File'!$C:$C,B8,'Base File'!$V:$V,"Met")/SUM(COUNTIFS('Base File'!$G:$G,"Internal KPI",'Base File'!$C:$C,B8,'Base File'!$V:$V,"Met")+COUNTIFS('Base File'!$G:$G,"Internal KPI",'Base File'!$C:$C,B8,'Base File'!$V:$V,"Not Met")),"-") -> - | R8: =BR8 -> 0.5 | S8: =BS8 -> 0 | T8: =BT8 -> NR | U8: =BU8 -> 0.51612903 | V8: =IFERROR(COUNTIFS('Base File'!$X:$X,"Met",'Base File'!$C:$C,B8)/(COUNTIFS('Base File'!$X:$X,"Met",'Base File'!$C:$C,B8)+COUNTIFS('Base File'!$X:$X,"Not Met",'Base File'!$C:$C,B8)),"NR") -> NR | W8: =IFERROR(COUNTIFS('Base File'!$G:$G,"Contractual SLA",'Base File'!$H:$H,"No",'Base File'!$C:$C,B8,'Base File'!$X:$X,"Met")/SUM(COUNTIFS('Base File'!$G:$G,"Contractual SLA",'Base File'!$H:$H,"No",'Base File'!$C:$C,B8,'Base File'!$X:$X,"Met")+COUNTIFS('Base File'!$G:$G,"Contractual SLA",'Base File'!$H:$H,"No",'Base File'!$C:$C,B8,'Base File'!$X:$X,"Not Met")),"-") -> - | X8: =IFERROR(COUNTIFS('Base File'!$G:$G,"Contractual SLA",'Base File'!$H:$H,"Yes",'Base File'!$C:$C,B8,'Base File'!$X:$X,"Met")/SUM(COUNTIFS('Base File'!$G:$G,"Contractual SLA",'Base File'!$H:$H,"yes",'Base File'!$C:$C,B8,'Base File'!$X:$X,"Met")+COUNTIFS('Base File'!$G:$G,"Contractual SLA",'Base File'!$H:$H,"yes",'Base File'!$C:$C,B8,'Base File'!$X:$X,"Not Met")),"-") -> - | Y8: =IFERROR(COUNTIFS('Base File'!$G:$G,"Internal KPI",'Base File'!$C:$C,B8,'Base File'!$X:$X,"Met")/SUM(COUNTIFS('Base File'!$G:$G,"Internal KPI",'Base File'!$C:$C,B8,'Base File'!$X:$X,"Met")+COUNTIFS('Base File'!$G:$G,"Internal KPI",'Base File'!$C:$C,B8,'Base File'!$X:$X,"Not Met")),"-") -> - | Z8: =IFERROR(COUNTIFS('Base File'!$Z:$Z,"Met",'Base File'!$C:$C,B8)/(COUNTIFS('Base File'!$Z:$Z,"Met",'Base File'!$C:$C,B8)+COUNTIFS('Base File'!$Z:$Z,"Not Met",'Base File'!$C:$C,B8)),"NR") -> NR | AA8: =IFERROR(COUNTIFS('Base File'!$G:$G,"Contractual SLA",'Base File'!$H:$H,"No",'Base File'!$C:$C,B8,'Base File'!$Z:$Z,"Met")/SUM(COUNTIFS('Base File'!$G:$G,"Contractual SLA",'Base File'!$H:$H,"No",'Base File'!$C:$C,B8,'Base File'!$Z:$Z,"Met")+COUNTIFS('Base File'!$G:$G,"Contractual SLA",'Base File'!$H:$H,"No",'Base File'!$C:$C,B8,'Base File'!$Z:$Z,"Not Met")),"-") -> - | AB8: =IFERROR(COUNTIFS('Base File'!$G:$G,"Contractual SLA",'Base File'!$H:$H,"Yes",'Base File'!$C:$C,B8,'Base File'!$Z:$Z,"Met")/SUM(COUNTIFS('Base File'!$G:$G,"Contractual SLA",'Base File'!$H:$H,"yes",'Base File'!$C:$C,B8,'Base File'!$Z:$Z,"Met")+COUNTIFS('Base File'!$G:$G,"Contractual SLA",'Base File'!$H:$H,"yes",'Base File'!$C:$C,B8,'Base File'!$Z:$Z,"Not Met")),"-") -> - | AC8: =IFERROR(COUNTIFS('Base File'!$G:$G,"Internal KPI",'Base File'!$C:$C,B8,'Base File'!$Z:$Z,"Met")/SUM(COUNTIFS('Base File'!$G:$G,"Internal KPI",'Base File'!$C:$C,B8,'Base File'!$Z:$Z,"Met")+COUNTIFS('Base File'!$G:$G,"Internal KPI",'Base File'!$C:$C,B8,'Base File'!$Z:$Z,"Not Met")),"-") -> - | AD8: =IFERROR(COUNTIFS('Base File'!$AB:$AB,"Met",'Base File'!$C:$C,B8)/(COUNTIFS('Base File'!$AB:$AB,"Met",'Base File'!$C:$C,B8)+COUNTIFS('Base File'!$AB:$AB,"Not Met",'Base File'!$C:$C,B8)),"NR") -> NR | AE8: =IFERROR(COUNTIFS('Base File'!$G:$G,"Contractual SLA",'Base File'!$H:$H,"No",'Base File'!$C:$C,B8,'Base File'!$AB:$AB,"Met")/SUM(COUNTIFS('Base File'!$G:$G,"Contractual SLA",'Base File'!$H:$H,"No",'Base File'!$C:$C,B8,'Base File'!$AB:$AB,"Met")+COUNTIFS('Base File'!$G:$G,"Contractual SLA",'Base File'!$H:$H,"No",'Base File'!$C:$C,B8,'Base File'!$AB:$AB,"Not Met")),"-") -> - | AF8: =IFERROR(COUNTIFS('Base File'!$G:$G,"Contractual SLA",'Base File'!$H:$H,"Yes",'Base File'!$C:$C,B8,'Base File'!$AB:$AB,"Met")/SUM(COUNTIFS('Base File'!$G:$G,"Contractual SLA",'Base File'!$H:$H,"yes",'Base File'!$C:$C,B8,'Base File'!$AB:$AB,"Met")+COUNTIFS('Base File'!$G:$G,"Contractual SLA",'Base File'!$H:$H,"yes",'Base File'!$C:$C,B8,'Base File'!$AB:$AB,"Not Met")),"-") -> - | AG8: =IFERROR(COUNTIFS('Base File'!$G:$G,"Internal KPI",'Base File'!$C:$C,B8,'Base File'!$AB:$AB,"Met")/SUM(COUNTIFS('Base File'!$G:$G,"Internal KPI",'Base File'!$C:$C,B8,'Base File'!$AB:$AB,"Met")+COUNTIFS('Base File'!$G:$G,"Internal KPI",'Base File'!$C:$C,B8,'Base File'!$AB:$AB,"Not Met")),"-") -> - | AH8: =IFERROR(COUNTIFS('Base File'!$AD:$AD,"Met",'Base File'!$C:$C,B8)/(COUNTIFS('Base File'!$AD:$AD,"Met",'Base File'!$C:$C,B8)+COUNTIFS('Base File'!$AD:$AD,"Not Met",'Base File'!$C:$C,B8)),"NR") -> NR | AI8: =IFERROR(COUNTIFS('Base File'!$G:$G,"Contractual SLA",'Base File'!$H:$H,"No",'Base File'!$C:$C,B8,'Base File'!$AD:$AD,"Met")/SUM(COUNTIFS('Base File'!$G:$G,"Contractual SLA",'Base File'!$H:$H,"No",'Base File'!$C:$C,B8,'Base File'!$AD:$AD,"Met")+COUNTIFS('Base File'!$G:$G,"Contractual SLA",'Base File'!$H:$H,"No",'Base File'!$C:$C,B8,'Base File'!$AD:$AD,"Not Met")),"-") -> - | AJ8: =IFERROR(COUNTIFS('Base File'!$G:$G,"Contractual SLA",'Base File'!$H:$H,"Yes",'Base File'!$C:$C,B8,'Base File'!$AD:$AD,"Met")/SUM(COUNTIFS('Base File'!$G:$G,"Contractual SLA",'Base File'!$H:$H,"yes",'Base File'!$C:$C,B8,'Base File'!$AD:$AD,"Met")+COUNTIFS('Base File'!$G:$G,"Contractual SLA",'Base File'!$H:$H,"yes",'Base File'!$C:$C,B8,'Base File'!$AD:$AD,"Not Met")),"-") -> - | AK8: =IFERROR(COUNTIFS('Base File'!$G:$G,"Internal KPI",'Base File'!$C:$C,B8,'Base File'!$AD:$AD,"Met")/SUM(COUNTIFS('Base File'!$G:$G,"Internal KPI",'Base File'!$C:$C,B8,'Base File'!$AD:$AD,"Met")+COUNTIFS('Base File'!$G:$G,"Internal KPI",'Base File'!$C:$C,B8,'Base File'!$AD:$AD,"Not Met")),"-") -> - | AL8: =IFERROR(COUNTIFS('Base File'!$AF:$AF,"Met",'Base File'!$C:$C,B8)/(COUNTIFS('Base File'!$AF:$AF,"Met",'Base File'!$C:$C,B8)+COUNTIFS('Base File'!$AF:$AF,"Not Met",'Base File'!$C:$C,B8)),"NR") -> NR | AM8: =IFERROR(COUNTIFS('Base File'!$G:$G,"Contractual SLA",'Base File'!$H:$H,"No",'Base File'!$C:$C,B8,'Base File'!$AF:$AF,"Met")/SUM(COUNTIFS('Base File'!$G:$G,"Contractual SLA",'Base File'!$H:$H,"No",'Base File'!$C:$C,B8,'Base File'!$AF:$AF,"Met")+COUNTIFS('Base File'!$G:$G,"Contractual SLA",'Base File'!$H:$H,"No",'Base File'!$C:$C,B8,'Base File'!$AF:$AF,"Not Met")),"-") -> - | AN8: =IFERROR(COUNTIFS('Base File'!$G:$G,"Contractual SLA",'Base File'!$H:$H,"Yes",'Base File'!$C:$C,B8,'Base File'!$AF:$AF,"Met")/SUM(COUNTIFS('Base File'!$G:$G,"Contractual SLA",'Base File'!$H:$H,"yes",'Base File'!$C:$C,B8,'Base File'!$AF:$AF,"Met")+COUNTIFS('Base File'!$G:$G,"Contractual SLA",'Base File'!$H:$H,"yes",'Base File'!$C:$C,B8,'Base File'!$AF:$AF,"Not Met")),"-") -> - | AO8: =IFERROR(COUNTIFS('Base File'!$G:$G,"Internal KPI",'Base File'!$C:$C,B8,'Base File'!$AF:$AF,"Met")/SUM(COUNTIFS('Base File'!$G:$G,"Internal KPI",'Base File'!$C:$C,B8,'Base File'!$AF:$AF,"Met")+COUNTIFS('Base File'!$G:$G,"Internal KPI",'Base File'!$C:$C,B8,'Base File'!$AF:$AF,"Not Met")),"-") -> - | AP8: =12/23 -> 0.52173913 | AQ8: =0/2 -> 0 | AR8: =0/2 -> 0 | AS8: =12/19 -> 0.63157895 | AT8: =29/60 -> 0.48333333 | AU8: =1/2 -> 0.5 | AV8: =0/2 -> 0 | AW8: =28/56 -> 0.5 | AX8: =28/58 -> 0.48275862 | AY8: =1/2 -> 0.5 | AZ8: =0/2 -> 0 | BA8: =27/54 -> 0.5 | BB8: =38/61 -> 0.62295082 | BC8: =0/2 -> 0 | BD8: =0/2 -> 0 | BE8: =38/57 -> 0.66666667 | BF8: =29/48 -> 0.60416667 | BG8: =1/2 -> 0.5 | BH8: NR | BI8: =28/46 -> 0.60869565 | BJ8: =25/48 -> 0.52083333 | BK8: =1/2 -> 0.5 | BL8: NR | BM8: =24/46 -> 0.52173913 | BN8: =28/48 -> 0.58333333 | BO8: =1/2 -> 0.5 | BP8: NR | BQ8: =27/46 -> 0.58695652 | BR8: =32/64 -> 0.5 | BS8: =0/2 -> 0 | BT8: NR | BU8: =32/62 -> 0.51612903 | BV8: =22/47 -> 0.46808511 | BW8: NR | BX8: NR | BY8: =22/47 -> 0.46808511 | BZ8: - | CA8: - | CB8: - | CC8: - | CD8: - | CE8: - | CF8: - | CG8: - | CH8: - | CI8: - | CJ8: - | CK8: - | CL8: NA | CM8: NA | CN8: NA | CO8: NA | CP8: NA | CQ8: NA | CR8: NA | CS8: NA | CT8: NA | CU8: NA | CV8: NA | CW8: NA | DF8: NA | DG8: NA | DH8: NA | DI8: NA | DJ8: NA | DK8: NA | DL8: NA | DM8: NA | DN8: NA | DO8: NA | DP8: NA | DQ8: NA | DR8: NA | DS8: NA | DT8: NA | DU8: NA
A9: 6 | B9: Mumbai & Gujrat | C9: Alifiya | D9: NA - SLAs/KPIs not finalised with the customer | E9: NA - SLAs/KPIs not finalised with the customer | F9: =61/98 -> 0.62244898 | G9: =15/23 -> 0.65217391 | H9: =2/3 -> 0.66666667 | I9: =44/72 -> 0.61111111 | J9: =68/101 -> 0.67326733 | K9: =19/27 -> 0.7037037 | L9: =5/7 -> 0.71428571 | M9: =44/67 -> 0.65671642 | N9: =IFERROR(COUNTIFS('Base File'!$V:$V,"Met",'Base File'!$C:$C,B9)/(COUNTIFS('Base File'!$V:$V,"Met",'Base File'!$C:$C,B9)+COUNTIFS('Base File'!$V:$V,"Not Met",'Base File'!$C:$C,B9)),"NR") -> NR | O9: =IFERROR(COUNTIFS('Base File'!$G:$G,"Contractual SLA",'Base File'!$H:$H,"No",'Base File'!$C:$C,B9,'Base File'!$V:$V,"Met")/SUM(COUNTIFS('Base File'!$G:$G,"Contractual SLA",'Base File'!$H:$H,"No",'Base File'!$C:$C,B9,'Base File'!$V:$V,"Met")+COUNTIFS('Base File'!$G:$G,"Contractual SLA",'Base File'!$H:$H,"No",'Base File'!$C:$C,B9,'Base File'!$V:$V,"Not Met")),"-") -> - | P9: =IFERROR(COUNTIFS('Base File'!$G:$G,"Contractual SLA",'Base File'!$H:$H,"Yes",'Base File'!$C:$C,B9,'Base File'!$V:$V,"Met")/SUM(COUNTIFS('Base File'!$G:$G,"Contractual SLA",'Base File'!$H:$H,"yes",'Base File'!$C:$C,B9,'Base File'!$V:$V,"Met")+COUNTIFS('Base File'!$G:$G,"Contractual SLA",'Base File'!$H:$H,"yes",'Base File'!$C:$C,B9,'Base File'!$V:$V,"Not Met")),"-") -> - | Q9: =IFERROR(COUNTIFS('Base File'!$G:$G,"Internal KPI",'Base File'!$C:$C,B9,'Base File'!$V:$V,"Met")/SUM(COUNTIFS('Base File'!$G:$G,"Internal KPI",'Base File'!$C:$C,B9,'Base File'!$V:$V,"Met")+COUNTIFS('Base File'!$G:$G,"Internal KPI",'Base File'!$C:$C,B9,'Base File'!$V:$V,"Not Met")),"-") -> - | R9: =BR9 -> 0.28571429 | S9: =BS9 -> 0.5 | T9: =BT9 -> - | U9: =BU9 -> 0 | V9: =IFERROR(COUNTIFS('Base File'!$X:$X,"Met",'Base File'!$C:$C,B9)/(COUNTIFS('Base File'!$X:$X,"Met",'Base File'!$C:$C,B9)+COUNTIFS('Base File'!$X:$X,"Not Met",'Base File'!$C:$C,B9)),"NR") -> NR | W9: =IFERROR(COUNTIFS('Base File'!$G:$G,"Contractual SLA",'Base File'!$H:$H,"No",'Base File'!$C:$C,B9,'Base File'!$X:$X,"Met")/SUM(COUNTIFS('Base File'!$G:$G,"Contractual SLA",'Base File'!$H:$H,"No",'Base File'!$C:$C,B9,'Base File'!$X:$X,"Met")+COUNTIFS('Base File'!$G:$G,"Contractual SLA",'Base File'!$H:$H,"No",'Base File'!$C:$C,B9,'Base File'!$X:$X,"Not Met")),"-") -> - | X9: =IFERROR(COUNTIFS('Base File'!$G:$G,"Contractual SLA",'Base File'!$H:$H,"Yes",'Base File'!$C:$C,B9,'Base File'!$X:$X,"Met")/SUM(COUNTIFS('Base File'!$G:$G,"Contractual SLA",'Base File'!$H:$H,"yes",'Base File'!$C:$C,B9,'Base File'!$X:$X,"Met")+COUNTIFS('Base File'!$G:$G,"Contractual SLA",'Base File'!$H:$H,"yes",'Base File'!$C:$C,B9,'Base File'!$X:$X,"Not Met")),"-") -> - | Y9: =IFERROR(COUNTIFS('Base File'!$G:$G,"Internal KPI",'Base File'!$C:$C,B9,'Base File'!$X:$X,"Met")/SUM(COUNTIFS('Base File'!$G:$G,"Internal KPI",'Base File'!$C:$C,B9,'Base File'!$X:$X,"Met")+COUNTIFS('Base File'!$G:$G,"Internal KPI",'Base File'!$C:$C,B9,'Base File'!$X:$X,"Not Met")),"-") -> - | Z9: =IFERROR(COUNTIFS('Base File'!$Z:$Z,"Met",'Base File'!$C:$C,B9)/(COUNTIFS('Base File'!$Z:$Z,"Met",'Base File'!$C:$C,B9)+COUNTIFS('Base File'!$Z:$Z,"Not Met",'Base File'!$C:$C,B9)),"NR") -> NR | AA9: =IFERROR(COUNTIFS('Base File'!$G:$G,"Contractual SLA",'Base File'!$H:$H,"No",'Base File'!$C:$C,B9,'Base File'!$Z:$Z,"Met")/SUM(COUNTIFS('Base File'!$G:$G,"Contractual SLA",'Base File'!$H:$H,"No",'Base File'!$C:$C,B9,'Base File'!$Z:$Z,"Met")+COUNTIFS('Base File'!$G:$G,"Contractual SLA",'Base File'!$H:$H,"No",'Base File'!$C:$C,B9,'Base File'!$Z:$Z,"Not Met")),"-") -> - | AB9: =IFERROR(COUNTIFS('Base File'!$G:$G,"Contractual SLA",'Base File'!$H:$H,"Yes",'Base File'!$C:$C,B9,'Base File'!$Z:$Z,"Met")/SUM(COUNTIFS('Base File'!$G:$G,"Contractual SLA",'Base File'!$H:$H,"yes",'Base File'!$C:$C,B9,'Base File'!$Z:$Z,"Met")+COUNTIFS('Base File'!$G:$G,"Contractual SLA",'Base File'!$H:$H,"yes",'Base File'!$C:$C,B9,'Base File'!$Z:$Z,"Not Met")),"-") -> - | AC9: =IFERROR(COUNTIFS('Base File'!$G:$G,"Internal KPI",'Base File'!$C:$C,B9,'Base File'!$Z:$Z,"Met")/SUM(COUNTIFS('Base File'!$G:$G,"Internal KPI",'Base File'!$C:$C,B9,'Base File'!$Z:$Z,"Met")+COUNTIFS('Base File'!$G:$G,"Internal KPI",'Base File'!$C:$C,B9,'Base File'!$Z:$Z,"Not Met")),"-") -> - | AD9: =4/7 -> 0.57142857 | AE9: 0.5 | AF9: - | AG9: =IFERROR(COUNTIFS('Base File'!$G:$G,"Internal KPI",'Base File'!$C:$C,B9,'Base File'!$AB:$AB,"Met")/SUM(COUNTIFS('Base File'!$G:$G,"Internal KPI",'Base File'!$C:$C,B9,'Base File'!$AB:$AB,"Met")+COUNTIFS('Base File'!$G:$G,"Internal KPI",'Base File'!$C:$C,B9,'Base File'!$AB:$AB,"Not Met")),"-") -> - | AH9: NR | AI9: NR | AJ9: =IFERROR(COUNTIFS('Base File'!$G:$G,"Contractual SLA",'Base File'!$H:$H,"Yes",'Base File'!$C:$C,B9,'Base File'!$AD:$AD,"Met")/SUM(COUNTIFS('Base File'!$G:$G,"Contractual SLA",'Base File'!$H:$H,"yes",'Base File'!$C:$C,B9,'Base File'!$AD:$AD,"Met")+COUNTIFS('Base File'!$G:$G,"Contractual SLA",'Base File'!$H:$H,"yes",'Base File'!$C:$C,B9,'Base File'!$AD:$AD,"Not Met")),"-") -> - | AK9: NR | AL9: =2/7 -> 0.28571429 | AM9: =2/4 -> 0.5 | AN9: - | AO9: =0/3 -> 0 | AP9: =3/7 -> 0.42857143 | AQ9: =2/4 -> 0.5 | AR9: - | AS9: =1/3 -> 0.33333333 | AT9: =2/7 -> 0.28571429 | AU9: =2/4 -> 0.5 | AV9: - | AW9: =0/3 -> 0 | AX9: =2/7 -> 0.28571429 | AY9: =2/4 -> 0.5 | AZ9: - | BA9: =0/3 -> 0 | BB9: =2/7 -> 0.28571429 | BC9: =2/4 -> 0.5 | BD9: - | BE9: =0/3 -> 0 | BF9: =1/7 -> 0.14285714 | BG9: =1/4 -> 0.25 | BH9: - | BI9: =0/3 -> 0 | BJ9: =2/7 -> 0.28571429 | BK9: =2/4 -> 0.5 | BL9: - | BM9: =0/3 -> 0 | BN9: =2/7 -> 0.28571429 | BO9: =2/4 -> 0.5 | BP9: - | BQ9: =0/3 -> 0 | BR9: =2/7 -> 0.28571429 | BS9: =2/4 -> 0.5 | BT9: - | BU9: =0/3 -> 0 | BV9: =2/7 -> 0.28571429 | BW9: =2/4 -> 0.5 | BX9: NA | BY9: =0/3 -> 0 | BZ9: NA | CA9: NA | CB9: - | CC9: NA | CD9: NA | CE9: NA | CF9: - | CG9: NA | CH9: NA | CI9: NA | CJ9: - | CK9: NA | CL9: NA | CM9: NA | CN9: - | CO9: NA | CP9: NA | CQ9: NA | CR9: NA | CS9: NA | CT9: NA | CU9: NA | CV9: NA | CW9: NA | DF9: NA | DG9: NA | DH9: NA | DI9: NA | DJ9: NA | DK9: NA | DL9: NA | DM9: NA | DN9: NA | DO9: NA | DP9: - | DQ9: NA | DR9: =2/7 -> 0.28571429 | DS9: =2/4 -> 0.5 | DT9: - | DU9: =0/3 -> 0
A10: 7 | B10: Mumbai & Gujrat | C10: Usha | D10: Partially Reported | E10: Partially Validated | F10: =61/98 -> 0.62244898 | G10: =15/23 -> 0.65217391 | H10: =2/3 -> 0.66666667 | I10: =44/72 -> 0.61111111 | J10: =68/101 -> 0.67326733 | K10: =19/27 -> 0.7037037 | L10: =5/7 -> 0.71428571 | M10: =44/67 -> 0.65671642 | N10: =IFERROR(COUNTIFS('Base File'!$V:$V,"Met",'Base File'!$C:$C,B10)/(COUNTIFS('Base File'!$V:$V,"Met",'Base File'!$C:$C,B10)+COUNTIFS('Base File'!$V:$V,"Not Met",'Base File'!$C:$C,B10)),"NR") -> NR | O10: =IFERROR(COUNTIFS('Base File'!$G:$G,"Contractual SLA",'Base File'!$H:$H,"No",'Base File'!$C:$C,B10,'Base File'!$V:$V,"Met")/SUM(COUNTIFS('Base File'!$G:$G,"Contractual SLA",'Base File'!$H:$H,"No",'Base File'!$C:$C,B10,'Base File'!$V:$V,"Met")+COUNTIFS('Base File'!$G:$G,"Contractual SLA",'Base File'!$H:$H,"No",'Base File'!$C:$C,B10,'Base File'!$V:$V,"Not Met")),"-") -> - | P10: =IFERROR(COUNTIFS('Base File'!$G:$G,"Contractual SLA",'Base File'!$H:$H,"Yes",'Base File'!$C:$C,B10,'Base File'!$V:$V,"Met")/SUM(COUNTIFS('Base File'!$G:$G,"Contractual SLA",'Base File'!$H:$H,"yes",'Base File'!$C:$C,B10,'Base File'!$V:$V,"Met")+COUNTIFS('Base File'!$G:$G,"Contractual SLA",'Base File'!$H:$H,"yes",'Base File'!$C:$C,B10,'Base File'!$V:$V,"Not Met")),"-") -> - | Q10: =IFERROR(COUNTIFS('Base File'!$G:$G,"Internal KPI",'Base File'!$C:$C,B10,'Base File'!$V:$V,"Met")/SUM(COUNTIFS('Base File'!$G:$G,"Internal KPI",'Base File'!$C:$C,B10,'Base File'!$V:$V,"Met")+COUNTIFS('Base File'!$G:$G,"Internal KPI",'Base File'!$C:$C,B10,'Base File'!$V:$V,"Not Met")),"-") -> - | R10: =BR10 -> 0.7962963 | S10: =BS10 -> 0.88888889 | T10: =BT10 -> 0.5 | U10: =BU10 -> 0.78125 | V10: =IFERROR(COUNTIFS('Base File'!$X:$X,"Met",'Base File'!$C:$C,B10)/(COUNTIFS('Base File'!$X:$X,"Met",'Base File'!$C:$C,B10)+COUNTIFS('Base File'!$X:$X,"Not Met",'Base File'!$C:$C,B10)),"NR") -> NR | W10: =IFERROR(COUNTIFS('Base File'!$G:$G,"Contractual SLA",'Base File'!$H:$H,"No",'Base File'!$C:$C,B10,'Base File'!$X:$X,"Met")/SUM(COUNTIFS('Base File'!$G:$G,"Contractual SLA",'Base File'!$H:$H,"No",'Base File'!$C:$C,B10,'Base File'!$X:$X,"Met")+COUNTIFS('Base File'!$G:$G,"Contractual SLA",'Base File'!$H:$H,"No",'Base File'!$C:$C,B10,'Base File'!$X:$X,"Not Met")),"-") -> - | X10: =IFERROR(COUNTIFS('Base File'!$G:$G,"Contractual SLA",'Base File'!$H:$H,"Yes",'Base File'!$C:$C,B10,'Base File'!$X:$X,"Met")/SUM(COUNTIFS('Base File'!$G:$G,"Contractual SLA",'Base File'!$H:$H,"yes",'Base File'!$C:$C,B10,'Base File'!$X:$X,"Met")+COUNTIFS('Base File'!$G:$G,"Contractual SLA",'Base File'!$H:$H,"yes",'Base File'!$C:$C,B10,'Base File'!$X:$X,"Not Met")),"-") -> - | Y10: =IFERROR(COUNTIFS('Base File'!$G:$G,"Internal KPI",'Base File'!$C:$C,B10,'Base File'!$X:$X,"Met")/SUM(COUNTIFS('Base File'!$G:$G,"Internal KPI",'Base File'!$C:$C,B10,'Base File'!$X:$X,"Met")+COUNTIFS('Base File'!$G:$G,"Internal KPI",'Base File'!$C:$C,B10,'Base File'!$X:$X,"Not Met")),"-") -> - | Z10: =IFERROR(COUNTIFS('Base File'!$Z:$Z,"Met",'Base File'!$C:$C,B10)/(COUNTIFS('Base File'!$Z:$Z,"Met",'Base File'!$C:$C,B10)+COUNTIFS('Base File'!$Z:$Z,"Not Met",'Base File'!$C:$C,B10)),"NR") -> NR | AA10: =IFERROR(COUNTIFS('Base File'!$G:$G,"Contractual SLA",'Base File'!$H:$H,"No",'Base File'!$C:$C,B10,'Base File'!$Z:$Z,"Met")/SUM(COUNTIFS('Base File'!$G:$G,"Contractual SLA",'Base File'!$H:$H,"No",'Base File'!$C:$C,B10,'Base File'!$Z:$Z,"Met")+COUNTIFS('Base File'!$G:$G,"Contractual SLA",'Base File'!$H:$H,"No",'Base File'!$C:$C,B10,'Base File'!$Z:$Z,"Not Met")),"-") -> - | AB10: =IFERROR(COUNTIFS('Base File'!$G:$G,"Contractual SLA",'Base File'!$H:$H,"Yes",'Base File'!$C:$C,B10,'Base File'!$Z:$Z,"Met")/SUM(COUNTIFS('Base File'!$G:$G,"Contractual SLA",'Base File'!$H:$H,"yes",'Base File'!$C:$C,B10,'Base File'!$Z:$Z,"Met")+COUNTIFS('Base File'!$G:$G,"Contractual SLA",'Base File'!$H:$H,"yes",'Base File'!$C:$C,B10,'Base File'!$Z:$Z,"Not Met")),"-") -> - | AC10: =IFERROR(COUNTIFS('Base File'!$G:$G,"Internal KPI",'Base File'!$C:$C,B10,'Base File'!$Z:$Z,"Met")/SUM(COUNTIFS('Base File'!$G:$G,"Internal KPI",'Base File'!$C:$C,B10,'Base File'!$Z:$Z,"Met")+COUNTIFS('Base File'!$G:$G,"Internal KPI",'Base File'!$C:$C,B10,'Base File'!$Z:$Z,"Not Met")),"-") -> - | AD10: =24/30 -> 0.8 | AE10: =13/14 -> 0.92857143 | AF10: =IFERROR(COUNTIFS('Base File'!$G:$G,"Contractual SLA",'Base File'!$H:$H,"Yes",'Base File'!$C:$C,B10,'Base File'!$AB:$AB,"Met")/SUM(COUNTIFS('Base File'!$G:$G,"Contractual SLA",'Base File'!$H:$H,"yes",'Base File'!$C:$C,B10,'Base File'!$AB:$AB,"Met")+COUNTIFS('Base File'!$G:$G,"Contractual SLA",'Base File'!$H:$H,"yes",'Base File'!$C:$C,B10,'Base File'!$AB:$AB,"Not Met")),"-") -> - | AG10: =9/14 -> 0.64285714 | AH10: NR | AI10: NR | AJ10: NR | AK10: NR | AL10: =15/26 -> 0.57692308 | AM10: =6/8 -> 0.75 | AN10: =1/2 -> 0.5 | AO10: =8/16 -> 0.5 | AP10: =9/15 -> 0.6 | AQ10: - | AR10: =2/2 -> 1 | AS10: =7/13 -> 0.53846154 | AT10: =23/27 -> 0.85185185 | AU10: =8/8 -> 1 | AV10: =2/2 -> 1 | AW10: =13/17 -> 0.76470588 | AX10: =7/11 -> 0.63636364 | AY10: NR | AZ10: =1/2 -> 0.5 | BA10: =6/9 -> 0.66666667 | BB10: =14/18 -> 0.77777778 | BC10: =8/8 -> 1 | BD10: NR | BE10: =6/10 -> 0.6 | BF10: =23/31 -> 0.74193548 | BG10: =1/1 -> 1 | BH10: =2/4 -> 0.5 | BI10: =20/26 -> 0.76923077 | BJ10: =31/38 -> 0.81578947 | BK10: =10/11 -> 0.90909091 | BL10: =2/4 -> 0.5 | BM10: =19/23 -> 0.82608696 | BN10: =22/30 -> 0.73333333 | BO10: =4/4 -> 1 | BP10: =1/4 -> 0.25 | BQ10: =17/22 -> 0.77272727 | BR10: =43/54 -> 0.7962963 | BS10: =16/18 -> 0.88888889 | BT10: =2/4 -> 0.5 | BU10: =25/32 -> 0.78125 | BV10: =17/32 -> 0.53125 | BW10: =3/4 -> 0.75 | BX10: =2/4 -> 0.5 | BY10: =12/24 -> 0.5 | BZ10: =17/31 -> 0.5483871 | CA10: =3/4 -> 0.75 | CB10: =0/4 -> 0 | CC10: =14/23 -> 0.60869565 | CD10: =19/31 -> 0.61290323 | CE10: =3/4 -> 0.75 | CF10: =1/4 -> 0.25 | CG10: =15/23 -> 0.65217391 | CH10: =16/33 -> 0.48484848 | CI10: =3/4 -> 0.75 | CJ10: =0/4 -> 0 | CK10: =13/25 -> 0.52 | CL10: =26/43 -> 0.60465116 | CM10: =10/11 -> 0.90909091 | CN10: =0/4 -> 0 | CO10: =16/28 -> 0.57142857 | CP10: =23/33 -> 0.6969697 | CQ10: =4/4 -> 1 | CR10: =1/4 -> 0.25 | CS10: =18/25 -> 0.72 | CT10: =15/25 -> 0.6 | CU10: NA | CV10: =0/4 -> 0 | CW10: =15/21 -> 0.71428571 | DF10: =8/14 -> 0.57142857 | DG10: NR | DH10: =0/2 -> 0 | DI10: =8/12 -> 0.66666667 | DJ10: =8/11 -> 0.72727273 | DK10: NR | DL10: =0/2 -> 0 | DM10: =8/9 -> 0.88888889 | DN10: =10/13 -> 0.76923077 | DO10: NR | DP10: =1/2 -> 0.5 | DQ10: =9/11 -> 0.81818182 | DR10: =15/21 -> 0.71428571 | DS10: =3/4 -> 0.75 | DT10: =0/2 -> 0 | DU10: =12/25 -> 0.48
A11: 8 | B11: Bangalore | C11: Mahak | D11: Reported | E11: Not Validated | AL11: =9/12 -> 0.75 | AM11: =7/8 -> 0.875 | AN11: =2/4 -> 0.5 | AO11: - | AP11: =9/12 -> 0.75 | AQ11: =7/8 -> 0.875 | AR11: =2/4 -> 0.5 | AS11: - | AT11: =9/12 -> 0.75 | AU11: =8/8 -> 1 | AV11: =1/4 -> 0.25 | AW11: NA | AX11: NA | AY11: NA | AZ11: NA | BA11: NA | BB11: =9/12 -> 0.75 | BC11: =8/8 -> 1 | BD11: =1/4 -> 0.25 | BE11: - | BF11: =10/12 -> 0.83333333 | BG11: =8/8 -> 1 | BH11: =2/4 -> 0.5 | BI11: NA | BJ11: =11/12 -> 0.91666667 | BK11: =7/8 -> 0.875 | BL11: =4/4 -> 1 | BM11: NA | BN11: NR | BO11: NR | BP11: NR | BQ11: NA | BR11: =8/12 -> 0.66666667 | BS11: =8/8 -> 1 | BT11: =0/4 -> 0 | BU11: NA | BV11: NR | BW11: NR | BX11: NR | BY11: NR | BZ11: =8/10 -> 0.8 | CA11: =6/6 -> 1 | CB11: =2/4 -> 0.5 | CC11: NA | CD11: =7/10 -> 0.7 | CE11: =5/6 -> 0.83333333 | CF11: =2/4 -> 0.5 | CG11: NA | CH11: =8/10 -> 0.8 | CI11: =6/6 -> 1 | CJ11: =2/4 -> 0.5 | CK11: NA | CL11: 1 | CM11: 1 | CN11: 1 | CO11: NA | CP11: =10/10 -> 1 | CQ11: =6/6 -> 1 | CR11: =4/4 -> 1 | CS11: NA | CT11: =10/10 -> 1 | CU11: =6/6 -> 1 | CV11: =4/4 -> 1 | CW11: NA | DF11: =9/10 -> 0.9 | DG11: =5/6 -> 0.83333333 | DH11: 1 | DI11: NA | DJ11: NR | DK11: NR | DL11: NR | DM11: NA | DN11: =8/10 -> 0.8 | DO11: =4/6 -> 0.66666667 | DP11: =4/4 -> 1 | DQ11: NA | DR11: =8/10 -> 0.8 | DS11: =4/6 -> 0.66666667 | DT11: =4/4 -> 1 | DU11: NA
A12: 9 | B12: Mumbai & Gujrat | C12: Megha Joshi | D12: Not Reported | E12: Not Validated | AL12: =7/7 -> 1 | AM12: - | AN12: =7/7 -> 1 | AO12: - | AP12: =11/15 -> 0.73333333 | AQ12: - | AR12: =7/7 -> 1 | AS12: =4/8 -> 0.5 | AT12: NR | AU12: - | AV12: - | AW12: NR | AX12: NR | AY12: - | AZ12: - | BA12: NR | BB12: =9/13 -> 0.69230769 | BC12: =3/5 -> 0.6 | BD12: - | BE12: =6/8 -> 0.75 | BF12: =12/14 -> 0.85714286 | BG12: =5/5 -> 1 | BH12: - | BI12: =7/9 -> 0.77777778 | BJ12: =11/14 -> 0.78571429 | BK12: =4/5 -> 0.8 | BL12: - | BM12: =7/9 -> 0.77777778 | BN12: NR | BO12: NR | BP12: - | BQ12: NR | BR12: =12/14 -> 0.85714286 | BS12: =5/5 -> 1 | BT12: - | BU12: =7/9 -> 0.77777778 | BV12: =10/13 -> 0.76923077 | BW12: =3/4 -> 0.75 | BX12: NA | BY12: =7/9 -> 0.77777778 | BZ12: NR | CA12: NR | CB12: NA | CC12: NR | CD12: NR | CE12: NR | CF12: NA | CG12: NR | CH12: NR | CI12: NR | CJ12: NA | CK12: NR | CL12: NR | CM12: NR | CN12: - | CO12: NR | CP12: NR | CQ12: NR | CR12: - | CS12: NR | CT12: NR | CU12: NR | CV12: - | CW12: NR | DF12: NR | DG12: NR | DH12: NR | DI12: NR | DJ12: NR | DK12: NR | DL12: NR | DM12: NR | DN12: =5/12 -> 0.41666667 | DO12: =1/4 -> 0.25 | DP12: - | DQ12: =4/8 -> 0.5 | DR12: =3/12 -> 0.25 | DS12: =0/4 -> 0 | DT12: - | DU12: =3/8 -> 0.375
A13: 10 | B13: North | C13: Kirti | D13: Reported | E13: Partially Validated | AL13: =7/7 -> 1 | AM13: - | AN13: =7/7 -> 1 | AO13: - | AP13: =11/15 -> 0.73333333 | AQ13: - | AR13: =7/7 -> 1 | AS13: =4/8 -> 0.5 | AT13: NR | AU13: - | AV13: - | AW13: NR | AX13: NR | AY13: - | AZ13: - | BA13: NR | BB13: =4/7 -> 0.57142857 | BC13: - | BD13: - | BE13: =4/7 -> 0.57142857 | BF13: =4/7 -> 0.57142857 | BG13: - | BH13: - | BI13: =4/7 -> 0.57142857 | BJ13: =4/7 -> 0.57142857 | BK13: - | BL13: - | BM13: =4/7 -> 0.57142857 | BN13: =5/7 -> 0.71428571 | BO13: - | BP13: - | BQ13: =4/7 -> 0.57142857 | BR13: =3/7 -> 0.42857143 | BS13: - | BT13: - | BU13: =4/7 -> 0.57142857 | BV13: =5/7 -> 0.71428571 | BW13: NA | BX13: NA | BY13: =5/7 -> 0.71428571 | BZ13: =5/7 -> 0.71428571 | CA13: NA | CB13: NA | CC13: =5/7 -> 0.71428571 | CD13: =4/7 -> 0.57142857 | CE13: NA | CF13: NA | CG13: =4/7 -> 0.57142857 | CH13: =6/7 -> 0.85714286 | CI13: NA | CJ13: NA | CK13: =6/7 -> 0.85714286 | CL13: =6/7 -> 0.85714286 | CM13: - | CN13: - | CO13: =6/7 -> 0.85714286 | CP13: =5/7 -> 0.71428571 | CQ13: - | CR13: - | CS13: =5/7 -> 0.71428571 | CT13: =5/7 -> 0.71428571 | CU13: - | CV13: - | CW13: =5/7 -> 0.71428571 | DF13: =4/7 -> 0.57142857 | DG13: NA | DH13: NA | DI13: =4/7 -> 0.57142857 | DJ13: =4/7 -> 0.57142857 | DK13: NA | DL13: NA | DM13: =4/7 -> 0.57142857 | DN13: =4/7 -> 0.57142857 | DO13: - | DP13: - | DQ13: =4/7 -> 0.57142857 | DR13: =6/8 -> 0.75 | DS13: - | DT13: - | DU13: =6/8 -> 0.75
A14: 11 | B14: Bangalore | C14: Reddy Bapi | D14: Reported | E14: Not Validated | BJ14: =8/8 -> 1 | BK14: - | BL14: =7/7 -> 1 | BM14: =1/1 -> 1 | BN14: =8/8 -> 1 | BO14: - | BP14: =7/7 -> 1 | BQ14: =1/1 -> 1 | BR14: =8/8 -> 1 | BS14: - | BT14: =7/7 -> 1 | BU14: =1/1 -> 1 | BV14: =8/8 -> 1 | BW14: NA | BX14: =7/7 -> 1 | BY14: =1/1 -> 1 | BZ14: NA | CA14: NA | CB14: NA | CC14: NA | CD14: NA | CE14: NA | CF14: NA | CG14: NA | CH14: NA | CI14: NA | CJ14: NA | CK14: NA | CL14: =8/8 -> 1 | CM14: - | CN14: =7/7 -> 1 | CO14: =1/1 -> 1 | CP14: =8/8 -> 1 | CQ14: - | CR14: =7/7 -> 1 | CS14: =1/1 -> 1 | CT14: =8/8 -> 1 | CU14: - | CV14: =7/7 -> 1 | CW14: =1/1 -> 1 | DF14: =6/7 -> 0.85714286 | DG14: NA | DH14: =6/7 -> 0.85714286 | DI14: NA | DJ14: =6/7 -> 0.85714286 | DK14: NA | DL14: =6/7 -> 0.85714286 | DM14: NA | DN14: =7/8 -> 0.875 | DO14: - | DP14: =6/7 -> 0.85714286 | DQ14: =1/1 -> 1 | DR14: =7/8 -> 0.875 | DS14: - | DT14: =6/7 -> 0.85714286 | DU14: =1/1 -> 1
A15: 12 | B15: Mumbai & Gujrat | C15: Geetu Lalwani | D15: Partially Reported | E15: Partially Validated | BZ15: =24/45 -> 0.53333333 | CA15: NR | CB15: NR | CC15: =24/45 -> 0.53333333 | CD15: =25/46 -> 0.54347826 | CE15: NR | CF15: NR | CG15: =25/46 -> 0.54347826 | CH15: =19/37 -> 0.51351351 | CI15: NR | CJ15: NR | CK15: =19/37 -> 0.51351351 | CL15: =17/33 -> 0.51515152 | CM15: - | CN15: - | CO15: =17/33 -> 0.51515152 | CP15: =28/40 -> 0.7 | CQ15: NR | CR15: NR | CS15: =28/40 -> 0.7 | CT15: =29/48 -> 0.60416667 | CU15: NA | CV15: NA | CW15: =29/48 -> 0.60416667 | DF15: =31/63 -> 0.49206349 | DG15: =1/2 -> 0.5 | DH15: 0 | DI15: =30/60 -> 0.5 | DJ15: =8/15 -> 0.53333333 | DK15: =1/2 -> 0.5 | DL15: NR | DM15: =7/13 -> 0.53846154 | DN15: =30/62 -> 0.48387097 | DO15: =0/2 -> 0 | DP15: NR | DQ15: =30/60 -> 0.5 | DR15: =31/64 -> 0.484375 | DS15: 0 | DT15: NR | DU15: =31/62 -> 0.5
A16: 13 | B16: Mumbai & Gujrat | C16: Ankit Dave | D16: Reported | E16: Not Validated | DF16: =3/8 -> 0.375 | DG16: - | DH16: - | DI16: =3/8 -> 0.375 | DJ16: NR | DK16: - | DL16: - | DM16: NR | DN16: =8/8 -> 1 | DO16: - | DP16: - | DQ16: =8/8 -> 1 | DR16: NR | DS16: - | DT16: - | DU16: =4/8 -> 0.5

Sheet Account Summary
L2: Mar 2025 | M2: Mar 2025 | N2: Mar 2025 | O2: Mar 2025 | P2: April 2025 | Q2: April 2025 | R2: April 2025 | S2: April 2025 | T2: May 2025 | U2: May 2025 | V2: May 2025 | W2: May 2025 | X2: June 2025 | Y2: June 2025 | Z2: June 2025 | AA2: June 2025 | AB2: AMJ 2025 | AC2: AMJ 2025 | AD2: AMJ 2025 | AE2: AMJ 2025 | AF2: July 2025 | AG2: July 2025 | AH2: July 2025 | AI2: July 2025 | AJ2: Aug 2025 | AK2: Aug 2025 | AL2: Aug 2025 | AM2: Aug 2025 | AN2: Sep 2025 | AO2: Sep 2025 | AP2: Sep 2025 | AQ2: Sep 2025 | AR2: JAS 2025 | AS2: JAS 2025 | AT2: JAS 2025 | AU2: JAS 2025 | AV2: Oct 2025 | AW2: Oct 2025 | AX2: Oct 2025 | AY2: Oct 2025 | AZ2: Nov 2025 | BA2: Nov 2025 | BB2: Nov 2025 | BC2: Nov 2025 | BD2: Dec 2025 | BE2: Dec 2025 | BF2: Dec 2025 | BG2: Dec 2025 | BH2: OND 2025 | BI2: OND 2025 | BJ2: OND 2025 | BK2: OND 2025 | BL2: Jan 2026 | BM2: Jan 2026 | BN2: Jan 2026 | BO2: Jan 2026 | BP2: YTD 2025-2026 | BQ2: YTD 2025-2026 | BR2: YTD 2025-2026 | BS2: YTD 2025-2026
B3: Serial # | C3: Account Name | D3: Region | E3: Region | F3: BE SPOC | G3: Go-Live Date | H3: Tenure - In Weeks | I3: PH | J3: Reporting Status | K3: Validation Status | L3: Overall MET% | M3: Contractual Non- Penalty MET% | N3: Contractual Penalty MET% | O3: Internal KPI MET% | P3: Overall MET% | Q3: Contractual Non- Penalty MET% | R3: Contractual Penalty MET% | S3: Internal KPI MET% | T3: Overall MET% | U3: Contractual NonNA Penalty MET% | V3: Contractual Penalty MET% | W3: Internal KPI MET% | X3: Overall MET% | Y3: Contractual Non Penalty MET% | Z3: Contractual Penalty MET% | AA3: Internal KPI MET% | AB3: Overall MET% | AC3: Contractual NonNA Penalty MET% | AD3: Contractual Penalty MET% | AE3: Internal KPI MET% | AF3: Overall MET% | AG3: Contractual Non Penalty MET% | AH3: Contractual Penalty MET% | AI3: Internal KPI MET% | AJ3: Overall MET% | AK3: Contractual Non Penalty MET% | AL3: Contractual Penalty MET% | AM3: Internal KPI MET% | AN3: Overall MET% | AO3: Contractual Non Penalty MET% | AP3: Contractual Penalty MET% | AQ3: Internal KPI MET% | AR3: Overall MET% | AS3: Contractual Non Penalty MET% | AT3: Contractual Penalty MET% | AU3: Internal KPI MET% | AV3: Overall MET% | AW3: Contractual Non Penalty MET% | AX3: Contractual Penalty MET% | AY3: Internal KPI MET% | AZ3: Overall MET% | BA3: Contractual Non Penalty MET% | BB3: Contractual Penalty MET% | BC3: Internal KPI MET% | BD3: Overall MET% | BE3: Contractual Non Penalty MET% | BF3: Contractual Penalty MET% | BG3: Internal KPI MET% | BH3: Overall MET% | BI3: Contractual Non Penalty MET% | BJ3: Contractual Penalty MET% | BK3: Internal KPI MET% | BL3: Overall MET% | BM3: Contractual Non Penalty MET% | BN3: Contractual Penalty MET% | BO3: Internal KPI MET% | BP3: Overall MET% | BQ3: Contractual Non Penalty MET% | BR3: Contractual Penalty MET% | BS3: Internal KPI MET%
B4: 1 | C4: Honeywell | D4: Bangalore | E4: South 1 | F4: Himanshu Srivastava & Mehvish Naz | I4: Bapi Reddy | J4: Reported | K4: Not Validated | L4: =IFERROR(COUNTIFS('Base File'!$AR:$AR,"Met",'Base File'!$B:$B,'Account Summary'!C4)/(COUNTIFS('Base File'!$AR:$AR,"Met",'Base File'!$B:$B,'Account Summary'!C4)+COUNTIFS('Base File'!$AR:$AR,"Not Met",'Base File'!$B:$B,'Account Summary'!C4)),"NR") -> 1 | M4: =IFERROR(COUNTIFS('Base File'!$G:$G,"Contractual SLA",'Base File'!$H:$H,"No",'Base File'!$B:$B,'Account Summary'!$C4,'Base File'!$AR:$AR,"Met")/SUM(COUNTIFS('Base File'!$G:$G,"Contractual SLA",'Base File'!$H:$H,"No",'Base File'!$B:$B,'Account Summary'!$C4,'Base File'!$AR:$AR,"Met")+COUNTIFS('Base File'!$G:$G,"Contractual SLA",'Base File'!$H:$H,"No",'Base File'!$B:$B,'Account Summary'!$C4,'Base File'!$AR:$AR,"Not Met")),"-") -> - | N4: =IFERROR(COUNTIFS('Base File'!$G:$G,"Contractual SLA",'Base File'!$H:$H,"Yes",'Base File'!$B:$B,'Account Summary'!$C4,'Base File'!$AR:$AR,"Met")/SUM(COUNTIFS('Base File'!$G:$G,"Contractual SLA",'Base File'!$H:$H,"yes",'Base File'!$B:$B,'Account Summary'!$C4,'Base File'!$AR:$AR,"Met")+COUNTIFS('Base File'!$G:$G,"Contractual SLA",'Base File'!$H:$H,"yes",'Base File'!$B:$B,'Account Summary'!$C4,'Base File'!$AR:$AR,"Not Met")),"-") -> 1 | O4: =IFERROR(COUNTIFS('Base File'!$G:$G,"Internal KPI",'Base File'!$B:$B,'Account Summary'!$C4,'Base File'!$AR:$AR,"Met")/SUM(COUNTIFS('Base File'!$G:$G,"Internal KPI",'Base File'!$B:$B,'Account Summary'!$C4,'Base File'!$AR:$AR,"Met")+COUNTIFS('Base File'!$G:$G,"Internal KPI",'Base File'!$B:$B,'Account Summary'!$C4,'Base File'!$AR:$AR,"Not Met")),"-") -> 1 | P4: =IFERROR(COUNTIFS('Base File'!$AV:$AV,"Met",'Base File'!$B:$B,'Account Summary'!C4)/(COUNTIFS('Base File'!$AV:$AV,"Met",'Base File'!$B:$B,'Account Summary'!C4)+COUNTIFS('Base File'!$AV:$AV,"Not Met",'Base File'!$B:$B,'Account Summary'!C4)),"NR") -> 1 | Q4: =IFERROR(COUNTIFS('Base File'!$G:$G,"Contractual SLA",'Base File'!$H:$H,"No",'Base File'!$B:$B,'Account Summary'!$C4,'Base File'!$AV:$AV,"Met")/SUM(COUNTIFS('Base File'!$G:$G,"Contractual SLA",'Base File'!$H:$H,"No",'Base File'!$B:$B,'Account Summary'!$C4,'Base File'!$AV:$AV,"Met")+COUNTIFS('Base File'!$G:$G,"Contractual SLA",'Base File'!$H:$H,"No",'Base File'!$B:$B,'Account Summary'!$C4,'Base File'!$AV:$AV,"Not Met")),"-") -> - | R4: =IFERROR(COUNTIFS('Base File'!$G:$G,"Contractual SLA",'Base File'!$H:$H,"Yes",'Base File'!$B:$B,'Account Summary'!$C4,'Base File'!$AV:$AV,"Met")/SUM(COUNTIFS('Base File'!$G:$G,"Contractual SLA",'Base File'!$H:$H,"yes",'Base File'!$B:$B,'Account Summary'!$C4,'Base File'!$AV:$AV,"Met")+COUNTIFS('Base File'!$G:$G,"Contractual SLA",'Base File'!$H:$H,"yes",'Base File'!$B:$B,'Account Summary'!$C4,'Base File'!$AV:$AV,"Not Met")),"-") -> 1 | S4: =IFERROR(COUNTIFS('Base File'!$G:$G,"Internal KPI",'Base File'!$B:$B,'Account Summary'!$C4,'Base File'!$AV:$AV,"Met")/SUM(COUNTIFS('Base File'!$G:$G,"Internal KPI",'Base File'!$B:$B,'Account Summary'!$C4,'Base File'!$AV:$AV,"Met")+COUNTIFS('Base File'!$G:$G,"Internal KPI",'Base File'!$B:$B,'Account Summary'!$C4,'Base File'!$AV:$AV,"Not Met")),"-") -> 1 | T4: NA | U4: =IFERROR(COUNTIFS('Base File'!$G:$G,"Contractual SLA",'Base File'!$H:$H,"No",'Base File'!$B:$B,'Account Summary'!$C4,'Base File'!$AX:$AX,"Met")/SUM(COUNTIFS('Base File'!$G:$G,"Contractual SLA",'Base File'!$H:$H,"No",'Base File'!$B:$B,'Account Summary'!$C4,'Base File'!$AX:$AX,"Met")+COUNTIFS('Base File'!$G:$G,"Contractual SLA",'Base File'!$H:$H,"No",'Base File'!$B:$B,'Account Summary'!$C4,'Base File'!$AX:$AX,"Not Met")),"NA") -> NA | V4: =IFERROR(COUNTIFS('Base File'!$G:$G,"Contractual SLA",'Base File'!$H:$H,"Yes",'Base File'!$B:$B,'Account Summary'!$C4,'Base File'!$AX:$AX,"Met")/SUM(COUNTIFS('Base File'!$G:$G,"Contractual SLA",'Base File'!$H:$H,"yes",'Base File'!$B:$B,'Account Summary'!$C4,'Base File'!$AX:$AX,"Met")+COUNTIFS('Base File'!$G:$G,"Contractual SLA",'Base File'!$H:$H,"yes",'Base File'!$B:$B,'Account Summary'!$C4,'Base File'!$AX:$AX,"Not Met")),"NA") -> NA | W4: =IFERROR(COUNTIFS('Base File'!$G:$G,"Internal KPI",'Base File'!$B:$B,'Account Summary'!$C4,'Base File'!$AX:$AX,"Met")/SUM(COUNTIFS('Base File'!$G:$G,"Internal KPI",'Base File'!$B:$B,'Account Summary'!$C4,'Base File'!$AX:$AX,"Met")+COUNTIFS('Base File'!$G:$G,"Internal KPI",'Base File'!$B:$B,'Account Summary'!$C4,'Base File'!$AX:$AX,"Not Met")),"NA") -> NA | X4: =IFERROR(COUNTIFS('Base File'!$G:$G,"Internal KPI",'Base File'!$B:$B,'Account Summary'!$C4,'Base File'!$AX:$AX,"Met")/SUM(COUNTIFS('Base File'!$G:$G,"Internal KPI",'Base File'!$B:$B,'Account Summary'!$C4,'Base File'!$AX:$AX,"Met")+COUNTIFS('Base File'!$G:$G,"Internal KPI",'Base File'!$B:$B,'Account Summary'!$C4,'Base File'!$AX:$AX,"Not Met")),"NA") -> NA | Y4: - | Z4: =IFERROR(COUNTIFS('Base File'!$G:$G,"Internal KPI",'Base File'!$B:$B,'Account Summary'!$C4,'Base File'!$AX:$AX,"Met")/SUM(COUNTIFS('Base File'!$G:$G,"Internal KPI",'Base File'!$B:$B,'Account Summary'!$C4,'Base File'!$AX:$AX,"Met")+COUNTIFS('Base File'!$G:$G,"Internal KPI",'Base File'!$B:$B,'Account Summary'!$C4,'Base File'!$AX:$AX,"Not Met")),"NA") -> NA | AA4: =IFERROR(COUNTIFS('Base File'!$G:$G,"Internal KPI",'Base File'!$B:$B,'Account Summary'!$C4,'Base File'!$AX:$AX,"Met")/SUM(COUNTIFS('Base File'!$G:$G,"Internal KPI",'Base File'!$B:$B,'Account Summary'!$C4,'Base File'!$AX:$AX,"Met")+COUNTIFS('Base File'!$G:$G,"Internal KPI",'Base File'!$B:$B,'Account Summary'!$C4,'Base File'!$AX:$AX,"Not Met")),"NA") -> NA | AB4: =IFERROR(COUNTIFS('Base File'!$G:$G,"Internal KPI",'Base File'!$B:$B,'Account Summary'!$C4,'Base File'!$AX:$AX,"Met")/SUM(COUNTIFS('Base File'!$G:$G,"Internal KPI",'Base File'!$B:$B,'Account Summary'!$C4,'Base File'!$AX:$AX,"Met")+COUNTIFS('Base File'!$G:$G,"Internal KPI",'Base File'!$B:$B,'Account Summary'!$C4,'Base File'!$AX:$AX,"Not Met")),"NA") -> NA | AC4: - | AD4: NA | AE4: NA | AF4: =IFERROR(COUNTIFS('Base File'!$G:$G,"Internal KPI",'Base File'!$B:$B,'Account Summary'!$C4,'Base File'!$AX:$AX,"Met")/SUM(COUNTIFS('Base File'!$G:$G,"Internal KPI",'Base File'!$B:$B,'Account Summary'!$C4,'Base File'!$AX:$AX,"Met")+COUNTIFS('Base File'!$G:$G,"Internal KPI",'Base File'!$B:$B,'Account Summary'!$C4,'Base File'!$AX:$AX,"Not Met")),"NA") -> NA | AG4: - | AH4: =IFERROR(COUNTIFS('Base File'!$G:$G,"Internal KPI",'Base File'!$B:$B,'Account Summary'!$C4,'Base File'!$AX:$AX,"Met")/SUM(COUNTIFS('Base File'!$G:$G,"Internal KPI",'Base File'!$B:$B,'Account Summary'!$C4,'Base File'!$AX:$AX,"Met")+COUNTIFS('Base File'!$G:$G,"Internal KPI",'Base File'!$B:$B,'Account Summary'!$C4,'Base File'!$AX:$AX,"Not Met")),"NA") -> NA | AI4: =IFERROR(COUNTIFS('Base File'!$G:$G,"Internal KPI",'Base File'!$B:$B,'Account Summary'!$C4,'Base File'!$AX:$AX,"Met")/SUM(COUNTIFS('Base File'!$G:$G,"Internal KPI",'Base File'!$B:$B,'Account Summary'!$C4,'Base File'!$AX:$AX,"Met")+COUNTIFS('Base File'!$G:$G,"Internal KPI",'Base File'!$B:$B,'Account Summary'!$C4,'Base File'!$AX:$AX,"Not Met")),"NA") -> NA | AJ4: =IFERROR(COUNTIFS('Base File'!$BF:$BF,"Met",'Base File'!$B:$B,'Account Summary'!C4)/(COUNTIFS('Base File'!$BF:$BF,"Met",'Base File'!$B:$B,'Account Summary'!C4)+COUNTIFS('Base File'!$BF:$BF,"Not Met",'Base File'!$B:$B,'Account Summary'!C4)),"NR") -> 1 | AK4: =IFERROR(COUNTIFS('Base File'!$G:$G,"Contractual SLA",'Base File'!$H:$H,"No",'Base File'!$B:$B,'Account Summary'!$C4,'Base File'!$BF:$BF,"Met")/SUM(COUNTIFS('Base File'!$G:$G,"Contractual SLA",'Base File'!$H:$H,"No",'Base File'!$B:$B,'Account Summary'!$C4,'Base File'!$BF:$BF,"Met")+COUNTIFS('Base File'!$G:$G,"Contractual SLA",'Base File'!$H:$H,"No",'Base File'!$B:$B,'Account Summary'!$C4,'Base File'!$BF:$BF,"Not Met")),"-") -> - | AL4: =IFERROR(COUNTIFS('Base File'!$G:$G,"Contractual SLA",'Base File'!$H:$H,"Yes",'Base File'!$B:$B,'Account Summary'!$C4,'Base File'!$BF:$BF,"Met")/SUM(COUNTIFS('Base File'!$G:$G,"Contractual SLA",'Base File'!$H:$H,"yes",'Base File'!$B:$B,'Account Summary'!$C4,'Base File'!$BF:$BF,"Met")+COUNTIFS('Base File'!$G:$G,"Contractual SLA",'Base File'!$H:$H,"yes",'Base File'!$B:$B,'Account Summary'!$C4,'Base File'!$BF:$BF,"Not Met")),"-") -> 1 | AM4: =IFERROR(COUNTIFS('Base File'!$G:$G,"Internal KPI",'Base File'!$B:$B,'Account Summary'!$C4,'Base File'!$BF:$BF,"Met")/SUM(COUNTIFS('Base File'!$G:$G,"Internal KPI",'Base File'!$B:$B,'Account Summary'!$C4,'Base File'!$BF:$BF,"Met")+COUNTIFS('Base File'!$G:$G,"Internal KPI",'Base File'!$B:$B,'Account Summary'!$C4,'Base File'!$BF:$BF,"Not Met")),"-") -> 1 | AN4: =IFERROR(COUNTIFS('Base File'!$BH:$BH,"Met",'Base File'!$B:$B,'Account Summary'!C4)/(COUNTIFS('Base File'!$BH:$BH,"Met",'Base File'!$B:$B,'Account Summary'!C4)+COUNTIFS('Base File'!$BH:$BH,"Not Met",'Base File'!$B:$B,'Account Summary'!C4)),"NR") -> 1 | AO4: =IFERROR(COUNTIFS('Base File'!$G:$G,"Contractual SLA",'Base File'!$H:$H,"No",'Base File'!$B:$B,'Account Summary'!$C4,'Base File'!$BH:$BH,"Met")/SUM(COUNTIFS('Base File'!$G:$G,"Contractual SLA",'Base File'!$H:$H,"No",'Base File'!$B:$B,'Account Summary'!$C4,'Base File'!$BH:$BH,"Met")+COUNTIFS('Base File'!$G:$G,"Contractual SLA",'Base File'!$H:$H,"No",'Base File'!$B:$B,'Account Summary'!$C4,'Base File'!$BH:$BH,"Not Met")),"-") -> - | AP4: =IFERROR(COUNTIFS('Base File'!$G:$G,"Contractual SLA",'Base File'!$H:$H,"Yes",'Base File'!$B:$B,'Account Summary'!$C4,'Base File'!$BH:$BH,"Met")/SUM(COUNTIFS('Base File'!$G:$G,"Contractual SLA",'Base File'!$H:$H,"yes",'Base File'!$B:$B,'Account Summary'!$C4,'Base File'!$BH:$BH,"Met")+COUNTIFS('Base File'!$G:$G,"Contractual SLA",'Base File'!$H:$H,"yes",'Base File'!$B:$B,'Account Summary'!$C4,'Base File'!$BH:$BH,"Not Met")),"-") -> 1 | AQ4: =IFERROR(COUNTIFS('Base File'!$G:$G,"Internal KPI",'Base File'!$B:$B,'Account Summary'!$C4,'Base File'!$BH:$BH,"Met")/SUM(COUNTIFS('Base File'!$G:$G,"Internal KPI",'Base File'!$B:$B,'Account Summary'!$C4,'Base File'!$BH:$BH,"Met")+COUNTIFS('Base File'!$G:$G,"Internal KPI",'Base File'!$B:$B,'Account Summary'!$C4,'Base File'!$BH:$BH,"Not Met")),"-") -> 1 | AR4: =IFERROR(COUNTIFS('Base File'!$BJ:$BJ,"Met",'Base File'!$B:$B,'Account Summary'!C4)/(COUNTIFS('Base File'!$BJ:$BJ,"Met",'Base File'!$B:$B,'Account Summary'!C4)+COUNTIFS('Base File'!$BJ:$BJ,"Not Met",'Base File'!$B:$B,'Account Summary'!C4)),"NR") -> 1 | AS4: =IFERROR(COUNTIFS('Base File'!$G:$G,"Contractual SLA",'Base File'!$H:$H,"No",'Base File'!$B:$B,'Account Summary'!$C4,'Base File'!$BJ:$BJ,"Met")/SUM(COUNTIFS('Base File'!$G:$G,"Contractual SLA",'Base File'!$H:$H,"No",'Base File'!$B:$B,'Account Summary'!$C4,'Base File'!$BJ:$BJ,"Met")+COUNTIFS('Base File'!$G:$G,"Contractual SLA",'Base File'!$H:$H,"No",'Base File'!$B:$B,'Account Summary'!$C4,'Base File'!$BJ:$BJ,"Not Met")),"-") -> - | AT4: =IFERROR(COUNTIFS('Base File'!$G:$G,"Contractual SLA",'Base File'!$H:$H,"Yes",'Base File'!$B:$B,'Account Summary'!$C4,'Base File'!$BJ:$BJ,"Met")/SUM(COUNTIFS('Base File'!$G:$G,"Contractual SLA",'Base File'!$H:$H,"yes",'Base File'!$B:$B,'Account Summary'!$C4,'Base File'!$BJ:$BJ,"Met")+COUNTIFS('Base File'!$G:$G,"Contractual SLA",'Base File'!$H:$H,"yes",'Base File'!$B:$B,'Account Summary'!$C4,'Base File'!$BJ:$BJ,"Not Met")),"-") -> 1 | AU4: =IFERROR(COUNTIFS('Base File'!$G:$G,"Internal KPI",'Base File'!$B:$B,'Account Summary'!$C4,'Base File'!$BJ:$BJ,"Met")/SUM(COUNTIFS('Base File'!$G:$G,"Internal KPI",'Base File'!$B:$B,'Account Summary'!$C4,'Base File'!$BJ:$BJ,"Met")+COUNTIFS('Base File'!$G:$G,"Internal KPI",'Base File'!$B:$B,'Account Summary'!$C4,'Base File'!$BJ:$BJ,"Not Met")),"-") -> 1 | AV4: =IFERROR(COUNTIFS('Base File'!$BL:$BL,"Met",'Base File'!$B:$B,'Account Summary'!C4)/(COUNTIFS('Base File'!$BL:$BL,"Met",'Base File'!$B:$B,'Account Summary'!C4)+COUNTIFS('Base File'!$BL:$BL,"Not Met",'Base File'!$B:$B,'Account Summary'!C4)),"NR") -> 0.85714286 | AW4: =IFERROR(COUNTIFS('Base File'!$G:$G,"Contractual SLA",'Base File'!$H:$H,"No",'Base File'!$B:$B,'Account Summary'!$C4,'Base File'!$BL:$BL,"Met")/SUM(COUNTIFS('Base File'!$G:$G,"Contractual SLA",'Base File'!$H:$H,"No",'Base File'!$B:$B,'Account Summary'!$C4,'Base File'!$BL:$BL,"Met")+COUNTIFS('Base File'!$G:$G,"Contractual SLA",'Base File'!$H:$H,"No",'Base File'!$B:$B,'Account Summary'!$C4,'Base File'!$BL:$BL,"Not Met")),"-") -> - | AX4: =IFERROR(COUNTIFS('Base File'!$G:$G,"Contractual SLA",'Base File'!$H:$H,"Yes",'Base File'!$B:$B,'Account Summary'!$C4,'Base File'!$BL:$BL,"Met")/SUM(COUNTIFS('Base File'!$G:$G,"Contractual SLA",'Base File'!$H:$H,"yes",'Base File'!$B:$B,'Account Summary'!$C4,'Base File'!$BL:$BL,"Met")+COUNTIFS('Base File'!$G:$G,"Contractual SLA",'Base File'!$H:$H,"yes",'Base File'!$B:$B,'Account Summary'!$C4,'Base File'!$BL:$BL,"Not Met")),"-") -> 0.85714286 | AY4: =IFERROR(COUNTIFS('Base File'!$G:$G,"Internal KPI",'Base File'!$B:$B,'Account Summary'!$C4,'Base File'!$BL:$BL,"Met")/SUM(COUNTIFS('Base File'!$G:$G,"Internal KPI",'Base File'!$B:$B,'Account Summary'!$C4,'Base File'!$BL:$BL,"Met")+COUNTIFS('Base File'!$G:$G,"Internal KPI",'Base File'!$B:$B,'Account Summary'!$C4,'Base File'!$BL:$BL,"Not Met")),"-") -> - | AZ4: 1 | BA4: - | BB4: 1 | BC4: NA | BD4: =IFERROR(COUNTIFS('Base File'!$BP:$BP,"Met",'Base File'!$B:$B,'Account Summary'!C4)/(COUNTIFS('Base File'!$BP:$BP,"Met",'Base File'!$B:$B,'Account Summary'!C4)+COUNTIFS('Base File'!$BP:$BP,"Not Met",'Base File'!$B:$B,'Account Summary'!C4)),"NR") -> 0.85714286 | BE4: =IFERROR(COUNTIFS('Base File'!$G:$G,"Contractual SLA",'Base File'!$H:$H,"No",'Base File'!$B:$B,'Account Summary'!$C4,'Base File'!$BP:$BP,"Met")/SUM(COUNTIFS('Base File'!$G:$G,"Contractual SLA",'Base File'!$H:$H,"No",'Base File'!$B:$B,'Account Summary'!$C4,'Base File'!$BP:$BP,"Met")+COUNTIFS('Base File'!$G:$G,"Contractual SLA",'Base File'!$H:$H,"No",'Base File'!$B:$B,'Account Summary'!$C4,'Base File'!$BP:$BP,"Not Met")),"-") -> - | BF4: =IFERROR(COUNTIFS('Base File'!$G:$G,"Contractual SLA",'Base File'!$H:$H,"Yes",'Base File'!$B:$B,'Account Summary'!$C4,'Base File'!$BP:$BP,"Met")/SUM(COUNTIFS('Base File'!$G:$G,"Contractual SLA",'Base File'!$H:$H,"yes",'Base File'!$B:$B,'Account Summary'!$C4,'Base File'!$BP:$BP,"Met")+COUNTIFS('Base File'!$G:$G,"Contractual SLA",'Base File'!$H:$H,"yes",'Base File'!$B:$B,'Account Summary'!$C4,'Base File'!$BP:$BP,"Not Met")),"-") -> 0.85714286 | BG4: NA | BH4: =IFERROR(COUNTIFS('Base File'!$BR:$BR,"Met",'Base File'!$B:$B,'Account Summary'!C4)/(COUNTIFS('Base File'!$BR:$BR,"Met",'Base File'!$B:$B,'Account Summary'!C4)+COUNTIFS('Base File'!$BR:$BR,"Not Met",'Base File'!$B:$B,'Account Summary'!C4)),"NR") -> 0.85714286 | BI4: =IFERROR(COUNTIFS('Base File'!$G:$G,"Contractual SLA",'Base File'!$H:$H,"No",'Base File'!$B:$B,'Account Summary'!$C4,'Base File'!$BR:$BR,"Met")/SUM(COUNTIFS('Base File'!$G:$G,"Contractual SLA",'Base File'!$H:$H,"No",'Base File'!$B:$B,'Account Summary'!$C4,'Base File'!$BR:$BR,"Met")+COUNTIFS('Base File'!$G:$G,"Contractual SLA",'Base File'!$H:$H,"No",'Base File'!$B:$B,'Account Summary'!$C4,'Base File'!$BR:$BR,"Not Met")),"-") -> - | BJ4: 0.86 | BK4: NA | BL4: =IFERROR(COUNTIFS('Base File'!$BT:$BT,"Met",'Base File'!$B:$B,'Account Summary'!C4)/(COUNTIFS('Base File'!$BT:$BT,"Met",'Base File'!$B:$B,'Account Summary'!C4)+COUNTIFS('Base File'!$BT:$BT,"Not Met",'Base File'!$B:$B,'Account Summary'!C4)),"NR") -> 0.875 | BM4: =IFERROR(COUNTIFS('Base File'!$G:$G,"Contractual SLA",'Base File'!$H:$H,"No",'Base File'!$B:$B,'Account Summary'!$C4,'Base File'!$BT:$BT,"Met")/SUM(COUNTIFS('Base File'!$G:$G,"Contractual SLA",'Base File'!$H:$H,"No",'Base File'!$B:$B,'Account Summary'!$C4,'Base File'!$BT:$BT,"Met")+COUNTIFS('Base File'!$G:$G,"Contractual SLA",'Base File'!$H:$H,"No",'Base File'!$B:$B,'Account Summary'!$C4,'Base File'!$BT:$BT,"Not Met")),"-") -> - | BN4: =IFERROR(COUNTIFS('Base File'!$G:$G,"Contractual SLA",'Base File'!$H:$H,"Yes",'Base File'!$B:$B,'Account Summary'!$C4,'Base File'!$BT:$BT,"Met")/SUM(COUNTIFS('Base File'!$G:$G,"Contractual SLA",'Base File'!$H:$H,"yes",'Base File'!$B:$B,'Account Summary'!$C4,'Base File'!$BT:$BT,"Met")+COUNTIFS('Base File'!$G:$G,"Contractual SLA",'Base File'!$H:$H,"yes",'Base File'!$B:$B,'Account Summary'!$C4,'Base File'!$BT:$BT,"Not Met")),"-") -> 0.85714286 | BO4: =IFERROR(COUNTIFS('Base File'!$G:$G,"Internal KPI",'Base File'!$B:$B,'Account Summary'!$C4,'Base File'!$BT:$BT,"Met")/SUM(COUNTIFS('Base File'!$G:$G,"Internal KPI",'Base File'!$B:$B,'Account Summary'!$C4,'Base File'!$BT:$BT,"Met")+COUNTIFS('Base File'!$G:$G,"Internal KPI",'Base File'!$B:$B,'Account Summary'!$C4,'Base File'!$BT:$BT,"Not Met")),"-") -> 1 | BP4: =IFERROR(COUNTIFS('Base File'!$BV:$BV,"Met",'Base File'!$B:$B,'Account Summary'!C4)/(COUNTIFS('Base File'!$BV:$BV,"Met",'Base File'!$B:$B,'Account Summary'!C4)+COUNTIFS('Base File'!$BV:$BV,"Not Met",'Base File'!$B:$B,'Account Summary'!C4)),"NR") -> 0.875 | BQ4: - | BR4: =IFERROR(COUNTIFS('Base File'!$G:$G,"Contractual SLA",'Base File'!$H:$H,"Yes",'Base File'!$B:$B,'Account Summary'!$C4,'Base File'!$BV:$BV,"Met")/SUM(COUNTIFS('Base File'!$G:$G,"Contractual SLA",'Base File'!$H:$H,"Yes",'Base File'!$B:$B,'Account Summary'!$C4,'Base File'!$BV:$BV,"Met")+COUNTIFS('Base File'!$G:$G,"Contractual SLA",'Base File'!$H:$H,"Yes",'Base File'!$B:$B,'Account Summary'!$C4,'Base File'!$BV:$BV,"Not Met")),"-") -> 0.85714286 | BS4: 1
B5: 2 | C5: ISUZU (UD Trucks) | D5: Bangalore | E5: South 1 | F5: Himanshu Srivastava & Mehvish Naz | I5: Sulabh | J5: Reported | K5: Validated | L5: =IFERROR(COUNTIFS('Base File'!$AR:$AR,"Met",'Base File'!$B:$B,'Account Summary'!C5)/(COUNTIFS('Base File'!$AR:$AR,"Met",'Base File'!$B:$B,'Account Summary'!C5)+COUNTIFS('Base File'!$AR:$AR,"Not Met",'Base File'!$B:$B,'Account Summary'!C5)),"NR") -> NR | M5: =IFERROR(COUNTIFS('Base File'!$G:$G,"Contractual SLA",'Base File'!$H:$H,"No",'Base File'!$B:$B,'Account Summary'!$C5,'Base File'!$AR:$AR,"Met")/SUM(COUNTIFS('Base File'!$G:$G,"Contractual SLA",'Base File'!$H:$H,"No",'Base File'!$B:$B,'Account Summary'!$C5,'Base File'!$AR:$AR,"Met")+COUNTIFS('Base File'!$G:$G,"Contractual SLA",'Base File'!$H:$H,"No",'Base File'!$B:$B,'Account Summary'!$C5,'Base File'!$AR:$AR,"Not Met")),"-") -> - | N5: NR | O5: NR | P5: =IFERROR(COUNTIFS('Base File'!$AV:$AV,"Met",'Base File'!$B:$B,'Account Summary'!C5)/(COUNTIFS('Base File'!$AV:$AV,"Met",'Base File'!$B:$B,'Account Summary'!C5)+COUNTIFS('Base File'!$AV:$AV,"Not Met",'Base File'!$B:$B,'Account Summary'!C5)),"NR") -> NR | Q5: =IFERROR(COUNTIFS('Base File'!$G:$G,"Contractual SLA",'Base File'!$H:$H,"No",'Base File'!$B:$B,'Account Summary'!$C5,'Base File'!$AV:$AV,"Met")/SUM(COUNTIFS('Base File'!$G:$G,"Contractual SLA",'Base File'!$H:$H,"No",'Base File'!$B:$B,'Account Summary'!$C5,'Base File'!$AV:$AV,"Met")+COUNTIFS('Base File'!$G:$G,"Contractual SLA",'Base File'!$H:$H,"No",'Base File'!$B:$B,'Account Summary'!$C5,'Base File'!$AV:$AV,"Not Met")),"-") -> - | R5: =IFERROR(COUNTIFS('Base File'!$BV:$BV,"Met",'Base File'!$B:$B,'Account Summary'!A5)/(COUNTIFS('Base File'!$BV:$BV,"Met",'Base File'!$B:$B,'Account Summary'!A5)+COUNTIFS('Base File'!$BV:$BV,"Not Met",'Base File'!$B:$B,'Account Summary'!A5)),"NR") -> NR | S5: =IFERROR(COUNTIFS('Base File'!$BV:$BV,"Met",'Base File'!$B:$B,'Account Summary'!B5)/(COUNTIFS('Base File'!$BV:$BV,"Met",'Base File'!$B:$B,'Account Summary'!B5)+COUNTIFS('Base File'!$BV:$BV,"Not Met",'Base File'!$B:$B,'Account Summary'!B5)),"NR") -> NR | T5: =IFERROR(COUNTIFS('Base File'!$AX:$AX,"Met",'Base File'!$B:$B,'Account Summary'!C5)/(COUNTIFS('Base File'!$AX:$AX,"Met",'Base File'!$B:$B,'Account Summary'!C5)+COUNTIFS('Base File'!$AX:$AX,"Not Met",'Base File'!$B:$B,'Account Summary'!C5)),"NR") -> NR | U5: =IFERROR(COUNTIFS('Base File'!$G:$G,"Contractual SLA",'Base File'!$H:$H,"No",'Base File'!$B:$B,'Account Summary'!$C5,'Base File'!$AX:$AX,"Met")/SUM(COUNTIFS('Base File'!$G:$G,"Contractual SLA",'Base File'!$H:$H,"No",'Base File'!$B:$B,'Account Summary'!$C5,'Base File'!$AX:$AX,"Met")+COUNTIFS('Base File'!$G:$G,"Contractual SLA",'Base File'!$H:$H,"No",'Base File'!$B:$B,'Account Summary'!$C5,'Base File'!$AX:$AX,"Not Met")),"NA") -> NA | V5: NR | W5: NR | X5: =IFERROR(COUNTIFS('Base File'!$AZ:$AZ,"Met",'Base File'!$B:$B,'Account Summary'!C5)/(COUNTIFS('Base File'!$AZ:$AZ,"Met",'Base File'!$B:$B,'Account Summary'!C5)+COUNTIFS('Base File'!$AZ:$AZ,"Not Met",'Base File'!$B:$B,'Account Summary'!C5)),"NR") -> NR | Y5: =IFERROR(COUNTIFS('Base File'!$G:$G,"Contractual SLA",'Base File'!$H:$H,"No",'Base File'!$B:$B,'Account Summary'!$C5,'Base File'!$AZ:$AZ,"Met")/SUM(COUNTIFS('Base File'!$G:$G,"Contractual SLA",'Base File'!$H:$H,"No",'Base File'!$B:$B,'Account Summary'!$C5,'Base File'!$AZ:$AZ,"Met")+COUNTIFS('Base File'!$G:$G,"Contractual SLA",'Base File'!$H:$H,"No",'Base File'!$B:$B,'Account Summary'!$C5,'Base File'!$AZ:$AZ,"Not Met")),"-") -> - | Z5: NR | AA5: NR | AB5: =IFERROR(COUNTIFS('Base File'!$BB:$BB,"Met",'Base File'!$B:$B,'Account Summary'!C5)/(COUNTIFS('Base File'!$BB:$BB,"Met",'Base File'!$B:$B,'Account Summary'!C5)+COUNTIFS('Base File'!$BB:$BB,"Not Met",'Base File'!$B:$B,'Account Summary'!C5)),"NR") -> NR | AC5: - | AD5: NR | AE5: NR | AF5: =IFERROR(COUNTIFS('Base File'!$AZ:$AZ,"Met",'Base File'!$B:$B,'Account Summary'!L5)/(COUNTIFS('Base File'!$AZ:$AZ,"Met",'Base File'!$B:$B,'Account Summary'!L5)+COUNTIFS('Base File'!$AZ:$AZ,"Not Met",'Base File'!$B:$B,'Account Summary'!L5)),"NR") -> NR | AG5: =IFERROR(COUNTIFS('Base File'!$G:$G,"Contractual SLA",'Base File'!$H:$H,"No",'Base File'!$B:$B,'Account Summary'!$C5,'Base File'!$AZ:$AZ,"Met")/SUM(COUNTIFS('Base File'!$G:$G,"Contractual SLA",'Base File'!$H:$H,"No",'Base File'!$B:$B,'Account Summary'!$C5,'Base File'!$AZ:$AZ,"Met")+COUNTIFS('Base File'!$G:$G,"Contractual SLA",'Base File'!$H:$H,"No",'Base File'!$B:$B,'Account Summary'!$C5,'Base File'!$AZ:$AZ,"Not Met")),"-") -> - | AH5: NR | AI5: NR | AJ5: =IFERROR(COUNTIFS('Base File'!$BF:$BF,"Met",'Base File'!$B:$B,'Account Summary'!C5)/(COUNTIFS('Base File'!$BF:$BF,"Met",'Base File'!$B:$B,'Account Summary'!C5)+COUNTIFS('Base File'!$BF:$BF,"Not Met",'Base File'!$B:$B,'Account Summary'!C5)),"NR") -> NR | AK5: =IFERROR(COUNTIFS('Base File'!$G:$G,"Contractual SLA",'Base File'!$H:$H,"No",'Base File'!$B:$B,'Account Summary'!$C5,'Base File'!$BF:$BF,"Met")/SUM(COUNTIFS('Base File'!$G:$G,"Contractual SLA",'Base File'!$H:$H,"No",'Base File'!$B:$B,'Account Summary'!$C5,'Base File'!$BF:$BF,"Met")+COUNTIFS('Base File'!$G:$G,"Contractual SLA",'Base File'!$H:$H,"No",'Base File'!$B:$B,'Account Summary'!$C5,'Base File'!$BF:$BF,"Not Met")),"-") -> - | AL5: NR | AM5: NR | AN5: =IFERROR(COUNTIFS('Base File'!$BH:$BH,"Met",'Base File'!$B:$B,'Account Summary'!C5)/(COUNTIFS('Base File'!$BH:$BH,"Met",'Base File'!$B:$B,'Account Summary'!C5)+COUNTIFS('Base File'!$BH:$BH,"Not Met",'Base File'!$B:$B,'Account Summary'!C5)),"NR") -> NR | AO5: =IFERROR(COUNTIFS('Base File'!$G:$G,"Contractual SLA",'Base File'!$H:$H,"No",'Base File'!$B:$B,'Account Summary'!$C5,'Base File'!$BH:$BH,"Met")/SUM(COUNTIFS('Base File'!$G:$G,"Contractual SLA",'Base File'!$H:$H,"No",'Base File'!$B:$B,'Account Summary'!$C5,'Base File'!$BH:$BH,"Met")+COUNTIFS('Base File'!$G:$G,"Contractual SLA",'Base File'!$H:$H,"No",'Base File'!$B:$B,'Account Summary'!$C5,'Base File'!$BH:$BH,"Not Met")),"-") -> - | AP5: NR | AQ5: NR | AR5: =IFERROR(COUNTIFS('Base File'!$BJ:$BJ,"Met",'Base File'!$B:$B,'Account Summary'!C5)/(COUNTIFS('Base File'!$BJ:$BJ,"Met",'Base File'!$B:$B,'Account Summary'!C5)+COUNTIFS('Base File'!$BJ:$BJ,"Not Met",'Base File'!$B:$B,'Account Summary'!C5)),"NR") -> NR | AS5: =IFERROR(COUNTIFS('Base File'!$G:$G,"Contractual SLA",'Base File'!$H:$H,"No",'Base File'!$B:$B,'Account Summary'!$C5,'Base File'!$BJ:$BJ,"Met")/SUM(COUNTIFS('Base File'!$G:$G,"Contractual SLA",'Base File'!$H:$H,"No",'Base File'!$B:$B,'Account Summary'!$C5,'Base File'!$BJ:$BJ,"Met")+COUNTIFS('Base File'!$G:$G,"Contractual SLA",'Base File'!$H:$H,"No",'Base File'!$B:$B,'Account Summary'!$C5,'Base File'!$BJ:$BJ,"Not Met")),"-") -> - | AT5: NR | AU5: NR | AV5: =IFERROR(COUNTIFS('Base File'!$AZ:$AZ,"Met",'Base File'!$B:$B,'Account Summary'!L5)/(COUNTIFS('Base File'!$AZ:$AZ,"Met",'Base File'!$B:$B,'Account Summary'!L5)+COUNTIFS('Base File'!$AZ:$AZ,"Not Met",'Base File'!$B:$B,'Account Summary'!L5)),"NR") -> NR | AW5: =IFERROR(COUNTIFS('Base File'!$G:$G,"Contractual SLA",'Base File'!$H:$H,"No",'Base File'!$B:$B,'Account Summary'!$C5,'Base File'!$AZ:$AZ,"Met")/SUM(COUNTIFS('Base File'!$G:$G,"Contractual SLA",'Base File'!$H:$H,"No",'Base File'!$B:$B,'Account Summary'!$C5,'Base File'!$AZ:$AZ,"Met")+COUNTIFS('Base File'!$G:$G,"Contractual SLA",'Base File'!$H:$H,"No",'Base File'!$B:$B,'Account Summary'!$C5,'Base File'!$AZ:$AZ,"Not Met")),"-") -> - | AX5: NR | AY5: NR | AZ5: NR | BA5: - | BB5: NR | BC5: NR | BD5: =IFERROR(COUNTIFS('Base File'!$BP:$BP,"Met",'Base File'!$B:$B,'Account Summary'!C5)/(COUNTIFS('Base File'!$BP:$BP,"Met",'Base File'!$B:$B,'Account Summary'!C5)+COUNTIFS('Base File'!$BP:$BP,"Not Met",'Base File'!$B:$B,'Account Summary'!C5)),"NR") -> NR | BE5: =IFERROR(COUNTIFS('Base File'!$G:$G,"Contractual SLA",'Base File'!$H:$H,"No",'Base File'!$B:$B,'Account Summary'!$C5,'Base File'!$BP:$BP,"Met")/SUM(COUNTIFS('Base File'!$G:$G,"Contractual SLA",'Base File'!$H:$H,"No",'Base File'!$B:$B,'Account Summary'!$C5,'Base File'!$BP:$BP,"Met")+COUNTIFS('Base File'!$G:$G,"Contractual SLA",'Base File'!$H:$H,"No",'Base File'!$B:$B,'Account Summary'!$C5,'Base File'!$BP:$BP,"Not Met")),"-") -> - | BF5: NR | BG5: NR | BH5: =IFERROR(COUNTIFS('Base File'!$BR:$BR,"Met",'Base File'!$B:$B,'Account Summary'!C5)/(COUNTIFS('Base File'!$BR:$BR,"Met",'Base File'!$B:$B,'Account Summary'!C5)+COUNTIFS('Base File'!$BR:$BR,"Not Met",'Base File'!$B:$B,'Account Summary'!C5)),"NR") -> NR | BI5: =IFERROR(COUNTIFS('Base File'!$G:$G,"Contractual SLA",'Base File'!$H:$H,"No",'Base File'!$B:$B,'Account Summary'!$C5,'Base File'!$BR:$BR,"Met")/SUM(COUNTIFS('Base File'!$G:$G,"Contractual SLA",'Base File'!$H:$H,"No",'Base File'!$B:$B,'Account Summary'!$C5,'Base File'!$BR:$BR,"Met")+COUNTIFS('Base File'!$G:$G,"Contractual SLA",'Base File'!$H:$H,"No",'Base File'!$B:$B,'Account Summary'!$C5,'Base File'!$BR:$BR,"Not Met")),"-") -> - | BJ5: NR | BK5: NR | BL5: =IFERROR(COUNTIFS('Base File'!$BT:$BT,"Met",'Base File'!$B:$B,'Account Summary'!C5)/(COUNTIFS('Base File'!$BT:$BT,"Met",'Base File'!$B:$B,'Account Summary'!C5)+COUNTIFS('Base File'!$BT:$BT,"Not Met",'Base File'!$B:$B,'Account Summary'!C5)),"NR") -> 0.625 | BM5: =IFERROR(COUNTIFS('Base File'!$G:$G,"Contractual SLA",'Base File'!$H:$H,"No",'Base File'!$B:$B,'Account Summary'!$C5,'Base File'!$BT:$BT,"Met")/SUM(COUNTIFS('Base File'!$G:$G,"Contractual SLA",'Base File'!$H:$H,"No",'Base File'!$B:$B,'Account Summary'!$C5,'Base File'!$BT:$BT,"Met")+COUNTIFS('Base File'!$G:$G,"Contractual SLA",'Base File'!$H:$H,"No",'Base File'!$B:$B,'Account Summary'!$C5,'Base File'!$BT:$BT,"Not Met")),"-") -> - | BN5: =IFERROR(COUNTIFS('Base File'!$G:$G,"Contractual SLA",'Base File'!$H:$H,"Yes",'Base File'!$B:$B,'Account Summary'!$C5,'Base File'!$BT:$BT,"Met")/SUM(COUNTIFS('Base File'!$G:$G,"Contractual SLA",'Base File'!$H:$H,"yes",'Base File'!$B:$B,'Account Summary'!$C5,'Base File'!$BT:$BT,"Met")+COUNTIFS('Base File'!$G:$G,"Contractual SLA",'Base File'!$H:$H,"yes",'Base File'!$B:$B,'Account Summary'!$C5,'Base File'!$BT:$BT,"Not Met")),"-") -> 0 | BO5: =IFERROR(COUNTIFS('Base File'!$G:$G,"Internal KPI",'Base File'!$B:$B,'Account Summary'!$C5,'Base File'!$BT:$BT,"Met")/SUM(COUNTIFS('Base File'!$G:$G,"Internal KPI",'Base File'!$B:$B,'Account Summary'!$C5,'Base File'!$BT:$BT,"Met")+COUNTIFS('Base File'!$G:$G,"Internal KPI",'Base File'!$B:$B,'Account Summary'!$C5,'Base File'!$BT:$BT,"Not Met")),"-") -> 0.83333333 | BP5: =IFERROR(COUNTIFS('Base File'!$BV:$BV,"Met",'Base File'!$B:$B,'Account Summary'!C5)/(COUNTIFS('Base File'!$BV:$BV,"Met",'Base File'!$B:$B,'Account Summary'!C5)+COUNTIFS('Base File'!$BV:$BV,"Not Met",'Base File'!$B:$B,'Account Summary'!C5)),"NR") -> 0.625 | BQ5: - | BR5: =IFERROR(COUNTIFS('Base File'!$G:$G,"Contractual SLA",'Base File'!$H:$H,"Yes",'Base File'!$B:$B,'Account Summary'!$C5,'Base File'!$BV:$BV,"Met")/SUM(COUNTIFS('Base File'!$G:$G,"Contractual SLA",'Base File'!$H:$H,"Yes",'Base File'!$B:$B,'Account Summary'!$C5,'Base File'!$BV:$BV,"Met")+COUNTIFS('Base File'!$G:$G,"Contractual SLA",'Base File'!$H:$H,"Yes",'Base File'!$B:$B,'Account Summary'!$C5,'Base File'!$BV:$BV,"Not Met")),"-") -> 0.5 | BS5: 0.67
B6: 3 | C6: Siemens - GBS | D6: Bangalore | E6: South 1 | F6: Himanshu Srivastava & Mehvish Naz | I6: Sulabh | J6: Reported | K6: Validated | L6: =IFERROR(COUNTIFS('Base File'!$AR:$AR,"Met",'Base File'!$B:$B,'Account Summary'!C6)/(COUNTIFS('Base File'!$AR:$AR,"Met",'Base File'!$B:$B,'Account Summary'!C6)+COUNTIFS('Base File'!$AR:$AR,"Not Met",'Base File'!$B:$B,'Account Summary'!C6)),"NR") -> 0.81818182 | M6: =IFERROR(COUNTIFS('Base File'!$G:$G,"Contractual SLA",'Base File'!$H:$H,"No",'Base File'!$B:$B,'Account Summary'!$C6,'Base File'!$AR:$AR,"Met")/SUM(COUNTIFS('Base File'!$G:$G,"Contractual SLA",'Base File'!$H:$H,"No",'Base File'!$B:$B,'Account Summary'!$C6,'Base File'!$AR:$AR,"Met")+COUNTIFS('Base File'!$G:$G,"Contractual SLA",'Base File'!$H:$H,"No",'Base File'!$B:$B,'Account Summary'!$C6,'Base File'!$AR:$AR,"Not Met")),"-") -> 0.8 | N6: =IFERROR(COUNTIFS('Base File'!$G:$G,"Contractual SLA",'Base File'!$H:$H,"Yes",'Base File'!$B:$B,'Account Summary'!$C6,'Base File'!$AR:$AR,"Met")/SUM(COUNTIFS('Base File'!$G:$G,"Contractual SLA",'Base File'!$H:$H,"yes",'Base File'!$B:$B,'Account Summary'!$C6,'Base File'!$AR:$AR,"Met")+COUNTIFS('Base File'!$G:$G,"Contractual SLA",'Base File'!$H:$H,"yes",'Base File'!$B:$B,'Account Summary'!$C6,'Base File'!$AR:$AR,"Not Met")),"-") -> - | O6: =IFERROR(COUNTIFS('Base File'!$G:$G,"Internal KPI",'Base File'!$B:$B,'Account Summary'!$C6,'Base File'!$AR:$AR,"Met")/SUM(COUNTIFS('Base File'!$G:$G,"Internal KPI",'Base File'!$B:$B,'Account Summary'!$C6,'Base File'!$AR:$AR,"Met")+COUNTIFS('Base File'!$G:$G,"Internal KPI",'Base File'!$B:$B,'Account Summary'!$C6,'Base File'!$AR:$AR,"Not Met")),"-") -> 0.83333333 | P6: =IFERROR(COUNTIFS('Base File'!$AV:$AV,"Met",'Base File'!$B:$B,'Account Summary'!C6)/(COUNTIFS('Base File'!$AV:$AV,"Met",'Base File'!$B:$B,'Account Summary'!C6)+COUNTIFS('Base File'!$AV:$AV,"Not Met",'Base File'!$B:$B,'Account Summary'!C6)),"NR") -> 0.90909091 | Q6: =IFERROR(COUNTIFS('Base File'!$G:$G,"Contractual SLA",'Base File'!$H:$H,"No",'Base File'!$B:$B,'Account Summary'!$C6,'Base File'!$AV:$AV,"Met")/SUM(COUNTIFS('Base File'!$G:$G,"Contractual SLA",'Base File'!$H:$H,"No",'Base File'!$B:$B,'Account Summary'!$C6,'Base File'!$AV:$AV,"Met")+COUNTIFS('Base File'!$G:$G,"Contractual SLA",'Base File'!$H:$H,"No",'Base File'!$B:$B,'Account Summary'!$C6,'Base File'!$AV:$AV,"Not Met")),"-") -> 1 | R6: =IFERROR(COUNTIFS('Base File'!$G:$G,"Contractual SLA",'Base File'!$H:$H,"Yes",'Base File'!$B:$B,'Account Summary'!$C6,'Base File'!$AV:$AV,"Met")/SUM(COUNTIFS('Base File'!$G:$G,"Contractual SLA",'Base File'!$H:$H,"yes",'Base File'!$B:$B,'Account Summary'!$C6,'Base File'!$AV:$AV,"Met")+COUNTIFS('Base File'!$G:$G,"Contractual SLA",'Base File'!$H:$H,"yes",'Base File'!$B:$B,'Account Summary'!$C6,'Base File'!$AV:$AV,"Not Met")),"-") -> - | S6: =IFERROR(COUNTIFS('Base File'!$G:$G,"Internal KPI",'Base File'!$B:$B,'Account Summary'!$C6,'Base File'!$AV:$AV,"Met")/SUM(COUNTIFS('Base File'!$G:$G,"Internal KPI",'Base File'!$B:$B,'Account Summary'!$C6,'Base File'!$AV:$AV,"Met")+COUNTIFS('Base File'!$G:$G,"Internal KPI",'Base File'!$B:$B,'Account Summary'!$C6,'Base File'!$AV:$AV,"Not Met")),"-") -> 0.83333333 | T6: =IFERROR(COUNTIFS('Base File'!$AX:$AX,"Met",'Base File'!$B:$B,'Account Summary'!C6)/(COUNTIFS('Base File'!$AX:$AX,"Met",'Base File'!$B:$B,'Account Summary'!C6)+COUNTIFS('Base File'!$AX:$AX,"Not Met",'Base File'!$B:$B,'Account Summary'!C6)),"NR") -> 0.90909091 | U6: =IFERROR(COUNTIFS('Base File'!$G:$G,"Contractual SLA",'Base File'!$H:$H,"No",'Base File'!$B:$B,'Account Summary'!$C6,'Base File'!$AX:$AX,"Met")/SUM(COUNTIFS('Base File'!$G:$G,"Contractual SLA",'Base File'!$H:$H,"No",'Base File'!$B:$B,'Account Summary'!$C6,'Base File'!$AX:$AX,"Met")+COUNTIFS('Base File'!$G:$G,"Contractual SLA",'Base File'!$H:$H,"No",'Base File'!$B:$B,'Account Summary'!$C6,'Base File'!$AX:$AX,"Not Met")),"-") -> 1 | V6: NA | W6: =IFERROR(COUNTIFS('Base File'!$G:$G,"Internal KPI",'Base File'!$B:$B,'Account Summary'!$C6,'Base File'!$AX:$AX,"Met")/SUM(COUNTIFS('Base File'!$G:$G,"Internal KPI",'Base File'!$B:$B,'Account Summary'!$C6,'Base File'!$AX:$AX,"Met")+COUNTIFS('Base File'!$G:$G,"Internal KPI",'Base File'!$B:$B,'Account Summary'!$C6,'Base File'!$AX:$AX,"Not Met")),"-") -> 0.83333333 | X6: =IFERROR(COUNTIFS('Base File'!$AZ:$AZ,"Met",'Base File'!$B:$B,'Account Summary'!C6)/(COUNTIFS('Base File'!$AZ:$AZ,"Met",'Base File'!$B:$B,'Account Summary'!C6)+COUNTIFS('Base File'!$AZ:$AZ,"Not Met",'Base File'!$B:$B,'Account Summary'!C6)),"NR") -> 0.81818182 | Y6: =IFERROR(COUNTIFS('Base File'!$G:$G,"Contractual SLA",'Base File'!$H:$H,"No",'Base File'!$B:$B,'Account Summary'!$C6,'Base File'!$AZ:$AZ,"Met")/SUM(COUNTIFS('Base File'!$G:$G,"Contractual SLA",'Base File'!$H:$H,"No",'Base File'!$B:$B,'Account Summary'!$C6,'Base File'!$AZ:$AZ,"Met")+COUNTIFS('Base File'!$G:$G,"Contractual SLA",'Base File'!$H:$H,"No",'Base File'!$B:$B,'Account Summary'!$C6,'Base File'!$AZ:$AZ,"Not Met")),"-") -> 1 | Z6: =IFERROR(COUNTIFS('Base File'!$G:$G,"Contractual SLA",'Base File'!$H:$H,"Yes",'Base File'!$B:$B,'Account Summary'!$C6,'Base File'!$AZ:$AZ,"Met")/SUM(COUNTIFS('Base File'!$G:$G,"Contractual SLA",'Base File'!$H:$H,"yes",'Base File'!$B:$B,'Account Summary'!$C6,'Base File'!$AZ:$AZ,"Met")+COUNTIFS('Base File'!$G:$G,"Contractual SLA",'Base File'!$H:$H,"yes",'Base File'!$B:$B,'Account Summary'!$C6,'Base File'!$AZ:$AZ,"Not Met")),"-") -> - | AA6: =IFERROR(COUNTIFS('Base File'!$G:$G,"Internal KPI",'Base File'!$B:$B,'Account Summary'!$C6,'Base File'!$AZ:$AZ,"Met")/SUM(COUNTIFS('Base File'!$G:$G,"Internal KPI",'Base File'!$B:$B,'Account Summary'!$C6,'Base File'!$AZ:$AZ,"Met")+COUNTIFS('Base File'!$G:$G,"Internal KPI",'Base File'!$B:$B,'Account Summary'!$C6,'Base File'!$AZ:$AZ,"Not Met")),"-") -> 0.66666667 | AB6: =IFERROR(COUNTIFS('Base File'!$BB:$BB,"Met",'Base File'!$B:$B,'Account Summary'!C6)/(COUNTIFS('Base File'!$BB:$BB,"Met",'Base File'!$B:$B,'Account Summary'!C6)+COUNTIFS('Base File'!$BB:$BB,"Not Met",'Base File'!$B:$B,'Account Summary'!C6)),"NR") -> 0.81818182 | AC6: =IFERROR(COUNTIFS('Base File'!$G:$G,"Contractual SLA",'Base File'!$H:$H,"No",'Base File'!$B:$B,'Account Summary'!$C6,'Base File'!$BB:$BB,"Met")/SUM(COUNTIFS('Base File'!$G:$G,"Contractual SLA",'Base File'!$H:$H,"No",'Base File'!$B:$B,'Account Summary'!$C6,'Base File'!$BB:$BB,"Met")+COUNTIFS('Base File'!$G:$G,"Contractual SLA",'Base File'!$H:$H,"No",'Base File'!$B:$B,'Account Summary'!$C6,'Base File'!$BB:$BB,"Not Met")),"-") -> 1 | AD6: =IFERROR(COUNTIFS('Base File'!$G:$G,"Contractual SLA",'Base File'!$H:$H,"Yes",'Base File'!$B:$B,'Account Summary'!$C6,'Base File'!$BB:$BB,"Met")/SUM(COUNTIFS('Base File'!$G:$G,"Contractual SLA",'Base File'!$H:$H,"yes",'Base File'!$B:$B,'Account Summary'!$C6,'Base File'!$BB:$BB,"Met")+COUNTIFS('Base File'!$G:$G,"Contractual SLA",'Base File'!$H:$H,"yes",'Base File'!$B:$B,'Account Summary'!$C6,'Base File'!$BB:$BB,"Not Met")),"-") -> - | AE6: =IFERROR(COUNTIFS('Base File'!$G:$G,"Internal KPI",'Base File'!$B:$B,'Account Summary'!$C6,'Base File'!$BB:$BB,"Met")/SUM(COUNTIFS('Base File'!$G:$G,"Internal KPI",'Base File'!$B:$B,'Account Summary'!$C6,'Base File'!$BB:$BB,"Met")+COUNTIFS('Base File'!$G:$G,"Internal KPI",'Base File'!$B:$B,'Account Summary'!$C6,'Base File'!$BB:$BB,"Not Met")),"-") -> 0.66666667 | AF6: =IFERROR(COUNTIFS('Base File'!$BD:$BD,"Met",'Base File'!$B:$B,'Account Summary'!C6)/(COUNTIFS('Base File'!$BD:$BD,"Met",'Base File'!$B:$B,'Account Summary'!C6)+COUNTIFS('Base File'!$BD:$BD,"Not Met",'Base File'!$B:$B,'Account Summary'!C6)),"NR") -> 0.63636364 | AG6: =IFERROR(COUNTIFS('Base File'!$G:$G,"Contractual SLA",'Base File'!$H:$H,"No",'Base File'!$B:$B,'Account Summary'!$C6,'Base File'!$BD:$BD,"Met")/SUM(COUNTIFS('Base File'!$G:$G,"Contractual SLA",'Base File'!$H:$H,"No",'Base File'!$B:$B,'Account Summary'!$C6,'Base File'!$BD:$BD,"Met")+COUNTIFS('Base File'!$G:$G,"Contractual SLA",'Base File'!$H:$H,"No",'Base File'!$B:$B,'Account Summary'!$C6,'Base File'!$BD:$BD,"Not Met")),"-") -> 0.6 | AH6: =IFERROR(COUNTIFS('Base File'!$G:$G,"Contractual SLA",'Base File'!$H:$H,"Yes",'Base File'!$B:$B,'Account Summary'!$C6,'Base File'!$BD:$BD,"Met")/SUM(COUNTIFS('Base File'!$G:$G,"Contractual SLA",'Base File'!$H:$H,"yes",'Base File'!$B:$B,'Account Summary'!$C6,'Base File'!$BD:$BD,"Met")+COUNTIFS('Base File'!$G:$G,"Contractual SLA",'Base File'!$H:$H,"yes",'Base File'!$B:$B,'Account Summary'!$C6,'Base File'!$BD:$BD,"Not Met")),"-") -> - | AI6: =IFERROR(COUNTIFS('Base File'!$G:$G,"Internal KPI",'Base File'!$B:$B,'Account Summary'!$C6,'Base File'!$BD:$BD,"Met")/SUM(COUNTIFS('Base File'!$G:$G,"Internal KPI",'Base File'!$B:$B,'Account Summary'!$C6,'Base File'!$BD:$BD,"Met")+COUNTIFS('Base File'!$G:$G,"Internal KPI",'Base File'!$B:$B,'Account Summary'!$C6,'Base File'!$BD:$BD,"Not Met")),"-") -> 0.66666667 | AJ6: =IFERROR(COUNTIFS('Base File'!$BF:$BF,"Met",'Base File'!$B:$B,'Account Summary'!C6)/(COUNTIFS('Base File'!$BF:$BF,"Met",'Base File'!$B:$B,'Account Summary'!C6)+COUNTIFS('Base File'!$BF:$BF,"Not Met",'Base File'!$B:$B,'Account Summary'!C6)),"NR") -> 0.81818182 | AK6: =IFERROR(COUNTIFS('Base File'!$G:$G,"Contractual SLA",'Base File'!$H:$H,"No",'Base File'!$B:$B,'Account Summary'!$C6,'Base File'!$BF:$BF,"Met")/SUM(COUNTIFS('Base File'!$G:$G,"Contractual SLA",'Base File'!$H:$H,"No",'Base File'!$B:$B,'Account Summary'!$C6,'Base File'!$BF:$BF,"Met")+COUNTIFS('Base File'!$G:$G,"Contractual SLA",'Base File'!$H:$H,"No",'Base File'!$B:$B,'Account Summary'!$C6,'Base File'!$BF:$BF,"Not Met")),"-") -> 0.8 | AL6: =IFERROR(COUNTIFS('Base File'!$G:$G,"Contractual SLA",'Base File'!$H:$H,"Yes",'Base File'!$B:$B,'Account Summary'!$C6,'Base File'!$BF:$BF,"Met")/SUM(COUNTIFS('Base File'!$G:$G,"Contractual SLA",'Base File'!$H:$H,"yes",'Base File'!$B:$B,'Account Summary'!$C6,'Base File'!$BF:$BF,"Met")+COUNTIFS('Base File'!$G:$G,"Contractual SLA",'Base File'!$H:$H,"yes",'Base File'!$B:$B,'Account Summary'!$C6,'Base File'!$BF:$BF,"Not Met")),"-") -> - | AM6: =IFERROR(COUNTIFS('Base File'!$G:$G,"Internal KPI",'Base File'!$B:$B,'Account Summary'!$C6,'Base File'!$BF:$BF,"Met")/SUM(COUNTIFS('Base File'!$G:$G,"Internal KPI",'Base File'!$B:$B,'Account Summary'!$C6,'Base File'!$BF:$BF,"Met")+COUNTIFS('Base File'!$G:$G,"Internal KPI",'Base File'!$B:$B,'Account Summary'!$C6,'Base File'!$BF:$BF,"Not Met")),"-") -> 0.83333333 | AN6: =IFERROR(COUNTIFS('Base File'!$BH:$BH,"Met",'Base File'!$B:$B,'Account Summary'!C6)/(COUNTIFS('Base File'!$BH:$BH,"Met",'Base File'!$B:$B,'Account Summary'!C6)+COUNTIFS('Base File'!$BH:$BH,"Not Met",'Base File'!$B:$B,'Account Summary'!C6)),"NR") -> 0.81818182 | AO6: NR | AP6: =IFERROR(COUNTIFS('Base File'!$G:$G,"Contractual SLA",'Base File'!$H:$H,"Yes",'Base File'!$B:$B,'Account Summary'!$C6,'Base File'!$BH:$BH,"Met")/SUM(COUNTIFS('Base File'!$G:$G,"Contractual SLA",'Base File'!$H:$H,"yes",'Base File'!$B:$B,'Account Summary'!$C6,'Base File'!$BH:$BH,"Met")+COUNTIFS('Base File'!$G:$G,"Contractual SLA",'Base File'!$H:$H,"yes",'Base File'!$B:$B,'Account Summary'!$C6,'Base File'!$BH:$BH,"Not Met")),"-") -> - | AQ6: NR | AR6: =IFERROR(COUNTIFS('Base File'!$BJ:$BJ,"Met",'Base File'!$B:$B,'Account Summary'!C6)/(COUNTIFS('Base File'!$BJ:$BJ,"Met",'Base File'!$B:$B,'Account Summary'!C6)+COUNTIFS('Base File'!$BJ:$BJ,"Not Met",'Base File'!$B:$B,'Account Summary'!C6)),"NR") -> 0.90909091 | AS6: NR | AT6: =IFERROR(COUNTIFS('Base File'!$G:$G,"Contractual SLA",'Base File'!$H:$H,"Yes",'Base File'!$B:$B,'Account Summary'!$C6,'Base File'!$BJ:$BJ,"Met")/SUM(COUNTIFS('Base File'!$G:$G,"Contractual SLA",'Base File'!$H:$H,"yes",'Base File'!$B:$B,'Account Summary'!$C6,'Base File'!$BJ:$BJ,"Met")+COUNTIFS('Base File'!$G:$G,"Contractual SLA",'Base File'!$H:$H,"yes",'Base File'!$B:$B,'Account Summary'!$C6,'Base File'!$BJ:$BJ,"Not Met")),"-") -> - | AU6: NR | AV6: =IFERROR(COUNTIFS('Base File'!$BL:$BL,"Met",'Base File'!$B:$B,'Account Summary'!C6)/(COUNTIFS('Base File'!$BL:$BL,"Met",'Base File'!$B:$B,'Account Summary'!C6)+COUNTIFS('Base File'!$BL:$BL,"Not Met",'Base File'!$B:$B,'Account Summary'!C6)),"NR") -> 0.81818182 | AW6: =IFERROR(COUNTIFS('Base File'!$G:$G,"Contractual SLA",'Base File'!$H:$H,"No",'Base File'!$B:$B,'Account Summary'!$C6,'Base File'!$BL:$BL,"Met")/SUM(COUNTIFS('Base File'!$G:$G,"Contractual SLA",'Base File'!$H:$H,"No",'Base File'!$B:$B,'Account Summary'!$C6,'Base File'!$BL:$BL,"Met")+COUNTIFS('Base File'!$G:$G,"Contractual SLA",'Base File'!$H:$H,"No",'Base File'!$B:$B,'Account Summary'!$C6,'Base File'!$BL:$BL,"Not Met")),"-") -> 0.8 | AX6: =IFERROR(COUNTIFS('Base File'!$G:$G,"Contractual SLA",'Base File'!$H:$H,"Yes",'Base File'!$B:$B,'Account Summary'!$C6,'Base File'!$BL:$BL,"Met")/SUM(COUNTIFS('Base File'!$G:$G,"Contractual SLA",'Base File'!$H:$H,"yes",'Base File'!$B:$B,'Account Summary'!$C6,'Base File'!$BL:$BL,"Met")+COUNTIFS('Base File'!$G:$G,"Contractual SLA",'Base File'!$H:$H,"yes",'Base File'!$B:$B,'Account Summary'!$C6,'Base File'!$BL:$BL,"Not Met")),"-") -> - | AY6: =IFERROR(COUNTIFS('Base File'!$G:$G,"Internal KPI",'Base File'!$B:$B,'Account Summary'!$C6,'Base File'!$BL:$BL,"Met")/SUM(COUNTIFS('Base File'!$G:$G,"Internal KPI",'Base File'!$B:$B,'Account Summary'!$C6,'Base File'!$BL:$BL,"Met")+COUNTIFS('Base File'!$G:$G,"Internal KPI",'Base File'!$B:$B,'Account Summary'!$C6,'Base File'!$BL:$BL,"Not Met")),"-") -> 0.83333333 | AZ6: 0.81818182 | BA6: 0.8 | BB6: - | BC6: 0.83333333 | BD6: =IFERROR(COUNTIFS('Base File'!$BP:$BP,"Met",'Base File'!$B:$B,'Account Summary'!C6)/(COUNTIFS('Base File'!$BP:$BP,"Met",'Base File'!$B:$B,'Account Summary'!C6)+COUNTIFS('Base File'!$BP:$BP,"Not Met",'Base File'!$B:$B,'Account Summary'!C6)),"NR") -> NR | BE6: NR | BF6: =IFERROR(COUNTIFS('Base File'!$G:$G,"Contractual SLA",'Base File'!$H:$H,"Yes",'Base File'!$B:$B,'Account Summary'!$C6,'Base File'!$BP:$BP,"Met")/SUM(COUNTIFS('Base File'!$G:$G,"Contractual SLA",'Base File'!$H:$H,"yes",'Base File'!$B:$B,'Account Summary'!$C6,'Base File'!$BP:$BP,"Met")+COUNTIFS('Base File'!$G:$G,"Contractual SLA",'Base File'!$H:$H,"yes",'Base File'!$B:$B,'Account Summary'!$C6,'Base File'!$BP:$BP,"Not Met")),"-") -> - | BG6: NR | BH6: =IFERROR(COUNTIFS('Base File'!$BR:$BR,"Met",'Base File'!$B:$B,'Account Summary'!C6)/(COUNTIFS('Base File'!$BR:$BR,"Met",'Base File'!$B:$B,'Account Summary'!C6)+COUNTIFS('Base File'!$BR:$BR,"Not Met",'Base File'!$B:$B,'Account Summary'!C6)),"NR") -> NR | BI6: NR | BJ6: =IFERROR(COUNTIFS('Base File'!$G:$G,"Contractual SLA",'Base File'!$H:$H,"No",'Base File'!$B:$B,'Account Summary'!$C6,'Base File'!$BR:$BR,"Met")/SUM(COUNTIFS('Base File'!$G:$G,"Contractual SLA",'Base File'!$H:$H,"No",'Base File'!$B:$B,'Account Summary'!$C6,'Base File'!$BR:$BR,"Met")+COUNTIFS('Base File'!$G:$G,"Contractual SLA",'Base File'!$H:$H,"No",'Base File'!$B:$B,'Account Summary'!$C6,'Base File'!$BR:$BR,"Not Met")),"-") -> - | BK6: NR | BL6: =IFERROR(COUNTIFS('Base File'!$BT:$BT,"Met",'Base File'!$B:$B,'Account Summary'!C6)/(COUNTIFS('Base File'!$BT:$BT,"Met",'Base File'!$B:$B,'Account Summary'!C6)+COUNTIFS('Base File'!$BT:$BT,"Not Met",'Base File'!$B:$B,'Account Summary'!C6)),"NR") -> 0.90909091 | BM6: =IFERROR(COUNTIFS('Base File'!$G:$G,"Contractual SLA",'Base File'!$H:$H,"No",'Base File'!$B:$B,'Account Summary'!$C6,'Base File'!$BT:$BT,"Met")/SUM(COUNTIFS('Base File'!$G:$G,"Contractual SLA",'Base File'!$H:$H,"No",'Base File'!$B:$B,'Account Summary'!$C6,'Base File'!$BT:$BT,"Met")+COUNTIFS('Base File'!$G:$G,"Contractual SLA",'Base File'!$H:$H,"No",'Base File'!$B:$B,'Account Summary'!$C6,'Base File'!$BT:$BT,"Not Met")),"-") -> 1 | BN6: =IFERROR(COUNTIFS('Base File'!$G:$G,"Contractual SLA",'Base File'!$H:$H,"Yes",'Base File'!$B:$B,'Account Summary'!$C6,'Base File'!$BT:$BT,"Met")/SUM(COUNTIFS('Base File'!$G:$G,"Contractual SLA",'Base File'!$H:$H,"yes",'Base File'!$B:$B,'Account Summary'!$C6,'Base File'!$BT:$BT,"Met")+COUNTIFS('Base File'!$G:$G,"Contractual SLA",'Base File'!$H:$H,"yes",'Base File'!$B:$B,'Account Summary'!$C6,'Base File'!$BT:$BT,"Not Met")),"-") -> - | BO6: =IFERROR(COUNTIFS('Base File'!$G:$G,"Internal KPI",'Base File'!$B:$B,'Account Summary'!$C6,'Base File'!$BT:$BT,"Met")/SUM(COUNTIFS('Base File'!$G:$G,"Internal KPI",'Base File'!$B:$B,'Account Summary'!$C6,'Base File'!$BT:$BT,"Met")+COUNTIFS('Base File'!$G:$G,"Internal KPI",'Base File'!$B:$B,'Account Summary'!$C6,'Base File'!$BT:$BT,"Not Met")),"-") -> 0.83333333 | BP6: =IFERROR(COUNTIFS('Base File'!$BV:$BV,"Met",'Base File'!$B:$B,'Account Summary'!C6)/(COUNTIFS('Base File'!$BV:$BV,"Met",'Base File'!$B:$B,'Account Summary'!C6)+COUNTIFS('Base File'!$BV:$BV,"Not Met",'Base File'!$B:$B,'Account Summary'!C6)),"NR") -> 0.90909091 | BQ6: 1 | BR6: =IFERROR(COUNTIFS('Base File'!$G:$G,"Contractual SLA",'Base File'!$H:$H,"Yes",'Base File'!$B:$B,'Account Summary'!$C6,'Base File'!$BV:$BV,"Met")/SUM(COUNTIFS('Base File'!$G:$G,"Contractual SLA",'Base File'!$H:$H,"Yes",'Base File'!$B:$B,'Account Summary'!$C6,'Base File'!$BV:$BV,"Met")+COUNTIFS('Base File'!$G:$G,"Contractual SLA",'Base File'!$H:$H,"Yes",'Base File'!$B:$B,'Account Summary'!$C6,'Base File'!$BV:$BV,"Not Met")),"-") -> - | BS6: 0.83
B7: 4 | C7: Siemens - Advanta | D7: Bangalore | E7: South 1 | F7: Himanshu Srivastava & Mehvish Naz | I7: Sulabh | J7: Reported | K7: Validated | L7: =IFERROR(COUNTIFS('Base File'!$AR:$AR,"Met",'Base File'!$B:$B,'Account Summary'!C7)/(COUNTIFS('Base File'!$AR:$AR,"Met",'Base File'!$B:$B,'Account Summary'!C7)+COUNTIFS('Base File'!$AR:$AR,"Not Met",'Base File'!$B:$B,'Account Summary'!C7)),"NR") -> 0.54545455 | M7: =IFERROR(COUNTIFS('Base File'!$G:$G,"Contractual SLA",'Base File'!$H:$H,"No",'Base File'!$B:$B,'Account Summary'!$C7,'Base File'!$AR:$AR,"Met")/SUM(COUNTIFS('Base File'!$G:$G,"Contractual SLA",'Base File'!$H:$H,"No",'Base File'!$B:$B,'Account Summary'!$C7,'Base File'!$AR:$AR,"Met")+COUNTIFS('Base File'!$G:$G,"Contractual SLA",'Base File'!$H:$H,"No",'Base File'!$B:$B,'Account Summary'!$C7,'Base File'!$AR:$AR,"Not Met")),"-") -> 0.8 | N7: =IFERROR(COUNTIFS('Base File'!$G:$G,"Contractual SLA",'Base File'!$H:$H,"Yes",'Base File'!$B:$B,'Account Summary'!$C7,'Base File'!$AR:$AR,"Met")/SUM(COUNTIFS('Base File'!$G:$G,"Contractual SLA",'Base File'!$H:$H,"yes",'Base File'!$B:$B,'Account Summary'!$C7,'Base File'!$AR:$AR,"Met")+COUNTIFS('Base File'!$G:$G,"Contractual SLA",'Base File'!$H:$H,"yes",'Base File'!$B:$B,'Account Summary'!$C7,'Base File'!$AR:$AR,"Not Met")),"-") -> - | O7: =IFERROR(COUNTIFS('Base File'!$G:$G,"Internal KPI",'Base File'!$B:$B,'Account Summary'!$C7,'Base File'!$AR:$AR,"Met")/SUM(COUNTIFS('Base File'!$G:$G,"Internal KPI",'Base File'!$B:$B,'Account Summary'!$C7,'Base File'!$AR:$AR,"Met")+COUNTIFS('Base File'!$G:$G,"Internal KPI",'Base File'!$B:$B,'Account Summary'!$C7,'Base File'!$AR:$AR,"Not Met")),"-") -> 0.33333333 | P7: =IFERROR(COUNTIFS('Base File'!$AV:$AV,"Met",'Base File'!$B:$B,'Account Summary'!C7)/(COUNTIFS('Base File'!$AV:$AV,"Met",'Base File'!$B:$B,'Account Summary'!C7)+COUNTIFS('Base File'!$AV:$AV,"Not Met",'Base File'!$B:$B,'Account Summary'!C7)),"NR") -> 0.63636364 | Q7: =IFERROR(COUNTIFS('Base File'!$G:$G,"Contractual SLA",'Base File'!$H:$H,"No",'Base File'!$B:$B,'Account Summary'!$C7,'Base File'!$AV:$AV,"Met")/SUM(COUNTIFS('Base File'!$G:$G,"Contractual SLA",'Base File'!$H:$H,"No",'Base File'!$B:$B,'Account Summary'!$C7,'Base File'!$AV:$AV,"Met")+COUNTIFS('Base File'!$G:$G,"Contractual SLA",'Base File'!$H:$H,"No",'Base File'!$B:$B,'Account Summary'!$C7,'Base File'!$AV:$AV,"Not Met")),"-") -> 0.8 | R7: =IFERROR(COUNTIFS('Base File'!$G:$G,"Contractual SLA",'Base File'!$H:$H,"Yes",'Base File'!$B:$B,'Account Summary'!$C7,'Base File'!$AV:$AV,"Met")/SUM(COUNTIFS('Base File'!$G:$G,"Contractual SLA",'Base File'!$H:$H,"yes",'Base File'!$B:$B,'Account Summary'!$C7,'Base File'!$AV:$AV,"Met")+COUNTIFS('Base File'!$G:$G,"Contractual SLA",'Base File'!$H:$H,"yes",'Base File'!$B:$B,'Account Summary'!$C7,'Base File'!$AV:$AV,"Not Met")),"-") -> - | S7: =IFERROR(COUNTIFS('Base File'!$G:$G,"Internal KPI",'Base File'!$B:$B,'Account Summary'!$C7,'Base File'!$AV:$AV,"Met")/SUM(COUNTIFS('Base File'!$G:$G,"Internal KPI",'Base File'!$B:$B,'Account Summary'!$C7,'Base File'!$AV:$AV,"Met")+COUNTIFS('Base File'!$G:$G,"Internal KPI",'Base File'!$B:$B,'Account Summary'!$C7,'Base File'!$AV:$AV,"Not Met")),"-") -> 0.5 | T7: =IFERROR(COUNTIFS('Base File'!$AX:$AX,"Met",'Base File'!$B:$B,'Account Summary'!C7)/(COUNTIFS('Base File'!$AX:$AX,"Met",'Base File'!$B:$B,'Account Summary'!C7)+COUNTIFS('Base File'!$AX:$AX,"Not Met",'Base File'!$B:$B,'Account Summary'!C7)),"NR") -> 0.63636364 | U7: =IFERROR(COUNTIFS('Base File'!$G:$G,"Contractual SLA",'Base File'!$H:$H,"No",'Base File'!$B:$B,'Account Summary'!$C7,'Base File'!$AX:$AX,"Met")/SUM(COUNTIFS('Base File'!$G:$G,"Contractual SLA",'Base File'!$H:$H,"No",'Base File'!$B:$B,'Account Summary'!$C7,'Base File'!$AX:$AX,"Met")+COUNTIFS('Base File'!$G:$G,"Contractual SLA",'Base File'!$H:$H,"No",'Base File'!$B:$B,'Account Summary'!$C7,'Base File'!$AX:$AX,"Not Met")),"-") -> 0.8 | V7: NA | W7: =IFERROR(COUNTIFS('Base File'!$G:$G,"Internal KPI",'Base File'!$B:$B,'Account Summary'!$C7,'Base File'!$AX:$AX,"Met")/SUM(COUNTIFS('Base File'!$G:$G,"Internal KPI",'Base File'!$B:$B,'Account Summary'!$C7,'Base File'!$AX:$AX,"Met")+COUNTIFS('Base File'!$G:$G,"Internal KPI",'Base File'!$B:$B,'Account Summary'!$C7,'Base File'!$AX:$AX,"Not Met")),"-") -> 0.5 | X7: =IFERROR(COUNTIFS('Base File'!$AZ:$AZ,"Met",'Base File'!$B:$B,'Account Summary'!C7)/(COUNTIFS('Base File'!$AZ:$AZ,"Met",'Base File'!$B:$B,'Account Summary'!C7)+COUNTIFS('Base File'!$AZ:$AZ,"Not Met",'Base File'!$B:$B,'Account Summary'!C7)),"NR") -> 0.63636364 | Y7: =IFERROR(COUNTIFS('Base File'!$G:$G,"Contractual SLA",'Base File'!$H:$H,"No",'Base File'!$B:$B,'Account Summary'!$C7,'Base File'!$AZ:$AZ,"Met")/SUM(COUNTIFS('Base File'!$G:$G,"Contractual SLA",'Base File'!$H:$H,"No",'Base File'!$B:$B,'Account Summary'!$C7,'Base File'!$AZ:$AZ,"Met")+COUNTIFS('Base File'!$G:$G,"Contractual SLA",'Base File'!$H:$H,"No",'Base File'!$B:$B,'Account Summary'!$C7,'Base File'!$AZ:$AZ,"Not Met")),"-") -> 0.6 | Z7: =IFERROR(COUNTIFS('Base File'!$G:$G,"Contractual SLA",'Base File'!$H:$H,"Yes",'Base File'!$B:$B,'Account Summary'!$C7,'Base File'!$AZ:$AZ,"Met")/SUM(COUNTIFS('Base File'!$G:$G,"Contractual SLA",'Base File'!$H:$H,"yes",'Base File'!$B:$B,'Account Summary'!$C7,'Base File'!$AZ:$AZ,"Met")+COUNTIFS('Base File'!$G:$G,"Contractual SLA",'Base File'!$H:$H,"yes",'Base File'!$B:$B,'Account Summary'!$C7,'Base File'!$AZ:$AZ,"Not Met")),"-") -> - | AA7: =IFERROR(COUNTIFS('Base File'!$G:$G,"Internal KPI",'Base File'!$B:$B,'Account Summary'!$C7,'Base File'!$AZ:$AZ,"Met")/SUM(COUNTIFS('Base File'!$G:$G,"Internal KPI",'Base File'!$B:$B,'Account Summary'!$C7,'Base File'!$AZ:$AZ,"Met")+COUNTIFS('Base File'!$G:$G,"Internal KPI",'Base File'!$B:$B,'Account Summary'!$C7,'Base File'!$AZ:$AZ,"Not Met")),"-") -> 0.66666667 | AB7: =IFERROR(COUNTIFS('Base File'!$BB:$BB,"Met",'Base File'!$B:$B,'Account Summary'!C7)/(COUNTIFS('Base File'!$BB:$BB,"Met",'Base File'!$B:$B,'Account Summary'!C7)+COUNTIFS('Base File'!$BB:$BB,"Not Met",'Base File'!$B:$B,'Account Summary'!C7)),"NR") -> 0.63636364 | AC7: =IFERROR(COUNTIFS('Base File'!$G:$G,"Contractual SLA",'Base File'!$H:$H,"No",'Base File'!$B:$B,'Account Summary'!$C7,'Base File'!$BB:$BB,"Met")/SUM(COUNTIFS('Base File'!$G:$G,"Contractual SLA",'Base File'!$H:$H,"No",'Base File'!$B:$B,'Account Summary'!$C7,'Base File'!$BB:$BB,"Met")+COUNTIFS('Base File'!$G:$G,"Contractual SLA",'Base File'!$H:$H,"No",'Base File'!$B:$B,'Account Summary'!$C7,'Base File'!$BB:$BB,"Not Met")),"-") -> 0.8 | AD7: =IFERROR(COUNTIFS('Base File'!$G:$G,"Contractual SLA",'Base File'!$H:$H,"Yes",'Base File'!$B:$B,'Account Summary'!$C7,'Base File'!$BB:$BB,"Met")/SUM(COUNTIFS('Base File'!$G:$G,"Contractual SLA",'Base File'!$H:$H,"yes",'Base File'!$B:$B,'Account Summary'!$C7,'Base File'!$BB:$BB,"Met")+COUNTIFS('Base File'!$G:$G,"Contractual SLA",'Base File'!$H:$H,"yes",'Base File'!$B:$B,'Account Summary'!$C7,'Base File'!$BB:$BB,"Not Met")),"-") -> - | AE7: =IFERROR(COUNTIFS('Base File'!$G:$G,"Internal KPI",'Base File'!$B:$B,'Account Summary'!$C7,'Base File'!$BB:$BB,"Met")/SUM(COUNTIFS('Base File'!$G:$G,"Internal KPI",'Base File'!$B:$B,'Account Summary'!$C7,'Base File'!$BB:$BB,"Met")+COUNTIFS('Base File'!$G:$G,"Internal KPI",'Base File'!$B:$B,'Account Summary'!$C7,'Base File'!$BB:$BB,"Not Met")),"-") -> 0.5 | AF7: =IFERROR(COUNTIFS('Base File'!$BD:$BD,"Met",'Base File'!$B:$B,'Account Summary'!C7)/(COUNTIFS('Base File'!$BD:$BD,"Met",'Base File'!$B:$B,'Account Summary'!C7)+COUNTIFS('Base File'!$BD:$BD,"Not Met",'Base File'!$B:$B,'Account Summary'!C7)),"NR") -> 0.63636364 | AG7: =IFERROR(COUNTIFS('Base File'!$G:$G,"Contractual SLA",'Base File'!$H:$H,"No",'Base File'!$B:$B,'Account Summary'!$C7,'Base File'!$BD:$BD,"Met")/SUM(COUNTIFS('Base File'!$G:$G,"Contractual SLA",'Base File'!$H:$H,"No",'Base File'!$B:$B,'Account Summary'!$C7,'Base File'!$BD:$BD,"Met")+COUNTIFS('Base File'!$G:$G,"Contractual SLA",'Base File'!$H:$H,"No",'Base File'!$B:$B,'Account Summary'!$C7,'Base File'!$BD:$BD,"Not Met")),"-") -> 0.6 | AH7: =IFERROR(COUNTIFS('Base File'!$G:$G,"Contractual SLA",'Base File'!$H:$H,"Yes",'Base File'!$B:$B,'Account Summary'!$C7,'Base File'!$BD:$BD,"Met")/SUM(COUNTIFS('Base File'!$G:$G,"Contractual SLA",'Base File'!$H:$H,"yes",'Base File'!$B:$B,'Account Summary'!$C7,'Base File'!$BD:$BD,"Met")+COUNTIFS('Base File'!$G:$G,"Contractual SLA",'Base File'!$H:$H,"yes",'Base File'!$B:$B,'Account Summary'!$C7,'Base File'!$BD:$BD,"Not Met")),"-") -> - | AI7: =IFERROR(COUNTIFS('Base File'!$G:$G,"Internal KPI",'Base File'!$B:$B,'Account Summary'!$C7,'Base File'!$BD:$BD,"Met")/SUM(COUNTIFS('Base File'!$G:$G,"Internal KPI",'Base File'!$B:$B,'Account Summary'!$C7,'Base File'!$BD:$BD,"Met")+COUNTIFS('Base File'!$G:$G,"Internal KPI",'Base File'!$B:$B,'Account Summary'!$C7,'Base File'!$BD:$BD,"Not Met")),"-") -> 0.66666667 | AJ7: =IFERROR(COUNTIFS('Base File'!$BF:$BF,"Met",'Base File'!$B:$B,'Account Summary'!C7)/(COUNTIFS('Base File'!$BF:$BF,"Met",'Base File'!$B:$B,'Account Summary'!C7)+COUNTIFS('Base File'!$BF:$BF,"Not Met",'Base File'!$B:$B,'Account Summary'!C7)),"NR") -> 0.54545455 | AK7: =IFERROR(COUNTIFS('Base File'!$G:$G,"Contractual SLA",'Base File'!$H:$H,"No",'Base File'!$B:$B,'Account Summary'!$C7,'Base File'!$BF:$BF,"Met")/SUM(COUNTIFS('Base File'!$G:$G,"Contractual SLA",'Base File'!$H:$H,"No",'Base File'!$B:$B,'Account Summary'!$C7,'Base File'!$BF:$BF,"Met")+COUNTIFS('Base File'!$G:$G,"Contractual SLA",'Base File'!$H:$H,"No",'Base File'!$B:$B,'Account Summary'!$C7,'Base File'!$BF:$BF,"Not Met")),"-") -> 0.8 | AL7: =IFERROR(COUNTIFS('Base File'!$G:$G,"Contractual SLA",'Base File'!$H:$H,"Yes",'Base File'!$B:$B,'Account Summary'!$C7,'Base File'!$BF:$BF,"Met")/SUM(COUNTIFS('Base File'!$G:$G,"Contractual SLA",'Base File'!$H:$H,"yes",'Base File'!$B:$B,'Account Summary'!$C7,'Base File'!$BF:$BF,"Met")+COUNTIFS('Base File'!$G:$G,"Contractual SLA",'Base File'!$H:$H,"yes",'Base File'!$B:$B,'Account Summary'!$C7,'Base File'!$BF:$BF,"Not Met")),"-") -> - | AM7: =IFERROR(COUNTIFS('Base File'!$G:$G,"Internal KPI",'Base File'!$B:$B,'Account Summary'!$C7,'Base File'!$BF:$BF,"Met")/SUM(COUNTIFS('Base File'!$G:$G,"Internal KPI",'Base File'!$B:$B,'Account Summary'!$C7,'Base File'!$BF:$BF,"Met")+COUNTIFS('Base File'!$G:$G,"Internal KPI",'Base File'!$B:$B,'Account Summary'!$C7,'Base File'!$BF:$BF,"Not Met")),"-") -> 0.33333333 | AN7: =IFERROR(COUNTIFS('Base File'!$BH:$BH,"Met",'Base File'!$B:$B,'Account Summary'!C7)/(COUNTIFS('Base File'!$BH:$BH,"Met",'Base File'!$B:$B,'Account Summary'!C7)+COUNTIFS('Base File'!$BH:$BH,"Not Met",'Base File'!$B:$B,'Account Summary'!C7)),"NR") -> 0.72727273 | AO7: NR | AP7: =IFERROR(COUNTIFS('Base File'!$G:$G,"Contractual SLA",'Base File'!$H:$H,"Yes",'Base File'!$B:$B,'Account Summary'!$C7,'Base File'!$BH:$BH,"Met")/SUM(COUNTIFS('Base File'!$G:$G,"Contractual SLA",'Base File'!$H:$H,"yes",'Base File'!$B:$B,'Account Summary'!$C7,'Base File'!$BH:$BH,"Met")+COUNTIFS('Base File'!$G:$G,"Contractual SLA",'Base File'!$H:$H,"yes",'Base File'!$B:$B,'Account Summary'!$C7,'Base File'!$BH:$BH,"Not Met")),"-") -> - | AQ7: NR | AR7: =IFERROR(COUNTIFS('Base File'!$BJ:$BJ,"Met",'Base File'!$B:$B,'Account Summary'!C7)/(COUNTIFS('Base File'!$BJ:$BJ,"Met",'Base File'!$B:$B,'Account Summary'!C7)+COUNTIFS('Base File'!$BJ:$BJ,"Not Met",'Base File'!$B:$B,'Account Summary'!C7)),"NR") -> 0.81818182 | AS7: NR | AT7: =IFERROR(COUNTIFS('Base File'!$G:$G,"Contractual SLA",'Base File'!$H:$H,"Yes",'Base File'!$B:$B,'Account Summary'!$C7,'Base File'!$BJ:$BJ,"Met")/SUM(COUNTIFS('Base File'!$G:$G,"Contractual SLA",'Base File'!$H:$H,"yes",'Base File'!$B:$B,'Account Summary'!$C7,'Base File'!$BJ:$BJ,"Met")+COUNTIFS('Base File'!$G:$G,"Contractual SLA",'Base File'!$H:$H,"yes",'Base File'!$B:$B,'Account Summary'!$C7,'Base File'!$BJ:$BJ,"Not Met")),"-") -> - | AU7: NR | AV7: =IFERROR(COUNTIFS('Base File'!$BL:$BL,"Met",'Base File'!$B:$B,'Account Summary'!C7)/(COUNTIFS('Base File'!$BL:$BL,"Met",'Base File'!$B:$B,'Account Summary'!C7)+COUNTIFS('Base File'!$BL:$BL,"Not Met",'Base File'!$B:$B,'Account Summary'!C7)),"NR") -> 0.72727273 | AW7: =IFERROR(COUNTIFS('Base File'!$G:$G,"Contractual SLA",'Base File'!$H:$H,"No",'Base File'!$B:$B,'Account Summary'!$C7,'Base File'!$BL:$BL,"Met")/SUM(COUNTIFS('Base File'!$G:$G,"Contractual SLA",'Base File'!$H:$H,"No",'Base File'!$B:$B,'Account Summary'!$C7,'Base File'!$BL:$BL,"Met")+COUNTIFS('Base File'!$G:$G,"Contractual SLA",'Base File'!$H:$H,"No",'Base File'!$B:$B,'Account Summary'!$C7,'Base File'!$BL:$BL,"Not Met")),"-") -> 0.8 | AX7: =IFERROR(COUNTIFS('Base File'!$G:$G,"Contractual SLA",'Base File'!$H:$H,"Yes",'Base File'!$B:$B,'Account Summary'!$C7,'Base File'!$BL:$BL,"Met")/SUM(COUNTIFS('Base File'!$G:$G,"Contractual SLA",'Base File'!$H:$H,"yes",'Base File'!$B:$B,'Account Summary'!$C7,'Base File'!$BL:$BL,"Met")+COUNTIFS('Base File'!$G:$G,"Contractual SLA",'Base File'!$H:$H,"yes",'Base File'!$B:$B,'Account Summary'!$C7,'Base File'!$BL:$BL,"Not Met")),"-") -> - | AY7: =IFERROR(COUNTIFS('Base File'!$G:$G,"Internal KPI",'Base File'!$B:$B,'Account Summary'!$C7,'Base File'!$BL:$BL,"Met")/SUM(COUNTIFS('Base File'!$G:$G,"Internal KPI",'Base File'!$B:$B,'Account Summary'!$C7,'Base File'!$BL:$BL,"Met")+COUNTIFS('Base File'!$G:$G,"Internal KPI",'Base File'!$B:$B,'Account Summary'!$C7,'Base File'!$BL:$BL,"Not Met")),"-") -> 0.66666667 | AZ7: 0.72727273 | BA7: 0.8 | BB7: - | BC7: 0.66666667 | BD7: =IFERROR(COUNTIFS('Base File'!$BP:$BP,"Met",'Base File'!$B:$B,'Account Summary'!C7)/(COUNTIFS('Base File'!$BP:$BP,"Met",'Base File'!$B:$B,'Account Summary'!C7)+COUNTIFS('Base File'!$BP:$BP,"Not Met",'Base File'!$B:$B,'Account Summary'!C7)),"NR") -> NR | BE7: NR | BF7: =IFERROR(COUNTIFS('Base File'!$G:$G,"Contractual SLA",'Base File'!$H:$H,"Yes",'Base File'!$B:$B,'Account Summary'!$C7,'Base File'!$BP:$BP,"Met")/SUM(COUNTIFS('Base File'!$G:$G,"Contractual SLA",'Base File'!$H:$H,"yes",'Base File'!$B:$B,'Account Summary'!$C7,'Base File'!$BP:$BP,"Met")+COUNTIFS('Base File'!$G:$G,"Contractual SLA",'Base File'!$H:$H,"yes",'Base File'!$B:$B,'Account Summary'!$C7,'Base File'!$BP:$BP,"Not Met")),"-") -> - | BG7: NR | BH7: =IFERROR(COUNTIFS('Base File'!$BR:$BR,"Met",'Base File'!$B:$B,'Account Summary'!C7)/(COUNTIFS('Base File'!$BR:$BR,"Met",'Base File'!$B:$B,'Account Summary'!C7)+COUNTIFS('Base File'!$BR:$BR,"Not Met",'Base File'!$B:$B,'Account Summary'!C7)),"NR") -> NR | BI7: NR | BJ7: =IFERROR(COUNTIFS('Base File'!$G:$G,"Contractual SLA",'Base File'!$H:$H,"No",'Base File'!$B:$B,'Account Summary'!$C7,'Base File'!$BR:$BR,"Met")/SUM(COUNTIFS('Base File'!$G:$G,"Contractual SLA",'Base File'!$H:$H,"No",'Base File'!$B:$B,'Account Summary'!$C7,'Base File'!$BR:$BR,"Met")+COUNTIFS('Base File'!$G:$G,"Contractual SLA",'Base File'!$H:$H,"No",'Base File'!$B:$B,'Account Summary'!$C7,'Base File'!$BR:$BR,"Not Met")),"-") -> - | BK7: NR | BL7: =IFERROR(COUNTIFS('Base File'!$BT:$BT,"Met",'Base File'!$B:$B,'Account Summary'!C7)/(COUNTIFS('Base File'!$BT:$BT,"Met",'Base File'!$B:$B,'Account Summary'!C7)+COUNTIFS('Base File'!$BT:$BT,"Not Met",'Base File'!$B:$B,'Account Summary'!C7)),"NR") -> 0.54545455 | BM7: =IFERROR(COUNTIFS('Base File'!$G:$G,"Contractual SLA",'Base File'!$H:$H,"No",'Base File'!$B:$B,'Account Summary'!$C7,'Base File'!$BT:$BT,"Met")/SUM(COUNTIFS('Base File'!$G:$G,"Contractual SLA",'Base File'!$H:$H,"No",'Base File'!$B:$B,'Account Summary'!$C7,'Base File'!$BT:$BT,"Met")+COUNTIFS('Base File'!$G:$G,"Contractual SLA",'Base File'!$H:$H,"No",'Base File'!$B:$B,'Account Summary'!$C7,'Base File'!$BT:$BT,"Not Met")),"-") -> 1 | BN7: =IFERROR(COUNTIFS('Base File'!$G:$G,"Contractual SLA",'Base File'!$H:$H,"Yes",'Base File'!$B:$B,'Account Summary'!$C7,'Base File'!$BT:$BT,"Met")/SUM(COUNTIFS('Base File'!$G:$G,"Contractual SLA",'Base File'!$H:$H,"yes",'Base File'!$B:$B,'Account Summary'!$C7,'Base File'!$BT:$BT,"Met")+COUNTIFS('Base File'!$G:$G,"Contractual SLA",'Base File'!$H:$H,"yes",'Base File'!$B:$B,'Account Summary'!$C7,'Base File'!$BT:$BT,"Not Met")),"-") -> - | BO7: =IFERROR(COUNTIFS('Base File'!$G:$G,"Internal KPI",'Base File'!$B:$B,'Account Summary'!$C7,'Base File'!$BT:$BT,"Met")/SUM(COUNTIFS('Base File'!$G:$G,"Internal KPI",'Base File'!$B:$B,'Account Summary'!$C7,'Base File'!$BT:$BT,"Met")+COUNTIFS('Base File'!$G:$G,"Internal KPI",'Base File'!$B:$B,'Account Summary'!$C7,'Base File'!$BT:$BT,"Not Met")),"-") -> 0.16666667 | BP7: =IFERROR(COUNTIFS('Base File'!$BV:$BV,"Met",'Base File'!$B:$B,'Account Summary'!C7)/(COUNTIFS('Base File'!$BV:$BV,"Met",'Base File'!$B:$B,'Account Summary'!C7)+COUNTIFS('Base File'!$BV:$BV,"Not Met",'Base File'!$B:$B,'Account Summary'!C7)),"NR") -> 0.63636364 | BQ7: 0.8 | BR7: =IFERROR(COUNTIFS('Base File'!$G:$G,"Contractual SLA",'Base File'!$H:$H,"Yes",'Base File'!$B:$B,'Account Summary'!$C7,'Base File'!$BV:$BV,"Met")/SUM(COUNTIFS('Base File'!$G:$G,"Contractual SLA",'Base File'!$H:$H,"Yes",'Base File'!$B:$B,'Account Summary'!$C7,'Base File'!$BV:$BV,"Met")+COUNTIFS('Base File'!$G:$G,"Contractual SLA",'Base File'!$H:$H,"Yes",'Base File'!$B:$B,'Account Summary'!$C7,'Base File'!$BV:$BV,"Not Met")),"-") -> - | BS7: =IFERROR(COUNTIFS('Base File'!$G:$G,"Internal KPI",'Base File'!$B:$B,'Account Summary'!$C9,'Base File'!$BV:$BV,"Met")/SUM(COUNTIFS('Base File'!$G:$G,"Internal KPI",'Base File'!$B:$B,'Account Summary'!$C9,'Base File'!$BV:$BV,"Met")+COUNTIFS('Base File'!$G:$G,"Internal KPI",'Base File'!$B:$B,'Account Summary'!$C9,'Base File'!$BV:$BV,"Not Met")),"-") -> 0.5
B8: 5 | C8: Robert Bosch | D8: Bangalore | E8: South 1 | F8: Himanshu Srivastava & Mehvish Naz | I8: Sulabh | J8: NA | K8: NA | L8: NA | M8: NA | N8: - | O8: NA | P8: NA | Q8: NA | R8: =IFERROR(COUNTIFS('Base File'!$G:$G,"Contractual SLA",'Base File'!$H:$H,"Yes",'Base File'!$B:$B,'Account Summary'!$C8,'Base File'!$AV:$AV,"Met")/SUM(COUNTIFS('Base File'!$G:$G,"Contractual SLA",'Base File'!$H:$H,"yes",'Base File'!$B:$B,'Account Summary'!$C8,'Base File'!$AV:$AV,"Met")+COUNTIFS('Base File'!$G:$G,"Contractual SLA",'Base File'!$H:$H,"yes",'Base File'!$B:$B,'Account Summary'!$C8,'Base File'!$AV:$AV,"Not Met")),"-") -> - | S8: NA | T8: NA | U8: NA | V8: =IFERROR(COUNTIFS('Base File'!$G:$G,"Contractual SLA",'Base File'!$H:$H,"Yes",'Base File'!$B:$B,'Account Summary'!$C8,'Base File'!$AX:$AX,"Met")/SUM(COUNTIFS('Base File'!$G:$G,"Contractual SLA",'Base File'!$H:$H,"yes",'Base File'!$B:$B,'Account Summary'!$C8,'Base File'!$AX:$AX,"Met")+COUNTIFS('Base File'!$G:$G,"Contractual SLA",'Base File'!$H:$H,"yes",'Base File'!$B:$B,'Account Summary'!$C8,'Base File'!$AX:$AX,"Not Met")),"NA") -> NA | W8: NA | X8: NA | Y8: NA | Z8: =IFERROR(COUNTIFS('Base File'!$G:$G,"Contractual SLA",'Base File'!$H:$H,"Yes",'Base File'!$B:$B,'Account Summary'!$C8,'Base File'!$AZ:$AZ,"Met")/SUM(COUNTIFS('Base File'!$G:$G,"Contractual SLA",'Base File'!$H:$H,"yes",'Base File'!$B:$B,'Account Summary'!$C8,'Base File'!$AZ:$AZ,"Met")+COUNTIFS('Base File'!$G:$G,"Contractual SLA",'Base File'!$H:$H,"yes",'Base File'!$B:$B,'Account Summary'!$C8,'Base File'!$AZ:$AZ,"Not Met")),"-") -> - | AA8: NA | AB8: NA | AC8: NA | AD8: =IFERROR(COUNTIFS('Base File'!$G:$G,"Contractual SLA",'Base File'!$H:$H,"Yes",'Base File'!$B:$B,'Account Summary'!$C8,'Base File'!$BB:$BB,"Met")/SUM(COUNTIFS('Base File'!$G:$G,"Contractual SLA",'Base File'!$H:$H,"yes",'Base File'!$B:$B,'Account Summary'!$C8,'Base File'!$BB:$BB,"Met")+COUNTIFS('Base File'!$G:$G,"Contractual SLA",'Base File'!$H:$H,"yes",'Base File'!$B:$B,'Account Summary'!$C8,'Base File'!$BB:$BB,"Not Met")),"-") -> - | AE8: NA | AF8: NA | AG8: NA | AH8: =IFERROR(COUNTIFS('Base File'!$G:$G,"Contractual SLA",'Base File'!$H:$H,"Yes",'Base File'!$B:$B,'Account Summary'!$C8,'Base File'!$AZ:$AZ,"Met")/SUM(COUNTIFS('Base File'!$G:$G,"Contractual SLA",'Base File'!$H:$H,"yes",'Base File'!$B:$B,'Account Summary'!$C8,'Base File'!$AZ:$AZ,"Met")+COUNTIFS('Base File'!$G:$G,"Contractual SLA",'Base File'!$H:$H,"yes",'Base File'!$B:$B,'Account Summary'!$C8,'Base File'!$AZ:$AZ,"Not Met")),"-") -> - | AI8: NA | AJ8: NA | AK8: NA | AL8: =IFERROR(COUNTIFS('Base File'!$G:$G,"Contractual SLA",'Base File'!$H:$H,"Yes",'Base File'!$B:$B,'Account Summary'!$C8,'Base File'!$AZ:$AZ,"Met")/SUM(COUNTIFS('Base File'!$G:$G,"Contractual SLA",'Base File'!$H:$H,"yes",'Base File'!$B:$B,'Account Summary'!$C8,'Base File'!$AZ:$AZ,"Met")+COUNTIFS('Base File'!$G:$G,"Contractual SLA",'Base File'!$H:$H,"yes",'Base File'!$B:$B,'Account Summary'!$C8,'Base File'!$AZ:$AZ,"Not Met")),"-") -> - | AM8: NA | AN8: NA | AO8: NA | AP8: =IFERROR(COUNTIFS('Base File'!$G:$G,"Contractual SLA",'Base File'!$H:$H,"Yes",'Base File'!$B:$B,'Account Summary'!$C8,'Base File'!$BH:$BH,"Met")/SUM(COUNTIFS('Base File'!$G:$G,"Contractual SLA",'Base File'!$H:$H,"yes",'Base File'!$B:$B,'Account Summary'!$C8,'Base File'!$BH:$BH,"Met")+COUNTIFS('Base File'!$G:$G,"Contractual SLA",'Base File'!$H:$H,"yes",'Base File'!$B:$B,'Account Summary'!$C8,'Base File'!$BH:$BH,"Not Met")),"-") -> - | AQ8: NA | AR8: NA | AS8: NA | AT8: =IFERROR(COUNTIFS('Base File'!$G:$G,"Contractual SLA",'Base File'!$H:$H,"Yes",'Base File'!$B:$B,'Account Summary'!$C8,'Base File'!$BJ:$BJ,"Met")/SUM(COUNTIFS('Base File'!$G:$G,"Contractual SLA",'Base File'!$H:$H,"yes",'Base File'!$B:$B,'Account Summary'!$C8,'Base File'!$BJ:$BJ,"Met")+COUNTIFS('Base File'!$G:$G,"Contractual SLA",'Base File'!$H:$H,"yes",'Base File'!$B:$B,'Account Summary'!$C8,'Base File'!$BJ:$BJ,"Not Met")),"-") -> - | AU8: NA | AV8: NA | AW8: NA | AX8: =IFERROR(COUNTIFS('Base File'!$G:$G,"Contractual SLA",'Base File'!$H:$H,"Yes",'Base File'!$B:$B,'Account Summary'!$C8,'Base File'!$BL:$BL,"Met")/SUM(COUNTIFS('Base File'!$G:$G,"Contractual SLA",'Base File'!$H:$H,"yes",'Base File'!$B:$B,'Account Summary'!$C8,'Base File'!$BL:$BL,"Met")+COUNTIFS('Base File'!$G:$G,"Contractual SLA",'Base File'!$H:$H,"yes",'Base File'!$B:$B,'Account Summary'!$C8,'Base File'!$BL:$BL,"Not Met")),"-") -> - | AY8: NA | AZ8: NA | BA8: NA | BB8: - | BC8: NA | BD8: NA | BE8: NA | BF8: =IFERROR(COUNTIFS('Base File'!$G:$G,"Contractual SLA",'Base File'!$H:$H,"Yes",'Base File'!$B:$B,'Account Summary'!$C8,'Base File'!$BP:$BP,"Met")/SUM(COUNTIFS('Base File'!$G:$G,"Contractual SLA",'Base File'!$H:$H,"yes",'Base File'!$B:$B,'Account Summary'!$C8,'Base File'!$BP:$BP,"Met")+COUNTIFS('Base File'!$G:$G,"Contractual SLA",'Base File'!$H:$H,"yes",'Base File'!$B:$B,'Account Summary'!$C8,'Base File'!$BP:$BP,"Not Met")),"-") -> - | BG8: NA | BH8: NA | BI8: NA | BJ8: =IFERROR(COUNTIFS('Base File'!$G:$G,"Contractual SLA",'Base File'!$H:$H,"No",'Base File'!$B:$B,'Account Summary'!$C8,'Base File'!$BR:$BR,"Met")/SUM(COUNTIFS('Base File'!$G:$G,"Contractual SLA",'Base File'!$H:$H,"No",'Base File'!$B:$B,'Account Summary'!$C8,'Base File'!$BR:$BR,"Met")+COUNTIFS('Base File'!$G:$G,"Contractual SLA",'Base File'!$H:$H,"No",'Base File'!$B:$B,'Account Summary'!$C8,'Base File'!$BR:$BR,"Not Met")),"-") -> - | BK8: NA | BL8: NA | BM8: NA | BN8: =IFERROR(COUNTIFS('Base File'!$G:$G,"Contractual SLA",'Base File'!$H:$H,"Yes",'Base File'!$B:$B,'Account Summary'!$C8,'Base File'!$BT:$BT,"Met")/SUM(COUNTIFS('Base File'!$G:$G,"Contractual SLA",'Base File'!$H:$H,"yes",'Base File'!$B:$B,'Account Summary'!$C8,'Base File'!$BT:$BT,"Met")+COUNTIFS('Base File'!$G:$G,"Contractual SLA",'Base File'!$H:$H,"yes",'Base File'!$B:$B,'Account Summary'!$C8,'Base File'!$BT:$BT,"Not Met")),"-") -> - | BO8: NA | BP8: NA | BQ8: NA | BR8: =IFERROR(COUNTIFS('Base File'!$G:$G,"Contractual SLA",'Base File'!$H:$H,"Yes",'Base File'!$B:$B,'Account Summary'!$C8,'Base File'!$BT:$BT,"Met")/SUM(COUNTIFS('Base File'!$G:$G,"Contractual SLA",'Base File'!$H:$H,"yes",'Base File'!$B:$B,'Account Summary'!$C8,'Base File'!$BT:$BT,"Met")+COUNTIFS('Base File'!$G:$G,"Contractual SLA",'Base File'!$H:$H,"yes",'Base File'!$B:$B,'Account Summary'!$C8,'Base File'!$BT:$BT,"Not Met")),"-") -> - | BS8: NA
B9: 6 | C9: Siemens - Energy | D9: Bangalore | E9: South 1 | F9: Himanshu Srivastava & Mehvish Naz | I9: Sulabh | J9: Reported | K9: Validated | L9: =IFERROR(COUNTIFS('Base File'!$AR:$AR,"Met",'Base File'!$B:$B,'Account Summary'!C9)/(COUNTIFS('Base File'!$AR:$AR,"Met",'Base File'!$B:$B,'Account Summary'!C9)+COUNTIFS('Base File'!$AR:$AR,"Not Met",'Base File'!$B:$B,'Account Summary'!C9)),"NR") -> 0.54545455 | M9: =IFERROR(COUNTIFS('Base File'!$G:$G,"Contractual SLA",'Base File'!$H:$H,"No",'Base File'!$B:$B,'Account Summary'!$C9,'Base File'!$AR:$AR,"Met")/SUM(COUNTIFS('Base File'!$G:$G,"Contractual SLA",'Base File'!$H:$H,"No",'Base File'!$B:$B,'Account Summary'!$C9,'Base File'!$AR:$AR,"Met")+COUNTIFS('Base File'!$G:$G,"Contractual SLA",'Base File'!$H:$H,"No",'Base File'!$B:$B,'Account Summary'!$C9,'Base File'!$AR:$AR,"Not Met")),"-") -> 0.6 | N9: =IFERROR(COUNTIFS('Base File'!$G:$G,"Contractual SLA",'Base File'!$H:$H,"Yes",'Base File'!$B:$B,'Account Summary'!$C9,'Base File'!$AR:$AR,"Met")/SUM(COUNTIFS('Base File'!$G:$G,"Contractual SLA",'Base File'!$H:$H,"yes",'Base File'!$B:$B,'Account Summary'!$C9,'Base File'!$AR:$AR,"Met")+COUNTIFS('Base File'!$G:$G,"Contractual SLA",'Base File'!$H:$H,"yes",'Base File'!$B:$B,'Account Summary'!$C9,'Base File'!$AR:$AR,"Not Met")),"-") -> - | O9: =IFERROR(COUNTIFS('Base File'!$G:$G,"Internal KPI",'Base File'!$B:$B,'Account Summary'!$C9,'Base File'!$AR:$AR,"Met")/SUM(COUNTIFS('Base File'!$G:$G,"Internal KPI",'Base File'!$B:$B,'Account Summary'!$C9,'Base File'!$AR:$AR,"Met")+COUNTIFS('Base File'!$G:$G,"Internal KPI",'Base File'!$B:$B,'Account Summary'!$C9,'Base File'!$AR:$AR,"Not Met")),"-") -> 0.5 | P9: =IFERROR(COUNTIFS('Base File'!$AV:$AV,"Met",'Base File'!$B:$B,'Account Summary'!C9)/(COUNTIFS('Base File'!$AV:$AV,"Met",'Base File'!$B:$B,'Account Summary'!C9)+COUNTIFS('Base File'!$AV:$AV,"Not Met",'Base File'!$B:$B,'Account Summary'!C9)),"NR") -> 0.81818182 | Q9: =IFERROR(COUNTIFS('Base File'!$G:$G,"Contractual SLA",'Base File'!$H:$H,"No",'Base File'!$B:$B,'Account Summary'!$C9,'Base File'!$AV:$AV,"Met")/SUM(COUNTIFS('Base File'!$G:$G,"Contractual SLA",'Base File'!$H:$H,"No",'Base File'!$B:$B,'Account Summary'!$C9,'Base File'!$AV:$AV,"Met")+COUNTIFS('Base File'!$G:$G,"Contractual SLA",'Base File'!$H:$H,"No",'Base File'!$B:$B,'Account Summary'!$C9,'Base File'!$AV:$AV,"Not Met")),"-") -> 1 | R9: =IFERROR(COUNTIFS('Base File'!$G:$G,"Contractual SLA",'Base File'!$H:$H,"Yes",'Base File'!$B:$B,'Account Summary'!$C9,'Base File'!$AV:$AV,"Met")/SUM(COUNTIFS('Base File'!$G:$G,"Contractual SLA",'Base File'!$H:$H,"yes",'Base File'!$B:$B,'Account Summary'!$C9,'Base File'!$AV:$AV,"Met")+COUNTIFS('Base File'!$G:$G,"Contractual SLA",'Base File'!$H:$H,"yes",'Base File'!$B:$B,'Account Summary'!$C9,'Base File'!$AV:$AV,"Not Met")),"-") -> - | S9: =IFERROR(COUNTIFS('Base File'!$G:$G,"Internal KPI",'Base File'!$B:$B,'Account Summary'!$C9,'Base File'!$AV:$AV,"Met")/SUM(COUNTIFS('Base File'!$G:$G,"Internal KPI",'Base File'!$B:$B,'Account Summary'!$C9,'Base File'!$AV:$AV,"Met")+COUNTIFS('Base File'!$G:$G,"Internal KPI",'Base File'!$B:$B,'Account Summary'!$C9,'Base File'!$AV:$AV,"Not Met")),"-") -> 0.66666667 | T9: =IFERROR(COUNTIFS('Base File'!$AX:$AX,"Met",'Base File'!$B:$B,'Account Summary'!C9)/(COUNTIFS('Base File'!$AX:$AX,"Met",'Base File'!$B:$B,'Account Summary'!C9)+COUNTIFS('Base File'!$AX:$AX,"Not Met",'Base File'!$B:$B,'Account Summary'!C9)),"NR") -> 0.72727273 | U9: =IFERROR(COUNTIFS('Base File'!$G:$G,"Contractual SLA",'Base File'!$H:$H,"No",'Base File'!$B:$B,'Account Summary'!$C9,'Base File'!$AX:$AX,"Met")/SUM(COUNTIFS('Base File'!$G:$G,"Contractual SLA",'Base File'!$H:$H,"No",'Base File'!$B:$B,'Account Summary'!$C9,'Base File'!$AX:$AX,"Met")+COUNTIFS('Base File'!$G:$G,"Contractual SLA",'Base File'!$H:$H,"No",'Base File'!$B:$B,'Account Summary'!$C9,'Base File'!$AX:$AX,"Not Met")),"-") -> 1 | V9: NA | W9: =IFERROR(COUNTIFS('Base File'!$G:$G,"Internal KPI",'Base File'!$B:$B,'Account Summary'!$C9,'Base File'!$AX:$AX,"Met")/SUM(COUNTIFS('Base File'!$G:$G,"Internal KPI",'Base File'!$B:$B,'Account Summary'!$C9,'Base File'!$AX:$AX,"Met")+COUNTIFS('Base File'!$G:$G,"Internal KPI",'Base File'!$B:$B,'Account Summary'!$C9,'Base File'!$AX:$AX,"Not Met")),"-") -> 0.5 | X9: =IFERROR(COUNTIFS('Base File'!$AZ:$AZ,"Met",'Base File'!$B:$B,'Account Summary'!C9)/(COUNTIFS('Base File'!$AZ:$AZ,"Met",'Base File'!$B:$B,'Account Summary'!C9)+COUNTIFS('Base File'!$AZ:$AZ,"Not Met",'Base File'!$B:$B,'Account Summary'!C9)),"NR") -> 0.81818182 | Y9: =IFERROR(COUNTIFS('Base File'!$G:$G,"Contractual SLA",'Base File'!$H:$H,"No",'Base File'!$B:$B,'Account Summary'!$C9,'Base File'!$AZ:$AZ,"Met")/SUM(COUNTIFS('Base File'!$G:$G,"Contractual SLA",'Base File'!$H:$H,"No",'Base File'!$B:$B,'Account Summary'!$C9,'Base File'!$AZ:$AZ,"Met")+COUNTIFS('Base File'!$G:$G,"Contractual SLA",'Base File'!$H:$H,"No",'Base File'!$B:$B,'Account Summary'!$C9,'Base File'!$AZ:$AZ,"Not Met")),"-") -> 1 | Z9: =IFERROR(COUNTIFS('Base File'!$G:$G,"Contractual SLA",'Base File'!$H:$H,"Yes",'Base File'!$B:$B,'Account Summary'!$C9,'Base File'!$AZ:$AZ,"Met")/SUM(COUNTIFS('Base File'!$G:$G,"Contractual SLA",'Base File'!$H:$H,"yes",'Base File'!$B:$B,'Account Summary'!$C9,'Base File'!$AZ:$AZ,"Met")+COUNTIFS('Base File'!$G:$G,"Contractual SLA",'Base File'!$H:$H,"yes",'Base File'!$B:$B,'Account Summary'!$C9,'Base File'!$AZ:$AZ,"Not Met")),"-") -> - | AA9: =IFERROR(COUNTIFS('Base File'!$G:$G,"Internal KPI",'Base File'!$B:$B,'Account Summary'!$C9,'Base File'!$AZ:$AZ,"Met")/SUM(COUNTIFS('Base File'!$G:$G,"Internal KPI",'Base File'!$B:$B,'Account Summary'!$C9,'Base File'!$AZ:$AZ,"Met")+COUNTIFS('Base File'!$G:$G,"Internal KPI",'Base File'!$B:$B,'Account Summary'!$C9,'Base File'!$AZ:$AZ,"Not Met")),"-") -> 0.66666667 | AB9: =IFERROR(COUNTIFS('Base File'!$BB:$BB,"Met",'Base File'!$B:$B,'Account Summary'!C9)/(COUNTIFS('Base File'!$BB:$BB,"Met",'Base File'!$B:$B,'Account Summary'!C9)+COUNTIFS('Base File'!$BB:$BB,"Not Met",'Base File'!$B:$B,'Account Summary'!C9)),"NR") -> 0.81818182 | AC9: =IFERROR(COUNTIFS('Base File'!$G:$G,"Contractual SLA",'Base File'!$H:$H,"No",'Base File'!$B:$B,'Account Summary'!$C9,'Base File'!$BB:$BB,"Met")/SUM(COUNTIFS('Base File'!$G:$G,"Contractual SLA",'Base File'!$H:$H,"No",'Base File'!$B:$B,'Account Summary'!$C9,'Base File'!$BB:$BB,"Met")+COUNTIFS('Base File'!$G:$G,"Contractual SLA",'Base File'!$H:$H,"No",'Base File'!$B:$B,'Account Summary'!$C9,'Base File'!$BB:$BB,"Not Met")),"-") -> 1 | AD9: =IFERROR(COUNTIFS('Base File'!$G:$G,"Contractual SLA",'Base File'!$H:$H,"Yes",'Base File'!$B:$B,'Account Summary'!$C9,'Base File'!$BB:$BB,"Met")/SUM(COUNTIFS('Base File'!$G:$G,"Contractual SLA",'Base File'!$H:$H,"yes",'Base File'!$B:$B,'Account Summary'!$C9,'Base File'!$BB:$BB,"Met")+COUNTIFS('Base File'!$G:$G,"Contractual SLA",'Base File'!$H:$H,"yes",'Base File'!$B:$B,'Account Summary'!$C9,'Base File'!$BB:$BB,"Not Met")),"-") -> - | AE9: =IFERROR(COUNTIFS('Base File'!$G:$G,"Internal KPI",'Base File'!$B:$B,'Account Summary'!$C9,'Base File'!$BB:$BB,"Met")/SUM(COUNTIFS('Base File'!$G:$G,"Internal KPI",'Base File'!$B:$B,'Account Summary'!$C9,'Base File'!$BB:$BB,"Met")+COUNTIFS('Base File'!$G:$G,"Internal KPI",'Base File'!$B:$B,'Account Summary'!$C9,'Base File'!$BB:$BB,"Not Met")),"-") -> 0.66666667 | AF9: =IFERROR(COUNTIFS('Base File'!$BD:$BD,"Met",'Base File'!$B:$B,'Account Summary'!C9)/(COUNTIFS('Base File'!$BD:$BD,"Met",'Base File'!$B:$B,'Account Summary'!C9)+COUNTIFS('Base File'!$BD:$BD,"Not Met",'Base File'!$B:$B,'Account Summary'!C9)),"NR") -> 0.63636364 | AG9: =IFERROR(COUNTIFS('Base File'!$G:$G,"Contractual SLA",'Base File'!$H:$H,"No",'Base File'!$B:$B,'Account Summary'!$C9,'Base File'!$BD:$BD,"Met")/SUM(COUNTIFS('Base File'!$G:$G,"Contractual SLA",'Base File'!$H:$H,"No",'Base File'!$B:$B,'Account Summary'!$C9,'Base File'!$BD:$BD,"Met")+COUNTIFS('Base File'!$G:$G,"Contractual SLA",'Base File'!$H:$H,"No",'Base File'!$B:$B,'Account Summary'!$C9,'Base File'!$BD:$BD,"Not Met")),"-") -> 0.8 | AH9: =IFERROR(COUNTIFS('Base File'!$G:$G,"Contractual SLA",'Base File'!$H:$H,"Yes",'Base File'!$B:$B,'Account Summary'!$C9,'Base File'!$BD:$BD,"Met")/SUM(COUNTIFS('Base File'!$G:$G,"Contractual SLA",'Base File'!$H:$H,"yes",'Base File'!$B:$B,'Account Summary'!$C9,'Base File'!$BD:$BD,"Met")+COUNTIFS('Base File'!$G:$G,"Contractual SLA",'Base File'!$H:$H,"yes",'Base File'!$B:$B,'Account Summary'!$C9,'Base File'!$BD:$BD,"Not Met")),"-") -> - | AI9: =IFERROR(COUNTIFS('Base File'!$G:$G,"Internal KPI",'Base File'!$B:$B,'Account Summary'!$C9,'Base File'!$BD:$BD,"Met")/SUM(COUNTIFS('Base File'!$G:$G,"Internal KPI",'Base File'!$B:$B,'Account Summary'!$C9,'Base File'!$BD:$BD,"Met")+COUNTIFS('Base File'!$G:$G,"Internal KPI",'Base File'!$B:$B,'Account Summary'!$C9,'Base File'!$BD:$BD,"Not Met")),"-") -> 0.5 | AJ9: =IFERROR(COUNTIFS('Base File'!$BF:$BF,"Met",'Base File'!$B:$B,'Account Summary'!C9)/(COUNTIFS('Base File'!$BF:$BF,"Met",'Base File'!$B:$B,'Account Summary'!C9)+COUNTIFS('Base File'!$BF:$BF,"Not Met",'Base File'!$B:$B,'Account Summary'!C9)),"NR") -> 0.54545455 | AK9: =IFERROR(COUNTIFS('Base File'!$G:$G,"Contractual SLA",'Base File'!$H:$H,"No",'Base File'!$B:$B,'Account Summary'!$C9,'Base File'!$BF:$BF,"Met")/SUM(COUNTIFS('Base File'!$G:$G,"Contractual SLA",'Base File'!$H:$H,"No",'Base File'!$B:$B,'Account Summary'!$C9,'Base File'!$BF:$BF,"Met")+COUNTIFS('Base File'!$G:$G,"Contractual SLA",'Base File'!$H:$H,"No",'Base File'!$B:$B,'Account Summary'!$C9,'Base File'!$BF:$BF,"Not Met")),"-") -> 1 | AL9: =IFERROR(COUNTIFS('Base File'!$G:$G,"Contractual SLA",'Base File'!$H:$H,"Yes",'Base File'!$B:$B,'Account Summary'!$C9,'Base File'!$BF:$BF,"Met")/SUM(COUNTIFS('Base File'!$G:$G,"Contractual SLA",'Base File'!$H:$H,"yes",'Base File'!$B:$B,'Account Summary'!$C9,'Base File'!$BF:$BF,"Met")+COUNTIFS('Base File'!$G:$G,"Contractual SLA",'Base File'!$H:$H,"yes",'Base File'!$B:$B,'Account Summary'!$C9,'Base File'!$BF:$BF,"Not Met")),"-") -> - | AM9: =IFERROR(COUNTIFS('Base File'!$G:$G,"Internal KPI",'Base File'!$B:$B,'Account Summary'!$C9,'Base File'!$BF:$BF,"Met")/SUM(COUNTIFS('Base File'!$G:$G,"Internal KPI",'Base File'!$B:$B,'Account Summary'!$C9,'Base File'!$BF:$BF,"Met")+COUNTIFS('Base File'!$G:$G,"Internal KPI",'Base File'!$B:$B,'Account Summary'!$C9,'Base File'!$BF:$BF,"Not Met")),"-") -> 0.16666667 | AN9: =IFERROR(COUNTIFS('Base File'!$BH:$BH,"Met",'Base File'!$B:$B,'Account Summary'!C9)/(COUNTIFS('Base File'!$BH:$BH,"Met",'Base File'!$B:$B,'Account Summary'!C9)+COUNTIFS('Base File'!$BH:$BH,"Not Met",'Base File'!$B:$B,'Account Summary'!C9)),"NR") -> 0.81818182 | AO9: NR | AP9: =IFERROR(COUNTIFS('Base File'!$G:$G,"Contractual SLA",'Base File'!$H:$H,"Yes",'Base File'!$B:$B,'Account Summary'!$C9,'Base File'!$BH:$BH,"Met")/SUM(COUNTIFS('Base File'!$G:$G,"Contractual SLA",'Base File'!$H:$H,"yes",'Base File'!$B:$B,'Account Summary'!$C9,'Base File'!$BH:$BH,"Met")+COUNTIFS('Base File'!$G:$G,"Contractual SLA",'Base File'!$H:$H,"yes",'Base File'!$B:$B,'Account Summary'!$C9,'Base File'!$BH:$BH,"Not Met")),"-") -> - | AQ9: NR | AR9: =IFERROR(COUNTIFS('Base File'!$BJ:$BJ,"Met",'Base File'!$B:$B,'Account Summary'!C9)/(COUNTIFS('Base File'!$BJ:$BJ,"Met",'Base File'!$B:$B,'Account Summary'!C9)+COUNTIFS('Base File'!$BJ:$BJ,"Not Met",'Base File'!$B:$B,'Account Summary'!C9)),"NR") -> 0.54545455 | AS9: NR | AT9: =IFERROR(COUNTIFS('Base File'!$G:$G,"Contractual SLA",'Base File'!$H:$H,"Yes",'Base File'!$B:$B,'Account Summary'!$C9,'Base File'!$BJ:$BJ,"Met")/SUM(COUNTIFS('Base File'!$G:$G,"Contractual SLA",'Base File'!$H:$H,"yes",'Base File'!$B:$B,'Account Summary'!$C9,'Base File'!$BJ:$BJ,"Met")+COUNTIFS('Base File'!$G:$G,"Contractual SLA",'Base File'!$H:$H,"yes",'Base File'!$B:$B,'Account Summary'!$C9,'Base File'!$BJ:$BJ,"Not Met")),"-") -> - | AU9: NR | AV9: =IFERROR(COUNTIFS('Base File'!$BL:$BL,"Met",'Base File'!$B:$B,'Account Summary'!C9)/(COUNTIFS('Base File'!$BL:$BL,"Met",'Base File'!$B:$B,'Account Summary'!C9)+COUNTIFS('Base File'!$BL:$BL,"Not Met",'Base File'!$B:$B,'Account Summary'!C9)),"NR") -> 0.54545455 | AW9: =IFERROR(COUNTIFS('Base File'!$G:$G,"Contractual SLA",'Base File'!$H:$H,"No",'Base File'!$B:$B,'Account Summary'!$C9,'Base File'!$BL:$BL,"Met")/SUM(COUNTIFS('Base File'!$G:$G,"Contractual SLA",'Base File'!$H:$H,"No",'Base File'!$B:$B,'Account Summary'!$C9,'Base File'!$BL:$BL,"Met")+COUNTIFS('Base File'!$G:$G,"Contractual SLA",'Base File'!$H:$H,"No",'Base File'!$B:$B,'Account Summary'!$C9,'Base File'!$BL:$BL,"Not Met")),"-") -> 1 | AX9: =IFERROR(COUNTIFS('Base File'!$G:$G,"Contractual SLA",'Base File'!$H:$H,"Yes",'Base File'!$B:$B,'Account Summary'!$C9,'Base File'!$BL:$BL,"Met")/SUM(COUNTIFS('Base File'!$G:$G,"Contractual SLA",'Base File'!$H:$H,"yes",'Base File'!$B:$B,'Account Summary'!$C9,'Base File'!$BL:$BL,"Met")+COUNTIFS('Base File'!$G:$G,"Contractual SLA",'Base File'!$H:$H,"yes",'Base File'!$B:$B,'Account Summary'!$C9,'Base File'!$BL:$BL,"Not Met")),"-") -> - | AY9: =IFERROR(COUNTIFS('Base File'!$G:$G,"Internal KPI",'Base File'!$B:$B,'Account Summary'!$C9,'Base File'!$BL:$BL,"Met")/SUM(COUNTIFS('Base File'!$G:$G,"Internal KPI",'Base File'!$B:$B,'Account Summary'!$C9,'Base File'!$BL:$BL,"Met")+COUNTIFS('Base File'!$G:$G,"Internal KPI",'Base File'!$B:$B,'Account Summary'!$C9,'Base File'!$BL:$BL,"Not Met")),"-") -> 0.16666667 | AZ9: 0.63636364 | BA9: 1 | BB9: - | BC9: 0.33333333 | BD9: =IFERROR(COUNTIFS('Base File'!$BP:$BP,"Met",'Base File'!$B:$B,'Account Summary'!C9)/(COUNTIFS('Base File'!$BP:$BP,"Met",'Base File'!$B:$B,'Account Summary'!C9)+COUNTIFS('Base File'!$BP:$BP,"Not Met",'Base File'!$B:$B,'Account Summary'!C9)),"NR") -> NR | BE9: NR | BF9: =IFERROR(COUNTIFS('Base File'!$G:$G,"Contractual SLA",'Base File'!$H:$H,"Yes",'Base File'!$B:$B,'Account Summary'!$C9,'Base File'!$BP:$BP,"Met")/SUM(COUNTIFS('Base File'!$G:$G,"Contractual SLA",'Base File'!$H:$H,"yes",'Base File'!$B:$B,'Account Summary'!$C9,'Base File'!$BP:$BP,"Met")+COUNTIFS('Base File'!$G:$G,"Contractual SLA",'Base File'!$H:$H,"yes",'Base File'!$B:$B,'Account Summary'!$C9,'Base File'!$BP:$BP,"Not Met")),"-") -> - | BG9: NR | BH9: =IFERROR(COUNTIFS('Base File'!$BR:$BR,"Met",'Base File'!$B:$B,'Account Summary'!C9)/(COUNTIFS('Base File'!$BR:$BR,"Met",'Base File'!$B:$B,'Account Summary'!C9)+COUNTIFS('Base File'!$BR:$BR,"Not Met",'Base File'!$B:$B,'Account Summary'!C9)),"NR") -> NR | BI9: NR | BJ9: =IFERROR(COUNTIFS('Base File'!$G:$G,"Contractual SLA",'Base File'!$H:$H,"No",'Base File'!$B:$B,'Account Summary'!$C9,'Base File'!$BR:$BR,"Met")/SUM(COUNTIFS('Base File'!$G:$G,"Contractual SLA",'Base File'!$H:$H,"No",'Base File'!$B:$B,'Account Summary'!$C9,'Base File'!$BR:$BR,"Met")+COUNTIFS('Base File'!$G:$G,"Contractual SLA",'Base File'!$H:$H,"No",'Base File'!$B:$B,'Account Summary'!$C9,'Base File'!$BR:$BR,"Not Met")),"-") -> - | BK9: NR | BL9: =IFERROR(COUNTIFS('Base File'!$BT:$BT,"Met",'Base File'!$B:$B,'Account Summary'!C9)/(COUNTIFS('Base File'!$BT:$BT,"Met",'Base File'!$B:$B,'Account Summary'!C9)+COUNTIFS('Base File'!$BT:$BT,"Not Met",'Base File'!$B:$B,'Account Summary'!C9)),"NR") -> 0.63636364 | BM9: =IFERROR(COUNTIFS('Base File'!$G:$G,"Contractual SLA",'Base File'!$H:$H,"No",'Base File'!$B:$B,'Account Summary'!$C9,'Base File'!$BT:$BT,"Met")/SUM(COUNTIFS('Base File'!$G:$G,"Contractual SLA",'Base File'!$H:$H,"No",'Base File'!$B:$B,'Account Summary'!$C9,'Base File'!$BT:$BT,"Met")+COUNTIFS('Base File'!$G:$G,"Contractual SLA",'Base File'!$H:$H,"No",'Base File'!$B:$B,'Account Summary'!$C9,'Base File'!$BT:$BT,"Not Met")),"-") -> 1 | BN9: =IFERROR(COUNTIFS('Base File'!$G:$G,"Contractual SLA",'Base File'!$H:$H,"Yes",'Base File'!$B:$B,'Account Summary'!$C9,'Base File'!$BT:$BT,"Met")/SUM(COUNTIFS('Base File'!$G:$G,"Contractual SLA",'Base File'!$H:$H,"yes",'Base File'!$B:$B,'Account Summary'!$C9,'Base File'!$BT:$BT,"Met")+COUNTIFS('Base File'!$G:$G,"Contractual SLA",'Base File'!$H:$H,"yes",'Base File'!$B:$B,'Account Summary'!$C9,'Base File'!$BT:$BT,"Not Met")),"-") -> - | BO9: =IFERROR(COUNTIFS('Base File'!$G:$G,"Internal KPI",'Base File'!$B:$B,'Account Summary'!$C9,'Base File'!$BT:$BT,"Met")/SUM(COUNTIFS('Base File'!$G:$G,"Internal KPI",'Base File'!$B:$B,'Account Summary'!$C9,'Base File'!$BT:$BT,"Met")+COUNTIFS('Base File'!$G:$G,"Internal KPI",'Base File'!$B:$B,'Account Summary'!$C9,'Base File'!$BT:$BT,"Not Met")),"-") -> 0.33333333 | BP9: =IFERROR(COUNTIFS('Base File'!$BV:$BV,"Met",'Base File'!$B:$B,'Account Summary'!C9)/(COUNTIFS('Base File'!$BV:$BV,"Met",'Base File'!$B:$B,'Account Summary'!C9)+COUNTIFS('Base File'!$BV:$BV,"Not Met",'Base File'!$B:$B,'Account Summary'!C9)),"NR") -> 0.72727273 | BQ9: 1 | BR9: =IFERROR(COUNTIFS('Base File'!$G:$G,"Contractual SLA",'Base File'!$H:$H,"Yes",'Base File'!$B:$B,'Account Summary'!$C9,'Base File'!$BV:$BV,"Met")/SUM(COUNTIFS('Base File'!$G:$G,"Contractual SLA",'Base File'!$H:$H,"Yes",'Base File'!$B:$B,'Account Summary'!$C9,'Base File'!$BV:$BV,"Met")+COUNTIFS('Base File'!$G:$G,"Contractual SLA",'Base File'!$H:$H,"Yes",'Base File'!$B:$B,'Account Summary'!$C9,'Base File'!$BV:$BV,"Not Met")),"-") -> - | BS9: 0.5
B10: 7 | C10: HPE | D10: Bangalore | E10: South 1 | F10: Himanshu Srivastava & Mehvish Naz | I10: Mahak | J10: Reported | K10: Partially Validated | L10: =IFERROR(COUNTIFS('Base File'!$AR:$AR,"Met",'Base File'!$B:$B,'Account Summary'!C10)/(COUNTIFS('Base File'!$AR:$AR,"Met",'Base File'!$B:$B,'Account Summary'!C10)+COUNTIFS('Base File'!$AR:$AR,"Not Met",'Base File'!$B:$B,'Account Summary'!C10)),"NR") -> 0.91666667 | M10: =IFERROR(COUNTIFS('Base File'!$G:$G,"Contractual SLA",'Base File'!$H:$H,"No",'Base File'!$B:$B,'Account Summary'!$C10,'Base File'!$AR:$AR,"Met")/SUM(COUNTIFS('Base File'!$G:$G,"Contractual SLA",'Base File'!$H:$H,"No",'Base File'!$B:$B,'Account Summary'!$C10,'Base File'!$AR:$AR,"Met")+COUNTIFS('Base File'!$G:$G,"Contractual SLA",'Base File'!$H:$H,"No",'Base File'!$B:$B,'Account Summary'!$C10,'Base File'!$AR:$AR,"Not Met")),"-") -> 0.875 | N10: =IFERROR(COUNTIFS('Base File'!$G:$G,"Contractual SLA",'Base File'!$H:$H,"Yes",'Base File'!$B:$B,'Account Summary'!$C10,'Base File'!$AR:$AR,"Met")/SUM(COUNTIFS('Base File'!$G:$G,"Contractual SLA",'Base File'!$H:$H,"yes",'Base File'!$B:$B,'Account Summary'!$C10,'Base File'!$AR:$AR,"Met")+COUNTIFS('Base File'!$G:$G,"Contractual SLA",'Base File'!$H:$H,"yes",'Base File'!$B:$B,'Account Summary'!$C10,'Base File'!$AR:$AR,"Not Met")),"-") -> 1 | O10: NA | P10: =IFERROR(COUNTIFS('Base File'!$AV:$AV,"Met",'Base File'!$B:$B,'Account Summary'!C10)/(COUNTIFS('Base File'!$AV:$AV,"Met",'Base File'!$B:$B,'Account Summary'!C10)+COUNTIFS('Base File'!$AV:$AV,"Not Met",'Base File'!$B:$B,'Account Summary'!C10)),"NR") -> NR | Q10: =IFERROR(COUNTIFS('Base File'!$AV:$AV,"Met",'Base File'!$B:$B,'Account Summary'!D10)/(COUNTIFS('Base File'!$AV:$AV,"Met",'Base File'!$B:$B,'Account Summary'!D10)+COUNTIFS('Base File'!$AV:$AV,"Not Met",'Base File'!$B:$B,'Account Summary'!D10)),"NR") -> NR | R10: =IFERROR(COUNTIFS('Base File'!$AV:$AV,"Met",'Base File'!$B:$B,'Account Summary'!F10)/(COUNTIFS('Base File'!$AV:$AV,"Met",'Base File'!$B:$B,'Account Summary'!F10)+COUNTIFS('Base File'!$AV:$AV,"Not Met",'Base File'!$B:$B,'Account Summary'!F10)),"NR") -> NR | S10: =IFERROR(COUNTIFS('Base File'!$AV:$AV,"Met",'Base File'!$B:$B,'Account Summary'!G10)/(COUNTIFS('Base File'!$AV:$AV,"Met",'Base File'!$B:$B,'Account Summary'!G10)+COUNTIFS('Base File'!$AV:$AV,"Not Met",'Base File'!$B:$B,'Account Summary'!G10)),"NR") -> NR | T10: =IFERROR(COUNTIFS('Base File'!$AX:$AX,"Met",'Base File'!$B:$B,'Account Summary'!C10)/(COUNTIFS('Base File'!$AX:$AX,"Met",'Base File'!$B:$B,'Account Summary'!C10)+COUNTIFS('Base File'!$AX:$AX,"Not Met",'Base File'!$B:$B,'Account Summary'!C10)),"NR") -> 0.8 | U10: =IFERROR(COUNTIFS('Base File'!$G:$G,"Contractual SLA",'Base File'!$H:$H,"No",'Base File'!$B:$B,'Account Summary'!$C10,'Base File'!$AX:$AX,"Met")/SUM(COUNTIFS('Base File'!$G:$G,"Contractual SLA",'Base File'!$H:$H,"No",'Base File'!$B:$B,'Account Summary'!$C10,'Base File'!$AX:$AX,"Met")+COUNTIFS('Base File'!$G:$G,"Contractual SLA",'Base File'!$H:$H,"No",'Base File'!$B:$B,'Account Summary'!$C10,'Base File'!$AX:$AX,"Not Met")),"-") -> 0.83333333 | V10: =IFERROR(COUNTIFS('Base File'!$G:$G,"Contractual SLA",'Base File'!$H:$H,"Yes",'Base File'!$B:$B,'Account Summary'!$C10,'Base File'!$AX:$AX,"Met")/SUM(COUNTIFS('Base File'!$G:$G,"Contractual SLA",'Base File'!$H:$H,"yes",'Base File'!$B:$B,'Account Summary'!$C10,'Base File'!$AX:$AX,"Met")+COUNTIFS('Base File'!$G:$G,"Contractual SLA",'Base File'!$H:$H,"yes",'Base File'!$B:$B,'Account Summary'!$C10,'Base File'!$AX:$AX,"Not Met")),"-") -> 0.75 | W10: NA | X10: =IFERROR(COUNTIFS('Base File'!$AZ:$AZ,"Met",'Base File'!$B:$B,'Account Summary'!C10)/(COUNTIFS('Base File'!$AZ:$AZ,"Met",'Base File'!$B:$B,'Account Summary'!C10)+COUNTIFS('Base File'!$AZ:$AZ,"Not Met",'Base File'!$B:$B,'Account Summary'!C10)),"NR") -> 0.8 | Y10: =IFERROR(COUNTIFS('Base File'!$G:$G,"Contractual SLA",'Base File'!$H:$H,"No",'Base File'!$B:$B,'Account Summary'!$C10,'Base File'!$AZ:$AZ,"Met")/SUM(COUNTIFS('Base File'!$G:$G,"Contractual SLA",'Base File'!$H:$H,"No",'Base File'!$B:$B,'Account Summary'!$C10,'Base File'!$AZ:$AZ,"Met")+COUNTIFS('Base File'!$G:$G,"Contractual SLA",'Base File'!$H:$H,"No",'Base File'!$B:$B,'Account Summary'!$C10,'Base File'!$AZ:$AZ,"Not Met")),"-") -> 1 | Z10: =IFERROR(COUNTIFS('Base File'!$G:$G,"Contractual SLA",'Base File'!$H:$H,"Yes",'Base File'!$B:$B,'Account Summary'!$C10,'Base File'!$AZ:$AZ,"Met")/SUM(COUNTIFS('Base File'!$G:$G,"Contractual SLA",'Base File'!$H:$H,"yes",'Base File'!$B:$B,'Account Summary'!$C10,'Base File'!$AZ:$AZ,"Met")+COUNTIFS('Base File'!$G:$G,"Contractual SLA",'Base File'!$H:$H,"yes",'Base File'!$B:$B,'Account Summary'!$C10,'Base File'!$AZ:$AZ,"Not Met")),"-") -> 0.5 | AA10: =IFERROR(COUNTIFS('Base File'!$G:$G,"Internal KPI",'Base File'!$B:$B,'Account Summary'!$C10,'Base File'!$AZ:$AZ,"Met")/SUM(COUNTIFS('Base File'!$G:$G,"Internal KPI",'Base File'!$B:$B,'Account Summary'!$C10,'Base File'!$AZ:$AZ,"Met")+COUNTIFS('Base File'!$G:$G,"Internal KPI",'Base File'!$B:$B,'Account Summary'!$C10,'Base File'!$AZ:$AZ,"Not Met")),"-") -> - | AB10: =IFERROR(COUNTIFS('Base File'!$BB:$BB,"Met",'Base File'!$B:$B,'Account Summary'!C10)/(COUNTIFS('Base File'!$BB:$BB,"Met",'Base File'!$B:$B,'Account Summary'!C10)+COUNTIFS('Base File'!$BB:$BB,"Not Met",'Base File'!$B:$B,'Account Summary'!C10)),"NR") -> 0.7 | AC10: =IFERROR(COUNTIFS('Base File'!$G:$G,"Contractual SLA",'Base File'!$H:$H,"No",'Base File'!$B:$B,'Account Summary'!$C10,'Base File'!$BB:$BB,"Met")/SUM(COUNTIFS('Base File'!$G:$G,"Contractual SLA",'Base File'!$H:$H,"No",'Base File'!$B:$B,'Account Summary'!$C10,'Base File'!$BB:$BB,"Met")+COUNTIFS('Base File'!$G:$G,"Contractual SLA",'Base File'!$H:$H,"No",'Base File'!$B:$B,'Account Summary'!$C10,'Base File'!$BB:$BB,"Not Met")),"-") -> 0.83333333 | AD10: =IFERROR(COUNTIFS('Base File'!$G:$G,"Contractual SLA",'Base File'!$H:$H,"Yes",'Base File'!$B:$B,'Account Summary'!$C10,'Base File'!$BB:$BB,"Met")/SUM(COUNTIFS('Base File'!$G:$G,"Contractual SLA",'Base File'!$H:$H,"yes",'Base File'!$B:$B,'Account Summary'!$C10,'Base File'!$BB:$BB,"Met")+COUNTIFS('Base File'!$G:$G,"Contractual SLA",'Base File'!$H:$H,"yes",'Base File'!$B:$B,'Account Summary'!$C10,'Base File'!$BB:$BB,"Not Met")),"-") -> 0.5 | AE10: NA | AF10: =IFERROR(COUNTIFS('Base File'!$BD:$BD,"Met",'Base File'!$B:$B,'Account Summary'!C10)/(COUNTIFS('Base File'!$BD:$BD,"Met",'Base File'!$B:$B,'Account Summary'!C10)+COUNTIFS('Base File'!$BD:$BD,"Not Met",'Base File'!$B:$B,'Account Summary'!C10)),"NR") -> 0.8 | AG10: =IFERROR(COUNTIFS('Base File'!$G:$G,"Contractual SLA",'Base File'!$H:$H,"No",'Base File'!$B:$B,'Account Summary'!$C10,'Base File'!$BD:$BD,"Met")/SUM(COUNTIFS('Base File'!$G:$G,"Contractual SLA",'Base File'!$H:$H,"No",'Base File'!$B:$B,'Account Summary'!$C10,'Base File'!$BD:$BD,"Met")+COUNTIFS('Base File'!$G:$G,"Contractual SLA",'Base File'!$H:$H,"No",'Base File'!$B:$B,'Account Summary'!$C10,'Base File'!$BD:$BD,"Not Met")),"-") -> 1 | AH10: =IFERROR(COUNTIFS('Base File'!$G:$G,"Contractual SLA",'Base File'!$H:$H,"Yes",'Base File'!$B:$B,'Account Summary'!$C10,'Base File'!$BD:$BD,"Met")/SUM(COUNTIFS('Base File'!$G:$G,"Contractual SLA",'Base File'!$H:$H,"yes",'Base File'!$B:$B,'Account Summary'!$C10,'Base File'!$BD:$BD,"Met")+COUNTIFS('Base File'!$G:$G,"Contractual SLA",'Base File'!$H:$H,"yes",'Base File'!$B:$B,'Account Summary'!$C10,'Base File'!$BD:$BD,"Not Met")),"-") -> 0.5 | AI10: NA | AJ10: =IFERROR(COUNTIFS('Base File'!$BF:$BF,"Met",'Base File'!$B:$B,'Account Summary'!C10)/(COUNTIFS('Base File'!$BF:$BF,"Met",'Base File'!$B:$B,'Account Summary'!C10)+COUNTIFS('Base File'!$BF:$BF,"Not Met",'Base File'!$B:$B,'Account Summary'!C10)),"NR") -> 1 | AK10: =IFERROR(COUNTIFS('Base File'!$G:$G,"Contractual SLA",'Base File'!$H:$H,"No",'Base File'!$B:$B,'Account Summary'!$C10,'Base File'!$BF:$BF,"Met")/SUM(COUNTIFS('Base File'!$G:$G,"Contractual SLA",'Base File'!$H:$H,"No",'Base File'!$B:$B,'Account Summary'!$C10,'Base File'!$BF:$BF,"Met")+COUNTIFS('Base File'!$G:$G,"Contractual SLA",'Base File'!$H:$H,"No",'Base File'!$B:$B,'Account Summary'!$C10,'Base File'!$BF:$BF,"Not Met")),"-") -> 1 | AL10: =IFERROR(COUNTIFS('Base File'!$G:$G,"Contractual SLA",'Base File'!$H:$H,"Yes",'Base File'!$B:$B,'Account Summary'!$C10,'Base File'!$BF:$BF,"Met")/SUM(COUNTIFS('Base File'!$G:$G,"Contractual SLA",'Base File'!$H:$H,"yes",'Base File'!$B:$B,'Account Summary'!$C10,'Base File'!$BF:$BF,"Met")+COUNTIFS('Base File'!$G:$G,"Contractual SLA",'Base File'!$H:$H,"yes",'Base File'!$B:$B,'Account Summary'!$C10,'Base File'!$BF:$BF,"Not Met")),"-") -> 1 | AM10: NA | AN10: =IFERROR(COUNTIFS('Base File'!$BH:$BH,"Met",'Base File'!$B:$B,'Account Summary'!C10)/(COUNTIFS('Base File'!$BH:$BH,"Met",'Base File'!$B:$B,'Account Summary'!C10)+COUNTIFS('Base File'!$BH:$BH,"Not Met",'Base File'!$B:$B,'Account Summary'!C10)),"NR") -> 1 | AO10: =IFERROR(COUNTIFS('Base File'!$G:$G,"Contractual SLA",'Base File'!$H:$H,"No",'Base File'!$B:$B,'Account Summary'!$C10,'Base File'!$BH:$BH,"Met")/SUM(COUNTIFS('Base File'!$G:$G,"Contractual SLA",'Base File'!$H:$H,"No",'Base File'!$B:$B,'Account Summary'!$C10,'Base File'!$BH:$BH,"Met")+COUNTIFS('Base File'!$G:$G,"Contractual SLA",'Base File'!$H:$H,"No",'Base File'!$B:$B,'Account Summary'!$C10,'Base File'!$BH:$BH,"Not Met")),"-") -> 1 | AP10: =IFERROR(COUNTIFS('Base File'!$G:$G,"Contractual SLA",'Base File'!$H:$H,"Yes",'Base File'!$B:$B,'Account Summary'!$C10,'Base File'!$BH:$BH,"Met")/SUM(COUNTIFS('Base File'!$G:$G,"Contractual SLA",'Base File'!$H:$H,"yes",'Base File'!$B:$B,'Account Summary'!$C10,'Base File'!$BH:$BH,"Met")+COUNTIFS('Base File'!$G:$G,"Contractual SLA",'Base File'!$H:$H,"yes",'Base File'!$B:$B,'Account Summary'!$C10,'Base File'!$BH:$BH,"Not Met")),"-") -> 1 | AQ10: NA | AR10: =IFERROR(COUNTIFS('Base File'!$BJ:$BJ,"Met",'Base File'!$B:$B,'Account Summary'!C10)/(COUNTIFS('Base File'!$BJ:$BJ,"Met",'Base File'!$B:$B,'Account Summary'!C10)+COUNTIFS('Base File'!$BJ:$BJ,"Not Met",'Base File'!$B:$B,'Account Summary'!C10)),"NR") -> 0.8 | AS10: =IFERROR(COUNTIFS('Base File'!$G:$G,"Contractual SLA",'Base File'!$H:$H,"No",'Base File'!$B:$B,'Account Summary'!$C10,'Base File'!$BJ:$BJ,"Met")/SUM(COUNTIFS('Base File'!$G:$G,"Contractual SLA",'Base File'!$H:$H,"No",'Base File'!$B:$B,'Account Summary'!$C10,'Base File'!$BJ:$BJ,"Met")+COUNTIFS('Base File'!$G:$G,"Contractual SLA",'Base File'!$H:$H,"No",'Base File'!$B:$B,'Account Summary'!$C10,'Base File'!$BJ:$BJ,"Not Met")),"-") -> 0.83333333 | AT10: =IFERROR(COUNTIFS('Base File'!$G:$G,"Contractual SLA",'Base File'!$H:$H,"Yes",'Base File'!$B:$B,'Account Summary'!$C10,'Base File'!$BJ:$BJ,"Met")/SUM(COUNTIFS('Base File'!$G:$G,"Contractual SLA",'Base File'!$H:$H,"yes",'Base File'!$B:$B,'Account Summary'!$C10,'Base File'!$BJ:$BJ,"Met")+COUNTIFS('Base File'!$G:$G,"Contractual SLA",'Base File'!$H:$H,"yes",'Base File'!$B:$B,'Account Summary'!$C10,'Base File'!$BJ:$BJ,"Not Met")),"-") -> 0.75 | AU10: NA | AV10: =IFERROR(COUNTIFS('Base File'!$BL:$BL,"Met",'Base File'!$B:$B,'Account Summary'!C10)/(COUNTIFS('Base File'!$BL:$BL,"Met",'Base File'!$B:$B,'Account Summary'!C10)+COUNTIFS('Base File'!$BL:$BL,"Not Met",'Base File'!$B:$B,'Account Summary'!C10)),"NR") -> 0.66666667 | AW10: =IFERROR(COUNTIFS('Base File'!$G:$G,"Contractual SLA",'Base File'!$H:$H,"No",'Base File'!$B:$B,'Account Summary'!$C10,'Base File'!$BL:$BL,"Met")/SUM(COUNTIFS('Base File'!$G:$G,"Contractual SLA",'Base File'!$H:$H,"No",'Base File'!$B:$B,'Account Summary'!$C10,'Base File'!$BL:$BL,"Met")+COUNTIFS('Base File'!$G:$G,"Contractual SLA",'Base File'!$H:$H,"No",'Base File'!$B:$B,'Account Summary'!$C10,'Base File'!$BL:$BL,"Not Met")),"-") -> 0.5 | AX10: =IFERROR(COUNTIFS('Base File'!$G:$G,"Contractual SLA",'Base File'!$H:$H,"Yes",'Base File'!$B:$B,'Account Summary'!$C10,'Base File'!$BL:$BL,"Met")/SUM(COUNTIFS('Base File'!$G:$G,"Contractual SLA",'Base File'!$H:$H,"yes",'Base File'!$B:$B,'Account Summary'!$C10,'Base File'!$BL:$BL,"Met")+COUNTIFS('Base File'!$G:$G,"Contractual SLA",'Base File'!$H:$H,"yes",'Base File'!$B:$B,'Account Summary'!$C10,'Base File'!$BL:$BL,"Not Met")),"-") -> 1 | AY10: NA | AZ10: 1 | BA10: 1 | BB10: 1 | BC10: NA | BD10: =IFERROR(COUNTIFS('Base File'!$BP:$BP,"Met",'Base File'!$B:$B,'Account Summary'!C10)/(COUNTIFS('Base File'!$BP:$BP,"Met",'Base File'!$B:$B,'Account Summary'!C10)+COUNTIFS('Base File'!$BP:$BP,"Not Met",'Base File'!$B:$B,'Account Summary'!C10)),"NR") -> 0.9 | BE10: =IFERROR(COUNTIFS('Base File'!$G:$G,"Contractual SLA",'Base File'!$H:$H,"No",'Base File'!$B:$B,'Account Summary'!$C10,'Base File'!$BP:$BP,"Met")/SUM(COUNTIFS('Base File'!$G:$G,"Contractual SLA",'Base File'!$H:$H,"No",'Base File'!$B:$B,'Account Summary'!$C10,'Base File'!$BP:$BP,"Met")+COUNTIFS('Base File'!$G:$G,"Contractual SLA",'Base File'!$H:$H,"No",'Base File'!$B:$B,'Account Summary'!$C10,'Base File'!$BP:$BP,"Not Met")),"-") -> 0.83333333 | BF10: =IFERROR(COUNTIFS('Base File'!$G:$G,"Contractual SLA",'Base File'!$H:$H,"Yes",'Base File'!$B:$B,'Account Summary'!$C10,'Base File'!$BP:$BP,"Met")/SUM(COUNTIFS('Base File'!$G:$G,"Contractual SLA",'Base File'!$H:$H,"yes",'Base File'!$B:$B,'Account Summary'!$C10,'Base File'!$BP:$BP,"Met")+COUNTIFS('Base File'!$G:$G,"Contractual SLA",'Base File'!$H:$H,"yes",'Base File'!$B:$B,'Account Summary'!$C10,'Base File'!$BP:$BP,"Not Met")),"-") -> 1 | BG10: NA | BH10: =IFERROR(COUNTIFS('Base File'!$BR:$BR,"Met",'Base File'!$B:$B,'Account Summary'!C10)/(COUNTIFS('Base File'!$BR:$BR,"Met",'Base File'!$B:$B,'Account Summary'!C10)+COUNTIFS('Base File'!$BR:$BR,"Not Met",'Base File'!$B:$B,'Account Summary'!C10)),"NR") -> NR | BI10: NR | BJ10: NR | BK10: NA | BL10: =IFERROR(COUNTIFS('Base File'!$BT:$BT,"Met",'Base File'!$B:$B,'Account Summary'!C10)/(COUNTIFS('Base File'!$BT:$BT,"Met",'Base File'!$B:$B,'Account Summary'!C10)+COUNTIFS('Base File'!$BT:$BT,"Not Met",'Base File'!$B:$B,'Account Summary'!C10)),"NR") -> 0.8 | BM10: =IFERROR(COUNTIFS('Base File'!$G:$G,"Contractual SLA",'Base File'!$H:$H,"No",'Base File'!$B:$B,'Account Summary'!$C10,'Base File'!$BT:$BT,"Met")/SUM(COUNTIFS('Base File'!$G:$G,"Contractual SLA",'Base File'!$H:$H,"No",'Base File'!$B:$B,'Account Summary'!$C10,'Base File'!$BT:$BT,"Met")+COUNTIFS('Base File'!$G:$G,"Contractual SLA",'Base File'!$H:$H,"No",'Base File'!$B:$B,'Account Summary'!$C10,'Base File'!$BT:$BT,"Not Met")),"-") -> 0.66666667 | BN10: =IFERROR(COUNTIFS('Base File'!$G:$G,"Contractual SLA",'Base File'!$H:$H,"Yes",'Base File'!$B:$B,'Account Summary'!$C10,'Base File'!$BT:$BT,"Met")/SUM(COUNTIFS('Base File'!$G:$G,"Contractual SLA",'Base File'!$H:$H,"yes",'Base File'!$B:$B,'Account Summary'!$C10,'Base File'!$BT:$BT,"Met")+COUNTIFS('Base File'!$G:$G,"Contractual SLA",'Base File'!$H:$H,"yes",'Base File'!$B:$B,'Account Summary'!$C10,'Base File'!$BT:$BT,"Not Met")),"-") -> 1 | BO10: NA | BP10: =IFERROR(COUNTIFS('Base File'!$BV:$BV,"Met",'Base File'!$B:$B,'Account Summary'!C10)/(COUNTIFS('Base File'!$BV:$BV,"Met",'Base File'!$B:$B,'Account Summary'!C10)+COUNTIFS('Base File'!$BV:$BV,"Not Met",'Base File'!$B:$B,'Account Summary'!C10)),"NR") -> 0.8 | BQ10: 0.67 | BR10: =IFERROR(COUNTIFS('Base File'!$G:$G,"Contractual SLA",'Base File'!$H:$H,"Yes",'Base File'!$B:$B,'Account Summary'!$C10,'Base File'!$BV:$BV,"Met")/SUM(COUNTIFS('Base File'!$G:$G,"Contractual SLA",'Base File'!$H:$H,"Yes",'Base File'!$B:$B,'Account Summary'!$C10,'Base File'!$BV:$BV,"Met")+COUNTIFS('Base File'!$G:$G,"Contractual SLA",'Base File'!$H:$H,"Yes",'Base File'!$B:$B,'Account Summary'!$C10,'Base File'!$BV:$BV,"Not Met")),"-") -> 1 | BS10: NA
B11: 8 | C11: Ametek | D11: Bangalore | E11: South 1 | F11: Himanshu Srivastava & Mehvish Naz | I11: Sulabh | J11: NA | K11: NA | L11: =IFERROR(COUNTIFS('Base File'!$AR:$AR,"Met",'Base File'!$B:$B,'Account Summary'!C11)/(COUNTIFS('Base File'!$AR:$AR,"Met",'Base File'!$B:$B,'Account Summary'!C11)+COUNTIFS('Base File'!$AR:$AR,"Not Met",'Base File'!$B:$B,'Account Summary'!C11)),"NR") -> NR | M11: =IFERROR(COUNTIFS('Base File'!$G:$G,"Contractual SLA",'Base File'!$H:$H,"No",'Base File'!$B:$B,'Account Summary'!$C11,'Base File'!$AR:$AR,"Met")/SUM(COUNTIFS('Base File'!$G:$G,"Contractual SLA",'Base File'!$H:$H,"No",'Base File'!$B:$B,'Account Summary'!$C11,'Base File'!$AR:$AR,"Met")+COUNTIFS('Base File'!$G:$G,"Contractual SLA",'Base File'!$H:$H,"No",'Base File'!$B:$B,'Account Summary'!$C11,'Base File'!$AR:$AR,"Not Met")),"-") -> - | N11: =IFERROR(COUNTIFS('Base File'!$G:$G,"Contractual SLA",'Base File'!$H:$H,"Yes",'Base File'!$B:$B,'Account Summary'!$C11,'Base File'!$AR:$AR,"Met")/SUM(COUNTIFS('Base File'!$G:$G,"Contractual SLA",'Base File'!$H:$H,"yes",'Base File'!$B:$B,'Account Summary'!$C11,'Base File'!$AR:$AR,"Met")+COUNTIFS('Base File'!$G:$G,"Contractual SLA",'Base File'!$H:$H,"yes",'Base File'!$B:$B,'Account Summary'!$C11,'Base File'!$AR:$AR,"Not Met")),"-") -> - | O11: NR | P11: =IFERROR(COUNTIFS('Base File'!$AV:$AV,"Met",'Base File'!$B:$B,'Account Summary'!C11)/(COUNTIFS('Base File'!$AV:$AV,"Met",'Base File'!$B:$B,'Account Summary'!C11)+COUNTIFS('Base File'!$AV:$AV,"Not Met",'Base File'!$B:$B,'Account Summary'!C11)),"NR") -> NR | Q11: =IFERROR(COUNTIFS('Base File'!$G:$G,"Contractual SLA",'Base File'!$H:$H,"No",'Base File'!$B:$B,'Account Summary'!$C11,'Base File'!$AV:$AV,"Met")/SUM(COUNTIFS('Base File'!$G:$G,"Contractual SLA",'Base File'!$H:$H,"No",'Base File'!$B:$B,'Account Summary'!$C11,'Base File'!$AV:$AV,"Met")+COUNTIFS('Base File'!$G:$G,"Contractual SLA",'Base File'!$H:$H,"No",'Base File'!$B:$B,'Account Summary'!$C11,'Base File'!$AV:$AV,"Not Met")),"-") -> - | R11: =IFERROR(COUNTIFS('Base File'!$G:$G,"Contractual SLA",'Base File'!$H:$H,"Yes",'Base File'!$B:$B,'Account Summary'!$C11,'Base File'!$AV:$AV,"Met")/SUM(COUNTIFS('Base File'!$G:$G,"Contractual SLA",'Base File'!$H:$H,"yes",'Base File'!$B:$B,'Account Summary'!$C11,'Base File'!$AV:$AV,"Met")+COUNTIFS('Base File'!$G:$G,"Contractual SLA",'Base File'!$H:$H,"yes",'Base File'!$B:$B,'Account Summary'!$C11,'Base File'!$AV:$AV,"Not Met")),"-") -> - | S11: =IFERROR(COUNTIFS('Base File'!$AV:$AV,"Met",'Base File'!$B:$B,'Account Summary'!G11)/(COUNTIFS('Base File'!$AV:$AV,"Met",'Base File'!$B:$B,'Account Summary'!G11)+COUNTIFS('Base File'!$AV:$AV,"Not Met",'Base File'!$B:$B,'Account Summary'!G11)),"NR") -> NR | T11: =IFERROR(COUNTIFS('Base File'!$AX:$AX,"Met",'Base File'!$B:$B,'Account Summary'!C11)/(COUNTIFS('Base File'!$AX:$AX,"Met",'Base File'!$B:$B,'Account Summary'!C11)+COUNTIFS('Base File'!$AX:$AX,"Not Met",'Base File'!$B:$B,'Account Summary'!C11)),"NR") -> NR | U11: =IFERROR(COUNTIFS('Base File'!$G:$G,"Contractual SLA",'Base File'!$H:$H,"No",'Base File'!$B:$B,'Account Summary'!$C11,'Base File'!$AX:$AX,"Met")/SUM(COUNTIFS('Base File'!$G:$G,"Contractual SLA",'Base File'!$H:$H,"No",'Base File'!$B:$B,'Account Summary'!$C11,'Base File'!$AX:$AX,"Met")+COUNTIFS('Base File'!$G:$G,"Contractual SLA",'Base File'!$H:$H,"No",'Base File'!$B:$B,'Account Summary'!$C11,'Base File'!$AX:$AX,"Not Met")),"NA") -> NA | V11: =IFERROR(COUNTIFS('Base File'!$G:$G,"Contractual SLA",'Base File'!$H:$H,"Yes",'Base File'!$B:$B,'Account Summary'!$C11,'Base File'!$AX:$AX,"Met")/SUM(COUNTIFS('Base File'!$G:$G,"Contractual SLA",'Base File'!$H:$H,"yes",'Base File'!$B:$B,'Account Summary'!$C11,'Base File'!$AX:$AX,"Met")+COUNTIFS('Base File'!$G:$G,"Contractual SLA",'Base File'!$H:$H,"yes",'Base File'!$B:$B,'Account Summary'!$C11,'Base File'!$AX:$AX,"Not Met")),"NA") -> NA | W11: NR | X11: =IFERROR(COUNTIFS('Base File'!$AZ:$AZ,"Met",'Base File'!$B:$B,'Account Summary'!C11)/(COUNTIFS('Base File'!$AZ:$AZ,"Met",'Base File'!$B:$B,'Account Summary'!C11)+COUNTIFS('Base File'!$AZ:$AZ,"Not Met",'Base File'!$B:$B,'Account Summary'!C11)),"NR") -> NR | Y11: =IFERROR(COUNTIFS('Base File'!$G:$G,"Contractual SLA",'Base File'!$H:$H,"No",'Base File'!$B:$B,'Account Summary'!$C11,'Base File'!$AZ:$AZ,"Met")/SUM(COUNTIFS('Base File'!$G:$G,"Contractual SLA",'Base File'!$H:$H,"No",'Base File'!$B:$B,'Account Summary'!$C11,'Base File'!$AZ:$AZ,"Met")+COUNTIFS('Base File'!$G:$G,"Contractual SLA",'Base File'!$H:$H,"No",'Base File'!$B:$B,'Account Summary'!$C11,'Base File'!$AZ:$AZ,"Not Met")),"-") -> - | Z11: =IFERROR(COUNTIFS('Base File'!$G:$G,"Contractual SLA",'Base File'!$H:$H,"Yes",'Base File'!$B:$B,'Account Summary'!$C11,'Base File'!$AZ:$AZ,"Met")/SUM(COUNTIFS('Base File'!$G:$G,"Contractual SLA",'Base File'!$H:$H,"yes",'Base File'!$B:$B,'Account Summary'!$C11,'Base File'!$AZ:$AZ,"Met")+COUNTIFS('Base File'!$G:$G,"Contractual SLA",'Base File'!$H:$H,"yes",'Base File'!$B:$B,'Account Summary'!$C11,'Base File'!$AZ:$AZ,"Not Met")),"-") -> - | AA11: NR | AB11: =IFERROR(COUNTIFS('Base File'!$BB:$BB,"Met",'Base File'!$B:$B,'Account Summary'!C11)/(COUNTIFS('Base File'!$BB:$BB,"Met",'Base File'!$B:$B,'Account Summary'!C11)+COUNTIFS('Base File'!$BB:$BB,"Not Met",'Base File'!$B:$B,'Account Summary'!C11)),"NR") -> NR | AC11: =IFERROR(COUNTIFS('Base File'!$G:$G,"Contractual SLA",'Base File'!$H:$H,"No",'Base File'!$B:$B,'Account Summary'!$C11,'Base File'!$BB:$BB,"Met")/SUM(COUNTIFS('Base File'!$G:$G,"Contractual SLA",'Base File'!$H:$H,"No",'Base File'!$B:$B,'Account Summary'!$C11,'Base File'!$BB:$BB,"Met")+COUNTIFS('Base File'!$G:$G,"Contractual SLA",'Base File'!$H:$H,"No",'Base File'!$B:$B,'Account Summary'!$C11,'Base File'!$BB:$BB,"Not Met")),"-") -> - | AD11: =IFERROR(COUNTIFS('Base File'!$G:$G,"Contractual SLA",'Base File'!$H:$H,"Yes",'Base File'!$B:$B,'Account Summary'!$C11,'Base File'!$BB:$BB,"Met")/SUM(COUNTIFS('Base File'!$G:$G,"Contractual SLA",'Base File'!$H:$H,"yes",'Base File'!$B:$B,'Account Summary'!$C11,'Base File'!$BB:$BB,"Met")+COUNTIFS('Base File'!$G:$G,"Contractual SLA",'Base File'!$H:$H,"yes",'Base File'!$B:$B,'Account Summary'!$C11,'Base File'!$BB:$BB,"Not Met")),"-") -> - | AE11: NR | AF11: =IFERROR(COUNTIFS('Base File'!$BD:$BD,"Met",'Base File'!$B:$B,'Account Summary'!C11)/(COUNTIFS('Base File'!$BD:$BD,"Met",'Base File'!$B:$B,'Account Summary'!C11)+COUNTIFS('Base File'!$BD:$BD,"Not Met",'Base File'!$B:$B,'Account Summary'!C11)),"NR") -> NR | AG11: =IFERROR(COUNTIFS('Base File'!$G:$G,"Contractual SLA",'Base File'!$H:$H,"No",'Base File'!$B:$B,'Account Summary'!$C11,'Base File'!$BD:$BD,"Met")/SUM(COUNTIFS('Base File'!$G:$G,"Contractual SLA",'Base File'!$H:$H,"No",'Base File'!$B:$B,'Account Summary'!$C11,'Base File'!$BD:$BD,"Met")+COUNTIFS('Base File'!$G:$G,"Contractual SLA",'Base File'!$H:$H,"No",'Base File'!$B:$B,'Account Summary'!$C11,'Base File'!$BD:$BD,"Not Met")),"-") -> - | AH11: =IFERROR(COUNTIFS('Base File'!$G:$G,"Contractual SLA",'Base File'!$H:$H,"Yes",'Base File'!$B:$B,'Account Summary'!$C11,'Base File'!$BD:$BD,"Met")/SUM(COUNTIFS('Base File'!$G:$G,"Contractual SLA",'Base File'!$H:$H,"yes",'Base File'!$B:$B,'Account Summary'!$C11,'Base File'!$BD:$BD,"Met")+COUNTIFS('Base File'!$G:$G,"Contractual SLA",'Base File'!$H:$H,"yes",'Base File'!$B:$B,'Account Summary'!$C11,'Base File'!$BD:$BD,"Not Met")),"-") -> - | AI11: =IFERROR(COUNTIFS('Base File'!$BD:$BD,"Met",'Base File'!$B:$B,'Account Summary'!G11)/(COUNTIFS('Base File'!$BD:$BD,"Met",'Base File'!$B:$B,'Account Summary'!G11)+COUNTIFS('Base File'!$BD:$BD,"Not Met",'Base File'!$B:$B,'Account Summary'!G11)),"NR") -> NR | AJ11: =IFERROR(COUNTIFS('Base File'!$BV:$BV,"Met",'Base File'!$B:$B,'Account Summary'!#REF!)/(COUNTIFS('Base File'!$BV:$BV,"Met",'Base File'!$B:$B,'Account Summary'!#REF!)+COUNTIFS('Base File'!$BV:$BV,"Not Met",'Base File'!$B:$B,'Account Summary'!#REF!)),"NR") -> NR | AK11: =IFERROR(COUNTIFS('Base File'!$G:$G,"Contractual SLA",'Base File'!$H:$H,"No",'Base File'!$B:$B,'Account Summary'!$C11,'Base File'!$BV:$BV,"Met")/SUM(COUNTIFS('Base File'!$G:$G,"Contractual SLA",'Base File'!$H:$H,"No",'Base File'!$B:$B,'Account Summary'!$C11,'Base File'!$BV:$BV,"Met")+COUNTIFS('Base File'!$G:$G,"Contractual SLA",'Base File'!$H:$H,"No",'Base File'!$B:$B,'Account Summary'!$C11,'Base File'!$BV:$BV,"Not Met")),"-") -> - | AL11: =IFERROR(COUNTIFS('Base File'!$G:$G,"Contractual SLA",'Base File'!$H:$H,"Yes",'Base File'!$B:$B,'Account Summary'!$C11,'Base File'!$BV:$BV,"Met")/SUM(COUNTIFS('Base File'!$G:$G,"Contractual SLA",'Base File'!$H:$H,"Yes",'Base File'!$B:$B,'Account Summary'!$C11,'Base File'!$BV:$BV,"Met")+COUNTIFS('Base File'!$G:$G,"Contractual SLA",'Base File'!$H:$H,"Yes",'Base File'!$B:$B,'Account Summary'!$C11,'Base File'!$BV:$BV,"Not Met")),"-") -> - | AM11: =IFERROR(COUNTIFS('Base File'!$BD:$BD,"Met",'Base File'!$B:$B,'Account Summary'!G11)/(COUNTIFS('Base File'!$BD:$BD,"Met",'Base File'!$B:$B,'Account Summary'!G11)+COUNTIFS('Base File'!$BD:$BD,"Not Met",'Base File'!$B:$B,'Account Summary'!G11)),"NR") -> NR | AN11: =IFERROR(COUNTIFS('Base File'!$BH:$BH,"Met",'Base File'!$B:$B,'Account Summary'!C11)/(COUNTIFS('Base File'!$BH:$BH,"Met",'Base File'!$B:$B,'Account Summary'!C11)+COUNTIFS('Base File'!$BH:$BH,"Not Met",'Base File'!$B:$B,'Account Summary'!C11)),"NR") -> NR | AO11: =IFERROR(COUNTIFS('Base File'!$G:$G,"Contractual SLA",'Base File'!$H:$H,"No",'Base File'!$B:$B,'Account Summary'!$C11,'Base File'!$BH:$BH,"Met")/SUM(COUNTIFS('Base File'!$G:$G,"Contractual SLA",'Base File'!$H:$H,"No",'Base File'!$B:$B,'Account Summary'!$C11,'Base File'!$BH:$BH,"Met")+COUNTIFS('Base File'!$G:$G,"Contractual SLA",'Base File'!$H:$H,"No",'Base File'!$B:$B,'Account Summary'!$C11,'Base File'!$BH:$BH,"Not Met")),"-") -> - | AP11: =IFERROR(COUNTIFS('Base File'!$G:$G,"Contractual SLA",'Base File'!$H:$H,"Yes",'Base File'!$B:$B,'Account Summary'!$C11,'Base File'!$BH:$BH,"Met")/SUM(COUNTIFS('Base File'!$G:$G,"Contractual SLA",'Base File'!$H:$H,"yes",'Base File'!$B:$B,'Account Summary'!$C11,'Base File'!$BH:$BH,"Met")+COUNTIFS('Base File'!$G:$G,"Contractual SLA",'Base File'!$H:$H,"yes",'Base File'!$B:$B,'Account Summary'!$C11,'Base File'!$BH:$BH,"Not Met")),"-") -> - | AQ11: =IFERROR(COUNTIFS('Base File'!$BH:$BH,"Met",'Base File'!$B:$B,'Account Summary'!G11)/(COUNTIFS('Base File'!$BH:$BH,"Met",'Base File'!$B:$B,'Account Summary'!G11)+COUNTIFS('Base File'!$BH:$BH,"Not Met",'Base File'!$B:$B,'Account Summary'!G11)),"NR") -> NR | AR11: =IFERROR(COUNTIFS('Base File'!$BJ:$BJ,"Met",'Base File'!$B:$B,'Account Summary'!C11)/(COUNTIFS('Base File'!$BJ:$BJ,"Met",'Base File'!$B:$B,'Account Summary'!C11)+COUNTIFS('Base File'!$BJ:$BJ,"Not Met",'Base File'!$B:$B,'Account Summary'!C11)),"NR") -> NR | AS11: =IFERROR(COUNTIFS('Base File'!$G:$G,"Contractual SLA",'Base File'!$H:$H,"No",'Base File'!$B:$B,'Account Summary'!$C11,'Base File'!$BJ:$BJ,"Met")/SUM(COUNTIFS('Base File'!$G:$G,"Contractual SLA",'Base File'!$H:$H,"No",'Base File'!$B:$B,'Account Summary'!$C11,'Base File'!$BJ:$BJ,"Met")+COUNTIFS('Base File'!$G:$G,"Contractual SLA",'Base File'!$H:$H,"No",'Base File'!$B:$B,'Account Summary'!$C11,'Base File'!$BJ:$BJ,"Not Met")),"-") -> - | AT11: =IFERROR(COUNTIFS('Base File'!$G:$G,"Contractual SLA",'Base File'!$H:$H,"Yes",'Base File'!$B:$B,'Account Summary'!$C11,'Base File'!$BJ:$BJ,"Met")/SUM(COUNTIFS('Base File'!$G:$G,"Contractual SLA",'Base File'!$H:$H,"yes",'Base File'!$B:$B,'Account Summary'!$C11,'Base File'!$BJ:$BJ,"Met")+COUNTIFS('Base File'!$G:$G,"Contractual SLA",'Base File'!$H:$H,"yes",'Base File'!$B:$B,'Account Summary'!$C11,'Base File'!$BJ:$BJ,"Not Met")),"-") -> - | AU11: =IFERROR(COUNTIFS('Base File'!$BH:$BH,"Met",'Base File'!$B:$B,'Account Summary'!K11)/(COUNTIFS('Base File'!$BH:$BH,"Met",'Base File'!$B:$B,'Account Summary'!K11)+COUNTIFS('Base File'!$BH:$BH,"Not Met",'Base File'!$B:$B,'Account Summary'!K11)),"NR") -> NR | AV11: NA | AW11: =IFERROR(COUNTIFS('Base File'!$G:$G,"Contractual SLA",'Base File'!$H:$H,"No",'Base File'!$B:$B,'Account Summary'!$C11,'Base File'!$BL:$BL,"Met")/SUM(COUNTIFS('Base File'!$G:$G,"Contractual SLA",'Base File'!$H:$H,"No",'Base File'!$B:$B,'Account Summary'!$C11,'Base File'!$BL:$BL,"Met")+COUNTIFS('Base File'!$G:$G,"Contractual SLA",'Base File'!$H:$H,"No",'Base File'!$B:$B,'Account Summary'!$C11,'Base File'!$BL:$BL,"Not Met")),"-") -> - | AX11: =IFERROR(COUNTIFS('Base File'!$G:$G,"Contractual SLA",'Base File'!$H:$H,"Yes",'Base File'!$B:$B,'Account Summary'!$C11,'Base File'!$BL:$BL,"Met")/SUM(COUNTIFS('Base File'!$G:$G,"Contractual SLA",'Base File'!$H:$H,"yes",'Base File'!$B:$B,'Account Summary'!$C11,'Base File'!$BL:$BL,"Met")+COUNTIFS('Base File'!$G:$G,"Contractual SLA",'Base File'!$H:$H,"yes",'Base File'!$B:$B,'Account Summary'!$C11,'Base File'!$BL:$BL,"Not Met")),"-") -> - | AY11: NA | AZ11: NA | BA11: - | BB11: - | BC11: NA | BD11: NA | BE11: =IFERROR(COUNTIFS('Base File'!$G:$G,"Contractual SLA",'Base File'!$H:$H,"No",'Base File'!$B:$B,'Account Summary'!$C11,'Base File'!$BP:$BP,"Met")/SUM(COUNTIFS('Base File'!$G:$G,"Contractual SLA",'Base File'!$H:$H,"No",'Base File'!$B:$B,'Account Summary'!$C11,'Base File'!$BP:$BP,"Met")+COUNTIFS('Base File'!$G:$G,"Contractual SLA",'Base File'!$H:$H,"No",'Base File'!$B:$B,'Account Summary'!$C11,'Base File'!$BP:$BP,"Not Met")),"-") -> - | BF11: =IFERROR(COUNTIFS('Base File'!$G:$G,"Contractual SLA",'Base File'!$H:$H,"Yes",'Base File'!$B:$B,'Account Summary'!$C11,'Base File'!$BP:$BP,"Met")/SUM(COUNTIFS('Base File'!$G:$G,"Contractual SLA",'Base File'!$H:$H,"yes",'Base File'!$B:$B,'Account Summary'!$C11,'Base File'!$BP:$BP,"Met")+COUNTIFS('Base File'!$G:$G,"Contractual SLA",'Base File'!$H:$H,"yes",'Base File'!$B:$B,'Account Summary'!$C11,'Base File'!$BP:$BP,"Not Met")),"-") -> - | BG11: NA | BH11: NA | BI11: =IFERROR(COUNTIFS('Base File'!$G:$G,"Contractual SLA",'Base File'!$H:$H,"No",'Base File'!$B:$B,'Account Summary'!$C11,'Base File'!$BR:$BR,"Met")/SUM(COUNTIFS('Base File'!$G:$G,"Contractual SLA",'Base File'!$H:$H,"No",'Base File'!$B:$B,'Account Summary'!$C11,'Base File'!$BR:$BR,"Met")+COUNTIFS('Base File'!$G:$G,"Contractual SLA",'Base File'!$H:$H,"No",'Base File'!$B:$B,'Account Summary'!$C11,'Base File'!$BR:$BR,"Not Met")),"-") -> - | BJ11: =IFERROR(COUNTIFS('Base File'!$G:$G,"Contractual SLA",'Base File'!$H:$H,"No",'Base File'!$B:$B,'Account Summary'!$C11,'Base File'!$BR:$BR,"Met")/SUM(COUNTIFS('Base File'!$G:$G,"Contractual SLA",'Base File'!$H:$H,"No",'Base File'!$B:$B,'Account Summary'!$C11,'Base File'!$BR:$BR,"Met")+COUNTIFS('Base File'!$G:$G,"Contractual SLA",'Base File'!$H:$H,"No",'Base File'!$B:$B,'Account Summary'!$C11,'Base File'!$BR:$BR,"Not Met")),"-") -> - | BK11: NA | BL11: NA | BM11: =IFERROR(COUNTIFS('Base File'!$G:$G,"Contractual SLA",'Base File'!$H:$H,"No",'Base File'!$B:$B,'Account Summary'!$C11,'Base File'!$BT:$BT,"Met")/SUM(COUNTIFS('Base File'!$G:$G,"Contractual SLA",'Base File'!$H:$H,"No",'Base File'!$B:$B,'Account Summary'!$C11,'Base File'!$BT:$BT,"Met")+COUNTIFS('Base File'!$G:$G,"Contractual SLA",'Base File'!$H:$H,"No",'Base File'!$B:$B,'Account Summary'!$C11,'Base File'!$BT:$BT,"Not Met")),"-") -> - | BN11: =IFERROR(COUNTIFS('Base File'!$G:$G,"Contractual SLA",'Base File'!$H:$H,"Yes",'Base File'!$B:$B,'Account Summary'!$C11,'Base File'!$BT:$BT,"Met")/SUM(COUNTIFS('Base File'!$G:$G,"Contractual SLA",'Base File'!$H:$H,"yes",'Base File'!$B:$B,'Account Summary'!$C11,'Base File'!$BT:$BT,"Met")+COUNTIFS('Base File'!$G:$G,"Contractual SLA",'Base File'!$H:$H,"yes",'Base File'!$B:$B,'Account Summary'!$C11,'Base File'!$BT:$BT,"Not Met")),"-") -> - | BO11: NA | BP11: NA | BQ11: =IFERROR(COUNTIFS('Base File'!$G:$G,"Internal KPI",'Base File'!$B:$B,'Account Summary'!$C11,'Base File'!$BV:$BV,"Met")/SUM(COUNTIFS('Base File'!$G:$G,"Internal KPI",'Base File'!$B:$B,'Account Summary'!$C11,'Base File'!$BV:$BV,"Met")+COUNTIFS('Base File'!$G:$G,"Internal KPI",'Base File'!$B:$B,'Account Summary'!$C11,'Base File'!$BV:$BV,"Not Met")),"-") -> - | BR11: =IFERROR(COUNTIFS('Base File'!$G:$G,"Contractual SLA",'Base File'!$H:$H,"Yes",'Base File'!$B:$B,'Account Summary'!$C11,'Base File'!$BV:$BV,"Met")/SUM(COUNTIFS('Base File'!$G:$G,"Contractual SLA",'Base File'!$H:$H,"Yes",'Base File'!$B:$B,'Account Summary'!$C11,'Base File'!$BV:$BV,"Met")+COUNTIFS('Base File'!$G:$G,"Contractual SLA",'Base File'!$H:$H,"Yes",'Base File'!$B:$B,'Account Summary'!$C11,'Base File'!$BV:$BV,"Not Met")),"-") -> - | BS11: NA
