Workbook

Sheet Position Tracker
A1: S.No | B1: Requisition Date | C1: Aging | D1: Bucket | E1: Role | F1: No of Openings | G1: Diversity | H1: Hiring Manager | I1: HR Spoc | J1: Status | K1: Grade | L1: Experience | M1: Min Budget | N1: Max Budget | O1: Variable % | P1: Education | Q1: Location | R1: Mandatory CTQ | S1: Requisition Date | T1: Roll Id | U1: Total Shotlisted | V1: Reject count | W1: MINUS | X1: FTR% | Y1: Level | Z1: Date | AA1: Status | AB1: Intake Date | AC1: Hold Date | AD1: Offer Date | AE1: Join Date | AF1: TTO | AG1: TTF | AH1: Remarks | AI1: Replacement/New | AJ1: Replacement of (Name)
A2: 1 | B2: 45401 | C2: =IF(B2="","",NETWORKDAYS.INTL(B2,TODAY(),1,'HELPER(Dont Delete)'!A:A)) -> 419 | D2: =IF(J2="Open", IF(AND(C2>=0, C2<=30), "0-30", IF(AND(C2>=31, C2<=45), "31-45", IF(AND(C2>=46, C2<=60), "46-60", IF(AND(C2>=61, C2<=75), "61-75", IF(AND(C2>=76, C2<=90), "76-90", IF(AND(C2>=91, C2<=105), "91-105", IF(AND(C2>=106, C2<=120), "106-120", IF(C2>120, "120+", "")))))))),"") | E2: Fabrication | F2: 1 | G2: No | H2: SK Goel | I2: Ujjwal | J2: Hold | K2: DGM/GM | L2: 8-12 years | M2: 35 LPA/40 LPA | N2: 40 LPA/45 LPA | O2: 10%/30% | P2: B.tech | Q2: Mumbai | S2: =B2 -> 45401 | U2: =COUNTIFS('Candidate Tracker'!D:D,'Position Tracker'!E2,'Candidate Tracker'!V:V, "<>Screening Pending") -> 6 | V2: =COUNTIFS('Candidate Tracker'!D:D,'Position Tracker'!E2,'Candidate Tracker'!V:V, "Screen Reject") -> 0 | W2: =U2-V2 -> 6 | X2: =IFERROR(IF(U2=0,0,IF(V2=0,"100%",W2/U2)),"") -> 100% | Y2: RL3 | AF2: =IF(OR(AD2="",B2=""),"",NETWORKDAYS.INTL(B2,AD2,1,'HELPER(Dont Delete)'!A:A)) | AG2: =IF(OR(AD2="",B2=""),"",NETWORKDAYS.INTL(B2,AE2,1,'HELPER(Dont Delete)'!A:A))
A3: 2 | B3: 45356 | C3: =IF(B3="","",NETWORKDAYS.INTL(B3,TODAY(),1,'HELPER(Dont Delete)'!A:A)) -> 444 | D3: =IF(J3="Open", IF(AND(C3>=0, C3<=30), "0-30", IF(AND(C3>=31, C3<=45), "31-45", IF(AND(C3>=46, C3<=60), "46-60", IF(AND(C3>=61, C3<=75), "61-75", IF(AND(C3>=76, C3<=90), "76-90", IF(AND(C3>=91, C3<=105), "91-105", IF(AND(C3>=106, C3<=120), "106-120", IF(C3>120, "120+", "")))))))),"") | E3: KAM (Mumbai) | F3: 1 | G3: No | H3: Aman | I3: Ujjwal | J3: Scap | K3: Executive | L3: 2-4 years | N3: 7.5 LPA | O3: 0.1 | P3: B.tech/ B.tech + MBA/ MBA | Q3: Mumbai | S3: =B3 -> 45356 | U3: =COUNTIFS('Candidate Tracker'!D:D,'Position Tracker'!E3,'Candidate Tracker'!V:V, "<>Screening Pending") -> 5 | V3: =COUNTIFS('Candidate Tracker'!D:D,'Position Tracker'!E3,'Candidate Tracker'!V:V, "Screen Reject") -> 1 | W3: =U3-V3 -> 4 | X3: =IFERROR(IF(U3=0,0,IF(V3=0,"100%",W3/U3)),"") -> 0.8 | Y3: RL1 | AF3: =IF(OR(AD3="",B3=""),"",NETWORKDAYS.INTL(B3,AD3,1,'HELPER(Dont Delete)'!A:A)) | AG3: =IF(OR(AD3="",B3=""),"",NETWORKDAYS.INTL(B3,AE3,1,'HELPER(Dont Delete)'!A:A))
A4: 3 | B4: 45299 | C4: =IF(B4="","",NETWORKDAYS.INTL(B4,TODAY(),1,'HELPER(Dont Delete)'!A:A)) -> 479 | D4: =IF(J4="Open", IF(AND(C4>=0, C4<=30), "0-30", IF(AND(C4>=31, C4<=45), "31-45", IF(AND(C4>=46, C4<=60), "46-60", IF(AND(C4>=61, C4<=75), "61-75", IF(AND(C4>=76, C4<=90), "76-90", IF(AND(C4>=91, C4<=105), "91-105", IF(AND(C4>=106, C4<=120), "106-120", IF(C4>120, "120+", "")))))))),"") | E4: Logistics - Manager/Sr Manager | F4: 1 | G4: No | H4: DB Singh | I4: Ujjwal | J4: Joined | K4: Manager/Senior Manager | L4: 7-10 years | N4: 20 LPA | O4: 0.1 | P4: B.tech | Q4: Gurugram | R4: Logistics, Transportation, Trucks, Railways. Domestic transportation | S4: =B4 -> 45299 | U4: =COUNTIFS('Candidate Tracker'!D:D,'Position Tracker'!E4,'Candidate Tracker'!V:V, "<>Screening Pending") -> 11 | V4: =COUNTIFS('Candidate Tracker'!D:D,'Position Tracker'!E4,'Candidate Tracker'!V:V, "Screen Reject") -> 2 | W4: =U4-V4 -> 9 | X4: =IFERROR(IF(U4=0,0,IF(V4=0,"100%",W4/U4)),"") -> 0.81818182 | Y4: RL2 | AD4: 45425 | AE4: 45481 | AF4: =IF(OR(AD4="",B4=""),"",NETWORKDAYS.INTL(B4,AD4,1,'HELPER(Dont Delete)'!A:A)) -> 76 | AG4: =IF(OR(AD4="",B4=""),"",NETWORKDAYS.INTL(B4,AE4,1,'HELPER(Dont Delete)'!A:A)) -> 114
A5: 4 | B5: 45327 | C5: =IF(B5="","",NETWORKDAYS.INTL(B5,TODAY(),1,'HELPER(Dont Delete)'!A:A)) -> 463 | D5: =IF(J5="Open", IF(AND(C5>=0, C5<=30), "0-30", IF(AND(C5>=31, C5<=45), "31-45", IF(AND(C5>=46, C5<=60), "46-60", IF(AND(C5>=61, C5<=75), "61-75", IF(AND(C5>=76, C5<=90), "76-90", IF(AND(C5>=91, C5<=105), "91-105", IF(AND(C5>=106, C5<=120), "106-120", IF(C5>120, "120+", "")))))))),"") | E5: KAM (Kolkata) | F5: 1 | G5: No | H5: Aman | I5: Ujjwal | J5: Joined | K5: Manager | L5: 3-8 years | N5: 7.5 LPA | O5: 0.1 | P5: B.tech/ B.tech + MBA/ MBA | Q5: Kolkata | S5: =B5 -> 45327 | U5: =COUNTIFS('Candidate Tracker'!D:D,'Position Tracker'!E5,'Candidate Tracker'!V:V, "<>Screening Pending") -> 25 | V5: =COUNTIFS('Candidate Tracker'!D:D,'Position Tracker'!E5,'Candidate Tracker'!V:V, "Screen Reject") -> 7 | W5: =U5-V5 -> 18 | X5: =IFERROR(IF(U5=0,0,IF(V5=0,"100%",W5/U5)),"") -> 0.72 | Y5: RL2 | AD5: 45369 | AE5: 45390 | AF5: =IF(OR(AD5="",B5=""),"",NETWORKDAYS.INTL(B5,AD5,1,'HELPER(Dont Delete)'!A:A)) -> 27 | AG5: =IF(OR(AD5="",B5=""),"",NETWORKDAYS.INTL(B5,AE5,1,'HELPER(Dont Delete)'!A:A)) -> 39
A6: 5 | B6: 45356 | C6: =IF(B6="","",NETWORKDAYS.INTL(B6,TODAY(),1,'HELPER(Dont Delete)'!A:A)) -> 444 | D6: =IF(J6="Open", IF(AND(C6>=0, C6<=30), "0-30", IF(AND(C6>=31, C6<=45), "31-45", IF(AND(C6>=46, C6<=60), "46-60", IF(AND(C6>=61, C6<=75), "61-75", IF(AND(C6>=76, C6<=90), "76-90", IF(AND(C6>=91, C6<=105), "91-105", IF(AND(C6>=106, C6<=120), "106-120", IF(C6>120, "120+", "")))))))),"") | E6: KAM (Ahmedabad) | F6: 1 | G6: No | H6: Aman | I6: Ujjwal | J6: Joined | K6: Executive | L6: 2-4 years | N6: 7.5 LPA | O6: 0.1 | P6: B.tech/ B.tech + MBA/ MBA | Q6: Ahmedabad | S6: =B6 -> 45356 | U6: =COUNTIFS('Candidate Tracker'!D:D,'Position Tracker'!E6,'Candidate Tracker'!V:V, "<>Screening Pending") -> 0 | V6: =COUNTIFS('Candidate Tracker'!D:D,'Position Tracker'!E6,'Candidate Tracker'!V:V, "Screen Reject") -> 0 | W6: =U6-V6 -> 0 | X6: =IFERROR(IF(U6=0,0,IF(V6=0,"100%",W6/U6)),"") -> 0 | Y6: RL1 | AD6: 45397 | AE6: 45432 | AF6: =IF(OR(AD6="",B6=""),"",NETWORKDAYS.INTL(B6,AD6,1,'HELPER(Dont Delete)'!A:A)) -> 23 | AG6: =IF(OR(AD6="",B6=""),"",NETWORKDAYS.INTL(B6,AE6,1,'HELPER(Dont Delete)'!A:A)) -> 46
A7: 6 | B7: 45356 | C7: =IF(B7="","",NETWORKDAYS.INTL(B7,TODAY(),1,'HELPER(Dont Delete)'!A:A)) -> 444 | D7: =IF(J7="Open", IF(AND(C7>=0, C7<=30), "0-30", IF(AND(C7>=31, C7<=45), "31-45", IF(AND(C7>=46, C7<=60), "46-60", IF(AND(C7>=61, C7<=75), "61-75", IF(AND(C7>=76, C7<=90), "76-90", IF(AND(C7>=91, C7<=105), "91-105", IF(AND(C7>=106, C7<=120), "106-120", IF(C7>120, "120+", "")))))))),"") | E7: KAM (Gurgaon) | F7: 1 | G7: No | H7: Aman | I7: Ujjwal | J7: Hold | K7: Executive | L7: 2-4 years | N7: 7.5 LPA | O7: 0.1 | P7: B.tech/ B.tech + MBA/ MBA | Q7: Gurgaon | S7: =B7 -> 45356 | U7: =COUNTIFS('Candidate Tracker'!D:D,'Position Tracker'!E7,'Candidate Tracker'!V:V, "<>Screening Pending") -> 24 | V7: =COUNTIFS('Candidate Tracker'!D:D,'Position Tracker'!E7,'Candidate Tracker'!V:V, "Screen Reject") -> 4 | W7: =U7-V7 -> 20 | X7: =IFERROR(IF(U7=0,0,IF(V7=0,"100%",W7/U7)),"") -> 0.83333333 | Y7: RL1 | AF7: =IF(OR(AD7="",B7=""),"",NETWORKDAYS.INTL(B7,AD7,1,'HELPER(Dont Delete)'!A:A)) | AG7: =IF(OR(AD7="",B7=""),"",NETWORKDAYS.INTL(B7,AE7,1,'HELPER(Dont Delete)'!A:A))
A8: 7 | B8: 45476 | C8: =IF(B8="","",NETWORKDAYS.INTL(B8,TODAY(),1,'HELPER(Dont Delete)'!A:A))-9 -> 360 | D8: =IF(J8="Open", IF(AND(C8>=0, C8<=30), "0-30", IF(AND(C8>=31, C8<=45), "31-45", IF(AND(C8>=46, C8<=60), "46-60", IF(AND(C8>=61, C8<=75), "61-75", IF(AND(C8>=76, C8<=90), "76-90", IF(AND(C8>=91, C8<=105), "91-105", IF(AND(C8>=106, C8<=120), "106-120", IF(C8>120, "120+", "")))))))),"") | E8: KAM_ Steel (Mumbai) | F8: 1 | G8: No | H8: Aman | I8: Ujjwal | J8: Joined | K8: Executive | L8: 2-4 years | N8: 8 LPA | O8: 0.1 | P8: B.tech | Q8: Mumbai | R8: Position on hold at 16 Sep, position reopen at 24 Sep | S8: =B8 -> 45476 | U8: =COUNTIFS('Candidate Tracker'!D:D,'Position Tracker'!E8,'Candidate Tracker'!V:V, "<>Screening Pending") -> 20 | V8: =COUNTIFS('Candidate Tracker'!D:D,'Position Tracker'!E8,'Candidate Tracker'!V:V, "Screen Reject") -> 3 | W8: =U8-V8 -> 17 | X8: =IFERROR(IF(U8=0,0,IF(V8=0,"100%",W8/U8)),"") -> 0.85 | Y8: RL1 | AF8: =IF(OR(AD8="",B8=""),"",NETWORKDAYS.INTL(B8,AD8,1,'HELPER(Dont Delete)'!A:A)) | AG8: =IF(OR(AD8="",B8=""),"",NETWORKDAYS.INTL(B8,AE8,1,'HELPER(Dont Delete)'!A:A))
A9: 8 | B9: 45476 | C9: =IF(B9="","",NETWORKDAYS.INTL(B9,TODAY(),1,'HELPER(Dont Delete)'!A:A)) -> 369 | D9: =IF(J9="Open", IF(AND(C9>=0, C9<=30), "0-30", IF(AND(C9>=31, C9<=45), "31-45", IF(AND(C9>=46, C9<=60), "46-60", IF(AND(C9>=61, C9<=75), "61-75", IF(AND(C9>=76, C9<=90), "76-90", IF(AND(C9>=91, C9<=105), "91-105", IF(AND(C9>=106, C9<=120), "106-120", IF(C9>120, "120+", "")))))))),"") | E9: KAM - AM | F9: 1 | G9: No | H9: Aman | I9: Ujjwal | J9: Hold | K9: AM | L9: 3-8 Years | N9: 11 LPA | O9: 0.1 | P9: B.tech | Q9: Vadodara | S9: =B9 -> 45476 | U9: =COUNTIFS('Candidate Tracker'!D:D,'Position Tracker'!E9,'Candidate Tracker'!V:V, "<>Screening Pending") -> 8 | V9: =COUNTIFS('Candidate Tracker'!D:D,'Position Tracker'!E9,'Candidate Tracker'!V:V, "Screen Reject") -> 1 | W9: =U9-V9 -> 7 | X9: =IFERROR(IF(U9=0,0,IF(V9=0,"100%",W9/U9)),"") -> 0.875 | Y9: RL1 | AF9: =IF(OR(AD9="",B9=""),"",NETWORKDAYS.INTL(B9,AD9,1,'HELPER(Dont Delete)'!A:A)) | AG9: =IF(OR(AD9="",B9=""),"",NETWORKDAYS.INTL(B9,AE9,1,'HELPER(Dont Delete)'!A:A))
A10: 9 | B10: 45548 | C10: =IF(B10="","",NETWORKDAYS.INTL(B10,TODAY(),1,'HELPER(Dont Delete)'!A:A)) -> 321 | D10: =IF(J10="Open", IF(AND(C10>=0, C10<=30), "0-30", IF(AND(C10>=31, C10<=45), "31-45", IF(AND(C10>=46, C10<=60), "46-60", IF(AND(C10>=61, C10<=75), "61-75", IF(AND(C10>=76, C10<=90), "76-90", IF(AND(C10>=91, C10<=105), "91-105", IF(AND(C10>=106, C10<=120), "106-120", IF(C10>120, "120+", "")))))))),"") | E10: KAM_ Steel (Hyderabad) | F10: 1 | G10: No | H10: Aman | I10: Ujjwal | J10: Joined | K10: Executive | L10: 2-4 years | N10: 9 LPA | O10: 0.1 | P10: B.tech | Q10: Hyderabad | S10: =B10 -> 45548 | U10: =COUNTIFS('Candidate Tracker'!D:D,'Position Tracker'!E10,'Candidate Tracker'!V:V, "<>Screening Pending") -> 4 | V10: =COUNTIFS('Candidate Tracker'!D:D,'Position Tracker'!E10,'Candidate Tracker'!V:V, "Screen Reject") -> 0 | W10: =U10-V10 -> 4 | X10: =IFERROR(IF(U10=0,0,IF(V10=0,"100%",W10/U10)),"") -> 100% | Y10: RL1 | AF10: =IF(OR(AD10="",B10=""),"",NETWORKDAYS.INTL(B10,AD10,1,'HELPER(Dont Delete)'!A:A)) | AG10: =IF(OR(AD10="",B10=""),"",NETWORKDAYS.INTL(B10,AE10,1,'HELPER(Dont Delete)'!A:A))
A11: 10 | B11: 45551 | C11: =IF(B11="","",NETWORKDAYS.INTL(B11,TODAY(),1,'HELPER(Dont Delete)'!A:A)) -> 320 | D11: =IF(J11="Open", IF(AND(C11>=0, C11<=30), "0-30", IF(AND(C11>=31, C11<=45), "31-45", IF(AND(C11>=46, C11<=60), "46-60", IF(AND(C11>=61, C11<=75), "61-75", IF(AND(C11>=76, C11<=90), "76-90", IF(AND(C11>=91, C11<=105), "91-105", IF(AND(C11>=106, C11<=120), "106-120", IF(C11>120, "120+", "")))))))),"") | E11: Supply Chain Manager | F11: 1 | G11: No | H11: Aman | I11: Ujjwal | J11: Joined | K11: Manager | L11: 5-10 years | N11: 19 LPA | O11: 0.1 | P11: B.tech / MBA | Q11: Gurgaon | S11: =B11 -> 45551 | U11: =COUNTIFS('Candidate Tracker'!D:D,'Position Tracker'!E11,'Candidate Tracker'!V:V, "<>Screening Pending") -> 14 | V11: =COUNTIFS('Candidate Tracker'!D:D,'Position Tracker'!E11,'Candidate Tracker'!V:V, "Screen Reject") -> 3 | W11: =U11-V11 -> 11 | X11: =IFERROR(IF(U11=0,0,IF(V11=0,"100%",W11/U11)),"") -> 0.78571429 | Y11: RL2 | AF11: =IF(OR(AD11="",B11=""),"",NETWORKDAYS.INTL(B11,AD11,1,'HELPER(Dont Delete)'!A:A)) | AG11: =IF(OR(AD11="",B11=""),"",NETWORKDAYS.INTL(B11,AE11,1,'HELPER(Dont Delete)'!A:A))
A12: 11 | B12: 45593 | C12: =IF(B12="","",NETWORKDAYS.INTL(B12,TODAY(),1,'HELPER(Dont Delete)'!A:A)) -> 295 | D12: =IF(J12="Open", IF(AND(C12>=0, C12<=30), "0-30", IF(AND(C12>=31, C12<=45), "31-45", IF(AND(C12>=46, C12<=60), "46-60", IF(AND(C12>=61, C12<=75), "61-75", IF(AND(C12>=76, C12<=90), "76-90", IF(AND(C12>=91, C12<=105), "91-105", IF(AND(C12>=106, C12<=120), "106-120", IF(C12>120, "120+", "")))))))),"") | E12: Plant Head | F12: 1 | G12: No | H12: Aman | I12: Ujjwal | J12: Hold | K12: AGM/DGM | L12: 20-25 Years | N12: 60 LPA | O12: 0.2 | P12: B.tech | Q12: Mumbai | R12: Fabrication, steel, Remarks (2 Jan put on hold ) | S12: =B12 -> 45593 | U12: =COUNTIFS('Candidate Tracker'!D:D,'Position Tracker'!E12,'Candidate Tracker'!V:V, "<>Screening Pending") -> 8 | V12: =COUNTIFS('Candidate Tracker'!D:D,'Position Tracker'!E12,'Candidate Tracker'!V:V, "Screen Reject") -> 1 | W12: =U12-V12 -> 7 | X12: =IFERROR(IF(U12=0,0,IF(V12=0,"100%",W12/U12)),"") -> 0.875 | Y12: RL3
A13: 12 | B13: 45629 | C13: =IF(B13="","",NETWORKDAYS.INTL(B13,TODAY(),1,'HELPER(Dont Delete)'!A:A)) -> 272 | D13: =IF(J13="Open", IF(AND(C13>=0, C13<=30), "0-30", IF(AND(C13>=31, C13<=45), "31-45", IF(AND(C13>=46, C13<=60), "46-60", IF(AND(C13>=61, C13<=75), "61-75", IF(AND(C13>=76, C13<=90), "76-90", IF(AND(C13>=91, C13<=105), "91-105", IF(AND(C13>=106, C13<=120), "106-120", IF(C13>120, "120+", "")))))))),"") | E13: Electrical Manager Maintenance | F13: 1 | G13: No | H13: Aman | I13: Ujjwal | J13: Joined | K13: Manager | L13: 10-12 Years | N13: 19 LPA | O13: 0.1 | P13: B.tech | Q13: Mumbai | R13: Internally Closed on 1 NOV, reopen at 3 Dec | S13: =B13 -> 45629 | T13: 2032 | U13: =COUNTIFS('Candidate Tracker'!D:D,'Position Tracker'!E13,'Candidate Tracker'!V:V, "<>Screening Pending") -> 8 | V13: =COUNTIFS('Candidate Tracker'!D:D,'Position Tracker'!E13,'Candidate Tracker'!V:V, "Screen Reject") -> 1 | W13: =U13-V13 -> 7 | X13: =IFERROR(IF(U13=0,0,IF(V13=0,"100%",W13/U13)),"") -> 0.875 | Y13: RL2
A14: 13 | B14: 45628 | C14: =IF(B14="","",NETWORKDAYS.INTL(B14,TODAY(),1,'HELPER(Dont Delete)'!A:A)) -> 273 | D14: =IF(J14="Open", IF(AND(C14>=0, C14<=30), "0-30", IF(AND(C14>=31, C14<=45), "31-45", IF(AND(C14>=46, C14<=60), "46-60", IF(AND(C14>=61, C14<=75), "61-75", IF(AND(C14>=76, C14<=90), "76-90", IF(AND(C14>=91, C14<=105), "91-105", IF(AND(C14>=106, C14<=120), "106-120", IF(C14>120, "120+", "")))))))),"") | E14: KAM_ Steel (Chennai) | F14: 1 | G14: No | H14: Aman | I14: Ujjwal | J14: Joined | K14: AM | L14: 3-9 Years | M14: 5 LPA | N14: 11 LPA | O14: 0.1 | P14: B.tech | Q14: Chennai | S14: =B14 -> 45628 | T14: 2031 | U14: =COUNTIFS('Candidate Tracker'!D:D,'Position Tracker'!E14,'Candidate Tracker'!V:V, "<>Screening Pending") -> 4 | V14: =COUNTIFS('Candidate Tracker'!D:D,'Position Tracker'!E14,'Candidate Tracker'!V:V, "Screen Reject") -> 1 | W14: =U14-V14 -> 3 | X14: =IFERROR(IF(U14=0,0,IF(V14=0,"100%",W14/U14)),"") -> 0.75 | Y14: RL1
A15: 14 | B15: 45750 | C15: =IF(B15="","",NETWORKDAYS.INTL(B15,TODAY(),1,'HELPER(Dont Delete)'!A:A)) -> 187 | D15: =IF(J15="Open", IF(AND(C15>=0, C15<=30), "0-30", IF(AND(C15>=31, C15<=45), "31-45", IF(AND(C15>=46, C15<=60), "46-60", IF(AND(C15>=61, C15<=75), "61-75", IF(AND(C15>=76, C15<=90), "76-90", IF(AND(C15>=91, C15<=105), "91-105", IF(AND(C15>=106, C15<=120), "106-120", IF(C15>120, "120+", "")))))))),"") | E15: Design Executive | F15: 3 | G15: No | H15: Neeraj | I15: Ujjwal | J15: Hold | K15: Executive | L15: 3-5 Years | M15: 5 LPA | N15: 7 LPA | O15: 0.1 | P15: B.tech | Q15: Gurgaon | R15: Position closed on 29 jan | S15: =B15 -> 45750 | T15: 2321 | U15: =COUNTIFS('Candidate Tracker'!D:D,'Position Tracker'!E15,'Candidate Tracker'!V:V, "<>Screening Pending") -> 25 | V15: =COUNTIFS('Candidate Tracker'!D:D,'Position Tracker'!E15,'Candidate Tracker'!V:V, "Screen Reject") -> 13 | W15: =U15-V15 -> 12 | X15: =IFERROR(IF(U15=0,0,IF(V15=0,"100%",W15/U15)),"") -> 0.48 | Y15: RL1 | AC15: 45771 | AH15: 2Jan2025 - New req created|2076
A16: 15 | B16: 45659 | C16: =IF(B16="","",NETWORKDAYS.INTL(B16,TODAY(),1,'HELPER(Dont Delete)'!A:A)) -> 252 | D16: =IF(J16="Open", IF(AND(C16>=0, C16<=30), "0-30", IF(AND(C16>=31, C16<=45), "31-45", IF(AND(C16>=46, C16<=60), "46-60", IF(AND(C16>=61, C16<=75), "61-75", IF(AND(C16>=76, C16<=90), "76-90", IF(AND(C16>=91, C16<=105), "91-105", IF(AND(C16>=106, C16<=120), "106-120", IF(C16>120, "120+", "")))))))),"") | E16: Mechanical Maintenance | F16: 1 | G16: No | H16: Nilesh | I16: Ujjwal | J16: Joined | K16: AM | L16: 6-10 Years | M16: 10 LPA | N16: 12 LPA | O16: 0.1 | P16: B.tech | Q16: Mumbai | S16: =B16 -> 45659 | T16: 2074 | U16: =COUNTIFS('Candidate Tracker'!D:D,'Position Tracker'!E16,'Candidate Tracker'!V:V, "<>Screening Pending") -> 7 | V16: =COUNTIFS('Candidate Tracker'!D:D,'Position Tracker'!E16,'Candidate Tracker'!V:V, "Screen Reject") -> 1 | W16: =U16-V16 -> 6 | X16: =IFERROR(IF(U16=0,0,IF(V16=0,"100%",W16/U16)),"") -> 0.85714286 | Y16: RL1
A17: 16 | B17: 45685 | C17: =IF(B17="","",NETWORKDAYS.INTL(B17,TODAY(),1,'HELPER(Dont Delete)'!A:A)) -> 234 | D17: =IF(J17="Open", IF(AND(C17>=0, C17<=30), "0-30", IF(AND(C17>=31, C17<=45), "31-45", IF(AND(C17>=46, C17<=60), "46-60", IF(AND(C17>=61, C17<=75), "61-75", IF(AND(C17>=76, C17<=90), "76-90", IF(AND(C17>=91, C17<=105), "91-105", IF(AND(C17>=106, C17<=120), "106-120", IF(C17>120, "120+", "")))))))),"") | E17: Electrical Maintenance AM | F17: 1 | G17: No | H17: Hem Patel, Nilesh Faldu | I17: Ujjwal | J17: Joined | K17: AM | L17: 6-10 Years | M17: 10 LPA | N17: 11 LPA | O17: 0.1 | P17: B.tech | Q17: Mumbai | S17: =B17 -> 45685 | T17: 2131 | U17: =COUNTIFS('Candidate Tracker'!D:D,'Position Tracker'!E17,'Candidate Tracker'!V:V, "<>Screening Pending") -> 20 | V17: =COUNTIFS('Candidate Tracker'!D:D,'Position Tracker'!E17,'Candidate Tracker'!V:V, "Screen Reject") -> 5 | W17: =U17-V17 -> 15 | X17: =IFERROR(IF(U17=0,0,IF(V17=0,"100%",W17/U17)),"") -> 0.75 | Y17: RL1 | AH17: 1/28/2025- Req date (Electrical Maintenance AM) Req 2131 | AK17: 45792 | AL17: =AK17-B17 -> 107
A18: 17 | B18: 45742 | C18: =IF(B18="","",NETWORKDAYS.INTL(B18,TODAY(),1,'HELPER(Dont Delete)'!A:A)) -> 193 | D18: =IF(J18="Open", IF(AND(C18>=0, C18<=30), "0-30", IF(AND(C18>=31, C18<=45), "31-45", IF(AND(C18>=46, C18<=60), "46-60", IF(AND(C18>=61, C18<=75), "61-75", IF(AND(C18>=76, C18<=90), "76-90", IF(AND(C18>=91, C18<=105), "91-105", IF(AND(C18>=106, C18<=120), "106-120", IF(C18>120, "120+", "")))))))),"") | E18: Manager Design | F18: 1 | G18: No | H18: Suresh P | I18: Ujjwal | J18: Joined | K18: Manager | L18: 6-15 Years | N18: 20 LPA | O18: 0.1 | P18: B.tech | Q18: Mumbai | S18: =B18 -> 45742 | T18: 2289 | U18: =COUNTIFS('Candidate Tracker'!D:D,'Position Tracker'!E18,'Candidate Tracker'!V:V, "<>Screening Pending") -> 21 | V18: =COUNTIFS('Candidate Tracker'!D:D,'Position Tracker'!E18,'Candidate Tracker'!V:V, "Screen Reject") -> 2 | W18: =U18-V18 -> 19 | X18: =IFERROR(IF(U18=0,0,IF(V18=0,"100%",W18/U18)),"") -> 0.9047619 | Y18: RL1
A19: 18 | B19: 45743 | C19: =IF(B19="","",NETWORKDAYS.INTL(B19,TODAY(),1,'HELPER(Dont Delete)'!A:A)) -> 192 | D19: =IF(J19="Open", IF(AND(C19>=0, C19<=30), "0-30", IF(AND(C19>=31, C19<=45), "31-45", IF(AND(C19>=46, C19<=60), "46-60", IF(AND(C19>=61, C19<=75), "61-75", IF(AND(C19>=76, C19<=90), "76-90", IF(AND(C19>=91, C19<=105), "91-105", IF(AND(C19>=106, C19<=120), "106-120", IF(C19>120, "120+", "")))))))),"") | E19: Manager QA | F19: 1 | G19: No | H19: Nilesh, P Suresh | I19: Ujjwal | J19: Joined | K19: Manager | L19: 10-15 Years | N19: 15 - 16LPA | O19: 0.1 | P19: B.tech | Q19: Mumbai | S19: =B19 -> 45743 | T19: 2297 | U19: =COUNTIFS('Candidate Tracker'!D:D,'Position Tracker'!E19,'Candidate Tracker'!V:V, "<>Screening Pending") -> 7 | V19: =COUNTIFS('Candidate Tracker'!D:D,'Position Tracker'!E19,'Candidate Tracker'!V:V, "Screen Reject") -> 2 | W19: =U19-V19 -> 5 | X19: =IFERROR(IF(U19=0,0,IF(V19=0,"100%",W19/U19)),"") -> 0.71428571 | Y19: RL1
A20: 19 | B20: 45743 | C20: =IF(B20="","",NETWORKDAYS.INTL(B20,TODAY(),1,'HELPER(Dont Delete)'!A:A)) -> 192 | D20: =IF(J20="Open", IF(AND(C20>=0, C20<=30), "0-30", IF(AND(C20>=31, C20<=45), "31-45", IF(AND(C20>=46, C20<=60), "46-60", IF(AND(C20>=61, C20<=75), "61-75", IF(AND(C20>=76, C20<=90), "76-90", IF(AND(C20>=91, C20<=105), "91-105", IF(AND(C20>=106, C20<=120), "106-120", IF(C20>120, "120+", "")))))))),"") | E20: AM Purchase | F20: 1 | G20: No | H20: Shiv | I20: Ujjwal | J20: Joined | K20: AM | L20: 6-10 Years | M20: 10LPA | N20: 11LPA | O20: 0.1 | P20: B.tech | Q20: Mumbai | S20: =B20 -> 45743 | T20: 2295 | U20: =COUNTIFS('Candidate Tracker'!D:D,'Position Tracker'!E20,'Candidate Tracker'!V:V, "<>Screening Pending") -> 9 | V20: =COUNTIFS('Candidate Tracker'!D:D,'Position Tracker'!E20,'Candidate Tracker'!V:V, "Screen Reject") -> 1 | W20: =U20-V20 -> 8 | X20: =IFERROR(IF(U20=0,0,IF(V20=0,"100%",W20/U20)),"") -> 0.88888889 | Y20: RL1
A21: 20 | B21: 45743 | C21: =IF(B21="","",NETWORKDAYS.INTL(B21,TODAY(),1,'HELPER(Dont Delete)'!A:A)) -> 192 | D21: =IF(J21="Open", IF(AND(C21>=0, C21<=30), "0-30", IF(AND(C21>=31, C21<=45), "31-45", IF(AND(C21>=46, C21<=60), "46-60", IF(AND(C21>=61, C21<=75), "61-75", IF(AND(C21>=76, C21<=90), "76-90", IF(AND(C21>=91, C21<=105), "91-105", IF(AND(C21>=106, C21<=120), "106-120", IF(C21>120, "120+", "")))))))),"") | E21: Manager mechanical Maintenance | F21: 1 | G21: No | H21: Nilesh | I21: Ujjwal | J21: Hold | K21: Manager | L21: 10-15 Years | N21: 15-16 LPA | O21: 0.1 | P21: B.tech | Q21: Mumbai | S21: =B21 -> 45743 | T21: 2296 | U21: =COUNTIFS('Candidate Tracker'!D:D,'Position Tracker'!E21,'Candidate Tracker'!V:V, "<>Screening Pending") -> 7 | V21: =COUNTIFS('Candidate Tracker'!D:D,'Position Tracker'!E21,'Candidate Tracker'!V:V, "Screen Reject") -> 6 | W21: =U21-V21 -> 1 | X21: =IFERROR(IF(U21=0,0,IF(V21=0,"100%",W21/U21)),"") -> 0.14285714 | Y21: RL1 | AC21: 45771
A22: 21 | B22: 45743 | C22: =IF(B22="","",NETWORKDAYS.INTL(B22,TODAY(),1,'HELPER(Dont Delete)'!A:A)) -> 192 | D22: =IF(J22="Open", IF(AND(C22>=0, C22<=30), "0-30", IF(AND(C22>=31, C22<=45), "31-45", IF(AND(C22>=46, C22<=60), "46-60", IF(AND(C22>=61, C22<=75), "61-75", IF(AND(C22>=76, C22<=90), "76-90", IF(AND(C22>=91, C22<=105), "91-105", IF(AND(C22>=106, C22<=120), "106-120", IF(C22>120, "120+", "")))))))),"") | E22: AGM Finance | F22: 1 | G22: No | H22: DB Singh | I22: Ujjwal | J22: Internally Closed | K22: AGM | N22: 35-40 | O22: 0.1 | P22: B.tech | Q22: Gurugram | S22: =B22 -> 45743 | T22: 2470 | U22: =COUNTIFS('Candidate Tracker'!D:D,'Position Tracker'!E22,'Candidate Tracker'!V:V, "<>Screening Pending") -> 3 | V22: =COUNTIFS('Candidate Tracker'!D:D,'Position Tracker'!E22,'Candidate Tracker'!V:V, "Screen Reject") -> 1 | W22: =U22-V22 -> 2 | X22: =IFERROR(IF(U22=0,0,IF(V22=0,"100%",W22/U22)),"") -> 0.66666667 | Y22: RL3 | AC22: 45833
A23: 22 | B23: 45743 | C23: =IF(B23="","",NETWORKDAYS.INTL(B23,TODAY(),1,'HELPER(Dont Delete)'!A:A)) -> 192 | D23: =IF(J23="Open", IF(AND(C23>=0, C23<=30), "0-30", IF(AND(C23>=31, C23<=45), "31-45", IF(AND(C23>=46, C23<=60), "46-60", IF(AND(C23>=61, C23<=75), "61-75", IF(AND(C23>=76, C23<=90), "76-90", IF(AND(C23>=91, C23<=105), "91-105", IF(AND(C23>=106, C23<=120), "106-120", IF(C23>120, "120+", "")))))))),"") | E23: DGM Sales | F23: 1 | G23: No | H23: Madhur Gupta | I23: Ujjwal | J23: Hold | K23: DGM | N23: 40-45 | O23: 0.1 | P23: B.tech | Q23: Gurugram | S23: =B23 -> 45743 | U23: =COUNTIFS('Candidate Tracker'!D:D,'Position Tracker'!E23,'Candidate Tracker'!V:V, "<>Screening Pending") -> 6 | V23: =COUNTIFS('Candidate Tracker'!D:D,'Position Tracker'!E23,'Candidate Tracker'!V:V, "Screen Reject") -> 4 | W23: =U23-V23 -> 2 | X23: =IFERROR(IF(U23=0,0,IF(V23=0,"100%",W23/U23)),"") -> 0.33333333 | Y23: RL3 | AC23: 45828
A24: 23 | B24: 45747 | C24: =IF(B24="","",NETWORKDAYS.INTL(B24,TODAY(),1,'HELPER(Dont Delete)'!A:A)) -> 190 | D24: =IF(J24="Open", IF(AND(C24>=0, C24<=30), "0-30", IF(AND(C24>=31, C24<=45), "31-45", IF(AND(C24>=46, C24<=60), "46-60", IF(AND(C24>=61, C24<=75), "61-75", IF(AND(C24>=76, C24<=90), "76-90", IF(AND(C24>=91, C24<=105), "91-105", IF(AND(C24>=106, C24<=120), "106-120", IF(C24>120, "120+", "")))))))),"") | E24: Project head (reopened as lead) | F24: 1 | G24: No | H24: Venka Shivakrishna, Suresh p | I24: Ujjwal | J24: Hold | K24: Sr Mgr | L24: 12-18 Years | M24: 20LPA | N24: 25 LPA | O24: 0.1 | P24: B.tech | Q24: Mumbai | S24: =B24 -> 45747 | T24: 2317 | U24: =COUNTIFS('Candidate Tracker'!D:D,'Position Tracker'!E24,'Candidate Tracker'!V:V, "<>Screening Pending") -> 0 | V24: =COUNTIFS('Candidate Tracker'!D:D,'Position Tracker'!E24,'Candidate Tracker'!V:V, "Screen Reject") -> 0 | W24: =U24-V24 -> 0 | X24: =IFERROR(IF(U24=0,0,IF(V24=0,"100%",W24/U24)),"") -> 0 | Y24: RL3 | AC24: 45825 | AH24: 3/31/2025 - Requirement is changed
A25: 24 | B25: 45747 | C25: =IF(B25="","",NETWORKDAYS.INTL(B25,TODAY(),1,'HELPER(Dont Delete)'!A:A)) -> 190 | D25: =IF(J25="Open", IF(AND(C25>=0, C25<=30), "0-30", IF(AND(C25>=31, C25<=45), "31-45", IF(AND(C25>=46, C25<=60), "46-60", IF(AND(C25>=61, C25<=75), "61-75", IF(AND(C25>=76, C25<=90), "76-90", IF(AND(C25>=91, C25<=105), "91-105", IF(AND(C25>=106, C25<=120), "106-120", IF(C25>120, "120+", "")))))))),"") | E25: Project Manager (reopned as cordinator) | F25: 1 | G25: No | H25: Venka Shivakrishna, Suresh p | I25: Ujjwal | J25: Hold | K25: AM | L25: 6-10 Years | N25: 11 LPA | O25: 0.1 | P25: B.tech | Q25: Mumbai | S25: =B25 -> 45747 | T25: 2318 | U25: =COUNTIFS('Candidate Tracker'!D:D,'Position Tracker'!E25,'Candidate Tracker'!V:V, "<>Screening Pending") -> 0 | V25: =COUNTIFS('Candidate Tracker'!D:D,'Position Tracker'!E25,'Candidate Tracker'!V:V, "Screen Reject") -> 0 | W25: =U25-V25 -> 0 | X25: =IFERROR(IF(U25=0,0,IF(V25=0,"100%",W25/U25)),"") -> 0 | Y25: RL1 | AC25: 45860 | AH25: 3/31/2025 - Requirement is changed
A26: 25 | B26: 45747 | C26: =IF(B26="","",NETWORKDAYS.INTL(B26,TODAY(),1,'HELPER(Dont Delete)'!A:A)) -> 190 | D26: =IF(J26="Open", IF(AND(C26>=0, C26<=30), "0-30", IF(AND(C26>=31, C26<=45), "31-45", IF(AND(C26>=46, C26<=60), "46-60", IF(AND(C26>=61, C26<=75), "61-75", IF(AND(C26>=76, C26<=90), "76-90", IF(AND(C26>=91, C26<=105), "91-105", IF(AND(C26>=106, C26<=120), "106-120", IF(C26>120, "120+", "")))))))),"") | E26: Manager Purchase | F26: 1 | G26: No | H26: SK Sharma | I26: Ujjwal | J26: Offer Stage | K26: Manager / SM | L26: 10-15 Years | M26: 15 LPA | N26: 21LPA | O26: 0.1 | P26: B.tech | Q26: Gurugram | S26: =B26 -> 45747 | T26: 2303 | U26: =COUNTIFS('Candidate Tracker'!D:D,'Position Tracker'!E26,'Candidate Tracker'!V:V, "<>Screening Pending") -> 23 | V26: =COUNTIFS('Candidate Tracker'!D:D,'Position Tracker'!E26,'Candidate Tracker'!V:V, "Screen Reject") -> 3 | W26: =U26-V26 -> 20 | X26: =IFERROR(IF(U26=0,0,IF(V26=0,"100%",W26/U26)),"") -> 0.86956522 | Y26: RL1
A27: 26 | B27: 45747 | C27: =IF(B27="","",NETWORKDAYS.INTL(B27,TODAY(),1,'HELPER(Dont Delete)'!A:A)) -> 190 | D27: =IF(J27="Open", IF(AND(C27>=0, C27<=30), "0-30", IF(AND(C27>=31, C27<=45), "31-45", IF(AND(C27>=46, C27<=60), "46-60", IF(AND(C27>=61, C27<=75), "61-75", IF(AND(C27>=76, C27<=90), "76-90", IF(AND(C27>=91, C27<=105), "91-105", IF(AND(C27>=106, C27<=120), "106-120", IF(C27>120, "120+", "")))))))),"") | E27: Manager PPC | F27: 1 | G27: No | H27: Nilesh, P Suresh | I27: Ujjwal | J27: Joined | K27: Manager | L27: 10-15 Years | M27: 15 - 16 | N27: 17 - 22 | O27: 0.1 | P27: B.tech | Q27: Mumbai | S27: =B27 -> 45747 | T27: 2643 | U27: =COUNTIFS('Candidate Tracker'!D:D,'Position Tracker'!E27,'Candidate Tracker'!V:V, "<>Screening Pending") -> 8 | V27: =COUNTIFS('Candidate Tracker'!D:D,'Position Tracker'!E27,'Candidate Tracker'!V:V, "Screen Reject") -> 2 | W27: =U27-V27 -> 6 | X27: =IFERROR(IF(U27=0,0,IF(V27=0,"100%",W27/U27)),"") -> 0.75 | Y27: RL1 | AH27: 2316
A28: 31 | B28: 45848 | C28: =IF(B28="","",NETWORKDAYS.INTL(B28,TODAY(),1,'HELPER(Dont Delete)'!A:A)) -> 117 | D28: =IF(J28="Open", IF(AND(C28>=0, C28<=30), "0-30", IF(AND(C28>=31, C28<=45), "31-45", IF(AND(C28>=46, C28<=60), "46-60", IF(AND(C28>=61, C28<=75), "61-75", IF(AND(C28>=76, C28<=90), "76-90", IF(AND(C28>=91, C28<=105), "91-105", IF(AND(C28>=106, C28<=120), "106-120", IF(C28>120, "120+", "")))))))),"") | E28: Quality Assurance (QA) Coordinator | F28: 1 | G28: No | H28: Manoj Bhutani & P Suresh | I28: Ujjwal | J28: Hold | K28: Engineer/ Assistant Engineer | L28: 1-3 Years | M28: 5.5 LPA | N28: 7.6 LPA | O28: 0.1 | P28: Diploma / B.Tech in Mechanical / Industrial / Production / Metallurgy Engineering | Q28: Mumbai | S28: =B28 -> 45848 | T28: 2663 | U28: =COUNTIFS('Candidate Tracker'!D:D,'Position Tracker'!E32,'Candidate Tracker'!V:V, "<>Screening Pending") -> 27 | V28: =COUNTIFS('Candidate Tracker'!D:D,'Position Tracker'!E32,'Candidate Tracker'!V:V, "Screen Reject") -> 7 | W28: =U28-V28 -> 20 | X28: =IFERROR(IF(U28=0,0,IF(V28=0,"100%",W28/U28)),"") -> 0.74074074 | Y28: RL1 | AC28: 45898
A29: 28 | B29: 45750 | C29: =IF(B29="","",NETWORKDAYS.INTL(B29,TODAY(),1,'HELPER(Dont Delete)'!A:A)) -> 187 | D29: =IF(J29="Open", IF(AND(C29>=0, C29<=30), "0-30", IF(AND(C29>=31, C29<=45), "31-45", IF(AND(C29>=46, C29<=60), "46-60", IF(AND(C29>=61, C29<=75), "61-75", IF(AND(C29>=76, C29<=90), "76-90", IF(AND(C29>=91, C29<=105), "91-105", IF(AND(C29>=106, C29<=120), "106-120", IF(C29>120, "120+", "")))))))),"") | E29: Executive- Design | F29: 1 | G29: No | H29: Neeraj | I29: Ujjwal | J29: Joined | K29: Executive | L29: 3-5 Years | N29: 8.5 | O29: 0.1 | P29: B.tech | Q29: Mumbai | S29: =B29 -> 45750 | T29: 2321 | U29: =COUNTIFS('Candidate Tracker'!D:D,'Position Tracker'!E29,'Candidate Tracker'!V:V, "<>Screening Pending") -> 12 | V29: =COUNTIFS('Candidate Tracker'!D:D,'Position Tracker'!E29,'Candidate Tracker'!V:V, "Screen Reject") -> 1 | W29: =U29-V29 -> 11 | X29: =IFERROR(IF(U29=0,0,IF(V29=0,"100%",W29/U29)),"") -> 0.91666667 | Y29: RL1
A30: 29 | B30: 45762 | C30: =IF(B30="","",NETWORKDAYS.INTL(B30,TODAY(),1,'HELPER(Dont Delete)'!A:A)) -> 179 | D30: =IF(J30="Open", IF(AND(C30>=0, C30<=30), "0-30", IF(AND(C30>=31, C30<=45), "31-45", IF(AND(C30>=46, C30<=60), "46-60", IF(AND(C30>=61, C30<=75), "61-75", IF(AND(C30>=76, C30<=90), "76-90", IF(AND(C30>=91, C30<=105), "91-105", IF(AND(C30>=106, C30<=120), "106-120", IF(C30>120, "120+", "")))))))),"") | E30: Quality Engineer | F30: 2 | G30: No | H30: Suresh P | I30: Ujjwal | J30: Joined | K30: Executive | L30: 3-5 Years | N30: 8LPA | O30: 0.1 | P30: B.tech | Q30: Mumbai | S30: =B30 -> 45762 | T30: 2208, 2348 | U30: =COUNTIFS('Candidate Tracker'!D:D,'Position Tracker'!E30,'Candidate Tracker'!V:V, "<>Screening Pending") -> 0 | V30: =COUNTIFS('Candidate Tracker'!D:D,'Position Tracker'!E30,'Candidate Tracker'!V:V, "Screen Reject") -> 0 | W30: =U30-V30 -> 0 | X30: =IFERROR(IF(U30=0,0,IF(V30=0,"100%",W30/U30)),"") -> 0 | Y30: RL1
A31: 30 | B31: 45848 | C31: =IF(B31="","",NETWORKDAYS.INTL(B31,TODAY(),1,'HELPER(Dont Delete)'!A:A)) -> 117 | D31: =IF(J31="Open", IF(AND(C31>=0, C31<=30), "0-30", IF(AND(C31>=31, C31<=45), "31-45", IF(AND(C31>=46, C31<=60), "46-60", IF(AND(C31>=61, C31<=75), "61-75", IF(AND(C31>=76, C31<=90), "76-90", IF(AND(C31>=91, C31<=105), "91-105", IF(AND(C31>=106, C31<=120), "106-120", IF(C31>120, "120+", "")))))))),"") | E31: Quality Assurance (QA) Lead | F31: 1 | G31: No | H31: Manoj Bhutani & P Suresh | I31: Ujjwal | J31: Offer Stage | K31: Manager/ Associate Manager | L31: 8+ Years | M31: 12 LPA | N31: 18.4 LPA | O31: 0.1 | P31: B.Tech / Diploma in Mechanical / Production / Metallurgy / Materials Engineering | Q31: Mumbai | S31: =B31 -> 45848 | T31: 2664 | U31: =COUNTIFS('Candidate Tracker'!D:D,'Position Tracker'!E31,'Candidate Tracker'!V:V, "<>Screening Pending") -> 7 | V31: =COUNTIFS('Candidate Tracker'!D:D,'Position Tracker'!E31,'Candidate Tracker'!V:V, "Screen Reject") -> 3 | W31: =U31-V31 -> 4 | X31: =IFERROR(IF(U31=0,0,IF(V31=0,"100%",W31/U31)),"") -> 0.57142857 | Y31: RL1
A32: 32 | B32: 45848 | C32: =IF(B32="","",NETWORKDAYS.INTL(B32,TODAY(),1,'HELPER(Dont Delete)'!A:A)) -> 117 | D32: =IF(J32="Open", IF(AND(C32>=0, C32<=30), "0-30", IF(AND(C32>=31, C32<=45), "31-45", IF(AND(C32>=46, C32<=60), "46-60", IF(AND(C32>=61, C32<=75), "61-75", IF(AND(C32>=76, C32<=90), "76-90", IF(AND(C32>=91, C32<=105), "91-105", IF(AND(C32>=106, C32<=120), "106-120", IF(C32>120, "120+", "")))))))),"") | E32: Quality Control (QC) Coordinator | F32: 6 | G32: No | H32: Manoj Bhutani & P Suresh | I32: Ujjwal | J32: Offer Stage | K32: Engineer/ Assistant Engineer | L32: 1-4 Years | M32: 5.5 LPA | N32: 7.6 LPA | O32: 0.1 | P32: Diploma or B.Tech in Mechanical / Welding / Fabrication Engineering | Q32: Mumbai | S32: =B32 -> 45848 | T32: 2689 | U32: =COUNTIFS('Candidate Tracker'!D:D,'Position Tracker'!E33,'Candidate Tracker'!V:V, "<>Screening Pending") -> 18 | V32: =COUNTIFS('Candidate Tracker'!D:D,'Position Tracker'!E33,'Candidate Tracker'!V:V, "Screen Reject") -> 5 | W32: =U32-V32 -> 13 | X32: =IFERROR(IF(U32=0,0,IF(V32=0,"100%",W32/U32)),"") -> 0.72222222 | Y32: RL1
A33: 33 | B33: 45910 | C33: =IF(B33="","",NETWORKDAYS.INTL(B33,TODAY(),1,'HELPER(Dont Delete)'!A:A)) -> 73 | D33: =IF(J33="Open", IF(AND(C33>=0, C33<=30), "0-30", IF(AND(C33>=31, C33<=45), "31-45", IF(AND(C33>=46, C33<=60), "46-60", IF(AND(C33>=61, C33<=75), "61-75", IF(AND(C33>=76, C33<=90), "76-90", IF(AND(C33>=91, C33<=105), "91-105", IF(AND(C33>=106, C33<=120), "106-120", IF(C33>120, "120+", "")))))))),"") | E33: Machining & Beam Welding | F33: 3 | G33: No | H33: P Suresh & Navin Lalwani | I33: Ujjwal | J33: 1Hold/2joined | K33: Associate Manager/ Executive/ Engineer | L33: 5+ Years | M33: 7.6 LPA | N33: 12 LPA | O33: 0.1 | P33: Diploma or B.Tech in Mechanical, Production, or Fabrication Engineering | Q33: Mumbai | S33: =B33 -> 45910 | T33: 2661 | U33: =COUNTIFS('Candidate Tracker'!D:D,'Position Tracker'!E34,'Candidate Tracker'!V:V, "<>Screening Pending") -> 18 | V33: =COUNTIFS('Candidate Tracker'!D:D,'Position Tracker'!E34,'Candidate Tracker'!V:V, "Screen Reject") -> 5 | W33: =U33-V33 -> 13 | X33: =IFERROR(IF(U33=0,0,IF(V33=0,"100%",W33/U33)),"") -> 0.72222222 | Y33: RL1 | AC33: 45923 | AH33: 10July2025 - Req date chenged coz of bridge fabrication exp
A34: 35 | B34: 45848 | C34: =IF(B34="","",NETWORKDAYS.INTL(B34,TODAY(),1,'HELPER(Dont Delete)'!A:A)) -> 117 | D34: =IF(J34="Open", IF(AND(C34>=0, C34<=30), "0-30", IF(AND(C34>=31, C34<=45), "31-45", IF(AND(C34>=46, C34<=60), "46-60", IF(AND(C34>=61, C34<=75), "61-75", IF(AND(C34>=76, C34<=90), "76-90", IF(AND(C34>=91, C34<=105), "91-105", IF(AND(C34>=106, C34<=120), "106-120", IF(C34>120, "120+", "")))))))),"") | E34: Shot Blasting & Painting | F34: 3 | G34: No | H34: P Suresh & Navin Lalwani | I34: Ujjwal | J34: Offer stage | K34: Associate Manager/ Executive/ Engineer | L34: 5+ Years | M34: 7.6 LPA | N34: 12 LPA | O34: 0.1 | P34: ITI Painter or Diploma in Mechanical, Fabrication, or Paint Technology | Q34: Mumbai | S34: =B34 -> 45848 | T34: 2478/2791 | U34: =COUNTIFS('Candidate Tracker'!D:D,'Position Tracker'!E36,'Candidate Tracker'!V:V, "<>Screening Pending") -> 1 | V34: =COUNTIFS('Candidate Tracker'!D:D,'Position Tracker'!E36,'Candidate Tracker'!V:V, "Screen Reject") -> 0 | W34: =U34-V34 -> 1 | X34: =IFERROR(IF(U34=0,0,IF(V34=0,"100%",W34/U34)),"") -> 100% | Y34: RL1
A35: 34 | B35: 45848 | C35: =IF(B35="","",NETWORKDAYS.INTL(B35,TODAY(),1,'HELPER(Dont Delete)'!A:A)) -> 117 | D35: =IF(J35="Open", IF(AND(C35>=0, C35<=30), "0-30", IF(AND(C35>=31, C35<=45), "31-45", IF(AND(C35>=46, C35<=60), "46-60", IF(AND(C35>=61, C35<=75), "61-75", IF(AND(C35>=76, C35<=90), "76-90", IF(AND(C35>=91, C35<=105), "91-105", IF(AND(C35>=106, C35<=120), "106-120", IF(C35>120, "120+", "")))))))),"") | E35: Manual Welding | F35: 3 | G35: No | H35: P Suresh & Navin Lalwani | I35: Ujjwal | J35: 1Hold/2joined | K35: Associate Manager/ Executive/ Engineer | L35: 6+ Years | M35: 7.6 LPA | N35: 12 LPA | O35: 0.1 | P35: Diploma in Welding, Mechanical, or Fabrication Engineering (B.Tech. preferred) | Q35: Mumbai | S35: =B35 -> 45848 | T35: 2662 | U35: =COUNTIFS('Candidate Tracker'!D:D,'Position Tracker'!E35,'Candidate Tracker'!V:V, "<>Screening Pending") -> 8 | V35: =COUNTIFS('Candidate Tracker'!D:D,'Position Tracker'!E35,'Candidate Tracker'!V:V, "Screen Reject") -> 2 | W35: =U35-V35 -> 6 | X35: =IFERROR(IF(U35=0,0,IF(V35=0,"100%",W35/U35)),"") -> 0.75 | Y35: RL1 | AC35: 45923
A36: 36 | B36: 45848 | C36: =IF(B36="","",NETWORKDAYS.INTL(B36,TODAY(),1,'HELPER(Dont Delete)'!A:A)) -> 117 | D36: =IF(J36="Open", IF(AND(C36>=0, C36<=30), "0-30", IF(AND(C36>=31, C36<=45), "31-45", IF(AND(C36>=46, C36<=60), "46-60", IF(AND(C36>=61, C36<=75), "61-75", IF(AND(C36>=76, C36<=90), "76-90", IF(AND(C36>=91, C36<=105), "91-105", IF(AND(C36>=106, C36<=120), "106-120", IF(C36>120, "120+", "")))))))),"") | E36: Detailer | F36: 1 | G36: No | H36: Navin Lalwani & Niraj Yadav | I36: Ujjwal | J36: Internally Closed | K36: Engineer/ Assistant Engineer | L36: 3-7 Years | M36: 5.5 LPA | N36: 7.6 LPA | O36: 0.1 | P36: Diploma or B.Tech. in Mechanical/ Civil/ Structural/ Production Engineering | Q36: Mumbai | S36: =B36 -> 45848 | T36: 2686 | U36: =COUNTIFS('Candidate Tracker'!D:D,'Position Tracker'!E37,'Candidate Tracker'!V:V, "<>Screening Pending") -> 5 | V36: =COUNTIFS('Candidate Tracker'!D:D,'Position Tracker'!E37,'Candidate Tracker'!V:V, "Screen Reject") -> 1 | W36: =U36-V36 -> 4 | X36: =IFERROR(IF(U36=0,0,IF(V36=0,"100%",W36/U36)),"") -> 0.8 | Y36: RL1 | AC36: 45881
A37: 37 | B37: 45848 | C37: =IF(B37="","",NETWORKDAYS.INTL(B37,TODAY(),1,'HELPER(Dont Delete)'!A:A)) -> 117 | D37: =IF(J37="Open", IF(AND(C37>=0, C37<=30), "0-30", IF(AND(C37>=31, C37<=45), "31-45", IF(AND(C37>=46, C37<=60), "46-60", IF(AND(C37>=61, C37<=75), "61-75", IF(AND(C37>=76, C37<=90), "76-90", IF(AND(C37>=91, C37<=105), "91-105", IF(AND(C37>=106, C37<=120), "106-120", IF(C37>120, "120+", "")))))))),"") | E37: Welding Expert | F37: 1 | G37: No | H37: P Suresh & Navin Lalwani | I37: Ujjwal | J37: Hold | K37: Senior Manager/ Manager | L37: 12+ Years | M37: 18.4 LPA | N37: 24 LPA | O37: 0.1 | P37: B.Tech / M.Tech in Metallurgy or Mechanical Engineering | Q37: Mumbai | S37: =B37 -> 45848 | T37: 2666 | U37: =COUNTIFS('Candidate Tracker'!D:D,'Position Tracker'!E38,'Candidate Tracker'!V:V, "<>Screening Pending") -> 0 | V37: =COUNTIFS('Candidate Tracker'!D:D,'Position Tracker'!E38,'Candidate Tracker'!V:V, "Screen Reject") -> 0 | W37: =U37-V37 -> 0 | X37: =IFERROR(IF(U37=0,0,IF(V37=0,"100%",W37/U37)),"") -> 0 | Y37: RL2 | AC37: 45880
A38: 38 | B38: 45859 | C38: =IF(B38="","",NETWORKDAYS.INTL(B38,TODAY(),1,'HELPER(Dont Delete)'!A:A)) -> 110 | D38: =IF(J38="Open", IF(AND(C38>=0, C38<=30), "0-30", IF(AND(C38>=31, C38<=45), "31-45", IF(AND(C38>=46, C38<=60), "46-60", IF(AND(C38>=61, C38<=75), "61-75", IF(AND(C38>=76, C38<=90), "76-90", IF(AND(C38>=91, C38<=105), "91-105", IF(AND(C38>=106, C38<=120), "106-120", IF(C38>120, "120+", "")))))))),"") | E38: Plant Project Lead | F38: 1 | G38: No | H38: P Suresh & Navin Lalwani | I38: Ujjwal | J38: Cancelled | K38: Manager / SM | L38: 15-25 Years | M38: 24LPA | N38: 33LPA | O38: 0.1 | P38: B.tech | Q38: Mumbai | S38: =B38 -> 45859 | U38: =COUNTIFS('Candidate Tracker'!D:D,'Position Tracker'!E39,'Candidate Tracker'!V:V, "<>Screening Pending") -> 9 | V38: =COUNTIFS('Candidate Tracker'!D:D,'Position Tracker'!E39,'Candidate Tracker'!V:V, "Screen Reject") -> 4 | W38: =U38-V38 -> 5 | X38: =IFERROR(IF(U38=0,0,IF(V38=0,"100%",W38/U38)),"") -> 0.55555556 | Y38: RL2 | AC38: 45908
A39: 39 | B39: 45758 | C39: =IF(B39="","",NETWORKDAYS.INTL(B39,TODAY(),1,'HELPER(Dont Delete)'!A:A)) -> 181 | D39: =IF(J39="Open", IF(AND(C39>=0, C39<=30), "0-30", IF(AND(C39>=31, C39<=45), "31-45", IF(AND(C39>=46, C39<=60), "46-60", IF(AND(C39>=61, C39<=75), "61-75", IF(AND(C39>=76, C39<=90), "76-90", IF(AND(C39>=91, C39<=105), "91-105", IF(AND(C39>=106, C39<=120), "106-120", IF(C39>120, "120+", "")))))))),"") | E39: Plant Head (New) | F39: 1 | G39: No | H39: SK Goyal | I39: Ujjwal | J39: Internally Closed | K39: DGM | O39: 0.1 | P39: B.tech | Q39: Mumbai | S39: =B39 -> 45758 | U39: =COUNTIFS('Candidate Tracker'!D:D,'Position Tracker'!E28,'Candidate Tracker'!V:V, "<>Screening Pending") -> 15 | V39: =COUNTIFS('Candidate Tracker'!D:D,'Position Tracker'!E28,'Candidate Tracker'!V:V, "Screen Reject") -> 5 | W39: =U39-V39 -> 10 | X39: =IFERROR(IF(U39=0,0,IF(V39=0,"100%",W39/U39)),"") -> 0.66666667 | Y39: RL3 | AC39: 45871
A40: 40 | B40: 45860 | C40: =IF(B40="","",NETWORKDAYS.INTL(B40,TODAY(),1,'HELPER(Dont Delete)'!A:A)) -> 109 | D40: =IF(J40="Open", IF(AND(C40>=0, C40<=30), "0-30", IF(AND(C40>=31, C40<=45), "31-45", IF(AND(C40>=46, C40<=60), "46-60", IF(AND(C40>=61, C40<=75), "61-75", IF(AND(C40>=76, C40<=90), "76-90", IF(AND(C40>=91, C40<=105), "91-105", IF(AND(C40>=106, C40<=120), "106-120", IF(C40>120, "120+", "")))))))),"") | E40: Sales (new) | F40: 1 | G40: No | H40: Aman Vashishtha | I40: Ujjwal | J40: Hold | K40: DGM | L40: 15-20 Years | N40: 45 LPA | O40: 0.1 | P40: B.Tech & MBA | Q40: Gurugram | S40: =B40 -> 45860 | U40: =COUNTIFS('Candidate Tracker'!D:D,'Position Tracker'!E40,'Candidate Tracker'!V:V, "<>Screening Pending") -> 0 | V40: =COUNTIFS('Candidate Tracker'!D:D,'Position Tracker'!E40,'Candidate Tracker'!V:V, "Screen Reject") -> 0 | W40: =U40-V40 -> 0 | X40: =IFERROR(IF(U40=0,0,IF(V40=0,"100%",W40/U40)),"") -> 0 | Y40: RL3
A41: 41 | B41: 45873 | C41: =IF(B41="","",NETWORKDAYS.INTL(B41,TODAY(),1,'HELPER(Dont Delete)'!A:A)) -> 100 | D41: =IF(J41="Open", IF(AND(C41>=0, C41<=30), "0-30", IF(AND(C41>=31, C41<=45), "31-45", IF(AND(C41>=46, C41<=60), "46-60", IF(AND(C41>=61, C41<=75), "61-75", IF(AND(C41>=76, C41<=90), "76-90", IF(AND(C41>=91, C41<=105), "91-105", IF(AND(C41>=106, C41<=120), "106-120", IF(C41>120, "120+", "")))))))),"") | E41: Electrical Manager | F41: 1 | G41: No | H41: GP Gupta Mr. Nilesh Ratilal Faladu, Suresh P | I41: Ujjwal | J41: Hold | K41: Manager | L41: 10-12 Years | N41: 19 LPA | O41: 0.1 | P41: Btech | Q41: Mumbai | S41: =B41 -> 45873 | U41: =COUNTIFS('Candidate Tracker'!D:D,'Position Tracker'!E42,'Candidate Tracker'!V:V, "<>Screening Pending") -> 4 | V41: =COUNTIFS('Candidate Tracker'!D:D,'Position Tracker'!E42,'Candidate Tracker'!V:V, "Screen Reject") -> 2 | W41: =U41-V41 -> 2 | X41: =IFERROR(IF(U41=0,0,IF(V41=0,"100%",W41/U41)),"") -> 0.5 | Y41: RL1 | AC41: 45898
A42: 42 | B42: 45881 | C42: =IF(B42="","",NETWORKDAYS.INTL(B42,TODAY(),1,'HELPER(Dont Delete)'!A:A)) -> 94 | D42: =IF(J42="Open", IF(AND(C42>=0, C42<=30), "0-30", IF(AND(C42>=31, C42<=45), "31-45", IF(AND(C42>=46, C42<=60), "46-60", IF(AND(C42>=61, C42<=75), "61-75", IF(AND(C42>=76, C42<=90), "76-90", IF(AND(C42>=91, C42<=105), "91-105", IF(AND(C42>=106, C42<=120), "106-120", IF(C42>120, "120+", "")))))))),"") | E42: Plant Project Incharge | F42: 1 | G42: No | H42: Suresh p | I42: Ujjwal | J42: Hold | K42: AM | L42: 6-10 Years | N42: 11 LPA | O42: 0.1 | P42: B.tech | Q42: Mumbai | S42: =B42 -> 45881 | T42: 2318 | U42: =COUNTIFS('Candidate Tracker'!D:D,'Position Tracker'!E43,'Candidate Tracker'!V:V, "<>Screening Pending") -> 9 | V42: =COUNTIFS('Candidate Tracker'!D:D,'Position Tracker'!E43,'Candidate Tracker'!V:V, "Screen Reject") -> 4 | W42: =U42-V42 -> 5 | X42: =IFERROR(IF(U42=0,0,IF(V42=0,"100%",W42/U42)),"") -> 0.55555556 | Y42: RL1 | AC42: 45922
B43: 45923 | C43: =IF(B43="","",NETWORKDAYS.INTL(B43,TODAY(),1,'HELPER(Dont Delete)'!A:A)) -> 64 | D43: =IF(J43="Open", IF(AND(C43>=0, C43<=30), "0-30", IF(AND(C43>=31, C43<=45), "31-45", IF(AND(C43>=46, C43<=60), "46-60", IF(AND(C43>=61, C43<=75), "61-75", IF(AND(C43>=76, C43<=90), "76-90", IF(AND(C43>=91, C43<=105), "91-105", IF(AND(C43>=106, C43<=120), "106-120", IF(C43>120, "120+", "")))))))),"") -> 61-75 | E43: Exe/AM HR | F43: 1 | G43: No | H43: Ujjwal | I43: Ujjwal | J43: Open | K43: Executive/AM | L43: 7+ Years | M43: 7.6 LPA | N43: 12 LPA | O43: 0.1 | P43: MBA/PGDM | Q43: Mumbai | S43: =B43 -> 45923 | U43: =COUNTIFS('Candidate Tracker'!D:D,'Position Tracker'!E43,'Candidate Tracker'!V:V, "<>Screening Pending") -> 9 | V43: =COUNTIFS('Candidate Tracker'!D:D,'Position Tracker'!E43,'Candidate Tracker'!V:V, "Screen Reject") -> 4 | W43: =U43-V43 -> 5 | X43: =IFERROR(IF(U43=0,0,IF(V43=0,"100%",W43/U43)),"") -> 0.55555556 | Y43: RL1
B44: 45940 | C44: =IF(B44="","",NETWORKDAYS.INTL(B44,TODAY(),1,'HELPER(Dont Delete)'!A:A)) -> 51 | D44: =IF(J44="Open", IF(AND(C44>=0, C44<=30), "0-30", IF(AND(C44>=31, C44<=45), "31-45", IF(AND(C44>=46, C44<=60), "46-60", IF(AND(C44>=61, C44<=75), "61-75", IF(AND(C44>=76, C44<=90), "76-90", IF(AND(C44>=91, C44<=105), "91-105", IF(AND(C44>=106, C44<=120), "106-120", IF(C44>120, "120+", "")))))))),"") -> 46-60 | E44: Costing Head | F44: 1 | J44: Open | R44: 3126 | Y44: RL2
B45: 45940 | C45: =IF(B45="","",NETWORKDAYS.INTL(B45,TODAY(),1,'HELPER(Dont Delete)'!A:A)) -> 51 | D45: =IF(J45="Open", IF(AND(C45>=0, C45<=30), "0-30", IF(AND(C45>=31, C45<=45), "31-45", IF(AND(C45>=46, C45<=60), "46-60", IF(AND(C45>=61, C45<=75), "61-75", IF(AND(C45>=76, C45<=90), "76-90", IF(AND(C45>=91, C45<=105), "91-105", IF(AND(C45>=106, C45<=120), "106-120", IF(C45>120, "120+", "")))))))),"") -> 46-60 | E45: Production Head | F45: 1 | J45: Open | R45: 3125 | Y45: RL2

Sheet Candidate Tracker
A1: 1 | B1: 45219 | C1: 45219 | D1: KAM | E1: Steelway | F1: Ujjwal Singh | G1: Parsi Sainaresh Gupta | H1: 7004306497 | I1: parsisainaresh700@gmail.com | J1: Key Account Manager | K1: 5 | L1: 3 | M1: Mjunction Services limited | N1: LWD: 7/12/2023 | O1: 8.5 | P1: As per market | Q1: B.Tech | R1: Pune | T1: Steel Industries Exp | U1: Preeti Koli | V1: L1 Reject | X1: 45295 | Y1: 45296 | Z1: Reject | AP1: =IF(OR(X1="",C1=""),"",NETWORKDAYS.INTL(C1,X1,1,'HELPER(Dont Delete)'!A:A)) -> 51 | AQ1: =IF(OR(X1="",Y1=""),"",NETWORKDAYS.INTL(X1,Y1,1,'HELPER(Dont Delete)'!A:A)) -> 2 | AR1: =IF(OR(Y1="",AA1=""),"",NETWORKDAYS.INTL(Y1,AA1,1,'HELPER(Dont Delete)'!A:A))
A2: 2 | B2: 45219 | C2: 45229 | D2: KAM | E2: Steelway | F2: Ujjwal Singh | G2: Kumaran S | H2: 9600624431 | I2: skumaran106@gmail.com | K2: 8 | L2: 8 | M2: Saint-Gobain India Private Limited | N2: Immediate | O2: 10.85 | P2: 12.5 | Q2: B.E Mechanical | R2: Chennai | U2: Prakash Mishra | V2: Candidate Backout | X2: 45295 | AP2: =IF(OR(X2="",C2=""),"",NETWORKDAYS.INTL(C2,X2,1,'HELPER(Dont Delete)'!A:A)) -> 46 | AQ2: =IF(OR(X2="",Y2=""),"",NETWORKDAYS.INTL(X2,Y2,1,'HELPER(Dont Delete)'!A:A)) | AR2: =IF(OR(Y2="",AA2=""),"",NETWORKDAYS.INTL(Y2,AA2,1,'HELPER(Dont Delete)'!A:A))
A3: 3 | B3: 45219 | C3: 45229 | D3: KAM | E3: Steelway | F3: Ujjwal Singh | G3: Abhijot Mittal | H3: 9501614374 | I3: abhijotmittal@gmail.com | K3: 5 | L3: 5 | M3: Steel Strips Wheels Limited | N3: 60 | O3: 15 | P3: 25% Hike | Q3: B.Tech | R3: Pune | U3: Prakash Mishra | V3: Candidate Backout | X3: 45295 | AP3: =IF(OR(X3="",C3=""),"",NETWORKDAYS.INTL(C3,X3,1,'HELPER(Dont Delete)'!A:A)) -> 46 | AQ3: =IF(OR(X3="",Y3=""),"",NETWORKDAYS.INTL(X3,Y3,1,'HELPER(Dont Delete)'!A:A)) | AR3: =IF(OR(Y3="",AA3=""),"",NETWORKDAYS.INTL(Y3,AA3,1,'HELPER(Dont Delete)'!A:A))
A4: 4 | B4: 45219 | C4: 45236 | D4: KAM | E4: Steelway | F4: Ujjwal Singh | G4: Kabilan Ramdoss | H4: 9600097730 | I4: kapilan15@gmail.com | J4: KAM | K4: 6 | L4: 5 | M4: Baliga Lighting Equipments | N4: 60 | O4: 6.5 | P4: 8 | Q4: B.E.(Mechanical) | R4: Chennai | T4: Product sales, Key account management, handling Export and domestic sales | U4: Trupti Harichandan | V4: L1 Reject | X4: 45295 | Y4: 45296 | Z4: Reject | AP4: =IF(OR(X4="",C4=""),"",NETWORKDAYS.INTL(C4,X4,1,'HELPER(Dont Delete)'!A:A)) -> 41 | AQ4: =IF(OR(X4="",Y4=""),"",NETWORKDAYS.INTL(X4,Y4,1,'HELPER(Dont Delete)'!A:A)) -> 2 | AR4: =IF(OR(Y4="",AA4=""),"",NETWORKDAYS.INTL(Y4,AA4,1,'HELPER(Dont Delete)'!A:A))
A5: 5 | B5: 45275 | C5: 45276 | D5: Logistics - Manager/Sr Manager | E5: Steelway | F5: Ujjwal Singh | G5: ARYAN BHARDWAJ | H5: 9711477470 | I5: aryan.sharma230@gmail.com | J5: 9 yrs exp in logistic | K5: 9 | L5: 9 | M5: TATA Steel | N5: 90 | O5: 14 | P5: 20 | Q5: B.Tech +Mba | R5: New delhi | U5: Preeti Koli | V5: L1 Reject | X5: 45294 | Y5: 45307 | Z5: Reject | AP5: =IF(OR(X5="",C5=""),"",NETWORKDAYS.INTL(C5,X5,1,'HELPER(Dont Delete)'!A:A)) -> 11 | AQ5: =IF(OR(X5="",Y5=""),"",NETWORKDAYS.INTL(X5,Y5,1,'HELPER(Dont Delete)'!A:A)) -> 9 | AR5: =IF(OR(Y5="",AA5=""),"",NETWORKDAYS.INTL(Y5,AA5,1,'HELPER(Dont Delete)'!A:A))
A6: 6 | B6: 45275 | C6: 45276 | D6: Logistics - Manager/Sr Manager | E6: Steelway | F6: Ujjwal Singh | G6: PURUSOTTAM BEHERA | H6: 8126580486 | I6: purushottam.behera1986@gmail.com | J6: 15 yrs exp in logistic | K6: 15 | L6: 15 | M6: Tata Steel Downstream Products Ltd | N6: LWD: 14-Feb-23 | O6: 9.5 | P6: 25% Hike | Q6: B.Tech | R6: A.P-Tada | U6: Preeti Koli | V6: L1 Reject | X6: 45294 | Y6: 45295 | Z6: Reject | AP6: =IF(OR(X6="",C6=""),"",NETWORKDAYS.INTL(C6,X6,1,'HELPER(Dont Delete)'!A:A)) -> 11 | AQ6: =IF(OR(X6="",Y6=""),"",NETWORKDAYS.INTL(X6,Y6,1,'HELPER(Dont Delete)'!A:A)) -> 2 | AR6: =IF(OR(Y6="",AA6=""),"",NETWORKDAYS.INTL(Y6,AA6,1,'HELPER(Dont Delete)'!A:A))
A7: 7 | B7: 45275 | C7: 45276 | D7: Logistics - Manager/Sr Manager | E7: Steelway | F7: Ujjwal Singh | G7: Amit Chaudhari | H7: 9891020260 | I7: amitaustown@gmail.com | J7: 11 yrs in Lugistic, Supply chain | K7: 11 | L7: 11 | M7: Nippon Express India Pvt. Ltd. | N7: 60 | O7: 11 | P7: 25% Hike | Q7: B.Com + MBA | R7: Gurgaon | U7: Preeti Koli | V7: L1 Reject | X7: 45294 | Y7: 45307 | Z7: Reject | AP7: =IF(OR(X7="",C7=""),"",NETWORKDAYS.INTL(C7,X7,1,'HELPER(Dont Delete)'!A:A)) -> 11 | AQ7: =IF(OR(X7="",Y7=""),"",NETWORKDAYS.INTL(X7,Y7,1,'HELPER(Dont Delete)'!A:A)) -> 9 | AR7: =IF(OR(Y7="",AA7=""),"",NETWORKDAYS.INTL(Y7,AA7,1,'HELPER(Dont Delete)'!A:A))
A8: 8 | B8: 45189 | C8: 45276 | D8: Fabrication | E8: Steelway | F8: Ujjwal Singh | G8: Niteen kumar Belkoniker | H8: 9036897409 | I8: niteen.b17@gmail.com | K8: 18 | L8: 18 | M8: Tata Projects | N8: 60 | O8: 17.5 | P8: 30% Hike | Q8: B.tech | R8: Mumbai | U8: Ajay Singh | V8: L1 Reject | X8: 45405 | Y8: 45406 | Z8: Reject | AP8: =IF(OR(X8="",C8=""),"",NETWORKDAYS.INTL(C8,X8,1,'HELPER(Dont Delete)'!A:A)) -> 76 | AQ8: =IF(OR(X8="",Y8=""),"",NETWORKDAYS.INTL(X8,Y8,1,'HELPER(Dont Delete)'!A:A)) -> 2 | AR8: =IF(OR(Y8="",AA8=""),"",NETWORKDAYS.INTL(Y8,AA8,1,'HELPER(Dont Delete)'!A:A))
A9: 9 | B9: 45219 | C9: 45301 | D9: KAM | E9: Steelway | F9: Ujjwal Singh | G9: Karthikeyan Dhanpal | H9: 7306467140 | I9: dhanpalkarthikeyan@gmail.com | J9: 8 yrs exp in sales, industry- metal | K9: 10 | L9: 8 | M9: Samrat Irons | N9: 30 | O9: 7 | P9: 30% Hike | Q9: B.Sc | R9: Telengana | U9: Preeti Koli | V9: Position on Hold | AP9: =IF(OR(X9="",C9=""),"",NETWORKDAYS.INTL(C9,X9,1,'HELPER(Dont Delete)'!A:A)) | AQ9: =IF(OR(X9="",Y9=""),"",NETWORKDAYS.INTL(X9,Y9,1,'HELPER(Dont Delete)'!A:A)) | AR9: =IF(OR(Y9="",AA9=""),"",NETWORKDAYS.INTL(Y9,AA9,1,'HELPER(Dont Delete)'!A:A))
A10: 10 | B10: 45219 | C10: 45301 | D10: KAM | E10: Steelway | F10: Ujjwal Singh | G10: Praveen Arokiaraj | H10: 9600696769 | I10: praveenarokiaraj1610@gmail.com | J10: 8 yrs exp in sales, 6 yrs in steel industry | K10: 8 | L10: 8 | M10: Tata BlueScope Steel Private Ltd | N10: 45 | O10: 8.5 | P10: 30% Hike | Negotiable | Q10: B.Tech | R10: Chennai | U10: Preeti Koli | V10: Position on Hold | AP10: =IF(OR(X10="",C10=""),"",NETWORKDAYS.INTL(C10,X10,1,'HELPER(Dont Delete)'!A:A)) | AQ10: =IF(OR(X10="",Y10=""),"",NETWORKDAYS.INTL(X10,Y10,1,'HELPER(Dont Delete)'!A:A)) | AR10: =IF(OR(Y10="",AA10=""),"",NETWORKDAYS.INTL(Y10,AA10,1,'HELPER(Dont Delete)'!A:A))
A11: 11 | B11: 45275 | C11: 45310 | D11: Logistics - Manager/Sr Manager | E11: Steelway | F11: Ujjwal Singh | G11: Chandra Shekhar Vishwakarma | H11: 9968231511 | I11: chandrashekharvishwakarma@yahoo.co.in | J11: 14 yrs exp in Logistic, inventory management, transportation, | K11: 14 | L11: 14 | M11: Derwiser India | N11: 30 | O11: 11.7 | P11: 25% Hike | Q11: B.Sc + MBA | R11: Noida | U11: Preeti Koli | V11: Screen Reject | X11: 45316 | AP11: =IF(OR(X11="",C11=""),"",NETWORKDAYS.INTL(C11,X11,1,'HELPER(Dont Delete)'!A:A)) -> 4 | AQ11: =IF(OR(X11="",Y11=""),"",NETWORKDAYS.INTL(X11,Y11,1,'HELPER(Dont Delete)'!A:A)) | AR11: =IF(OR(Y11="",AA11=""),"",NETWORKDAYS.INTL(Y11,AA11,1,'HELPER(Dont Delete)'!A:A))
A12: 12 | B12: 45275 | C12: 45310 | D12: Logistics - Manager/Sr Manager | E12: Steelway | F12: Ujjwal Singh | G12: Gaurav Gupta | H12: 8427060151 | I12: gaurav.guptascm@gmail.com | J12: 15 Yrs exp in logistic, inventory management,transportion, shipments | K12: 15 | L12: 15 | M12: Stylam Industries | N12: 60 | O12: 15 | P12: 18 | Q12: B.Sc + MBA | R12: Chandigarh | U12: Preeti Koli | V12: L1 Reject | X12: 45316 | AP12: =IF(OR(X12="",C12=""),"",NETWORKDAYS.INTL(C12,X12,1,'HELPER(Dont Delete)'!A:A)) -> 4 | AQ12: =IF(OR(X12="",Y12=""),"",NETWORKDAYS.INTL(X12,Y12,1,'HELPER(Dont Delete)'!A:A)) | AR12: =IF(OR(Y12="",AA12=""),"",NETWORKDAYS.INTL(Y12,AA12,1,'HELPER(Dont Delete)'!A:A))
A13: 13 | B13: 45324 | C13: 45327 | D13: KAM (Gurgaon) | E13: Steelway | F13: Ujjwal Singh | G13: Keshav Kaushik | H13: 9999254190 | K13: 8 | L13: 5 | M13: Nippon Steel Pipe India | N13: 60 | Q13: B.Tech | R13: Faridabad | U13: Preeti Koli | V13: Candidate Backout | X13: 45330 | Z13: 45342 | AP13: =IF(OR(X13="",C13=""),"",NETWORKDAYS.INTL(C13,X13,1,'HELPER(Dont Delete)'!A:A)) -> 4 | AQ13: =IF(OR(X13="",Y13=""),"",NETWORKDAYS.INTL(X13,Y13,1,'HELPER(Dont Delete)'!A:A)) | AR13: =IF(OR(Y13="",AA13=""),"",NETWORKDAYS.INTL(Y13,AA13,1,'HELPER(Dont Delete)'!A:A))
A14: 14 | B14: 45324 | C14: 45327 | D14: KAM (Gurgaon) | E14: Steelway | F14: Ujjwal Singh | G14: Prashant Sharma | H14: 8741855547 | I14: prashantjims@gmail.co | K14: 12 | L14: 8.5 | M14: Nippon Steel Pipes | N14: 30 | Q14: M.Sc+ PGDM | R14: Gurgaon | U14: Preeti Koli | V14: Candidate Backout | X14: 45330 | Z14: 45342 | AP14: =IF(OR(X14="",C14=""),"",NETWORKDAYS.INTL(C14,X14,1,'HELPER(Dont Delete)'!A:A)) -> 4 | AQ14: =IF(OR(X14="",Y14=""),"",NETWORKDAYS.INTL(X14,Y14,1,'HELPER(Dont Delete)'!A:A)) | AR14: =IF(OR(Y14="",AA14=""),"",NETWORKDAYS.INTL(Y14,AA14,1,'HELPER(Dont Delete)'!A:A))
A15: 15 | B15: 45324 | C15: 45327 | D15: KAM (Gurgaon) | E15: Steelway | F15: Ujjwal Singh | G15: Bhawana | H15: 8742967460 | I15: sbhawna376@gmail.com | K15: 7 | L15: 5 | M15: Maharashtra Seamless Limited | N15: 60 | Q15: B.tech + MBA | R15: Gurgaon | U15: Preeti Koli | V15: Candidate Backout | X15: 45330 | AP15: =IF(OR(X15="",C15=""),"",NETWORKDAYS.INTL(C15,X15,1,'HELPER(Dont Delete)'!A:A)) -> 4 | AQ15: =IF(OR(X15="",Y15=""),"",NETWORKDAYS.INTL(X15,Y15,1,'HELPER(Dont Delete)'!A:A)) | AR15: =IF(OR(Y15="",AA15=""),"",NETWORKDAYS.INTL(Y15,AA15,1,'HELPER(Dont Delete)'!A:A))
A16: 16 | B16: 45324 | C16: 45337 | D16: KAM (Gurgaon) | E16: Steelway | F16: Ujjwal Singh | G16: Pravesh Kumar Sahu | H16: 7060796556 | I16: praveshsahu269@gmail.com | K16: 4.5 | L16: 4.5 | M16: Ambica Steels | N16: 30 Days | O16: 4.3 LPA | P16: 6 .5 LPA | Q16: B.Tech Mechanical | R16: New Delhi | U16: Prakash Mishra | V16: Candidate Backout | X16: 45343 | Z16: 45344 | AP16: =IF(OR(X16="",C16=""),"",NETWORKDAYS.INTL(C16,X16,1,'HELPER(Dont Delete)'!A:A)) -> 4 | AQ16: =IF(OR(X16="",Y16=""),"",NETWORKDAYS.INTL(X16,Y16,1,'HELPER(Dont Delete)'!A:A)) | AR16: =IF(OR(Y16="",AA16=""),"",NETWORKDAYS.INTL(Y16,AA16,1,'HELPER(Dont Delete)'!A:A))
A17: 17 | B17: 45324 | C17: 45337 | D17: KAM (Gurgaon) | E17: Steelway | F17: Ujjwal Singh | G17: Rahul Khurana | H17: 9871631046 | I17: rahulrkkhurana001@gmail.com | K17: 8.5 | L17: 8.5 | M17: Ambica Steels | N17: 60 Days | O17: 16 LPA | P17: 22 LPA | Q17: B.Tech (Mechanical & Automation) | R17: New Delhi | U17: Prakash Mishra | V17: L1 Reject | X17: 45343 | Z17: 45344 | AP17: =IF(OR(X17="",C17=""),"",NETWORKDAYS.INTL(C17,X17,1,'HELPER(Dont Delete)'!A:A)) -> 4 | AQ17: =IF(OR(X17="",Y17=""),"",NETWORKDAYS.INTL(X17,Y17,1,'HELPER(Dont Delete)'!A:A)) | AR17: =IF(OR(Y17="",AA17=""),"",NETWORKDAYS.INTL(Y17,AA17,1,'HELPER(Dont Delete)'!A:A))
A18: 18 | B18: 45324 | C18: 45351 | D18: KAM (Gurgaon) | E18: Steelway | F18: Ujjwal Singh | G18: Mohit Tyagi | H18: 8800334384 | I18: mohitmtl.tyagi@gmail.com | J18: KAM- BD- Pipes | K18: 12 | L18: 12.00 Years | M18: Apl Apollo Pipes | N18: 30 | O18: 7 | P18: 25% hike on fixed | Q18: MBA | R18: Ghaziabad | U18: Nikitha Agarwal | V18: Duplicate | X18: 45352 | AP18: =IF(OR(X18="",C18=""),"",NETWORKDAYS.INTL(C18,X18,1,'HELPER(Dont Delete)'!A:A)) -> 2 | AQ18: =IF(OR(X18="",Y18=""),"",NETWORKDAYS.INTL(X18,Y18,1,'HELPER(Dont Delete)'!A:A)) | AR18: =IF(OR(Y18="",AA18=""),"",NETWORKDAYS.INTL(Y18,AA18,1,'HELPER(Dont Delete)'!A:A))
A19: 19 | B19: 45324 | C19: 45351 | D19: KAM (Kolkata) | E19: Steelway | F19: Ujjwal Singh | G19: Kushgra Wardhan | H19: 8210445564 | I19: kushagra.wardhan94@gmail.com | J19: KAM- BD- Pipes | K19: 30 | L19: 2.10 Years | M19: Shyam Steel manufacture | N19: 60 | O19: 7 | P19: 30% hike on 6.47 LPA | Q19: PGDM- full time | R19: Kolkata | U19: Nikitha Agarwal | V19: Final Select | W19: Joined | X19: 45352 | Y19: 45355 | Z19: Select | AG19: 45369 | AP19: =IF(OR(X19="",C19=""),"",NETWORKDAYS.INTL(C19,X19,1,'HELPER(Dont Delete)'!A:A)) -> 2 | AQ19: =IF(OR(X19="",Y19=""),"",NETWORKDAYS.INTL(X19,Y19,1,'HELPER(Dont Delete)'!A:A)) -> 2 | AR19: =IF(OR(Y19="",AA19=""),"",NETWORKDAYS.INTL(Y19,AA19,1,'HELPER(Dont Delete)'!A:A))
A20: 20 | B20: 45324 | C20: 45351 | D20: KAM (Gurgaon) | E20: Steelway | F20: Ujjwal Singh | G20: Siddarth Birla | H20: 8373994823 | I20: siddharth.birla1@gmail.com | J20: KAM- BD- Pipes | K20: 5.00 Years | L20: 2.00 Years | M20: DBS Building Products | N20: 30 | O20: 10.2 | P20: 25% on hike fixed | Q20: Btech, PDGM - full time | R20: Ghaziabad | U20: Nikitha Agarwal | V20: Candidate Backout | X20: 45352 | AP20: =IF(OR(X20="",C20=""),"",NETWORKDAYS.INTL(C20,X20,1,'HELPER(Dont Delete)'!A:A)) -> 2 | AQ20: =IF(OR(X20="",Y20=""),"",NETWORKDAYS.INTL(X20,Y20,1,'HELPER(Dont Delete)'!A:A)) | AR20: =IF(OR(Y20="",AA20=""),"",NETWORKDAYS.INTL(Y20,AA20,1,'HELPER(Dont Delete)'!A:A))
A21: 21 | B21: 45275 | C21: 45352 | D21: Logistics - Manager/Sr Manager | E21: Steelway | F21: Ujjwal Singh | G21: Tinu Anand | H21: 8908416288 | I21: tinuanand29@gmail.com | J21: logistics, transportation management, | K21: 11 | L21: 9 | M21: Adani Logistics Ltd,Multi-modal logistics parks | N21: 60 | O21: 14.5 | P21: 30% hike | Q21: MBA | R21: Gurgaon | U21: Shilpa H | V21: L1 Reject | X21: 45357 | Y21: 45357 | Z21: Reject | AP21: =IF(OR(X21="",C21=""),"",NETWORKDAYS.INTL(C21,X21,1,'HELPER(Dont Delete)'!A:A)) -> 3 | AQ21: =IF(OR(X21="",Y21=""),"",NETWORKDAYS.INTL(X21,Y21,1,'HELPER(Dont Delete)'!A:A)) -> 0 | AR21: =IF(OR(Y21="",AA21=""),"",NETWORKDAYS.INTL(Y21,AA21,1,'HELPER(Dont Delete)'!A:A))
A22: 22 | B22: 45275 | C22: 45352 | D22: Logistics - Manager/Sr Manager | E22: Steelway | F22: Ujjwal Singh | G22: Sudhanshu Tripathi | H22: 7218435695, 9834595866 | I22: tripathi5690@gmail.com | K22: 10 | L22: 8.5 | M22: Reliance retail Limited | N22: 60 | O22: 12 | P22: 25% hike | Q22: B.Com + MBA | R22: Jajjar | U22: Preeti Koli | V22: Screen Reject | X22: 45357 | AP22: =IF(OR(X22="",C22=""),"",NETWORKDAYS.INTL(C22,X22,1,'HELPER(Dont Delete)'!A:A)) -> 3 | AQ22: =IF(OR(X22="",Y22=""),"",NETWORKDAYS.INTL(X22,Y22,1,'HELPER(Dont Delete)'!A:A)) | AR22: =IF(OR(Y22="",AA22=""),"",NETWORKDAYS.INTL(Y22,AA22,1,'HELPER(Dont Delete)'!A:A))
A23: 23 | B23: 45327 | C23: 45355 | D23: KAM (Gurgaon) | E23: Steelway | F23: Ujjwal Singh | G23: Amit Gupta | H23: 7042904888 | I23: amit85ei@gmail.com | J23: Sales, BD, KAM, Customer Acquisition, Customer Retention, B2B, Market Mapping | K23: 14+ | L23: 14+ | M23: Surya Roshni | N23: 30 | O23: 15 LPA | P23: 25-30% hike | Q23: BE + MBA | R23: Delhi | T23: 14 + yrs of exp in sales and marketing | U23: Vinay Kumar | V23: L1 Reject | X23: 45359 | Y23: 45362 | Z23: Reject | AP23: =IF(OR(X23="",C23=""),"",NETWORKDAYS.INTL(C23,X23,1,'HELPER(Dont Delete)'!A:A)) -> 3 | AQ23: =IF(OR(X23="",Y23=""),"",NETWORKDAYS.INTL(X23,Y23,1,'HELPER(Dont Delete)'!A:A)) -> 1 | AR23: =IF(OR(Y23="",AA23=""),"",NETWORKDAYS.INTL(Y23,AA23,1,'HELPER(Dont Delete)'!A:A))
A24: 24 | B24: 45327 | C24: 45355 | D24: KAM (Gurgaon) | E24: Steelway | F24: Ujjwal Singh | G24: Gaurav Singh | H24: 9713478007 | I24: grvsingh2009@gmail.com | J24: Sales, BD, KAM, Customer Acquisition, Customer Retention, B2B, Market Mapping | K24: 8.9 | L24: 8.9 | M24: APL Apollo Tubes | N24: 30 | O24: 5 LPA | P24: 7 to 8 LPA | Q24: BE + MBA | R24: Indore | T24: 8.9 yrs of exp in sales and marketing | U24: Vinay Kumar | V24: L1 Reject | X24: 45359 | Y24: 45366 | Z24: Reject | AP24: =IF(OR(X24="",C24=""),"",NETWORKDAYS.INTL(C24,X24,1,'HELPER(Dont Delete)'!A:A)) -> 3 | AQ24: =IF(OR(X24="",Y24=""),"",NETWORKDAYS.INTL(X24,Y24,1,'HELPER(Dont Delete)'!A:A)) -> 5 | AR24: =IF(OR(Y24="",AA24=""),"",NETWORKDAYS.INTL(Y24,AA24,1,'HELPER(Dont Delete)'!A:A))
A25: 25 | B25: 45327 | C25: 45355 | D25: KAM (Gurgaon) | E25: Steelway | F25: Ujjwal Singh | G25: Ajay Kumar Singh | H25: 9056272236 | I25: ajay20580@gmail.com | J25: Sales, BD, KAM, Customer Acquisition, Customer Retention, B2B, Market Mapping | K25: 14 | L25: 14 | M25: APL Apollo Tubes | N25: 30 | O25: 8.9 LPA | P25: 12 LPA | Q25: MBA | R25: Bhubaneshwar | T25: 14 yrs of exp in sales and marketing | U25: Vinay Kumar | V25: L1 Reject | X25: 45359 | Y25: 45366 | Z25: Reject | AP25: =IF(OR(X25="",C25=""),"",NETWORKDAYS.INTL(C25,X25,1,'HELPER(Dont Delete)'!A:A)) -> 3 | AQ25: =IF(OR(X25="",Y25=""),"",NETWORKDAYS.INTL(X25,Y25,1,'HELPER(Dont Delete)'!A:A)) -> 5 | AR25: =IF(OR(Y25="",AA25=""),"",NETWORKDAYS.INTL(Y25,AA25,1,'HELPER(Dont Delete)'!A:A))
A26: 26 | B26: 45327 | C26: 45355 | D26: KAM (Gurgaon) | E26: Steelway | F26: Ujjwal Singh | G26: Deepanshu Katiyar | H26: 7982783407 | I26: dkatiyarmae@gmail.com | J26: Sales, BD, KAM, Customer Acquisition, Customer Retention, B2B, Market Mapping | K26: 11 | L26: 11 | M26: Uttam Strips | N26: 30 | O26: 9.7 LPA | P26: 25-30% hike | Q26: B Tech+ MBA | R26: Faridabad | T26: 11 yrs of exp in sales and marketing | U26: Vinay Kumar | V26: L1 Reject | X26: 45359 | Y26: 45366 | Z26: Reject | AP26: =IF(OR(X26="",C26=""),"",NETWORKDAYS.INTL(C26,X26,1,'HELPER(Dont Delete)'!A:A)) -> 3 | AQ26: =IF(OR(X26="",Y26=""),"",NETWORKDAYS.INTL(X26,Y26,1,'HELPER(Dont Delete)'!A:A)) -> 5 | AR26: =IF(OR(Y26="",AA26=""),"",NETWORKDAYS.INTL(Y26,AA26,1,'HELPER(Dont Delete)'!A:A))
A27: 27 | B27: 45327 | C27: 45355 | D27: KAM (Kolkata) | E27: Steelway | F27: Ujjwal Singh | G27: Kuldeep Jain | H27: 9981145050 | I27: kuldeep_jain01@yahoo.co.in | J27: Sales, BD, KAM, Customer Acquisition, Customer Retention, B2B, Market Mapping | K27: 14 | L27: 14 | M27: APL Apollo Tubes | N27: 45 | O27: 8.5 LPA | P27: 25-30% hike | Q27: MBA | R27: Jabalpur | T27: 14 yrs of exp in sales and marketing | U27: Vinay Kumar | V27: Final Select | W27: Joined | X27: 45359 | Y27: 45362 | Z27: Select | AP27: =IF(OR(X27="",C27=""),"",NETWORKDAYS.INTL(C27,X27,1,'HELPER(Dont Delete)'!A:A)) -> 3 | AQ27: =IF(OR(X27="",Y27=""),"",NETWORKDAYS.INTL(X27,Y27,1,'HELPER(Dont Delete)'!A:A)) -> 1 | AR27: =IF(OR(Y27="",AA27=""),"",NETWORKDAYS.INTL(Y27,AA27,1,'HELPER(Dont Delete)'!A:A))
A28: 28 | B28: 45327 | C28: 45355 | D28: KAM (Kolkata) | E28: Steelway | F28: Ujjwal Singh | G28: Shakti Kundu | H28: 9811169004 | I28: shaktikundu466@gmail.com | J28: - | K28: 10 | L28: 8 | M28: Mukand Sumi Special Steel Ltd | N28: 90 | O28: 10 LPA | P28: 16 LPA | Q28: B.Tech/B.E.,Mechanical | R28: Gurgaon | T28: - | U28: Rutali | V28: Candidate Backout | X28: 45359 | AP28: =IF(OR(X28="",C28=""),"",NETWORKDAYS.INTL(C28,X28,1,'HELPER(Dont Delete)'!A:A)) -> 3 | AQ28: =IF(OR(X28="",Y28=""),"",NETWORKDAYS.INTL(X28,Y28,1,'HELPER(Dont Delete)'!A:A)) | AR28: =IF(OR(Y28="",AA28=""),"",NETWORKDAYS.INTL(Y28,AA28,1,'HELPER(Dont Delete)'!A:A))
A29: 29 | B29: 45327 | C29: 45364 | D29: KAM (Kolkata) | E29: Steelway | F29: Ujjwal Singh | G29: Mankeshwar Kumar Mishra | H29: 7236006626 | I29: mishramk372@gmail.com | J29: KAM, BD, Sales & Marketing, Tubes/Pipes/Long products | K29: 3 | L29: 3 | M29: APL Apollo Tubes | N29: 30 | O29: 3.6 LPA | P29: 25 to 30% hike | Q29: B Tech (ME) | R29: Gurugram | T29: 1 year of exp in sales and marketing | U29: Vinay Kumar | V29: L1 Reject | X29: 45365 | Y29: 45366 | Z29: Reject | AP29: =IF(OR(X29="",C29=""),"",NETWORKDAYS.INTL(C29,X29,1,'HELPER(Dont Delete)'!A:A)) -> 2 | AQ29: =IF(OR(X29="",Y29=""),"",NETWORKDAYS.INTL(X29,Y29,1,'HELPER(Dont Delete)'!A:A)) -> 2 | AR29: =IF(OR(Y29="",AA29=""),"",NETWORKDAYS.INTL(Y29,AA29,1,'HELPER(Dont Delete)'!A:A))
A30: 30 | B30: 45327 | C30: 45364 | D30: KAM (Kolkata) | E30: Steelway | F30: Ujjwal Singh | G30: Ravi Awasthi | H30: 7980188746 | I30: awasthiravi305@gmail.com | J30: KAM | K30: 2 | L30: 2 | M30: Shyam Steels | N30: 90 | O30: 40 K/month | P30: 55-60 K/month | Q30: B.Com | R30: Kolkata | U30: Trupti Harichandan | V30: L1 Reject | X30: 45365 | Y30: 45366 | Z30: Reject | AP30: =IF(OR(X30="",C30=""),"",NETWORKDAYS.INTL(C30,X30,1,'HELPER(Dont Delete)'!A:A)) -> 2 | AQ30: =IF(OR(X30="",Y30=""),"",NETWORKDAYS.INTL(X30,Y30,1,'HELPER(Dont Delete)'!A:A)) -> 2 | AR30: =IF(OR(Y30="",AA30=""),"",NETWORKDAYS.INTL(Y30,AA30,1,'HELPER(Dont Delete)'!A:A))
A31: 31 | B31: 45327 | C31: 45364 | D31: KAM (Kolkata) | E31: Steelway | F31: Ujjwal Singh | G31: Mayank Singh | H31: 6394952048, 8533041362 | I31: Mayanksingh4409@gmail.com | J31: KAM | K31: 4.7 | L31: 4.7 | M31: APL Apollo Tubes Limited | N31: 30 | O31: 45 K/month | P31: 0.3 | Q31: B.Tech | R31: Haryana | U31: Trupti Harichandan | V31: Candidate Backout | X31: 45365 | AP31: =IF(OR(X31="",C31=""),"",NETWORKDAYS.INTL(C31,X31,1,'HELPER(Dont Delete)'!A:A)) -> 2 | AQ31: =IF(OR(X31="",Y31=""),"",NETWORKDAYS.INTL(X31,Y31,1,'HELPER(Dont Delete)'!A:A)) | AR31: =IF(OR(Y31="",AA31=""),"",NETWORKDAYS.INTL(Y31,AA31,1,'HELPER(Dont Delete)'!A:A))
A32: 32 | B32: 45327 | C32: 45364 | D32: KAM (Kolkata) | E32: Steelway | F32: Ujjwal Singh | G32: Anup Kumar Vishwakarma | H32: 8423251160, 9453199247 | I32: akvishwakarma073@gmail.com | J32: KAM | K32: 5.8 | L32: 5.8 | M32: Shyam Steels | N32: 60 | O32: 7.82 LPA F+ variable | P32: 10 LPA, Can discuss | Q32: B.Tech | R32: Delhi | T32: handling Utakhand and UP | U32: Trupti Harichandan | V32: L1 Reject | X32: 45365 | Y32: 45365 | Z32: Reject | AP32: =IF(OR(X32="",C32=""),"",NETWORKDAYS.INTL(C32,X32,1,'HELPER(Dont Delete)'!A:A)) -> 2 | AQ32: =IF(OR(X32="",Y32=""),"",NETWORKDAYS.INTL(X32,Y32,1,'HELPER(Dont Delete)'!A:A)) -> 1 | AR32: =IF(OR(Y32="",AA32=""),"",NETWORKDAYS.INTL(Y32,AA32,1,'HELPER(Dont Delete)'!A:A))
A33: 33 | B33: 45327 | C33: 45364 | D33: KAM (Kolkata) | E33: Steelway | F33: Ujjwal Singh | G33: Hritik Shishodia | H33: 8810651176 | I33: hritikshishodia@gmail.com | J33: KAM | K33: 3.4 | L33: 3.4 | M33: Goodluck INDIA LTD | N33: 30 days | O33: 30 K/ Month | P33: 40 K/ Month | Q33: B.Tech | R33: Kerala | T33: Reason for job change-Job Security | U33: Trupti Harichandan | V33: L1 Reject | X33: 45365 | Y33: 45366 | Z33: Reject | AP33: =IF(OR(X33="",C33=""),"",NETWORKDAYS.INTL(C33,X33,1,'HELPER(Dont Delete)'!A:A)) -> 2 | AQ33: =IF(OR(X33="",Y33=""),"",NETWORKDAYS.INTL(X33,Y33,1,'HELPER(Dont Delete)'!A:A)) -> 2 | AR33: =IF(OR(Y33="",AA33=""),"",NETWORKDAYS.INTL(Y33,AA33,1,'HELPER(Dont Delete)'!A:A))
A34: 34 | B34: 45327 | C34: 45364 | D34: KAM (Kolkata) | E34: Steelway | F34: Ujjwal Singh | G34: Ashish Tiwari | H34: 7500974204 | I34: ashishtiwari8440@gmail.com | J34: KAM | K34: 6 | L34: 6 | M34: Surya Roshni Limited | N34: 30 days | O34: 34 K/ hand | P34: 0.3 | Q34: B.Sc | R34: Uttarakhand | U34: Trupti Harichandan | V34: Candidate Backout | X34: 45365 | AP34: =IF(OR(X34="",C34=""),"",NETWORKDAYS.INTL(C34,X34,1,'HELPER(Dont Delete)'!A:A)) -> 2 | AQ34: =IF(OR(X34="",Y34=""),"",NETWORKDAYS.INTL(X34,Y34,1,'HELPER(Dont Delete)'!A:A)) | AR34: =IF(OR(Y34="",AA34=""),"",NETWORKDAYS.INTL(Y34,AA34,1,'HELPER(Dont Delete)'!A:A))
A35: 35 | B35: 45327 | C35: 45364 | D35: KAM (Kolkata) | E35: Steelway | F35: Ujjwal Singh | G35: Sachin Kumar | H35: 8789182355, 7561907526 | I35: sachinkumararwal@gmail.com | J35: KAM | K35: 6.6 | L35: 6.6 | M35: Shyam Steel manufacturing ltd | N35: 30 days | O35: 4.5 LPA F | P35: 6 LPA | Q35: B.Tech | R35: Bihar | U35: Trupti Harichandan | V35: L1 Reject | X35: 45365 | Y35: 45366 | Z35: Reject | AP35: =IF(OR(X35="",C35=""),"",NETWORKDAYS.INTL(C35,X35,1,'HELPER(Dont Delete)'!A:A)) -> 2 | AQ35: =IF(OR(X35="",Y35=""),"",NETWORKDAYS.INTL(X35,Y35,1,'HELPER(Dont Delete)'!A:A)) -> 2 | AR35: =IF(OR(Y35="",AA35=""),"",NETWORKDAYS.INTL(Y35,AA35,1,'HELPER(Dont Delete)'!A:A))
A36: 36 | B36: 45275 | C36: 45364 | D36: KAM (Kolkata) | E36: Steelway | F36: Ujjwal Singh | G36: Somesh Gupta | H36: 9968883423 | I36: somugupta0494@gmail.com | J36: Logistics & transportation | K36: 6.00 Years | L36: 6.00 Years | M36: Ultratech Cement | N36: 90 | O36: 12.25 LPA Total , + 36k | P36: 30% Hike | Q36: Bcom, MBA - PGDM | R36: Noida | U36: Nikitha Agarwal | V36: L1 Reject | X36: 45364 | AP36: =IF(OR(X36="",C36=""),"",NETWORKDAYS.INTL(C36,X36,1,'HELPER(Dont Delete)'!A:A)) -> 1 | AQ36: =IF(OR(X36="",Y36=""),"",NETWORKDAYS.INTL(X36,Y36,1,'HELPER(Dont Delete)'!A:A)) | AR36: =IF(OR(Y36="",AA36=""),"",NETWORKDAYS.INTL(Y36,AA36,1,'HELPER(Dont Delete)'!A:A))
A37: 37 | B37: 45275 | C37: 45364 | D37: KAM (Kolkata) | E37: Steelway | F37: Ujjwal Singh | G37: Prabin Goswami | H37: 7827572093 | I37: prabingoswami@gmail.com | J37: Logistics & transportation | K37: 10.00 Years | L37: 10.00 Years | M37: Dalmia Cement | N37: 90 | O37: 15.50 LPA fixed | P37: 40% Hike | Q37: BE | R37: Guwahati | U37: Nikitha Agarwal | V37: Screen Reject | X37: 45364 | AP37: =IF(OR(X37="",C37=""),"",NETWORKDAYS.INTL(C37,X37,1,'HELPER(Dont Delete)'!A:A)) -> 1 | AQ37: =IF(OR(X37="",Y37=""),"",NETWORKDAYS.INTL(X37,Y37,1,'HELPER(Dont Delete)'!A:A)) | AR37: =IF(OR(Y37="",AA37=""),"",NETWORKDAYS.INTL(Y37,AA37,1,'HELPER(Dont Delete)'!A:A))
A38: 38 | B38: 45299 | C38: 45377 | D38: KAM (Kolkata) | E38: Steelway | F38: Ujjwal Singh | G38: Shaik Mohammed Haneef | H38: 9502394088 | I38: haneefmohammed011@gmail.com | J38: Domestic Logistics | K38: 10.9 | L38: 10.9 | M38: Ultratech Cement Ltd | N38: 90 days | O38: 10.6 LPA (13% variable included) | P38: 40%, negotiable upto 30% | Q38: B.Tech | R38: AP | U38: Trupti Harichandan | V38: Screen Reject | X38: 45386 | AP38: =IF(OR(X38="",C38=""),"",NETWORKDAYS.INTL(C38,X38,1,'HELPER(Dont Delete)'!A:A)) -> 7 | AQ38: =IF(OR(X38="",Y38=""),"",NETWORKDAYS.INTL(X38,Y38,1,'HELPER(Dont Delete)'!A:A)) | AR38: =IF(OR(Y38="",AA38=""),"",NETWORKDAYS.INTL(Y38,AA38,1,'HELPER(Dont Delete)'!A:A))
A39: 39 | B39: 45327 | C39: 45380 | D39: KAM (Kolkata) | E39: Steelway | F39: Ujjwal Singh | G39: Akshay Panchal | H39: 8128538003 | I39: akspanchal33@gmail.com | J39: sales and marketing, business development | K39: 5 | L39: 5 | M39: POSCO | N39: 30 | O39: 6 | P39: 7.5 to 8 LPA | Q39: B.Tech | R39: Ahmedabad | T39: 5 years of exp in sales and marketing | U39: Vinay Kumar | V39: Candidate Backout | X39: 45380 | AP39: =IF(OR(X39="",C39=""),"",NETWORKDAYS.INTL(C39,X39,1,'HELPER(Dont Delete)'!A:A)) -> 0 | AQ39: =IF(OR(X39="",Y39=""),"",NETWORKDAYS.INTL(X39,Y39,1,'HELPER(Dont Delete)'!A:A)) | AR39: =IF(OR(Y39="",AA39=""),"",NETWORKDAYS.INTL(Y39,AA39,1,'HELPER(Dont Delete)'!A:A))
A40: 40 | B40: 45327 | C40: 45380 | D40: KAM (Kolkata) | E40: Steelway | F40: Ujjwal Singh | G40: Vivek Singh | H40: 7991783481 | I40: vivekkumarsingh5223@gmail.com | J40: KAM- BD- Pipes | K40: 2 | L40: 2 | M40: Shyam steel | N40: 15 | O40: 4.38 | P40: 40k in hand | Q40: MBA | R40: Ghazipur | U40: Nikitha Agarwal | V40: L1 Reject | X40: 45380 | Y40: 45383 | Z40: Reject | AP40: =IF(OR(X40="",C40=""),"",NETWORKDAYS.INTL(C40,X40,1,'HELPER(Dont Delete)'!A:A)) -> 0 | AQ40: =IF(OR(X40="",Y40=""),"",NETWORKDAYS.INTL(X40,Y40,1,'HELPER(Dont Delete)'!A:A)) -> 1 | AR40: =IF(OR(Y40="",AA40=""),"",NETWORKDAYS.INTL(Y40,AA40,1,'HELPER(Dont Delete)'!A:A))
A41: 41 | B41: 45327 | C41: 45380 | D41: KAM (Kolkata) | E41: Steelway | F41: Ujjwal Singh | G41: Anuj Kumar | H41: 9919992234 | I41: anuj05262@gmail.com | J41: KAM- BD- Pipes | K41: 8 | L41: 8 | M41: APL Apollo pipes | N41: 30 | O41: 5.4 | P41: 50k in hand | Q41: MBA | R41: Dehradhun | U41: Nikitha Agarwal | V41: L1 Reject | X41: 45380 | Y41: 45383 | Z41: Reject | AP41: =IF(OR(X41="",C41=""),"",NETWORKDAYS.INTL(C41,X41,1,'HELPER(Dont Delete)'!A:A)) -> 0 | AQ41: =IF(OR(X41="",Y41=""),"",NETWORKDAYS.INTL(X41,Y41,1,'HELPER(Dont Delete)'!A:A)) -> 1 | AR41: =IF(OR(Y41="",AA41=""),"",NETWORKDAYS.INTL(Y41,AA41,1,'HELPER(Dont Delete)'!A:A))
A42: 42 | B42: 45299 | C42: 45383 | D42: KAM (Kolkata) | E42: Steelway | F42: Ujjwal Singh | G42: Rakesh Roy | H42: 9654808798 | I42: Royrakesh1993@gmail.com | J42: Domestics Logistics | K42: 8.8 | L42: 8.8 | M42: Adani Logistics Limited (ALL) | N42: 90 days | O42: 11.6 +1.4 | P42: 25-30% | Q42: MBA | R42: Gurgaon | T42: Product: Paints, Cement, multiple products | U42: Trupti Harichandan | V42: Final Select | W42: Y2J | X42: 45386 | Y42: 45394 | Z42: Select | AA42: 45408 | AB42: Select | AP42: =IF(OR(X42="",C42=""),"",NETWORKDAYS.INTL(C42,X42,1,'HELPER(Dont Delete)'!A:A)) -> 4 | AQ42: =IF(OR(X42="",Y42=""),"",NETWORKDAYS.INTL(X42,Y42,1,'HELPER(Dont Delete)'!A:A)) -> 4 | AR42: =IF(OR(Y42="",AA42=""),"",NETWORKDAYS.INTL(Y42,AA42,1,'HELPER(Dont Delete)'!A:A)) -> 10
A43: 43 | B43: 45299 | C43: 45383 | D43: KAM (Kolkata) | E43: Steelway | F43: Ujjwal Singh | G43: Devansh Khandelwal | H43: 9754820437 | I43: devansh12khandelwal@gmail.com | J43: Domestics Logistics | K43: 8.8 | L43: 8.8 | M43: Transport Corporation of India Pvt. Ltd. | N43: 60 | O43: 9.5 Fixed | P43: 30-35% | Q43: B.Tech | R43: Gurgaon | T43: 25 K/month bikes, 1500/month cars | U43: Trupti Harichandan | V43: L1 Reject | X43: 45386 | Y43: 45394 | Z43: Reject | AP43: =IF(OR(X43="",C43=""),"",NETWORKDAYS.INTL(C43,X43,1,'HELPER(Dont Delete)'!A:A)) -> 4 | AQ43: =IF(OR(X43="",Y43=""),"",NETWORKDAYS.INTL(X43,Y43,1,'HELPER(Dont Delete)'!A:A)) -> 4 | AR43: =IF(OR(Y43="",AA43=""),"",NETWORKDAYS.INTL(Y43,AA43,1,'HELPER(Dont Delete)'!A:A))
A44: 44 | B44: 45299 | C44: 45383 | D44: KAM (Kolkata) | E44: Steelway | F44: Ujjwal Singh | G44: Ravi Yelappa Golar | H44: 7069005477, 8369813245 | I44: rgolar92@gmail.com | J44: Domestics Logistics | K44: 8 | L44: 8 | M44: Reliance Industries Limited | N44: 90 | O44: 11.06 + 1.60 | P44: 0.3 | Q44: BE | R44: Rewari | T44: Product: Oil, Gas, Petrolium | U44: Trupti Harichandan | V44: Screen Reject | X44: 45386 | AP44: =IF(OR(X44="",C44=""),"",NETWORKDAYS.INTL(C44,X44,1,'HELPER(Dont Delete)'!A:A)) -> 4 | AQ44: =IF(OR(X44="",Y44=""),"",NETWORKDAYS.INTL(X44,Y44,1,'HELPER(Dont Delete)'!A:A)) | AR44: =IF(OR(Y44="",AA44=""),"",NETWORKDAYS.INTL(Y44,AA44,1,'HELPER(Dont Delete)'!A:A))
A45: 45 | B45: 45299 | C45: 45383 | D45: KAM (Kolkata) | E45: Steelway | F45: Ujjwal Singh | G45: Manish Kumar | H45: 7739776538 | I45: krmanish28@rediffmail.com | J45: Domestics Logistics | K45: 10 | L45: 10 | M45: ULTRATECH Cement Ltd | N45: 90 | O45: 9.40 LPA Fixed | P45: 0.4 | Q45: MBA | R45: Ratnagiri | U45: Trupti Harichandan | V45: Backup Profiles | X45: 45386 | Y45: 45394 | Z45: Select | AP45: =IF(OR(X45="",C45=""),"",NETWORKDAYS.INTL(C45,X45,1,'HELPER(Dont Delete)'!A:A)) -> 4 | AQ45: =IF(OR(X45="",Y45=""),"",NETWORKDAYS.INTL(X45,Y45,1,'HELPER(Dont Delete)'!A:A)) -> 4 | AR45: =IF(OR(Y45="",AA45=""),"",NETWORKDAYS.INTL(Y45,AA45,1,'HELPER(Dont Delete)'!A:A))
A46: 46 | B46: 45299 | C46: 45383 | D46: KAM (Kolkata) | E46: Steelway | F46: Ujjwal Singh | G46: Abhishek Kumar | H46: 9711105636 | I46: abhishekkmr12@gmail.com | J46: logistic operation, domestic transporation, truck, railway | K46: 10 | L46: 10 | M46: YAMAHA Motors Pvt Ltd | N46: 30 | O46: 16 LPA | P46: 19 LPA | Q46: MBA | R46: Noida | U46: Shilpa H | V46: L1 Reject | X46: 45386 | Y46: 45394 | Z46: Reject | AP46: =IF(OR(X46="",C46=""),"",NETWORKDAYS.INTL(C46,X46,1,'HELPER(Dont Delete)'!A:A)) -> 4 | AQ46: =IF(OR(X46="",Y46=""),"",NETWORKDAYS.INTL(X46,Y46,1,'HELPER(Dont Delete)'!A:A)) -> 4 | AR46: =IF(OR(Y46="",AA46=""),"",NETWORKDAYS.INTL(Y46,AA46,1,'HELPER(Dont Delete)'!A:A))
A47: 47 | B47: 45299 | C47: 45383 | D47: KAM (Kolkata) | E47: Steelway | F47: Ujjwal Singh | G47: Vishav Vibhu | H47: 9690272734 | I47: vishav58@gmail.com | J47: logistic operation, domestic transporation, truck, railway | K47: 10 | L47: 10 | M47: Honda Motorcycle & Scooters India Pvt Ltd | N47: 90 | O47: 16.20 LPA | P47: 30% hike | Q47: MBA | R47: Gurgaon | U47: Shilpa H | V47: Screen Reject | X47: 45386 | AP47: =IF(OR(X47="",C47=""),"",NETWORKDAYS.INTL(C47,X47,1,'HELPER(Dont Delete)'!A:A)) -> 4 | AQ47: =IF(OR(X47="",Y47=""),"",NETWORKDAYS.INTL(X47,Y47,1,'HELPER(Dont Delete)'!A:A)) | AR47: =IF(OR(Y47="",AA47=""),"",NETWORKDAYS.INTL(Y47,AA47,1,'HELPER(Dont Delete)'!A:A))
A48: 48 | B48: 45327 | C48: 45387 | D48: KAM (Kolkata) | E48: Steelway | F48: Ujjwal Singh | G48: Vimal Kumar | H48: 8802111955 | I48: vimalkkr25@gmail.com | J48: KAM | K48: 8.7 | L48: 3.3 | M48: Shyam Steel | N48: 90 days | O48: 6 LPA F+ Variable | P48: 25% hike | Q48: BA | R48: Delhi | T48: TMT Rebar | U48: Trupti Harichandan | V48: Screen Reject | X48: 45400 | AP48: =IF(OR(X48="",C48=""),"",NETWORKDAYS.INTL(C48,X48,1,'HELPER(Dont Delete)'!A:A)) -> 6 | AQ48: =IF(OR(X48="",Y48=""),"",NETWORKDAYS.INTL(X48,Y48,1,'HELPER(Dont Delete)'!A:A)) | AR48: =IF(OR(Y48="",AA48=""),"",NETWORKDAYS.INTL(Y48,AA48,1,'HELPER(Dont Delete)'!A:A))
A49: 49 | B49: 45327 | C49: 45387 | D49: KAM (Kolkata) | E49: Steelway | F49: Ujjwal Singh | G49: Punit Kumar | H49: 9801560800 | I49: punitsngh98@gmail.com | J49: KAM | K49: 8.6 | L49: 8.6 | M49: Shyaam Steel | N49: 30 days | O49: 6.5 LPA F+Variable | P49: 8.5 LPA (offer- Bihar-8.5 LPA) | Q49: MBA | R49: Noida | T49: TMT Rebar | U49: Trupti Harichandan | V49: Screen Reject | X49: 45400 | AP49: =IF(OR(X49="",C49=""),"",NETWORKDAYS.INTL(C49,X49,1,'HELPER(Dont Delete)'!A:A)) -> 6 | AQ49: =IF(OR(X49="",Y49=""),"",NETWORKDAYS.INTL(X49,Y49,1,'HELPER(Dont Delete)'!A:A)) | AR49: =IF(OR(Y49="",AA49=""),"",NETWORKDAYS.INTL(Y49,AA49,1,'HELPER(Dont Delete)'!A:A))
A50: 50 | B50: 45327 | C50: 45387 | D50: KAM (Kolkata) | E50: Steelway | F50: Ujjwal Singh | G50: Parth Patel | H50: 9727043207) | I50: parth18993@gmail.com | J50: BD, SALES, Steel | K50: 8 | L50: 4 | M50: Ratnaflex Engineering Pvt. Ltd | N50: 45 days | O50: 6 LPA | P50: 8 LPA | Q50: B.Tech | R50: Ahmedabad | U50: Shilpa H | V50: Screen Reject | X50: 45400 | AP50: =IF(OR(X50="",C50=""),"",NETWORKDAYS.INTL(C50,X50,1,'HELPER(Dont Delete)'!A:A)) -> 6 | AQ50: =IF(OR(X50="",Y50=""),"",NETWORKDAYS.INTL(X50,Y50,1,'HELPER(Dont Delete)'!A:A)) | AR50: =IF(OR(Y50="",AA50=""),"",NETWORKDAYS.INTL(Y50,AA50,1,'HELPER(Dont Delete)'!A:A))
A51: 51 | B51: 45327 | C51: 45387 | D51: KAM (Gurgaon) | E51: Steelway | F51: Ujjwal Singh | G51: Vishal Singh | H51: 9031358980 | I51: vishal.singh17994@gmail.com | J51: KAM- BD- Pipes | K51: 4 | L51: 4 | M51: Shyam Steel | N51: 30 Days | O51: 4.77 LPA LPA | P51: 30% Hike | Q51: MBA - Marketing | R51: Ranchi | U51: Nikitha Agarwal | V51: L1 Reject | X51: 45400 | Y51: 45404 | Z51: Reject | AP51: =IF(OR(X51="",C51=""),"",NETWORKDAYS.INTL(C51,X51,1,'HELPER(Dont Delete)'!A:A)) -> 6 | AQ51: =IF(OR(X51="",Y51=""),"",NETWORKDAYS.INTL(X51,Y51,1,'HELPER(Dont Delete)'!A:A)) -> 3 | AR51: =IF(OR(Y51="",AA51=""),"",NETWORKDAYS.INTL(Y51,AA51,1,'HELPER(Dont Delete)'!A:A))
A52: 52 | B52: 45327 | C52: 45387 | D52: KAM (Gurgaon) | E52: Steelway | F52: Ujjwal Singh | G52: Ashutosh kumar | H52: 8318062087 | I52: at559033@gmail.com | J52: KAM- BD- Pipes | K52: 4 | L52: 4 | M52: Khamdenu | N52: 30 Days | O52: 4.70 LPA Fixed | P52: 7.00 LPA | Q52: MBA - Marketing | R52: Kanpur | U52: Nikitha Agarwal | V52: Screen Reject | X52: 45400 | AP52: =IF(OR(X52="",C52=""),"",NETWORKDAYS.INTL(C52,X52,1,'HELPER(Dont Delete)'!A:A)) -> 6 | AQ52: =IF(OR(X52="",Y52=""),"",NETWORKDAYS.INTL(X52,Y52,1,'HELPER(Dont Delete)'!A:A)) | AR52: =IF(OR(Y52="",AA52=""),"",NETWORKDAYS.INTL(Y52,AA52,1,'HELPER(Dont Delete)'!A:A))
A53: 53 | B53: 45327 | C53: 45387 | D53: KAM (Gurgaon) | E53: Steelway | F53: Ujjwal Singh | G53: Dharmendra Dubey | H53: 9988975217 | I53: dharmendradubey33@gmail.com | J53: KAM- BD- Pipes | K53: 10 | L53: 10 | M53: Vishal Pipes | N53: 30 Days | O53: 6.72 LPA Fixed | P53: 40% hike | Q53: MBA - Marketing | R53: Ghaziabad | U53: Nikitha Agarwal | V53: Screen Reject | X53: 45400 | AP53: =IF(OR(X53="",C53=""),"",NETWORKDAYS.INTL(C53,X53,1,'HELPER(Dont Delete)'!A:A)) -> 6 | AQ53: =IF(OR(X53="",Y53=""),"",NETWORKDAYS.INTL(X53,Y53,1,'HELPER(Dont Delete)'!A:A)) | AR53: =IF(OR(Y53="",AA53=""),"",NETWORKDAYS.INTL(Y53,AA53,1,'HELPER(Dont Delete)'!A:A))
A54: 54 | B54: 45327 | C54: 45400 | D54: KAM (Mumbai) | E54: Steelway | F54: Ujjwal Singh | G54: Nair Suraj Unnikrishnan | H54: 7387717709 | I54: surajnair1810@gmail.com | J54: sales and marketing, business development | K54: 2 | L54: 2 | M54: Ratnamani Metals & Tubes | N54: 90 days, Buyout available | O54: 3.84 LPA | P54: 5.4 LPA | Q54: BE (ME) | R54: Mumbai | T54: 2 years of exp in sales and marketing | U54: Vinay Kumar | V54: L1 Reject | X54: 45400 | AP54: =IF(OR(X54="",C54=""),"",NETWORKDAYS.INTL(C54,X54,1,'HELPER(Dont Delete)'!A:A)) -> 1 | AQ54: =IF(OR(X54="",Y54=""),"",NETWORKDAYS.INTL(X54,Y54,1,'HELPER(Dont Delete)'!A:A)) | AR54: =IF(OR(Y54="",AA54=""),"",NETWORKDAYS.INTL(Y54,AA54,1,'HELPER(Dont Delete)'!A:A))
A55: 55 | B55: 45401 | C55: 45402 | D55: Fabrication | E55: Steelway | F55: Ujjwal Singh | G55: Himanshu Sukhralia | H55: 8827478208 | I55: er.himanshu.roorkee@gmail.com | J55: Fabrication | K55: 18 | L55: 18 | M55: Zetwerk Manufacturing | N55: 45 | O55: 27 | P55: 35 | Q55: B.Tech/MBA | R55: Nagpur | T55: 18 yrs in Fabrication, SAP exp | U55: Trupti Harichandan | V55: Position on Hold | X55: 45404 | AP55: =IF(OR(X55="",C55=""),"",NETWORKDAYS.INTL(C55,X55,1,'HELPER(Dont Delete)'!A:A)) -> 1 | AQ55: =IF(OR(X55="",Y55=""),"",NETWORKDAYS.INTL(X55,Y55,1,'HELPER(Dont Delete)'!A:A)) | AR55: =IF(OR(Y55="",AA55=""),"",NETWORKDAYS.INTL(Y55,AA55,1,'HELPER(Dont Delete)'!A:A))
A56: 56 | B56: 45401 | C56: 45402 | D56: Fabrication | E56: Steelway | F56: Ujjwal Singh | G56: Nitin Sawant | H56: 9110129369 | I56: nitin_2359@rediffmail.com | J56: Fabrication | K56: 18 | L56: 18 | M56: Heavy Engineering Corporation | N56: 90 | O56: 18 | P56: 24 | Q56: M.Tech | R56: Rachi | T56: 18 yrs in Fabrication, SAP exp | U56: Ajay Singh | V56: Candidate Backout | X56: 45404 | AP56: =IF(OR(X56="",C56=""),"",NETWORKDAYS.INTL(C56,X56,1,'HELPER(Dont Delete)'!A:A)) -> 1 | AQ56: =IF(OR(X56="",Y56=""),"",NETWORKDAYS.INTL(X56,Y56,1,'HELPER(Dont Delete)'!A:A)) | AR56: =IF(OR(Y56="",AA56=""),"",NETWORKDAYS.INTL(Y56,AA56,1,'HELPER(Dont Delete)'!A:A))
A57: 57 | B57: 45401 | C57: 45402 | D57: Fabrication | E57: Steelway | F57: Ujjwal Singh | G57: Sachin Shambharkar | H57: 8788507744 | I57: sachin.shambharkar@rediffmail.com | J57: 8 Yrs exp in fabrications | K57: 15 | L57: 8 | M57: Indiana Gratings | N57: 15 | O57: 15.2 | P57: 19 | Q57: BE-Machenical | R57: Nagpur | U57: Ajay Singh | V57: L1 Reject | X57: 45404 | Y57: 45406 | Z57: Reject | AP57: =IF(OR(X57="",C57=""),"",NETWORKDAYS.INTL(C57,X57,1,'HELPER(Dont Delete)'!A:A)) -> 1 | AQ57: =IF(OR(X57="",Y57=""),"",NETWORKDAYS.INTL(X57,Y57,1,'HELPER(Dont Delete)'!A:A)) -> 3 | AR57: =IF(OR(Y57="",AA57=""),"",NETWORKDAYS.INTL(Y57,AA57,1,'HELPER(Dont Delete)'!A:A))
A58: 58 | B58: 45401 | C58: 45404 | D58: Fabrication | E58: Steelway | F58: Ujjwal Singh | G58: Ganesh Kumar | H58: 7908401549 | I58: ganesh4ong@gmail.com | J58: Plant Commissioning & Running, equipments, EXIM, Operation | K58: 17 | L58: 17 | M58: Supersmelter | N58: 60 | O58: 32 LPA | P58: As per market standard | Q58: M.tech | R58: Durgapur | T58: 17 years of exp in fabrication, plant commissioning, operation, equipments, EXIM | U58: Vinay Kumar | V58: Position on Hold | AP58: =IF(OR(X58="",C58=""),"",NETWORKDAYS.INTL(C58,X58,1,'HELPER(Dont Delete)'!A:A)) | AQ58: =IF(OR(X58="",Y58=""),"",NETWORKDAYS.INTL(X58,Y58,1,'HELPER(Dont Delete)'!A:A)) | AR58: =IF(OR(Y58="",AA58=""),"",NETWORKDAYS.INTL(Y58,AA58,1,'HELPER(Dont Delete)'!A:A))
A59: 59 | B59: 45401 | C59: 45404 | D59: Fabrication | E59: Steelway | F59: Ujjwal Singh | G59: Shahnawaz Siddiqui | H59: 6397410135 | I59: siddiqui.shahnawaz77@gmail.com | J59: Plant Commissioning & Running, equipments, EXIM, Operation | K59: 22 | L59: 22 | M59: Mecon Ltd | N59: 30 | O59: 18 LPA | P59: 26 LPA | Q59: BE | R59: Nasik | T59: 22 years of exp in fabrication,plant commissioning, operation, equipments, EXIM | U59: Vinay Kumar | V59: Position on Hold | AP59: =IF(OR(X59="",C59=""),"",NETWORKDAYS.INTL(C59,X59,1,'HELPER(Dont Delete)'!A:A)) | AQ59: =IF(OR(X59="",Y59=""),"",NETWORKDAYS.INTL(X59,Y59,1,'HELPER(Dont Delete)'!A:A)) | AR59: =IF(OR(Y59="",AA59=""),"",NETWORKDAYS.INTL(Y59,AA59,1,'HELPER(Dont Delete)'!A:A))
A60: 60 | B60: 45327 | C60: 45411 | D60: KAM (Gurgaon) | E60: Steelway | F60: Ujjwal Singh | G60: Ratnesh Katiyar | H60: 9919286167 | I60: ratneshkatiyar1993@gmail.com | J60: sales, BD | K60: 6 years | L60: 6 years | M60: SURYA ROSHNI LIMITED | N60: 15 | O60: 3,40 LPA | P60: 6 LPA | Q60: MBA | R60: Kanpur | U60: Shilpa H | V60: L2 Reject | X60: 45422 | Y60: 45425 | Z60: Pending | AA60: 45453 | AP60: =IF(OR(X60="",C60=""),"",NETWORKDAYS.INTL(C60,X60,1,'HELPER(Dont Delete)'!A:A)) -> 9 | AQ60: =IF(OR(X60="",Y60=""),"",NETWORKDAYS.INTL(X60,Y60,1,'HELPER(Dont Delete)'!A:A)) -> 2 | AR60: =IF(OR(Y60="",AA60=""),"",NETWORKDAYS.INTL(Y60,AA60,1,'HELPER(Dont Delete)'!A:A)) -> 20
A61: 61 | B61: 45327 | C61: 45411 | D61: KAM (Mumbai) | E61: Steelway | F61: Ujjwal Singh | G61: Ziaur Rahman Molla | H61: 9475212252 | I61: z.rahman63@gmail.com | J61: KAM | K61: 9.7 | L61: 4.5 | M61: Shyam Steel Industries Ltd | N61: 30 | O61: 2.77 LPA F+Variable | P61: 4-5 LPA | Q61: BE | R61: West Bengal | T61: TMT Rebar. Govt and private project | U61: Trupti Harichandan | V61: Candidate Backout | X61: 45422 | AP61: =IF(OR(X61="",C61=""),"",NETWORKDAYS.INTL(C61,X61,1,'HELPER(Dont Delete)'!A:A)) -> 9 | AQ61: =IF(OR(X61="",Y61=""),"",NETWORKDAYS.INTL(X61,Y61,1,'HELPER(Dont Delete)'!A:A)) | AR61: =IF(OR(Y61="",AA61=""),"",NETWORKDAYS.INTL(Y61,AA61,1,'HELPER(Dont Delete)'!A:A))
A62: 62 | B62: 45327 | C62: 45411 | D62: KAM (Mumbai) | E62: Steelway | F62: Ujjwal Singh | G62: Soumitra Chakraborty | H62: 7797527376 | I62: soumitrancp13@gmail.com | J62: KAM | K62: 9.3 | L62: 2.8 | M62: Shyam Steel Industries Ltd | N62: 30 | O62: 4.20 LPA F+ variable | P62: 6 LPA | Q62: B.Tech | R62: West Bengal | T62: TMT Bar | U62: Trupti Harichandan | V62: L1 Reject | X62: 45422 | Y62: 45425 | Z62: Feedback Pending | AA62: 45439 | AP62: =IF(OR(X62="",C62=""),"",NETWORKDAYS.INTL(C62,X62,1,'HELPER(Dont Delete)'!A:A)) -> 9 | AQ62: =IF(OR(X62="",Y62=""),"",NETWORKDAYS.INTL(X62,Y62,1,'HELPER(Dont Delete)'!A:A)) -> 2 | AR62: =IF(OR(Y62="",AA62=""),"",NETWORKDAYS.INTL(Y62,AA62,1,'HELPER(Dont Delete)'!A:A)) -> 10
A63: 63 | B63: 45327 | C63: 45411 | D63: KAM (Gurgaon) | E63: Steelway | F63: Ujjwal Singh | G63: Pavan Kumar Pandey | H63: 7566019731 | I63: pandeypavan52@gmail.com | J63: KAM | K63: 3 | L63: 2 | M63: Shyam Steel Industries Ltd | N63: 30 | O63: 5.2 LPA (including variable) | P63: 7 LPA | Q63: MBA | R63: Delhi | T63: Sales and Marketing | U63: Trupti Harichandan | V63: L1 Reject | X63: 45422 | Y63: 45425 | AA63: 45460 | AP63: =IF(OR(X63="",C63=""),"",NETWORKDAYS.INTL(C63,X63,1,'HELPER(Dont Delete)'!A:A)) -> 9 | AQ63: =IF(OR(X63="",Y63=""),"",NETWORKDAYS.INTL(X63,Y63,1,'HELPER(Dont Delete)'!A:A)) -> 2 | AR63: =IF(OR(Y63="",AA63=""),"",NETWORKDAYS.INTL(Y63,AA63,1,'HELPER(Dont Delete)'!A:A)) -> 24
A64: 64 | B64: 45299 | C64: 45411 | D64: Logistics - Manager/Sr Manager | E64: Steelway | F64: Ujjwal Singh | G64: Siddharth Singh | H64: 8527247095, 8004809794 | I64: sid800480@gmail.com | J64: logistic operation, domestic transporation, truck, railway | K64: 8 | L64: 8 | M64: Tata Steel | N64: 90 | O64: 11.75 LPA | P64: 16LPA | Q64: MBA | R64: Kolkata | T64: Domestic Logistics | U64: Shilpa H | V64: Backup Profiles | AP64: =IF(OR(X64="",C64=""),"",NETWORKDAYS.INTL(C64,X64,1,'HELPER(Dont Delete)'!A:A)) | AQ64: =IF(OR(X64="",Y64=""),"",NETWORKDAYS.INTL(X64,Y64,1,'HELPER(Dont Delete)'!A:A)) | AR64: =IF(OR(Y64="",AA64=""),"",NETWORKDAYS.INTL(Y64,AA64,1,'HELPER(Dont Delete)'!A:A))
A65: 65 | B65: 45299 | C65: 45411 | D65: Logistics - Manager/Sr Manager | E65: Steelway | F65: Ujjwal Singh | G65: Aman Jain | H65: 6395706426; 9068176660 | I65: aman.jain02111@gmail.com | J65: logistic operation, domestic transporation, truck, railway | K65: 7 | L65: 7 | M65: Nayara Energy | N65: 90 | O65: 13.20 LPA | P65: 18LPA | Q65: MBA | R65: Jamnagar | T65: Domestic Logistics | U65: Shilpa H | V65: Backup Profiles | X65: 45386 | Y65: 45460 | Z65: Select | AP65: =IF(OR(X65="",C65=""),"",NETWORKDAYS.INTL(C65,X65,1,'HELPER(Dont Delete)'!A:A)) -> -14 | AQ65: =IF(OR(X65="",Y65=""),"",NETWORKDAYS.INTL(X65,Y65,1,'HELPER(Dont Delete)'!A:A)) -> 46 | AR65: =IF(OR(Y65="",AA65=""),"",NETWORKDAYS.INTL(Y65,AA65,1,'HELPER(Dont Delete)'!A:A))
A66: 66 | B66: 45299 | C66: 45411 | D66: Logistics - Manager/Sr Manager | E66: Steelway | F66: Ujjwal Singh | G66: Aditya Rawat | H66: 9536257955 | I66: aditya.kool11@gmail.com | J66: logistic operation, domestic transporation, truck, railway | K66: 8 | L66: 8 | M66: UltraTech Cement | N66: 90 | O66: 13 LPA | P66: 20-30% Hike | Q66: MBA | R66: Noida | U66: Monika | V66: Backup Profiles | AP66: =IF(OR(X66="",C66=""),"",NETWORKDAYS.INTL(C66,X66,1,'HELPER(Dont Delete)'!A:A)) | AQ66: =IF(OR(X66="",Y66=""),"",NETWORKDAYS.INTL(X66,Y66,1,'HELPER(Dont Delete)'!A:A)) | AR66: =IF(OR(Y66="",AA66=""),"",NETWORKDAYS.INTL(Y66,AA66,1,'HELPER(Dont Delete)'!A:A))
A67: 67 | B67: 45327 | C67: 45436 | D67: KAM (Gurgaon) | E67: Steelway | F67: Ujjwal Singh | G67: Sharique Ali | H67: 7503800712 | I67: ali.sharique05@gmail.com | J67: KAM | K67: 8.6 | L67: 8.6 | M67: Shyam Steel Industries Ltd | N67: 60 | O67: 6.5 LPA F+Incentive | P67: can discuss | Q67: B.Tech | R67: Delhi | T67: 5 yrs into steel industry | U67: Trupti Harichandan | V67: Screen Reject | AP67: =IF(OR(X67="",C67=""),"",NETWORKDAYS.INTL(C67,X67,1,'HELPER(Dont Delete)'!A:A)) | AQ67: =IF(OR(X67="",Y67=""),"",NETWORKDAYS.INTL(X67,Y67,1,'HELPER(Dont Delete)'!A:A)) | AR67: =IF(OR(Y67="",AA67=""),"",NETWORKDAYS.INTL(Y67,AA67,1,'HELPER(Dont Delete)'!A:A))
A68: 68 | B68: 45327 | C68: 45436 | D68: KAM (Gurgaon) | E68: Steelway | F68: Ujjwal Singh | G68: Mukund Ranjan Ojha | H68: 8226912467, 8826058628 | I68: mukundojha125@gmail.com | J68: KAM | K68: 9 | L68: 9 | M68: Dina Iron & Steel Ltd | N68: 15 | O68: 5 LPA (including variable) | P68: 0.25 | Q68: BA | R68: Delhi | T68: 9 years into steel industry and product : TMT Rebar | U68: Trupti Harichandan | V68: Screen Reject | AP68: =IF(OR(X68="",C68=""),"",NETWORKDAYS.INTL(C68,X68,1,'HELPER(Dont Delete)'!A:A)) | AQ68: =IF(OR(X68="",Y68=""),"",NETWORKDAYS.INTL(X68,Y68,1,'HELPER(Dont Delete)'!A:A)) | AR68: =IF(OR(Y68="",AA68=""),"",NETWORKDAYS.INTL(Y68,AA68,1,'HELPER(Dont Delete)'!A:A))
A69: 69 | B69: 45327 | C69: 45436 | D69: KAM (Mumbai) | E69: Steelway | F69: Ujjwal Singh | G69: Deepak Ojha | H69: 9589437257 | I69: ojha.deepak1991@gmail.com | J69: KAM | K69: 10.6 | L69: 10.6 | M69: APL Apollo Tubes | N69: 30 | O69: 7.5 LPA F | P69: 9 LPA, can negotiate-depend on interview | Q69: B.sc | R69: Indore, MP | T69: 6 years into Steel industry | U69: Trupti Harichandan | V69: Screen Reject | AP69: =IF(OR(X69="",C69=""),"",NETWORKDAYS.INTL(C69,X69,1,'HELPER(Dont Delete)'!A:A)) | AQ69: =IF(OR(X69="",Y69=""),"",NETWORKDAYS.INTL(X69,Y69,1,'HELPER(Dont Delete)'!A:A)) | AR69: =IF(OR(Y69="",AA69=""),"",NETWORKDAYS.INTL(Y69,AA69,1,'HELPER(Dont Delete)'!A:A))
A70: 70 | B70: 45327 | C70: 45456 | D70: KAM (Gurgaon) | E70: Steelway | F70: Ujjwal Singh | G70: Pravesh Kumar Sahu | H70: 7060796556 | I70: praveshsahu269@gmail.com | J70: KAM | K70: 4.9 | L70: 4.9 | M70: Ambica Steels Limited | N70: 30 | O70: 4.7 CTC( 35K In Hand)Increment due | P70: 25- 30 % Hike | Q70: B.Tech | R70: Delhi | U70: Kanika Goyal | V70: L1 Reject | X70: 45457 | AP70: =IF(OR(X70="",C70=""),"",NETWORKDAYS.INTL(C70,X70,1,'HELPER(Dont Delete)'!A:A)) -> 2 | AQ70: =IF(OR(X70="",Y70=""),"",NETWORKDAYS.INTL(X70,Y70,1,'HELPER(Dont Delete)'!A:A)) | AR70: =IF(OR(Y70="",AA70=""),"",NETWORKDAYS.INTL(Y70,AA70,1,'HELPER(Dont Delete)'!A:A))
A71: 71 | B71: 45327 | C71: 45456 | D71: KAM (Gurgaon) | E71: Steelway | F71: Ujjwal Singh | G71: Akhand Pratap Singh | H71: 8077083571 | I71: coolakhandsingh21@gmail.com | J71: KAM | K71: 3 | L71: 3 | M71: APL Apollo Tubes Ltd | N71: 30 | O71: 6 LPA | P71: 30% hike | Q71: MBA | R71: Raipur | U71: Shilpa H | V71: L1 Reject | X71: 45457 | Y71: 45460 | AP71: =IF(OR(X71="",C71=""),"",NETWORKDAYS.INTL(C71,X71,1,'HELPER(Dont Delete)'!A:A)) -> 2 | AQ71: =IF(OR(X71="",Y71=""),"",NETWORKDAYS.INTL(X71,Y71,1,'HELPER(Dont Delete)'!A:A)) -> 1 | AR71: =IF(OR(Y71="",AA71=""),"",NETWORKDAYS.INTL(Y71,AA71,1,'HELPER(Dont Delete)'!A:A))
A72: 72 | B72: 45299 | C72: 45456 | D72: Logistics - Manager/Sr Manager | E72: Steelway | F72: Ujjwal Singh | G72: Somesh Gupta | H72: 9968883423 | I72: someshgupta0494@gmail.com | J72: Logistic TrNorth Zone | K72: 6.5 | L72: 6.5 | M72: UltraTech Cement | N72: 90 | O72: 11.5LPA + 2LPA | P72: 0.3 | Q72: PGDM, B.Com | R72: Noida | U72: Vaishali | V72: L1 Reject | X72: 45457 | Y72: 45460 | Z72: Reject | AP72: =IF(OR(X72="",C72=""),"",NETWORKDAYS.INTL(C72,X72,1,'HELPER(Dont Delete)'!A:A)) -> 2 | AQ72: =IF(OR(X72="",Y72=""),"",NETWORKDAYS.INTL(X72,Y72,1,'HELPER(Dont Delete)'!A:A)) -> 1 | AR72: =IF(OR(Y72="",AA72=""),"",NETWORKDAYS.INTL(Y72,AA72,1,'HELPER(Dont Delete)'!A:A))
A73: 73 | B73: 45327 | C73: 45464 | D73: KAM (Gurgaon) | E73: Steelway | F73: Ujjwal Singh | G73: Raman Singh | H73: 9805171912 | I73: raman26695@gmail.com | J73: KAM | K73: 2.6 | L73: 2.6 | M73: Neemrana Steel Service Center India | N73: 30 | O73: 3.36LPA | P73: 5LPA | Q73: MBA | R73: Rajasthan | U73: Vaishali | V73: L1 Reject | X73: 45464 | Y73: 45468 | AP73: =IF(OR(X73="",C73=""),"",NETWORKDAYS.INTL(C73,X73,1,'HELPER(Dont Delete)'!A:A)) -> 1 | AQ73: =IF(OR(X73="",Y73=""),"",NETWORKDAYS.INTL(X73,Y73,1,'HELPER(Dont Delete)'!A:A)) -> 3 | AR73: =IF(OR(Y73="",AA73=""),"",NETWORKDAYS.INTL(Y73,AA73,1,'HELPER(Dont Delete)'!A:A))
A74: 74 | B74: 45327 | C74: 45471 | D74: KAM (Gurgaon) | E74: Steelway | F74: Ujjwal Singh | G74: Chetan Singh | H74: 8700764322 | I74: chetans0692@gmail.com | K74: 6 Years | L74: 6 Years | M74: SRJ Tubes | N74: 30Days | Q74: MBA | R74: Aurangabad | U74: Kanika Goyal | V74: Backup Profiles | AP74: =IF(OR(X74="",C74=""),"",NETWORKDAYS.INTL(C74,X74,1,'HELPER(Dont Delete)'!A:A)) | AQ74: =IF(OR(X74="",Y74=""),"",NETWORKDAYS.INTL(X74,Y74,1,'HELPER(Dont Delete)'!A:A)) | AR74: =IF(OR(Y74="",AA74=""),"",NETWORKDAYS.INTL(Y74,AA74,1,'HELPER(Dont Delete)'!A:A))
A75: 75 | B75: 45327 | C75: 45471 | D75: KAM (Gurgaon) | E75: Steelway | F75: Ujjwal Singh | G75: Goutam Roy | H75: 8016057633 | I75: goutam1405@gmail.com | K75: 6 Years | L75: 2.5 Years | M75: Shyam Steel industries Ltd | N75: 30Days | Q75: B.Tech | R75: Kolkata | U75: Kanika Goyal | V75: Backup Profiles | AP75: =IF(OR(X75="",C75=""),"",NETWORKDAYS.INTL(C75,X75,1,'HELPER(Dont Delete)'!A:A)) | AQ75: =IF(OR(X75="",Y75=""),"",NETWORKDAYS.INTL(X75,Y75,1,'HELPER(Dont Delete)'!A:A)) | AR75: =IF(OR(Y75="",AA75=""),"",NETWORKDAYS.INTL(Y75,AA75,1,'HELPER(Dont Delete)'!A:A))
A76: 76 | B76: 45327 | C76: 45471 | D76: KAM (Gurgaon) | E76: Steelway | F76: Ujjwal Singh | G76: Sourabh Saxena | H76: 7000083686 | I76: sourabh.saxena7898@gmail.com | K76: 4.5 Years | L76: 2 Years | M76: Astral Pipes | N76: 30Days | Q76: MBA | R76: Bhopal | U76: Kanika Goyal | V76: Backup Profiles | AP76: =IF(OR(X76="",C76=""),"",NETWORKDAYS.INTL(C76,X76,1,'HELPER(Dont Delete)'!A:A)) | AQ76: =IF(OR(X76="",Y76=""),"",NETWORKDAYS.INTL(X76,Y76,1,'HELPER(Dont Delete)'!A:A)) | AR76: =IF(OR(Y76="",AA76=""),"",NETWORKDAYS.INTL(Y76,AA76,1,'HELPER(Dont Delete)'!A:A))
A77: 77 | B77: 45476 | C77: 45481 | D77: KAM (Mumbai) | E77: Steelway | F77: Ujjwal Singh | G77: Vineet Kubal | H77: 9156763848 | I77: vineet.kubal55@gmail.com | K77: 3Yrs | L77: 1.5Yrs | M77: Nevatia Steel & Alloys pvt ltd | N77: 30days | O77: 3.96LPA + 1.5LPA | P77: 0.3 | Q77: MBA, BE | R77: Dahanu | U77: Kanika | V77: Candidate Drop | AP77: =IF(OR(X77="",C77=""),"",NETWORKDAYS.INTL(C77,X77,1,'HELPER(Dont Delete)'!A:A)) | AQ77: =IF(OR(X77="",Y77=""),"",NETWORKDAYS.INTL(X77,Y77,1,'HELPER(Dont Delete)'!A:A)) | AR77: =IF(OR(Y77="",AA77=""),"",NETWORKDAYS.INTL(Y77,AA77,1,'HELPER(Dont Delete)'!A:A))
A78: 78 | B78: 45476 | C78: 45482 | D78: KAM_ Steel (Mumbai) | E78: Steelway | F78: Ujjwal Singh | G78: Pratik Khandke | H78: 7770072909 | I78: pratik.khandke15@gmail.com | J78: KAM, Sales, BD, steel | K78: 3.5 | L78: 2 | M78: Blue Ocean Steels | N78: 30 | O78: 4.1LPA fixed | P78: 30% hike | Q78: B.Tech | R78: Pune | T78: steel round rod | U78: Shilpa H | V78: Candidate Drop | AP78: =IF(OR(X78="",C78=""),"",NETWORKDAYS.INTL(C78,X78,1,'HELPER(Dont Delete)'!A:A)) | AQ78: =IF(OR(X78="",Y78=""),"",NETWORKDAYS.INTL(X78,Y78,1,'HELPER(Dont Delete)'!A:A)) | AR78: =IF(OR(Y78="",AA78=""),"",NETWORKDAYS.INTL(Y78,AA78,1,'HELPER(Dont Delete)'!A:A))
A79: 79 | B79: 45476 | C79: 45482 | D79: KAM_ Steel (Mumbai) | E79: Steelway | F79: Ujjwal Singh | G79: Dhruv J Darji | H79: 9173718552 | I79: darjidhruv17101999@gmail.com | J79: KAM, Sales, BD, steel | K79: 3 | L79: 2 | M79: Harsha Engineers International Ltd | N79: 60 | O79: 4LPA fixed + .5V | P79: 8 LPA(Nego) | Q79: B.Tech | R79: Ahmedabad | T79: steel stamping product | U79: Shilpa H | V79: Candidate Drop | AP79: =IF(OR(X79="",C79=""),"",NETWORKDAYS.INTL(C79,X79,1,'HELPER(Dont Delete)'!A:A)) | AQ79: =IF(OR(X79="",Y79=""),"",NETWORKDAYS.INTL(X79,Y79,1,'HELPER(Dont Delete)'!A:A)) | AR79: =IF(OR(Y79="",AA79=""),"",NETWORKDAYS.INTL(Y79,AA79,1,'HELPER(Dont Delete)'!A:A))
A80: 80 | B80: 45476 | C80: 45484 | D80: KAM - AM | E80: Steelway | F80: Ujjwal Singh | G80: Dushyant Nehar | H80: 7879261915 | I80: dushyantnehar@gmail.com | J80: KAM, Sales, BD, steel | K80: 7 | L80: 7 | M80: Tata Precisión Industries (India) Ltd. | N80: 30 | O80: 6.5 LPA fixed | P80: 9 to 10 LPA | Q80: BE+MBA | R80: Indore | U80: Shilpa H | V80: L1 Reject | X80: 45497 | Y80: 45503 | AP80: =IF(OR(X80="",C80=""),"",NETWORKDAYS.INTL(C80,X80,1,'HELPER(Dont Delete)'!A:A)) -> 9 | AQ80: =IF(OR(X80="",Y80=""),"",NETWORKDAYS.INTL(X80,Y80,1,'HELPER(Dont Delete)'!A:A)) -> 5 | AR80: =IF(OR(Y80="",AA80=""),"",NETWORKDAYS.INTL(Y80,AA80,1,'HELPER(Dont Delete)'!A:A))
A81: 81 | B81: 45476 | C81: 45484 | D81: KAM - AM | E81: Steelway | F81: Ujjwal Singh | G81: Tanmay Rathi | H81: 9175745520 | I81: infotanmayrathi@gmail.com | J81: KAM, Sales, BD, steel | K81: 4.5 | L81: 4.5 | M81: Metalbook | N81: 45 | O81: 7 LPA fixed + 25 PMV | P81: 10 LPA fixed | Q81: B.Tech | R81: Pune | U81: Shilpa H | V81: Candidate Drop | AP81: =IF(OR(X81="",C81=""),"",NETWORKDAYS.INTL(C81,X81,1,'HELPER(Dont Delete)'!A:A)) | AQ81: =IF(OR(X81="",Y81=""),"",NETWORKDAYS.INTL(X81,Y81,1,'HELPER(Dont Delete)'!A:A)) | AR81: =IF(OR(Y81="",AA81=""),"",NETWORKDAYS.INTL(Y81,AA81,1,'HELPER(Dont Delete)'!A:A))
A82: 82 | B82: 45476 | C82: 45484 | D82: KAM - AM | E82: Steelway | F82: Ujjwal Singh | G82: Romio Ranjan Mallick | H82: 8763105087 | I82: romioranjanmallick@gmail.com | J82: KAM, Sales, BD, steel | K82: 7.2 | L82: 7.2 | M82: Aarti Steels Limited | N82: 90 | O82: 10 LPA fixed | P82: 12 LPA | Q82: B.Tech+MBA | R82: Odisha | U82: Shilpa H | V82: Candidate Drop | AP82: =IF(OR(X82="",C82=""),"",NETWORKDAYS.INTL(C82,X82,1,'HELPER(Dont Delete)'!A:A)) | AQ82: =IF(OR(X82="",Y82=""),"",NETWORKDAYS.INTL(X82,Y82,1,'HELPER(Dont Delete)'!A:A)) | AR82: =IF(OR(Y82="",AA82=""),"",NETWORKDAYS.INTL(Y82,AA82,1,'HELPER(Dont Delete)'!A:A))
A83: 83 | B83: 45476 | C83: 45484 | D83: KAM - AM | E83: Steelway | F83: Ujjwal Singh | G83: Hardik Vekariya | H83: 9099676570 | I83: hardikvekariya74@gmail.com | J83: KAM, Sales, BD, steel | K83: 7 | L83: 5 | M83: Toyota Tsusho India Pvt. Ltd | N83: 60 | O83: 8 LPA | P83: 11 LPA | Q83: B.Tech | R83: Ahmedabad | U83: Shilpa H | V83: L1 Reject | X83: 45497 | Y83: 45504 | AP83: =IF(OR(X83="",C83=""),"",NETWORKDAYS.INTL(C83,X83,1,'HELPER(Dont Delete)'!A:A)) -> 9 | AQ83: =IF(OR(X83="",Y83=""),"",NETWORKDAYS.INTL(X83,Y83,1,'HELPER(Dont Delete)'!A:A)) -> 6 | AR83: =IF(OR(Y83="",AA83=""),"",NETWORKDAYS.INTL(Y83,AA83,1,'HELPER(Dont Delete)'!A:A))
A84: 84 | B84: 45476 | C84: 45484 | D84: KAM - AM | E84: Steelway | F84: Ujjwal Singh | G84: Manish Kumar | H84: 8457936306 | I84: manish.kumar2@amns.in | J84: KAM, Sales, BD, steel | K84: 6 | L84: 6 | M84: AMNS | N84: 60 | O84: 8 + 1 LPA | P84: Okay for same as well | Q84: B.Tech | R84: Gandhidham | U84: Shilpa H | V84: L1 Reject | W84: L1 Stage | X84: 45497 | Y84: 45498 | AP84: =IF(OR(X84="",C84=""),"",NETWORKDAYS.INTL(C84,X84,1,'HELPER(Dont Delete)'!A:A)) -> 9 | AQ84: =IF(OR(X84="",Y84=""),"",NETWORKDAYS.INTL(X84,Y84,1,'HELPER(Dont Delete)'!A:A)) -> 2 | AR84: =IF(OR(Y84="",AA84=""),"",NETWORKDAYS.INTL(Y84,AA84,1,'HELPER(Dont Delete)'!A:A))
A85: 85 | B85: 45327 | C85: 45492 | D85: KAM_ Steel (Mumbai) | E85: Steelway | F85: Ujjwal Singh | G85: Sagar Shashikant Bhosale | H85: 9096864858 | I85: sagarbhosle91@gmail.com | J85: KAM, Sales, BD, steel | K85: 8 Years | L85: 3.5 Years | M85: Nathasha Fin Tubes Private Limited | N85: 30 | Q85: BE Mech | R85: Pune | U85: Shilpa H | V85: Screen Reject | AP85: =IF(OR(X85="",C85=""),"",NETWORKDAYS.INTL(C85,X85,1,'HELPER(Dont Delete)'!A:A)) | AQ85: =IF(OR(X85="",Y85=""),"",NETWORKDAYS.INTL(X85,Y85,1,'HELPER(Dont Delete)'!A:A)) | AR85: =IF(OR(Y85="",AA85=""),"",NETWORKDAYS.INTL(Y85,AA85,1,'HELPER(Dont Delete)'!A:A))
A86: 86 | B86: 45327 | C86: 45499 | D86: KAM_ Steel (Mumbai) | E86: Steelway | F86: Ujjwal Singh | G86: Shashank Jadhav | H86: 9869301790 | I86: Shash.jdv@gmail.com | J86: KAM, Sales, BD, steel | K86: 10 | L86: 7 | M86: Ratnamani Metals & Tubes Ltd | N86: 60 | O86: 5.5 CTC (All Fixed) | P86: 30-35 % Hike | Q86: BE Mech | R86: Mumbai | U86: Kanika Goyal | V86: Screen Reject | AP86: =IF(OR(X86="",C86=""),"",NETWORKDAYS.INTL(C86,X86,1,'HELPER(Dont Delete)'!A:A)) | AQ86: =IF(OR(X86="",Y86=""),"",NETWORKDAYS.INTL(X86,Y86,1,'HELPER(Dont Delete)'!A:A)) | AR86: =IF(OR(Y86="",AA86=""),"",NETWORKDAYS.INTL(Y86,AA86,1,'HELPER(Dont Delete)'!A:A))
A87: 87 | B87: 45476 | C87: 45505 | D87: KAM - AM | E87: Steelway | F87: Ujjwal Singh | G87: Chetan Golwalkar | H87: 9644921497 | I87: chetangolwalkar@gmail.com | J87: KAM, Sales, BD, steel | K87: 13 | L87: 13 | M87: Innovative Clad Solutions | N87: 90 days, buy out available | Q87: BE | R87: Indore | U87: Shilpa H | V87: L1 to be scheduled | W87: L1 Stage | AP87: =IF(OR(X87="",C87=""),"",NETWORKDAYS.INTL(C87,X87,1,'HELPER(Dont Delete)'!A:A)) | AQ87: =IF(OR(X87="",Y87=""),"",NETWORKDAYS.INTL(X87,Y87,1,'HELPER(Dont Delete)'!A:A)) | AR87: =IF(OR(Y87="",AA87=""),"",NETWORKDAYS.INTL(Y87,AA87,1,'HELPER(Dont Delete)'!A:A))
A88: 88 | B88: 45476 | C88: 45505 | D88: KAM - AM | E88: Steelway | F88: Ujjwal Singh | G88: Kaushik Vamza | H88: 9601165062 | I88: vamzakaushik21@gmail.com | J88: KAM, Sales, BD, steel | K88: 8 | L88: 8 | M88: ASR Multi Metals | N88: 30 | Q88: BE | R88: Rajkot | U88: Shilpa H | V88: Screen Reject | AP88: =IF(OR(X88="",C88=""),"",NETWORKDAYS.INTL(C88,X88,1,'HELPER(Dont Delete)'!A:A)) | AQ88: =IF(OR(X88="",Y88=""),"",NETWORKDAYS.INTL(X88,Y88,1,'HELPER(Dont Delete)'!A:A)) | AR88: =IF(OR(Y88="",AA88=""),"",NETWORKDAYS.INTL(Y88,AA88,1,'HELPER(Dont Delete)'!A:A))
A89: 89 | B89: 45476 | C89: 45505 | D89: KAM_ Steel (Mumbai) | E89: Steelway | F89: Ujjwal Singh | G89: Mohit Jaiswal | H89: 9770097620 | I89: mohitjaiswal3281@gmail.com | J89: KAM, Sales, BD, steel | K89: 4.6 | L89: 4.6 | M89: Jaideep Ispat & Alloys | N89: 30 | Q89: BE | R89: Indore | U89: Shilpa H | V89: Candidate Drop | AP89: =IF(OR(X89="",C89=""),"",NETWORKDAYS.INTL(C89,X89,1,'HELPER(Dont Delete)'!A:A)) | AQ89: =IF(OR(X89="",Y89=""),"",NETWORKDAYS.INTL(X89,Y89,1,'HELPER(Dont Delete)'!A:A)) | AR89: =IF(OR(Y89="",AA89=""),"",NETWORKDAYS.INTL(Y89,AA89,1,'HELPER(Dont Delete)'!A:A))
A90: 90 | B90: 45476 | C90: 45512 | D90: KAM_ Steel (Mumbai) | E90: Steelway | F90: Ujjwal Singh | G90: Ashish Kumar | H90: 9504342598 | I90: ashishkum950@gmail.com | J90: KAM, Sales, BD, steel | K90: 1.5 | L90: 1.5 | M90: Synergy Steel Ltd | N90: 30 | O90: 4 LPA (34000 in hand) | P90: 25% to 30% hike | Q90: MBA | R90: Delhi | U90: Vinay Kumar | V90: Candidate Drop | AP90: =IF(OR(X90="",C90=""),"",NETWORKDAYS.INTL(C90,X90,1,'HELPER(Dont Delete)'!A:A)) | AQ90: =IF(OR(X90="",Y90=""),"",NETWORKDAYS.INTL(X90,Y90,1,'HELPER(Dont Delete)'!A:A)) | AR90: =IF(OR(Y90="",AA90=""),"",NETWORKDAYS.INTL(Y90,AA90,1,'HELPER(Dont Delete)'!A:A))
A91: 91 | B91: 45476 | C91: 45512 | D91: KAM - AM | E91: Steelway | F91: Ujjwal Singh | G91: Darshit Bhakhar | H91: 9033896018 | I91: darshitp113@gmail.com | J91: KAM, Sales, BD, steel | K91: 5+ | L91: 5+ | M91: Baosteel India | N91: 30 | O91: 27000 in hand | P91: 25% to 30% hike | Q91: BE (ME) | R91: Ahmedabad | U91: Vinay Kumar | V91: L1 Reject | Y91: 45517 | AP91: =IF(OR(X91="",C91=""),"",NETWORKDAYS.INTL(C91,X91,1,'HELPER(Dont Delete)'!A:A)) | AQ91: =IF(OR(X91="",Y91=""),"",NETWORKDAYS.INTL(X91,Y91,1,'HELPER(Dont Delete)'!A:A)) | AR91: =IF(OR(Y91="",AA91=""),"",NETWORKDAYS.INTL(Y91,AA91,1,'HELPER(Dont Delete)'!A:A))
A92: 92 | B92: 45476 | C92: 45524 | D92: KAM_ Steel (Mumbai) | E92: Steelway | F92: Ujjwal Singh | G92: Aniket Rajendra Mane | H92: 9987801040 | I92: maneaniket027@gmail.com | J92: KAM, Sales, BD, steel | K92: 7 Years | L92: 3 Years | M92: Swastik Industrial Works | N92: 60 | Q92: PGDM | R92: Mumbai | U92: Vinay Kumar | V92: Screen Reject | AP92: =IF(OR(X92="",C92=""),"",NETWORKDAYS.INTL(C92,X92,1,'HELPER(Dont Delete)'!A:A)) | AQ92: =IF(OR(X92="",Y92=""),"",NETWORKDAYS.INTL(X92,Y92,1,'HELPER(Dont Delete)'!A:A)) | AR92: =IF(OR(Y92="",AA92=""),"",NETWORKDAYS.INTL(Y92,AA92,1,'HELPER(Dont Delete)'!A:A))
A93: 93 | B93: 45476 | C93: 45524 | D93: KAM_ Steel (Mumbai) | E93: Steelway | F93: Ujjwal Singh | G93: Rishi Kesh Jha | H93: 9425756237 | I93: rishikeshjha92@gmail.com | J93: KAM, Sales, BD, steel | K93: 10 Years | L93: 10 Years | M93: Univteck Pvt Ltd | N93: 15 | Q93: MBA | R93: Noida | U93: Kanika | V93: Screen Reject | AP93: =IF(OR(X93="",C93=""),"",NETWORKDAYS.INTL(C93,X93,1,'HELPER(Dont Delete)'!A:A)) | AQ93: =IF(OR(X93="",Y93=""),"",NETWORKDAYS.INTL(X93,Y93,1,'HELPER(Dont Delete)'!A:A)) | AR93: =IF(OR(Y93="",AA93=""),"",NETWORKDAYS.INTL(Y93,AA93,1,'HELPER(Dont Delete)'!A:A))
A94: 94 | B94: 45476 | C94: 45524 | D94: KAM- AM | E94: Steelway | F94: Ujjwal Singh | G94: Arvind Kumar | H94: 9714891908 | I94: arvindpassion2008@gmail.com | J94: KAM, Sales, BD, steel | K94: 10 Years | L94: 10 Years | M94: Varalka Engineers Pvt Ltd | N94: 30 | Q94: MBA | R94: Vadodara | U94: Vinay Kumar | V94: L1 Reject | Y94: 45545 | AP94: =IF(OR(X94="",C94=""),"",NETWORKDAYS.INTL(C94,X94,1,'HELPER(Dont Delete)'!A:A)) | AQ94: =IF(OR(X94="",Y94=""),"",NETWORKDAYS.INTL(X94,Y94,1,'HELPER(Dont Delete)'!A:A)) | AR94: =IF(OR(Y94="",AA94=""),"",NETWORKDAYS.INTL(Y94,AA94,1,'HELPER(Dont Delete)'!A:A))
A95: 95 | B95: 45476 | C95: 45534 | D95: KAM_ Steel (Mumbai) | E95: Steelway | F95: Ujjwal Singh | G95: Abhimanyu Kumar | H95: 9694624866 | I95: abhimanyukumar804@gmail.com | J95: KAM, Sales, BD, steel | K95: 5 Years | L95: 5 Years | M95: Shyam Steel industries Ltd | N95: 15 | Q95: MBA | R95: Rajasthan | U95: Kanika | V95: Candidate Drop | AP95: =IF(OR(X95="",C95=""),"",NETWORKDAYS.INTL(C95,X95,1,'HELPER(Dont Delete)'!A:A)) | AQ95: =IF(OR(X95="",Y95=""),"",NETWORKDAYS.INTL(X95,Y95,1,'HELPER(Dont Delete)'!A:A)) | AR95: =IF(OR(Y95="",AA95=""),"",NETWORKDAYS.INTL(Y95,AA95,1,'HELPER(Dont Delete)'!A:A))
A96: 96 | B96: 45476 | C96: 45534 | D96: KAM_ Steel (Mumbai) | E96: Steelway | F96: Ujjwal Singh | G96: Anjani Shukla | H96: 9300604095 | I96: anjanishu42@gmail.com | J96: KAM, Sales, BD, steel | K96: 9 Years | L96: 6 Years | M96: SKA steel power Ltd | N96: 30 | Q96: MBA | R96: Raipur | U96: Kanika | V96: Candidate Drop | AP96: =IF(OR(X96="",C96=""),"",NETWORKDAYS.INTL(C96,X96,1,'HELPER(Dont Delete)'!A:A)) | AQ96: =IF(OR(X96="",Y96=""),"",NETWORKDAYS.INTL(X96,Y96,1,'HELPER(Dont Delete)'!A:A)) | AR96: =IF(OR(Y96="",AA96=""),"",NETWORKDAYS.INTL(Y96,AA96,1,'HELPER(Dont Delete)'!A:A))
A97: 97 | B97: 45476 | C97: 45534 | D97: KAM_ Steel (Mumbai) | E97: Steelway | F97: Ujjwal Singh | G97: Ashish Kumar | H97: 9504342598 | I97: ashishkum950@gmail.com | J97: KAM, Sales, BD, steel | K97: 1.7 Years | L97: 1.7 Years | M97: Synergy Steel Ltd | N97: 30 | Q97: MBA | R97: Delhi | U97: Vinay Kumar | V97: Candidate Drop | AP97: =IF(OR(X97="",C97=""),"",NETWORKDAYS.INTL(C97,X97,1,'HELPER(Dont Delete)'!A:A)) | AQ97: =IF(OR(X97="",Y97=""),"",NETWORKDAYS.INTL(X97,Y97,1,'HELPER(Dont Delete)'!A:A)) | AR97: =IF(OR(Y97="",AA97=""),"",NETWORKDAYS.INTL(Y97,AA97,1,'HELPER(Dont Delete)'!A:A))
A98: 98 | B98: 45476 | C98: 45547 | D98: KAM_ Steel (Mumbai) | E98: Steelway | F98: Ujjwal Singh | G98: Tanmay | H98: 9175745520 | I98: infotanmayrathi@gmail.com | J98: KAM, Sales, BD, steel | K98: 5.3 Years | L98: 4.5 Years | M98: Metalbook | N98: 30 | Q98: BE | R98: Pune | U98: Kanika | V98: Candidate Drop | AP98: =IF(OR(X98="",C98=""),"",NETWORKDAYS.INTL(C98,X98,1,'HELPER(Dont Delete)'!A:A)) | AQ98: =IF(OR(X98="",Y98=""),"",NETWORKDAYS.INTL(X98,Y98,1,'HELPER(Dont Delete)'!A:A)) | AR98: =IF(OR(Y98="",AA98=""),"",NETWORKDAYS.INTL(Y98,AA98,1,'HELPER(Dont Delete)'!A:A))
A99: 99 | B99: 45548 | C99: 45551 | D99: KAM_ Steel (Hyderabad) | E99: Steelway | F99: Ujjwal Singh | G99: Abhimanyu Kumar | H99: 9694624866 | I99: abhimanyukumar804@gmail.com | J99: KAM, Sales, BD, steel | K99: 5 Years | L99: 5 Years | M99: Shyam Steel industries Ltd | N99: 15 Days | Q99: MBA | R99: Rajasthan | U99: Kanika | V99: Candidate Drop | AP99: =IF(OR(X99="",C99=""),"",NETWORKDAYS.INTL(C99,X99,1,'HELPER(Dont Delete)'!A:A)) | AQ99: =IF(OR(X99="",Y99=""),"",NETWORKDAYS.INTL(X99,Y99,1,'HELPER(Dont Delete)'!A:A)) | AR99: =IF(OR(Y99="",AA99=""),"",NETWORKDAYS.INTL(Y99,AA99,1,'HELPER(Dont Delete)'!A:A))
A100: 100 | B100: 45548 | C100: 45551 | D100: KAM_ Steel (Hyderabad) | E100: Steelway | F100: Ujjwal Singh | G100: Anjani Shukla | H100: 9300604095 | I100: anjanishu42@gmail.com | J100: KAM, Sales, BD, steel | K100: 9 Years | L100: 6 Years | M100: SKA steel power Ltd | N100: 30 Days | Q100: MBA | R100: Raipur | U100: Kanika | V100: Screening Pending | AP100: =IF(OR(X100="",C100=""),"",NETWORKDAYS.INTL(C100,X100,1,'HELPER(Dont Delete)'!A:A)) | AQ100: =IF(OR(X100="",Y100=""),"",NETWORKDAYS.INTL(X100,Y100,1,'HELPER(Dont Delete)'!A:A)) | AR100: =IF(OR(Y100="",AA100=""),"",NETWORKDAYS.INTL(Y100,AA100,1,'HELPER(Dont Delete)'!A:A))
...

Sheet Dashboard
A1: REQ. DATE | B1: Role | C1: Aging | D1: Position Count | E1: Total CV Shared | F1: FTR% | G1: Screening | H1: L1 Stage | I1: L2 Stage | J1: Offer Stage | K1: Status | L1: Level
A2: =_xlfn.XLOOKUP(B2,'Position Tracker'!E:E,'Position Tracker'!B:B,,0) -> 45401 | B2: Fabrication | C2: =NETWORKDAYS.INTL(A2,TODAY(),1,'HELPER(Dont Delete)'!A:A) -> 419 | D2: =VLOOKUP(B2,'Position Tracker'!E:F,3,0) -> #REF! | E2: =COUNTIFS('Candidate Tracker'!D:D,B2) -> 6 | F2: =_xlfn.XLOOKUP(B2,'Position Tracker'!E:E,'Position Tracker'!X:X,,0) -> 100% | G2: =COUNTIFS('Candidate Tracker'!D:D,B2,'Candidate Tracker'!W:W,"Screening Stage") -> 0 | H2: =COUNTIFS('Candidate Tracker'!D:D,B2,'Candidate Tracker'!W:W,"L1 Stage") -> 0 | I2: =COUNTIFS('Candidate Tracker'!D:D,B2,'Candidate Tracker'!W:W,"L2 Stage") -> 0 | J2: =COUNTIFS('Candidate Tracker'!D:D,B2,'Candidate Tracker'!W:W,"Offer Stage") -> 0 | K2: =_xlfn.XLOOKUP(B2,'Position Tracker'!E:E,'Position Tracker'!J:J,,0) -> Hold | L2: =_xlfn.XLOOKUP(B2,'Position Tracker'!E:E,'Position Tracker'!Y:Y,,0) -> RL3
A3: =_xlfn.XLOOKUP(B3,'Position Tracker'!E:E,'Position Tracker'!B:B,,0) -> 45356 | B3: KAM (Mumbai) | C3: =NETWORKDAYS.INTL(A3,TODAY(),1,'HELPER(Dont Delete)'!A:A) -> 444 | D3: =VLOOKUP(B3,'Position Tracker'!E:F,3,0) -> #REF! | E3: =COUNTIFS('Candidate Tracker'!D:D,B3) -> 5 | F3: =_xlfn.XLOOKUP(B3,'Position Tracker'!E:E,'Position Tracker'!X:X,,0) -> 0.8 | G3: =COUNTIFS('Candidate Tracker'!D:D,B3,'Candidate Tracker'!W:W,"Screening Stage") -> 0 | H3: =COUNTIFS('Candidate Tracker'!D:D,B3,'Candidate Tracker'!W:W,"L1 Stage") -> 0 | I3: =COUNTIFS('Candidate Tracker'!D:D,B3,'Candidate Tracker'!W:W,"L2 Stage") -> 0 | J3: =COUNTIFS('Candidate Tracker'!D:D,B3,'Candidate Tracker'!W:W,"Offer Stage") -> 0 | K3: =_xlfn.XLOOKUP(B3,'Position Tracker'!E:E,'Position Tracker'!J:J,,0) -> Scap | L3: =_xlfn.XLOOKUP(B3,'Position Tracker'!E:E,'Position Tracker'!Y:Y,,0) -> RL1
A4: =_xlfn.XLOOKUP(B4,'Position Tracker'!E:E,'Position Tracker'!B:B,,0) -> 45299 | B4: Logistics - Manager/Sr Manager | C4: =NETWORKDAYS.INTL(A4,TODAY(),1,'HELPER(Dont Delete)'!A:A) -> 479 | D4: =VLOOKUP(B4,'Position Tracker'!E:F,3,0) -> #REF! | E4: =COUNTIFS('Candidate Tracker'!D:D,B4) -> 11 | F4: =_xlfn.XLOOKUP(B4,'Position Tracker'!E:E,'Position Tracker'!X:X,,0) -> 0.81818182 | G4: =COUNTIFS('Candidate Tracker'!D:D,B4,'Candidate Tracker'!W:W,"Screening Stage") -> 0 | H4: =COUNTIFS('Candidate Tracker'!D:D,B4,'Candidate Tracker'!W:W,"L1 Stage") -> 0 | I4: =COUNTIFS('Candidate Tracker'!D:D,B4,'Candidate Tracker'!W:W,"L2 Stage") -> 0 | J4: =COUNTIFS('Candidate Tracker'!D:D,B4,'Candidate Tracker'!W:W,"Offer Stage") -> 0 | K4: =_xlfn.XLOOKUP(B4,'Position Tracker'!E:E,'Position Tracker'!J:J,,0) -> Joined | L4: =_xlfn.XLOOKUP(B4,'Position Tracker'!E:E,'Position Tracker'!Y:Y,,0) -> RL2
A5: =_xlfn.XLOOKUP(B5,'Position Tracker'!E:E,'Position Tracker'!B:B,,0) -> 45327 | B5: KAM (Kolkata) | C5: =NETWORKDAYS.INTL(A5,TODAY(),1,'HELPER(Dont Delete)'!A:A) -> 463 | D5: =VLOOKUP(B5,'Position Tracker'!E:F,3,0) -> #REF! | E5: =COUNTIFS('Candidate Tracker'!D:D,B5) -> 25 | F5: =_xlfn.XLOOKUP(B5,'Position Tracker'!E:E,'Position Tracker'!X:X,,0) -> 0.72 | G5: =COUNTIFS('Candidate Tracker'!D:D,B5,'Candidate Tracker'!W:W,"Screening Stage") -> 0 | H5: =COUNTIFS('Candidate Tracker'!D:D,B5,'Candidate Tracker'!W:W,"L1 Stage") -> 0 | I5: =COUNTIFS('Candidate Tracker'!D:D,B5,'Candidate Tracker'!W:W,"L2 Stage") -> 0 | J5: =COUNTIFS('Candidate Tracker'!D:D,B5,'Candidate Tracker'!W:W,"Offer Stage") -> 0 | K5: =_xlfn.XLOOKUP(B5,'Position Tracker'!E:E,'Position Tracker'!J:J,,0) -> Joined | L5: =_xlfn.XLOOKUP(B5,'Position Tracker'!E:E,'Position Tracker'!Y:Y,,0) -> RL2
A6: =_xlfn.XLOOKUP(B6,'Position Tracker'!E:E,'Position Tracker'!B:B,,0) -> 45356 | B6: KAM (Ahmedabad) | C6: =NETWORKDAYS.INTL(A6,TODAY(),1,'HELPER(Dont Delete)'!A:A) -> 444 | D6: =VLOOKUP(B6,'Position Tracker'!E:F,3,0) -> #REF! | E6: =COUNTIFS('Candidate Tracker'!D:D,B6) -> 0 | F6: =_xlfn.XLOOKUP(B6,'Position Tracker'!E:E,'Position Tracker'!X:X,,0) -> 0 | G6: =COUNTIFS('Candidate Tracker'!D:D,B6,'Candidate Tracker'!W:W,"Screening Stage") -> 0 | H6: =COUNTIFS('Candidate Tracker'!D:D,B6,'Candidate Tracker'!W:W,"L1 Stage") -> 0 | I6: =COUNTIFS('Candidate Tracker'!D:D,B6,'Candidate Tracker'!W:W,"L2 Stage") -> 0 | J6: =COUNTIFS('Candidate Tracker'!D:D,B6,'Candidate Tracker'!W:W,"Offer Stage") -> 0 | K6: =_xlfn.XLOOKUP(B6,'Position Tracker'!E:E,'Position Tracker'!J:J,,0) -> Joined | L6: =_xlfn.XLOOKUP(B6,'Position Tracker'!E:E,'Position Tracker'!Y:Y,,0) -> RL1
A7: =_xlfn.XLOOKUP(B7,'Position Tracker'!E:E,'Position Tracker'!B:B,,0) -> 45356 | B7: KAM (Gurgaon) | C7: =NETWORKDAYS.INTL(A7,TODAY(),1,'HELPER(Dont Delete)'!A:A) -> 444 | D7: =VLOOKUP(B7,'Position Tracker'!E:F,3,0) -> #REF! | E7: =COUNTIFS('Candidate Tracker'!D:D,B7) -> 24 | F7: =_xlfn.XLOOKUP(B7,'Position Tracker'!E:E,'Position Tracker'!X:X,,0) -> 0.83333333 | G7: =COUNTIFS('Candidate Tracker'!D:D,B7,'Candidate Tracker'!W:W,"Screening Stage") -> 0 | H7: =COUNTIFS('Candidate Tracker'!D:D,B7,'Candidate Tracker'!W:W,"L1 Stage") -> 0 | I7: =COUNTIFS('Candidate Tracker'!D:D,B7,'Candidate Tracker'!W:W,"L2 Stage") -> 0 | J7: =COUNTIFS('Candidate Tracker'!D:D,B7,'Candidate Tracker'!W:W,"Offer Stage") -> 0 | K7: =_xlfn.XLOOKUP(B7,'Position Tracker'!E:E,'Position Tracker'!J:J,,0) -> Hold | L7: =_xlfn.XLOOKUP(B7,'Position Tracker'!E:E,'Position Tracker'!Y:Y,,0) -> RL1
A8: =_xlfn.XLOOKUP(B8,'Position Tracker'!E:E,'Position Tracker'!B:B,,0) -> 45476 | B8: KAM_ Steel (Mumbai) | C8: =NETWORKDAYS.INTL(A8,TODAY(),1,'HELPER(Dont Delete)'!A:A) -> 369 | D8: =VLOOKUP(B8,'Position Tracker'!E:F,3,0) -> #REF! | E8: =COUNTIFS('Candidate Tracker'!D:D,B8) -> 21 | F8: =_xlfn.XLOOKUP(B8,'Position Tracker'!E:E,'Position Tracker'!X:X,,0) -> 0.85 | G8: =COUNTIFS('Candidate Tracker'!D:D,B8,'Candidate Tracker'!W:W,"Screening Stage") -> 1 | H8: =COUNTIFS('Candidate Tracker'!D:D,B8,'Candidate Tracker'!W:W,"L1 Stage") -> 1 | I8: =COUNTIFS('Candidate Tracker'!D:D,B8,'Candidate Tracker'!W:W,"L2 Stage") -> 0 | J8: =COUNTIFS('Candidate Tracker'!D:D,B8,'Candidate Tracker'!W:W,"Offer Stage") -> 0 | K8: =_xlfn.XLOOKUP(B8,'Position Tracker'!E:E,'Position Tracker'!J:J,,0) -> Joined | L8: =_xlfn.XLOOKUP(B8,'Position Tracker'!E:E,'Position Tracker'!Y:Y,,0) -> RL1
A9: =_xlfn.XLOOKUP(B9,'Position Tracker'!E:E,'Position Tracker'!B:B,,0) -> 45476 | B9: KAM - AM | C9: =NETWORKDAYS.INTL(A9,TODAY(),1,'HELPER(Dont Delete)'!A:A)-9 -> 360 | D9: =VLOOKUP(B9,'Position Tracker'!E:F,3,0) -> #REF! | E9: =COUNTIFS('Candidate Tracker'!D:D,B9) -> 8 | F9: =_xlfn.XLOOKUP(B9,'Position Tracker'!E:E,'Position Tracker'!X:X,,0) -> 0.875 | G9: =COUNTIFS('Candidate Tracker'!D:D,B9,'Candidate Tracker'!W:W,"Screening Stage") -> 0 | H9: =COUNTIFS('Candidate Tracker'!D:D,B9,'Candidate Tracker'!W:W,"L1 Stage") -> 2 | I9: =COUNTIFS('Candidate Tracker'!D:D,B9,'Candidate Tracker'!W:W,"L2 Stage") -> 0 | J9: =COUNTIFS('Candidate Tracker'!D:D,B9,'Candidate Tracker'!W:W,"Offer Stage") -> 0 | K9: =_xlfn.XLOOKUP(B9,'Position Tracker'!E:E,'Position Tracker'!J:J,,0) -> Hold | L9: =_xlfn.XLOOKUP(B9,'Position Tracker'!E:E,'Position Tracker'!Y:Y,,0) -> RL1
A10: =_xlfn.XLOOKUP(B10,'Position Tracker'!E:E,'Position Tracker'!B:B,,0) -> 45548 | B10: KAM_ Steel (Hyderabad) | C10: =NETWORKDAYS.INTL(A10,TODAY(),1,'HELPER(Dont Delete)'!A:A) -> 321 | D10: =VLOOKUP(B10,'Position Tracker'!E:F,3,0) -> #REF! | E10: =COUNTIFS('Candidate Tracker'!D:D,B10) -> 6 | F10: =_xlfn.XLOOKUP(B10,'Position Tracker'!E:E,'Position Tracker'!X:X,,0) -> 100% | G10: =COUNTIFS('Candidate Tracker'!D:D,B10,'Candidate Tracker'!W:W,"Screening Stage") -> 2 | H10: =COUNTIFS('Candidate Tracker'!D:D,B10,'Candidate Tracker'!W:W,"L1 Stage") -> 1 | I10: =COUNTIFS('Candidate Tracker'!D:D,B10,'Candidate Tracker'!W:W,"L2 Stage") -> 0 | J10: =COUNTIFS('Candidate Tracker'!D:D,B10,'Candidate Tracker'!W:W,"Offer Stage") -> 0 | K10: =_xlfn.XLOOKUP(B10,'Position Tracker'!E:E,'Position Tracker'!J:J,,0) -> Joined | L10: =_xlfn.XLOOKUP(B10,'Position Tracker'!E:E,'Position Tracker'!Y:Y,,0) -> RL1
A11: =_xlfn.XLOOKUP(B11,'Position Tracker'!E:E,'Position Tracker'!B:B,,0) -> 45551 | B11: Supply Chain Manager | C11: =NETWORKDAYS.INTL(A11,TODAY(),1,'HELPER(Dont Delete)'!A:A) -> 320 | D11: =VLOOKUP(B11,'Position Tracker'!E:F,3,0) -> #REF! | E11: =COUNTIFS('Candidate Tracker'!D:D,B11) -> 14 | F11: =_xlfn.XLOOKUP(B11,'Position Tracker'!E:E,'Position Tracker'!X:X,,0) -> 0.78571429 | G11: =COUNTIFS('Candidate Tracker'!D:D,B11,'Candidate Tracker'!W:W,"Screening Stage") -> 0 | H11: =COUNTIFS('Candidate Tracker'!D:D,B11,'Candidate Tracker'!W:W,"L1 Stage") -> 0 | I11: =COUNTIFS('Candidate Tracker'!D:D,B11,'Candidate Tracker'!W:W,"L2 Stage") -> 0 | J11: =COUNTIFS('Candidate Tracker'!D:D,B11,'Candidate Tracker'!W:W,"Offer Stage") -> 0 | K11: =_xlfn.XLOOKUP(B11,'Position Tracker'!E:E,'Position Tracker'!J:J,,0) -> Joined | L11: =_xlfn.XLOOKUP(B11,'Position Tracker'!E:E,'Position Tracker'!Y:Y,,0) -> RL2
A12: =_xlfn.XLOOKUP(B12,'Position Tracker'!E:E,'Position Tracker'!B:B,,0) -> 45593 | B12: Plant Head | C12: =NETWORKDAYS.INTL(A12,TODAY(),1,'HELPER(Dont Delete)'!A:A) -> 295 | D12: =VLOOKUP(B12,'Position Tracker'!E:F,3,0) -> #REF! | E12: =COUNTIFS('Candidate Tracker'!D:D,B12) -> 8 | F12: =_xlfn.XLOOKUP(B12,'Position Tracker'!E:E,'Position Tracker'!X:X,,0) -> 0.875 | G12: =COUNTIFS('Candidate Tracker'!D:D,B12,'Candidate Tracker'!W:W,"Screening Stage") -> 0 | H12: =COUNTIFS('Candidate Tracker'!D:D,B12,'Candidate Tracker'!W:W,"L1 Stage") -> 4 | I12: =COUNTIFS('Candidate Tracker'!D:D,B12,'Candidate Tracker'!W:W,"L2 Stage") -> 0 | J12: =COUNTIFS('Candidate Tracker'!D:D,B12,'Candidate Tracker'!W:W,"Offer Stage") -> 0 | K12: =_xlfn.XLOOKUP(B12,'Position Tracker'!E:E,'Position Tracker'!J:J,,0) -> Hold | L12: =_xlfn.XLOOKUP(B12,'Position Tracker'!E:E,'Position Tracker'!Y:Y,,0) -> RL3
A13: =_xlfn.XLOOKUP(B13,'Position Tracker'!E:E,'Position Tracker'!B:B,,0) -> 45629 | B13: Electrical Manager Maintenance | C13: =NETWORKDAYS.INTL(A13,TODAY(),1,'HELPER(Dont Delete)'!A:A) -> 272 | D13: =VLOOKUP(B13,'Position Tracker'!E:F,3,0) -> #REF! | E13: =COUNTIFS('Candidate Tracker'!D:D,B13) -> 8 | F13: =_xlfn.XLOOKUP(B13,'Position Tracker'!E:E,'Position Tracker'!X:X,,0) -> 0.875 | G13: =COUNTIFS('Candidate Tracker'!D:D,B13,'Candidate Tracker'!W:W,"Screening Stage") -> 0 | H13: =COUNTIFS('Candidate Tracker'!D:D,B13,'Candidate Tracker'!W:W,"L1 Stage") -> 0 | I13: =COUNTIFS('Candidate Tracker'!D:D,B13,'Candidate Tracker'!W:W,"L2 Stage") -> 0 | J13: =COUNTIFS('Candidate Tracker'!D:D,B13,'Candidate Tracker'!W:W,"Offer Stage") -> 0 | K13: =_xlfn.XLOOKUP(B13,'Position Tracker'!E:E,'Position Tracker'!J:J,,0) -> Joined | L13: =_xlfn.XLOOKUP(B13,'Position Tracker'!E:E,'Position Tracker'!Y:Y,,0) -> RL2
A14: =_xlfn.XLOOKUP(B14,'Position Tracker'!E:E,'Position Tracker'!B:B,,0) -> 45628 | B14: KAM_ Steel (Chennai) | C14: =NETWORKDAYS.INTL(A14,TODAY(),1,'HELPER(Dont Delete)'!A:A) -> 273 | D14: =VLOOKUP(B14,'Position Tracker'!E:F,3,0) -> #REF! | E14: =COUNTIFS('Candidate Tracker'!D:D,B14) -> 4 | F14: =_xlfn.XLOOKUP(B14,'Position Tracker'!E:E,'Position Tracker'!X:X,,0) -> 0.75 | G14: =COUNTIFS('Candidate Tracker'!D:D,B14,'Candidate Tracker'!W:W,"Screening Stage") -> 0 | H14: =COUNTIFS('Candidate Tracker'!D:D,B14,'Candidate Tracker'!W:W,"L1 Stage") -> 1 | I14: =COUNTIFS('Candidate Tracker'!D:D,B14,'Candidate Tracker'!W:W,"L2 Stage") -> 0 | J14: =COUNTIFS('Candidate Tracker'!D:D,B14,'Candidate Tracker'!W:W,"Offer Stage") -> 0 | K14: =_xlfn.XLOOKUP(B14,'Position Tracker'!E:E,'Position Tracker'!J:J,,0) -> Joined | L14: =_xlfn.XLOOKUP(B14,'Position Tracker'!E:E,'Position Tracker'!Y:Y,,0) -> RL1
A15: =_xlfn.XLOOKUP(B15,'Position Tracker'!E:E,'Position Tracker'!B:B,,0) -> 45750 | B15: Design Executive | C15: =NETWORKDAYS.INTL(A15,TODAY(),1,'HELPER(Dont Delete)'!A:A) -> 187 | D15: =VLOOKUP(B15,'Position Tracker'!E:F,3,0) -> #REF! | E15: =COUNTIFS('Candidate Tracker'!D:D,B15) -> 25 | F15: =_xlfn.XLOOKUP(B15,'Position Tracker'!E:E,'Position Tracker'!X:X,,0) -> 0.48 | G15: =COUNTIFS('Candidate Tracker'!D:D,B15,'Candidate Tracker'!W:W,"Screening Stage") -> 0 | H15: =COUNTIFS('Candidate Tracker'!D:D,B15,'Candidate Tracker'!W:W,"L1 Stage") -> 5 | I15: =COUNTIFS('Candidate Tracker'!D:D,B15,'Candidate Tracker'!W:W,"L2 Stage") -> 0 | J15: =COUNTIFS('Candidate Tracker'!D:D,B15,'Candidate Tracker'!W:W,"Offer Stage") -> 0 | K15: =_xlfn.XLOOKUP(B15,'Position Tracker'!E:E,'Position Tracker'!J:J,,0) -> Hold | L15: =_xlfn.XLOOKUP(B15,'Position Tracker'!E:E,'Position Tracker'!Y:Y,,0) -> RL1
A16: =_xlfn.XLOOKUP(B16,'Position Tracker'!E:E,'Position Tracker'!B:B,,0) -> 45659 | B16: Mechanical Maintenance | C16: =NETWORKDAYS.INTL(A16,TODAY(),1,'HELPER(Dont Delete)'!A:A) -> 252 | D16: =VLOOKUP(B16,'Position Tracker'!E:F,3,0) -> #REF! | E16: =COUNTIFS('Candidate Tracker'!D:D,B16) -> 7 | F16: =_xlfn.XLOOKUP(B16,'Position Tracker'!E:E,'Position Tracker'!X:X,,0) -> 0.85714286 | G16: =COUNTIFS('Candidate Tracker'!D:D,B16,'Candidate Tracker'!W:W,"Screening Stage") -> 0 | H16: =COUNTIFS('Candidate Tracker'!D:D,B16,'Candidate Tracker'!W:W,"L1 Stage") -> 1 | I16: =COUNTIFS('Candidate Tracker'!D:D,B16,'Candidate Tracker'!W:W,"L2 Stage") -> 0 | J16: =COUNTIFS('Candidate Tracker'!D:D,B16,'Candidate Tracker'!W:W,"Offer Stage") -> 2 | K16: =_xlfn.XLOOKUP(B16,'Position Tracker'!E:E,'Position Tracker'!J:J,,0) -> Joined | L16: =_xlfn.XLOOKUP(B16,'Position Tracker'!E:E,'Position Tracker'!Y:Y,,0) -> RL1
A17: =_xlfn.XLOOKUP(B17,'Position Tracker'!E:E,'Position Tracker'!B:B,,0) -> 45685 | B17: Electrical Maintenance AM | C17: =NETWORKDAYS.INTL(A17,TODAY(),1,'HELPER(Dont Delete)'!A:A) -> 234 | D17: =VLOOKUP(B17,'Position Tracker'!E:F,3,0) -> #REF! | E17: =COUNTIFS('Candidate Tracker'!D:D,B17) -> 20 | F17: =_xlfn.XLOOKUP(B17,'Position Tracker'!E:E,'Position Tracker'!X:X,,0) -> 0.75 | G17: =COUNTIFS('Candidate Tracker'!D:D,B17,'Candidate Tracker'!W:W,"Screening Stage") -> 0 | H17: =COUNTIFS('Candidate Tracker'!D:D,B17,'Candidate Tracker'!W:W,"L1 Stage") -> 0 | I17: =COUNTIFS('Candidate Tracker'!D:D,B17,'Candidate Tracker'!W:W,"L2 Stage") -> 0 | J17: =COUNTIFS('Candidate Tracker'!D:D,B17,'Candidate Tracker'!W:W,"Offer Stage") -> 1 | K17: =_xlfn.XLOOKUP(B17,'Position Tracker'!E:E,'Position Tracker'!J:J,,0) -> Joined | L17: =_xlfn.XLOOKUP(B17,'Position Tracker'!E:E,'Position Tracker'!Y:Y,,0) -> RL1
A18: =_xlfn.XLOOKUP(B18,'Position Tracker'!E:E,'Position Tracker'!B:B,,0) -> 45743 | B18: AM Purchase | C18: =NETWORKDAYS.INTL(A18,TODAY(),1,'HELPER(Dont Delete)'!A:A) -> 192 | D18: =VLOOKUP(B18,'Position Tracker'!E:F,3,0) -> #REF! | E18: =COUNTIFS('Candidate Tracker'!D:D,B18) -> 9 | F18: =_xlfn.XLOOKUP(B18,'Position Tracker'!E:E,'Position Tracker'!X:X,,0) -> 0.88888889 | G18: =COUNTIFS('Candidate Tracker'!D:D,B18,'Candidate Tracker'!W:W,"Screening Stage") -> 0 | H18: =COUNTIFS('Candidate Tracker'!D:D,B18,'Candidate Tracker'!W:W,"L1 Stage") -> 1 | I18: =COUNTIFS('Candidate Tracker'!D:D,B18,'Candidate Tracker'!W:W,"L2 Stage") -> 0 | J18: =COUNTIFS('Candidate Tracker'!D:D,B18,'Candidate Tracker'!W:W,"Offer Stage") -> 0 | K18: =_xlfn.XLOOKUP(B18,'Position Tracker'!E:E,'Position Tracker'!J:J,,0) -> Joined | L18: =_xlfn.XLOOKUP(B18,'Position Tracker'!E:E,'Position Tracker'!Y:Y,,0) -> RL1
A19: =_xlfn.XLOOKUP(B19,'Position Tracker'!E:E,'Position Tracker'!B:B,,0) -> 45743 | B19: Manager mechanical Maintenance | C19: =NETWORKDAYS.INTL(A19,TODAY(),1,'HELPER(Dont Delete)'!A:A) -> 192 | D19: =VLOOKUP(B19,'Position Tracker'!E:F,3,0) -> #REF! | E19: =COUNTIFS('Candidate Tracker'!D:D,B19) -> 7 | F19: =_xlfn.XLOOKUP(B19,'Position Tracker'!E:E,'Position Tracker'!X:X,,0) -> 0.14285714 | G19: =COUNTIFS('Candidate Tracker'!D:D,B19,'Candidate Tracker'!W:W,"Screening Stage") -> 0 | H19: =COUNTIFS('Candidate Tracker'!D:D,B19,'Candidate Tracker'!W:W,"L1 Stage") -> 1 | I19: =COUNTIFS('Candidate Tracker'!D:D,B19,'Candidate Tracker'!W:W,"L2 Stage") -> 0 | J19: =COUNTIFS('Candidate Tracker'!D:D,B19,'Candidate Tracker'!W:W,"Offer Stage") -> 0 | K19: =_xlfn.XLOOKUP(B19,'Position Tracker'!E:E,'Position Tracker'!J:J,,0) -> Hold | L19: =_xlfn.XLOOKUP(B19,'Position Tracker'!E:E,'Position Tracker'!Y:Y,,0) -> RL1
A20: =_xlfn.XLOOKUP(B20,'Position Tracker'!E:E,'Position Tracker'!B:B,,0) -> 45742 | B20: Manager Design | C20: =NETWORKDAYS.INTL(A20,TODAY(),1,'HELPER(Dont Delete)'!A:A) -> 193 | D20: =VLOOKUP(B20,'Position Tracker'!E:F,3,0) -> #REF! | E20: =COUNTIFS('Candidate Tracker'!D:D,B20) -> 23 | F20: =_xlfn.XLOOKUP(B20,'Position Tracker'!E:E,'Position Tracker'!X:X,,0) -> 0.9047619 | G20: =COUNTIFS('Candidate Tracker'!D:D,B20,'Candidate Tracker'!W:W,"Screening Stage") -> 0 | H20: =COUNTIFS('Candidate Tracker'!D:D,B20,'Candidate Tracker'!W:W,"L1 Stage") -> 0 | I20: =COUNTIFS('Candidate Tracker'!D:D,B20,'Candidate Tracker'!W:W,"L2 Stage") -> 5 | J20: =COUNTIFS('Candidate Tracker'!D:D,B20,'Candidate Tracker'!W:W,"Offer Stage") -> 1 | K20: =_xlfn.XLOOKUP(B20,'Position Tracker'!E:E,'Position Tracker'!J:J,,0) -> Joined | L20: =_xlfn.XLOOKUP(B20,'Position Tracker'!E:E,'Position Tracker'!Y:Y,,0) -> RL1
A21: =_xlfn.XLOOKUP(B21,'Position Tracker'!E:E,'Position Tracker'!B:B,,0) -> 45743 | B21: AGM Finance | C21: =NETWORKDAYS.INTL(A21,TODAY(),1,'HELPER(Dont Delete)'!A:A) -> 192 | D21: =VLOOKUP(B21,'Position Tracker'!E:F,3,0) -> #REF! | E21: =COUNTIFS('Candidate Tracker'!D:D,B21) -> 3 | F21: =_xlfn.XLOOKUP(B21,'Position Tracker'!E:E,'Position Tracker'!X:X,,0) -> 0.66666667 | G21: =COUNTIFS('Candidate Tracker'!D:D,B21,'Candidate Tracker'!W:W,"Screening Stage") -> 0 | H21: =COUNTIFS('Candidate Tracker'!D:D,B21,'Candidate Tracker'!W:W,"L1 Stage") -> 0 | I21: =COUNTIFS('Candidate Tracker'!D:D,B21,'Candidate Tracker'!W:W,"L2 Stage") -> 3 | J21: =COUNTIFS('Candidate Tracker'!D:D,B21,'Candidate Tracker'!W:W,"Offer Stage") -> 0 | K21: =_xlfn.XLOOKUP(B21,'Position Tracker'!E:E,'Position Tracker'!J:J,,0) -> Internally Closed | L21: =_xlfn.XLOOKUP(B21,'Position Tracker'!E:E,'Position Tracker'!Y:Y,,0) -> RL3
... A31: =_xlfn.XLOOKUP(B31,'Position Tracker'!E:E,'Position Tracker'!B:B,,0) -> 45848 | B31: Quality Assurance (QA) Coordinator | C31: =NETWORKDAYS.INTL(A31,TODAY(),1,'HELPER(Dont Delete)'!A:A) -> 117 | D31: =VLOOKUP(B31,'Position Tracker'!E:F,3,0) -> #REF! | E31: =COUNTIFS('Candidate Tracker'!D:D,B31) -> 15 | F31: =_xlfn.XLOOKUP(B31,'Position Tracker'!E:E,'Position Tracker'!X:X,,0) -> 0.74074074 | G31: =COUNTIFS('Candidate Tracker'!D:D,B31,'Candidate Tracker'!W:W,"Screening Stage") -> 0 | H31: =COUNTIFS('Candidate Tracker'!D:D,B31,'Candidate Tracker'!W:W,"L1 Stage") -> 3 | I31: =COUNTIFS('Candidate Tracker'!D:D,B31,'Candidate Tracker'!W:W,"L2 Stage") -> 1 | J31: =COUNTIFS('Candidate Tracker'!D:D,B31,'Candidate Tracker'!W:W,"Offer Stage") -> 1 | K31: =_xlfn.XLOOKUP(B31,'Position Tracker'!E:E,'Position Tracker'!J:J,,0) -> Hold | L31: =_xlfn.XLOOKUP(B31,'Position Tracker'!E:E,'Position Tracker'!Y:Y,,0) -> RL1
A32: =_xlfn.XLOOKUP(B32,'Position Tracker'!E:E,'Position Tracker'!B:B,,0) -> 45848 | B32: Quality Assurance (QA) Lead | C32: =NETWORKDAYS.INTL(A32,TODAY(),1,'HELPER(Dont Delete)'!A:A) -> 117 | D32: =VLOOKUP(B32,'Position Tracker'!E:F,3,0) -> #REF! | E32: =COUNTIFS('Candidate Tracker'!D:D,B32) -> 7 | F32: =_xlfn.XLOOKUP(B32,'Position Tracker'!E:E,'Position Tracker'!X:X,,0) -> 0.57142857 | G32: =COUNTIFS('Candidate Tracker'!D:D,B32,'Candidate Tracker'!W:W,"Screening Stage") -> 0 | H32: =COUNTIFS('Candidate Tracker'!D:D,B32,'Candidate Tracker'!W:W,"L1 Stage") -> 1 | I32: =COUNTIFS('Candidate Tracker'!D:D,B32,'Candidate Tracker'!W:W,"L2 Stage") -> 0 | J32: =COUNTIFS('Candidate Tracker'!D:D,B32,'Candidate Tracker'!W:W,"Offer Stage") -> 1 | K32: =_xlfn.XLOOKUP(B32,'Position Tracker'!E:E,'Position Tracker'!J:J,,0) -> Offer Stage
A33: =_xlfn.XLOOKUP(B33,'Position Tracker'!E:E,'Position Tracker'!B:B,,0) -> 45848 | B33: Quality Control (QC) Coordinator | C33: =NETWORKDAYS.INTL(A33,TODAY(),1,'HELPER(Dont Delete)'!A:A) -> 117 | D33: =VLOOKUP(B33,'Position Tracker'!E:F,3,0) -> #REF! | E33: =COUNTIFS('Candidate Tracker'!D:D,B33) -> 27 | F33: =_xlfn.XLOOKUP(B33,'Position Tracker'!E:E,'Position Tracker'!X:X,,0) -> 0.72222222 | G33: =COUNTIFS('Candidate Tracker'!D:D,B33,'Candidate Tracker'!W:W,"Screening Stage") -> 0 | H33: =COUNTIFS('Candidate Tracker'!D:D,B33,'Candidate Tracker'!W:W,"L1 Stage") -> 7 | I33: =COUNTIFS('Candidate Tracker'!D:D,B33,'Candidate Tracker'!W:W,"L2 Stage") -> 0 | J33: =COUNTIFS('Candidate Tracker'!D:D,B33,'Candidate Tracker'!W:W,"Offer Stage") -> 7 | K33: =_xlfn.XLOOKUP(B33,'Position Tracker'!E:E,'Position Tracker'!J:J,,0) -> Offer Stage | L33: =_xlfn.XLOOKUP(B33,'Position Tracker'!E:E,'Position Tracker'!Y:Y,,0) -> RL1
A34: =_xlfn.XLOOKUP(B34,'Position Tracker'!E:E,'Position Tracker'!B:B,,0) -> 45910 | B34: Machining & Beam Welding | C34: =NETWORKDAYS.INTL(A34,TODAY(),1,'HELPER(Dont Delete)'!A:A) -> 73 | D34: =VLOOKUP(B34,'Position Tracker'!E:F,3,0) -> #REF! | E34: =COUNTIFS('Candidate Tracker'!D:D,B34) -> 18 | F34: =_xlfn.XLOOKUP(B34,'Position Tracker'!E:E,'Position Tracker'!X:X,,0) -> 0.72222222 | G34: =COUNTIFS('Candidate Tracker'!D:D,B34,'Candidate Tracker'!W:W,"Screening Stage") -> 0 | H34: =COUNTIFS('Candidate Tracker'!D:D,B34,'Candidate Tracker'!W:W,"L1 Stage") -> 3 | I34: =COUNTIFS('Candidate Tracker'!D:D,B34,'Candidate Tracker'!W:W,"L2 Stage") -> 0 | J34: =COUNTIFS('Candidate Tracker'!D:D,B34,'Candidate Tracker'!W:W,"Offer Stage") -> 4 | K34: =_xlfn.XLOOKUP(B34,'Position Tracker'!E:E,'Position Tracker'!J:J,,0) -> 1Hold/2joined | L34: =_xlfn.XLOOKUP(B34,'Position Tracker'!E:E,'Position Tracker'!Y:Y,,0) -> RL1
A35: =_xlfn.XLOOKUP(B35,'Position Tracker'!E:E,'Position Tracker'!B:B,,0) -> 45848 | B35: Manual Welding | C35: =NETWORKDAYS.INTL(A35,TODAY(),1,'HELPER(Dont Delete)'!A:A) -> 117 | D35: =VLOOKUP(B35,'Position Tracker'!E:F,3,0) -> #REF! | E35: =COUNTIFS('Candidate Tracker'!D:D,B35) -> 10 | F35: =_xlfn.XLOOKUP(B35,'Position Tracker'!E:E,'Position Tracker'!X:X,,0) -> 0.75 | G35: =COUNTIFS('Candidate Tracker'!D:D,B35,'Candidate Tracker'!W:W,"Screening Stage") -> 2 | H35: =COUNTIFS('Candidate Tracker'!D:D,B35,'Candidate Tracker'!W:W,"L1 Stage") -> 0 | I35: =COUNTIFS('Candidate Tracker'!D:D,B35,'Candidate Tracker'!W:W,"L2 Stage") -> 0 | J35: =COUNTIFS('Candidate Tracker'!D:D,B35,'Candidate Tracker'!W:W,"Offer Stage") -> 4 | K35: =_xlfn.XLOOKUP(B35,'Position Tracker'!E:E,'Position Tracker'!J:J,,0) -> 1Hold/2joined | L35: =_xlfn.XLOOKUP(B35,'Position Tracker'!E:E,'Position Tracker'!Y:Y,,0) -> RL1
A36: =_xlfn.XLOOKUP(B36,'Position Tracker'!E:E,'Position Tracker'!B:B,,0) -> 45848 | B36: Shot Blasting & Painting | C36: =NETWORKDAYS.INTL(A36,TODAY(),1,'HELPER(Dont Delete)'!A:A) -> 117 | D36: =VLOOKUP(B36,'Position Tracker'!E:F,3,0) -> #REF! | E36: =COUNTIFS('Candidate Tracker'!D:D,B36) -> 18 | F36: =_xlfn.XLOOKUP(B36,'Position Tracker'!E:E,'Position Tracker'!X:X,,0) -> 100% | G36: =COUNTIFS('Candidate Tracker'!D:D,B36,'Candidate Tracker'!W:W,"Screening Stage") -> 0 | H36: =COUNTIFS('Candidate Tracker'!D:D,B36,'Candidate Tracker'!W:W,"L1 Stage") -> 1 | I36: =COUNTIFS('Candidate Tracker'!D:D,B36,'Candidate Tracker'!W:W,"L2 Stage") -> 0 | J36: =COUNTIFS('Candidate Tracker'!D:D,B36,'Candidate Tracker'!W:W,"Offer Stage") -> 2 | K36: =_xlfn.XLOOKUP(B36,'Position Tracker'!E:E,'Position Tracker'!J:J,,0) -> Offer stage | L36: =_xlfn.XLOOKUP(B36,'Position Tracker'!E:E,'Position Tracker'!Y:Y,,0) -> RL1
A37: =_xlfn.XLOOKUP(B37,'Position Tracker'!E:E,'Position Tracker'!B:B,,0) -> 45848 | B37: Detailer | C37: =NETWORKDAYS.INTL(A37,TODAY(),1,'HELPER(Dont Delete)'!A:A) -> 117 | D37: =VLOOKUP(B37,'Position Tracker'!E:F,3,0) -> #REF! | E37: =COUNTIFS('Candidate Tracker'!D:D,B37) -> 3 | F37: =_xlfn.XLOOKUP(B37,'Position Tracker'!E:E,'Position Tracker'!X:X,,0) -> 0.8 | G37: =COUNTIFS('Candidate Tracker'!D:D,B37,'Candidate Tracker'!W:W,"Screening Stage") -> 2 | H37: =COUNTIFS('Candidate Tracker'!D:D,B37,'Candidate Tracker'!W:W,"L1 Stage") -> 0 | I37: =COUNTIFS('Candidate Tracker'!D:D,B37,'Candidate Tracker'!W:W,"L2 Stage") -> 0 | J37: =COUNTIFS('Candidate Tracker'!D:D,B37,'Candidate Tracker'!W:W,"Offer Stage") -> 0 | K37: =_xlfn.XLOOKUP(B37,'Position Tracker'!E:E,'Position Tracker'!J:J,,0) -> Internally Closed | L37: =_xlfn.XLOOKUP(B37,'Position Tracker'!E:E,'Position Tracker'!Y:Y,,0) -> RL1
A38: =_xlfn.XLOOKUP(B38,'Position Tracker'!E:E,'Position Tracker'!B:B,,0) -> 45848 | B38: Welding Expert | C38: =NETWORKDAYS.INTL(A38,TODAY(),1,'HELPER(Dont Delete)'!A:A) -> 117 | D38: =VLOOKUP(B38,'Position Tracker'!E:F,3,0) -> #REF! | E38: =COUNTIFS('Candidate Tracker'!D:D,B38) -> 5 | F38: =_xlfn.XLOOKUP(B38,'Position Tracker'!E:E,'Position Tracker'!X:X,,0) -> 0 | G38: =COUNTIFS('Candidate Tracker'!D:D,B38,'Candidate Tracker'!W:W,"Screening Stage") -> 0 | H38: =COUNTIFS('Candidate Tracker'!D:D,B38,'Candidate Tracker'!W:W,"L1 Stage") -> 2 | I38: =COUNTIFS('Candidate Tracker'!D:D,B38,'Candidate Tracker'!W:W,"L2 Stage") -> 1 | J38: =COUNTIFS('Candidate Tracker'!D:D,B38,'Candidate Tracker'!W:W,"Offer Stage") -> 0 | K38: =_xlfn.XLOOKUP(B38,'Position Tracker'!E:E,'Position Tracker'!J:J,,0) -> Hold | L38: =_xlfn.XLOOKUP(B38,'Position Tracker'!E:E,'Position Tracker'!Y:Y,,0) -> RL2
A39: =_xlfn.XLOOKUP(B39,'Position Tracker'!E:E,'Position Tracker'!B:B,,0) -> 45859 | B39: Plant Project Lead | C39: =NETWORKDAYS.INTL(A39,TODAY(),1,'HELPER(Dont Delete)'!A:A) -> 110 | D39: =VLOOKUP(B39,'Position Tracker'!E:F,3,0) -> #REF! | E39: =COUNTIFS('Candidate Tracker'!D:D,B39) -> 0 | F39: =_xlfn.XLOOKUP(B39,'Position Tracker'!E:E,'Position Tracker'!X:X,,0) -> 0.55555556 | G39: =COUNTIFS('Candidate Tracker'!D:D,B39,'Candidate Tracker'!W:W,"Screening Stage") -> 0 | H39: =COUNTIFS('Candidate Tracker'!D:D,B39,'Candidate Tracker'!W:W,"L1 Stage") -> 0 | I39: =COUNTIFS('Candidate Tracker'!D:D,B39,'Candidate Tracker'!W:W,"L2 Stage") -> 0 | J39: =COUNTIFS('Candidate Tracker'!D:D,B39,'Candidate Tracker'!W:W,"Offer Stage") -> 0 | K39: =_xlfn.XLOOKUP(B39,'Position Tracker'!E:E,'Position Tracker'!J:J,,0) -> Cancelled | L39: =_xlfn.XLOOKUP(B39,'Position Tracker'!E:E,'Position Tracker'!Y:Y,,0) -> RL2
A40: =_xlfn.XLOOKUP(B40,'Position Tracker'!E:E,'Position Tracker'!B:B,,0) -> 45860 | B40: Sales (new) | C40: =NETWORKDAYS.INTL(A40,TODAY(),1,'HELPER(Dont Delete)'!A:A) -> 109 | D40: =VLOOKUP(B40,'Position Tracker'!E:F,3,0) -> #REF! | E40: =COUNTIFS('Candidate Tracker'!D:D,B40) -> 0 | F40: =_xlfn.XLOOKUP(B40,'Position Tracker'!E:E,'Position Tracker'!X:X,,0) -> 0 | G40: =COUNTIFS('Candidate Tracker'!D:D,B40,'Candidate Tracker'!W:W,"Screening Stage") -> 0 | H40: =COUNTIFS('Candidate Tracker'!D:D,B40,'Candidate Tracker'!W:W,"L1 Stage") -> 0 | I40: =COUNTIFS('Candidate Tracker'!D:D,B40,'Candidate Tracker'!W:W,"L2 Stage") -> 0 | J40: =COUNTIFS('Candidate Tracker'!D:D,B40,'Candidate Tracker'!W:W,"Offer Stage") -> 0 | K40: =_xlfn.XLOOKUP(B40,'Position Tracker'!E:E,'Position Tracker'!J:J,,0) -> Hold | L40: =_xlfn.XLOOKUP(B40,'Position Tracker'!E:E,'Position Tracker'!Y:Y,,0) -> RL3
A41: =_xlfn.XLOOKUP(B41,'Position Tracker'!E:E,'Position Tracker'!B:B,,0) -> 45873 | B41: Electrical Manager | C41: =NETWORKDAYS.INTL(A41,TODAY(),1,'HELPER(Dont Delete)'!A:A) -> 100 | D41: =VLOOKUP(B41,'Position Tracker'!E:F,3,0) -> #REF! | E41: =COUNTIFS('Candidate Tracker'!D:D,B41) -> 3 | F41: =_xlfn.XLOOKUP(B41,'Position Tracker'!E:E,'Position Tracker'!X:X,,0) -> 0.5 | G41: =COUNTIFS('Candidate Tracker'!D:D,B41,'Candidate Tracker'!W:W,"Screening Stage") -> 0 | H41: =COUNTIFS('Candidate Tracker'!D:D,B41,'Candidate Tracker'!W:W,"L1 Stage") -> 0 | I41: =COUNTIFS('Candidate Tracker'!D:D,B41,'Candidate Tracker'!W:W,"L2 Stage") -> 0 | J41: =COUNTIFS('Candidate Tracker'!D:D,B41,'Candidate Tracker'!W:W,"Offer Stage") -> 0 | K41: =_xlfn.XLOOKUP(B41,'Position Tracker'!E:E,'Position Tracker'!J:J,,0) -> Hold | L41: =_xlfn.XLOOKUP(B41,'Position Tracker'!E:E,'Position Tracker'!Y:Y,,0) -> RL1
A42: =_xlfn.XLOOKUP(B42,'Position Tracker'!E:E,'Position Tracker'!B:B,,0) -> 45881 | B42: Plant Project Incharge | C42: =NETWORKDAYS.INTL(A42,TODAY(),1,'HELPER(Dont Delete)'!A:A) -> 94 | D42: =VLOOKUP(B42,'Position Tracker'!E:F,3,0) -> #REF! | E42: =COUNTIFS('Candidate Tracker'!D:D,B42) -> 4 | F42: =_xlfn.XLOOKUP(B42,'Position Tracker'!E:E,'Position Tracker'!X:X,,0) -> 0.55555556 | G42: =COUNTIFS('Candidate Tracker'!D:D,B42,'Candidate Tracker'!W:W,"Screening Stage") -> 0 | H42: =COUNTIFS('Candidate Tracker'!D:D,B42,'Candidate Tracker'!W:W,"L1 Stage") -> 1 | I42: =COUNTIFS('Candidate Tracker'!D:D,B42,'Candidate Tracker'!W:W,"L2 Stage") -> 0 | J42: =COUNTIFS('Candidate Tracker'!D:D,B42,'Candidate Tracker'!W:W,"Offer Stage") -> 0 | K42: =_xlfn.XLOOKUP(B42,'Position Tracker'!E:E,'Position Tracker'!J:J,,0) -> Hold | L42: =_xlfn.XLOOKUP(B42,'Position Tracker'!E:E,'Position Tracker'!Y:Y,,0) -> RL1
B43: GRAND TOTAL | C43: =SUM(C2:C16) -> 5342 | D43: =SUM(D2:D16) -> #REF! | E43: =SUM(E2:E16) -> 172 | F43: =AVERAGEA(F2:F16) -> 0.63462482 | G43: =SUM(G2:G16) -> 3 | H43: =SUM(H2:H16) -> 15 | I43: =SUM(I2:I16) -> 0 | J43: =SUM(J2:J16) -> 2
A47: Stages | B47: Total CV | C47: Avg Time(Days) | E47: OVERALL FTR%
A48: Screening | B48: =COUNTIFS('Candidate Tracker'!W:W,"Screening Stage") -> 10 | C48: =AVERAGE('Candidate Tracker'!AP:AP) -> 5.0429185 | F48: Upto Dec | G48: Jan | H48: feb | I48: March | J48: April | K48: May | L48: June | M48: July | N48: August
A49: L1 Stage | B49: =COUNTIFS('Candidate Tracker'!W:W,"L1 Stage") -> 48 | C49: =AVERAGE('Candidate Tracker'!AQ:AQ) -> 4.1344538 | E49: Screening Pending | F49: =COUNTIFS('Candidate Tracker'!C:C, "<=31/12/2023", 'Candidate Tracker'!V:V, "<>Screening Pending",'Candidate Tracker'!V:V, "<>") -> 8 | G49: =COUNTIFS('Candidate Tracker'!C:C, ">=1/1/2024", 'Candidate Tracker'!C:C, "<=31/1/2024", 'Candidate Tracker'!V:V, "<>Screening Pending",'Candidate Tracker'!V:V, "<>") -> 4 | H49: =COUNTIFS('Candidate Tracker'!C:C, ">=1/2/2024", 'Candidate Tracker'!C:C, "<=28/2/2024", 'Candidate Tracker'!V:V, "<>Screening Pending",'Candidate Tracker'!V:V, "<>") -> 5 | I49: =COUNTIFS('Candidate Tracker'!C:C, ">=1/3/2024", 'Candidate Tracker'!C:C, "<=31/3/2024", 'Candidate Tracker'!V:V, "<>Screening Pending",'Candidate Tracker'!V:V, "<>") -> 21 | J49: =COUNTIFS('Candidate Tracker'!C:C, ">=1/4/2024", 'Candidate Tracker'!C:C, "<=30/4/2024", 'Candidate Tracker'!V:V, "<>Screening Pending",'Candidate Tracker'!V:V, "<>") -> 25 | K49: =COUNTIFS('Candidate Tracker'!C:C, ">=1/5/2024", 'Candidate Tracker'!C:C, "<=31/5/2024", 'Candidate Tracker'!V:V, "<>Screening Pending",'Candidate Tracker'!V:V, "<>") -> 3 | L49: =COUNTIFS('Candidate Tracker'!C:C, ">=1/6/2024", 'Candidate Tracker'!C:C, "<=30/6/2024", 'Candidate Tracker'!V:V, "<>Screening Pending",'Candidate Tracker'!V:V, "<>") -> 7 | M49: =COUNTIFS('Candidate Tracker'!C:C, ">=1/7/2024", 'Candidate Tracker'!C:C, "<=31/7/2024", 'Candidate Tracker'!V:V, "<>Screening Pending",'Candidate Tracker'!V:V, "<>") -> 10 | N49: =COUNTIFS('Candidate Tracker'!C:C, ">=1/8/2024", 'Candidate Tracker'!C:C, "<=30/8/2024", 'Candidate Tracker'!V:V, "<>Screening Pending",'Candidate Tracker'!V:V, "<>") -> 11
A50: L2 Stage | B50: =COUNTIFS('Candidate Tracker'!W:W,"L2 Stage") -> 24 | C50: =AVERAGE('Candidate Tracker'!AR:AR) -> 10.09375 | E50: Reject | F50: =COUNTIFS('Candidate Tracker'!C:C, "<=31/12/2023", 'Candidate Tracker'!V:V, "Screen Reject") -> 0 | G50: =COUNTIFS('Candidate Tracker'!C:C, ">=1/1/2024", 'Candidate Tracker'!C:C, "<=31/1/2024", 'Candidate Tracker'!V:V, "Screen Reject") -> 1 | H50: =COUNTIFS('Candidate Tracker'!C:C, ">=1/2/2024", 'Candidate Tracker'!C:C, "<=28/2/2024", 'Candidate Tracker'!V:V, "Screen Reject") -> 0 | I50: =COUNTIFS('Candidate Tracker'!C:C, ">=1/3/2024", 'Candidate Tracker'!C:C, "<=31/3/2024", 'Candidate Tracker'!V:V, "Screen Reject") -> 3 | J50: =COUNTIFS('Candidate Tracker'!C:C, ">=1/4/2024", 'Candidate Tracker'!C:C, "<=30/4/2024", 'Candidate Tracker'!V:V, "Screen Reject") -> 7 | K50: =COUNTIFS('Candidate Tracker'!C:C, ">=1/5/2024", 'Candidate Tracker'!C:C, "<=31/5/2024", 'Candidate Tracker'!V:V, "Screen Reject") -> 3 | L50: =COUNTIFS('Candidate Tracker'!C:C, ">=1/6/2024", 'Candidate Tracker'!C:C, "<=30/6/2024", 'Candidate Tracker'!V:V, "Screen Reject") -> 0 | M50: =COUNTIFS('Candidate Tracker'!C:C, ">=1/7/2024", 'Candidate Tracker'!C:C, "<=31/7/2024", 'Candidate Tracker'!V:V, "Screen Reject") -> 2 | N50: =COUNTIFS('Candidate Tracker'!C:C, ">=1/8/2024", 'Candidate Tracker'!C:C, "<=30/8/2024", 'Candidate Tracker'!V:V, "Screen Reject") -> 1
E51: Minus | F51: =F49-F50 -> 8 | G51: =G49-G50 -> 3 | H51: =H49-H50 -> 5 | I51: =I49-I50 -> 18 | J51: =J49-J50 -> 18 | K51: =K49-K50 -> 0 | L51: =L49-L50 -> 7 | M51: =M49-M50 -> 8 | N51: =N49-N50 -> 10
E52: FTR% | F52: =IFERROR(F51/F49,0) -> 1 | G52: =IFERROR(G51/G49,0) -> 0.75 | H52: =IFERROR(H51/H49,0) -> 1 | I52: =IFERROR(I51/I49,0) -> 0.85714286 | J52: =IFERROR(J51/J49,0) -> 0.72 | K52: =IFERROR(K51/K49,0) -> 0 | L52: =IFERROR(L51/L49,0) -> 1 | M52: =IFERROR(M51/M49,0) -> 0.8 | N52: =IFERROR(N51/N49,0) -> 0.90909091
A53: Aging Bucket | B53: Count
A54: 0-30 | B54: =COUNTIFS('Position Tracker'!D:D,Dashboard!A54) -> 0
A55: 31-45 | B55: =COUNTIFS('Position Tracker'!D:D,Dashboard!A55) -> 0
A56: 46-60 | B56: =COUNTIFS('Position Tracker'!D:D,Dashboard!A56) -> 2
A57: 61-75 | B57: =COUNTIFS('Position Tracker'!D:D,Dashboard!A57) -> 1
A58: 76-90 | B58: =COUNTIFS('Position Tracker'!D:D,Dashboard!A58) -> 0
A59: 91-105 | B59: =COUNTIFS('Position Tracker'!D:D,Dashboard!A59) -> 0
A60: 106-120 | B60: =COUNTIFS('Position Tracker'!D:D,Dashboard!A60) -> 0
A61: 120+ | B61: =COUNTIFS('Position Tracker'!D:D,Dashboard!A61) -> 0

Sheet HELPER(Dont Delete)
A2: 44927
A3: 44952
A4: 44993
A5: 45015
A6: 45020
A7: 45023
A8: 45038
A9: 45051
A10: 45106
A11: 45136
A12: 45153
A13: 45176
... A84: 45651

Sheet Contract
A1: CTC Range | B1: Opening Fee | C1: Closing Fee (Taggd Source) | D1: Other Source
A2: 800000 To 1200000 | B2: 27000 | C2: 4.85% Of Total CTC less than 27000 | D2: 0
A3: 1200000 To 1800000 | B3: 27000 | C3: 4.85% Of Total CTC less than 27000 | D3: 5050
A4: 1800000 To 3000000 | B4: 27000 | C4: 4.85% Of Total CTC less than 27000 | D4: 11800
A5: 3000000 To 5000000 | B5: 27000 | C5: 6.50% Of Total CTC less than 27000 | D5: 11800
A6: 5000000 To 6000000 | B6: 27000 | C6: 7% Of Total CTC less than 27000 | D6: 11800
A7: 6000000 T0 8000000 | C7: 10.50% Of Total CTC
A8: 8000000 T0 10000000 | C8: 13% Of Total CTC

Sheet Sheet1
B1: Role Name | C1: Funnel | D1: Funnel to be added
B2: Electrical Maintenance AM | C2: 5 | D2: 0
B3: Manager Design | C3: 1 | D3: 4
B4: Manager QA | C4: 4 | D4: 1
B5: DGM Sales | C5: Meeting with HM pending | D5: NA
B6: Project Head | C6: 0 | D6: 5
B7: Project Manager | C7: 0 | D7: 5
B8: Manager Purchase | C8: 3 | D8: 0
B9: Manager PPC | C9: 4 | D9: 1
B10: Plant Head (New) | C10: 2 | D10: 3
B11: Executive- Design | C11: 1 | D11: 4
