Workbook
Name Pivot: OFFSET('Positions Tracker'!$A$1,0,0,COUNTA('Positions Tracker'!A:A),COUNTA('Positions Tracker'!1048575:1048575))
Name Pivots: OFFSET('Positions Tracker'!$A$1,0,0,COUNTA('Positions Tracker'!$A:$A),COUNTA('Positions Tracker'!$1:$1))

Sheet Positions Tracker
A1: S.No | B1: ORC ID | C1: Final Status | D1: Current Stage | E1: Position Title | F1: Skills | G1: BU | H1: Department | I1: HM | J1: Source of Hire | K1: ORC Open Date | L1: Req Received Date- RPO | M1: Intake Meeting Date | N1: Track Level | O1: Hold Date 1 | P1: Hold Date 2 | Q1: Hold Date 3 | R1: Re - Open Date 1 | S1: Re - Open Date 2 | T1: Re - Open Date 3 | U1: Years of Experience | V1: Min Salary | W1: Max Salary | X1: Job Location | Y1: Recruiter | Z1: Sourcer | AA1: Remarks | AB1: Total CV | AC1: Active CV | AD1: Diversity CV | AE1: Candidate Name | AF1: Contact Number | AG1: Email Address | AH1: Gender | AI1: Date of Selection | AJ1: Fitment Approval Date | AK1: Offered location | AL1: CTC offered | AM1: Fitment released Date | AN1: Fitment Acceptance Date | AO1: Offer Reject Date | AP1: AL relesaed date | AQ1: AL Acceptance Date | AR1: OB Trigger Date | AS1: DOJ | AT1: RSLA | AU1: Ageing | AV1: Bucket | AW1: TTO | AX1: TTH | AY1: Offer Drop | AZ1: FTR% | BA1: Diversity of Supply Female | BB1: Diversity of Supply Male | BC1: Hit Ratio | BD1: Intake Month | BE1: Selection Month | BF1: Offer Month | BG1: Joining Month
A2: 1 | B2: 20245762 | C2: Cancelled | D2: Position Cancelled | E2: FEA - Associate | F2: FEM | G2: Integrated Business Services | H2: Core Engineering | I2: AmitKumar | J2: External | K2: 45532 | L2: 45161 | M2: 45161 | N2: T8 | X2: Pune | Y2: Motwani, Hani | Z2: Bharwade, Amruta | AA2: Updated as on 21 Feb 25- 1 F2f interview scheduled, 1 L1 interview scheduled Update as on 8th Feb- 3 L1 interview are scheduled 11th, 12th and 14 feb | AB2: 30 | AC2: 19 | AT2: =IFERROR(SUM(IF(AND(ISBLANK(T2),ISBLANK(Q2)),0,IF(T2="",TODAY()-Q2,T2-Q2))+IF(AND(ISBLANK(S2),ISBLANK(P2)),0,IF(S2="",TODAY()-P2,S2-P2))+IF(AND(ISBLANK(O2),ISBLANK(R2)),0,IF(R2="",TODAY()-O2,R2-O2))),"") -> 0 | AU2: =IFERROR(IF(($M2=""),"",IF(OR(,$C2="Offer in Progress",$C2="WIP",$C2="WIP/Drop",$C2="WIP/New",$C2="WIP/Hold"),(TODAY()-$M2)-$AT2,"")),"") | AV2: {=IFERROR(_xlfn.IFS($AU2="","",$AU2<=15,"0-15",AND($AU2>=16,$AU2<=30),"16-30",AND($AU2>=31,$AU2<=45),"31-45",AND($AU2>=46,$AU2<=60),"46-60",AND($AU2>=61,$AU2<=90),"61-90",AND($AU2>=91),"> 90",AND($AU2>=2000),""),"")} | AW2: {=IFERROR(_xlfn.IFS(OR($M2="",$AM2=""),"",OR($C2="Offered",$C2="Joined"),($AM2-$M2)-$AT2),"")} | AX2: {=IFERROR(_xlfn.IFS(OR($M2="",$AS2=""),"",$C2="Joined",($AS2-$M2)-$AT2),"")} | AY2: =IFERROR(IF(COUNTIFS('Candidate Tracker'!$E:$E,'Positions Tracker'!$B2,'Candidate Tracker'!$C:$C,"Offer Drop")=0,"",COUNTIFS('Candidate Tracker'!$E:$E,'Positions Tracker'!$B2,'Candidate Tracker'!$C:$C,"Offer Drop")),"") | AZ2: =IFERROR(IF((COUNTIFS('Candidate Tracker'!$D:$D,"<>",'Candidate Tracker'!$D:$D,"<>Screening",'Candidate Tracker'!$D:$D,"<>Screening Pending",'Candidate Tracker'!$D:$D,"<>Candidate Hold",'Candidate Tracker'!$D:$D,"<>Position Cancelled",'Candidate Tracker'!$D:$D,"<>Internal closed")/COUNTIF('Candidate Tracker'!$D:$D,"<>"))=0,"",(COUNTIFS('Candidate Tracker'!$D:$D,"<>",'Candidate Tracker'!$D:$D,"<>Screening",'Candidate Tracker'!$D:$D,"<>Candidate Hold",'Candidate Tracker'!$D:$D,"<>Position Cancelled",'Candidate Tracker'!$D:$D,"<>Internal closed")/COUNTIF('Candidate Tracker'!$D:$D,"<>"))),"") -> 0.88111888 | BA2: =IFERROR(IF(COUNTIFS('Candidate Tracker'!$E:$E,'Positions Tracker'!$B2,'Candidate Tracker'!$I:$I,"Female")=0,"",COUNTIFS('Candidate Tracker'!$E:$E,'Positions Tracker'!$B2,'Candidate Tracker'!$I:$I,"Female")),"") | BB2: =IFERROR(IF(COUNTIFS('Candidate Tracker'!$E:$E,'Positions Tracker'!$B2,'Candidate Tracker'!$I:$I,"male")=0,"",COUNTIFS('Candidate Tracker'!$E:$E,'Positions Tracker'!$B2,'Candidate Tracker'!$I:$I,"male")),"") -> 7 | BC2: =IFERROR(IF(COUNTIFS('Candidate Tracker'!$E:$E,'Positions Tracker'!$B2,'Candidate Tracker'!$C:$C,"<>WIP",'Candidate Tracker'!$C:$C,"<>Hold",'Candidate Tracker'!$C:$C,"<>Cancelled",'Candidate Tracker'!$C:$C,"<>Closed")/COUNTIFS('Candidate Tracker'!$E:$E,'Positions Tracker'!$B2)=0,"",COUNTIFS('Candidate Tracker'!$E:$E,'Positions Tracker'!$B2,'Candidate Tracker'!$C:$C,"<>WIP",'Candidate Tracker'!$C:$C,"<>Hold",'Candidate Tracker'!$C:$C,"<>Cancelled",'Candidate Tracker'!$C:$C,"<>Closed")/COUNTIFS('Candidate Tracker'!$E:$E,'Positions Tracker'!$B2)),"") | BD2: =IFERROR(IF($M2="","",TEXT($M2,"MMM-YY")),"") -> Aug-23 | BE2: =IFERROR(IF($AI2="","",TEXT($AI2,"MMM-YY")),"") | BF2: =IFERROR(IF($AM2="","",TEXT($AM2,"MMM-YY")),"") | BG2: =IFERROR(IF($AS2="","",TEXT($AS2,"MMM-YY")),"")
A3: =A2+1 -> 2 | B3: 20250721 | C3: Cancelled | D3: Position Cancelled | E3: Junior Writer, Portfolio Content Creation | F3: CAM | G3: Integrated Business Services | H3: Core Engineering | I3: Hemantkumar shinde | J3: External | K3: 45625 | L3: 45625 | M3: 45625 | N3: T8 | X3: Pune | Y3: Bharwade, Amruta | Z3: Bharwade, Amruta | AA3: Update on 13th feb- Offer declined pooja sawant, Update as on 21st Feb 3 profiles shared for shortlisting | AB3: 15 | AC3: 12 | AD3: 5 | AT3: =IFERROR(SUM(IF(AND(ISBLANK(T3),ISBLANK(Q3)),0,IF(T3="",TODAY()-Q3,T3-Q3))+IF(AND(ISBLANK(S3),ISBLANK(P3)),0,IF(S3="",TODAY()-P3,S3-P3))+IF(AND(ISBLANK(O3),ISBLANK(R3)),0,IF(R3="",TODAY()-O3,R3-O3))),"") -> 0 | AU3: =IFERROR(IF(($M3=""),"",IF(OR(,$C3="Offer in Progress",$C3="WIP",$C3="WIP/Drop",$C3="WIP/New",$C3="WIP/Hold"),(TODAY()-$M3)-$AT3,"")),"") | AV3: {=IFERROR(_xlfn.IFS($AU3="","",$AU3<=15,"0-15",AND($AU3>=16,$AU3<=30),"16-30",AND($AU3>=31,$AU3<=45),"31-45",AND($AU3>=46,$AU3<=60),"46-60",AND($AU3>=61,$AU3<=90),"61-90",AND($AU3>=91),"> 90",AND($AU3>=2000),""),"")} | AW3: {=IFERROR(_xlfn.IFS(OR($M3="",$AM3=""),"",OR($C3="Offered",$C3="Joined"),($AM3-$M3)-$AT3),"")} | AX3: {=IFERROR(_xlfn.IFS(OR($M3="",$AS3=""),"",$C3="Joined",($AS3-$M3)-$AT3),"")} | AY3: =IFERROR(IF(COUNTIFS('Candidate Tracker'!$E:$E,'Positions Tracker'!$B3,'Candidate Tracker'!$C:$C,"Offer Drop")=0,"",COUNTIFS('Candidate Tracker'!$E:$E,'Positions Tracker'!$B3,'Candidate Tracker'!$C:$C,"Offer Drop")),"") | AZ3: =IFERROR(IF((COUNTIFS('Candidate Tracker'!$D:$D,"<>",'Candidate Tracker'!$D:$D,"<>Screening",'Candidate Tracker'!$D:$D,"<>Screening Pending",'Candidate Tracker'!$D:$D,"<>Candidate Hold",'Candidate Tracker'!$D:$D,"<>Position Cancelled",'Candidate Tracker'!$D:$D,"<>Internal closed")/COUNTIF('Candidate Tracker'!$D:$D,"<>"))=0,"",(COUNTIFS('Candidate Tracker'!$D:$D,"<>",'Candidate Tracker'!$D:$D,"<>Screening",'Candidate Tracker'!$D:$D,"<>Candidate Hold",'Candidate Tracker'!$D:$D,"<>Position Cancelled",'Candidate Tracker'!$D:$D,"<>Internal closed")/COUNTIF('Candidate Tracker'!$D:$D,"<>"))),"") -> 0.88111888 | BA3: =IFERROR(IF(COUNTIFS('Candidate Tracker'!$E:$E,'Positions Tracker'!$B3,'Candidate Tracker'!$I:$I,"Female")=0,"",COUNTIFS('Candidate Tracker'!$E:$E,'Positions Tracker'!$B3,'Candidate Tracker'!$I:$I,"Female")),"") | BB3: =IFERROR(IF(COUNTIFS('Candidate Tracker'!$E:$E,'Positions Tracker'!$B3,'Candidate Tracker'!$I:$I,"male")=0,"",COUNTIFS('Candidate Tracker'!$E:$E,'Positions Tracker'!$B3,'Candidate Tracker'!$I:$I,"male")),"") -> 9 | BC3: =IFERROR(IF(COUNTIFS('Candidate Tracker'!$E:$E,'Positions Tracker'!$B3,'Candidate Tracker'!$C:$C,"<>WIP",'Candidate Tracker'!$C:$C,"<>Hold",'Candidate Tracker'!$C:$C,"<>Cancelled",'Candidate Tracker'!$C:$C,"<>Closed")/COUNTIFS('Candidate Tracker'!$E:$E,'Positions Tracker'!$B3)=0,"",COUNTIFS('Candidate Tracker'!$E:$E,'Positions Tracker'!$B3,'Candidate Tracker'!$C:$C,"<>WIP",'Candidate Tracker'!$C:$C,"<>Hold",'Candidate Tracker'!$C:$C,"<>Cancelled",'Candidate Tracker'!$C:$C,"<>Closed")/COUNTIFS('Candidate Tracker'!$E:$E,'Positions Tracker'!$B3)),"") | BD3: =IFERROR(IF($M3="","",TEXT($M3,"MMM-YY")),"") -> Nov-24 | BE3: =IFERROR(IF($AI3="","",TEXT($AI3,"MMM-YY")),"") | BF3: =IFERROR(IF($AM3="","",TEXT($AM3,"MMM-YY")),"") | BG3: =IFERROR(IF($AS3="","",TEXT($AS3,"MMM-YY")),"")
A4: =A3+1 -> 3 | B4: 20245969 | C4: Offer Drop | D4: Offer Decline | E4: Senior Writer, Portfolio Content Creation | F4: CAM | G4: Integrated Business Services | H4: Core Engineering | I4: Hemantkumar shinde | J4: External | K4: 45625 | L4: 45625 | M4: 45625 | N4: T10 | X4: Pune | Y4: Bharwade, Amruta | Z4: Bharwade, Amruta | AA4: Komal has backout - CTC Compensation . Update as on 8th Feb: Komal Dhumal comp breakup to be sent to HM on 8thFeb | AB4: 11 | AC4: 8 | AE4: Komal Dhumal | AF4: 7709030818 | AG4: dhumalkomal2904@gmail.com | AH4: Female | AI4: 45695 | AJ4: 45693 | AK4: Pune | AL4: 1000000 | AM4: 45693 | AN4: 45693 | AP4: 45698 | AQ4: 45698 | AR4: 45757 | AS4: 45761 | AT4: =IFERROR(SUM(IF(AND(ISBLANK(T4),ISBLANK(Q4)),0,IF(T4="",TODAY()-Q4,T4-Q4))+IF(AND(ISBLANK(S4),ISBLANK(P4)),0,IF(S4="",TODAY()-P4,S4-P4))+IF(AND(ISBLANK(O4),ISBLANK(R4)),0,IF(R4="",TODAY()-O4,R4-O4))),"") -> 0 | AU4: =IFERROR(IF(($M4=""),"",IF(OR(,$C4="Offer in Progress",$C4="WIP",$C4="WIP/Drop",$C4="WIP/New",$C4="WIP/Hold"),(TODAY()-$M4)-$AT4,"")),"") | AV4: {=IFERROR(_xlfn.IFS($AU4="","",$AU4<=15,"0-15",AND($AU4>=16,$AU4<=30),"16-30",AND($AU4>=31,$AU4<=45),"31-45",AND($AU4>=46,$AU4<=60),"46-60",AND($AU4>=61,$AU4<=90),"61-90",AND($AU4>=91),"> 90",AND($AU4>=2000),""),"")} | AW4: {=IFERROR(_xlfn.IFS(OR($M4="",$AM4=""),"",OR($C4="Offered",$C4="Joined"),($AM4-$M4)-$AT4),"")} | AX4: {=IFERROR(_xlfn.IFS(OR($M4="",$AS4=""),"",$C4="Joined",($AS4-$M4)-$AT4),"")} | AY4: =IFERROR(IF(COUNTIFS('Candidate Tracker'!$E:$E,'Positions Tracker'!$B4,'Candidate Tracker'!$C:$C,"Offer Drop")=0,"",COUNTIFS('Candidate Tracker'!$E:$E,'Positions Tracker'!$B4,'Candidate Tracker'!$C:$C,"Offer Drop")),"") | AZ4: =IFERROR(IF((COUNTIFS('Candidate Tracker'!$D:$D,"<>",'Candidate Tracker'!$D:$D,"<>Screening",'Candidate Tracker'!$D:$D,"<>Screening Pending",'Candidate Tracker'!$D:$D,"<>Candidate Hold",'Candidate Tracker'!$D:$D,"<>Position Cancelled",'Candidate Tracker'!$D:$D,"<>Internal closed")/COUNTIF('Candidate Tracker'!$D:$D,"<>"))=0,"",(COUNTIFS('Candidate Tracker'!$D:$D,"<>",'Candidate Tracker'!$D:$D,"<>Screening",'Candidate Tracker'!$D:$D,"<>Candidate Hold",'Candidate Tracker'!$D:$D,"<>Position Cancelled",'Candidate Tracker'!$D:$D,"<>Internal closed")/COUNTIF('Candidate Tracker'!$D:$D,"<>"))),"") -> 0.88111888 | BA4: =IFERROR(IF(COUNTIFS('Candidate Tracker'!$E:$E,'Positions Tracker'!$B4,'Candidate Tracker'!$I:$I,"Female")=0,"",COUNTIFS('Candidate Tracker'!$E:$E,'Positions Tracker'!$B4,'Candidate Tracker'!$I:$I,"Female")),"") -> 4 | BB4: =IFERROR(IF(COUNTIFS('Candidate Tracker'!$E:$E,'Positions Tracker'!$B4,'Candidate Tracker'!$I:$I,"male")=0,"",COUNTIFS('Candidate Tracker'!$E:$E,'Positions Tracker'!$B4,'Candidate Tracker'!$I:$I,"male")),"") -> 15 | BC4: =IFERROR(IF(COUNTIFS('Candidate Tracker'!$E:$E,'Positions Tracker'!$B4,'Candidate Tracker'!$C:$C,"<>WIP",'Candidate Tracker'!$C:$C,"<>Hold",'Candidate Tracker'!$C:$C,"<>Cancelled",'Candidate Tracker'!$C:$C,"<>Closed")/COUNTIFS('Candidate Tracker'!$E:$E,'Positions Tracker'!$B4)=0,"",COUNTIFS('Candidate Tracker'!$E:$E,'Positions Tracker'!$B4,'Candidate Tracker'!$C:$C,"<>WIP",'Candidate Tracker'!$C:$C,"<>Hold",'Candidate Tracker'!$C:$C,"<>Cancelled",'Candidate Tracker'!$C:$C,"<>Closed")/COUNTIFS('Candidate Tracker'!$E:$E,'Positions Tracker'!$B4)),"") | BD4: =IFERROR(IF($M4="","",TEXT($M4,"MMM-YY")),"") -> Nov-24 | BE4: =IFERROR(IF($AI4="","",TEXT($AI4,"MMM-YY")),"") -> Feb-25 | BF4: =IFERROR(IF($AM4="","",TEXT($AM4,"MMM-YY")),"") -> Feb-25 | BG4: =IFERROR(IF($AS4="","",TEXT($AS4,"MMM-YY")),"") -> Apr-25
A5: =A4+1 -> 4 | B5: 20253846 | C5: Hold | D5: Hold | E5: Engineer II Technical Publications X: Sr Technical Writer | F5: CAM | G5: Integrated Business Services | H5: Core Engineering | I5: Sami Kar | J5: External | K5: 45744 | L5: 45744 | M5: 45744 | N5: T10 | O5: 45757 | R5: 45776 | U5: 6 | X5: Pune | Y5: Bharwade, Amruta | Z5: Bharwade, Amruta | AA5: 23-June-25: Position on hold 18-June-25: 1 candidates Final interview done - F/b pending , 3 cvs shared with HM feedback pending - 11 june. 17-June-25 : 1 candidates Final interview done - F/b pending , 3 cvs shared with HM feedback pending - 11 june. 9-Jun-25: 3 L1 Interviews scheduled, 4 profiles shared for shortlisting awaiting on 27th May 25 for feedback 2-May-25: 2 candidates Test to be schedule , 1 candidates L2 to be schedule (Vinayak) 12th April 25: 2 L1 interview feedback is pending since 8th April 25, 1 L1 interview scheduled on 14th April 25 7th April 25: 2 L1 interviews scheduled Update on 8th feb- 1 candidate on hold, Update as on 21st Feb 3 profiles shared for shortlisting | AB5: 10 | AC5: 7 | AD5: 4 | AT5: =IFERROR(SUM(IF(AND(ISBLANK(T5),ISBLANK(Q5)),0,IF(T5="",TODAY()-Q5,T5-Q5))+IF(AND(ISBLANK(S5),ISBLANK(P5)),0,IF(S5="",TODAY()-P5,S5-P5))+IF(AND(ISBLANK(O5),ISBLANK(R5)),0,IF(R5="",TODAY()-O5,R5-O5))),"") -> 19 | AU5: =IFERROR(IF(($M5=""),"",IF(OR(,$C5="Offer in Progress",$C5="WIP",$C5="WIP/Drop",$C5="WIP/New",$C5="WIP/Hold"),(TODAY()-$M5)-$AT5,"")),"") | AV5: {=IFERROR(_xlfn.IFS($AU5="","",$AU5<=15,"0-15",AND($AU5>=16,$AU5<=30),"16-30",AND($AU5>=31,$AU5<=45),"31-45",AND($AU5>=46,$AU5<=60),"46-60",AND($AU5>=61,$AU5<=90),"61-90",AND($AU5>=91),"> 90",AND($AU5>=2000),""),"")} | AW5: {=IFERROR(_xlfn.IFS(OR($M5="",$AM5=""),"",OR($C5="Offered",$C5="Joined"),($AM5-$M5)-$AT5),"")} | AX5: {=IFERROR(_xlfn.IFS(OR($M5="",$AS5=""),"",$C5="Joined",($AS5-$M5)-$AT5),"")} | AY5: =IFERROR(IF(COUNTIFS('Candidate Tracker'!$E:$E,'Positions Tracker'!$B5,'Candidate Tracker'!$C:$C,"Offer Drop")=0,"",COUNTIFS('Candidate Tracker'!$E:$E,'Positions Tracker'!$B5,'Candidate Tracker'!$C:$C,"Offer Drop")),"") | AZ5: =IFERROR(IF((COUNTIFS('Candidate Tracker'!$D:$D,"<>",'Candidate Tracker'!$D:$D,"<>Screening",'Candidate Tracker'!$D:$D,"<>Screening Pending",'Candidate Tracker'!$D:$D,"<>Candidate Hold",'Candidate Tracker'!$D:$D,"<>Position Cancelled",'Candidate Tracker'!$D:$D,"<>Internal closed")/COUNTIF('Candidate Tracker'!$D:$D,"<>"))=0,"",(COUNTIFS('Candidate Tracker'!$D:$D,"<>",'Candidate Tracker'!$D:$D,"<>Screening",'Candidate Tracker'!$D:$D,"<>Candidate Hold",'Candidate Tracker'!$D:$D,"<>Position Cancelled",'Candidate Tracker'!$D:$D,"<>Internal closed")/COUNTIF('Candidate Tracker'!$D:$D,"<>"))),"") -> 0.88111888 | BA5: =IFERROR(IF(COUNTIFS('Candidate Tracker'!$E:$E,'Positions Tracker'!$B5,'Candidate Tracker'!$I:$I,"Female")=0,"",COUNTIFS('Candidate Tracker'!$E:$E,'Positions Tracker'!$B5,'Candidate Tracker'!$I:$I,"Female")),"") -> 1 | BB5: =IFERROR(IF(COUNTIFS('Candidate Tracker'!$E:$E,'Positions Tracker'!$B5,'Candidate Tracker'!$I:$I,"male")=0,"",COUNTIFS('Candidate Tracker'!$E:$E,'Positions Tracker'!$B5,'Candidate Tracker'!$I:$I,"male")),"") -> 2 | BC5: =IFERROR(IF(COUNTIFS('Candidate Tracker'!$E:$E,'Positions Tracker'!$B5,'Candidate Tracker'!$C:$C,"<>WIP",'Candidate Tracker'!$C:$C,"<>Hold",'Candidate Tracker'!$C:$C,"<>Cancelled",'Candidate Tracker'!$C:$C,"<>Closed")/COUNTIFS('Candidate Tracker'!$E:$E,'Positions Tracker'!$B5)=0,"",COUNTIFS('Candidate Tracker'!$E:$E,'Positions Tracker'!$B5,'Candidate Tracker'!$C:$C,"<>WIP",'Candidate Tracker'!$C:$C,"<>Hold",'Candidate Tracker'!$C:$C,"<>Cancelled",'Candidate Tracker'!$C:$C,"<>Closed")/COUNTIFS('Candidate Tracker'!$E:$E,'Positions Tracker'!$B5)),"") | BD5: =IFERROR(IF($M5="","",TEXT($M5,"MMM-YY")),"") -> Mar-25 | BE5: =IFERROR(IF($AI5="","",TEXT($AI5,"MMM-YY")),"") | BF5: =IFERROR(IF($AM5="","",TEXT($AM5,"MMM-YY")),"") | BG5: =IFERROR(IF($AS5="","",TEXT($AS5,"MMM-YY")),"")
A6: =A5+1 -> 5 | C6: Cancelled | D6: Position Cancelled | E6: Senior Writer, Software and IT Systems | F6: CAM | G6: Integrated Business Services | H6: Core Engineering | I6: Hemantkumar shinde | J6: External | K6: 45625 | L6: 45625 | M6: 45625 | N6: T10 | X6: Pune | Y6: Bharwade, Amruta | Z6: Bharwade, Amruta | AA6: Update on 8th feb- 2 L1 interviews scheduled on 12 Feb 14th feb 21st Feb 25 Rutvik P final satge | AB6: 12 | AC6: 9 | AT6: =IFERROR(SUM(IF(AND(ISBLANK(T6),ISBLANK(Q6)),0,IF(T6="",TODAY()-Q6,T6-Q6))+IF(AND(ISBLANK(S6),ISBLANK(P6)),0,IF(S6="",TODAY()-P6,S6-P6))+IF(AND(ISBLANK(O6),ISBLANK(R6)),0,IF(R6="",TODAY()-O6,R6-O6))),"") -> 0 | AU6: =IFERROR(IF(($M6=""),"",IF(OR(,$C6="Offer in Progress",$C6="WIP",$C6="WIP/Drop",$C6="WIP/New",$C6="WIP/Hold"),(TODAY()-$M6)-$AT6,"")),"") | AV6: {=IFERROR(_xlfn.IFS($AU6="","",$AU6<=15,"0-15",AND($AU6>=16,$AU6<=30),"16-30",AND($AU6>=31,$AU6<=45),"31-45",AND($AU6>=46,$AU6<=60),"46-60",AND($AU6>=61,$AU6<=90),"61-90",AND($AU6>=91),"> 90",AND($AU6>=2000),""),"")} | AW6: {=IFERROR(_xlfn.IFS(OR($M6="",$AM6=""),"",OR($C6="Offered",$C6="Joined"),($AM6-$M6)-$AT6),"")} | AX6: {=IFERROR(_xlfn.IFS(OR($M6="",$AS6=""),"",$C6="Joined",($AS6-$M6)-$AT6),"")} | AY6: =IFERROR(IF(COUNTIFS('Candidate Tracker'!$E:$E,'Positions Tracker'!$B6,'Candidate Tracker'!$C:$C,"Offer Drop")=0,"",COUNTIFS('Candidate Tracker'!$E:$E,'Positions Tracker'!$B6,'Candidate Tracker'!$C:$C,"Offer Drop")),"") | AZ6: =IFERROR(IF((COUNTIFS('Candidate Tracker'!$D:$D,"<>",'Candidate Tracker'!$D:$D,"<>Screening",'Candidate Tracker'!$D:$D,"<>Screening Pending",'Candidate Tracker'!$D:$D,"<>Candidate Hold",'Candidate Tracker'!$D:$D,"<>Position Cancelled",'Candidate Tracker'!$D:$D,"<>Internal closed")/COUNTIF('Candidate Tracker'!$D:$D,"<>"))=0,"",(COUNTIFS('Candidate Tracker'!$D:$D,"<>",'Candidate Tracker'!$D:$D,"<>Screening",'Candidate Tracker'!$D:$D,"<>Candidate Hold",'Candidate Tracker'!$D:$D,"<>Position Cancelled",'Candidate Tracker'!$D:$D,"<>Internal closed")/COUNTIF('Candidate Tracker'!$D:$D,"<>"))),"") -> 0.88111888 | BA6: =IFERROR(IF(COUNTIFS('Candidate Tracker'!$E:$E,'Positions Tracker'!$B6,'Candidate Tracker'!$I:$I,"Female")=0,"",COUNTIFS('Candidate Tracker'!$E:$E,'Positions Tracker'!$B6,'Candidate Tracker'!$I:$I,"Female")),"") | BB6: =IFERROR(IF(COUNTIFS('Candidate Tracker'!$E:$E,'Positions Tracker'!$B6,'Candidate Tracker'!$I:$I,"male")=0,"",COUNTIFS('Candidate Tracker'!$E:$E,'Positions Tracker'!$B6,'Candidate Tracker'!$I:$I,"male")),"") | BC6: =IFERROR(IF(COUNTIFS('Candidate Tracker'!$E:$E,'Positions Tracker'!$B6,'Candidate Tracker'!$C:$C,"<>WIP",'Candidate Tracker'!$C:$C,"<>Hold",'Candidate Tracker'!$C:$C,"<>Cancelled",'Candidate Tracker'!$C:$C,"<>Closed")/COUNTIFS('Candidate Tracker'!$E:$E,'Positions Tracker'!$B6)=0,"",COUNTIFS('Candidate Tracker'!$E:$E,'Positions Tracker'!$B6,'Candidate Tracker'!$C:$C,"<>WIP",'Candidate Tracker'!$C:$C,"<>Hold",'Candidate Tracker'!$C:$C,"<>Cancelled",'Candidate Tracker'!$C:$C,"<>Closed")/COUNTIFS('Candidate Tracker'!$E:$E,'Positions Tracker'!$B6)),"") | BD6: =IFERROR(IF($M6="","",TEXT($M6,"MMM-YY")),"") -> Nov-24 | BE6: =IFERROR(IF($AI6="","",TEXT($AI6,"MMM-YY")),"") | BF6: =IFERROR(IF($AM6="","",TEXT($AM6,"MMM-YY")),"") | BG6: =IFERROR(IF($AS6="","",TEXT($AS6,"MMM-YY")),"")
A7: =A6+1 -> 6 | B7: 20253845 | C7: Hold | D7: Hold | E7: Sr. Engineer Technical Publications XI: Lead Writer | F7: CAM | G7: Integrated Business Services | H7: Core Engineering | I7: Sami Kar | J7: Referral | K7: 45744 | L7: 45744 | M7: 45744 | N7: T11 | U7: 8 | X7: Pune | Y7: Bharwade, Amruta | Z7: Bharwade, Amruta | AA7: 23-June-25: Position on hold 18-June- 25: Test interview feedback pending , 3 cvs shared with HM on 11th June - Feedback is pending . Position is on HOLD in ORC. 17-June-25 : Test interview feedback pending , 3 cvs shared with HM on 11th June - Feedback is pending . Position is on HOLD in ORC. 7th April 25: 1 LOB interview scheduled Update on 8th feb- 1 Final interview feedback is awaiting, 2 L3 interview scheduled Update as on 21 Feb 25 Nigar shaikh rehired case | AB7: 47 | AC7: 30 | AE7: Nigar Shaikh | AF7: 7775960656 | AG7: nigarshaikh89@gmail.com | AH7: Female | AI7: 45758 | AJ7: 45764 | AK7: Pune | AL7: 1800000 | AM7: 45764 | AN7: 45765 | AO7: 45810 | AP7: 45768 | AQ7: 45768 | AT7: =IFERROR(SUM(IF(AND(ISBLANK(T7),ISBLANK(Q7)),0,IF(T7="",TODAY()-Q7,T7-Q7))+IF(AND(ISBLANK(S7),ISBLANK(P7)),0,IF(S7="",TODAY()-P7,S7-P7))+IF(AND(ISBLANK(O7),ISBLANK(R7)),0,IF(R7="",TODAY()-O7,R7-O7))),"") -> 0 | AU7: =IFERROR(IF(($M7=""),"",IF(OR(,$C7="Offer in Progress",$C7="WIP",$C7="WIP/Drop",$C7="WIP/New",$C7="WIP/Hold"),(TODAY()-$M7)-$AT7,"")),"") | AV7: {=IFERROR(_xlfn.IFS($AU7="","",$AU7<=15,"0-15",AND($AU7>=16,$AU7<=30),"16-30",AND($AU7>=31,$AU7<=45),"31-45",AND($AU7>=46,$AU7<=60),"46-60",AND($AU7>=61,$AU7<=90),"61-90",AND($AU7>=91),"> 90",AND($AU7>=2000),""),"")} | AW7: {=IFERROR(_xlfn.IFS(OR($M7="",$AM7=""),"",OR($C7="Offered",$C7="Joined"),($AM7-$M7)-$AT7),"")} | AX7: {=IFERROR(_xlfn.IFS(OR($M7="",$AS7=""),"",$C7="Joined",($AS7-$M7)-$AT7),"")} | AY7: =IFERROR(IF(COUNTIFS('Candidate Tracker'!$E:$E,'Positions Tracker'!$B7,'Candidate Tracker'!$C:$C,"Offer Drop")=0,"",COUNTIFS('Candidate Tracker'!$E:$E,'Positions Tracker'!$B7,'Candidate Tracker'!$C:$C,"Offer Drop")),"") | AZ7: =IFERROR(IF((COUNTIFS('Candidate Tracker'!$D:$D,"<>",'Candidate Tracker'!$D:$D,"<>Screening",'Candidate Tracker'!$D:$D,"<>Screening Pending",'Candidate Tracker'!$D:$D,"<>Candidate Hold",'Candidate Tracker'!$D:$D,"<>Position Cancelled",'Candidate Tracker'!$D:$D,"<>Internal closed")/COUNTIF('Candidate Tracker'!$D:$D,"<>"))=0,"",(COUNTIFS('Candidate Tracker'!$D:$D,"<>",'Candidate Tracker'!$D:$D,"<>Screening",'Candidate Tracker'!$D:$D,"<>Candidate Hold",'Candidate Tracker'!$D:$D,"<>Position Cancelled",'Candidate Tracker'!$D:$D,"<>Internal closed")/COUNTIF('Candidate Tracker'!$D:$D,"<>"))),"") -> 0.88111888 | BA7: =IFERROR(IF(COUNTIFS('Candidate Tracker'!$E:$E,'Positions Tracker'!$B7,'Candidate Tracker'!$I:$I,"Female")=0,"",COUNTIFS('Candidate Tracker'!$E:$E,'Positions Tracker'!$B7,'Candidate Tracker'!$I:$I,"Female")),"") | BB7: =IFERROR(IF(COUNTIFS('Candidate Tracker'!$E:$E,'Positions Tracker'!$B7,'Candidate Tracker'!$I:$I,"male")=0,"",COUNTIFS('Candidate Tracker'!$E:$E,'Positions Tracker'!$B7,'Candidate Tracker'!$I:$I,"male")),"") | BC7: =IFERROR(IF(COUNTIFS('Candidate Tracker'!$E:$E,'Positions Tracker'!$B7,'Candidate Tracker'!$C:$C,"<>WIP",'Candidate Tracker'!$C:$C,"<>Hold",'Candidate Tracker'!$C:$C,"<>Cancelled",'Candidate Tracker'!$C:$C,"<>Closed")/COUNTIFS('Candidate Tracker'!$E:$E,'Positions Tracker'!$B7)=0,"",COUNTIFS('Candidate Tracker'!$E:$E,'Positions Tracker'!$B7,'Candidate Tracker'!$C:$C,"<>WIP",'Candidate Tracker'!$C:$C,"<>Hold",'Candidate Tracker'!$C:$C,"<>Cancelled",'Candidate Tracker'!$C:$C,"<>Closed")/COUNTIFS('Candidate Tracker'!$E:$E,'Positions Tracker'!$B7)),"") | BD7: =IFERROR(IF($M7="","",TEXT($M7,"MMM-YY")),"") -> Mar-25 | BE7: =IFERROR(IF($AI7="","",TEXT($AI7,"MMM-YY")),"") -> Apr-25 | BF7: =IFERROR(IF($AM7="","",TEXT($AM7,"MMM-YY")),"") -> Apr-25 | BG7: =IFERROR(IF($AS7="","",TEXT($AS7,"MMM-YY")),"")
A8: =A7+1 -> 7 | B8: 20250697 | C8: Cancelled | D8: Position Cancelled | E8: Multimedia Designer | F8: Adobe after Effect | G8: Integrated Business Services | H8: Core Engineering | I8: Rashmin Patel | J8: External | K8: 45625 | L8: 45625 | M8: 45625 | N8: T10 | X8: Pune | Y8: Bharwade, Amruta | Z8: Bharwade, Amruta | AA8: Update as on 8th feb: 2 L1 interviews scheduled on 11 feb and 13 Feb , 1 candidate on hold Update as on 21st Feb 25 | AB8: 12 | AC8: 9 | AT8: =IFERROR(SUM(IF(AND(ISBLANK(T8),ISBLANK(Q8)),0,IF(T8="",TODAY()-Q8,T8-Q8))+IF(AND(ISBLANK(S8),ISBLANK(P8)),0,IF(S8="",TODAY()-P8,S8-P8))+IF(AND(ISBLANK(O8),ISBLANK(R8)),0,IF(R8="",TODAY()-O8,R8-O8))),"") -> 0 | AU8: =IFERROR(IF(($M8=""),"",IF(OR(,$C8="Offer in Progress",$C8="WIP",$C8="WIP/Drop",$C8="WIP/New",$C8="WIP/Hold"),(TODAY()-$M8)-$AT8,"")),"") | AV8: {=IFERROR(_xlfn.IFS($AU8="","",$AU8<=15,"0-15",AND($AU8>=16,$AU8<=30),"16-30",AND($AU8>=31,$AU8<=45),"31-45",AND($AU8>=46,$AU8<=60),"46-60",AND($AU8>=61,$AU8<=90),"61-90",AND($AU8>=91),"> 90",AND($AU8>=2000),""),"")} | AW8: {=IFERROR(_xlfn.IFS(OR($M8="",$AM8=""),"",OR($C8="Offered",$C8="Joined"),($AM8-$M8)-$AT8),"")} | AX8: {=IFERROR(_xlfn.IFS(OR($M8="",$AS8=""),"",$C8="Joined",($AS8-$M8)-$AT8),"")} | AY8: =IFERROR(IF(COUNTIFS('Candidate Tracker'!$E:$E,'Positions Tracker'!$B8,'Candidate Tracker'!$C:$C,"Offer Drop")=0,"",COUNTIFS('Candidate Tracker'!$E:$E,'Positions Tracker'!$B8,'Candidate Tracker'!$C:$C,"Offer Drop")),"") | AZ8: =IFERROR(IF((COUNTIFS('Candidate Tracker'!$D:$D,"<>",'Candidate Tracker'!$D:$D,"<>Screening",'Candidate Tracker'!$D:$D,"<>Screening Pending",'Candidate Tracker'!$D:$D,"<>Candidate Hold",'Candidate Tracker'!$D:$D,"<>Position Cancelled",'Candidate Tracker'!$D:$D,"<>Internal closed")/COUNTIF('Candidate Tracker'!$D:$D,"<>"))=0,"",(COUNTIFS('Candidate Tracker'!$D:$D,"<>",'Candidate Tracker'!$D:$D,"<>Screening",'Candidate Tracker'!$D:$D,"<>Candidate Hold",'Candidate Tracker'!$D:$D,"<>Position Cancelled",'Candidate Tracker'!$D:$D,"<>Internal closed")/COUNTIF('Candidate Tracker'!$D:$D,"<>"))),"") -> 0.88111888 | BA8: =IFERROR(IF(COUNTIFS('Candidate Tracker'!$E:$E,'Positions Tracker'!$B8,'Candidate Tracker'!$I:$I,"Female")=0,"",COUNTIFS('Candidate Tracker'!$E:$E,'Positions Tracker'!$B8,'Candidate Tracker'!$I:$I,"Female")),"") -> 1 | BB8: =IFERROR(IF(COUNTIFS('Candidate Tracker'!$E:$E,'Positions Tracker'!$B8,'Candidate Tracker'!$I:$I,"male")=0,"",COUNTIFS('Candidate Tracker'!$E:$E,'Positions Tracker'!$B8,'Candidate Tracker'!$I:$I,"male")),"") -> 7 | BC8: =IFERROR(IF(COUNTIFS('Candidate Tracker'!$E:$E,'Positions Tracker'!$B8,'Candidate Tracker'!$C:$C,"<>WIP",'Candidate Tracker'!$C:$C,"<>Hold",'Candidate Tracker'!$C:$C,"<>Cancelled",'Candidate Tracker'!$C:$C,"<>Closed")/COUNTIFS('Candidate Tracker'!$E:$E,'Positions Tracker'!$B8)=0,"",COUNTIFS('Candidate Tracker'!$E:$E,'Positions Tracker'!$B8,'Candidate Tracker'!$C:$C,"<>WIP",'Candidate Tracker'!$C:$C,"<>Hold",'Candidate Tracker'!$C:$C,"<>Cancelled",'Candidate Tracker'!$C:$C,"<>Closed")/COUNTIFS('Candidate Tracker'!$E:$E,'Positions Tracker'!$B8)),"") | BD8: =IFERROR(IF($M8="","",TEXT($M8,"MMM-YY")),"") -> Nov-24 | BE8: =IFERROR(IF($AI8="","",TEXT($AI8,"MMM-YY")),"") | BF8: =IFERROR(IF($AM8="","",TEXT($AM8,"MMM-YY")),"") | BG8: =IFERROR(IF($AS8="","",TEXT($AS8,"MMM-YY")),"")
A9: =A8+1 -> 8 | B9: 20250696 | C9: Cancelled | D9: Position Cancelled | E9: Senior Multimedia Designer | F9: Adobe after Effect | G9: Integrated Business Services | H9: Core Engineering | I9: Rashmin Patel | J9: External | K9: 45625 | L9: 45625 | M9: 45625 | N9: T8 | X9: Pune | Y9: Bharwade, Amruta | Z9: Bharwade, Amruta | AA9: Update as on 8th Feb:I shaan Deshpande Offer revovked Update as on 21st Feb 5 L1 interviews scheduled | AB9: 28 | AC9: 20 | AT9: =IFERROR(SUM(IF(AND(ISBLANK(T9),ISBLANK(Q9)),0,IF(T9="",TODAY()-Q9,T9-Q9))+IF(AND(ISBLANK(S9),ISBLANK(P9)),0,IF(S9="",TODAY()-P9,S9-P9))+IF(AND(ISBLANK(O9),ISBLANK(R9)),0,IF(R9="",TODAY()-O9,R9-O9))),"") -> 0 | AU9: =IFERROR(IF(($M9=""),"",IF(OR(,$C9="Offer in Progress",$C9="WIP",$C9="WIP/Drop",$C9="WIP/New",$C9="WIP/Hold"),(TODAY()-$M9)-$AT9,"")),"") | AV9: {=IFERROR(_xlfn.IFS($AU9="","",$AU9<=15,"0-15",AND($AU9>=16,$AU9<=30),"16-30",AND($AU9>=31,$AU9<=45),"31-45",AND($AU9>=46,$AU9<=60),"46-60",AND($AU9>=61,$AU9<=90),"61-90",AND($AU9>=91),"> 90",AND($AU9>=2000),""),"")} | AW9: {=IFERROR(_xlfn.IFS(OR($M9="",$AM9=""),"",OR($C9="Offered",$C9="Joined"),($AM9-$M9)-$AT9),"")} | AX9: {=IFERROR(_xlfn.IFS(OR($M9="",$AS9=""),"",$C9="Joined",($AS9-$M9)-$AT9),"")} | AY9: =IFERROR(IF(COUNTIFS('Candidate Tracker'!$E:$E,'Positions Tracker'!$B9,'Candidate Tracker'!$C:$C,"Offer Drop")=0,"",COUNTIFS('Candidate Tracker'!$E:$E,'Positions Tracker'!$B9,'Candidate Tracker'!$C:$C,"Offer Drop")),"") | AZ9: =IFERROR(IF((COUNTIFS('Candidate Tracker'!$D:$D,"<>",'Candidate Tracker'!$D:$D,"<>Screening",'Candidate Tracker'!$D:$D,"<>Screening Pending",'Candidate Tracker'!$D:$D,"<>Candidate Hold",'Candidate Tracker'!$D:$D,"<>Position Cancelled",'Candidate Tracker'!$D:$D,"<>Internal closed")/COUNTIF('Candidate Tracker'!$D:$D,"<>"))=0,"",(COUNTIFS('Candidate Tracker'!$D:$D,"<>",'Candidate Tracker'!$D:$D,"<>Screening",'Candidate Tracker'!$D:$D,"<>Candidate Hold",'Candidate Tracker'!$D:$D,"<>Position Cancelled",'Candidate Tracker'!$D:$D,"<>Internal closed")/COUNTIF('Candidate Tracker'!$D:$D,"<>"))),"") -> 0.88111888 | BA9: =IFERROR(IF(COUNTIFS('Candidate Tracker'!$E:$E,'Positions Tracker'!$B9,'Candidate Tracker'!$I:$I,"Female")=0,"",COUNTIFS('Candidate Tracker'!$E:$E,'Positions Tracker'!$B9,'Candidate Tracker'!$I:$I,"Female")),"") -> 2 | BB9: =IFERROR(IF(COUNTIFS('Candidate Tracker'!$E:$E,'Positions Tracker'!$B9,'Candidate Tracker'!$I:$I,"male")=0,"",COUNTIFS('Candidate Tracker'!$E:$E,'Positions Tracker'!$B9,'Candidate Tracker'!$I:$I,"male")),"") -> 10 | BC9: =IFERROR(IF(COUNTIFS('Candidate Tracker'!$E:$E,'Positions Tracker'!$B9,'Candidate Tracker'!$C:$C,"<>WIP",'Candidate Tracker'!$C:$C,"<>Hold",'Candidate Tracker'!$C:$C,"<>Cancelled",'Candidate Tracker'!$C:$C,"<>Closed")/COUNTIFS('Candidate Tracker'!$E:$E,'Positions Tracker'!$B9)=0,"",COUNTIFS('Candidate Tracker'!$E:$E,'Positions Tracker'!$B9,'Candidate Tracker'!$C:$C,"<>WIP",'Candidate Tracker'!$C:$C,"<>Hold",'Candidate Tracker'!$C:$C,"<>Cancelled",'Candidate Tracker'!$C:$C,"<>Closed")/COUNTIFS('Candidate Tracker'!$E:$E,'Positions Tracker'!$B9)),"") | BD9: =IFERROR(IF($M9="","",TEXT($M9,"MMM-YY")),"") -> Nov-24 | BE9: =IFERROR(IF($AI9="","",TEXT($AI9,"MMM-YY")),"") | BF9: =IFERROR(IF($AM9="","",TEXT($AM9,"MMM-YY")),"") | BG9: =IFERROR(IF($AS9="","",TEXT($AS9,"MMM-YY")),"")
A10: =A9+1 -> 9 | B10: 20251179 | C10: Cancelled | D10: Position Cancelled | E10: Sr Test Engineer | F10: HIL | G10: Integrated Business Services | H10: Core Engineering | I10: Ankur Singh | J10: External | K10: 45643 | L10: 45643 | M10: 45643 | N10: T11 | X10: Pune | Y10: Bharwade, Amruta | Z10: Bharwade, Amruta | AA10: Update as on 21st Feb 25- Position cancelled in the sys | AT10: =IFERROR(SUM(IF(AND(ISBLANK(T10),ISBLANK(Q10)),0,IF(T10="",TODAY()-Q10,T10-Q10))+IF(AND(ISBLANK(S10),ISBLANK(P10)),0,IF(S10="",TODAY()-P10,S10-P10))+IF(AND(ISBLANK(O10),ISBLANK(R10)),0,IF(R10="",TODAY()-O10,R10-O10))),"") -> 0 | AU10: =IFERROR(IF(($M10=""),"",IF(OR(,$C10="Offer in Progress",$C10="WIP",$C10="WIP/Drop",$C10="WIP/New",$C10="WIP/Hold"),(TODAY()-$M10)-$AT10,"")),"") | AV10: {=IFERROR(_xlfn.IFS($AU10="","",$AU10<=15,"0-15",AND($AU10>=16,$AU10<=30),"16-30",AND($AU10>=31,$AU10<=45),"31-45",AND($AU10>=46,$AU10<=60),"46-60",AND($AU10>=61,$AU10<=90),"61-90",AND($AU10>=91),"> 90",AND($AU10>=2000),""),"")} | AW10: {=IFERROR(_xlfn.IFS(OR($M10="",$AM10=""),"",OR($C10="Offered",$C10="Joined"),($AM10-$M10)-$AT10),"")} | AX10: {=IFERROR(_xlfn.IFS(OR($M10="",$AS10=""),"",$C10="Joined",($AS10-$M10)-$AT10),"")} | AY10: =IFERROR(IF(COUNTIFS('Candidate Tracker'!$E:$E,'Positions Tracker'!$B10,'Candidate Tracker'!$C:$C,"Offer Drop")=0,"",COUNTIFS('Candidate Tracker'!$E:$E,'Positions Tracker'!$B10,'Candidate Tracker'!$C:$C,"Offer Drop")),"") | AZ10: =IFERROR(IF((COUNTIFS('Candidate Tracker'!$D:$D,"<>",'Candidate Tracker'!$D:$D,"<>Screening",'Candidate Tracker'!$D:$D,"<>Screening Pending",'Candidate Tracker'!$D:$D,"<>Candidate Hold",'Candidate Tracker'!$D:$D,"<>Position Cancelled",'Candidate Tracker'!$D:$D,"<>Internal closed")/COUNTIF('Candidate Tracker'!$D:$D,"<>"))=0,"",(COUNTIFS('Candidate Tracker'!$D:$D,"<>",'Candidate Tracker'!$D:$D,"<>Screening",'Candidate Tracker'!$D:$D,"<>Candidate Hold",'Candidate Tracker'!$D:$D,"<>Position Cancelled",'Candidate Tracker'!$D:$D,"<>Internal closed")/COUNTIF('Candidate Tracker'!$D:$D,"<>"))),"") -> 0.88111888 | BA10: =IFERROR(IF(COUNTIFS('Candidate Tracker'!$E:$E,'Positions Tracker'!$B10,'Candidate Tracker'!$I:$I,"Female")=0,"",COUNTIFS('Candidate Tracker'!$E:$E,'Positions Tracker'!$B10,'Candidate Tracker'!$I:$I,"Female")),"") | BB10: =IFERROR(IF(COUNTIFS('Candidate Tracker'!$E:$E,'Positions Tracker'!$B10,'Candidate Tracker'!$I:$I,"male")=0,"",COUNTIFS('Candidate Tracker'!$E:$E,'Positions Tracker'!$B10,'Candidate Tracker'!$I:$I,"male")),"") | BC10: =IFERROR(IF(COUNTIFS('Candidate Tracker'!$E:$E,'Positions Tracker'!$B10,'Candidate Tracker'!$C:$C,"<>WIP",'Candidate Tracker'!$C:$C,"<>Hold",'Candidate Tracker'!$C:$C,"<>Cancelled",'Candidate Tracker'!$C:$C,"<>Closed")/COUNTIFS('Candidate Tracker'!$E:$E,'Positions Tracker'!$B10)=0,"",COUNTIFS('Candidate Tracker'!$E:$E,'Positions Tracker'!$B10,'Candidate Tracker'!$C:$C,"<>WIP",'Candidate Tracker'!$C:$C,"<>Hold",'Candidate Tracker'!$C:$C,"<>Cancelled",'Candidate Tracker'!$C:$C,"<>Closed")/COUNTIFS('Candidate Tracker'!$E:$E,'Positions Tracker'!$B10)),"") | BD10: =IFERROR(IF($M10="","",TEXT($M10,"MMM-YY")),"") -> Dec-24 | BE10: =IFERROR(IF($AI10="","",TEXT($AI10,"MMM-YY")),"") | BF10: =IFERROR(IF($AM10="","",TEXT($AM10,"MMM-YY")),"") | BG10: =IFERROR(IF($AS10="","",TEXT($AS10,"MMM-YY")),"")
A11: =A10+1 -> 10 | B11: 20242803 | C11: Hold | D11: Hold | E11: Mid Mendix Developer | F11: Mendix | G11: Integrated Business Services | H11: GSP | I11: Lucian | K11: 45580 | L11: 45580 | M11: 45710 | N11: T11 | O11: 45719 | R11: 45737 | X11: Pune | Y11: Bharwade, Amruta | Z11: Bharwade, Amruta | AA11: 21st April 25: 3 L1 interviews scheduled 12th April: 3 Profiles shared for shortlisting feedback awaited from 9th April 7th April 25: 5 profiles shared for shortlisting 28th Feb 25: 1 candidate scheduled 28th Feb 252 candidates L1 scheduled 3rd and 4th March 21st Feb 25- 3 L1 interviews scheidledUpdate as on 8th Feb 25Abhishek J Offer Declined, Satyjeet Pardeshi TBO Update as on 21st Feb 3 L1 scheduled, 2 L1 to be scheduled | AB11: 38 | AC11: 30 | AD11: 12 | AT11: =IFERROR(SUM(IF(AND(ISBLANK(T11),ISBLANK(Q11)),0,IF(T11="",TODAY()-Q11,T11-Q11))+IF(AND(ISBLANK(S11),ISBLANK(P11)),0,IF(S11="",TODAY()-P11,S11-P11))+IF(AND(ISBLANK(O11),ISBLANK(R11)),0,IF(R11="",TODAY()-O11,R11-O11))),"") -> 18 | AU11: =IFERROR(IF(($M11=""),"",IF(OR(,$C11="Offer in Progress",$C11="WIP",$C11="WIP/Drop",$C11="WIP/New",$C11="WIP/Hold"),(TODAY()-$M11)-$AT11,"")),"") | AV11: {=IFERROR(_xlfn.IFS($AU11="","",$AU11<=15,"0-15",AND($AU11>=16,$AU11<=30),"16-30",AND($AU11>=31,$AU11<=45),"31-45",AND($AU11>=46,$AU11<=60),"46-60",AND($AU11>=61,$AU11<=90),"61-90",AND($AU11>=91),"> 90",AND($AU11>=2000),""),"")} | AW11: {=IFERROR(_xlfn.IFS(OR($M11="",$AM11=""),"",OR($C11="Offered",$C11="Joined"),($AM11-$M11)-$AT11),"")} | AX11: {=IFERROR(_xlfn.IFS(OR($M11="",$AS11=""),"",$C11="Joined",($AS11-$M11)-$AT11),"")} | AY11: =IFERROR(IF(COUNTIFS('Candidate Tracker'!$E:$E,'Positions Tracker'!$B11,'Candidate Tracker'!$C:$C,"Offer Drop")=0,"",COUNTIFS('Candidate Tracker'!$E:$E,'Positions Tracker'!$B11,'Candidate Tracker'!$C:$C,"Offer Drop")),"") | AZ11: =IFERROR(IF((COUNTIFS('Candidate Tracker'!$D:$D,"<>",'Candidate Tracker'!$D:$D,"<>Screening",'Candidate Tracker'!$D:$D,"<>Screening Pending",'Candidate Tracker'!$D:$D,"<>Candidate Hold",'Candidate Tracker'!$D:$D,"<>Position Cancelled",'Candidate Tracker'!$D:$D,"<>Internal closed")/COUNTIF('Candidate Tracker'!$D:$D,"<>"))=0,"",(COUNTIFS('Candidate Tracker'!$D:$D,"<>",'Candidate Tracker'!$D:$D,"<>Screening",'Candidate Tracker'!$D:$D,"<>Candidate Hold",'Candidate Tracker'!$D:$D,"<>Position Cancelled",'Candidate Tracker'!$D:$D,"<>Internal closed")/COUNTIF('Candidate Tracker'!$D:$D,"<>"))),"") -> 0.88111888 | BA11: =IFERROR(IF(COUNTIFS('Candidate Tracker'!$E:$E,'Positions Tracker'!$B11,'Candidate Tracker'!$I:$I,"Female")=0,"",COUNTIFS('Candidate Tracker'!$E:$E,'Positions Tracker'!$B11,'Candidate Tracker'!$I:$I,"Female")),"") -> 14 | BB11: =IFERROR(IF(COUNTIFS('Candidate Tracker'!$E:$E,'Positions Tracker'!$B11,'Candidate Tracker'!$I:$I,"male")=0,"",COUNTIFS('Candidate Tracker'!$E:$E,'Positions Tracker'!$B11,'Candidate Tracker'!$I:$I,"male")),"") -> 31 | BC11: =IFERROR(IF(COUNTIFS('Candidate Tracker'!$E:$E,'Positions Tracker'!$B11,'Candidate Tracker'!$C:$C,"<>WIP",'Candidate Tracker'!$C:$C,"<>Hold",'Candidate Tracker'!$C:$C,"<>Cancelled",'Candidate Tracker'!$C:$C,"<>Closed")/COUNTIFS('Candidate Tracker'!$E:$E,'Positions Tracker'!$B11)=0,"",COUNTIFS('Candidate Tracker'!$E:$E,'Positions Tracker'!$B11,'Candidate Tracker'!$C:$C,"<>WIP",'Candidate Tracker'!$C:$C,"<>Hold",'Candidate Tracker'!$C:$C,"<>Cancelled",'Candidate Tracker'!$C:$C,"<>Closed")/COUNTIFS('Candidate Tracker'!$E:$E,'Positions Tracker'!$B11)),"") | BD11: =IFERROR(IF($M11="","",TEXT($M11,"MMM-YY")),"") -> Feb-25 | BE11: =IFERROR(IF($AI11="","",TEXT($AI11,"MMM-YY")),"") | BF11: =IFERROR(IF($AM11="","",TEXT($AM11,"MMM-YY")),"") | BG11: =IFERROR(IF($AS11="","",TEXT($AS11,"MMM-YY")),"")
A12: =A11+1 -> 11 | B12: 20245321 | C12: Hold | D12: Hold | E12: Sr Mendix Developer | F12: Mendix | G12: Integrated Business Services | H12: GSP | I12: Lucian | K12: 45580 | L12: 45580 | M12: 45580 | N12: T11 | O12: 45649 | R12: 45664 | X12: Pune | Y12: Bharwade, Amruta | Z12: Bharwade, Amruta | AA12: 21st April 25: 2 L1 interviews scheduled 12th April 25: 2 L1 feedback is pending 2 L1 interviews scheduled 7th April 25: 2 L1 interviews scheduled, 2 L1 interview feedback pending 28-Feb-25: L1 interview to be schedule 4 and 5 March . 8th Feb- 2 L1 interview to be scheduled, Update as on 21st Feb 25 3 L1 interviews scheduled | AB12: 38 | AC12: 29 | AD12: 10 | AT12: =IFERROR(SUM(IF(AND(ISBLANK(T12),ISBLANK(Q12)),0,IF(T12="",TODAY()-Q12,T12-Q12))+IF(AND(ISBLANK(S12),ISBLANK(P12)),0,IF(S12="",TODAY()-P12,S12-P12))+IF(AND(ISBLANK(O12),ISBLANK(R12)),0,IF(R12="",TODAY()-O12,R12-O12))),"") -> 15 | AU12: =IFERROR(IF(($M12=""),"",IF(OR(,$C12="Offer in Progress",$C12="WIP",$C12="WIP/Drop",$C12="WIP/New",$C12="WIP/Hold"),(TODAY()-$M12)-$AT12,"")),"") | AV12: {=IFERROR(_xlfn.IFS($AU12="","",$AU12<=15,"0-15",AND($AU12>=16,$AU12<=30),"16-30",AND($AU12>=31,$AU12<=45),"31-45",AND($AU12>=46,$AU12<=60),"46-60",AND($AU12>=61,$AU12<=90),"61-90",AND($AU12>=91),"> 90",AND($AU12>=2000),""),"")} | AW12: {=IFERROR(_xlfn.IFS(OR($M12="",$AM12=""),"",OR($C12="Offered",$C12="Joined"),($AM12-$M12)-$AT12),"")} | AX12: {=IFERROR(_xlfn.IFS(OR($M12="",$AS12=""),"",$C12="Joined",($AS12-$M12)-$AT12),"")} | AY12: =IFERROR(IF(COUNTIFS('Candidate Tracker'!$E:$E,'Positions Tracker'!$B12,'Candidate Tracker'!$C:$C,"Offer Drop")=0,"",COUNTIFS('Candidate Tracker'!$E:$E,'Positions Tracker'!$B12,'Candidate Tracker'!$C:$C,"Offer Drop")),"") | AZ12: =IFERROR(IF((COUNTIFS('Candidate Tracker'!$D:$D,"<>",'Candidate Tracker'!$D:$D,"<>Screening",'Candidate Tracker'!$D:$D,"<>Screening Pending",'Candidate Tracker'!$D:$D,"<>Candidate Hold",'Candidate Tracker'!$D:$D,"<>Position Cancelled",'Candidate Tracker'!$D:$D,"<>Internal closed")/COUNTIF('Candidate Tracker'!$D:$D,"<>"))=0,"",(COUNTIFS('Candidate Tracker'!$D:$D,"<>",'Candidate Tracker'!$D:$D,"<>Screening",'Candidate Tracker'!$D:$D,"<>Candidate Hold",'Candidate Tracker'!$D:$D,"<>Position Cancelled",'Candidate Tracker'!$D:$D,"<>Internal closed")/COUNTIF('Candidate Tracker'!$D:$D,"<>"))),"") -> 0.88111888 | BA12: =IFERROR(IF(COUNTIFS('Candidate Tracker'!$E:$E,'Positions Tracker'!$B12,'Candidate Tracker'!$I:$I,"Female")=0,"",COUNTIFS('Candidate Tracker'!$E:$E,'Positions Tracker'!$B12,'Candidate Tracker'!$I:$I,"Female")),"") -> 9 | BB12: =IFERROR(IF(COUNTIFS('Candidate Tracker'!$E:$E,'Positions Tracker'!$B12,'Candidate Tracker'!$I:$I,"male")=0,"",COUNTIFS('Candidate Tracker'!$E:$E,'Positions Tracker'!$B12,'Candidate Tracker'!$I:$I,"male")),"") -> 18 | BC12: =IFERROR(IF(COUNTIFS('Candidate Tracker'!$E:$E,'Positions Tracker'!$B12,'Candidate Tracker'!$C:$C,"<>WIP",'Candidate Tracker'!$C:$C,"<>Hold",'Candidate Tracker'!$C:$C,"<>Cancelled",'Candidate Tracker'!$C:$C,"<>Closed")/COUNTIFS('Candidate Tracker'!$E:$E,'Positions Tracker'!$B12)=0,"",COUNTIFS('Candidate Tracker'!$E:$E,'Positions Tracker'!$B12,'Candidate Tracker'!$C:$C,"<>WIP",'Candidate Tracker'!$C:$C,"<>Hold",'Candidate Tracker'!$C:$C,"<>Cancelled",'Candidate Tracker'!$C:$C,"<>Closed")/COUNTIFS('Candidate Tracker'!$E:$E,'Positions Tracker'!$B12)),"") | BD12: =IFERROR(IF($M12="","",TEXT($M12,"MMM-YY")),"") -> Oct-24 | BE12: =IFERROR(IF($AI12="","",TEXT($AI12,"MMM-YY")),"") | BF12: =IFERROR(IF($AM12="","",TEXT($AM12,"MMM-YY")),"") | BG12: =IFERROR(IF($AS12="","",TEXT($AS12,"MMM-YY")),"")
A13: =A12+1 -> 12 | B13: 20243902 | C13: Joined | D13: Joined | E13: Electrical Design Engineer | F13: Revit, Load Calculations | G13: Integrated Business Services | H13: Core Engineering | I13: Vinayak Bhat | J13: External | K13: 45476 | L13: 45476 | M13: 45660 | N13: T8 | O13: 45681 | P13: 45727 | R13: 45748 | X13: Pune | Y13: Bharwade, Amruta | Z13: Bharwade, Amruta | AA13: 7th April 25: 1 LOB interview TBS, 1 L1 interview scheduled Update as on 8th Feb- 3 L1 to be scheduled Update as on 21st Feb 25-1 F2f scheduled | AB13: 25 | AC13: 17 | AE13: Utkarsh Patil | AF13: 9637764488 | AG13: patilutkarsh025@gmail.com | AH13: Male | AI13: 45756 | AK13: Pune | AL13: 971942 | AM13: 45819 | AN13: 45819 | AP13: 45821 | AQ13: 45821 | AR13: 45855 | AS13: 45859 | AT13: =IFERROR(SUM(IF(AND(ISBLANK(T13),ISBLANK(Q13)),0,IF(T13="",TODAY()-Q13,T13-Q13))+IF(AND(ISBLANK(S13),ISBLANK(P13)),0,IF(S13="",TODAY()-P13,S13-P13))+IF(AND(ISBLANK(O13),ISBLANK(R13)),0,IF(R13="",TODAY()-O13,R13-O13))),"") -> 341 | AU13: =IFERROR(IF(($M13=""),"",IF(OR(,$C13="Offer in Progress",$C13="WIP",$C13="WIP/Drop",$C13="WIP/New",$C13="WIP/Hold"),(TODAY()-$M13)-$AT13,"")),"") | AV13: {=IFERROR(_xlfn.IFS($AU13="","",$AU13<=15,"0-15",AND($AU13>=16,$AU13<=30),"16-30",AND($AU13>=31,$AU13<=45),"31-45",AND($AU13>=46,$AU13<=60),"46-60",AND($AU13>=61,$AU13<=90),"61-90",AND($AU13>=91),"> 90",AND($AU13>=2000),""),"")} | AW13: {=IFERROR(_xlfn.IFS(OR($M13="",$AM13=""),"",OR($C13="Offered",$C13="Joined"),($AM13-$M13)-$AT13),"")} -> -182 | AX13: {=IFERROR(_xlfn.IFS(OR($M13="",$AS13=""),"",$C13="Joined",($AS13-$M13)-$AT13),"")} -> -142 | AY13: =IFERROR(IF(COUNTIFS('Candidate Tracker'!$E:$E,'Positions Tracker'!$B13,'Candidate Tracker'!$C:$C,"Offer Drop")=0,"",COUNTIFS('Candidate Tracker'!$E:$E,'Positions Tracker'!$B13,'Candidate Tracker'!$C:$C,"Offer Drop")),"") | AZ13: =IFERROR(IF((COUNTIFS('Candidate Tracker'!$D:$D,"<>",'Candidate Tracker'!$D:$D,"<>Screening",'Candidate Tracker'!$D:$D,"<>Screening Pending",'Candidate Tracker'!$D:$D,"<>Candidate Hold",'Candidate Tracker'!$D:$D,"<>Position Cancelled",'Candidate Tracker'!$D:$D,"<>Internal closed")/COUNTIF('Candidate Tracker'!$D:$D,"<>"))=0,"",(COUNTIFS('Candidate Tracker'!$D:$D,"<>",'Candidate Tracker'!$D:$D,"<>Screening",'Candidate Tracker'!$D:$D,"<>Candidate Hold",'Candidate Tracker'!$D:$D,"<>Position Cancelled",'Candidate Tracker'!$D:$D,"<>Internal closed")/COUNTIF('Candidate Tracker'!$D:$D,"<>"))),"") -> 0.88111888 | BA13: =IFERROR(IF(COUNTIFS('Candidate Tracker'!$E:$E,'Positions Tracker'!$B13,'Candidate Tracker'!$I:$I,"Female")=0,"",COUNTIFS('Candidate Tracker'!$E:$E,'Positions Tracker'!$B13,'Candidate Tracker'!$I:$I,"Female")),"") -> 2 | BB13: =IFERROR(IF(COUNTIFS('Candidate Tracker'!$E:$E,'Positions Tracker'!$B13,'Candidate Tracker'!$I:$I,"male")=0,"",COUNTIFS('Candidate Tracker'!$E:$E,'Positions Tracker'!$B13,'Candidate Tracker'!$I:$I,"male")),"") -> 13 | BC13: =IFERROR(IF(COUNTIFS('Candidate Tracker'!$E:$E,'Positions Tracker'!$B13,'Candidate Tracker'!$C:$C,"<>WIP",'Candidate Tracker'!$C:$C,"<>Hold",'Candidate Tracker'!$C:$C,"<>Cancelled",'Candidate Tracker'!$C:$C,"<>Closed")/COUNTIFS('Candidate Tracker'!$E:$E,'Positions Tracker'!$B13)=0,"",COUNTIFS('Candidate Tracker'!$E:$E,'Positions Tracker'!$B13,'Candidate Tracker'!$C:$C,"<>WIP",'Candidate Tracker'!$C:$C,"<>Hold",'Candidate Tracker'!$C:$C,"<>Cancelled",'Candidate Tracker'!$C:$C,"<>Closed")/COUNTIFS('Candidate Tracker'!$E:$E,'Positions Tracker'!$B13)),"") | BD13: =IFERROR(IF($M13="","",TEXT($M13,"MMM-YY")),"") -> Jan-25 | BE13: =IFERROR(IF($AI13="","",TEXT($AI13,"MMM-YY")),"") -> Apr-25 | BF13: =IFERROR(IF($AM13="","",TEXT($AM13,"MMM-YY")),"") -> Jun-25 | BG13: =IFERROR(IF($AS13="","",TEXT($AS13,"MMM-YY")),"") -> Jul-25
A14: =A13+1 -> 13 | B14: 20252045 | C14: Joined | D14: Joined | E14: Associate Technical Publication | F14: CAM, DAM | G14: Integrated Business Services | H14: Core Engineering | I14: Hemantkumar shinde | J14: Referral | K14: 45691 | L14: 45691 | M14: 45691 | N14: T8 | X14: Pune | Y14: Bharwade, Amruta | Z14: Bharwade, Amruta | AA14: Update as on 8th Feb: Siddheshwar Patil comp <80% Uodate as on 21st Feb Siddheshwar Patil Offer accepted | AB14: 5 | AC14: 5 | AE14: Siddheshwar Patil | AF14: 8766529114 | AG14: sid.patil1553@gmail.com | AH14: Male | AI14: 45693 | AJ14: 45700 | AK14: Pune | AL14: 700000 | AM14: 45699 | AN14: 45702 | AP14: 45706 | AQ14: 45706 | AR14: 45751 | AS14: 45740 | AT14: =IFERROR(SUM(IF(AND(ISBLANK(T14),ISBLANK(Q14)),0,IF(T14="",TODAY()-Q14,T14-Q14))+IF(AND(ISBLANK(S14),ISBLANK(P14)),0,IF(S14="",TODAY()-P14,S14-P14))+IF(AND(ISBLANK(O14),ISBLANK(R14)),0,IF(R14="",TODAY()-O14,R14-O14))),"") -> 0 | AU14: =IFERROR(IF(($M14=""),"",IF(OR(,$C14="Offer in Progress",$C14="WIP",$C14="WIP/Drop",$C14="WIP/New",$C14="WIP/Hold"),(TODAY()-$M14)-$AT14,"")),"") | AV14: {=IFERROR(_xlfn.IFS($AU14="","",$AU14<=15,"0-15",AND($AU14>=16,$AU14<=30),"16-30",AND($AU14>=31,$AU14<=45),"31-45",AND($AU14>=46,$AU14<=60),"46-60",AND($AU14>=61,$AU14<=90),"61-90",AND($AU14>=91),"> 90",AND($AU14>=2000),""),"")} | AW14: {=IFERROR(_xlfn.IFS(OR($M14="",$AM14=""),"",OR($C14="Offered",$C14="Joined"),($AM14-$M14)-$AT14),"")} -> 8 | AX14: {=IFERROR(_xlfn.IFS(OR($M14="",$AS14=""),"",$C14="Joined",($AS14-$M14)-$AT14),"")} -> 49 | AY14: =IFERROR(IF(COUNTIFS('Candidate Tracker'!$E:$E,'Positions Tracker'!$B14,'Candidate Tracker'!$C:$C,"Offer Drop")=0,"",COUNTIFS('Candidate Tracker'!$E:$E,'Positions Tracker'!$B14,'Candidate Tracker'!$C:$C,"Offer Drop")),"") | AZ14: =IFERROR(IF((COUNTIFS('Candidate Tracker'!$D:$D,"<>",'Candidate Tracker'!$D:$D,"<>Screening",'Candidate Tracker'!$D:$D,"<>Screening Pending",'Candidate Tracker'!$D:$D,"<>Candidate Hold",'Candidate Tracker'!$D:$D,"<>Position Cancelled",'Candidate Tracker'!$D:$D,"<>Internal closed")/COUNTIF('Candidate Tracker'!$D:$D,"<>"))=0,"",(COUNTIFS('Candidate Tracker'!$D:$D,"<>",'Candidate Tracker'!$D:$D,"<>Screening",'Candidate Tracker'!$D:$D,"<>Candidate Hold",'Candidate Tracker'!$D:$D,"<>Position Cancelled",'Candidate Tracker'!$D:$D,"<>Internal closed")/COUNTIF('Candidate Tracker'!$D:$D,"<>"))),"") -> 0.88111888 | BA14: =IFERROR(IF(COUNTIFS('Candidate Tracker'!$E:$E,'Positions Tracker'!$B14,'Candidate Tracker'!$I:$I,"Female")=0,"",COUNTIFS('Candidate Tracker'!$E:$E,'Positions Tracker'!$B14,'Candidate Tracker'!$I:$I,"Female")),"") | BB14: =IFERROR(IF(COUNTIFS('Candidate Tracker'!$E:$E,'Positions Tracker'!$B14,'Candidate Tracker'!$I:$I,"male")=0,"",COUNTIFS('Candidate Tracker'!$E:$E,'Positions Tracker'!$B14,'Candidate Tracker'!$I:$I,"male")),"") -> 1 | BC14: =IFERROR(IF(COUNTIFS('Candidate Tracker'!$E:$E,'Positions Tracker'!$B14,'Candidate Tracker'!$C:$C,"<>WIP",'Candidate Tracker'!$C:$C,"<>Hold",'Candidate Tracker'!$C:$C,"<>Cancelled",'Candidate Tracker'!$C:$C,"<>Closed")/COUNTIFS('Candidate Tracker'!$E:$E,'Positions Tracker'!$B14)=0,"",COUNTIFS('Candidate Tracker'!$E:$E,'Positions Tracker'!$B14,'Candidate Tracker'!$C:$C,"<>WIP",'Candidate Tracker'!$C:$C,"<>Hold",'Candidate Tracker'!$C:$C,"<>Cancelled",'Candidate Tracker'!$C:$C,"<>Closed")/COUNTIFS('Candidate Tracker'!$E:$E,'Positions Tracker'!$B14)),"") -> 1 | BD14: =IFERROR(IF($M14="","",TEXT($M14,"MMM-YY")),"") -> Feb-25 | BE14: =IFERROR(IF($AI14="","",TEXT($AI14,"MMM-YY")),"") -> Feb-25 | BF14: =IFERROR(IF($AM14="","",TEXT($AM14,"MMM-YY")),"") -> Feb-25 | BG14: =IFERROR(IF($AS14="","",TEXT($AS14,"MMM-YY")),"") -> Mar-25
A15: =A14+1 -> 14 | B15: 20252046 | C15: Joined | D15: Joined | E15: Engineer I Technical Publications IX | F15: CAM, DAM | G15: Integrated Business Services | H15: Core Engineering | I15: Hemantkumar shinde | J15: Referral | K15: 45691 | L15: 45691 | M15: 45691 | N15: T10 | X15: Pune | Y15: Bharwade, Amruta | Z15: Bharwade, Amruta | AA15: Update as on 8th Feb: comp approval shared with HM on 7th Feb, approval awaited Update as on 21st Feb: Raja Kumar yadav offered | AB15: 10 | AC15: 6 | AE15: Raja Kumar Yadhav | AF15: 9973287316 | AG15: raja.rex92@gmail.com | AH15: Male | AI15: 45695 | AJ15: 45706 | AK15: Pune | AL15: 1050000 | AM15: 45709 | AN15: 45712 | AP15: 45713 | AQ15: 45713 | AR15: 45807 | AS15: 45810 | AT15: =IFERROR(SUM(IF(AND(ISBLANK(T15),ISBLANK(Q15)),0,IF(T15="",TODAY()-Q15,T15-Q15))+IF(AND(ISBLANK(S15),ISBLANK(P15)),0,IF(S15="",TODAY()-P15,S15-P15))+IF(AND(ISBLANK(O15),ISBLANK(R15)),0,IF(R15="",TODAY()-O15,R15-O15))),"") -> 0 | AU15: =IFERROR(IF(($M15=""),"",IF(OR(,$C15="Offer in Progress",$C15="WIP",$C15="WIP/Drop",$C15="WIP/New",$C15="WIP/Hold"),(TODAY()-$M15)-$AT15,"")),"") | AV15: {=IFERROR(_xlfn.IFS($AU15="","",$AU15<=15,"0-15",AND($AU15>=16,$AU15<=30),"16-30",AND($AU15>=31,$AU15<=45),"31-45",AND($AU15>=46,$AU15<=60),"46-60",AND($AU15>=61,$AU15<=90),"61-90",AND($AU15>=91),"> 90",AND($AU15>=2000),""),"")} | AW15: {=IFERROR(_xlfn.IFS(OR($M15="",$AM15=""),"",OR($C15="Offered",$C15="Joined"),($AM15-$M15)-$AT15),"")} -> 18 | AX15: {=IFERROR(_xlfn.IFS(OR($M15="",$AS15=""),"",$C15="Joined",($AS15-$M15)-$AT15),"")} -> 119 | AY15: =IFERROR(IF(COUNTIFS('Candidate Tracker'!$E:$E,'Positions Tracker'!$B15,'Candidate Tracker'!$C:$C,"Offer Drop")=0,"",COUNTIFS('Candidate Tracker'!$E:$E,'Positions Tracker'!$B15,'Candidate Tracker'!$C:$C,"Offer Drop")),"") | AZ15: =IFERROR(IF((COUNTIFS('Candidate Tracker'!$D:$D,"<>",'Candidate Tracker'!$D:$D,"<>Screening",'Candidate Tracker'!$D:$D,"<>Screening Pending",'Candidate Tracker'!$D:$D,"<>Candidate Hold",'Candidate Tracker'!$D:$D,"<>Position Cancelled",'Candidate Tracker'!$D:$D,"<>Internal closed")/COUNTIF('Candidate Tracker'!$D:$D,"<>"))=0,"",(COUNTIFS('Candidate Tracker'!$D:$D,"<>",'Candidate Tracker'!$D:$D,"<>Screening",'Candidate Tracker'!$D:$D,"<>Candidate Hold",'Candidate Tracker'!$D:$D,"<>Position Cancelled",'Candidate Tracker'!$D:$D,"<>Internal closed")/COUNTIF('Candidate Tracker'!$D:$D,"<>"))),"") -> 0.88111888 | BA15: =IFERROR(IF(COUNTIFS('Candidate Tracker'!$E:$E,'Positions Tracker'!$B15,'Candidate Tracker'!$I:$I,"Female")=0,"",COUNTIFS('Candidate Tracker'!$E:$E,'Positions Tracker'!$B15,'Candidate Tracker'!$I:$I,"Female")),"") | BB15: =IFERROR(IF(COUNTIFS('Candidate Tracker'!$E:$E,'Positions Tracker'!$B15,'Candidate Tracker'!$I:$I,"male")=0,"",COUNTIFS('Candidate Tracker'!$E:$E,'Positions Tracker'!$B15,'Candidate Tracker'!$I:$I,"male")),"") -> 1 | BC15: =IFERROR(IF(COUNTIFS('Candidate Tracker'!$E:$E,'Positions Tracker'!$B15,'Candidate Tracker'!$C:$C,"<>WIP",'Candidate Tracker'!$C:$C,"<>Hold",'Candidate Tracker'!$C:$C,"<>Cancelled",'Candidate Tracker'!$C:$C,"<>Closed")/COUNTIFS('Candidate Tracker'!$E:$E,'Positions Tracker'!$B15)=0,"",COUNTIFS('Candidate Tracker'!$E:$E,'Positions Tracker'!$B15,'Candidate Tracker'!$C:$C,"<>WIP",'Candidate Tracker'!$C:$C,"<>Hold",'Candidate Tracker'!$C:$C,"<>Cancelled",'Candidate Tracker'!$C:$C,"<>Closed")/COUNTIFS('Candidate Tracker'!$E:$E,'Positions Tracker'!$B15)),"") -> 1 | BD15: =IFERROR(IF($M15="","",TEXT($M15,"MMM-YY")),"") -> Feb-25 | BE15: =IFERROR(IF($AI15="","",TEXT($AI15,"MMM-YY")),"") -> Feb-25 | BF15: =IFERROR(IF($AM15="","",TEXT($AM15,"MMM-YY")),"") -> Feb-25 | BG15: =IFERROR(IF($AS15="","",TEXT($AS15,"MMM-YY")),"") -> Jun-25
A16: =A15+1 -> 15 | B16: 20254425 | C16: Joined | D16: Joined | E16: Manager Materials and Manufacturing Planning | F16: PPC | G16: India Business | H16: Core Engineering | I16: Ankush Mehta | J16: External | K16: 45580 | L16: 45580 | M16: 45580 | N16: M2 | O16: 45615 | P16: 45649 | Q16: 45706 | U16: 13 | X16: Pune | Y16: Bharwade, Amruta | Z16: Bharwade, Amruta | AA16: Update on 8th feb-2 Interviews scheduled, 3 profiles shared for shortlisting Update as on 21st Feb 1 final interview is scheduled | AB16: 27 | AC16: 24 | AE16: Amar Lahoti | AF16: 8983128692 | AG16: amar.lahoti123@gmail.com | AH16: Male | AI16: 45742 | AJ16: 45764 | AK16: Pune | AL16: 2341410 | AM16: 45764 | AN16: 45764 | AP16: 45765 | AQ16: 45765 | AR16: 45827 | AS16: 45831 | AT16: =IFERROR(SUM(IF(AND(ISBLANK(T16),ISBLANK(Q16)),0,IF(T16="",TODAY()-Q16,T16-Q16))+IF(AND(ISBLANK(S16),ISBLANK(P16)),0,IF(S16="",TODAY()-P16,S16-P16))+IF(AND(ISBLANK(O16),ISBLANK(R16)),0,IF(R16="",TODAY()-O16,R16-O16))),"") -> 1033 | AU16: =IFERROR(IF(($M16=""),"",IF(OR(,$C16="Offer in Progress",$C16="WIP",$C16="WIP/Drop",$C16="WIP/New",$C16="WIP/Hold"),(TODAY()-$M16)-$AT16,"")),"") | AV16: {=IFERROR(_xlfn.IFS($AU16="","",$AU16<=15,"0-15",AND($AU16>=16,$AU16<=30),"16-30",AND($AU16>=31,$AU16<=45),"31-45",AND($AU16>=46,$AU16<=60),"46-60",AND($AU16>=61,$AU16<=90),"61-90",AND($AU16>=91),"> 90",AND($AU16>=2000),""),"")} | AW16: {=IFERROR(_xlfn.IFS(OR($M16="",$AM16=""),"",OR($C16="Offered",$C16="Joined"),($AM16-$M16)-$AT16),"")} -> -849 | AX16: {=IFERROR(_xlfn.IFS(OR($M16="",$AS16=""),"",$C16="Joined",($AS16-$M16)-$AT16),"")} -> -782 | AY16: =IFERROR(IF(COUNTIFS('Candidate Tracker'!$E:$E,'Positions Tracker'!$B16,'Candidate Tracker'!$C:$C,"Offer Drop")=0,"",COUNTIFS('Candidate Tracker'!$E:$E,'Positions Tracker'!$B16,'Candidate Tracker'!$C:$C,"Offer Drop")),"") | AZ16: =IFERROR(IF((COUNTIFS('Candidate Tracker'!$D:$D,"<>",'Candidate Tracker'!$D:$D,"<>Screening",'Candidate Tracker'!$D:$D,"<>Screening Pending",'Candidate Tracker'!$D:$D,"<>Candidate Hold",'Candidate Tracker'!$D:$D,"<>Position Cancelled",'Candidate Tracker'!$D:$D,"<>Internal closed")/COUNTIF('Candidate Tracker'!$D:$D,"<>"))=0,"",(COUNTIFS('Candidate Tracker'!$D:$D,"<>",'Candidate Tracker'!$D:$D,"<>Screening",'Candidate Tracker'!$D:$D,"<>Candidate Hold",'Candidate Tracker'!$D:$D,"<>Position Cancelled",'Candidate Tracker'!$D:$D,"<>Internal closed")/COUNTIF('Candidate Tracker'!$D:$D,"<>"))),"") -> 0.88111888 | BA16: =IFERROR(IF(COUNTIFS('Candidate Tracker'!$E:$E,'Positions Tracker'!$B16,'Candidate Tracker'!$I:$I,"Female")=0,"",COUNTIFS('Candidate Tracker'!$E:$E,'Positions Tracker'!$B16,'Candidate Tracker'!$I:$I,"Female")),"") | BB16: =IFERROR(IF(COUNTIFS('Candidate Tracker'!$E:$E,'Positions Tracker'!$B16,'Candidate Tracker'!$I:$I,"male")=0,"",COUNTIFS('Candidate Tracker'!$E:$E,'Positions Tracker'!$B16,'Candidate Tracker'!$I:$I,"male")),"") | BC16: =IFERROR(IF(COUNTIFS('Candidate Tracker'!$E:$E,'Positions Tracker'!$B16,'Candidate Tracker'!$C:$C,"<>WIP",'Candidate Tracker'!$C:$C,"<>Hold",'Candidate Tracker'!$C:$C,"<>Cancelled",'Candidate Tracker'!$C:$C,"<>Closed")/COUNTIFS('Candidate Tracker'!$E:$E,'Positions Tracker'!$B16)=0,"",COUNTIFS('Candidate Tracker'!$E:$E,'Positions Tracker'!$B16,'Candidate Tracker'!$C:$C,"<>WIP",'Candidate Tracker'!$C:$C,"<>Hold",'Candidate Tracker'!$C:$C,"<>Cancelled",'Candidate Tracker'!$C:$C,"<>Closed")/COUNTIFS('Candidate Tracker'!$E:$E,'Positions Tracker'!$B16)),"") | BD16: =IFERROR(IF($M16="","",TEXT($M16,"MMM-YY")),"") -> Oct-24 | BE16: =IFERROR(IF($AI16="","",TEXT($AI16,"MMM-YY")),"") -> Mar-25 | BF16: =IFERROR(IF($AM16="","",TEXT($AM16,"MMM-YY")),"") -> Apr-25 | BG16: =IFERROR(IF($AS16="","",TEXT($AS16,"MMM-YY")),"") -> Jun-25
A17: =A16+1 -> 16 | B17: TG6 | C17: Joined | D17: Joined | E17: Engineer - Firmware | F17: HMI | G17: Integrated Business Services | H17: HMI | I17: Yogesh S | J17: External | K17: 44999 | L17: 44999 | M17: 45274 | N17: T10 | X17: Pune | Y17: Raisoni, Rushabh | Z17: Priyanka Gupta | AA17: Joined | AE17: Sharikh Shaikh | AF17: 8793916009 | AG17: sharikhshaikh@gmail.com | AH17: Male | AI17: 45296 | AJ17: 45299 | AK17: Pune | AL17: 750000 | AM17: 45299 | AN17: 45299 | AP17: 45302 | AQ17: 45302 | AR17: 45360 | AS17: 45362 | AT17: =IFERROR(SUM(IF(AND(ISBLANK(T17),ISBLANK(Q17)),0,IF(T17="",TODAY()-Q17,T17-Q17))+IF(AND(ISBLANK(S17),ISBLANK(P17)),0,IF(S17="",TODAY()-P17,S17-P17))+IF(AND(ISBLANK(O17),ISBLANK(R17)),0,IF(R17="",TODAY()-O17,R17-O17))),"") -> 0 | AU17: =IFERROR(IF(($M17=""),"",IF(OR(,$C17="Offer in Progress",$C17="WIP",$C17="WIP/Drop",$C17="WIP/New",$C17="WIP/Hold"),(TODAY()-$M17)-$AT17,"")),"") | AV17: {=IFERROR(_xlfn.IFS($AU17="","",$AU17<=15,"0-15",AND($AU17>=16,$AU17<=30),"16-30",AND($AU17>=31,$AU17<=45),"31-45",AND($AU17>=46,$AU17<=60),"46-60",AND($AU17>=61,$AU17<=90),"61-90",AND($AU17>=91),"> 90",AND($AU17>=2000),""),"")} | AW17: {=IFERROR(_xlfn.IFS(OR($M17="",$AM17=""),"",OR($C17="Offered",$C17="Joined"),($AM17-$M17)-$AT17),"")} -> 25 | AX17: {=IFERROR(_xlfn.IFS(OR($M17="",$AS17=""),"",$C17="Joined",($AS17-$M17)-$AT17),"")} -> 88 | AY17: =IFERROR(IF(COUNTIFS('Candidate Tracker'!$E:$E,'Positions Tracker'!$B17,'Candidate Tracker'!$C:$C,"Offer Drop")=0,"",COUNTIFS('Candidate Tracker'!$E:$E,'Positions Tracker'!$B17,'Candidate Tracker'!$C:$C,"Offer Drop")),"") | AZ17: =IFERROR(IF((COUNTIFS('Candidate Tracker'!$D:$D,"<>",'Candidate Tracker'!$D:$D,"<>Screening",'Candidate Tracker'!$D:$D,"<>Screening Pending",'Candidate Tracker'!$D:$D,"<>Candidate Hold",'Candidate Tracker'!$D:$D,"<>Position Cancelled",'Candidate Tracker'!$D:$D,"<>Internal closed")/COUNTIF('Candidate Tracker'!$D:$D,"<>"))=0,"",(COUNTIFS('Candidate Tracker'!$D:$D,"<>",'Candidate Tracker'!$D:$D,"<>Screening",'Candidate Tracker'!$D:$D,"<>Candidate Hold",'Candidate Tracker'!$D:$D,"<>Position Cancelled",'Candidate Tracker'!$D:$D,"<>Internal closed")/COUNTIF('Candidate Tracker'!$D:$D,"<>"))),"") -> 0.88111888 | BA17: =IFERROR(IF(COUNTIFS('Candidate Tracker'!$E:$E,'Positions Tracker'!$B17,'Candidate Tracker'!$I:$I,"Female")=0,"",COUNTIFS('Candidate Tracker'!$E:$E,'Positions Tracker'!$B17,'Candidate Tracker'!$I:$I,"Female")),"") | BB17: =IFERROR(IF(COUNTIFS('Candidate Tracker'!$E:$E,'Positions Tracker'!$B17,'Candidate Tracker'!$I:$I,"male")=0,"",COUNTIFS('Candidate Tracker'!$E:$E,'Positions Tracker'!$B17,'Candidate Tracker'!$I:$I,"male")),"") -> 1 | BC17: =IFERROR(IF(COUNTIFS('Candidate Tracker'!$E:$E,'Positions Tracker'!$B17,'Candidate Tracker'!$C:$C,"<>WIP",'Candidate Tracker'!$C:$C,"<>Hold",'Candidate Tracker'!$C:$C,"<>Cancelled",'Candidate Tracker'!$C:$C,"<>Closed")/COUNTIFS('Candidate Tracker'!$E:$E,'Positions Tracker'!$B17)=0,"",COUNTIFS('Candidate Tracker'!$E:$E,'Positions Tracker'!$B17,'Candidate Tracker'!$C:$C,"<>WIP",'Candidate Tracker'!$C:$C,"<>Hold",'Candidate Tracker'!$C:$C,"<>Cancelled",'Candidate Tracker'!$C:$C,"<>Closed")/COUNTIFS('Candidate Tracker'!$E:$E,'Positions Tracker'!$B17)),"") -> 1 | BD17: =IFERROR(IF($M17="","",TEXT($M17,"MMM-YY")),"") -> Dec-23 | BE17: =IFERROR(IF($AI17="","",TEXT($AI17,"MMM-YY")),"") -> Jan-24 | BF17: =IFERROR(IF($AM17="","",TEXT($AM17,"MMM-YY")),"") -> Jan-24 | BG17: =IFERROR(IF($AS17="","",TEXT($AS17,"MMM-YY")),"") -> Mar-24
A18: =A17+1 -> 17 | B18: 20235907 | C18: Joined | D18: Joined | E18: Sr. Engineer - Full Stack Developer | F18: Dot Net | G18: Integrated Business Services | H18: Thermal | I18: Vaibhav T | J18: External | K18: 45301 | L18: 45301 | M18: 45361 | N18: T12 | X18: Pune | Y18: Raisoni, Rushabh | Z18: Raisoni, Rushabh | AA18: Joined | AE18: Suvarna Thoke | AF18: 8421691758 | AG18: suvarnaahire251192@gmail.com | AH18: Female | AI18: 45443 | AJ18: 45384 | AK18: Pune | AL18: 2200000 | AM18: 45447 | AN18: 45384 | AP18: 45447 | AQ18: 45447 | AR18: 45445 | AS18: 45449 | AT18: =IFERROR(SUM(IF(AND(ISBLANK(T18),ISBLANK(Q18)),0,IF(T18="",TODAY()-Q18,T18-Q18))+IF(AND(ISBLANK(S18),ISBLANK(P18)),0,IF(S18="",TODAY()-P18,S18-P18))+IF(AND(ISBLANK(O18),ISBLANK(R18)),0,IF(R18="",TODAY()-O18,R18-O18))),"") -> 0 | AU18: =IFERROR(IF(($M18=""),"",IF(OR(,$C18="Offer in Progress",$C18="WIP",$C18="WIP/Drop",$C18="WIP/New",$C18="WIP/Hold"),(TODAY()-$M18)-$AT18,"")),"") | AV18: {=IFERROR(_xlfn.IFS($AU18="","",$AU18<=15,"0-15",AND($AU18>=16,$AU18<=30),"16-30",AND($AU18>=31,$AU18<=45),"31-45",AND($AU18>=46,$AU18<=60),"46-60",AND($AU18>=61,$AU18<=90),"61-90",AND($AU18>=91),"> 90",AND($AU18>=2000),""),"")} | AW18: {=IFERROR(_xlfn.IFS(OR($M18="",$AM18=""),"",OR($C18="Offered",$C18="Joined"),($AM18-$M18)-$AT18),"")} -> 86 | AX18: {=IFERROR(_xlfn.IFS(OR($M18="",$AS18=""),"",$C18="Joined",($AS18-$M18)-$AT18),"")} -> 88 | AY18: =IFERROR(IF(COUNTIFS('Candidate Tracker'!$E:$E,'Positions Tracker'!$B18,'Candidate Tracker'!$C:$C,"Offer Drop")=0,"",COUNTIFS('Candidate Tracker'!$E:$E,'Positions Tracker'!$B18,'Candidate Tracker'!$C:$C,"Offer Drop")),"") | AZ18: =IFERROR(IF((COUNTIFS('Candidate Tracker'!$D:$D,"<>",'Candidate Tracker'!$D:$D,"<>Screening",'Candidate Tracker'!$D:$D,"<>Screening Pending",'Candidate Tracker'!$D:$D,"<>Candidate Hold",'Candidate Tracker'!$D:$D,"<>Position Cancelled",'Candidate Tracker'!$D:$D,"<>Internal closed")/COUNTIF('Candidate Tracker'!$D:$D,"<>"))=0,"",(COUNTIFS('Candidate Tracker'!$D:$D,"<>",'Candidate Tracker'!$D:$D,"<>Screening",'Candidate Tracker'!$D:$D,"<>Candidate Hold",'Candidate Tracker'!$D:$D,"<>Position Cancelled",'Candidate Tracker'!$D:$D,"<>Internal closed")/COUNTIF('Candidate Tracker'!$D:$D,"<>"))),"") -> 0.88111888 | BA18: =IFERROR(IF(COUNTIFS('Candidate Tracker'!$E:$E,'Positions Tracker'!$B18,'Candidate Tracker'!$I:$I,"Female")=0,"",COUNTIFS('Candidate Tracker'!$E:$E,'Positions Tracker'!$B18,'Candidate Tracker'!$I:$I,"Female")),"") -> 1 | BB18: =IFERROR(IF(COUNTIFS('Candidate Tracker'!$E:$E,'Positions Tracker'!$B18,'Candidate Tracker'!$I:$I,"male")=0,"",COUNTIFS('Candidate Tracker'!$E:$E,'Positions Tracker'!$B18,'Candidate Tracker'!$I:$I,"male")),"") | BC18: =IFERROR(IF(COUNTIFS('Candidate Tracker'!$E:$E,'Positions Tracker'!$B18,'Candidate Tracker'!$C:$C,"<>WIP",'Candidate Tracker'!$C:$C,"<>Hold",'Candidate Tracker'!$C:$C,"<>Cancelled",'Candidate Tracker'!$C:$C,"<>Closed")/COUNTIFS('Candidate Tracker'!$E:$E,'Positions Tracker'!$B18)=0,"",COUNTIFS('Candidate Tracker'!$E:$E,'Positions Tracker'!$B18,'Candidate Tracker'!$C:$C,"<>WIP",'Candidate Tracker'!$C:$C,"<>Hold",'Candidate Tracker'!$C:$C,"<>Cancelled",'Candidate Tracker'!$C:$C,"<>Closed")/COUNTIFS('Candidate Tracker'!$E:$E,'Positions Tracker'!$B18)),"") -> 1 | BD18: =IFERROR(IF($M18="","",TEXT($M18,"MMM-YY")),"") -> Mar-24 | BE18: =IFERROR(IF($AI18="","",TEXT($AI18,"MMM-YY")),"") -> May-24 | BF18: =IFERROR(IF($AM18="","",TEXT($AM18,"MMM-YY")),"") -> Jun-24 | BG18: =IFERROR(IF($AS18="","",TEXT($AS18,"MMM-YY")),"") -> Jun-24
A19: =A18+1 -> 18 | B19: 20246741 | C19: Cancelled | D19: Position Cancelled | E19: Sr. Engineer Firmware | F19: Firmware | G19: Integrated Business Services | H19: Thermal | I19: Girish Padiyar | J19: External | K19: 45203 | L19: 45203 | M19: 45398 | X19: Pune | Y19: Raisoni, Rushabh | Z19: Raisoni, Rushabh | AA19: 28-Feb-25: 2 candidates L2 rejected , 1 candidate L2 schedule on 3 March . 27 Feb - 3 L2 Scheduled | AT19: =IFERROR(SUM(IF(AND(ISBLANK(T19),ISBLANK(Q19)),0,IF(T19="",TODAY()-Q19,T19-Q19))+IF(AND(ISBLANK(S19),ISBLANK(P19)),0,IF(S19="",TODAY()-P19,S19-P19))+IF(AND(ISBLANK(O19),ISBLANK(R19)),0,IF(R19="",TODAY()-O19,R19-O19))),"") -> 0 | AU19: =IFERROR(IF(($M19=""),"",IF(OR(,$C19="Offer in Progress",$C19="WIP",$C19="WIP/Drop",$C19="WIP/New",$C19="WIP/Hold"),(TODAY()-$M19)-$AT19,"")),"") | AV19: {=IFERROR(_xlfn.IFS($AU19="","",$AU19<=15,"0-15",AND($AU19>=16,$AU19<=30),"16-30",AND($AU19>=31,$AU19<=45),"31-45",AND($AU19>=46,$AU19<=60),"46-60",AND($AU19>=61,$AU19<=90),"61-90",AND($AU19>=91),"> 90",AND($AU19>=2000),""),"")} | AW19: {=IFERROR(_xlfn.IFS(OR($M19="",$AM19=""),"",OR($C19="Offered",$C19="Joined"),($AM19-$M19)-$AT19),"")} | AX19: {=IFERROR(_xlfn.IFS(OR($M19="",$AS19=""),"",$C19="Joined",($AS19-$M19)-$AT19),"")} | AY19: =IFERROR(IF(COUNTIFS('Candidate Tracker'!$E:$E,'Positions Tracker'!$B19,'Candidate Tracker'!$C:$C,"Offer Drop")=0,"",COUNTIFS('Candidate Tracker'!$E:$E,'Positions Tracker'!$B19,'Candidate Tracker'!$C:$C,"Offer Drop")),"") | AZ19: =IFERROR(IF((COUNTIFS('Candidate Tracker'!$D:$D,"<>",'Candidate Tracker'!$D:$D,"<>Screening",'Candidate Tracker'!$D:$D,"<>Screening Pending",'Candidate Tracker'!$D:$D,"<>Candidate Hold",'Candidate Tracker'!$D:$D,"<>Position Cancelled",'Candidate Tracker'!$D:$D,"<>Internal closed")/COUNTIF('Candidate Tracker'!$D:$D,"<>"))=0,"",(COUNTIFS('Candidate Tracker'!$D:$D,"<>",'Candidate Tracker'!$D:$D,"<>Screening",'Candidate Tracker'!$D:$D,"<>Candidate Hold",'Candidate Tracker'!$D:$D,"<>Position Cancelled",'Candidate Tracker'!$D:$D,"<>Internal closed")/COUNTIF('Candidate Tracker'!$D:$D,"<>"))),"") -> 0.88111888 | BA19: =IFERROR(IF(COUNTIFS('Candidate Tracker'!$E:$E,'Positions Tracker'!$B19,'Candidate Tracker'!$I:$I,"Female")=0,"",COUNTIFS('Candidate Tracker'!$E:$E,'Positions Tracker'!$B19,'Candidate Tracker'!$I:$I,"Female")),"") -> 3 | BB19: =IFERROR(IF(COUNTIFS('Candidate Tracker'!$E:$E,'Positions Tracker'!$B19,'Candidate Tracker'!$I:$I,"male")=0,"",COUNTIFS('Candidate Tracker'!$E:$E,'Positions Tracker'!$B19,'Candidate Tracker'!$I:$I,"male")),"") -> 7 | BC19: =IFERROR(IF(COUNTIFS('Candidate Tracker'!$E:$E,'Positions Tracker'!$B19,'Candidate Tracker'!$C:$C,"<>WIP",'Candidate Tracker'!$C:$C,"<>Hold",'Candidate Tracker'!$C:$C,"<>Cancelled",'Candidate Tracker'!$C:$C,"<>Closed")/COUNTIFS('Candidate Tracker'!$E:$E,'Positions Tracker'!$B19)=0,"",COUNTIFS('Candidate Tracker'!$E:$E,'Positions Tracker'!$B19,'Candidate Tracker'!$C:$C,"<>WIP",'Candidate Tracker'!$C:$C,"<>Hold",'Candidate Tracker'!$C:$C,"<>Cancelled",'Candidate Tracker'!$C:$C,"<>Closed")/COUNTIFS('Candidate Tracker'!$E:$E,'Positions Tracker'!$B19)),"") | BD19: =IFERROR(IF($M19="","",TEXT($M19,"MMM-YY")),"") -> Apr-24 | BE19: =IFERROR(IF($AI19="","",TEXT($AI19,"MMM-YY")),"") | BF19: =IFERROR(IF($AM19="","",TEXT($AM19,"MMM-YY")),"") | BG19: =IFERROR(IF($AS19="","",TEXT($AS19,"MMM-YY")),"")
A20: =A19+1 -> 19 | B20: 20245072 | C20: Joined | D20: Joined | E20: Engineer Firmware | F20: Firmware | G20: Integrated Business Services | H20: Core Engineering | I20: Ankur Singh | J20: External | K20: 45181 | L20: 45181 | M20: 45488 | N20: T9 | X20: Pune | Y20: Raisoni, Rushabh | Z20: Raisoni, Rushabh | AA20: Joined | AE20: Sarang Dondal | AF20: 9823065456 | AG20: sarangdondal123@gmail.com | AH20: Male | AI20: 45527 | AJ20: 45530 | AK20: Pune | AL20: 1100000 | AM20: 45541 | AN20: 45530 | AP20: 45541 | AQ20: 45541 | AR20: 45638 | AS20: 45642 | AT20: =IFERROR(SUM(IF(AND(ISBLANK(T20),ISBLANK(Q20)),0,IF(T20="",TODAY()-Q20,T20-Q20))+IF(AND(ISBLANK(S20),ISBLANK(P20)),0,IF(S20="",TODAY()-P20,S20-P20))+IF(AND(ISBLANK(O20),ISBLANK(R20)),0,IF(R20="",TODAY()-O20,R20-O20))),"") -> 0 | AU20: =IFERROR(IF(($M20=""),"",IF(OR(,$C20="Offer in Progress",$C20="WIP",$C20="WIP/Drop",$C20="WIP/New",$C20="WIP/Hold"),(TODAY()-$M20)-$AT20,"")),"") | AV20: {=IFERROR(_xlfn.IFS($AU20="","",$AU20<=15,"0-15",AND($AU20>=16,$AU20<=30),"16-30",AND($AU20>=31,$AU20<=45),"31-45",AND($AU20>=46,$AU20<=60),"46-60",AND($AU20>=61,$AU20<=90),"61-90",AND($AU20>=91),"> 90",AND($AU20>=2000),""),"")} | AW20: {=IFERROR(_xlfn.IFS(OR($M20="",$AM20=""),"",OR($C20="Offered",$C20="Joined"),($AM20-$M20)-$AT20),"")} -> 53 | AX20: {=IFERROR(_xlfn.IFS(OR($M20="",$AS20=""),"",$C20="Joined",($AS20-$M20)-$AT20),"")} -> 154 | AY20: =IFERROR(IF(COUNTIFS('Candidate Tracker'!$E:$E,'Positions Tracker'!$B20,'Candidate Tracker'!$C:$C,"Offer Drop")=0,"",COUNTIFS('Candidate Tracker'!$E:$E,'Positions Tracker'!$B20,'Candidate Tracker'!$C:$C,"Offer Drop")),"") | AZ20: =IFERROR(IF((COUNTIFS('Candidate Tracker'!$D:$D,"<>",'Candidate Tracker'!$D:$D,"<>Screening",'Candidate Tracker'!$D:$D,"<>Screening Pending",'Candidate Tracker'!$D:$D,"<>Candidate Hold",'Candidate Tracker'!$D:$D,"<>Position Cancelled",'Candidate Tracker'!$D:$D,"<>Internal closed")/COUNTIF('Candidate Tracker'!$D:$D,"<>"))=0,"",(COUNTIFS('Candidate Tracker'!$D:$D,"<>",'Candidate Tracker'!$D:$D,"<>Screening",'Candidate Tracker'!$D:$D,"<>Candidate Hold",'Candidate Tracker'!$D:$D,"<>Position Cancelled",'Candidate Tracker'!$D:$D,"<>Internal closed")/COUNTIF('Candidate Tracker'!$D:$D,"<>"))),"") -> 0.88111888 | BA20: =IFERROR(IF(COUNTIFS('Candidate Tracker'!$E:$E,'Positions Tracker'!$B20,'Candidate Tracker'!$I:$I,"Female")=0,"",COUNTIFS('Candidate Tracker'!$E:$E,'Positions Tracker'!$B20,'Candidate Tracker'!$I:$I,"Female")),"") | BB20: =IFERROR(IF(COUNTIFS('Candidate Tracker'!$E:$E,'Positions Tracker'!$B20,'Candidate Tracker'!$I:$I,"male")=0,"",COUNTIFS('Candidate Tracker'!$E:$E,'Positions Tracker'!$B20,'Candidate Tracker'!$I:$I,"male")),"") -> 1 | BC20: =IFERROR(IF(COUNTIFS('Candidate Tracker'!$E:$E,'Positions Tracker'!$B20,'Candidate Tracker'!$C:$C,"<>WIP",'Candidate Tracker'!$C:$C,"<>Hold",'Candidate Tracker'!$C:$C,"<>Cancelled",'Candidate Tracker'!$C:$C,"<>Closed")/COUNTIFS('Candidate Tracker'!$E:$E,'Positions Tracker'!$B20)=0,"",COUNTIFS('Candidate Tracker'!$E:$E,'Positions Tracker'!$B20,'Candidate Tracker'!$C:$C,"<>WIP",'Candidate Tracker'!$C:$C,"<>Hold",'Candidate Tracker'!$C:$C,"<>Cancelled",'Candidate Tracker'!$C:$C,"<>Closed")/COUNTIFS('Candidate Tracker'!$E:$E,'Positions Tracker'!$B20)),"") -> 1 | BD20: =IFERROR(IF($M20="","",TEXT($M20,"MMM-YY")),"") -> Jul-24 | BE20: =IFERROR(IF($AI20="","",TEXT($AI20,"MMM-YY")),"") -> Aug-24 | BF20: =IFERROR(IF($AM20="","",TEXT($AM20,"MMM-YY")),"") -> Sep-24 | BG20: =IFERROR(IF($AS20="","",TEXT($AS20,"MMM-YY")),"") -> Dec-24
A21: =A20+1 -> 20 | B21: TG11 | C21: Joined | D21: Joined | E21: Engineer - PCB Design | F21: PCB Design | G21: Integrated Business Services | H21: HMI | I21: Yogesh S | J21: External | K21: 45327 | L21: 45327 | M21: 45327 | N21: T10 | X21: Pune | Y21: Raisoni, Rushabh | Z21: Raisoni, Rushabh | AA21: Joined | AE21: Chandrashekar Yashoda | AF21: 7989696428 | AG21: y.chandra.chari@gmail.com | AH21: Male | AI21: 45363 | AJ21: 45368 | AK21: Pune | AL21: 1500000 | AM21: 45383 | AN21: 45368 | AP21: 45383 | AQ21: 45383 | AR21: 45386 | AS21: 45390 | AT21: =IFERROR(SUM(IF(AND(ISBLANK(T21),ISBLANK(Q21)),0,IF(T21="",TODAY()-Q21,T21-Q21))+IF(AND(ISBLANK(S21),ISBLANK(P21)),0,IF(S21="",TODAY()-P21,S21-P21))+IF(AND(ISBLANK(O21),ISBLANK(R21)),0,IF(R21="",TODAY()-O21,R21-O21))),"") -> 0 | AU21: =IFERROR(IF(($M21=""),"",IF(OR(,$C21="Offer in Progress",$C21="WIP",$C21="WIP/Drop",$C21="WIP/New",$C21="WIP/Hold"),(TODAY()-$M21)-$AT21,"")),"") | AV21: {=IFERROR(_xlfn.IFS($AU21="","",$AU21<=15,"0-15",AND($AU21>=16,$AU21<=30),"16-30",AND($AU21>=31,$AU21<=45),"31-45",AND($AU21>=46,$AU21<=60),"46-60",AND($AU21>=61,$AU21<=90),"61-90",AND($AU21>=91),"> 90",AND($AU21>=2000),""),"")} | AW21: {=IFERROR(_xlfn.IFS(OR($M21="",$AM21=""),"",OR($C21="Offered",$C21="Joined"),($AM21-$M21)-$AT21),"")} -> 56 | AX21: {=IFERROR(_xlfn.IFS(OR($M21="",$AS21=""),"",$C21="Joined",($AS21-$M21)-$AT21),"")} -> 63 | AY21: =IFERROR(IF(COUNTIFS('Candidate Tracker'!$E:$E,'Positions Tracker'!$B21,'Candidate Tracker'!$C:$C,"Offer Drop")=0,"",COUNTIFS('Candidate Tracker'!$E:$E,'Positions Tracker'!$B21,'Candidate Tracker'!$C:$C,"Offer Drop")),"") | AZ21: =IFERROR(IF((COUNTIFS('Candidate Tracker'!$D:$D,"<>",'Candidate Tracker'!$D:$D,"<>Screening",'Candidate Tracker'!$D:$D,"<>Screening Pending",'Candidate Tracker'!$D:$D,"<>Candidate Hold",'Candidate Tracker'!$D:$D,"<>Position Cancelled",'Candidate Tracker'!$D:$D,"<>Internal closed")/COUNTIF('Candidate Tracker'!$D:$D,"<>"))=0,"",(COUNTIFS('Candidate Tracker'!$D:$D,"<>",'Candidate Tracker'!$D:$D,"<>Screening",'Candidate Tracker'!$D:$D,"<>Candidate Hold",'Candidate Tracker'!$D:$D,"<>Position Cancelled",'Candidate Tracker'!$D:$D,"<>Internal closed")/COUNTIF('Candidate Tracker'!$D:$D,"<>"))),"") -> 0.88111888 | BA21: =IFERROR(IF(COUNTIFS('Candidate Tracker'!$E:$E,'Positions Tracker'!$B21,'Candidate Tracker'!$I:$I,"Female")=0,"",COUNTIFS('Candidate Tracker'!$E:$E,'Positions Tracker'!$B21,'Candidate Tracker'!$I:$I,"Female")),"") | BB21: =IFERROR(IF(COUNTIFS('Candidate Tracker'!$E:$E,'Positions Tracker'!$B21,'Candidate Tracker'!$I:$I,"male")=0,"",COUNTIFS('Candidate Tracker'!$E:$E,'Positions Tracker'!$B21,'Candidate Tracker'!$I:$I,"male")),"") -> 1 | BC21: =IFERROR(IF(COUNTIFS('Candidate Tracker'!$E:$E,'Positions Tracker'!$B21,'Candidate Tracker'!$C:$C,"<>WIP",'Candidate Tracker'!$C:$C,"<>Hold",'Candidate Tracker'!$C:$C,"<>Cancelled",'Candidate Tracker'!$C:$C,"<>Closed")/COUNTIFS('Candidate Tracker'!$E:$E,'Positions Tracker'!$B21)=0,"",COUNTIFS('Candidate Tracker'!$E:$E,'Positions Tracker'!$B21,'Candidate Tracker'!$C:$C,"<>WIP",'Candidate Tracker'!$C:$C,"<>Hold",'Candidate Tracker'!$C:$C,"<>Cancelled",'Candidate Tracker'!$C:$C,"<>Closed")/COUNTIFS('Candidate Tracker'!$E:$E,'Positions Tracker'!$B21)),"") -> 1 | BD21: =IFERROR(IF($M21="","",TEXT($M21,"MMM-YY")),"") -> Feb-24 | BE21: =IFERROR(IF($AI21="","",TEXT($AI21,"MMM-YY")),"") -> Mar-24 | BF21: =IFERROR(IF($AM21="","",TEXT($AM21,"MMM-YY")),"") -> Apr-24 | BG21: =IFERROR(IF($AS21="","",TEXT($AS21,"MMM-YY")),"") -> Apr-24
A22: =A21+1 -> 21 | B22: 20246912 | C22: Joined | D22: Joined | E22: Engineer - Full Stack Developer | F22: ASP.NET | G22: Integrated Business Services | H22: Thermal | I22: Vaibhav T | J22: External | K22: 45301 | L22: 45301 | M22: 45545 | N22: T8 | X22: Pune | Y22: Raisoni, Rushabh | Z22: Raisoni, Rushabh | AA22: Joined | AE22: Rutuja Nafade | AF22: 7378871101 | AG22: rutujadnaphade@gmail.com | AH22: Female | AI22: 45566 | AJ22: 45571 | AK22: Pune | AL22: 760000 | AM22: 45575 | AN22: 45571 | AP22: 45575 | AQ22: 45575 | AR22: 45631 | AS22: 45635 | AT22: =IFERROR(SUM(IF(AND(ISBLANK(T22),ISBLANK(Q22)),0,IF(T22="",TODAY()-Q22,T22-Q22))+IF(AND(ISBLANK(S22),ISBLANK(P22)),0,IF(S22="",TODAY()-P22,S22-P22))+IF(AND(ISBLANK(O22),ISBLANK(R22)),0,IF(R22="",TODAY()-O22,R22-O22))),"") -> 0 | AU22: =IFERROR(IF(($M22=""),"",IF(OR(,$C22="Offer in Progress",$C22="WIP",$C22="WIP/Drop",$C22="WIP/New",$C22="WIP/Hold"),(TODAY()-$M22)-$AT22,"")),"") | AV22: {=IFERROR(_xlfn.IFS($AU22="","",$AU22<=15,"0-15",AND($AU22>=16,$AU22<=30),"16-30",AND($AU22>=31,$AU22<=45),"31-45",AND($AU22>=46,$AU22<=60),"46-60",AND($AU22>=61,$AU22<=90),"61-90",AND($AU22>=91),"> 90",AND($AU22>=2000),""),"")} | AW22: {=IFERROR(_xlfn.IFS(OR($M22="",$AM22=""),"",OR($C22="Offered",$C22="Joined"),($AM22-$M22)-$AT22),"")} -> 30 | AX22: {=IFERROR(_xlfn.IFS(OR($M22="",$AS22=""),"",$C22="Joined",($AS22-$M22)-$AT22),"")} -> 90 | AY22: =IFERROR(IF(COUNTIFS('Candidate Tracker'!$E:$E,'Positions Tracker'!$B22,'Candidate Tracker'!$C:$C,"Offer Drop")=0,"",COUNTIFS('Candidate Tracker'!$E:$E,'Positions Tracker'!$B22,'Candidate Tracker'!$C:$C,"Offer Drop")),"") | AZ22: =IFERROR(IF((COUNTIFS('Candidate Tracker'!$D:$D,"<>",'Candidate Tracker'!$D:$D,"<>Screening",'Candidate Tracker'!$D:$D,"<>Screening Pending",'Candidate Tracker'!$D:$D,"<>Candidate Hold",'Candidate Tracker'!$D:$D,"<>Position Cancelled",'Candidate Tracker'!$D:$D,"<>Internal closed")/COUNTIF('Candidate Tracker'!$D:$D,"<>"))=0,"",(COUNTIFS('Candidate Tracker'!$D:$D,"<>",'Candidate Tracker'!$D:$D,"<>Screening",'Candidate Tracker'!$D:$D,"<>Candidate Hold",'Candidate Tracker'!$D:$D,"<>Position Cancelled",'Candidate Tracker'!$D:$D,"<>Internal closed")/COUNTIF('Candidate Tracker'!$D:$D,"<>"))),"") -> 0.88111888 | BA22: =IFERROR(IF(COUNTIFS('Candidate Tracker'!$E:$E,'Positions Tracker'!$B22,'Candidate Tracker'!$I:$I,"Female")=0,"",COUNTIFS('Candidate Tracker'!$E:$E,'Positions Tracker'!$B22,'Candidate Tracker'!$I:$I,"Female")),"") -> 1 | BB22: =IFERROR(IF(COUNTIFS('Candidate Tracker'!$E:$E,'Positions Tracker'!$B22,'Candidate Tracker'!$I:$I,"male")=0,"",COUNTIFS('Candidate Tracker'!$E:$E,'Positions Tracker'!$B22,'Candidate Tracker'!$I:$I,"male")),"") | BC22: =IFERROR(IF(COUNTIFS('Candidate Tracker'!$E:$E,'Positions Tracker'!$B22,'Candidate Tracker'!$C:$C,"<>WIP",'Candidate Tracker'!$C:$C,"<>Hold",'Candidate Tracker'!$C:$C,"<>Cancelled",'Candidate Tracker'!$C:$C,"<>Closed")/COUNTIFS('Candidate Tracker'!$E:$E,'Positions Tracker'!$B22)=0,"",COUNTIFS('Candidate Tracker'!$E:$E,'Positions Tracker'!$B22,'Candidate Tracker'!$C:$C,"<>WIP",'Candidate Tracker'!$C:$C,"<>Hold",'Candidate Tracker'!$C:$C,"<>Cancelled",'Candidate Tracker'!$C:$C,"<>Closed")/COUNTIFS('Candidate Tracker'!$E:$E,'Positions Tracker'!$B22)),"") -> 1 | BD22: =IFERROR(IF($M22="","",TEXT($M22,"MMM-YY")),"") -> Sep-24 | BE22: =IFERROR(IF($AI22="","",TEXT($AI22,"MMM-YY")),"") -> Oct-24 | BF22: =IFERROR(IF($AM22="","",TEXT($AM22,"MMM-YY")),"") -> Oct-24 | BG22: =IFERROR(IF($AS22="","",TEXT($AS22,"MMM-YY")),"") -> Dec-24
A23: =A22+1 -> 22 | B23: TG8 | C23: Joined | D23: Joined | E23: Engineer - Angular | F23: Full Stack/ Angular | G23: Integrated Business Services | H23: Thermal | I23: Vaibhav T | J23: External | K23: 45294 | L23: 45294 | M23: 45294 | N23: T10 | X23: Pune | Y23: Raisoni, Rushabh | Z23: Raisoni, Rushabh | AA23: Joined | AE23: Shubham Khairnar | AF23: 9850569538 | AG23: shubhamk.khairnar@gmail.com | AH23: Male | AI23: 45252 | AJ23: 45257 | AK23: Pune | AL23: 1000000 | AM23: 45257 | AN23: 45257 | AP23: 45258 | AQ23: 45258 | AR23: 45267 | AS23: 45271 | AT23: =IFERROR(SUM(IF(AND(ISBLANK(T23),ISBLANK(Q23)),0,IF(T23="",TODAY()-Q23,T23-Q23))+IF(AND(ISBLANK(S23),ISBLANK(P23)),0,IF(S23="",TODAY()-P23,S23-P23))+IF(AND(ISBLANK(O23),ISBLANK(R23)),0,IF(R23="",TODAY()-O23,R23-O23))),"") -> 0 | AU23: =IFERROR(IF(($M23=""),"",IF(OR(,$C23="Offer in Progress",$C23="WIP",$C23="WIP/Drop",$C23="WIP/New",$C23="WIP/Hold"),(TODAY()-$M23)-$AT23,"")),"") | AV23: {=IFERROR(_xlfn.IFS($AU23="","",$AU23<=15,"0-15",AND($AU23>=16,$AU23<=30),"16-30",AND($AU23>=31,$AU23<=45),"31-45",AND($AU23>=46,$AU23<=60),"46-60",AND($AU23>=61,$AU23<=90),"61-90",AND($AU23>=91),"> 90",AND($AU23>=2000),""),"")} | AW23: {=IFERROR(_xlfn.IFS(OR($M23="",$AM23=""),"",OR($C23="Offered",$C23="Joined"),($AM23-$M23)-$AT23),"")} -> -37 | AX23: {=IFERROR(_xlfn.IFS(OR($M23="",$AS23=""),"",$C23="Joined",($AS23-$M23)-$AT23),"")} -> -23 | AY23: =IFERROR(IF(COUNTIFS('Candidate Tracker'!$E:$E,'Positions Tracker'!$B23,'Candidate Tracker'!$C:$C,"Offer Drop")=0,"",COUNTIFS('Candidate Tracker'!$E:$E,'Positions Tracker'!$B23,'Candidate Tracker'!$C:$C,"Offer Drop")),"") | AZ23: =IFERROR(IF((COUNTIFS('Candidate Tracker'!$D:$D,"<>",'Candidate Tracker'!$D:$D,"<>Screening",'Candidate Tracker'!$D:$D,"<>Screening Pending",'Candidate Tracker'!$D:$D,"<>Candidate Hold",'Candidate Tracker'!$D:$D,"<>Position Cancelled",'Candidate Tracker'!$D:$D,"<>Internal closed")/COUNTIF('Candidate Tracker'!$D:$D,"<>"))=0,"",(COUNTIFS('Candidate Tracker'!$D:$D,"<>",'Candidate Tracker'!$D:$D,"<>Screening",'Candidate Tracker'!$D:$D,"<>Candidate Hold",'Candidate Tracker'!$D:$D,"<>Position Cancelled",'Candidate Tracker'!$D:$D,"<>Internal closed")/COUNTIF('Candidate Tracker'!$D:$D,"<>"))),"") -> 0.88111888 | BA23: =IFERROR(IF(COUNTIFS('Candidate Tracker'!$E:$E,'Positions Tracker'!$B23,'Candidate Tracker'!$I:$I,"Female")=0,"",COUNTIFS('Candidate Tracker'!$E:$E,'Positions Tracker'!$B23,'Candidate Tracker'!$I:$I,"Female")),"") | BB23: =IFERROR(IF(COUNTIFS('Candidate Tracker'!$E:$E,'Positions Tracker'!$B23,'Candidate Tracker'!$I:$I,"male")=0,"",COUNTIFS('Candidate Tracker'!$E:$E,'Positions Tracker'!$B23,'Candidate Tracker'!$I:$I,"male")),"") -> 1 | BC23: =IFERROR(IF(COUNTIFS('Candidate Tracker'!$E:$E,'Positions Tracker'!$B23,'Candidate Tracker'!$C:$C,"<>WIP",'Candidate Tracker'!$C:$C,"<>Hold",'Candidate Tracker'!$C:$C,"<>Cancelled",'Candidate Tracker'!$C:$C,"<>Closed")/COUNTIFS('Candidate Tracker'!$E:$E,'Positions Tracker'!$B23)=0,"",COUNTIFS('Candidate Tracker'!$E:$E,'Positions Tracker'!$B23,'Candidate Tracker'!$C:$C,"<>WIP",'Candidate Tracker'!$C:$C,"<>Hold",'Candidate Tracker'!$C:$C,"<>Cancelled",'Candidate Tracker'!$C:$C,"<>Closed")/COUNTIFS('Candidate Tracker'!$E:$E,'Positions Tracker'!$B23)),"") -> 1 | BD23: =IFERROR(IF($M23="","",TEXT($M23,"MMM-YY")),"") -> Jan-24 | BE23: =IFERROR(IF($AI23="","",TEXT($AI23,"MMM-YY")),"") -> Nov-23 | BF23: =IFERROR(IF($AM23="","",TEXT($AM23,"MMM-YY")),"") -> Nov-23 | BG23: =IFERROR(IF($AS23="","",TEXT($AS23,"MMM-YY")),"") -> Dec-23
A24: =A23+1 -> 23 | B24: TG7 | C24: Joined | D24: Joined | E24: Engineer - Angular | F24: Full Stack | G24: Integrated Business Services | H24: Thermal | I24: Vaibhav T | J24: External | K24: 45232 | L24: 45232 | M24: 45232 | N24: T10 | X24: Pune | Y24: Raisoni, Rushabh | Z24: Raisoni, Rushabh | AA24: Joined | AE24: Tejaswini Chikhale | AF24: 8668520481 | AG24: tejaswini.it.2023@gmail.com | AH24: Female | AI24: 45257 | AJ24: 45260 | AK24: Pune | AL24: 1800000 | AM24: 45260 | AN24: 45260 | AP24: 45264 | AQ24: 45264 | AR24: 45267 | AS24: 45271 | AT24: =IFERROR(SUM(IF(AND(ISBLANK(T24),ISBLANK(Q24)),0,IF(T24="",TODAY()-Q24,T24-Q24))+IF(AND(ISBLANK(S24),ISBLANK(P24)),0,IF(S24="",TODAY()-P24,S24-P24))+IF(AND(ISBLANK(O24),ISBLANK(R24)),0,IF(R24="",TODAY()-O24,R24-O24))),"") -> 0 | AU24: =IFERROR(IF(($M24=""),"",IF(OR(,$C24="Offer in Progress",$C24="WIP",$C24="WIP/Drop",$C24="WIP/New",$C24="WIP/Hold"),(TODAY()-$M24)-$AT24,"")),"") | AV24: {=IFERROR(_xlfn.IFS($AU24="","",$AU24<=15,"0-15",AND($AU24>=16,$AU24<=30),"16-30",AND($AU24>=31,$AU24<=45),"31-45",AND($AU24>=46,$AU24<=60),"46-60",AND($AU24>=61,$AU24<=90),"61-90",AND($AU24>=91),"> 90",AND($AU24>=2000),""),"")} | AW24: {=IFERROR(_xlfn.IFS(OR($M24="",$AM24=""),"",OR($C24="Offered",$C24="Joined"),($AM24-$M24)-$AT24),"")} -> 28 | AX24: {=IFERROR(_xlfn.IFS(OR($M24="",$AS24=""),"",$C24="Joined",($AS24-$M24)-$AT24),"")} -> 39 | AY24: =IFERROR(IF(COUNTIFS('Candidate Tracker'!$E:$E,'Positions Tracker'!$B24,'Candidate Tracker'!$C:$C,"Offer Drop")=0,"",COUNTIFS('Candidate Tracker'!$E:$E,'Positions Tracker'!$B24,'Candidate Tracker'!$C:$C,"Offer Drop")),"") | AZ24: =IFERROR(IF((COUNTIFS('Candidate Tracker'!$D:$D,"<>",'Candidate Tracker'!$D:$D,"<>Screening",'Candidate Tracker'!$D:$D,"<>Screening Pending",'Candidate Tracker'!$D:$D,"<>Candidate Hold",'Candidate Tracker'!$D:$D,"<>Position Cancelled",'Candidate Tracker'!$D:$D,"<>Internal closed")/COUNTIF('Candidate Tracker'!$D:$D,"<>"))=0,"",(COUNTIFS('Candidate Tracker'!$D:$D,"<>",'Candidate Tracker'!$D:$D,"<>Screening",'Candidate Tracker'!$D:$D,"<>Candidate Hold",'Candidate Tracker'!$D:$D,"<>Position Cancelled",'Candidate Tracker'!$D:$D,"<>Internal closed")/COUNTIF('Candidate Tracker'!$D:$D,"<>"))),"") -> 0.88111888 | BA24: =IFERROR(IF(COUNTIFS('Candidate Tracker'!$E:$E,'Positions Tracker'!$B24,'Candidate Tracker'!$I:$I,"Female")=0,"",COUNTIFS('Candidate Tracker'!$E:$E,'Positions Tracker'!$B24,'Candidate Tracker'!$I:$I,"Female")),"") -> 1 | BB24: =IFERROR(IF(COUNTIFS('Candidate Tracker'!$E:$E,'Positions Tracker'!$B24,'Candidate Tracker'!$I:$I,"male")=0,"",COUNTIFS('Candidate Tracker'!$E:$E,'Positions Tracker'!$B24,'Candidate Tracker'!$I:$I,"male")),"") | BC24: =IFERROR(IF(COUNTIFS('Candidate Tracker'!$E:$E,'Positions Tracker'!$B24,'Candidate Tracker'!$C:$C,"<>WIP",'Candidate Tracker'!$C:$C,"<>Hold",'Candidate Tracker'!$C:$C,"<>Cancelled",'Candidate Tracker'!$C:$C,"<>Closed")/COUNTIFS('Candidate Tracker'!$E:$E,'Positions Tracker'!$B24)=0,"",COUNTIFS('Candidate Tracker'!$E:$E,'Positions Tracker'!$B24,'Candidate Tracker'!$C:$C,"<>WIP",'Candidate Tracker'!$C:$C,"<>Hold",'Candidate Tracker'!$C:$C,"<>Cancelled",'Candidate Tracker'!$C:$C,"<>Closed")/COUNTIFS('Candidate Tracker'!$E:$E,'Positions Tracker'!$B24)),"") -> 1 | BD24: =IFERROR(IF($M24="","",TEXT($M24,"MMM-YY")),"") -> Nov-23 | BE24: =IFERROR(IF($AI24="","",TEXT($AI24,"MMM-YY")),"") -> Nov-23 | BF24: =IFERROR(IF($AM24="","",TEXT($AM24,"MMM-YY")),"") -> Nov-23 | BG24: =IFERROR(IF($AS24="","",TEXT($AS24,"MMM-YY")),"") -> Dec-23
A25: =A24+1 -> 24 | B25: TG9 | C25: Joined | D25: Joined | E25: Sr. Engineer - Electrical | F25: Electrical | G25: Integrated Business Services | H25: SP UPS | I25: Dipak G | J25: External | K25: 45217 | L25: 45217 | M25: 45217 | N25: T12 | X25: Pune | Y25: Raisoni, Rushabh | Z25: Raisoni, Rushabh | AA25: Joined | AE25: Sujit Barman | AF25: 8097756156 | AG25: sujitmbarman@gmail.com | AH25: Male | AI25: 45257 | AJ25: 45260 | AK25: Pune | AL25: 2050000 | AM25: 45260 | AN25: 45260 | AP25: 45261 | AQ25: 45261 | AR25: 45344 | AS25: 45348 | AT25: =IFERROR(SUM(IF(AND(ISBLANK(T25),ISBLANK(Q25)),0,IF(T25="",TODAY()-Q25,T25-Q25))+IF(AND(ISBLANK(S25),ISBLANK(P25)),0,IF(S25="",TODAY()-P25,S25-P25))+IF(AND(ISBLANK(O25),ISBLANK(R25)),0,IF(R25="",TODAY()-O25,R25-O25))),"") -> 0 | AU25: =IFERROR(IF(($M25=""),"",IF(OR(,$C25="Offer in Progress",$C25="WIP",$C25="WIP/Drop",$C25="WIP/New",$C25="WIP/Hold"),(TODAY()-$M25)-$AT25,"")),"") | AV25: {=IFERROR(_xlfn.IFS($AU25="","",$AU25<=15,"0-15",AND($AU25>=16,$AU25<=30),"16-30",AND($AU25>=31,$AU25<=45),"31-45",AND($AU25>=46,$AU25<=60),"46-60",AND($AU25>=61,$AU25<=90),"61-90",AND($AU25>=91),"> 90",AND($AU25>=2000),""),"")} | AW25: {=IFERROR(_xlfn.IFS(OR($M25="",$AM25=""),"",OR($C25="Offered",$C25="Joined"),($AM25-$M25)-$AT25),"")} -> 43 | AX25: {=IFERROR(_xlfn.IFS(OR($M25="",$AS25=""),"",$C25="Joined",($AS25-$M25)-$AT25),"")} -> 131 | AY25: =IFERROR(IF(COUNTIFS('Candidate Tracker'!$E:$E,'Positions Tracker'!$B25,'Candidate Tracker'!$C:$C,"Offer Drop")=0,"",COUNTIFS('Candidate Tracker'!$E:$E,'Positions Tracker'!$B25,'Candidate Tracker'!$C:$C,"Offer Drop")),"") | AZ25: =IFERROR(IF((COUNTIFS('Candidate Tracker'!$D:$D,"<>",'Candidate Tracker'!$D:$D,"<>Screening",'Candidate Tracker'!$D:$D,"<>Screening Pending",'Candidate Tracker'!$D:$D,"<>Candidate Hold",'Candidate Tracker'!$D:$D,"<>Position Cancelled",'Candidate Tracker'!$D:$D,"<>Internal closed")/COUNTIF('Candidate Tracker'!$D:$D,"<>"))=0,"",(COUNTIFS('Candidate Tracker'!$D:$D,"<>",'Candidate Tracker'!$D:$D,"<>Screening",'Candidate Tracker'!$D:$D,"<>Candidate Hold",'Candidate Tracker'!$D:$D,"<>Position Cancelled",'Candidate Tracker'!$D:$D,"<>Internal closed")/COUNTIF('Candidate Tracker'!$D:$D,"<>"))),"") -> 0.88111888 | BA25: =IFERROR(IF(COUNTIFS('Candidate Tracker'!$E:$E,'Positions Tracker'!$B25,'Candidate Tracker'!$I:$I,"Female")=0,"",COUNTIFS('Candidate Tracker'!$E:$E,'Positions Tracker'!$B25,'Candidate Tracker'!$I:$I,"Female")),"") | BB25: =IFERROR(IF(COUNTIFS('Candidate Tracker'!$E:$E,'Positions Tracker'!$B25,'Candidate Tracker'!$I:$I,"male")=0,"",COUNTIFS('Candidate Tracker'!$E:$E,'Positions Tracker'!$B25,'Candidate Tracker'!$I:$I,"male")),"") -> 1 | BC25: =IFERROR(IF(COUNTIFS('Candidate Tracker'!$E:$E,'Positions Tracker'!$B25,'Candidate Tracker'!$C:$C,"<>WIP",'Candidate Tracker'!$C:$C,"<>Hold",'Candidate Tracker'!$C:$C,"<>Cancelled",'Candidate Tracker'!$C:$C,"<>Closed")/COUNTIFS('Candidate Tracker'!$E:$E,'Positions Tracker'!$B25)=0,"",COUNTIFS('Candidate Tracker'!$E:$E,'Positions Tracker'!$B25,'Candidate Tracker'!$C:$C,"<>WIP",'Candidate Tracker'!$C:$C,"<>Hold",'Candidate Tracker'!$C:$C,"<>Cancelled",'Candidate Tracker'!$C:$C,"<>Closed")/COUNTIFS('Candidate Tracker'!$E:$E,'Positions Tracker'!$B25)),"") -> 1 | BD25: =IFERROR(IF($M25="","",TEXT($M25,"MMM-YY")),"") -> Oct-23 | BE25: =IFERROR(IF($AI25="","",TEXT($AI25,"MMM-YY")),"") -> Nov-23 | BF25: =IFERROR(IF($AM25="","",TEXT($AM25,"MMM-YY")),"") -> Nov-23 | BG25: =IFERROR(IF($AS25="","",TEXT($AS25,"MMM-YY")),"") -> Feb-24
A26: =A25+1 -> 25 | B26: TG4 | C26: Joined | D26: Joined | E26: Sr Firmware Engineer | F26: Firmware | G26: Integrated Business Services | H26: ITS | I26: Sameer U | J26: External | K26: 45329 | L26: 45329 | M26: 45434 | N26: T14 | X26: Pune | Y26: Raisoni, Rushabh | Z26: Raisoni, Rushabh | AA26: Joined | AE26: Chaitanya Jibhakate | AF26: 9096115118 | AG26: chaitanya.n.jibhakate@gmail.com | AH26: Male | AI26: 45392 | AJ26: 45397 | AK26: Pune | AL26: 3000000 | AM26: 45405 | AN26: 45397 | AP26: 45405 | AQ26: 45405 | AR26: 45498 | AS26: 45502 | AT26: =IFERROR(SUM(IF(AND(ISBLANK(T26),ISBLANK(Q26)),0,IF(T26="",TODAY()-Q26,T26-Q26))+IF(AND(ISBLANK(S26),ISBLANK(P26)),0,IF(S26="",TODAY()-P26,S26-P26))+IF(AND(ISBLANK(O26),ISBLANK(R26)),0,IF(R26="",TODAY()-O26,R26-O26))),"") -> 0 | AU26: =IFERROR(IF(($M26=""),"",IF(OR(,$C26="Offer in Progress",$C26="WIP",$C26="WIP/Drop",$C26="WIP/New",$C26="WIP/Hold"),(TODAY()-$M26)-$AT26,"")),"") | AV26: {=IFERROR(_xlfn.IFS($AU26="","",$AU26<=15,"0-15",AND($AU26>=16,$AU26<=30),"16-30",AND($AU26>=31,$AU26<=45),"31-45",AND($AU26>=46,$AU26<=60),"46-60",AND($AU26>=61,$AU26<=90),"61-90",AND($AU26>=91),"> 90",AND($AU26>=2000),""),"")} | AW26: {=IFERROR(_xlfn.IFS(OR($M26="",$AM26=""),"",OR($C26="Offered",$C26="Joined"),($AM26-$M26)-$AT26),"")} -> -29 | AX26: {=IFERROR(_xlfn.IFS(OR($M26="",$AS26=""),"",$C26="Joined",($AS26-$M26)-$AT26),"")} -> 68 | AY26: =IFERROR(IF(COUNTIFS('Candidate Tracker'!$E:$E,'Positions Tracker'!$B26,'Candidate Tracker'!$C:$C,"Offer Drop")=0,"",COUNTIFS('Candidate Tracker'!$E:$E,'Positions Tracker'!$B26,'Candidate Tracker'!$C:$C,"Offer Drop")),"") | AZ26: =IFERROR(IF((COUNTIFS('Candidate Tracker'!$D:$D,"<>",'Candidate Tracker'!$D:$D,"<>Screening",'Candidate Tracker'!$D:$D,"<>Screening Pending",'Candidate Tracker'!$D:$D,"<>Candidate Hold",'Candidate Tracker'!$D:$D,"<>Position Cancelled",'Candidate Tracker'!$D:$D,"<>Internal closed")/COUNTIF('Candidate Tracker'!$D:$D,"<>"))=0,"",(COUNTIFS('Candidate Tracker'!$D:$D,"<>",'Candidate Tracker'!$D:$D,"<>Screening",'Candidate Tracker'!$D:$D,"<>Candidate Hold",'Candidate Tracker'!$D:$D,"<>Position Cancelled",'Candidate Tracker'!$D:$D,"<>Internal closed")/COUNTIF('Candidate Tracker'!$D:$D,"<>"))),"") -> 0.88111888 | BA26: =IFERROR(IF(COUNTIFS('Candidate Tracker'!$E:$E,'Positions Tracker'!$B26,'Candidate Tracker'!$I:$I,"Female")=0,"",COUNTIFS('Candidate Tracker'!$E:$E,'Positions Tracker'!$B26,'Candidate Tracker'!$I:$I,"Female")),"") | BB26: =IFERROR(IF(COUNTIFS('Candidate Tracker'!$E:$E,'Positions Tracker'!$B26,'Candidate Tracker'!$I:$I,"male")=0,"",COUNTIFS('Candidate Tracker'!$E:$E,'Positions Tracker'!$B26,'Candidate Tracker'!$I:$I,"male")),"") -> 1 | BC26: =IFERROR(IF(COUNTIFS('Candidate Tracker'!$E:$E,'Positions Tracker'!$B26,'Candidate Tracker'!$C:$C,"<>WIP",'Candidate Tracker'!$C:$C,"<>Hold",'Candidate Tracker'!$C:$C,"<>Cancelled",'Candidate Tracker'!$C:$C,"<>Closed")/COUNTIFS('Candidate Tracker'!$E:$E,'Positions Tracker'!$B26)=0,"",COUNTIFS('Candidate Tracker'!$E:$E,'Positions Tracker'!$B26,'Candidate Tracker'!$C:$C,"<>WIP",'Candidate Tracker'!$C:$C,"<>Hold",'Candidate Tracker'!$C:$C,"<>Cancelled",'Candidate Tracker'!$C:$C,"<>Closed")/COUNTIFS('Candidate Tracker'!$E:$E,'Positions Tracker'!$B26)),"") -> 1 | BD26: =IFERROR(IF($M26="","",TEXT($M26,"MMM-YY")),"") -> May-24 | BE26: =IFERROR(IF($AI26="","",TEXT($AI26,"MMM-YY")),"") -> Apr-24 | BF26: =IFERROR(IF($AM26="","",TEXT($AM26,"MMM-YY")),"") -> Apr-24 | BG26: =IFERROR(IF($AS26="","",TEXT($AS26,"MMM-YY")),"") -> Jul-24
A27: =A26+1 -> 26 | B27: TG1 | C27: Joined | D27: Joined | E27: Associate Engineer - Firmware | F27: Firmware | G27: Integrated Business Services | H27: ITS | I27: Sameer U | J27: External | K27: 45261 | L27: 45261 | M27: 45292 | N27: T9 | X27: Pune | Y27: Raisoni, Rushabh | Z27: Raisoni, Rushabh | AA27: Joined | AE27: Trupti malekar | AF27: 7767934337 | AG27: malekartrupti@gmail.com | AH27: Female | AI27: 45343 | AJ27: 45350 | AK27: Pune | AL27: 900000 | AM27: 45350 | AN27: 45350 | AP27: 45356 | AQ27: 45356 | AR27: 45428 | AS27: 45432 | AT27: =IFERROR(SUM(IF(AND(ISBLANK(T27),ISBLANK(Q27)),0,IF(T27="",TODAY()-Q27,T27-Q27))+IF(AND(ISBLANK(S27),ISBLANK(P27)),0,IF(S27="",TODAY()-P27,S27-P27))+IF(AND(ISBLANK(O27),ISBLANK(R27)),0,IF(R27="",TODAY()-O27,R27-O27))),"") -> 0 | AU27: =IFERROR(IF(($M27=""),"",IF(OR(,$C27="Offer in Progress",$C27="WIP",$C27="WIP/Drop",$C27="WIP/New",$C27="WIP/Hold"),(TODAY()-$M27)-$AT27,"")),"") | AV27: {=IFERROR(_xlfn.IFS($AU27="","",$AU27<=15,"0-15",AND($AU27>=16,$AU27<=30),"16-30",AND($AU27>=31,$AU27<=45),"31-45",AND($AU27>=46,$AU27<=60),"46-60",AND($AU27>=61,$AU27<=90),"61-90",AND($AU27>=91),"> 90",AND($AU27>=2000),""),"")} | AW27: {=IFERROR(_xlfn.IFS(OR($M27="",$AM27=""),"",OR($C27="Offered",$C27="Joined"),($AM27-$M27)-$AT27),"")} -> 58 | AX27: {=IFERROR(_xlfn.IFS(OR($M27="",$AS27=""),"",$C27="Joined",($AS27-$M27)-$AT27),"")} -> 140 | AY27: =IFERROR(IF(COUNTIFS('Candidate Tracker'!$E:$E,'Positions Tracker'!$B27,'Candidate Tracker'!$C:$C,"Offer Drop")=0,"",COUNTIFS('Candidate Tracker'!$E:$E,'Positions Tracker'!$B27,'Candidate Tracker'!$C:$C,"Offer Drop")),"") | AZ27: =IFERROR(IF((COUNTIFS('Candidate Tracker'!$D:$D,"<>",'Candidate Tracker'!$D:$D,"<>Screening",'Candidate Tracker'!$D:$D,"<>Screening Pending",'Candidate Tracker'!$D:$D,"<>Candidate Hold",'Candidate Tracker'!$D:$D,"<>Position Cancelled",'Candidate Tracker'!$D:$D,"<>Internal closed")/COUNTIF('Candidate Tracker'!$D:$D,"<>"))=0,"",(COUNTIFS('Candidate Tracker'!$D:$D,"<>",'Candidate Tracker'!$D:$D,"<>Screening",'Candidate Tracker'!$D:$D,"<>Candidate Hold",'Candidate Tracker'!$D:$D,"<>Position Cancelled",'Candidate Tracker'!$D:$D,"<>Internal closed")/COUNTIF('Candidate Tracker'!$D:$D,"<>"))),"") -> 0.88111888 | BA27: =IFERROR(IF(COUNTIFS('Candidate Tracker'!$E:$E,'Positions Tracker'!$B27,'Candidate Tracker'!$I:$I,"Female")=0,"",COUNTIFS('Candidate Tracker'!$E:$E,'Positions Tracker'!$B27,'Candidate Tracker'!$I:$I,"Female")),"") -> 1 | BB27: =IFERROR(IF(COUNTIFS('Candidate Tracker'!$E:$E,'Positions Tracker'!$B27,'Candidate Tracker'!$I:$I,"male")=0,"",COUNTIFS('Candidate Tracker'!$E:$E,'Positions Tracker'!$B27,'Candidate Tracker'!$I:$I,"male")),"") | BC27: =IFERROR(IF(COUNTIFS('Candidate Tracker'!$E:$E,'Positions Tracker'!$B27,'Candidate Tracker'!$C:$C,"<>WIP",'Candidate Tracker'!$C:$C,"<>Hold",'Candidate Tracker'!$C:$C,"<>Cancelled",'Candidate Tracker'!$C:$C,"<>Closed")/COUNTIFS('Candidate Tracker'!$E:$E,'Positions Tracker'!$B27)=0,"",COUNTIFS('Candidate Tracker'!$E:$E,'Positions Tracker'!$B27,'Candidate Tracker'!$C:$C,"<>WIP",'Candidate Tracker'!$C:$C,"<>Hold",'Candidate Tracker'!$C:$C,"<>Cancelled",'Candidate Tracker'!$C:$C,"<>Closed")/COUNTIFS('Candidate Tracker'!$E:$E,'Positions Tracker'!$B27)),"") -> 1 | BD27: =IFERROR(IF($M27="","",TEXT($M27,"MMM-YY")),"") -> Jan-24 | BE27: =IFERROR(IF($AI27="","",TEXT($AI27,"MMM-YY")),"") -> Feb-24 | BF27: =IFERROR(IF($AM27="","",TEXT($AM27,"MMM-YY")),"") -> Feb-24 | BG27: =IFERROR(IF($AS27="","",TEXT($AS27,"MMM-YY")),"") -> May-24
A28: =A27+1 -> 27 | B28: TG10 | C28: Joined | D28: Joined | E28: Engineer - Electrical | F28: Electrical | G28: Integrated Business Services | H28: SP UPS | I28: Dipak G | J28: External | K28: 45261 | L28: 45261 | M28: 45261 | N28: T13 | X28: Pune | Y28: Raisoni, Rushabh | Z28: Raisoni, Rushabh | AA28: Joined | AE28: Nikhil Bodele | AF28: 7709985010 | AG28: b.nikhil1890@gmail.com | AH28: Male | AI28: 45300 | AJ28: 45306 | AK28: Pune | AL28: 1500000 | AM28: 45306 | AN28: 45306 | AP28: 45308 | AQ28: 45308 | AR28: 45358 | AS28: 45362 | AT28: =IFERROR(SUM(IF(AND(ISBLANK(T28),ISBLANK(Q28)),0,IF(T28="",TODAY()-Q28,T28-Q28))+IF(AND(ISBLANK(S28),ISBLANK(P28)),0,IF(S28="",TODAY()-P28,S28-P28))+IF(AND(ISBLANK(O28),ISBLANK(R28)),0,IF(R28="",TODAY()-O28,R28-O28))),"") -> 0 | AU28: =IFERROR(IF(($M28=""),"",IF(OR(,$C28="Offer in Progress",$C28="WIP",$C28="WIP/Drop",$C28="WIP/New",$C28="WIP/Hold"),(TODAY()-$M28)-$AT28,"")),"") | AV28: {=IFERROR(_xlfn.IFS($AU28="","",$AU28<=15,"0-15",AND($AU28>=16,$AU28<=30),"16-30",AND($AU28>=31,$AU28<=45),"31-45",AND($AU28>=46,$AU28<=60),"46-60",AND($AU28>=61,$AU28<=90),"61-90",AND($AU28>=91),"> 90",AND($AU28>=2000),""),"")} | AW28: {=IFERROR(_xlfn.IFS(OR($M28="",$AM28=""),"",OR($C28="Offered",$C28="Joined"),($AM28-$M28)-$AT28),"")} -> 45 | AX28: {=IFERROR(_xlfn.IFS(OR($M28="",$AS28=""),"",$C28="Joined",($AS28-$M28)-$AT28),"")} -> 101 | AY28: =IFERROR(IF(COUNTIFS('Candidate Tracker'!$E:$E,'Positions Tracker'!$B28,'Candidate Tracker'!$C:$C,"Offer Drop")=0,"",COUNTIFS('Candidate Tracker'!$E:$E,'Positions Tracker'!$B28,'Candidate Tracker'!$C:$C,"Offer Drop")),"") | AZ28: =IFERROR(IF((COUNTIFS('Candidate Tracker'!$D:$D,"<>",'Candidate Tracker'!$D:$D,"<>Screening",'Candidate Tracker'!$D:$D,"<>Screening Pending",'Candidate Tracker'!$D:$D,"<>Candidate Hold",'Candidate Tracker'!$D:$D,"<>Position Cancelled",'Candidate Tracker'!$D:$D,"<>Internal closed")/COUNTIF('Candidate Tracker'!$D:$D,"<>"))=0,"",(COUNTIFS('Candidate Tracker'!$D:$D,"<>",'Candidate Tracker'!$D:$D,"<>Screening",'Candidate Tracker'!$D:$D,"<>Candidate Hold",'Candidate Tracker'!$D:$D,"<>Position Cancelled",'Candidate Tracker'!$D:$D,"<>Internal closed")/COUNTIF('Candidate Tracker'!$D:$D,"<>"))),"") -> 0.88111888 | BA28: =IFERROR(IF(COUNTIFS('Candidate Tracker'!$E:$E,'Positions Tracker'!$B28,'Candidate Tracker'!$I:$I,"Female")=0,"",COUNTIFS('Candidate Tracker'!$E:$E,'Positions Tracker'!$B28,'Candidate Tracker'!$I:$I,"Female")),"") | BB28: =IFERROR(IF(COUNTIFS('Candidate Tracker'!$E:$E,'Positions Tracker'!$B28,'Candidate Tracker'!$I:$I,"male")=0,"",COUNTIFS('Candidate Tracker'!$E:$E,'Positions Tracker'!$B28,'Candidate Tracker'!$I:$I,"male")),"") -> 1 | BC28: =IFERROR(IF(COUNTIFS('Candidate Tracker'!$E:$E,'Positions Tracker'!$B28,'Candidate Tracker'!$C:$C,"<>WIP",'Candidate Tracker'!$C:$C,"<>Hold",'Candidate Tracker'!$C:$C,"<>Cancelled",'Candidate Tracker'!$C:$C,"<>Closed")/COUNTIFS('Candidate Tracker'!$E:$E,'Positions Tracker'!$B28)=0,"",COUNTIFS('Candidate Tracker'!$E:$E,'Positions Tracker'!$B28,'Candidate Tracker'!$C:$C,"<>WIP",'Candidate Tracker'!$C:$C,"<>Hold",'Candidate Tracker'!$C:$C,"<>Cancelled",'Candidate Tracker'!$C:$C,"<>Closed")/COUNTIFS('Candidate Tracker'!$E:$E,'Positions Tracker'!$B28)),"") -> 1 | BD28: =IFERROR(IF($M28="","",TEXT($M28,"MMM-YY")),"") -> Dec-23 | BE28: =IFERROR(IF($AI28="","",TEXT($AI28,"MMM-YY")),"") -> Jan-24 | BF28: =IFERROR(IF($AM28="","",TEXT($AM28,"MMM-YY")),"") -> Jan-24 | BG28: =IFERROR(IF($AS28="","",TEXT($AS28,"MMM-YY")),"") -> Mar-24
A29: =A28+1 -> 28 | B29: 20246589 | C29: Joined | D29: Joined | E29: Principal Engineer - Firmware | F29: Firmware | G29: Integrated Business Services | H29: KVM | I29: Jitesh Verma | J29: External | K29: 45442 | L29: 45442 | M29: 45565 | N29: T13 | X29: Pune | Y29: Raisoni, Rushabh | Z29: Raisoni, Rushabh | AA29: Joined | AE29: Asmita Kulkarni | AF29: 7875200079 | AG29: asmibhalvankar@gmail.com | AH29: Female | AI29: 45576 | AJ29: 45578 | AK29: Pune | AL29: 4000000 | AM29: 45607 | AN29: 45578 | AP29: 45607 | AQ29: 45607 | AR29: 45708 | AS29: 45712 | AT29: =IFERROR(SUM(IF(AND(ISBLANK(T29),ISBLANK(Q29)),0,IF(T29="",TODAY()-Q29,T29-Q29))+IF(AND(ISBLANK(S29),ISBLANK(P29)),0,IF(S29="",TODAY()-P29,S29-P29))+IF(AND(ISBLANK(O29),ISBLANK(R29)),0,IF(R29="",TODAY()-O29,R29-O29))),"") -> 0 | AU29: =IFERROR(IF(($M29=""),"",IF(OR(,$C29="Offer in Progress",$C29="WIP",$C29="WIP/Drop",$C29="WIP/New",$C29="WIP/Hold"),(TODAY()-$M29)-$AT29,"")),"") | AV29: {=IFERROR(_xlfn.IFS($AU29="","",$AU29<=15,"0-15",AND($AU29>=16,$AU29<=30),"16-30",AND($AU29>=31,$AU29<=45),"31-45",AND($AU29>=46,$AU29<=60),"46-60",AND($AU29>=61,$AU29<=90),"61-90",AND($AU29>=91),"> 90",AND($AU29>=2000),""),"")} | AW29: {=IFERROR(_xlfn.IFS(OR($M29="",$AM29=""),"",OR($C29="Offered",$C29="Joined"),($AM29-$M29)-$AT29),"")} -> 42 | AX29: {=IFERROR(_xlfn.IFS(OR($M29="",$AS29=""),"",$C29="Joined",($AS29-$M29)-$AT29),"")} -> 147 | AY29: =IFERROR(IF(COUNTIFS('Candidate Tracker'!$E:$E,'Positions Tracker'!$B29,'Candidate Tracker'!$C:$C,"Offer Drop")=0,"",COUNTIFS('Candidate Tracker'!$E:$E,'Positions Tracker'!$B29,'Candidate Tracker'!$C:$C,"Offer Drop")),"") | AZ29: =IFERROR(IF((COUNTIFS('Candidate Tracker'!$D:$D,"<>",'Candidate Tracker'!$D:$D,"<>Screening",'Candidate Tracker'!$D:$D,"<>Screening Pending",'Candidate Tracker'!$D:$D,"<>Candidate Hold",'Candidate Tracker'!$D:$D,"<>Position Cancelled",'Candidate Tracker'!$D:$D,"<>Internal closed")/COUNTIF('Candidate Tracker'!$D:$D,"<>"))=0,"",(COUNTIFS('Candidate Tracker'!$D:$D,"<>",'Candidate Tracker'!$D:$D,"<>Screening",'Candidate Tracker'!$D:$D,"<>Candidate Hold",'Candidate Tracker'!$D:$D,"<>Position Cancelled",'Candidate Tracker'!$D:$D,"<>Internal closed")/COUNTIF('Candidate Tracker'!$D:$D,"<>"))),"") -> 0.88111888 | BA29: =IFERROR(IF(COUNTIFS('Candidate Tracker'!$E:$E,'Positions Tracker'!$B29,'Candidate Tracker'!$I:$I,"Female")=0,"",COUNTIFS('Candidate Tracker'!$E:$E,'Positions Tracker'!$B29,'Candidate Tracker'!$I:$I,"Female")),"") -> 1 | BB29: =IFERROR(IF(COUNTIFS('Candidate Tracker'!$E:$E,'Positions Tracker'!$B29,'Candidate Tracker'!$I:$I,"male")=0,"",COUNTIFS('Candidate Tracker'!$E:$E,'Positions Tracker'!$B29,'Candidate Tracker'!$I:$I,"male")),"") | BC29: =IFERROR(IF(COUNTIFS('Candidate Tracker'!$E:$E,'Positions Tracker'!$B29,'Candidate Tracker'!$C:$C,"<>WIP",'Candidate Tracker'!$C:$C,"<>Hold",'Candidate Tracker'!$C:$C,"<>Cancelled",'Candidate Tracker'!$C:$C,"<>Closed")/COUNTIFS('Candidate Tracker'!$E:$E,'Positions Tracker'!$B29)=0,"",COUNTIFS('Candidate Tracker'!$E:$E,'Positions Tracker'!$B29,'Candidate Tracker'!$C:$C,"<>WIP",'Candidate Tracker'!$C:$C,"<>Hold",'Candidate Tracker'!$C:$C,"<>Cancelled",'Candidate Tracker'!$C:$C,"<>Closed")/COUNTIFS('Candidate Tracker'!$E:$E,'Positions Tracker'!$B29)),"") -> 1 | BD29: =IFERROR(IF($M29="","",TEXT($M29,"MMM-YY")),"") -> Sep-24 | BE29: =IFERROR(IF($AI29="","",TEXT($AI29,"MMM-YY")),"") -> Oct-24 | BF29: =IFERROR(IF($AM29="","",TEXT($AM29,"MMM-YY")),"") -> Nov-24 | BG29: =IFERROR(IF($AS29="","",TEXT($AS29,"MMM-YY")),"") -> Feb-25
A30: =A29+1 -> 29 | B30: TG2 | C30: Joined | D30: Joined | E30: Sr Firmware Engineer | F30: Firmware | G30: Integrated Business Services | H30: ITS | I30: Sameer U | J30: External | K30: 45329 | L30: 45329 | M30: 45329 | N30: T10 | X30: Pune | Y30: Raisoni, Rushabh | Z30: Raisoni, Rushabh | AA30: Joined | AE30: Anvit Khare | AF30: 8238422816 | AG30: anvitkhare@yahoo.co.in | AH30: Male | AI30: 45372 | AJ30: 45376 | AK30: Pune | AL30: 1900000 | AM30: 45408 | AN30: 45376 | AP30: 45408 | AQ30: 45408 | AR30: 45442 | AS30: 45446 | AT30: =IFERROR(SUM(IF(AND(ISBLANK(T30),ISBLANK(Q30)),0,IF(T30="",TODAY()-Q30,T30-Q30))+IF(AND(ISBLANK(S30),ISBLANK(P30)),0,IF(S30="",TODAY()-P30,S30-P30))+IF(AND(ISBLANK(O30),ISBLANK(R30)),0,IF(R30="",TODAY()-O30,R30-O30))),"") -> 0 | AU30: =IFERROR(IF(($M30=""),"",IF(OR(,$C30="Offer in Progress",$C30="WIP",$C30="WIP/Drop",$C30="WIP/New",$C30="WIP/Hold"),(TODAY()-$M30)-$AT30,"")),"") | AV30: {=IFERROR(_xlfn.IFS($AU30="","",$AU30<=15,"0-15",AND($AU30>=16,$AU30<=30),"16-30",AND($AU30>=31,$AU30<=45),"31-45",AND($AU30>=46,$AU30<=60),"46-60",AND($AU30>=61,$AU30<=90),"61-90",AND($AU30>=91),"> 90",AND($AU30>=2000),""),"")} | AW30: {=IFERROR(_xlfn.IFS(OR($M30="",$AM30=""),"",OR($C30="Offered",$C30="Joined"),($AM30-$M30)-$AT30),"")} -> 79 | AX30: {=IFERROR(_xlfn.IFS(OR($M30="",$AS30=""),"",$C30="Joined",($AS30-$M30)-$AT30),"")} -> 117 | AY30: =IFERROR(IF(COUNTIFS('Candidate Tracker'!$E:$E,'Positions Tracker'!$B30,'Candidate Tracker'!$C:$C,"Offer Drop")=0,"",COUNTIFS('Candidate Tracker'!$E:$E,'Positions Tracker'!$B30,'Candidate Tracker'!$C:$C,"Offer Drop")),"") | AZ30: =IFERROR(IF((COUNTIFS('Candidate Tracker'!$D:$D,"<>",'Candidate Tracker'!$D:$D,"<>Screening",'Candidate Tracker'!$D:$D,"<>Screening Pending",'Candidate Tracker'!$D:$D,"<>Candidate Hold",'Candidate Tracker'!$D:$D,"<>Position Cancelled",'Candidate Tracker'!$D:$D,"<>Internal closed")/COUNTIF('Candidate Tracker'!$D:$D,"<>"))=0,"",(COUNTIFS('Candidate Tracker'!$D:$D,"<>",'Candidate Tracker'!$D:$D,"<>Screening",'Candidate Tracker'!$D:$D,"<>Candidate Hold",'Candidate Tracker'!$D:$D,"<>Position Cancelled",'Candidate Tracker'!$D:$D,"<>Internal closed")/COUNTIF('Candidate Tracker'!$D:$D,"<>"))),"") -> 0.88111888 | BA30: =IFERROR(IF(COUNTIFS('Candidate Tracker'!$E:$E,'Positions Tracker'!$B30,'Candidate Tracker'!$I:$I,"Female")=0,"",COUNTIFS('Candidate Tracker'!$E:$E,'Positions Tracker'!$B30,'Candidate Tracker'!$I:$I,"Female")),"") | BB30: =IFERROR(IF(COUNTIFS('Candidate Tracker'!$E:$E,'Positions Tracker'!$B30,'Candidate Tracker'!$I:$I,"male")=0,"",COUNTIFS('Candidate Tracker'!$E:$E,'Positions Tracker'!$B30,'Candidate Tracker'!$I:$I,"male")),"") -> 1 | BC30: =IFERROR(IF(COUNTIFS('Candidate Tracker'!$E:$E,'Positions Tracker'!$B30,'Candidate Tracker'!$C:$C,"<>WIP",'Candidate Tracker'!$C:$C,"<>Hold",'Candidate Tracker'!$C:$C,"<>Cancelled",'Candidate Tracker'!$C:$C,"<>Closed")/COUNTIFS('Candidate Tracker'!$E:$E,'Positions Tracker'!$B30)=0,"",COUNTIFS('Candidate Tracker'!$E:$E,'Positions Tracker'!$B30,'Candidate Tracker'!$C:$C,"<>WIP",'Candidate Tracker'!$C:$C,"<>Hold",'Candidate Tracker'!$C:$C,"<>Cancelled",'Candidate Tracker'!$C:$C,"<>Closed")/COUNTIFS('Candidate Tracker'!$E:$E,'Positions Tracker'!$B30)),"") -> 1 | BD30: =IFERROR(IF($M30="","",TEXT($M30,"MMM-YY")),"") -> Feb-24 | BE30: =IFERROR(IF($AI30="","",TEXT($AI30,"MMM-YY")),"") -> Mar-24 | BF30: =IFERROR(IF($AM30="","",TEXT($AM30,"MMM-YY")),"") -> Apr-24 | BG30: =IFERROR(IF($AS30="","",TEXT($AS30,"MMM-YY")),"") -> Jun-24
A31: =A30+1 -> 30 | B31: 20248336 | C31: Cancelled | D31: Position Cancelled | E31: Principal Eng - Java | F31: Java | G31: Integrated Business Services | H31: Global Monitoring Solutions | I31: Nitin Kudale | J31: External | K31: 45547 | L31: 45547 | M31: 45547 | X31: Pune | Y31: Raisoni, Rushabh | Z31: Raisoni, Rushabh | AA31: 21 Feb - Cancelled on 21st Feb by Business | AT31: =IFERROR(SUM(IF(AND(ISBLANK(T31),ISBLANK(Q31)),0,IF(T31="",TODAY()-Q31,T31-Q31))+IF(AND(ISBLANK(S31),ISBLANK(P31)),0,IF(S31="",TODAY()-P31,S31-P31))+IF(AND(ISBLANK(O31),ISBLANK(R31)),0,IF(R31="",TODAY()-O31,R31-O31))),"") -> 0 | AU31: =IFERROR(IF(($M31=""),"",IF(OR(,$C31="Offer in Progress",$C31="WIP",$C31="WIP/Drop",$C31="WIP/New",$C31="WIP/Hold"),(TODAY()-$M31)-$AT31,"")),"") | AV31: {=IFERROR(_xlfn.IFS($AU31="","",$AU31<=15,"0-15",AND($AU31>=16,$AU31<=30),"16-30",AND($AU31>=31,$AU31<=45),"31-45",AND($AU31>=46,$AU31<=60),"46-60",AND($AU31>=61,$AU31<=90),"61-90",AND($AU31>=91),"> 90",AND($AU31>=2000),""),"")} | AW31: {=IFERROR(_xlfn.IFS(OR($M31="",$AM31=""),"",OR($C31="Offered",$C31="Joined"),($AM31-$M31)-$AT31),"")} | AX31: {=IFERROR(_xlfn.IFS(OR($M31="",$AS31=""),"",$C31="Joined",($AS31-$M31)-$AT31),"")} | AY31: =IFERROR(IF(COUNTIFS('Candidate Tracker'!$E:$E,'Positions Tracker'!$B31,'Candidate Tracker'!$C:$C,"Offer Drop")=0,"",COUNTIFS('Candidate Tracker'!$E:$E,'Positions Tracker'!$B31,'Candidate Tracker'!$C:$C,"Offer Drop")),"") | AZ31: =IFERROR(IF((COUNTIFS('Candidate Tracker'!$D:$D,"<>",'Candidate Tracker'!$D:$D,"<>Screening",'Candidate Tracker'!$D:$D,"<>Screening Pending",'Candidate Tracker'!$D:$D,"<>Candidate Hold",'Candidate Tracker'!$D:$D,"<>Position Cancelled",'Candidate Tracker'!$D:$D,"<>Internal closed")/COUNTIF('Candidate Tracker'!$D:$D,"<>"))=0,"",(COUNTIFS('Candidate Tracker'!$D:$D,"<>",'Candidate Tracker'!$D:$D,"<>Screening",'Candidate Tracker'!$D:$D,"<>Candidate Hold",'Candidate Tracker'!$D:$D,"<>Position Cancelled",'Candidate Tracker'!$D:$D,"<>Internal closed")/COUNTIF('Candidate Tracker'!$D:$D,"<>"))),"") -> 0.88111888 | BA31: =IFERROR(IF(COUNTIFS('Candidate Tracker'!$E:$E,'Positions Tracker'!$B31,'Candidate Tracker'!$I:$I,"Female")=0,"",COUNTIFS('Candidate Tracker'!$E:$E,'Positions Tracker'!$B31,'Candidate Tracker'!$I:$I,"Female")),"") | BB31: =IFERROR(IF(COUNTIFS('Candidate Tracker'!$E:$E,'Positions Tracker'!$B31,'Candidate Tracker'!$I:$I,"male")=0,"",COUNTIFS('Candidate Tracker'!$E:$E,'Positions Tracker'!$B31,'Candidate Tracker'!$I:$I,"male")),"") | BC31: =IFERROR(IF(COUNTIFS('Candidate Tracker'!$E:$E,'Positions Tracker'!$B31,'Candidate Tracker'!$C:$C,"<>WIP",'Candidate Tracker'!$C:$C,"<>Hold",'Candidate Tracker'!$C:$C,"<>Cancelled",'Candidate Tracker'!$C:$C,"<>Closed")/COUNTIFS('Candidate Tracker'!$E:$E,'Positions Tracker'!$B31)=0,"",COUNTIFS('Candidate Tracker'!$E:$E,'Positions Tracker'!$B31,'Candidate Tracker'!$C:$C,"<>WIP",'Candidate Tracker'!$C:$C,"<>Hold",'Candidate Tracker'!$C:$C,"<>Cancelled",'Candidate Tracker'!$C:$C,"<>Closed")/COUNTIFS('Candidate Tracker'!$E:$E,'Positions Tracker'!$B31)),"") | BD31: =IFERROR(IF($M31="","",TEXT($M31,"MMM-YY")),"") -> Sep-24 | BE31: =IFERROR(IF($AI31="","",TEXT($AI31,"MMM-YY")),"") | BF31: =IFERROR(IF($AM31="","",TEXT($AM31,"MMM-YY")),"") | BG31: =IFERROR(IF($AS31="","",TEXT($AS31,"MMM-YY")),"")
A32: =A31+1 -> 31 | B32: 20243791 | C32: Joined | D32: Joined | E32: Sr Engineer - Firmware | F32: Firmware | G32: Integrated Business Services | H32: KVM | I32: Jitesh Verma | J32: External | K32: 45442 | L32: 45442 | M32: 45442 | N32: T11 | X32: Pune | Y32: Raisoni, Rushabh | Z32: Raisoni, Rushabh | AA32: Joined | AE32: Aijaz Baig | AF32: 8097346716 | AG32: aijazbaig1@gmail.com | AH32: Male | AI32: 45517 | AJ32: 45520 | AK32: Pune | AL32: 2500000 | AM32: 45533 | AN32: 45520 | AP32: 45533 | AQ32: 45533 | AR32: 45555 | AS32: 45559 | AT32: =IFERROR(SUM(IF(AND(ISBLANK(T32),ISBLANK(Q32)),0,IF(T32="",TODAY()-Q32,T32-Q32))+IF(AND(ISBLANK(S32),ISBLANK(P32)),0,IF(S32="",TODAY()-P32,S32-P32))+IF(AND(ISBLANK(O32),ISBLANK(R32)),0,IF(R32="",TODAY()-O32,R32-O32))),"") -> 0 | AU32: =IFERROR(IF(($M32=""),"",IF(OR(,$C32="Offer in Progress",$C32="WIP",$C32="WIP/Drop",$C32="WIP/New",$C32="WIP/Hold"),(TODAY()-$M32)-$AT32,"")),"") | AV32: {=IFERROR(_xlfn.IFS($AU32="","",$AU32<=15,"0-15",AND($AU32>=16,$AU32<=30),"16-30",AND($AU32>=31,$AU32<=45),"31-45",AND($AU32>=46,$AU32<=60),"46-60",AND($AU32>=61,$AU32<=90),"61-90",AND($AU32>=91),"> 90",AND($AU32>=2000),""),"")} | AW32: {=IFERROR(_xlfn.IFS(OR($M32="",$AM32=""),"",OR($C32="Offered",$C32="Joined"),($AM32-$M32)-$AT32),"")} -> 91 | AX32: {=IFERROR(_xlfn.IFS(OR($M32="",$AS32=""),"",$C32="Joined",($AS32-$M32)-$AT32),"")} -> 117 | AY32: =IFERROR(IF(COUNTIFS('Candidate Tracker'!$E:$E,'Positions Tracker'!$B32,'Candidate Tracker'!$C:$C,"Offer Drop")=0,"",COUNTIFS('Candidate Tracker'!$E:$E,'Positions Tracker'!$B32,'Candidate Tracker'!$C:$C,"Offer Drop")),"") | AZ32: =IFERROR(IF((COUNTIFS('Candidate Tracker'!$D:$D,"<>",'Candidate Tracker'!$D:$D,"<>Screening",'Candidate Tracker'!$D:$D,"<>Screening Pending",'Candidate Tracker'!$D:$D,"<>Candidate Hold",'Candidate Tracker'!$D:$D,"<>Position Cancelled",'Candidate Tracker'!$D:$D,"<>Internal closed")/COUNTIF('Candidate Tracker'!$D:$D,"<>"))=0,"",(COUNTIFS('Candidate Tracker'!$D:$D,"<>",'Candidate Tracker'!$D:$D,"<>Screening",'Candidate Tracker'!$D:$D,"<>Candidate Hold",'Candidate Tracker'!$D:$D,"<>Position Cancelled",'Candidate Tracker'!$D:$D,"<>Internal closed")/COUNTIF('Candidate Tracker'!$D:$D,"<>"))),"") -> 0.88111888 | BA32: =IFERROR(IF(COUNTIFS('Candidate Tracker'!$E:$E,'Positions Tracker'!$B32,'Candidate Tracker'!$I:$I,"Female")=0,"",COUNTIFS('Candidate Tracker'!$E:$E,'Positions Tracker'!$B32,'Candidate Tracker'!$I:$I,"Female")),"") | BB32: =IFERROR(IF(COUNTIFS('Candidate Tracker'!$E:$E,'Positions Tracker'!$B32,'Candidate Tracker'!$I:$I,"male")=0,"",COUNTIFS('Candidate Tracker'!$E:$E,'Positions Tracker'!$B32,'Candidate Tracker'!$I:$I,"male")),"") -> 1 | BC32: =IFERROR(IF(COUNTIFS('Candidate Tracker'!$E:$E,'Positions Tracker'!$B32,'Candidate Tracker'!$C:$C,"<>WIP",'Candidate Tracker'!$C:$C,"<>Hold",'Candidate Tracker'!$C:$C,"<>Cancelled",'Candidate Tracker'!$C:$C,"<>Closed")/COUNTIFS('Candidate Tracker'!$E:$E,'Positions Tracker'!$B32)=0,"",COUNTIFS('Candidate Tracker'!$E:$E,'Positions Tracker'!$B32,'Candidate Tracker'!$C:$C,"<>WIP",'Candidate Tracker'!$C:$C,"<>Hold",'Candidate Tracker'!$C:$C,"<>Cancelled",'Candidate Tracker'!$C:$C,"<>Closed")/COUNTIFS('Candidate Tracker'!$E:$E,'Positions Tracker'!$B32)),"") -> 1 | BD32: =IFERROR(IF($M32="","",TEXT($M32,"MMM-YY")),"") -> May-24 | BE32: =IFERROR(IF($AI32="","",TEXT($AI32,"MMM-YY")),"") -> Aug-24 | BF32: =IFERROR(IF($AM32="","",TEXT($AM32,"MMM-YY")),"") -> Aug-24 | BG32: =IFERROR(IF($AS32="","",TEXT($AS32,"MMM-YY")),"") -> Sep-24
A33: =A32+1 -> 32 | B33: TG5 | C33: Joined | D33: Joined | E33: Sr Firmware Engineer | F33: Firmware | G33: Integrated Business Services | H33: ITS | I33: Sameer U | J33: External | K33: 45329 | L33: 45329 | M33: 45434 | N33: T12 | X33: Pune | Y33: Raisoni, Rushabh | Z33: Raisoni, Rushabh | AA33: Joined | AE33: Gaurav Badgujar | AF33: 9960004432 | AG33: 3015gaurav@gmail.com | AH33: Male | AI33: 45434 | AJ33: 45437 | AK33: Pune | AL33: 1800000 | AM33: 45447 | AN33: 45437 | AP33: 45447 | AQ33: 45447 | AR33: 45492 | AS33: 45495 | AT33: =IFERROR(SUM(IF(AND(ISBLANK(T33),ISBLANK(Q33)),0,IF(T33="",TODAY()-Q33,T33-Q33))+IF(AND(ISBLANK(S33),ISBLANK(P33)),0,IF(S33="",TODAY()-P33,S33-P33))+IF(AND(ISBLANK(O33),ISBLANK(R33)),0,IF(R33="",TODAY()-O33,R33-O33))),"") -> 0 | AU33: =IFERROR(IF(($M33=""),"",IF(OR(,$C33="Offer in Progress",$C33="WIP",$C33="WIP/Drop",$C33="WIP/New",$C33="WIP/Hold"),(TODAY()-$M33)-$AT33,"")),"") | AV33: {=IFERROR(_xlfn.IFS($AU33="","",$AU33<=15,"0-15",AND($AU33>=16,$AU33<=30),"16-30",AND($AU33>=31,$AU33<=45),"31-45",AND($AU33>=46,$AU33<=60),"46-60",AND($AU33>=61,$AU33<=90),"61-90",AND($AU33>=91),"> 90",AND($AU33>=2000),""),"")} | AW33: {=IFERROR(_xlfn.IFS(OR($M33="",$AM33=""),"",OR($C33="Offered",$C33="Joined"),($AM33-$M33)-$AT33),"")} -> 13 | AX33: {=IFERROR(_xlfn.IFS(OR($M33="",$AS33=""),"",$C33="Joined",($AS33-$M33)-$AT33),"")} -> 61 | AY33: =IFERROR(IF(COUNTIFS('Candidate Tracker'!$E:$E,'Positions Tracker'!$B33,'Candidate Tracker'!$C:$C,"Offer Drop")=0,"",COUNTIFS('Candidate Tracker'!$E:$E,'Positions Tracker'!$B33,'Candidate Tracker'!$C:$C,"Offer Drop")),"") | AZ33: =IFERROR(IF((COUNTIFS('Candidate Tracker'!$D:$D,"<>",'Candidate Tracker'!$D:$D,"<>Screening",'Candidate Tracker'!$D:$D,"<>Screening Pending",'Candidate Tracker'!$D:$D,"<>Candidate Hold",'Candidate Tracker'!$D:$D,"<>Position Cancelled",'Candidate Tracker'!$D:$D,"<>Internal closed")/COUNTIF('Candidate Tracker'!$D:$D,"<>"))=0,"",(COUNTIFS('Candidate Tracker'!$D:$D,"<>",'Candidate Tracker'!$D:$D,"<>Screening",'Candidate Tracker'!$D:$D,"<>Candidate Hold",'Candidate Tracker'!$D:$D,"<>Position Cancelled",'Candidate Tracker'!$D:$D,"<>Internal closed")/COUNTIF('Candidate Tracker'!$D:$D,"<>"))),"") -> 0.88111888 | BA33: =IFERROR(IF(COUNTIFS('Candidate Tracker'!$E:$E,'Positions Tracker'!$B33,'Candidate Tracker'!$I:$I,"Female")=0,"",COUNTIFS('Candidate Tracker'!$E:$E,'Positions Tracker'!$B33,'Candidate Tracker'!$I:$I,"Female")),"") | BB33: =IFERROR(IF(COUNTIFS('Candidate Tracker'!$E:$E,'Positions Tracker'!$B33,'Candidate Tracker'!$I:$I,"male")=0,"",COUNTIFS('Candidate Tracker'!$E:$E,'Positions Tracker'!$B33,'Candidate Tracker'!$I:$I,"male")),"") -> 1 | BC33: =IFERROR(IF(COUNTIFS('Candidate Tracker'!$E:$E,'Positions Tracker'!$B33,'Candidate Tracker'!$C:$C,"<>WIP",'Candidate Tracker'!$C:$C,"<>Hold",'Candidate Tracker'!$C:$C,"<>Cancelled",'Candidate Tracker'!$C:$C,"<>Closed")/COUNTIFS('Candidate Tracker'!$E:$E,'Positions Tracker'!$B33)=0,"",COUNTIFS('Candidate Tracker'!$E:$E,'Positions Tracker'!$B33,'Candidate Tracker'!$C:$C,"<>WIP",'Candidate Tracker'!$C:$C,"<>Hold",'Candidate Tracker'!$C:$C,"<>Cancelled",'Candidate Tracker'!$C:$C,"<>Closed")/COUNTIFS('Candidate Tracker'!$E:$E,'Positions Tracker'!$B33)),"") -> 1 | BD33: =IFERROR(IF($M33="","",TEXT($M33,"MMM-YY")),"") -> May-24 | BE33: =IFERROR(IF($AI33="","",TEXT($AI33,"MMM-YY")),"") -> May-24 | BF33: =IFERROR(IF($AM33="","",TEXT($AM33,"MMM-YY")),"") -> Jun-24 | BG33: =IFERROR(IF($AS33="","",TEXT($AS33,"MMM-YY")),"") -> Jul-24
A34: =A33+1 -> 33 | B34: 20252505 | C34: Joined | D34: Joined | E34: Service Technical Support | F34: Application Support | G34: Integrated Business Services | H34: Global Monitoring Solutions | I34: Nitin Kudale | J34: Referral | K34: 45531 | L34: 45450 | M34: 45623 | N34: T8 | X34: Pune | Y34: Raisoni, Rushabh | Z34: Referral | AA34: Selection - Mayuri Jadhav | AE34: Mayuri Jadhav | AF34: 8378024668 | AG34: mayuri.wid2800@gmail.com | AH34: Female | AI34: 45684 | AJ34: 45695 | AK34: Pune | AL34: 850000 | AM34: 45695 | AN34: 45695 | AP34: 45697 | AQ34: 45697 | AS34: 45761 | AT34: =IFERROR(SUM(IF(AND(ISBLANK(T34),ISBLANK(Q34)),0,IF(T34="",TODAY()-Q34,T34-Q34))+IF(AND(ISBLANK(S34),ISBLANK(P34)),0,IF(S34="",TODAY()-P34,S34-P34))+IF(AND(ISBLANK(O34),ISBLANK(R34)),0,IF(R34="",TODAY()-O34,R34-O34))),"") -> 0 | AU34: =IFERROR(IF(($M34=""),"",IF(OR(,$C34="Offer in Progress",$C34="WIP",$C34="WIP/Drop",$C34="WIP/New",$C34="WIP/Hold"),(TODAY()-$M34)-$AT34,"")),"") | AV34: {=IFERROR(_xlfn.IFS($AU34="","",$AU34<=15,"0-15",AND($AU34>=16,$AU34<=30),"16-30",AND($AU34>=31,$AU34<=45),"31-45",AND($AU34>=46,$AU34<=60),"46-60",AND($AU34>=61,$AU34<=90),"61-90",AND($AU34>=91),"> 90",AND($AU34>=2000),""),"")} | AW34: {=IFERROR(_xlfn.IFS(OR($M34="",$AM34=""),"",OR($C34="Offered",$C34="Joined"),($AM34-$M34)-$AT34),"")} -> 72 | AX34: {=IFERROR(_xlfn.IFS(OR($M34="",$AS34=""),"",$C34="Joined",($AS34-$M34)-$AT34),"")} -> 138 | AY34: =IFERROR(IF(COUNTIFS('Candidate Tracker'!$E:$E,'Positions Tracker'!$B34,'Candidate Tracker'!$C:$C,"Offer Drop")=0,"",COUNTIFS('Candidate Tracker'!$E:$E,'Positions Tracker'!$B34,'Candidate Tracker'!$C:$C,"Offer Drop")),"") | AZ34: =IFERROR(IF((COUNTIFS('Candidate Tracker'!$D:$D,"<>",'Candidate Tracker'!$D:$D,"<>Screening",'Candidate Tracker'!$D:$D,"<>Screening Pending",'Candidate Tracker'!$D:$D,"<>Candidate Hold",'Candidate Tracker'!$D:$D,"<>Position Cancelled",'Candidate Tracker'!$D:$D,"<>Internal closed")/COUNTIF('Candidate Tracker'!$D:$D,"<>"))=0,"",(COUNTIFS('Candidate Tracker'!$D:$D,"<>",'Candidate Tracker'!$D:$D,"<>Screening",'Candidate Tracker'!$D:$D,"<>Candidate Hold",'Candidate Tracker'!$D:$D,"<>Position Cancelled",'Candidate Tracker'!$D:$D,"<>Internal closed")/COUNTIF('Candidate Tracker'!$D:$D,"<>"))),"") -> 0.88111888 | BA34: =IFERROR(IF(COUNTIFS('Candidate Tracker'!$E:$E,'Positions Tracker'!$B34,'Candidate Tracker'!$I:$I,"Female")=0,"",COUNTIFS('Candidate Tracker'!$E:$E,'Positions Tracker'!$B34,'Candidate Tracker'!$I:$I,"Female")),"") | BB34: =IFERROR(IF(COUNTIFS('Candidate Tracker'!$E:$E,'Positions Tracker'!$B34,'Candidate Tracker'!$I:$I,"male")=0,"",COUNTIFS('Candidate Tracker'!$E:$E,'Positions Tracker'!$B34,'Candidate Tracker'!$I:$I,"male")),"") | BC34: =IFERROR(IF(COUNTIFS('Candidate Tracker'!$E:$E,'Positions Tracker'!$B34,'Candidate Tracker'!$C:$C,"<>WIP",'Candidate Tracker'!$C:$C,"<>Hold",'Candidate Tracker'!$C:$C,"<>Cancelled",'Candidate Tracker'!$C:$C,"<>Closed")/COUNTIFS('Candidate Tracker'!$E:$E,'Positions Tracker'!$B34)=0,"",COUNTIFS('Candidate Tracker'!$E:$E,'Positions Tracker'!$B34,'Candidate Tracker'!$C:$C,"<>WIP",'Candidate Tracker'!$C:$C,"<>Hold",'Candidate Tracker'!$C:$C,"<>Cancelled",'Candidate Tracker'!$C:$C,"<>Closed")/COUNTIFS('Candidate Tracker'!$E:$E,'Positions Tracker'!$B34)),"") | BD34: =IFERROR(IF($M34="","",TEXT($M34,"MMM-YY")),"") -> Nov-24 | BE34: =IFERROR(IF($AI34="","",TEXT($AI34,"MMM-YY")),"") -> Jan-25 | BF34: =IFERROR(IF($AM34="","",TEXT($AM34,"MMM-YY")),"") -> Feb-25 | BG34: =IFERROR(IF($AS34="","",TEXT($AS34,"MMM-YY")),"") -> Apr-25
A35: =A34+1 -> 34 | B35: 20246232 | C35: Offer Drop | D35: Offer Decline | E35: Principal Eng - Java | F35: Java | G35: Integrated Business Services | H35: Global Monitoring Solutions | I35: Nitin Kudale | J35: External | K35: 45460 | L35: 45460 | M35: 45674 | X35: Pune | Y35: Hiwrale, Sanjana | Z35: Hiwrale, Sanjana | AA35: Mahendra Pitamber Kolambe - Offer Decline. Position was under Sanjana, Transferred to Rushabh on 20-Feb-25 | AE35: Mahendra Pitamber Kolambe | AF35: 9767994726 | AH35: Male | AI35: 45481 | AJ35: 45488 | AL35: 2700000 | AM35: 45488 | AT35: =IFERROR(SUM(IF(AND(ISBLANK(T35),ISBLANK(Q35)),0,IF(T35="",TODAY()-Q35,T35-Q35))+IF(AND(ISBLANK(S35),ISBLANK(P35)),0,IF(S35="",TODAY()-P35,S35-P35))+IF(AND(ISBLANK(O35),ISBLANK(R35)),0,IF(R35="",TODAY()-O35,R35-O35))),"") -> 0 | AU35: =IFERROR(IF(($M35=""),"",IF(OR(,$C35="Offer in Progress",$C35="WIP",$C35="WIP/Drop",$C35="WIP/New",$C35="WIP/Hold"),(TODAY()-$M35)-$AT35,"")),"") | AV35: {=IFERROR(_xlfn.IFS($AU35="","",$AU35<=15,"0-15",AND($AU35>=16,$AU35<=30),"16-30",AND($AU35>=31,$AU35<=45),"31-45",AND($AU35>=46,$AU35<=60),"46-60",AND($AU35>=61,$AU35<=90),"61-90",AND($AU35>=91),"> 90",AND($AU35>=2000),""),"")} | AW35: {=IFERROR(_xlfn.IFS(OR($M35="",$AM35=""),"",OR($C35="Offered",$C35="Joined"),($AM35-$M35)-$AT35),"")} | AX35: {=IFERROR(_xlfn.IFS(OR($M35="",$AS35=""),"",$C35="Joined",($AS35-$M35)-$AT35),"")} | AY35: =IFERROR(IF(COUNTIFS('Candidate Tracker'!$E:$E,'Positions Tracker'!$B35,'Candidate Tracker'!$C:$C,"Offer Drop")=0,"",COUNTIFS('Candidate Tracker'!$E:$E,'Positions Tracker'!$B35,'Candidate Tracker'!$C:$C,"Offer Drop")),"") | AZ35: =IFERROR(IF((COUNTIFS('Candidate Tracker'!$D:$D,"<>",'Candidate Tracker'!$D:$D,"<>Screening",'Candidate Tracker'!$D:$D,"<>Screening Pending",'Candidate Tracker'!$D:$D,"<>Candidate Hold",'Candidate Tracker'!$D:$D,"<>Position Cancelled",'Candidate Tracker'!$D:$D,"<>Internal closed")/COUNTIF('Candidate Tracker'!$D:$D,"<>"))=0,"",(COUNTIFS('Candidate Tracker'!$D:$D,"<>",'Candidate Tracker'!$D:$D,"<>Screening",'Candidate Tracker'!$D:$D,"<>Candidate Hold",'Candidate Tracker'!$D:$D,"<>Position Cancelled",'Candidate Tracker'!$D:$D,"<>Internal closed")/COUNTIF('Candidate Tracker'!$D:$D,"<>"))),"") -> 0.88111888 | BA35: =IFERROR(IF(COUNTIFS('Candidate Tracker'!$E:$E,'Positions Tracker'!$B35,'Candidate Tracker'!$I:$I,"Female")=0,"",COUNTIFS('Candidate Tracker'!$E:$E,'Positions Tracker'!$B35,'Candidate Tracker'!$I:$I,"Female")),"") | BB35: =IFERROR(IF(COUNTIFS('Candidate Tracker'!$E:$E,'Positions Tracker'!$B35,'Candidate Tracker'!$I:$I,"male")=0,"",COUNTIFS('Candidate Tracker'!$E:$E,'Positions Tracker'!$B35,'Candidate Tracker'!$I:$I,"male")),"") -> 13 | BC35: =IFERROR(IF(COUNTIFS('Candidate Tracker'!$E:$E,'Positions Tracker'!$B35,'Candidate Tracker'!$C:$C,"<>WIP",'Candidate Tracker'!$C:$C,"<>Hold",'Candidate Tracker'!$C:$C,"<>Cancelled",'Candidate Tracker'!$C:$C,"<>Closed")/COUNTIFS('Candidate Tracker'!$E:$E,'Positions Tracker'!$B35)=0,"",COUNTIFS('Candidate Tracker'!$E:$E,'Positions Tracker'!$B35,'Candidate Tracker'!$C:$C,"<>WIP",'Candidate Tracker'!$C:$C,"<>Hold",'Candidate Tracker'!$C:$C,"<>Cancelled",'Candidate Tracker'!$C:$C,"<>Closed")/COUNTIFS('Candidate Tracker'!$E:$E,'Positions Tracker'!$B35)),"") | BD35: =IFERROR(IF($M35="","",TEXT($M35,"MMM-YY")),"") -> Jan-25 | BE35: =IFERROR(IF($AI35="","",TEXT($AI35,"MMM-YY")),"") -> Jul-24 | BF35: =IFERROR(IF($AM35="","",TEXT($AM35,"MMM-YY")),"") -> Jul-24 | BG35: =IFERROR(IF($AS35="","",TEXT($AS35,"MMM-YY")),"")
A36: =A35+1 -> 35 | B36: TG3 | C36: Joined | D36: Joined | E36: Sr Engineer - Firmware | F36: Firmware | G36: Integrated Business Services | H36: ITS | I36: Sameer U | J36: External | K36: 45468 | L36: 45468 | M36: 45468 | N36: T13 | X36: Pune | Y36: Raisoni, Rushabh | Z36: Raisoni, Rushabh | AA36: Joined | AE36: Avik Bhowmik | AF36: 9096041070 | AG36: avik.bhowmik@gmail.com | AH36: Male | AI36: 45392 | AJ36: 45394 | AK36: Pune | AL36: 2400000 | AM36: 45417 | AN36: 45394 | AP36: 45417 | AQ36: 45417 | AR36: 45484 | AS36: 45488 | AT36: =IFERROR(SUM(IF(AND(ISBLANK(T36),ISBLANK(Q36)),0,IF(T36="",TODAY()-Q36,T36-Q36))+IF(AND(ISBLANK(S36),ISBLANK(P36)),0,IF(S36="",TODAY()-P36,S36-P36))+IF(AND(ISBLANK(O36),ISBLANK(R36)),0,IF(R36="",TODAY()-O36,R36-O36))),"") -> 0 | AU36: =IFERROR(IF(($M36=""),"",IF(OR(,$C36="Offer in Progress",$C36="WIP",$C36="WIP/Drop",$C36="WIP/New",$C36="WIP/Hold"),(TODAY()-$M36)-$AT36,"")),"") | AV36: {=IFERROR(_xlfn.IFS($AU36="","",$AU36<=15,"0-15",AND($AU36>=16,$AU36<=30),"16-30",AND($AU36>=31,$AU36<=45),"31-45",AND($AU36>=46,$AU36<=60),"46-60",AND($AU36>=61,$AU36<=90),"61-90",AND($AU36>=91),"> 90",AND($AU36>=2000),""),"")} | AW36: {=IFERROR(_xlfn.IFS(OR($M36="",$AM36=""),"",OR($C36="Offered",$C36="Joined"),($AM36-$M36)-$AT36),"")} -> -51 | AX36: {=IFERROR(_xlfn.IFS(OR($M36="",$AS36=""),"",$C36="Joined",($AS36-$M36)-$AT36),"")} -> 20 | AY36: =IFERROR(IF(COUNTIFS('Candidate Tracker'!$E:$E,'Positions Tracker'!$B36,'Candidate Tracker'!$C:$C,"Offer Drop")=0,"",COUNTIFS('Candidate Tracker'!$E:$E,'Positions Tracker'!$B36,'Candidate Tracker'!$C:$C,"Offer Drop")),"") | AZ36: =IFERROR(IF((COUNTIFS('Candidate Tracker'!$D:$D,"<>",'Candidate Tracker'!$D:$D,"<>Screening",'Candidate Tracker'!$D:$D,"<>Screening Pending",'Candidate Tracker'!$D:$D,"<>Candidate Hold",'Candidate Tracker'!$D:$D,"<>Position Cancelled",'Candidate Tracker'!$D:$D,"<>Internal closed")/COUNTIF('Candidate Tracker'!$D:$D,"<>"))=0,"",(COUNTIFS('Candidate Tracker'!$D:$D,"<>",'Candidate Tracker'!$D:$D,"<>Screening",'Candidate Tracker'!$D:$D,"<>Candidate Hold",'Candidate Tracker'!$D:$D,"<>Position Cancelled",'Candidate Tracker'!$D:$D,"<>Internal closed")/COUNTIF('Candidate Tracker'!$D:$D,"<>"))),"") -> 0.88111888 | BA36: =IFERROR(IF(COUNTIFS('Candidate Tracker'!$E:$E,'Positions Tracker'!$B36,'Candidate Tracker'!$I:$I,"Female")=0,"",COUNTIFS('Candidate Tracker'!$E:$E,'Positions Tracker'!$B36,'Candidate Tracker'!$I:$I,"Female")),"") | BB36: =IFERROR(IF(COUNTIFS('Candidate Tracker'!$E:$E,'Positions Tracker'!$B36,'Candidate Tracker'!$I:$I,"male")=0,"",COUNTIFS('Candidate Tracker'!$E:$E,'Positions Tracker'!$B36,'Candidate Tracker'!$I:$I,"male")),"") -> 1 | BC36: =IFERROR(IF(COUNTIFS('Candidate Tracker'!$E:$E,'Positions Tracker'!$B36,'Candidate Tracker'!$C:$C,"<>WIP",'Candidate Tracker'!$C:$C,"<>Hold",'Candidate Tracker'!$C:$C,"<>Cancelled",'Candidate Tracker'!$C:$C,"<>Closed")/COUNTIFS('Candidate Tracker'!$E:$E,'Positions Tracker'!$B36)=0,"",COUNTIFS('Candidate Tracker'!$E:$E,'Positions Tracker'!$B36,'Candidate Tracker'!$C:$C,"<>WIP",'Candidate Tracker'!$C:$C,"<>Hold",'Candidate Tracker'!$C:$C,"<>Cancelled",'Candidate Tracker'!$C:$C,"<>Closed")/COUNTIFS('Candidate Tracker'!$E:$E,'Positions Tracker'!$B36)),"") -> 1 | BD36: =IFERROR(IF($M36="","",TEXT($M36,"MMM-YY")),"") -> Jun-24 | BE36: =IFERROR(IF($AI36="","",TEXT($AI36,"MMM-YY")),"") -> Apr-24 | BF36: =IFERROR(IF($AM36="","",TEXT($AM36,"MMM-YY")),"") -> May-24 | BG36: =IFERROR(IF($AS36="","",TEXT($AS36,"MMM-YY")),"") -> Jul-24
A37: =A36+1 -> 36 | B37: 20243901 | C37: Joined | D37: Joined | E37: Sr. Engineer - Electrical Design | F37: IMS Design | G37: Integrated Business Services | H37: IMS | I37: Vinayak Bhat | J37: External | K37: 45476 | L37: 45476 | M37: 45476 | N37: T12 | X37: Pune | Y37: Raisoni, Rushabh | Z37: Raisoni, Rushabh | AA37: Joined | AE37: Maheshkumar Chandak | AF37: 7030678844 | AG37: m.chandak444@gmail.com | AH37: Male | AI37: 45527 | AJ37: 45529 | AK37: Pune | AL37: 1650000 | AM37: 45538 | AN37: 45529 | AP37: 45538 | AQ37: 45538 | AR37: 45624 | AS37: 45628 | AT37: =IFERROR(SUM(IF(AND(ISBLANK(T37),ISBLANK(Q37)),0,IF(T37="",TODAY()-Q37,T37-Q37))+IF(AND(ISBLANK(S37),ISBLANK(P37)),0,IF(S37="",TODAY()-P37,S37-P37))+IF(AND(ISBLANK(O37),ISBLANK(R37)),0,IF(R37="",TODAY()-O37,R37-O37))),"") -> 0 | AU37: =IFERROR(IF(($M37=""),"",IF(OR(,$C37="Offer in Progress",$C37="WIP",$C37="WIP/Drop",$C37="WIP/New",$C37="WIP/Hold"),(TODAY()-$M37)-$AT37,"")),"") | AV37: {=IFERROR(_xlfn.IFS($AU37="","",$AU37<=15,"0-15",AND($AU37>=16,$AU37<=30),"16-30",AND($AU37>=31,$AU37<=45),"31-45",AND($AU37>=46,$AU37<=60),"46-60",AND($AU37>=61,$AU37<=90),"61-90",AND($AU37>=91),"> 90",AND($AU37>=2000),""),"")} | AW37: {=IFERROR(_xlfn.IFS(OR($M37="",$AM37=""),"",OR($C37="Offered",$C37="Joined"),($AM37-$M37)-$AT37),"")} -> 62 | AX37: {=IFERROR(_xlfn.IFS(OR($M37="",$AS37=""),"",$C37="Joined",($AS37-$M37)-$AT37),"")} -> 152 | AY37: =IFERROR(IF(COUNTIFS('Candidate Tracker'!$E:$E,'Positions Tracker'!$B37,'Candidate Tracker'!$C:$C,"Offer Drop")=0,"",COUNTIFS('Candidate Tracker'!$E:$E,'Positions Tracker'!$B37,'Candidate Tracker'!$C:$C,"Offer Drop")),"") | AZ37: =IFERROR(IF((COUNTIFS('Candidate Tracker'!$D:$D,"<>",'Candidate Tracker'!$D:$D,"<>Screening",'Candidate Tracker'!$D:$D,"<>Screening Pending",'Candidate Tracker'!$D:$D,"<>Candidate Hold",'Candidate Tracker'!$D:$D,"<>Position Cancelled",'Candidate Tracker'!$D:$D,"<>Internal closed")/COUNTIF('Candidate Tracker'!$D:$D,"<>"))=0,"",(COUNTIFS('Candidate Tracker'!$D:$D,"<>",'Candidate Tracker'!$D:$D,"<>Screening",'Candidate Tracker'!$D:$D,"<>Candidate Hold",'Candidate Tracker'!$D:$D,"<>Position Cancelled",'Candidate Tracker'!$D:$D,"<>Internal closed")/COUNTIF('Candidate Tracker'!$D:$D,"<>"))),"") -> 0.88111888 | BA37: =IFERROR(IF(COUNTIFS('Candidate Tracker'!$E:$E,'Positions Tracker'!$B37,'Candidate Tracker'!$I:$I,"Female")=0,"",COUNTIFS('Candidate Tracker'!$E:$E,'Positions Tracker'!$B37,'Candidate Tracker'!$I:$I,"Female")),"") | BB37: =IFERROR(IF(COUNTIFS('Candidate Tracker'!$E:$E,'Positions Tracker'!$B37,'Candidate Tracker'!$I:$I,"male")=0,"",COUNTIFS('Candidate Tracker'!$E:$E,'Positions Tracker'!$B37,'Candidate Tracker'!$I:$I,"male")),"") -> 1 | BC37: =IFERROR(IF(COUNTIFS('Candidate Tracker'!$E:$E,'Positions Tracker'!$B37,'Candidate Tracker'!$C:$C,"<>WIP",'Candidate Tracker'!$C:$C,"<>Hold",'Candidate Tracker'!$C:$C,"<>Cancelled",'Candidate Tracker'!$C:$C,"<>Closed")/COUNTIFS('Candidate Tracker'!$E:$E,'Positions Tracker'!$B37)=0,"",COUNTIFS('Candidate Tracker'!$E:$E,'Positions Tracker'!$B37,'Candidate Tracker'!$C:$C,"<>WIP",'Candidate Tracker'!$C:$C,"<>Hold",'Candidate Tracker'!$C:$C,"<>Cancelled",'Candidate Tracker'!$C:$C,"<>Closed")/COUNTIFS('Candidate Tracker'!$E:$E,'Positions Tracker'!$B37)),"") -> 1 | BD37: =IFERROR(IF($M37="","",TEXT($M37,"MMM-YY")),"") -> Jul-24 | BE37: =IFERROR(IF($AI37="","",TEXT($AI37,"MMM-YY")),"") -> Aug-24 | BF37: =IFERROR(IF($AM37="","",TEXT($AM37,"MMM-YY")),"") -> Sep-24 | BG37: =IFERROR(IF($AS37="","",TEXT($AS37,"MMM-YY")),"") -> Dec-24
A38: =A37+1 -> 37 | B38: 20252486 | C38: Joined | D38: Joined | E38: Service Technical Support | F38: Application Support | G38: Integrated Business Services | H38: Global Monitoring Solutions | I38: Nitin Kudale | J38: Referral | K38: 45562 | L38: 45562 | M38: 45623 | N38: M1 | X38: Pune | Y38: Raisoni, Rushabh | Z38: Referral | AA38: Selection - Pritam Kadlag | AE38: Pritam Kadlag | AF38: 8390373904 | AG38: pritamkadlag@gmail.com | AH38: Male | AI38: 45677 | AJ38: 45698 | AK38: Pune | AL38: 1600000 | AM38: 45698 | AN38: 45698 | AP38: 45700 | AQ38: 45700 | AS38: 45768 | AT38: =IFERROR(SUM(IF(AND(ISBLANK(T38),ISBLANK(Q38)),0,IF(T38="",TODAY()-Q38,T38-Q38))+IF(AND(ISBLANK(S38),ISBLANK(P38)),0,IF(S38="",TODAY()-P38,S38-P38))+IF(AND(ISBLANK(O38),ISBLANK(R38)),0,IF(R38="",TODAY()-O38,R38-O38))),"") -> 0 | AU38: =IFERROR(IF(($M38=""),"",IF(OR(,$C38="Offer in Progress",$C38="WIP",$C38="WIP/Drop",$C38="WIP/New",$C38="WIP/Hold"),(TODAY()-$M38)-$AT38,"")),"") | AV38: {=IFERROR(_xlfn.IFS($AU38="","",$AU38<=15,"0-15",AND($AU38>=16,$AU38<=30),"16-30",AND($AU38>=31,$AU38<=45),"31-45",AND($AU38>=46,$AU38<=60),"46-60",AND($AU38>=61,$AU38<=90),"61-90",AND($AU38>=91),"> 90",AND($AU38>=2000),""),"")} | AW38: {=IFERROR(_xlfn.IFS(OR($M38="",$AM38=""),"",OR($C38="Offered",$C38="Joined"),($AM38-$M38)-$AT38),"")} -> 75 | AX38: {=IFERROR(_xlfn.IFS(OR($M38="",$AS38=""),"",$C38="Joined",($AS38-$M38)-$AT38),"")} -> 145 | AY38: =IFERROR(IF(COUNTIFS('Candidate Tracker'!$E:$E,'Positions Tracker'!$B38,'Candidate Tracker'!$C:$C,"Offer Drop")=0,"",COUNTIFS('Candidate Tracker'!$E:$E,'Positions Tracker'!$B38,'Candidate Tracker'!$C:$C,"Offer Drop")),"") | AZ38: =IFERROR(IF((COUNTIFS('Candidate Tracker'!$D:$D,"<>",'Candidate Tracker'!$D:$D,"<>Screening",'Candidate Tracker'!$D:$D,"<>Screening Pending",'Candidate Tracker'!$D:$D,"<>Candidate Hold",'Candidate Tracker'!$D:$D,"<>Position Cancelled",'Candidate Tracker'!$D:$D,"<>Internal closed")/COUNTIF('Candidate Tracker'!$D:$D,"<>"))=0,"",(COUNTIFS('Candidate Tracker'!$D:$D,"<>",'Candidate Tracker'!$D:$D,"<>Screening",'Candidate Tracker'!$D:$D,"<>Candidate Hold",'Candidate Tracker'!$D:$D,"<>Position Cancelled",'Candidate Tracker'!$D:$D,"<>Internal closed")/COUNTIF('Candidate Tracker'!$D:$D,"<>"))),"") -> 0.88111888 | BA38: =IFERROR(IF(COUNTIFS('Candidate Tracker'!$E:$E,'Positions Tracker'!$B38,'Candidate Tracker'!$I:$I,"Female")=0,"",COUNTIFS('Candidate Tracker'!$E:$E,'Positions Tracker'!$B38,'Candidate Tracker'!$I:$I,"Female")),"") | BB38: =IFERROR(IF(COUNTIFS('Candidate Tracker'!$E:$E,'Positions Tracker'!$B38,'Candidate Tracker'!$I:$I,"male")=0,"",COUNTIFS('Candidate Tracker'!$E:$E,'Positions Tracker'!$B38,'Candidate Tracker'!$I:$I,"male")),"") | BC38: =IFERROR(IF(COUNTIFS('Candidate Tracker'!$E:$E,'Positions Tracker'!$B38,'Candidate Tracker'!$C:$C,"<>WIP",'Candidate Tracker'!$C:$C,"<>Hold",'Candidate Tracker'!$C:$C,"<>Cancelled",'Candidate Tracker'!$C:$C,"<>Closed")/COUNTIFS('Candidate Tracker'!$E:$E,'Positions Tracker'!$B38)=0,"",COUNTIFS('Candidate Tracker'!$E:$E,'Positions Tracker'!$B38,'Candidate Tracker'!$C:$C,"<>WIP",'Candidate Tracker'!$C:$C,"<>Hold",'Candidate Tracker'!$C:$C,"<>Cancelled",'Candidate Tracker'!$C:$C,"<>Closed")/COUNTIFS('Candidate Tracker'!$E:$E,'Positions Tracker'!$B38)),"") | BD38: =IFERROR(IF($M38="","",TEXT($M38,"MMM-YY")),"") -> Nov-24 | BE38: =IFERROR(IF($AI38="","",TEXT($AI38,"MMM-YY")),"") -> Jan-25 | BF38: =IFERROR(IF($AM38="","",TEXT($AM38,"MMM-YY")),"") -> Feb-25 | BG38: =IFERROR(IF($AS38="","",TEXT($AS38,"MMM-YY")),"") -> Apr-25
A39: =A38+1 -> 38 | B39: 20246613 | C39: Joined | D39: Joined | E39: Engineer - Firmware | F39: Firmware | G39: Integrated Business Services | H39: KVM | I39: Jitesh Verma | J39: External | K39: 45560 | L39: 45560 | M39: 45560 | N39: T11 | X39: Pune | Y39: Raisoni, Rushabh | Z39: Raisoni, Rushabh | AA39: Joined | AE39: Suraj Bhand | AF39: 8605172315 | AG39: bhands.d@gmail.com | AH39: Male | AI39: 45588 | AJ39: 45591 | AK39: Pune | AL39: 2275000 | AM39: 45605 | AN39: 45591 | AP39: 45605 | AQ39: 45711 | AR39: 45672 | AS39: 45677 | AT39: =IFERROR(SUM(IF(AND(ISBLANK(T39),ISBLANK(Q39)),0,IF(T39="",TODAY()-Q39,T39-Q39))+IF(AND(ISBLANK(S39),ISBLANK(P39)),0,IF(S39="",TODAY()-P39,S39-P39))+IF(AND(ISBLANK(O39),ISBLANK(R39)),0,IF(R39="",TODAY()-O39,R39-O39))),"") -> 0 | AU39: =IFERROR(IF(($M39=""),"",IF(OR(,$C39="Offer in Progress",$C39="WIP",$C39="WIP/Drop",$C39="WIP/New",$C39="WIP/Hold"),(TODAY()-$M39)-$AT39,"")),"") | AV39: {=IFERROR(_xlfn.IFS($AU39="","",$AU39<=15,"0-15",AND($AU39>=16,$AU39<=30),"16-30",AND($AU39>=31,$AU39<=45),"31-45",AND($AU39>=46,$AU39<=60),"46-60",AND($AU39>=61,$AU39<=90),"61-90",AND($AU39>=91),"> 90",AND($AU39>=2000),""),"")} | AW39: {=IFERROR(_xlfn.IFS(OR($M39="",$AM39=""),"",OR($C39="Offered",$C39="Joined"),($AM39-$M39)-$AT39),"")} -> 45 | AX39: {=IFERROR(_xlfn.IFS(OR($M39="",$AS39=""),"",$C39="Joined",($AS39-$M39)-$AT39),"")} -> 117 | AY39: =IFERROR(IF(COUNTIFS('Candidate Tracker'!$E:$E,'Positions Tracker'!$B39,'Candidate Tracker'!$C:$C,"Offer Drop")=0,"",COUNTIFS('Candidate Tracker'!$E:$E,'Positions Tracker'!$B39,'Candidate Tracker'!$C:$C,"Offer Drop")),"") | AZ39: =IFERROR(IF((COUNTIFS('Candidate Tracker'!$D:$D,"<>",'Candidate Tracker'!$D:$D,"<>Screening",'Candidate Tracker'!$D:$D,"<>Screening Pending",'Candidate Tracker'!$D:$D,"<>Candidate Hold",'Candidate Tracker'!$D:$D,"<>Position Cancelled",'Candidate Tracker'!$D:$D,"<>Internal closed")/COUNTIF('Candidate Tracker'!$D:$D,"<>"))=0,"",(COUNTIFS('Candidate Tracker'!$D:$D,"<>",'Candidate Tracker'!$D:$D,"<>Screening",'Candidate Tracker'!$D:$D,"<>Candidate Hold",'Candidate Tracker'!$D:$D,"<>Position Cancelled",'Candidate Tracker'!$D:$D,"<>Internal closed")/COUNTIF('Candidate Tracker'!$D:$D,"<>"))),"") -> 0.88111888 | BA39: =IFERROR(IF(COUNTIFS('Candidate Tracker'!$E:$E,'Positions Tracker'!$B39,'Candidate Tracker'!$I:$I,"Female")=0,"",COUNTIFS('Candidate Tracker'!$E:$E,'Positions Tracker'!$B39,'Candidate Tracker'!$I:$I,"Female")),"") | BB39: =IFERROR(IF(COUNTIFS('Candidate Tracker'!$E:$E,'Positions Tracker'!$B39,'Candidate Tracker'!$I:$I,"male")=0,"",COUNTIFS('Candidate Tracker'!$E:$E,'Positions Tracker'!$B39,'Candidate Tracker'!$I:$I,"male")),"") -> 1 | BC39: =IFERROR(IF(COUNTIFS('Candidate Tracker'!$E:$E,'Positions Tracker'!$B39,'Candidate Tracker'!$C:$C,"<>WIP",'Candidate Tracker'!$C:$C,"<>Hold",'Candidate Tracker'!$C:$C,"<>Cancelled",'Candidate Tracker'!$C:$C,"<>Closed")/COUNTIFS('Candidate Tracker'!$E:$E,'Positions Tracker'!$B39)=0,"",COUNTIFS('Candidate Tracker'!$E:$E,'Positions Tracker'!$B39,'Candidate Tracker'!$C:$C,"<>WIP",'Candidate Tracker'!$C:$C,"<>Hold",'Candidate Tracker'!$C:$C,"<>Cancelled",'Candidate Tracker'!$C:$C,"<>Closed")/COUNTIFS('Candidate Tracker'!$E:$E,'Positions Tracker'!$B39)),"") -> 1 | BD39: =IFERROR(IF($M39="","",TEXT($M39,"MMM-YY")),"") -> Sep-24 | BE39: =IFERROR(IF($AI39="","",TEXT($AI39,"MMM-YY")),"") -> Oct-24 | BF39: =IFERROR(IF($AM39="","",TEXT($AM39,"MMM-YY")),"") -> Nov-24 | BG39: =IFERROR(IF($AS39="","",TEXT($AS39,"MMM-YY")),"") -> Jan-25
A40: =A39+1 -> 39 | B40: 20245964 | C40: Joined | D40: Joined | E40: Lead Engineer - BIM | F40: MEPF | G40: Integrated Business Services | H40: BIM | I40: Hitesh Shende | J40: External | K40: 45391 | L40: 45579 | M40: 45592 | N40: T11 | X40: Pune | Y40: Raisoni, Rushabh | Z40: Raisoni, Rushabh | AA40: Joined | AE40: Nikhil Jadhav | AF40: 9975965098 | AG40: nikhilj028@gmail.com | AH40: Male | AI40: 45611 | AJ40: 45613 | AK40: Pune | AL40: 1700000 | AM40: 45618 | AN40: 45613 | AP40: 45618 | AQ40: 45618 | AR40: 45680 | AS40: 45684 | AT40: =IFERROR(SUM(IF(AND(ISBLANK(T40),ISBLANK(Q40)),0,IF(T40="",TODAY()-Q40,T40-Q40))+IF(AND(ISBLANK(S40),ISBLANK(P40)),0,IF(S40="",TODAY()-P40,S40-P40))+IF(AND(ISBLANK(O40),ISBLANK(R40)),0,IF(R40="",TODAY()-O40,R40-O40))),"") -> 0 | AU40: =IFERROR(IF(($M40=""),"",IF(OR(,$C40="Offer in Progress",$C40="WIP",$C40="WIP/Drop",$C40="WIP/New",$C40="WIP/Hold"),(TODAY()-$M40)-$AT40,"")),"") | AV40: {=IFERROR(_xlfn.IFS($AU40="","",$AU40<=15,"0-15",AND($AU40>=16,$AU40<=30),"16-30",AND($AU40>=31,$AU40<=45),"31-45",AND($AU40>=46,$AU40<=60),"46-60",AND($AU40>=61,$AU40<=90),"61-90",AND($AU40>=91),"> 90",AND($AU40>=2000),""),"")} | AW40: {=IFERROR(_xlfn.IFS(OR($M40="",$AM40=""),"",OR($C40="Offered",$C40="Joined"),($AM40-$M40)-$AT40),"")} -> 26 | AX40: {=IFERROR(_xlfn.IFS(OR($M40="",$AS40=""),"",$C40="Joined",($AS40-$M40)-$AT40),"")} -> 92 | AY40: =IFERROR(IF(COUNTIFS('Candidate Tracker'!$E:$E,'Positions Tracker'!$B40,'Candidate Tracker'!$C:$C,"Offer Drop")=0,"",COUNTIFS('Candidate Tracker'!$E:$E,'Positions Tracker'!$B40,'Candidate Tracker'!$C:$C,"Offer Drop")),"") | AZ40: =IFERROR(IF((COUNTIFS('Candidate Tracker'!$D:$D,"<>",'Candidate Tracker'!$D:$D,"<>Screening",'Candidate Tracker'!$D:$D,"<>Screening Pending",'Candidate Tracker'!$D:$D,"<>Candidate Hold",'Candidate Tracker'!$D:$D,"<>Position Cancelled",'Candidate Tracker'!$D:$D,"<>Internal closed")/COUNTIF('Candidate Tracker'!$D:$D,"<>"))=0,"",(COUNTIFS('Candidate Tracker'!$D:$D,"<>",'Candidate Tracker'!$D:$D,"<>Screening",'Candidate Tracker'!$D:$D,"<>Candidate Hold",'Candidate Tracker'!$D:$D,"<>Position Cancelled",'Candidate Tracker'!$D:$D,"<>Internal closed")/COUNTIF('Candidate Tracker'!$D:$D,"<>"))),"") -> 0.88111888 | BA40: =IFERROR(IF(COUNTIFS('Candidate Tracker'!$E:$E,'Positions Tracker'!$B40,'Candidate Tracker'!$I:$I,"Female")=0,"",COUNTIFS('Candidate Tracker'!$E:$E,'Positions Tracker'!$B40,'Candidate Tracker'!$I:$I,"Female")),"") | BB40: =IFERROR(IF(COUNTIFS('Candidate Tracker'!$E:$E,'Positions Tracker'!$B40,'Candidate Tracker'!$I:$I,"male")=0,"",COUNTIFS('Candidate Tracker'!$E:$E,'Positions Tracker'!$B40,'Candidate Tracker'!$I:$I,"male")),"") -> 1 | BC40: =IFERROR(IF(COUNTIFS('Candidate Tracker'!$E:$E,'Positions Tracker'!$B40,'Candidate Tracker'!$C:$C,"<>WIP",'Candidate Tracker'!$C:$C,"<>Hold",'Candidate Tracker'!$C:$C,"<>Cancelled",'Candidate Tracker'!$C:$C,"<>Closed")/COUNTIFS('Candidate Tracker'!$E:$E,'Positions Tracker'!$B40)=0,"",COUNTIFS('Candidate Tracker'!$E:$E,'Positions Tracker'!$B40,'Candidate Tracker'!$C:$C,"<>WIP",'Candidate Tracker'!$C:$C,"<>Hold",'Candidate Tracker'!$C:$C,"<>Cancelled",'Candidate Tracker'!$C:$C,"<>Closed")/COUNTIFS('Candidate Tracker'!$E:$E,'Positions Tracker'!$B40)),"") -> 1 | BD40: =IFERROR(IF($M40="","",TEXT($M40,"MMM-YY")),"") -> Oct-24 | BE40: =IFERROR(IF($AI40="","",TEXT($AI40,"MMM-YY")),"") -> Nov-24 | BF40: =IFERROR(IF($AM40="","",TEXT($AM40,"MMM-YY")),"") -> Nov-24 | BG40: =IFERROR(IF($AS40="","",TEXT($AS40,"MMM-YY")),"") -> Jan-25
A41: =A40+1 -> 40 | B41: 20248963 | C41: Joined | D41: Joined | E41: Engineer - Firmware | F41: Firmware | G41: Integrated Business Services | H41: KVM | I41: Jitesh Verma | J41: External | K41: 45560 | L41: 45603 | M41: 45603 | N41: T10 | X41: Pune | Y41: Raisoni, Rushabh | Z41: Raisoni, Rushabh | AA41: Joined | AE41: Nikita Taklikar | AF41: 8552882800 | AG41: nikitatakalikar94@gmail.com | AH41: Female | AI41: 45617 | AJ41: 45620 | AK41: Pune | AL41: 2200000 | AM41: 45631 | AN41: 45620 | AP41: 45631 | AQ41: 45631 | AR41: 45638 | AS41: 45642 | AT41: =IFERROR(SUM(IF(AND(ISBLANK(T41),ISBLANK(Q41)),0,IF(T41="",TODAY()-Q41,T41-Q41))+IF(AND(ISBLANK(S41),ISBLANK(P41)),0,IF(S41="",TODAY()-P41,S41-P41))+IF(AND(ISBLANK(O41),ISBLANK(R41)),0,IF(R41="",TODAY()-O41,R41-O41))),"") -> 0 | AU41: =IFERROR(IF(($M41=""),"",IF(OR(,$C41="Offer in Progress",$C41="WIP",$C41="WIP/Drop",$C41="WIP/New",$C41="WIP/Hold"),(TODAY()-$M41)-$AT41,"")),"") | AV41: {=IFERROR(_xlfn.IFS($AU41="","",$AU41<=15,"0-15",AND($AU41>=16,$AU41<=30),"16-30",AND($AU41>=31,$AU41<=45),"31-45",AND($AU41>=46,$AU41<=60),"46-60",AND($AU41>=61,$AU41<=90),"61-90",AND($AU41>=91),"> 90",AND($AU41>=2000),""),"")} | AW41: {=IFERROR(_xlfn.IFS(OR($M41="",$AM41=""),"",OR($C41="Offered",$C41="Joined"),($AM41-$M41)-$AT41),"")} -> 28 | AX41: {=IFERROR(_xlfn.IFS(OR($M41="",$AS41=""),"",$C41="Joined",($AS41-$M41)-$AT41),"")} -> 39 | AY41: =IFERROR(IF(COUNTIFS('Candidate Tracker'!$E:$E,'Positions Tracker'!$B41,'Candidate Tracker'!$C:$C,"Offer Drop")=0,"",COUNTIFS('Candidate Tracker'!$E:$E,'Positions Tracker'!$B41,'Candidate Tracker'!$C:$C,"Offer Drop")),"") | AZ41: =IFERROR(IF((COUNTIFS('Candidate Tracker'!$D:$D,"<>",'Candidate Tracker'!$D:$D,"<>Screening",'Candidate Tracker'!$D:$D,"<>Screening Pending",'Candidate Tracker'!$D:$D,"<>Candidate Hold",'Candidate Tracker'!$D:$D,"<>Position Cancelled",'Candidate Tracker'!$D:$D,"<>Internal closed")/COUNTIF('Candidate Tracker'!$D:$D,"<>"))=0,"",(COUNTIFS('Candidate Tracker'!$D:$D,"<>",'Candidate Tracker'!$D:$D,"<>Screening",'Candidate Tracker'!$D:$D,"<>Candidate Hold",'Candidate Tracker'!$D:$D,"<>Position Cancelled",'Candidate Tracker'!$D:$D,"<>Internal closed")/COUNTIF('Candidate Tracker'!$D:$D,"<>"))),"") -> 0.88111888 | BA41: =IFERROR(IF(COUNTIFS('Candidate Tracker'!$E:$E,'Positions Tracker'!$B41,'Candidate Tracker'!$I:$I,"Female")=0,"",COUNTIFS('Candidate Tracker'!$E:$E,'Positions Tracker'!$B41,'Candidate Tracker'!$I:$I,"Female")),"") -> 1 | BB41: =IFERROR(IF(COUNTIFS('Candidate Tracker'!$E:$E,'Positions Tracker'!$B41,'Candidate Tracker'!$I:$I,"male")=0,"",COUNTIFS('Candidate Tracker'!$E:$E,'Positions Tracker'!$B41,'Candidate Tracker'!$I:$I,"male")),"") | BC41: =IFERROR(IF(COUNTIFS('Candidate Tracker'!$E:$E,'Positions Tracker'!$B41,'Candidate Tracker'!$C:$C,"<>WIP",'Candidate Tracker'!$C:$C,"<>Hold",'Candidate Tracker'!$C:$C,"<>Cancelled",'Candidate Tracker'!$C:$C,"<>Closed")/COUNTIFS('Candidate Tracker'!$E:$E,'Positions Tracker'!$B41)=0,"",COUNTIFS('Candidate Tracker'!$E:$E,'Positions Tracker'!$B41,'Candidate Tracker'!$C:$C,"<>WIP",'Candidate Tracker'!$C:$C,"<>Hold",'Candidate Tracker'!$C:$C,"<>Cancelled",'Candidate Tracker'!$C:$C,"<>Closed")/COUNTIFS('Candidate Tracker'!$E:$E,'Positions Tracker'!$B41)),"") -> 1 | BD41: =IFERROR(IF($M41="","",TEXT($M41,"MMM-YY")),"") -> Nov-24 | BE41: =IFERROR(IF($AI41="","",TEXT($AI41,"MMM-YY")),"") -> Nov-24 | BF41: =IFERROR(IF($AM41="","",TEXT($AM41,"MMM-YY")),"") -> Dec-24 | BG41: =IFERROR(IF($AS41="","",TEXT($AS41,"MMM-YY")),"") -> Dec-24
A42: =A41+1 -> 41 | B42: 20252855 | C42: Offer Drop | D42: Offer Decline | E42: Sr. Software Eng - Security | F42: Full Stack | G42: Integrated Business Services | H42: Global Monitoring Solutions | I42: Nitin Kudale | J42: External | K42: 45625 | L42: 45625 | M42: 45625 | N42: T10 | X42: Pune | Y42: Raisoni, Rushabh | Z42: Raisoni, Rushabh | AA42: Offer decline - Vyankatesh Manwade Decline date - 17 March | AE42: Vyankatesh Manwade | AF42: 7057700769 | AG42: vyankymanwade8187@gmail.com | AH42: Male | AI42: 45705 | AJ42: 45709 | AK42: Pune | AL42: 1600000 | AM42: 45709 | AN42: 45709 | AO42: 45733 | AP42: 45711 | AQ42: 45711 | AS42: 45740 | AT42: =IFERROR(SUM(IF(AND(ISBLANK(T42),ISBLANK(Q42)),0,IF(T42="",TODAY()-Q42,T42-Q42))+IF(AND(ISBLANK(S42),ISBLANK(P42)),0,IF(S42="",TODAY()-P42,S42-P42))+IF(AND(ISBLANK(O42),ISBLANK(R42)),0,IF(R42="",TODAY()-O42,R42-O42))),"") -> 0 | AU42: =IFERROR(IF(($M42=""),"",IF(OR(,$C42="Offer in Progress",$C42="WIP",$C42="WIP/Drop",$C42="WIP/New",$C42="WIP/Hold"),(TODAY()-$M42)-$AT42,"")),"") | AV42: {=IFERROR(_xlfn.IFS($AU42="","",$AU42<=15,"0-15",AND($AU42>=16,$AU42<=30),"16-30",AND($AU42>=31,$AU42<=45),"31-45",AND($AU42>=46,$AU42<=60),"46-60",AND($AU42>=61,$AU42<=90),"61-90",AND($AU42>=91),"> 90",AND($AU42>=2000),""),"")} | AW42: {=IFERROR(_xlfn.IFS(OR($M42="",$AM42=""),"",OR($C42="Offered",$C42="Joined"),($AM42-$M42)-$AT42),"")} | AX42: {=IFERROR(_xlfn.IFS(OR($M42="",$AS42=""),"",$C42="Joined",($AS42-$M42)-$AT42),"")} | AY42: =IFERROR(IF(COUNTIFS('Candidate Tracker'!$E:$E,'Positions Tracker'!$B42,'Candidate Tracker'!$C:$C,"Offer Drop")=0,"",COUNTIFS('Candidate Tracker'!$E:$E,'Positions Tracker'!$B42,'Candidate Tracker'!$C:$C,"Offer Drop")),"") -> 1 | AZ42: =IFERROR(IF((COUNTIFS('Candidate Tracker'!$D:$D,"<>",'Candidate Tracker'!$D:$D,"<>Screening",'Candidate Tracker'!$D:$D,"<>Screening Pending",'Candidate Tracker'!$D:$D,"<>Candidate Hold",'Candidate Tracker'!$D:$D,"<>Position Cancelled",'Candidate Tracker'!$D:$D,"<>Internal closed")/COUNTIF('Candidate Tracker'!$D:$D,"<>"))=0,"",(COUNTIFS('Candidate Tracker'!$D:$D,"<>",'Candidate Tracker'!$D:$D,"<>Screening",'Candidate Tracker'!$D:$D,"<>Candidate Hold",'Candidate Tracker'!$D:$D,"<>Position Cancelled",'Candidate Tracker'!$D:$D,"<>Internal closed")/COUNTIF('Candidate Tracker'!$D:$D,"<>"))),"") -> 0.88111888 | BA42: =IFERROR(IF(COUNTIFS('Candidate Tracker'!$E:$E,'Positions Tracker'!$B42,'Candidate Tracker'!$I:$I,"Female")=0,"",COUNTIFS('Candidate Tracker'!$E:$E,'Positions Tracker'!$B42,'Candidate Tracker'!$I:$I,"Female")),"") -> 5 | BB42: =IFERROR(IF(COUNTIFS('Candidate Tracker'!$E:$E,'Positions Tracker'!$B42,'Candidate Tracker'!$I:$I,"male")=0,"",COUNTIFS('Candidate Tracker'!$E:$E,'Positions Tracker'!$B42,'Candidate Tracker'!$I:$I,"male")),"") -> 24 | BC42: =IFERROR(IF(COUNTIFS('Candidate Tracker'!$E:$E,'Positions Tracker'!$B42,'Candidate Tracker'!$C:$C,"<>WIP",'Candidate Tracker'!$C:$C,"<>Hold",'Candidate Tracker'!$C:$C,"<>Cancelled",'Candidate Tracker'!$C:$C,"<>Closed")/COUNTIFS('Candidate Tracker'!$E:$E,'Positions Tracker'!$B42)=0,"",COUNTIFS('Candidate Tracker'!$E:$E,'Positions Tracker'!$B42,'Candidate Tracker'!$C:$C,"<>WIP",'Candidate Tracker'!$C:$C,"<>Hold",'Candidate Tracker'!$C:$C,"<>Cancelled",'Candidate Tracker'!$C:$C,"<>Closed")/COUNTIFS('Candidate Tracker'!$E:$E,'Positions Tracker'!$B42)),"") -> 0.034482759 | BD42: =IFERROR(IF($M42="","",TEXT($M42,"MMM-YY")),"") -> Nov-24 | BE42: =IFERROR(IF($AI42="","",TEXT($AI42,"MMM-YY")),"") -> Feb-25 | BF42: =IFERROR(IF($AM42="","",TEXT($AM42,"MMM-YY")),"") -> Feb-25 | BG42: =IFERROR(IF($AS42="","",TEXT($AS42,"MMM-YY")),"") -> Mar-25
A43: =A42+1 -> 42 | B43: 20250681 | C43: Cancelled | D43: Position Cancelled | E43: Sr. Software Eng - Security | F43: Full Stack | G43: Integrated Business Services | H43: Global Monitoring Solutions | I43: Nitin Kudale | J43: External | K43: 45625 | L43: 45625 | M43: 45625 | X43: Pune | Y43: Raisoni, Rushabh | Z43: Raisoni, Rushabh | AA43: 21 Feb - Cancelled on 21st Feb by Business | AT43: =IFERROR(SUM(IF(AND(ISBLANK(T43),ISBLANK(Q43)),0,IF(T43="",TODAY()-Q43,T43-Q43))+IF(AND(ISBLANK(S43),ISBLANK(P43)),0,IF(S43="",TODAY()-P43,S43-P43))+IF(AND(ISBLANK(O43),ISBLANK(R43)),0,IF(R43="",TODAY()-O43,R43-O43))),"") -> 0 | AU43: =IFERROR(IF(($M43=""),"",IF(OR(,$C43="Offer in Progress",$C43="WIP",$C43="WIP/Drop",$C43="WIP/New",$C43="WIP/Hold"),(TODAY()-$M43)-$AT43,"")),"") | AV43: {=IFERROR(_xlfn.IFS($AU43="","",$AU43<=15,"0-15",AND($AU43>=16,$AU43<=30),"16-30",AND($AU43>=31,$AU43<=45),"31-45",AND($AU43>=46,$AU43<=60),"46-60",AND($AU43>=61,$AU43<=90),"61-90",AND($AU43>=91),"> 90",AND($AU43>=2000),""),"")} | AW43: {=IFERROR(_xlfn.IFS(OR($M43="",$AM43=""),"",OR($C43="Offered",$C43="Joined"),($AM43-$M43)-$AT43),"")} | AX43: {=IFERROR(_xlfn.IFS(OR($M43="",$AS43=""),"",$C43="Joined",($AS43-$M43)-$AT43),"")} | AY43: =IFERROR(IF(COUNTIFS('Candidate Tracker'!$E:$E,'Positions Tracker'!$B43,'Candidate Tracker'!$C:$C,"Offer Drop")=0,"",COUNTIFS('Candidate Tracker'!$E:$E,'Positions Tracker'!$B43,'Candidate Tracker'!$C:$C,"Offer Drop")),"") | AZ43: =IFERROR(IF((COUNTIFS('Candidate Tracker'!$D:$D,"<>",'Candidate Tracker'!$D:$D,"<>Screening",'Candidate Tracker'!$D:$D,"<>Screening Pending",'Candidate Tracker'!$D:$D,"<>Candidate Hold",'Candidate Tracker'!$D:$D,"<>Position Cancelled",'Candidate Tracker'!$D:$D,"<>Internal closed")/COUNTIF('Candidate Tracker'!$D:$D,"<>"))=0,"",(COUNTIFS('Candidate Tracker'!$D:$D,"<>",'Candidate Tracker'!$D:$D,"<>Screening",'Candidate Tracker'!$D:$D,"<>Candidate Hold",'Candidate Tracker'!$D:$D,"<>Position Cancelled",'Candidate Tracker'!$D:$D,"<>Internal closed")/COUNTIF('Candidate Tracker'!$D:$D,"<>"))),"") -> 0.88111888 | BA43: =IFERROR(IF(COUNTIFS('Candidate Tracker'!$E:$E,'Positions Tracker'!$B43,'Candidate Tracker'!$I:$I,"Female")=0,"",COUNTIFS('Candidate Tracker'!$E:$E,'Positions Tracker'!$B43,'Candidate Tracker'!$I:$I,"Female")),"") | BB43: =IFERROR(IF(COUNTIFS('Candidate Tracker'!$E:$E,'Positions Tracker'!$B43,'Candidate Tracker'!$I:$I,"male")=0,"",COUNTIFS('Candidate Tracker'!$E:$E,'Positions Tracker'!$B43,'Candidate Tracker'!$I:$I,"male")),"") | BC43: =IFERROR(IF(COUNTIFS('Candidate Tracker'!$E:$E,'Positions Tracker'!$B43,'Candidate Tracker'!$C:$C,"<>WIP",'Candidate Tracker'!$C:$C,"<>Hold",'Candidate Tracker'!$C:$C,"<>Cancelled",'Candidate Tracker'!$C:$C,"<>Closed")/COUNTIFS('Candidate Tracker'!$E:$E,'Positions Tracker'!$B43)=0,"",COUNTIFS('Candidate Tracker'!$E:$E,'Positions Tracker'!$B43,'Candidate Tracker'!$C:$C,"<>WIP",'Candidate Tracker'!$C:$C,"<>Hold",'Candidate Tracker'!$C:$C,"<>Cancelled",'Candidate Tracker'!$C:$C,"<>Closed")/COUNTIFS('Candidate Tracker'!$E:$E,'Positions Tracker'!$B43)),"") | BD43: =IFERROR(IF($M43="","",TEXT($M43,"MMM-YY")),"") -> Nov-24 | BE43: =IFERROR(IF($AI43="","",TEXT($AI43,"MMM-YY")),"") | BF43: =IFERROR(IF($AM43="","",TEXT($AM43,"MMM-YY")),"") | BG43: =IFERROR(IF($AS43="","",TEXT($AS43,"MMM-YY")),"")
A44: =A43+1 -> 43 | B44: 20249490 | C44: Cancelled | D44: Position Cancelled | E44: Sr. Software Eng - Security | F44: Full Stack | G44: Integrated Business Services | H44: Global Monitoring Solutions | I44: Nitin Kudale | J44: External | K44: 45625 | L44: 45625 | M44: 45625 | X44: Pune | Y44: Raisoni, Rushabh | Z44: Raisoni, Rushabh | AA44: 21 Feb - Cancelled on 21st Feb by Business | AT44: =IFERROR(SUM(IF(AND(ISBLANK(T44),ISBLANK(Q44)),0,IF(T44="",TODAY()-Q44,T44-Q44))+IF(AND(ISBLANK(S44),ISBLANK(P44)),0,IF(S44="",TODAY()-P44,S44-P44))+IF(AND(ISBLANK(O44),ISBLANK(R44)),0,IF(R44="",TODAY()-O44,R44-O44))),"") -> 0 | AU44: =IFERROR(IF(($M44=""),"",IF(OR(,$C44="Offer in Progress",$C44="WIP",$C44="WIP/Drop",$C44="WIP/New",$C44="WIP/Hold"),(TODAY()-$M44)-$AT44,"")),"") | AV44: {=IFERROR(_xlfn.IFS($AU44="","",$AU44<=15,"0-15",AND($AU44>=16,$AU44<=30),"16-30",AND($AU44>=31,$AU44<=45),"31-45",AND($AU44>=46,$AU44<=60),"46-60",AND($AU44>=61,$AU44<=90),"61-90",AND($AU44>=91),"> 90",AND($AU44>=2000),""),"")} | AW44: {=IFERROR(_xlfn.IFS(OR($M44="",$AM44=""),"",OR($C44="Offered",$C44="Joined"),($AM44-$M44)-$AT44),"")} | AX44: {=IFERROR(_xlfn.IFS(OR($M44="",$AS44=""),"",$C44="Joined",($AS44-$M44)-$AT44),"")} | AY44: =IFERROR(IF(COUNTIFS('Candidate Tracker'!$E:$E,'Positions Tracker'!$B44,'Candidate Tracker'!$C:$C,"Offer Drop")=0,"",COUNTIFS('Candidate Tracker'!$E:$E,'Positions Tracker'!$B44,'Candidate Tracker'!$C:$C,"Offer Drop")),"") | AZ44: =IFERROR(IF((COUNTIFS('Candidate Tracker'!$D:$D,"<>",'Candidate Tracker'!$D:$D,"<>Screening",'Candidate Tracker'!$D:$D,"<>Screening Pending",'Candidate Tracker'!$D:$D,"<>Candidate Hold",'Candidate Tracker'!$D:$D,"<>Position Cancelled",'Candidate Tracker'!$D:$D,"<>Internal closed")/COUNTIF('Candidate Tracker'!$D:$D,"<>"))=0,"",(COUNTIFS('Candidate Tracker'!$D:$D,"<>",'Candidate Tracker'!$D:$D,"<>Screening",'Candidate Tracker'!$D:$D,"<>Candidate Hold",'Candidate Tracker'!$D:$D,"<>Position Cancelled",'Candidate Tracker'!$D:$D,"<>Internal closed")/COUNTIF('Candidate Tracker'!$D:$D,"<>"))),"") -> 0.88111888 | BA44: =IFERROR(IF(COUNTIFS('Candidate Tracker'!$E:$E,'Positions Tracker'!$B44,'Candidate Tracker'!$I:$I,"Female")=0,"",COUNTIFS('Candidate Tracker'!$E:$E,'Positions Tracker'!$B44,'Candidate Tracker'!$I:$I,"Female")),"") | BB44: =IFERROR(IF(COUNTIFS('Candidate Tracker'!$E:$E,'Positions Tracker'!$B44,'Candidate Tracker'!$I:$I,"male")=0,"",COUNTIFS('Candidate Tracker'!$E:$E,'Positions Tracker'!$B44,'Candidate Tracker'!$I:$I,"male")),"") | BC44: =IFERROR(IF(COUNTIFS('Candidate Tracker'!$E:$E,'Positions Tracker'!$B44,'Candidate Tracker'!$C:$C,"<>WIP",'Candidate Tracker'!$C:$C,"<>Hold",'Candidate Tracker'!$C:$C,"<>Cancelled",'Candidate Tracker'!$C:$C,"<>Closed")/COUNTIFS('Candidate Tracker'!$E:$E,'Positions Tracker'!$B44)=0,"",COUNTIFS('Candidate Tracker'!$E:$E,'Positions Tracker'!$B44,'Candidate Tracker'!$C:$C,"<>WIP",'Candidate Tracker'!$C:$C,"<>Hold",'Candidate Tracker'!$C:$C,"<>Cancelled",'Candidate Tracker'!$C:$C,"<>Closed")/COUNTIFS('Candidate Tracker'!$E:$E,'Positions Tracker'!$B44)),"") | BD44: =IFERROR(IF($M44="","",TEXT($M44,"MMM-YY")),"") -> Nov-24 | BE44: =IFERROR(IF($AI44="","",TEXT($AI44,"MMM-YY")),"") | BF44: =IFERROR(IF($AM44="","",TEXT($AM44,"MMM-YY")),"") | BG44: =IFERROR(IF($AS44="","",TEXT($AS44,"MMM-YY")),"")
A45: =A44+1 -> 44 | B45: 20249317 | C45: Joined | D45: Joined | E45: Pricipal Eng - Electrical | F45: Electrical | G45: Integrated Business Services | H45: SP UPS | I45: Dipak G | J45: External | K45: 45617 | L45: 45617 | M45: 45647 | N45: T13 | X45: Pune | Y45: Bangar, Anuradha | Z45: Bangar, Anuradha | AA45: 3 Mar- Selection: Naveenkumar Marati | AE45: Naveenkumar Marati | AF45: 9291588656 | AG45: naveen0724@gmail.com | AH45: Male | AI45: 45716 | AJ45: 45716 | AK45: Pune | AL45: 4550000 | AM45: 45729 | AN45: 45733 | AP45: 45734 | AQ45: 45734 | AS45: 45859 | AT45: =IFERROR(SUM(IF(AND(ISBLANK(T45),ISBLANK(Q45)),0,IF(T45="",TODAY()-Q45,T45-Q45))+IF(AND(ISBLANK(S45),ISBLANK(P45)),0,IF(S45="",TODAY()-P45,S45-P45))+IF(AND(ISBLANK(O45),ISBLANK(R45)),0,IF(R45="",TODAY()-O45,R45-O45))),"") -> 0 | AU45: =IFERROR(IF(($M45=""),"",IF(OR(,$C45="Offer in Progress",$C45="WIP",$C45="WIP/Drop",$C45="WIP/New",$C45="WIP/Hold"),(TODAY()-$M45)-$AT45,"")),"") | AV45: {=IFERROR(_xlfn.IFS($AU45="","",$AU45<=15,"0-15",AND($AU45>=16,$AU45<=30),"16-30",AND($AU45>=31,$AU45<=45),"31-45",AND($AU45>=46,$AU45<=60),"46-60",AND($AU45>=61,$AU45<=90),"61-90",AND($AU45>=91),"> 90",AND($AU45>=2000),""),"")} | AW45: {=IFERROR(_xlfn.IFS(OR($M45="",$AM45=""),"",OR($C45="Offered",$C45="Joined"),($AM45-$M45)-$AT45),"")} -> 82 | AX45: {=IFERROR(_xlfn.IFS(OR($M45="",$AS45=""),"",$C45="Joined",($AS45-$M45)-$AT45),"")} -> 212 | AY45: =IFERROR(IF(COUNTIFS('Candidate Tracker'!$E:$E,'Positions Tracker'!$B45,'Candidate Tracker'!$C:$C,"Offer Drop")=0,"",COUNTIFS('Candidate Tracker'!$E:$E,'Positions Tracker'!$B45,'Candidate Tracker'!$C:$C,"Offer Drop")),"") | AZ45: =IFERROR(IF((COUNTIFS('Candidate Tracker'!$D:$D,"<>",'Candidate Tracker'!$D:$D,"<>Screening",'Candidate Tracker'!$D:$D,"<>Screening Pending",'Candidate Tracker'!$D:$D,"<>Candidate Hold",'Candidate Tracker'!$D:$D,"<>Position Cancelled",'Candidate Tracker'!$D:$D,"<>Internal closed")/COUNTIF('Candidate Tracker'!$D:$D,"<>"))=0,"",(COUNTIFS('Candidate Tracker'!$D:$D,"<>",'Candidate Tracker'!$D:$D,"<>Screening",'Candidate Tracker'!$D:$D,"<>Candidate Hold",'Candidate Tracker'!$D:$D,"<>Position Cancelled",'Candidate Tracker'!$D:$D,"<>Internal closed")/COUNTIF('Candidate Tracker'!$D:$D,"<>"))),"") -> 0.88111888 | BA45: =IFERROR(IF(COUNTIFS('Candidate Tracker'!$E:$E,'Positions Tracker'!$B45,'Candidate Tracker'!$I:$I,"Female")=0,"",COUNTIFS('Candidate Tracker'!$E:$E,'Positions Tracker'!$B45,'Candidate Tracker'!$I:$I,"Female")),"") | BB45: =IFERROR(IF(COUNTIFS('Candidate Tracker'!$E:$E,'Positions Tracker'!$B45,'Candidate Tracker'!$I:$I,"male")=0,"",COUNTIFS('Candidate Tracker'!$E:$E,'Positions Tracker'!$B45,'Candidate Tracker'!$I:$I,"male")),"") -> 16 | BC45: =IFERROR(IF(COUNTIFS('Candidate Tracker'!$E:$E,'Positions Tracker'!$B45,'Candidate Tracker'!$C:$C,"<>WIP",'Candidate Tracker'!$C:$C,"<>Hold",'Candidate Tracker'!$C:$C,"<>Cancelled",'Candidate Tracker'!$C:$C,"<>Closed")/COUNTIFS('Candidate Tracker'!$E:$E,'Positions Tracker'!$B45)=0,"",COUNTIFS('Candidate Tracker'!$E:$E,'Positions Tracker'!$B45,'Candidate Tracker'!$C:$C,"<>WIP",'Candidate Tracker'!$C:$C,"<>Hold",'Candidate Tracker'!$C:$C,"<>Cancelled",'Candidate Tracker'!$C:$C,"<>Closed")/COUNTIFS('Candidate Tracker'!$E:$E,'Positions Tracker'!$B45)),"") -> 0.0625 | BD45: =IFERROR(IF($M45="","",TEXT($M45,"MMM-YY")),"") -> Dec-24 | BE45: =IFERROR(IF($AI45="","",TEXT($AI45,"MMM-YY")),"") -> Feb-25 | BF45: =IFERROR(IF($AM45="","",TEXT($AM45,"MMM-YY")),"") -> Mar-25 | BG45: =IFERROR(IF($AS45="","",TEXT($AS45,"MMM-YY")),"") -> Jul-25
A46: =A45+1 -> 45 | B46: 20247894 | C46: Joined | D46: Joined | E46: Sr. Engineer Mechanical - RPDU | F46: Mechanical | G46: Integrated Business Services | H46: RPDU | I46: Kevin Ferguson | J46: External | K46: 45639 | L46: 45639 | M46: 45639 | N46: T11 | X46: Pune | Y46: Raisoni, Rushabh | Z46: Raisoni, Rushabh | AA46: Selection - Jafer Babude | AE46: Jafer Babude | AF46: 9130420354 | AG46: jaferbabude54@gmail.com | AH46: Male | AI46: 45684 | AJ46: 45689 | AK46: Pune | AL46: 1650000 | AM46: 45689 | AN46: 45689 | AP46: 45693 | AQ46: 45693 | AS46: 45768 | AT46: =IFERROR(SUM(IF(AND(ISBLANK(T46),ISBLANK(Q46)),0,IF(T46="",TODAY()-Q46,T46-Q46))+IF(AND(ISBLANK(S46),ISBLANK(P46)),0,IF(S46="",TODAY()-P46,S46-P46))+IF(AND(ISBLANK(O46),ISBLANK(R46)),0,IF(R46="",TODAY()-O46,R46-O46))),"") -> 0 | AU46: =IFERROR(IF(($M46=""),"",IF(OR(,$C46="Offer in Progress",$C46="WIP",$C46="WIP/Drop",$C46="WIP/New",$C46="WIP/Hold"),(TODAY()-$M46)-$AT46,"")),"") | AV46: {=IFERROR(_xlfn.IFS($AU46="","",$AU46<=15,"0-15",AND($AU46>=16,$AU46<=30),"16-30",AND($AU46>=31,$AU46<=45),"31-45",AND($AU46>=46,$AU46<=60),"46-60",AND($AU46>=61,$AU46<=90),"61-90",AND($AU46>=91),"> 90",AND($AU46>=2000),""),"")} | AW46: {=IFERROR(_xlfn.IFS(OR($M46="",$AM46=""),"",OR($C46="Offered",$C46="Joined"),($AM46-$M46)-$AT46),"")} -> 50 | AX46: {=IFERROR(_xlfn.IFS(OR($M46="",$AS46=""),"",$C46="Joined",($AS46-$M46)-$AT46),"")} -> 129 | AY46: =IFERROR(IF(COUNTIFS('Candidate Tracker'!$E:$E,'Positions Tracker'!$B46,'Candidate Tracker'!$C:$C,"Offer Drop")=0,"",COUNTIFS('Candidate Tracker'!$E:$E,'Positions Tracker'!$B46,'Candidate Tracker'!$C:$C,"Offer Drop")),"") | AZ46: =IFERROR(IF((COUNTIFS('Candidate Tracker'!$D:$D,"<>",'Candidate Tracker'!$D:$D,"<>Screening",'Candidate Tracker'!$D:$D,"<>Screening Pending",'Candidate Tracker'!$D:$D,"<>Candidate Hold",'Candidate Tracker'!$D:$D,"<>Position Cancelled",'Candidate Tracker'!$D:$D,"<>Internal closed")/COUNTIF('Candidate Tracker'!$D:$D,"<>"))=0,"",(COUNTIFS('Candidate Tracker'!$D:$D,"<>",'Candidate Tracker'!$D:$D,"<>Screening",'Candidate Tracker'!$D:$D,"<>Candidate Hold",'Candidate Tracker'!$D:$D,"<>Position Cancelled",'Candidate Tracker'!$D:$D,"<>Internal closed")/COUNTIF('Candidate Tracker'!$D:$D,"<>"))),"") -> 0.88111888 | BA46: =IFERROR(IF(COUNTIFS('Candidate Tracker'!$E:$E,'Positions Tracker'!$B46,'Candidate Tracker'!$I:$I,"Female")=0,"",COUNTIFS('Candidate Tracker'!$E:$E,'Positions Tracker'!$B46,'Candidate Tracker'!$I:$I,"Female")),"") | BB46: =IFERROR(IF(COUNTIFS('Candidate Tracker'!$E:$E,'Positions Tracker'!$B46,'Candidate Tracker'!$I:$I,"male")=0,"",COUNTIFS('Candidate Tracker'!$E:$E,'Positions Tracker'!$B46,'Candidate Tracker'!$I:$I,"male")),"") -> 1 | BC46: =IFERROR(IF(COUNTIFS('Candidate Tracker'!$E:$E,'Positions Tracker'!$B46,'Candidate Tracker'!$C:$C,"<>WIP",'Candidate Tracker'!$C:$C,"<>Hold",'Candidate Tracker'!$C:$C,"<>Cancelled",'Candidate Tracker'!$C:$C,"<>Closed")/COUNTIFS('Candidate Tracker'!$E:$E,'Positions Tracker'!$B46)=0,"",COUNTIFS('Candidate Tracker'!$E:$E,'Positions Tracker'!$B46,'Candidate Tracker'!$C:$C,"<>WIP",'Candidate Tracker'!$C:$C,"<>Hold",'Candidate Tracker'!$C:$C,"<>Cancelled",'Candidate Tracker'!$C:$C,"<>Closed")/COUNTIFS('Candidate Tracker'!$E:$E,'Positions Tracker'!$B46)),"") -> 1 | BD46: =IFERROR(IF($M46="","",TEXT($M46,"MMM-YY")),"") -> Dec-24 | BE46: =IFERROR(IF($AI46="","",TEXT($AI46,"MMM-YY")),"") -> Jan-25 | BF46: =IFERROR(IF($AM46="","",TEXT($AM46,"MMM-YY")),"") -> Feb-25 | BG46: =IFERROR(IF($AS46="","",TEXT($AS46,"MMM-YY")),"") -> Apr-25
A47: =A46+1 -> 46 | B47: 20247973 | C47: Cancelled | D47: Position Cancelled | E47: Sr. Engineer Mechanical - RPDU | F47: Mechanical | G47: Integrated Business Services | H47: RPDU | I47: Kevin Ferguson | J47: External | K47: 45639 | L47: 45639 | M47: 45639 | N47: T11 | X47: Pune | Y47: Bangar, Anuradha | Z47: Bangar, Anuradha | AA47: Selection - Ronak Kadam | AE47: Ronak Kadam | AF47: 8488997632 | AG47: kadamronak10@gmail.com | AH47: Male | AI47: 45677 | AJ47: 45686 | AK47: Pune | AL47: 1850000 | AM47: 45686 | AN47: 45686 | AP47: 45690 | AQ47: 45690 | AS47: 45782 | AT47: =IFERROR(SUM(IF(AND(ISBLANK(T47),ISBLANK(Q47)),0,IF(T47="",TODAY()-Q47,T47-Q47))+IF(AND(ISBLANK(S47),ISBLANK(P47)),0,IF(S47="",TODAY()-P47,S47-P47))+IF(AND(ISBLANK(O47),ISBLANK(R47)),0,IF(R47="",TODAY()-O47,R47-O47))),"") -> 0 | AU47: =IFERROR(IF(($M47=""),"",IF(OR(,$C47="Offer in Progress",$C47="WIP",$C47="WIP/Drop",$C47="WIP/New",$C47="WIP/Hold"),(TODAY()-$M47)-$AT47,"")),"") | AV47: {=IFERROR(_xlfn.IFS($AU47="","",$AU47<=15,"0-15",AND($AU47>=16,$AU47<=30),"16-30",AND($AU47>=31,$AU47<=45),"31-45",AND($AU47>=46,$AU47<=60),"46-60",AND($AU47>=61,$AU47<=90),"61-90",AND($AU47>=91),"> 90",AND($AU47>=2000),""),"")} | AW47: {=IFERROR(_xlfn.IFS(OR($M47="",$AM47=""),"",OR($C47="Offered",$C47="Joined"),($AM47-$M47)-$AT47),"")} | AX47: {=IFERROR(_xlfn.IFS(OR($M47="",$AS47=""),"",$C47="Joined",($AS47-$M47)-$AT47),"")} | AY47: =IFERROR(IF(COUNTIFS('Candidate Tracker'!$E:$E,'Positions Tracker'!$B47,'Candidate Tracker'!$C:$C,"Offer Drop")=0,"",COUNTIFS('Candidate Tracker'!$E:$E,'Positions Tracker'!$B47,'Candidate Tracker'!$C:$C,"Offer Drop")),"") | AZ47: =IFERROR(IF((COUNTIFS('Candidate Tracker'!$D:$D,"<>",'Candidate Tracker'!$D:$D,"<>Screening",'Candidate Tracker'!$D:$D,"<>Screening Pending",'Candidate Tracker'!$D:$D,"<>Candidate Hold",'Candidate Tracker'!$D:$D,"<>Position Cancelled",'Candidate Tracker'!$D:$D,"<>Internal closed")/COUNTIF('Candidate Tracker'!$D:$D,"<>"))=0,"",(COUNTIFS('Candidate Tracker'!$D:$D,"<>",'Candidate Tracker'!$D:$D,"<>Screening",'Candidate Tracker'!$D:$D,"<>Candidate Hold",'Candidate Tracker'!$D:$D,"<>Position Cancelled",'Candidate Tracker'!$D:$D,"<>Internal closed")/COUNTIF('Candidate Tracker'!$D:$D,"<>"))),"") -> 0.88111888 | BA47: =IFERROR(IF(COUNTIFS('Candidate Tracker'!$E:$E,'Positions Tracker'!$B47,'Candidate Tracker'!$I:$I,"Female")=0,"",COUNTIFS('Candidate Tracker'!$E:$E,'Positions Tracker'!$B47,'Candidate Tracker'!$I:$I,"Female")),"") | BB47: =IFERROR(IF(COUNTIFS('Candidate Tracker'!$E:$E,'Positions Tracker'!$B47,'Candidate Tracker'!$I:$I,"male")=0,"",COUNTIFS('Candidate Tracker'!$E:$E,'Positions Tracker'!$B47,'Candidate Tracker'!$I:$I,"male")),"") -> 4 | BC47: =IFERROR(IF(COUNTIFS('Candidate Tracker'!$E:$E,'Positions Tracker'!$B47,'Candidate Tracker'!$C:$C,"<>WIP",'Candidate Tracker'!$C:$C,"<>Hold",'Candidate Tracker'!$C:$C,"<>Cancelled",'Candidate Tracker'!$C:$C,"<>Closed")/COUNTIFS('Candidate Tracker'!$E:$E,'Positions Tracker'!$B47)=0,"",COUNTIFS('Candidate Tracker'!$E:$E,'Positions Tracker'!$B47,'Candidate Tracker'!$C:$C,"<>WIP",'Candidate Tracker'!$C:$C,"<>Hold",'Candidate Tracker'!$C:$C,"<>Cancelled",'Candidate Tracker'!$C:$C,"<>Closed")/COUNTIFS('Candidate Tracker'!$E:$E,'Positions Tracker'!$B47)),"") -> 0.25 | BD47: =IFERROR(IF($M47="","",TEXT($M47,"MMM-YY")),"") -> Dec-24 | BE47: =IFERROR(IF($AI47="","",TEXT($AI47,"MMM-YY")),"") -> Jan-25 | BF47: =IFERROR(IF($AM47="","",TEXT($AM47,"MMM-YY")),"") -> Jan-25 | BG47: =IFERROR(IF($AS47="","",TEXT($AS47,"MMM-YY")),"") -> May-25
A48: =A47+1 -> 47 | B48: 20247804 | C48: Joined | D48: Joined | E48: Sr. Engineer Mechanical - RPDU | F48: Mechanical | G48: Integrated Business Services | H48: RPDU | I48: Kevin Ferguson | J48: External | K48: 45639 | L48: 45639 | M48: 45639 | N48: T11 | X48: Pune | Y48: Raisoni, Rushabh | Z48: Raisoni, Rushabh | AA48: Selection - Nishant Singh | AE48: Nishant Singh | AF48: 7000553986 | AG48: nishantsinghsirt@gmail.com | AH48: Male | AI48: 45687 | AJ48: 45698 | AK48: Pune | AL48: 1800000 | AM48: 45698 | AN48: 45698 | AP48: 45701 | AQ48: 45701 | AS48: 45796 | AT48: =IFERROR(SUM(IF(AND(ISBLANK(T48),ISBLANK(Q48)),0,IF(T48="",TODAY()-Q48,T48-Q48))+IF(AND(ISBLANK(S48),ISBLANK(P48)),0,IF(S48="",TODAY()-P48,S48-P48))+IF(AND(ISBLANK(O48),ISBLANK(R48)),0,IF(R48="",TODAY()-O48,R48-O48))),"") -> 0 | AU48: =IFERROR(IF(($M48=""),"",IF(OR(,$C48="Offer in Progress",$C48="WIP",$C48="WIP/Drop",$C48="WIP/New",$C48="WIP/Hold"),(TODAY()-$M48)-$AT48,"")),"") | AV48: {=IFERROR(_xlfn.IFS($AU48="","",$AU48<=15,"0-15",AND($AU48>=16,$AU48<=30),"16-30",AND($AU48>=31,$AU48<=45),"31-45",AND($AU48>=46,$AU48<=60),"46-60",AND($AU48>=61,$AU48<=90),"61-90",AND($AU48>=91),"> 90",AND($AU48>=2000),""),"")} | AW48: {=IFERROR(_xlfn.IFS(OR($M48="",$AM48=""),"",OR($C48="Offered",$C48="Joined"),($AM48-$M48)-$AT48),"")} -> 59 | AX48: {=IFERROR(_xlfn.IFS(OR($M48="",$AS48=""),"",$C48="Joined",($AS48-$M48)-$AT48),"")} -> 157 | AY48: =IFERROR(IF(COUNTIFS('Candidate Tracker'!$E:$E,'Positions Tracker'!$B48,'Candidate Tracker'!$C:$C,"Offer Drop")=0,"",COUNTIFS('Candidate Tracker'!$E:$E,'Positions Tracker'!$B48,'Candidate Tracker'!$C:$C,"Offer Drop")),"") | AZ48: =IFERROR(IF((COUNTIFS('Candidate Tracker'!$D:$D,"<>",'Candidate Tracker'!$D:$D,"<>Screening",'Candidate Tracker'!$D:$D,"<>Screening Pending",'Candidate Tracker'!$D:$D,"<>Candidate Hold",'Candidate Tracker'!$D:$D,"<>Position Cancelled",'Candidate Tracker'!$D:$D,"<>Internal closed")/COUNTIF('Candidate Tracker'!$D:$D,"<>"))=0,"",(COUNTIFS('Candidate Tracker'!$D:$D,"<>",'Candidate Tracker'!$D:$D,"<>Screening",'Candidate Tracker'!$D:$D,"<>Candidate Hold",'Candidate Tracker'!$D:$D,"<>Position Cancelled",'Candidate Tracker'!$D:$D,"<>Internal closed")/COUNTIF('Candidate Tracker'!$D:$D,"<>"))),"") -> 0.88111888 | BA48: =IFERROR(IF(COUNTIFS('Candidate Tracker'!$E:$E,'Positions Tracker'!$B48,'Candidate Tracker'!$I:$I,"Female")=0,"",COUNTIFS('Candidate Tracker'!$E:$E,'Positions Tracker'!$B48,'Candidate Tracker'!$I:$I,"Female")),"") | BB48: =IFERROR(IF(COUNTIFS('Candidate Tracker'!$E:$E,'Positions Tracker'!$B48,'Candidate Tracker'!$I:$I,"male")=0,"",COUNTIFS('Candidate Tracker'!$E:$E,'Positions Tracker'!$B48,'Candidate Tracker'!$I:$I,"male")),"") -> 4 | BC48: =IFERROR(IF(COUNTIFS('Candidate Tracker'!$E:$E,'Positions Tracker'!$B48,'Candidate Tracker'!$C:$C,"<>WIP",'Candidate Tracker'!$C:$C,"<>Hold",'Candidate Tracker'!$C:$C,"<>Cancelled",'Candidate Tracker'!$C:$C,"<>Closed")/COUNTIFS('Candidate Tracker'!$E:$E,'Positions Tracker'!$B48)=0,"",COUNTIFS('Candidate Tracker'!$E:$E,'Positions Tracker'!$B48,'Candidate Tracker'!$C:$C,"<>WIP",'Candidate Tracker'!$C:$C,"<>Hold",'Candidate Tracker'!$C:$C,"<>Cancelled",'Candidate Tracker'!$C:$C,"<>Closed")/COUNTIFS('Candidate Tracker'!$E:$E,'Positions Tracker'!$B48)),"") -> 0.25 | BD48: =IFERROR(IF($M48="","",TEXT($M48,"MMM-YY")),"") -> Dec-24 | BE48: =IFERROR(IF($AI48="","",TEXT($AI48,"MMM-YY")),"") -> Jan-25 | BF48: =IFERROR(IF($AM48="","",TEXT($AM48,"MMM-YY")),"") -> Feb-25 | BG48: =IFERROR(IF($AS48="","",TEXT($AS48,"MMM-YY")),"") -> May-25
A49: =A48+1 -> 48 | B49: 20251843 | C49: Joined | D49: Joined | E49: Sr. Test Engineer | F49: Sr. Test Engineer - Electrical | G49: Integrated Business Services | H49: SP UPS | I49: Rahul Dhende | J49: External | K49: 45637 | L49: 45637 | M49: 45637 | N49: T10 | X49: Pune | Y49: Raisoni, Rushabh | Z49: Raisoni, Rushabh | AA49: Selection - Atul Mhaske | AE49: Atul Mhaske | AF49: 8669030508 | AG49: atulmhaske.mhaske3@gmail.com | AH49: Male | AI49: 45670 | AJ49: 45673 | AK49: Pune | AL49: 1250000 | AM49: 45673 | AN49: 45673 | AP49: 45674 | AQ49: 45674 | AS49: 45768 | AT49: =IFERROR(SUM(IF(AND(ISBLANK(T49),ISBLANK(Q49)),0,IF(T49="",TODAY()-Q49,T49-Q49))+IF(AND(ISBLANK(S49),ISBLANK(P49)),0,IF(S49="",TODAY()-P49,S49-P49))+IF(AND(ISBLANK(O49),ISBLANK(R49)),0,IF(R49="",TODAY()-O49,R49-O49))),"") -> 0 | AU49: =IFERROR(IF(($M49=""),"",IF(OR(,$C49="Offer in Progress",$C49="WIP",$C49="WIP/Drop",$C49="WIP/New",$C49="WIP/Hold"),(TODAY()-$M49)-$AT49,"")),"") | AV49: {=IFERROR(_xlfn.IFS($AU49="","",$AU49<=15,"0-15",AND($AU49>=16,$AU49<=30),"16-30",AND($AU49>=31,$AU49<=45),"31-45",AND($AU49>=46,$AU49<=60),"46-60",AND($AU49>=61,$AU49<=90),"61-90",AND($AU49>=91),"> 90",AND($AU49>=2000),""),"")} | AW49: {=IFERROR(_xlfn.IFS(OR($M49="",$AM49=""),"",OR($C49="Offered",$C49="Joined"),($AM49-$M49)-$AT49),"")} -> 36 | AX49: {=IFERROR(_xlfn.IFS(OR($M49="",$AS49=""),"",$C49="Joined",($AS49-$M49)-$AT49),"")} -> 131 | AY49: =IFERROR(IF(COUNTIFS('Candidate Tracker'!$E:$E,'Positions Tracker'!$B49,'Candidate Tracker'!$C:$C,"Offer Drop")=0,"",COUNTIFS('Candidate Tracker'!$E:$E,'Positions Tracker'!$B49,'Candidate Tracker'!$C:$C,"Offer Drop")),"") | AZ49: =IFERROR(IF((COUNTIFS('Candidate Tracker'!$D:$D,"<>",'Candidate Tracker'!$D:$D,"<>Screening",'Candidate Tracker'!$D:$D,"<>Screening Pending",'Candidate Tracker'!$D:$D,"<>Candidate Hold",'Candidate Tracker'!$D:$D,"<>Position Cancelled",'Candidate Tracker'!$D:$D,"<>Internal closed")/COUNTIF('Candidate Tracker'!$D:$D,"<>"))=0,"",(COUNTIFS('Candidate Tracker'!$D:$D,"<>",'Candidate Tracker'!$D:$D,"<>Screening",'Candidate Tracker'!$D:$D,"<>Candidate Hold",'Candidate Tracker'!$D:$D,"<>Position Cancelled",'Candidate Tracker'!$D:$D,"<>Internal closed")/COUNTIF('Candidate Tracker'!$D:$D,"<>"))),"") -> 0.88111888 | BA49: =IFERROR(IF(COUNTIFS('Candidate Tracker'!$E:$E,'Positions Tracker'!$B49,'Candidate Tracker'!$I:$I,"Female")=0,"",COUNTIFS('Candidate Tracker'!$E:$E,'Positions Tracker'!$B49,'Candidate Tracker'!$I:$I,"Female")),"") | BB49: =IFERROR(IF(COUNTIFS('Candidate Tracker'!$E:$E,'Positions Tracker'!$B49,'Candidate Tracker'!$I:$I,"male")=0,"",COUNTIFS('Candidate Tracker'!$E:$E,'Positions Tracker'!$B49,'Candidate Tracker'!$I:$I,"male")),"") -> 8 | BC49: =IFERROR(IF(COUNTIFS('Candidate Tracker'!$E:$E,'Positions Tracker'!$B49,'Candidate Tracker'!$C:$C,"<>WIP",'Candidate Tracker'!$C:$C,"<>Hold",'Candidate Tracker'!$C:$C,"<>Cancelled",'Candidate Tracker'!$C:$C,"<>Closed")/COUNTIFS('Candidate Tracker'!$E:$E,'Positions Tracker'!$B49)=0,"",COUNTIFS('Candidate Tracker'!$E:$E,'Positions Tracker'!$B49,'Candidate Tracker'!$C:$C,"<>WIP",'Candidate Tracker'!$C:$C,"<>Hold",'Candidate Tracker'!$C:$C,"<>Cancelled",'Candidate Tracker'!$C:$C,"<>Closed")/COUNTIFS('Candidate Tracker'!$E:$E,'Positions Tracker'!$B49)),"") -> 0.125 | BD49: =IFERROR(IF($M49="","",TEXT($M49,"MMM-YY")),"") -> Dec-24 | BE49: =IFERROR(IF($AI49="","",TEXT($AI49,"MMM-YY")),"") -> Jan-25 | BF49: =IFERROR(IF($AM49="","",TEXT($AM49,"MMM-YY")),"") -> Jan-25 | BG49: =IFERROR(IF($AS49="","",TEXT($AS49,"MMM-YY")),"") -> Apr-25
A50: =A49+1 -> 49 | B50: 20251215 | C50: Joined | D50: Joined | E50: Associate Engineer - Structural | F50: Reliability | G50: Integrated Business Services | H50: Core Engineering | I50: Dasa K | J50: External | K50: 45644 | L50: 45644 | M50: 45664 | N50: T8 | X50: Pune | Y50: Raisoni, Rushabh | Z50: Raisoni, Rushabh | AA50: Selection - Rohit Kamble | AE50: Rohit Kamble | AF50: 8329844440 | AG50: rohitskamble111@gmail.com | AH50: Male | AI50: 45691 | AJ50: 45702 | AK50: Pune | AL50: 820000 | AM50: 45702 | AN50: 45702 | AP50: 45704 | AQ50: 45704 | AS50: 45789 | AT50: =IFERROR(SUM(IF(AND(ISBLANK(T50),ISBLANK(Q50)),0,IF(T50="",TODAY()-Q50,T50-Q50))+IF(AND(ISBLANK(S50),ISBLANK(P50)),0,IF(S50="",TODAY()-P50,S50-P50))+IF(AND(ISBLANK(O50),ISBLANK(R50)),0,IF(R50="",TODAY()-O50,R50-O50))),"") -> 0 | AU50: =IFERROR(IF(($M50=""),"",IF(OR(,$C50="Offer in Progress",$C50="WIP",$C50="WIP/Drop",$C50="WIP/New",$C50="WIP/Hold"),(TODAY()-$M50)-$AT50,"")),"") | AV50: {=IFERROR(_xlfn.IFS($AU50="","",$AU50<=15,"0-15",AND($AU50>=16,$AU50<=30),"16-30",AND($AU50>=31,$AU50<=45),"31-45",AND($AU50>=46,$AU50<=60),"46-60",AND($AU50>=61,$AU50<=90),"61-90",AND($AU50>=91),"> 90",AND($AU50>=2000),""),"")} | AW50: {=IFERROR(_xlfn.IFS(OR($M50="",$AM50=""),"",OR($C50="Offered",$C50="Joined"),($AM50-$M50)-$AT50),"")} -> 38 | AX50: {=IFERROR(_xlfn.IFS(OR($M50="",$AS50=""),"",$C50="Joined",($AS50-$M50)-$AT50),"")} -> 125 | AY50: =IFERROR(IF(COUNTIFS('Candidate Tracker'!$E:$E,'Positions Tracker'!$B50,'Candidate Tracker'!$C:$C,"Offer Drop")=0,"",COUNTIFS('Candidate Tracker'!$E:$E,'Positions Tracker'!$B50,'Candidate Tracker'!$C:$C,"Offer Drop")),"") | AZ50: =IFERROR(IF((COUNTIFS('Candidate Tracker'!$D:$D,"<>",'Candidate Tracker'!$D:$D,"<>Screening",'Candidate Tracker'!$D:$D,"<>Screening Pending",'Candidate Tracker'!$D:$D,"<>Candidate Hold",'Candidate Tracker'!$D:$D,"<>Position Cancelled",'Candidate Tracker'!$D:$D,"<>Internal closed")/COUNTIF('Candidate Tracker'!$D:$D,"<>"))=0,"",(COUNTIFS('Candidate Tracker'!$D:$D,"<>",'Candidate Tracker'!$D:$D,"<>Screening",'Candidate Tracker'!$D:$D,"<>Candidate Hold",'Candidate Tracker'!$D:$D,"<>Position Cancelled",'Candidate Tracker'!$D:$D,"<>Internal closed")/COUNTIF('Candidate Tracker'!$D:$D,"<>"))),"") -> 0.88111888 | BA50: =IFERROR(IF(COUNTIFS('Candidate Tracker'!$E:$E,'Positions Tracker'!$B50,'Candidate Tracker'!$I:$I,"Female")=0,"",COUNTIFS('Candidate Tracker'!$E:$E,'Positions Tracker'!$B50,'Candidate Tracker'!$I:$I,"Female")),"") | BB50: =IFERROR(IF(COUNTIFS('Candidate Tracker'!$E:$E,'Positions Tracker'!$B50,'Candidate Tracker'!$I:$I,"male")=0,"",COUNTIFS('Candidate Tracker'!$E:$E,'Positions Tracker'!$B50,'Candidate Tracker'!$I:$I,"male")),"") -> 16 | BC50: =IFERROR(IF(COUNTIFS('Candidate Tracker'!$E:$E,'Positions Tracker'!$B50,'Candidate Tracker'!$C:$C,"<>WIP",'Candidate Tracker'!$C:$C,"<>Hold",'Candidate Tracker'!$C:$C,"<>Cancelled",'Candidate Tracker'!$C:$C,"<>Closed")/COUNTIFS('Candidate Tracker'!$E:$E,'Positions Tracker'!$B50)=0,"",COUNTIFS('Candidate Tracker'!$E:$E,'Positions Tracker'!$B50,'Candidate Tracker'!$C:$C,"<>WIP",'Candidate Tracker'!$C:$C,"<>Hold",'Candidate Tracker'!$C:$C,"<>Cancelled",'Candidate Tracker'!$C:$C,"<>Closed")/COUNTIFS('Candidate Tracker'!$E:$E,'Positions Tracker'!$B50)),"") -> 0.125 | BD50: =IFERROR(IF($M50="","",TEXT($M50,"MMM-YY")),"") -> Jan-25 | BE50: =IFERROR(IF($AI50="","",TEXT($AI50,"MMM-YY")),"") -> Feb-25 | BF50: =IFERROR(IF($AM50="","",TEXT($AM50,"MMM-YY")),"") -> Feb-25 | BG50: =IFERROR(IF($AS50="","",TEXT($AS50,"MMM-YY")),"") -> May-25
A51: =A50+1 -> 50 | B51: 20252712 | C51: Joined | D51: Joined | E51: Engineer - Reliability | F51: Reliability | G51: Integrated Business Services | H51: Core Engineering | I51: Dasa K | J51: External | K51: 45644 | L51: 45644 | M51: 45664 | N51: T9 | X51: Pune | Y51: Raisoni, Rushabh | Z51: Raisoni, Rushabh | AA51: Selection - Mohseen Momin | AE51: Mohseen Momin | AF51: 7972959010 | AG51: Mohseen.Momin44@gmail.com | AH51: Male | AI51: 45709 | AJ51: 45712 | AK51: Pune | AL51: 1100000 | AM51: 45712 | AN51: 45712 | AP51: 45714 | AQ51: 45714 | AS51: 45775 | AT51: =IFERROR(SUM(IF(AND(ISBLANK(T51),ISBLANK(Q51)),0,IF(T51="",TODAY()-Q51,T51-Q51))+IF(AND(ISBLANK(S51),ISBLANK(P51)),0,IF(S51="",TODAY()-P51,S51-P51))+IF(AND(ISBLANK(O51),ISBLANK(R51)),0,IF(R51="",TODAY()-O51,R51-O51))),"") -> 0 | AU51: =IFERROR(IF(($M51=""),"",IF(OR(,$C51="Offer in Progress",$C51="WIP",$C51="WIP/Drop",$C51="WIP/New",$C51="WIP/Hold"),(TODAY()-$M51)-$AT51,"")),"") | AV51: {=IFERROR(_xlfn.IFS($AU51="","",$AU51<=15,"0-15",AND($AU51>=16,$AU51<=30),"16-30",AND($AU51>=31,$AU51<=45),"31-45",AND($AU51>=46,$AU51<=60),"46-60",AND($AU51>=61,$AU51<=90),"61-90",AND($AU51>=91),"> 90",AND($AU51>=2000),""),"")} | AW51: {=IFERROR(_xlfn.IFS(OR($M51="",$AM51=""),"",OR($C51="Offered",$C51="Joined"),($AM51-$M51)-$AT51),"")} -> 48 | AX51: {=IFERROR(_xlfn.IFS(OR($M51="",$AS51=""),"",$C51="Joined",($AS51-$M51)-$AT51),"")} -> 111 | AY51: =IFERROR(IF(COUNTIFS('Candidate Tracker'!$E:$E,'Positions Tracker'!$B51,'Candidate Tracker'!$C:$C,"Offer Drop")=0,"",COUNTIFS('Candidate Tracker'!$E:$E,'Positions Tracker'!$B51,'Candidate Tracker'!$C:$C,"Offer Drop")),"") | AZ51: =IFERROR(IF((COUNTIFS('Candidate Tracker'!$D:$D,"<>",'Candidate Tracker'!$D:$D,"<>Screening",'Candidate Tracker'!$D:$D,"<>Screening Pending",'Candidate Tracker'!$D:$D,"<>Candidate Hold",'Candidate Tracker'!$D:$D,"<>Position Cancelled",'Candidate Tracker'!$D:$D,"<>Internal closed")/COUNTIF('Candidate Tracker'!$D:$D,"<>"))=0,"",(COUNTIFS('Candidate Tracker'!$D:$D,"<>",'Candidate Tracker'!$D:$D,"<>Screening",'Candidate Tracker'!$D:$D,"<>Candidate Hold",'Candidate Tracker'!$D:$D,"<>Position Cancelled",'Candidate Tracker'!$D:$D,"<>Internal closed")/COUNTIF('Candidate Tracker'!$D:$D,"<>"))),"") -> 0.88111888 | BA51: =IFERROR(IF(COUNTIFS('Candidate Tracker'!$E:$E,'Positions Tracker'!$B51,'Candidate Tracker'!$I:$I,"Female")=0,"",COUNTIFS('Candidate Tracker'!$E:$E,'Positions Tracker'!$B51,'Candidate Tracker'!$I:$I,"Female")),"") | BB51: =IFERROR(IF(COUNTIFS('Candidate Tracker'!$E:$E,'Positions Tracker'!$B51,'Candidate Tracker'!$I:$I,"male")=0,"",COUNTIFS('Candidate Tracker'!$E:$E,'Positions Tracker'!$B51,'Candidate Tracker'!$I:$I,"male")),"") | BC51: =IFERROR(IF(COUNTIFS('Candidate Tracker'!$E:$E,'Positions Tracker'!$B51,'Candidate Tracker'!$C:$C,"<>WIP",'Candidate Tracker'!$C:$C,"<>Hold",'Candidate Tracker'!$C:$C,"<>Cancelled",'Candidate Tracker'!$C:$C,"<>Closed")/COUNTIFS('Candidate Tracker'!$E:$E,'Positions Tracker'!$B51)=0,"",COUNTIFS('Candidate Tracker'!$E:$E,'Positions Tracker'!$B51,'Candidate Tracker'!$C:$C,"<>WIP",'Candidate Tracker'!$C:$C,"<>Hold",'Candidate Tracker'!$C:$C,"<>Cancelled",'Candidate Tracker'!$C:$C,"<>Closed")/COUNTIFS('Candidate Tracker'!$E:$E,'Positions Tracker'!$B51)),"") | BD51: =IFERROR(IF($M51="","",TEXT($M51,"MMM-YY")),"") -> Jan-25 | BE51: =IFERROR(IF($AI51="","",TEXT($AI51,"MMM-YY")),"") -> Feb-25 | BF51: =IFERROR(IF($AM51="","",TEXT($AM51,"MMM-YY")),"") -> Feb-25 | BG51: =IFERROR(IF($AS51="","",TEXT($AS51,"MMM-YY")),"") -> Apr-25
A52: =A51+1 -> 51 | B52: 20251210 | C52: Offer Drop | D52: Offer Decline | E52: Sr. Engineer - Structural | F52: Reliability | G52: Integrated Business Services | H52: Core Engineering | I52: Dasa K | J52: External | K52: 45644 | L52: 45644 | M52: 45664 | N52: T10 | X52: Pune | Y52: Raisoni, Rushabh | Z52: Raisoni, Rushabh | AA52: Selection - Mohammed Sohail Shaikh | AE52: Mohammed Sohail Shaikh | AF52: 7406747353 | AG52: mdsohailapr@gmail.com | AH52: Male | AI52: 45680 | AJ52: 45696 | AK52: Pune | AL52: 1300000 | AM52: 45696 | AN52: 45696 | AO52: 45762 | AP52: 45698 | AQ52: 45698 | AS52: 45782 | AT52: =IFERROR(SUM(IF(AND(ISBLANK(T52),ISBLANK(Q52)),0,IF(T52="",TODAY()-Q52,T52-Q52))+IF(AND(ISBLANK(S52),ISBLANK(P52)),0,IF(S52="",TODAY()-P52,S52-P52))+IF(AND(ISBLANK(O52),ISBLANK(R52)),0,IF(R52="",TODAY()-O52,R52-O52))),"") -> 0 | AU52: =IFERROR(IF(($M52=""),"",IF(OR(,$C52="Offer in Progress",$C52="WIP",$C52="WIP/Drop",$C52="WIP/New",$C52="WIP/Hold"),(TODAY()-$M52)-$AT52,"")),"") | AV52: {=IFERROR(_xlfn.IFS($AU52="","",$AU52<=15,"0-15",AND($AU52>=16,$AU52<=30),"16-30",AND($AU52>=31,$AU52<=45),"31-45",AND($AU52>=46,$AU52<=60),"46-60",AND($AU52>=61,$AU52<=90),"61-90",AND($AU52>=91),"> 90",AND($AU52>=2000),""),"")} | AW52: {=IFERROR(_xlfn.IFS(OR($M52="",$AM52=""),"",OR($C52="Offered",$C52="Joined"),($AM52-$M52)-$AT52),"")} | AX52: {=IFERROR(_xlfn.IFS(OR($M52="",$AS52=""),"",$C52="Joined",($AS52-$M52)-$AT52),"")} | AY52: =IFERROR(IF(COUNTIFS('Candidate Tracker'!$E:$E,'Positions Tracker'!$B52,'Candidate Tracker'!$C:$C,"Offer Drop")=0,"",COUNTIFS('Candidate Tracker'!$E:$E,'Positions Tracker'!$B52,'Candidate Tracker'!$C:$C,"Offer Drop")),"") -> 1 | AZ52: =IFERROR(IF((COUNTIFS('Candidate Tracker'!$D:$D,"<>",'Candidate Tracker'!$D:$D,"<>Screening",'Candidate Tracker'!$D:$D,"<>Screening Pending",'Candidate Tracker'!$D:$D,"<>Candidate Hold",'Candidate Tracker'!$D:$D,"<>Position Cancelled",'Candidate Tracker'!$D:$D,"<>Internal closed")/COUNTIF('Candidate Tracker'!$D:$D,"<>"))=0,"",(COUNTIFS('Candidate Tracker'!$D:$D,"<>",'Candidate Tracker'!$D:$D,"<>Screening",'Candidate Tracker'!$D:$D,"<>Candidate Hold",'Candidate Tracker'!$D:$D,"<>Position Cancelled",'Candidate Tracker'!$D:$D,"<>Internal closed")/COUNTIF('Candidate Tracker'!$D:$D,"<>"))),"") -> 0.88111888 | BA52: =IFERROR(IF(COUNTIFS('Candidate Tracker'!$E:$E,'Positions Tracker'!$B52,'Candidate Tracker'!$I:$I,"Female")=0,"",COUNTIFS('Candidate Tracker'!$E:$E,'Positions Tracker'!$B52,'Candidate Tracker'!$I:$I,"Female")),"") | BB52: =IFERROR(IF(COUNTIFS('Candidate Tracker'!$E:$E,'Positions Tracker'!$B52,'Candidate Tracker'!$I:$I,"male")=0,"",COUNTIFS('Candidate Tracker'!$E:$E,'Positions Tracker'!$B52,'Candidate Tracker'!$I:$I,"male")),"") -> 4 | BC52: =IFERROR(IF(COUNTIFS('Candidate Tracker'!$E:$E,'Positions Tracker'!$B52,'Candidate Tracker'!$C:$C,"<>WIP",'Candidate Tracker'!$C:$C,"<>Hold",'Candidate Tracker'!$C:$C,"<>Cancelled",'Candidate Tracker'!$C:$C,"<>Closed")/COUNTIFS('Candidate Tracker'!$E:$E,'Positions Tracker'!$B52)=0,"",COUNTIFS('Candidate Tracker'!$E:$E,'Positions Tracker'!$B52,'Candidate Tracker'!$C:$C,"<>WIP",'Candidate Tracker'!$C:$C,"<>Hold",'Candidate Tracker'!$C:$C,"<>Cancelled",'Candidate Tracker'!$C:$C,"<>Closed")/COUNTIFS('Candidate Tracker'!$E:$E,'Positions Tracker'!$B52)),"") -> 0.25 | BD52: =IFERROR(IF($M52="","",TEXT($M52,"MMM-YY")),"") -> Jan-25 | BE52: =IFERROR(IF($AI52="","",TEXT($AI52,"MMM-YY")),"") -> Jan-25 | BF52: =IFERROR(IF($AM52="","",TEXT($AM52,"MMM-YY")),"") -> Feb-25 | BG52: =IFERROR(IF($AS52="","",TEXT($AS52,"MMM-YY")),"") -> May-25
A53: =A52+1 -> 52 | B53: 20251209 | C53: Offer Drop | D53: Offer Decline | E53: Sr. Engineer - Reliability | F53: Reliability | G53: Integrated Business Services | H53: Core Engineering | I53: Dasa K | J53: External | K53: 45644 | L53: 45644 | M53: 45664 | N53: T11 | X53: Pune | Y53: Raisoni, Rushabh | Z53: Raisoni, Rushabh | AA53: Selection - Madivallaya K | AE53: Madivallaya K | AF53: 9503192369 | AG53: Mahesh.k.k.008@gmail.com | AH53: Male | AI53: 45709 | AJ53: 45712 | AK53: Pune | AL53: 1600000 | AM53: 45712 | AN53: 45712 | AO53: 45743 | AP53: 45715 | AQ53: 45715 | AS53: 45803 | AT53: =IFERROR(SUM(IF(AND(ISBLANK(T53),ISBLANK(Q53)),0,IF(T53="",TODAY()-Q53,T53-Q53))+IF(AND(ISBLANK(S53),ISBLANK(P53)),0,IF(S53="",TODAY()-P53,S53-P53))+IF(AND(ISBLANK(O53),ISBLANK(R53)),0,IF(R53="",TODAY()-O53,R53-O53))),"") -> 0 | AU53: =IFERROR(IF(($M53=""),"",IF(OR(,$C53="Offer in Progress",$C53="WIP",$C53="WIP/Drop",$C53="WIP/New",$C53="WIP/Hold"),(TODAY()-$M53)-$AT53,"")),"") | AV53: {=IFERROR(_xlfn.IFS($AU53="","",$AU53<=15,"0-15",AND($AU53>=16,$AU53<=30),"16-30",AND($AU53>=31,$AU53<=45),"31-45",AND($AU53>=46,$AU53<=60),"46-60",AND($AU53>=61,$AU53<=90),"61-90",AND($AU53>=91),"> 90",AND($AU53>=2000),""),"")} | AW53: {=IFERROR(_xlfn.IFS(OR($M53="",$AM53=""),"",OR($C53="Offered",$C53="Joined"),($AM53-$M53)-$AT53),"")} | AX53: {=IFERROR(_xlfn.IFS(OR($M53="",$AS53=""),"",$C53="Joined",($AS53-$M53)-$AT53),"")} | AY53: =IFERROR(IF(COUNTIFS('Candidate Tracker'!$E:$E,'Positions Tracker'!$B53,'Candidate Tracker'!$C:$C,"Offer Drop")=0,"",COUNTIFS('Candidate Tracker'!$E:$E,'Positions Tracker'!$B53,'Candidate Tracker'!$C:$C,"Offer Drop")),"") | AZ53: =IFERROR(IF((COUNTIFS('Candidate Tracker'!$D:$D,"<>",'Candidate Tracker'!$D:$D,"<>Screening",'Candidate Tracker'!$D:$D,"<>Screening Pending",'Candidate Tracker'!$D:$D,"<>Candidate Hold",'Candidate Tracker'!$D:$D,"<>Position Cancelled",'Candidate Tracker'!$D:$D,"<>Internal closed")/COUNTIF('Candidate Tracker'!$D:$D,"<>"))=0,"",(COUNTIFS('Candidate Tracker'!$D:$D,"<>",'Candidate Tracker'!$D:$D,"<>Screening",'Candidate Tracker'!$D:$D,"<>Candidate Hold",'Candidate Tracker'!$D:$D,"<>Position Cancelled",'Candidate Tracker'!$D:$D,"<>Internal closed")/COUNTIF('Candidate Tracker'!$D:$D,"<>"))),"") -> 0.88111888 | BA53: =IFERROR(IF(COUNTIFS('Candidate Tracker'!$E:$E,'Positions Tracker'!$B53,'Candidate Tracker'!$I:$I,"Female")=0,"",COUNTIFS('Candidate Tracker'!$E:$E,'Positions Tracker'!$B53,'Candidate Tracker'!$I:$I,"Female")),"") | BB53: =IFERROR(IF(COUNTIFS('Candidate Tracker'!$E:$E,'Positions Tracker'!$B53,'Candidate Tracker'!$I:$I,"male")=0,"",COUNTIFS('Candidate Tracker'!$E:$E,'Positions Tracker'!$B53,'Candidate Tracker'!$I:$I,"male")),"") -> 6 | BC53: =IFERROR(IF(COUNTIFS('Candidate Tracker'!$E:$E,'Positions Tracker'!$B53,'Candidate Tracker'!$C:$C,"<>WIP",'Candidate Tracker'!$C:$C,"<>Hold",'Candidate Tracker'!$C:$C,"<>Cancelled",'Candidate Tracker'!$C:$C,"<>Closed")/COUNTIFS('Candidate Tracker'!$E:$E,'Positions Tracker'!$B53)=0,"",COUNTIFS('Candidate Tracker'!$E:$E,'Positions Tracker'!$B53,'Candidate Tracker'!$C:$C,"<>WIP",'Candidate Tracker'!$C:$C,"<>Hold",'Candidate Tracker'!$C:$C,"<>Cancelled",'Candidate Tracker'!$C:$C,"<>Closed")/COUNTIFS('Candidate Tracker'!$E:$E,'Positions Tracker'!$B53)),"") -> 0.16666667 | BD53: =IFERROR(IF($M53="","",TEXT($M53,"MMM-YY")),"") -> Jan-25 | BE53: =IFERROR(IF($AI53="","",TEXT($AI53,"MMM-YY")),"") -> Feb-25 | BF53: =IFERROR(IF($AM53="","",TEXT($AM53,"MMM-YY")),"") -> Feb-25 | BG53: =IFERROR(IF($AS53="","",TEXT($AS53,"MMM-YY")),"") -> May-25
A54: =A53+1 -> 53 | B54: 20247717 | C54: Cancelled | D54: Position Cancelled | E54: Sr. Test Engineer | F54: Electrical Testing | G54: Integrated Business Services | H54: SP UPS | I54: Dipak G | J54: External | K54: 45637 | L54: 45637 | M54: 45637 | X54: Pune | Y54: Raisoni, Rushabh | Z54: Raisoni, Rushabh | AA54: 21 Feb - Cancelled on 21st Feb by Business | AT54: =IFERROR(SUM(IF(AND(ISBLANK(T54),ISBLANK(Q54)),0,IF(T54="",TODAY()-Q54,T54-Q54))+IF(AND(ISBLANK(S54),ISBLANK(P54)),0,IF(S54="",TODAY()-P54,S54-P54))+IF(AND(ISBLANK(O54),ISBLANK(R54)),0,IF(R54="",TODAY()-O54,R54-O54))),"") -> 0 | AU54: =IFERROR(IF(($M54=""),"",IF(OR(,$C54="Offer in Progress",$C54="WIP",$C54="WIP/Drop",$C54="WIP/New",$C54="WIP/Hold"),(TODAY()-$M54)-$AT54,"")),"") | AV54: {=IFERROR(_xlfn.IFS($AU54="","",$AU54<=15,"0-15",AND($AU54>=16,$AU54<=30),"16-30",AND($AU54>=31,$AU54<=45),"31-45",AND($AU54>=46,$AU54<=60),"46-60",AND($AU54>=61,$AU54<=90),"61-90",AND($AU54>=91),"> 90",AND($AU54>=2000),""),"")} | AW54: {=IFERROR(_xlfn.IFS(OR($M54="",$AM54=""),"",OR($C54="Offered",$C54="Joined"),($AM54-$M54)-$AT54),"")} | AX54: {=IFERROR(_xlfn.IFS(OR($M54="",$AS54=""),"",$C54="Joined",($AS54-$M54)-$AT54),"")} | AY54: =IFERROR(IF(COUNTIFS('Candidate Tracker'!$E:$E,'Positions Tracker'!$B54,'Candidate Tracker'!$C:$C,"Offer Drop")=0,"",COUNTIFS('Candidate Tracker'!$E:$E,'Positions Tracker'!$B54,'Candidate Tracker'!$C:$C,"Offer Drop")),"") | AZ54: =IFERROR(IF((COUNTIFS('Candidate Tracker'!$D:$D,"<>",'Candidate Tracker'!$D:$D,"<>Screening",'Candidate Tracker'!$D:$D,"<>Screening Pending",'Candidate Tracker'!$D:$D,"<>Candidate Hold",'Candidate Tracker'!$D:$D,"<>Position Cancelled",'Candidate Tracker'!$D:$D,"<>Internal closed")/COUNTIF('Candidate Tracker'!$D:$D,"<>"))=0,"",(COUNTIFS('Candidate Tracker'!$D:$D,"<>",'Candidate Tracker'!$D:$D,"<>Screening",'Candidate Tracker'!$D:$D,"<>Candidate Hold",'Candidate Tracker'!$D:$D,"<>Position Cancelled",'Candidate Tracker'!$D:$D,"<>Internal closed")/COUNTIF('Candidate Tracker'!$D:$D,"<>"))),"") -> 0.88111888 | BA54: =IFERROR(IF(COUNTIFS('Candidate Tracker'!$E:$E,'Positions Tracker'!$B54,'Candidate Tracker'!$I:$I,"Female")=0,"",COUNTIFS('Candidate Tracker'!$E:$E,'Positions Tracker'!$B54,'Candidate Tracker'!$I:$I,"Female")),"") | BB54: =IFERROR(IF(COUNTIFS('Candidate Tracker'!$E:$E,'Positions Tracker'!$B54,'Candidate Tracker'!$I:$I,"male")=0,"",COUNTIFS('Candidate Tracker'!$E:$E,'Positions Tracker'!$B54,'Candidate Tracker'!$I:$I,"male")),"") | BC54: =IFERROR(IF(COUNTIFS('Candidate Tracker'!$E:$E,'Positions Tracker'!$B54,'Candidate Tracker'!$C:$C,"<>WIP",'Candidate Tracker'!$C:$C,"<>Hold",'Candidate Tracker'!$C:$C,"<>Cancelled",'Candidate Tracker'!$C:$C,"<>Closed")/COUNTIFS('Candidate Tracker'!$E:$E,'Positions Tracker'!$B54)=0,"",COUNTIFS('Candidate Tracker'!$E:$E,'Positions Tracker'!$B54,'Candidate Tracker'!$C:$C,"<>WIP",'Candidate Tracker'!$C:$C,"<>Hold",'Candidate Tracker'!$C:$C,"<>Cancelled",'Candidate Tracker'!$C:$C,"<>Closed")/COUNTIFS('Candidate Tracker'!$E:$E,'Positions Tracker'!$B54)),"") | BD54: =IFERROR(IF($M54="","",TEXT($M54,"MMM-YY")),"") -> Dec-24 | BE54: =IFERROR(IF($AI54="","",TEXT($AI54,"MMM-YY")),"") | BF54: =IFERROR(IF($AM54="","",TEXT($AM54,"MMM-YY")),"") | BG54: =IFERROR(IF($AS54="","",TEXT($AS54,"MMM-YY")),"")
A55: =A54+1 -> 54 | B55: 20250682 | C55: Cancelled | D55: Position Cancelled | E55: Sr. Software Eng - Security | F55: Full Stack | G55: Integrated Business Services | H55: Global Monitoring Solutions | I55: Nitin Kudale | J55: External | K55: 45625 | L55: 45625 | M55: 45625 | X55: Pune | Y55: Raisoni, Rushabh | Z55: Raisoni, Rushabh | AA55: 21 Feb - Cancelled on 21st Feb by Business | AT55: =IFERROR(SUM(IF(AND(ISBLANK(T55),ISBLANK(Q55)),0,IF(T55="",TODAY()-Q55,T55-Q55))+IF(AND(ISBLANK(S55),ISBLANK(P55)),0,IF(S55="",TODAY()-P55,S55-P55))+IF(AND(ISBLANK(O55),ISBLANK(R55)),0,IF(R55="",TODAY()-O55,R55-O55))),"") -> 0 | AU55: =IFERROR(IF(($M55=""),"",IF(OR(,$C55="Offer in Progress",$C55="WIP",$C55="WIP/Drop",$C55="WIP/New",$C55="WIP/Hold"),(TODAY()-$M55)-$AT55,"")),"") | AV55: {=IFERROR(_xlfn.IFS($AU55="","",$AU55<=15,"0-15",AND($AU55>=16,$AU55<=30),"16-30",AND($AU55>=31,$AU55<=45),"31-45",AND($AU55>=46,$AU55<=60),"46-60",AND($AU55>=61,$AU55<=90),"61-90",AND($AU55>=91),"> 90",AND($AU55>=2000),""),"")} | AW55: {=IFERROR(_xlfn.IFS(OR($M55="",$AM55=""),"",OR($C55="Offered",$C55="Joined"),($AM55-$M55)-$AT55),"")} | AX55: {=IFERROR(_xlfn.IFS(OR($M55="",$AS55=""),"",$C55="Joined",($AS55-$M55)-$AT55),"")} | AY55: =IFERROR(IF(COUNTIFS('Candidate Tracker'!$E:$E,'Positions Tracker'!$B55,'Candidate Tracker'!$C:$C,"Offer Drop")=0,"",COUNTIFS('Candidate Tracker'!$E:$E,'Positions Tracker'!$B55,'Candidate Tracker'!$C:$C,"Offer Drop")),"") | AZ55: =IFERROR(IF((COUNTIFS('Candidate Tracker'!$D:$D,"<>",'Candidate Tracker'!$D:$D,"<>Screening",'Candidate Tracker'!$D:$D,"<>Screening Pending",'Candidate Tracker'!$D:$D,"<>Candidate Hold",'Candidate Tracker'!$D:$D,"<>Position Cancelled",'Candidate Tracker'!$D:$D,"<>Internal closed")/COUNTIF('Candidate Tracker'!$D:$D,"<>"))=0,"",(COUNTIFS('Candidate Tracker'!$D:$D,"<>",'Candidate Tracker'!$D:$D,"<>Screening",'Candidate Tracker'!$D:$D,"<>Candidate Hold",'Candidate Tracker'!$D:$D,"<>Position Cancelled",'Candidate Tracker'!$D:$D,"<>Internal closed")/COUNTIF('Candidate Tracker'!$D:$D,"<>"))),"") -> 0.88111888 | BA55: =IFERROR(IF(COUNTIFS('Candidate Tracker'!$E:$E,'Positions Tracker'!$B55,'Candidate Tracker'!$I:$I,"Female")=0,"",COUNTIFS('Candidate Tracker'!$E:$E,'Positions Tracker'!$B55,'Candidate Tracker'!$I:$I,"Female")),"") | BB55: =IFERROR(IF(COUNTIFS('Candidate Tracker'!$E:$E,'Positions Tracker'!$B55,'Candidate Tracker'!$I:$I,"male")=0,"",COUNTIFS('Candidate Tracker'!$E:$E,'Positions Tracker'!$B55,'Candidate Tracker'!$I:$I,"male")),"") | BC55: =IFERROR(IF(COUNTIFS('Candidate Tracker'!$E:$E,'Positions Tracker'!$B55,'Candidate Tracker'!$C:$C,"<>WIP",'Candidate Tracker'!$C:$C,"<>Hold",'Candidate Tracker'!$C:$C,"<>Cancelled",'Candidate Tracker'!$C:$C,"<>Closed")/COUNTIFS('Candidate Tracker'!$E:$E,'Positions Tracker'!$B55)=0,"",COUNTIFS('Candidate Tracker'!$E:$E,'Positions Tracker'!$B55,'Candidate Tracker'!$C:$C,"<>WIP",'Candidate Tracker'!$C:$C,"<>Hold",'Candidate Tracker'!$C:$C,"<>Cancelled",'Candidate Tracker'!$C:$C,"<>Closed")/COUNTIFS('Candidate Tracker'!$E:$E,'Positions Tracker'!$B55)),"") | BD55: =IFERROR(IF($M55="","",TEXT($M55,"MMM-YY")),"") -> Nov-24 | BE55: =IFERROR(IF($AI55="","",TEXT($AI55,"MMM-YY")),"") | BF55: =IFERROR(IF($AM55="","",TEXT($AM55,"MMM-YY")),"") | BG55: =IFERROR(IF($AS55="","",TEXT($AS55,"MMM-YY")),"")
A56: =A55+1 -> 55 | B56: 20243789 | C56: Cancelled | D56: Position Cancelled | E56: Sr. Engineer Automation Testing | F56: Firmware - Testing | G56: Integrated Business Services | H56: Core Engineering | I56: Ankur Singh | J56: External | K56: 45580 | L56: 45580 | M56: 45583 | N56: T11 | X56: Pune | Y56: Bharwade, Amruta | Z56: Bharwade, Amruta | AA56: Update as on 21st Feb 25 internal ref selected | AT56: =IFERROR(SUM(IF(AND(ISBLANK(T56),ISBLANK(Q56)),0,IF(T56="",TODAY()-Q56,T56-Q56))+IF(AND(ISBLANK(S56),ISBLANK(P56)),0,IF(S56="",TODAY()-P56,S56-P56))+IF(AND(ISBLANK(O56),ISBLANK(R56)),0,IF(R56="",TODAY()-O56,R56-O56))),"") -> 0 | AU56: =IFERROR(IF(($M56=""),"",IF(OR(,$C56="Offer in Progress",$C56="WIP",$C56="WIP/Drop",$C56="WIP/New",$C56="WIP/Hold"),(TODAY()-$M56)-$AT56,"")),"") | AV56: {=IFERROR(_xlfn.IFS($AU56="","",$AU56<=15,"0-15",AND($AU56>=16,$AU56<=30),"16-30",AND($AU56>=31,$AU56<=45),"31-45",AND($AU56>=46,$AU56<=60),"46-60",AND($AU56>=61,$AU56<=90),"61-90",AND($AU56>=91),"> 90",AND($AU56>=2000),""),"")} | AW56: {=IFERROR(_xlfn.IFS(OR($M56="",$AM56=""),"",OR($C56="Offered",$C56="Joined"),($AM56-$M56)-$AT56),"")} | AX56: {=IFERROR(_xlfn.IFS(OR($M56="",$AS56=""),"",$C56="Joined",($AS56-$M56)-$AT56),"")} | AY56: =IFERROR(IF(COUNTIFS('Candidate Tracker'!$E:$E,'Positions Tracker'!$B56,'Candidate Tracker'!$C:$C,"Offer Drop")=0,"",COUNTIFS('Candidate Tracker'!$E:$E,'Positions Tracker'!$B56,'Candidate Tracker'!$C:$C,"Offer Drop")),"") | AZ56: =IFERROR(IF((COUNTIFS('Candidate Tracker'!$D:$D,"<>",'Candidate Tracker'!$D:$D,"<>Screening",'Candidate Tracker'!$D:$D,"<>Screening Pending",'Candidate Tracker'!$D:$D,"<>Candidate Hold",'Candidate Tracker'!$D:$D,"<>Position Cancelled",'Candidate Tracker'!$D:$D,"<>Internal closed")/COUNTIF('Candidate Tracker'!$D:$D,"<>"))=0,"",(COUNTIFS('Candidate Tracker'!$D:$D,"<>",'Candidate Tracker'!$D:$D,"<>Screening",'Candidate Tracker'!$D:$D,"<>Candidate Hold",'Candidate Tracker'!$D:$D,"<>Position Cancelled",'Candidate Tracker'!$D:$D,"<>Internal closed")/COUNTIF('Candidate Tracker'!$D:$D,"<>"))),"") -> 0.88111888 | BA56: =IFERROR(IF(COUNTIFS('Candidate Tracker'!$E:$E,'Positions Tracker'!$B56,'Candidate Tracker'!$I:$I,"Female")=0,"",COUNTIFS('Candidate Tracker'!$E:$E,'Positions Tracker'!$B56,'Candidate Tracker'!$I:$I,"Female")),"") | BB56: =IFERROR(IF(COUNTIFS('Candidate Tracker'!$E:$E,'Positions Tracker'!$B56,'Candidate Tracker'!$I:$I,"male")=0,"",COUNTIFS('Candidate Tracker'!$E:$E,'Positions Tracker'!$B56,'Candidate Tracker'!$I:$I,"male")),"") | BC56: =IFERROR(IF(COUNTIFS('Candidate Tracker'!$E:$E,'Positions Tracker'!$B56,'Candidate Tracker'!$C:$C,"<>WIP",'Candidate Tracker'!$C:$C,"<>Hold",'Candidate Tracker'!$C:$C,"<>Cancelled",'Candidate Tracker'!$C:$C,"<>Closed")/COUNTIFS('Candidate Tracker'!$E:$E,'Positions Tracker'!$B56)=0,"",COUNTIFS('Candidate Tracker'!$E:$E,'Positions Tracker'!$B56,'Candidate Tracker'!$C:$C,"<>WIP",'Candidate Tracker'!$C:$C,"<>Hold",'Candidate Tracker'!$C:$C,"<>Cancelled",'Candidate Tracker'!$C:$C,"<>Closed")/COUNTIFS('Candidate Tracker'!$E:$E,'Positions Tracker'!$B56)),"") | BD56: =IFERROR(IF($M56="","",TEXT($M56,"MMM-YY")),"") -> Oct-24 | BE56: =IFERROR(IF($AI56="","",TEXT($AI56,"MMM-YY")),"") | BF56: =IFERROR(IF($AM56="","",TEXT($AM56,"MMM-YY")),"") | BG56: =IFERROR(IF($AS56="","",TEXT($AS56,"MMM-YY")),"")
A57: =A56+1 -> 56 | B57: 20243612 | C57: Cancelled | D57: Position Cancelled | E57: Production Supervisor DC Power | F57: Production Engineer | G57: India Business | H57: Production Engineer | I57: Luthra, Vikas | J57: External | K57: 45462 | L57: 45462 | M57: 45467 | X57: Pune | Y57: Bharwade, Amruta | Z57: Bharwade, Amruta | AA57: Update as on 21st Feb 25 On Hold | AT57: =IFERROR(SUM(IF(AND(ISBLANK(T57),ISBLANK(Q57)),0,IF(T57="",TODAY()-Q57,T57-Q57))+IF(AND(ISBLANK(S57),ISBLANK(P57)),0,IF(S57="",TODAY()-P57,S57-P57))+IF(AND(ISBLANK(O57),ISBLANK(R57)),0,IF(R57="",TODAY()-O57,R57-O57))),"") -> 0 | AU57: =IFERROR(IF(($M57=""),"",IF(OR(,$C57="Offer in Progress",$C57="WIP",$C57="WIP/Drop",$C57="WIP/New",$C57="WIP/Hold"),(TODAY()-$M57)-$AT57,"")),"") | AV57: {=IFERROR(_xlfn.IFS($AU57="","",$AU57<=15,"0-15",AND($AU57>=16,$AU57<=30),"16-30",AND($AU57>=31,$AU57<=45),"31-45",AND($AU57>=46,$AU57<=60),"46-60",AND($AU57>=61,$AU57<=90),"61-90",AND($AU57>=91),"> 90",AND($AU57>=2000),""),"")} | AW57: {=IFERROR(_xlfn.IFS(OR($M57="",$AM57=""),"",OR($C57="Offered",$C57="Joined"),($AM57-$M57)-$AT57),"")} | AX57: {=IFERROR(_xlfn.IFS(OR($M57="",$AS57=""),"",$C57="Joined",($AS57-$M57)-$AT57),"")} | AY57: =IFERROR(IF(COUNTIFS('Candidate Tracker'!$E:$E,'Positions Tracker'!$B57,'Candidate Tracker'!$C:$C,"Offer Drop")=0,"",COUNTIFS('Candidate Tracker'!$E:$E,'Positions Tracker'!$B57,'Candidate Tracker'!$C:$C,"Offer Drop")),"") | AZ57: =IFERROR(IF((COUNTIFS('Candidate Tracker'!$D:$D,"<>",'Candidate Tracker'!$D:$D,"<>Screening",'Candidate Tracker'!$D:$D,"<>Screening Pending",'Candidate Tracker'!$D:$D,"<>Candidate Hold",'Candidate Tracker'!$D:$D,"<>Position Cancelled",'Candidate Tracker'!$D:$D,"<>Internal closed")/COUNTIF('Candidate Tracker'!$D:$D,"<>"))=0,"",(COUNTIFS('Candidate Tracker'!$D:$D,"<>",'Candidate Tracker'!$D:$D,"<>Screening",'Candidate Tracker'!$D:$D,"<>Candidate Hold",'Candidate Tracker'!$D:$D,"<>Position Cancelled",'Candidate Tracker'!$D:$D,"<>Internal closed")/COUNTIF('Candidate Tracker'!$D:$D,"<>"))),"") -> 0.88111888 | BA57: =IFERROR(IF(COUNTIFS('Candidate Tracker'!$E:$E,'Positions Tracker'!$B57,'Candidate Tracker'!$I:$I,"Female")=0,"",COUNTIFS('Candidate Tracker'!$E:$E,'Positions Tracker'!$B57,'Candidate Tracker'!$I:$I,"Female")),"") | BB57: =IFERROR(IF(COUNTIFS('Candidate Tracker'!$E:$E,'Positions Tracker'!$B57,'Candidate Tracker'!$I:$I,"male")=0,"",COUNTIFS('Candidate Tracker'!$E:$E,'Positions Tracker'!$B57,'Candidate Tracker'!$I:$I,"male")),"") | BC57: =IFERROR(IF(COUNTIFS('Candidate Tracker'!$E:$E,'Positions Tracker'!$B57,'Candidate Tracker'!$C:$C,"<>WIP",'Candidate Tracker'!$C:$C,"<>Hold",'Candidate Tracker'!$C:$C,"<>Cancelled",'Candidate Tracker'!$C:$C,"<>Closed")/COUNTIFS('Candidate Tracker'!$E:$E,'Positions Tracker'!$B57)=0,"",COUNTIFS('Candidate Tracker'!$E:$E,'Positions Tracker'!$B57,'Candidate Tracker'!$C:$C,"<>WIP",'Candidate Tracker'!$C:$C,"<>Hold",'Candidate Tracker'!$C:$C,"<>Cancelled",'Candidate Tracker'!$C:$C,"<>Closed")/COUNTIFS('Candidate Tracker'!$E:$E,'Positions Tracker'!$B57)),"") | BD57: =IFERROR(IF($M57="","",TEXT($M57,"MMM-YY")),"") -> Jun-24 | BE57: =IFERROR(IF($AI57="","",TEXT($AI57,"MMM-YY")),"") | BF57: =IFERROR(IF($AM57="","",TEXT($AM57,"MMM-YY")),"") | BG57: =IFERROR(IF($AS57="","",TEXT($AS57,"MMM-YY")),"")
